Workbook

Sheet Project Overview
A1: Bank of America Stadium Modernization — Project Overview
A2: Panthers Stadium, LLC | 2026-03-31 | ANC Proposal Engine
B4: PROJECT INFORMATION
B5: Client | C5: Panthers Stadium, LLC
B6: Project Name | C6: Bank of America Stadium Modernization
B7: Location | C7: 800 South Mint St., Charlotte, NC 28202
B8: Date Created | C8: 2026-03-31
B9: Currency | C9: USD
B10: Environment | C10: Indoor
B11: Union Labor | C11: No
B12: Bond Required | C12: No
B13: Number of Displays | C13: =SUM('LED Cost Sheet'!I4:I28) -> 34
B15: FINANCIAL PARAMETERS
B16: LED Hardware Margin | C16: 15%
B17: Install / Services Margin | C17: 15%
B18: Engineering Margin | C18: 15%
B19: Equipment Margin | C19: 15%
B20: CMS Margin | C20: 15%
B21: Bond Rate | C21: N/A
B22: Tax Rate | C22: Per zone (editable on MA)
B23: Tariff Rate | C23: Per zone (editable on MA)
B25: SUMMARY TOTALS
B26: Total Cost | C26: ='Margin Analysis'!C340 -> 3218418.2
B27: Total Selling Price | C27: ='Margin Analysis'!D340 -> 3706135.2
B28: Project Margin $ | C28: ='Margin Analysis'!E340 -> 487717
B29: Project Margin % | C29: ='Margin Analysis'!F340 -> 0.13
B30: DOCUMENT TOTAL | C30: ='Margin Analysis'!D340 -> 3706135.2

Sheet Margin Analysis
A1: Bank of America Stadium Modernization — Margin Analysis
A2: Panthers Stadium, LLC | 2026-03-31 | ANC Proposal Engine
B4: Zone / Category | C4: Cost | D4: Selling Price | E4: Margin $ | F4: Margin %
B5: Team Room — Team Room | D5: Selling Price
B6: LED Hardware | C6: ='LED Cost Sheet'!T4 -> 28982.73 | D6: ='LED Cost Sheet'!V4 -> 34097.33 | E6: =IFERROR(D6-C6,0) -> 5114.6 | F6: 0.15
B7: Structural Materials | C7: ='Team Room - Install'!I26 -> 1290 | D7: =IFERROR(C7/(1-F7),0) -> 1517.65 | E7: =IFERROR(D7-C7,0) -> 227.65 | F7: 0.15
B8: Structural Labor & LED Installation | C8: ='Team Room - Install'!I35-'Team Room - Install'!I34 -> 5375 | D8: =IFERROR(C8/(1-F8),0) -> 6323.53 | E8: =IFERROR(D8-C8,0) -> 948.53 | F8: 0.15
B9: Electrical & Data | C9: ='Team Room - Install'!I44 -> 5375 | D9: =IFERROR(C9/(1-F9),0) -> 6323.53 | E9: =IFERROR(D9-C9,0) -> 948.53 | F9: 0.15
B10: PM / General Conditions / Travel | C10: ='Team Room - Install'!I34 -> 20882.35 | D10: =IFERROR(C10/(1-F10),0) -> 24567.47 | E10: =IFERROR(D10-C10,0) -> 3685.12 | F10: 0.15
B11: Engineering & Permits | C11: ='Team Room - Install'!I52 -> 4705.88 | D11: =IFERROR(C11/(1-F11),0) -> 5536.33 | E11: =IFERROR(D11-C11,0) -> 830.45 | F11: 0.15
B12: SUBTOTAL | C12: =SUM(C6:C11) -> 66610.96 | D12: =SUM(D6:D11) -> 77048.19 | E12: =IFERROR(D12-C12,0) -> 10437.23 | F12: =IFERROR(1-C12/D12,0) -> 0.135464
B13: TAX | C13: 0 | D13: 0 | E13: 0 | G13: 0
B14: BOND | C14: 0 | D14: 0 | E14: 0 | G14: 0
B15: TARIFF | C15: 0 | D15: 0 | E15: 0 | G15: 0
B16: GRAND TOTAL | C16: =C12+C13+C14+C15 -> 66610.96 | D16: =D12+D13+D14+D15 -> 77048.19 | E16: =IFERROR(D16-C16,0) -> 10437.23 | F16: =IFERROR(1-C16/D16,0) -> 0.13546366
B18: Incident Command — Incident Command | D18: Selling Price
B19: LED Hardware | C19: ='LED Cost Sheet'!T5 -> 31247.51 | D19: ='LED Cost Sheet'!V5 -> 36761.78 | E19: =IFERROR(D19-C19,0) -> 5514.27 | F19: 0.15
B20: Structural Materials | C20: ='Incident Command - Install'!I26 -> 1391.25 | D20: =IFERROR(C20/(1-F20),0) -> 1636.76 | E20: =IFERROR(D20-C20,0) -> 245.51 | F20: 0.15
B21: Structural Labor & LED Installation | C21: ='Incident Command - Install'!I35-'Incident Command - Install'!I34 -> 5796.88 | D21: =IFERROR(C21/(1-F21),0) -> 6819.86 | E21: =IFERROR(D21-C21,0) -> 1022.98 | F21: 0.15
B22: Electrical & Data | C22: ='Incident Command - Install'!I44 -> 5796.88 | D22: =IFERROR(C22/(1-F22),0) -> 6819.86 | E22: =IFERROR(D22-C22,0) -> 1022.98 | F22: 0.15
B23: PM / General Conditions / Travel | C23: ='Incident Command - Install'!I34 -> 20882.35 | D23: =IFERROR(C23/(1-F23),0) -> 24567.47 | E23: =IFERROR(D23-C23,0) -> 3685.12 | F23: 0.15
B24: Engineering & Permits | C24: ='Incident Command - Install'!I52 -> 4705.88 | D24: =IFERROR(C24/(1-F24),0) -> 5536.33 | E24: =IFERROR(D24-C24,0) -> 830.45 | F24: 0.15
B25: SUBTOTAL | C25: =SUM(C19:C24) -> 69820.75 | D25: =SUM(D19:D24) -> 80719.82 | E25: =IFERROR(D25-C25,0) -> 10899.07 | F25: =IFERROR(1-C25/D25,0) -> 0.135023
B26: TAX | C26: 0 | D26: 0 | E26: 0 | G26: 0
B27: BOND | C27: 0 | D27: 0 | E27: 0 | G27: 0
B28: TARIFF | C28: 0 | D28: 0 | E28: 0 | G28: 0
B29: GRAND TOTAL | C29: =C25+C26+C27+C28 -> 69820.75 | D29: =D25+D26+D27+D28 -> 80719.82 | E29: =IFERROR(D29-C29,0) -> 10899.07 | F29: =IFERROR(1-C29/D29,0) -> 0.13502347
B31: Def. Unit — Def. Unit | D31: Selling Price
B32: LED Hardware | C32: ='LED Cost Sheet'!T6 -> 28982.73 | D32: ='LED Cost Sheet'!V6 -> 34097.33 | E32: =IFERROR(D32-C32,0) -> 5114.6 | F32: 0.15
B33: Structural Materials | C33: ='Def. Unit - Install'!I26 -> 1290 | D33: =IFERROR(C33/(1-F33),0) -> 1517.65 | E33: =IFERROR(D33-C33,0) -> 227.65 | F33: 0.15
B34: Structural Labor & LED Installation | C34: ='Def. Unit - Install'!I35-'Def. Unit - Install'!I34 -> 5375 | D34: =IFERROR(C34/(1-F34),0) -> 6323.53 | E34: =IFERROR(D34-C34,0) -> 948.53 | F34: 0.15
B35: Electrical & Data | C35: ='Def. Unit - Install'!I44 -> 5375 | D35: =IFERROR(C35/(1-F35),0) -> 6323.53 | E35: =IFERROR(D35-C35,0) -> 948.53 | F35: 0.15
B36: PM / General Conditions / Travel | C36: ='Def. Unit - Install'!I34 -> 20882.35 | D36: =IFERROR(C36/(1-F36),0) -> 24567.47 | E36: =IFERROR(D36-C36,0) -> 3685.12 | F36: 0.15
B37: Engineering & Permits | C37: ='Def. Unit - Install'!I52 -> 4705.88 | D37: =IFERROR(C37/(1-F37),0) -> 5536.33 | E37: =IFERROR(D37-C37,0) -> 830.45 | F37: 0.15
B38: SUBTOTAL | C38: =SUM(C32:C37) -> 66610.96 | D38: =SUM(D32:D37) -> 77048.19 | E38: =IFERROR(D38-C38,0) -> 10437.23 | F38: =IFERROR(1-C38/D38,0) -> 0.135464
B39: TAX | C39: 0 | D39: 0 | E39: 0 | G39: 0
B40: BOND | C40: 0 | D40: 0 | E40: 0 | G40: 0
B41: TARIFF | C41: 0 | D41: 0 | E41: 0 | G41: 0
B42: GRAND TOTAL | C42: =C38+C39+C40+C41 -> 66610.96 | D42: =D38+D39+D40+D41 -> 77048.19 | E42: =IFERROR(D42-C42,0) -> 10437.23 | F42: =IFERROR(1-C42/D42,0) -> 0.13546366
B44: North Corridor — North Corridor | D44: Selling Price
B45: LED Hardware | C45: ='LED Cost Sheet'!T7 -> 300632.15 | D45: ='LED Cost Sheet'!V7 -> 353684.88 | E45: =IFERROR(D45-C45,0) -> 53052.73 | F45: 0.15
B46: Structural Materials | C46: ='North Corridor - Install'!I26 -> 12678.75 | D46: =IFERROR(C46/(1-F46),0) -> 14916.18 | E46: =IFERROR(D46-C46,0) -> 2237.43 | F46: 0.15
B47: Structural Labor & LED Installation | C47: ='North Corridor - Install'!I35-'North Corridor - Install'!I34 -> 52828.13 | D47: =IFERROR(C47/(1-F47),0) -> 62150.74 | E47: =IFERROR(D47-C47,0) -> 9322.61 | F47: 0.15
B48: Electrical & Data | C48: ='North Corridor - Install'!I44 -> 52828.13 | D48: =IFERROR(C48/(1-F48),0) -> 62150.74 | E48: =IFERROR(D48-C48,0) -> 9322.61 | F48: 0.15
B49: PM / General Conditions / Travel | C49: ='North Corridor - Install'!I34 -> 20882.35 | D49: =IFERROR(C49/(1-F49),0) -> 24567.47 | E49: =IFERROR(D49-C49,0) -> 3685.12 | F49: 0.15
B50: Engineering & Permits | C50: ='North Corridor - Install'!I52 -> 4705.88 | D50: =IFERROR(C50/(1-F50),0) -> 5536.33 | E50: =IFERROR(D50-C50,0) -> 830.45 | F50: 0.15
B51: SUBTOTAL | C51: =SUM(C45:C50) -> 444555.39 | D51: =SUM(D45:D50) -> 510065.17 | E51: =IFERROR(D51-C51,0) -> 65509.78 | F51: =IFERROR(1-C51/D51,0) -> 0.128434
B52: TAX | C52: 0 | D52: 0 | E52: 0 | G52: 0
B53: BOND | C53: 0 | D53: 0 | E53: 0 | G53: 0
B54: TARIFF | C54: 0 | D54: 0 | E54: 0 | G54: 0
B55: GRAND TOTAL | C55: =C51+C52+C53+C54 -> 444555.39 | D55: =D51+D52+D53+D54 -> 510065.17 | E55: =IFERROR(D55-C55,0) -> 65509.78 | F55: =IFERROR(1-C55/D55,0) -> 0.12843414
B57: South Corridor — South Corridor | D57: Selling Price
B58: LED Hardware | C58: ='LED Cost Sheet'!T8 -> 258597.33 | D58: ='LED Cost Sheet'!V8 -> 304232.15 | E58: =IFERROR(D58-C58,0) -> 45634.82 | F58: 0.15
B59: Structural Materials | C59: ='South Corridor - Install'!I26 -> 10777.5 | D59: =IFERROR(C59/(1-F59),0) -> 12679.41 | E59: =IFERROR(D59-C59,0) -> 1901.91 | F59: 0.15
B60: Structural Labor & LED Installation | C60: ='South Corridor - Install'!I35-'South Corridor - Install'!I34 -> 44906.25 | D60: =IFERROR(C60/(1-F60),0) -> 52830.88 | E60: =IFERROR(D60-C60,0) -> 7924.63 | F60: 0.15
B61: Electrical & Data | C61: ='South Corridor - Install'!I44 -> 44906.25 | D61: =IFERROR(C61/(1-F61),0) -> 52830.88 | E61: =IFERROR(D61-C61,0) -> 7924.63 | F61: 0.15
B62: PM / General Conditions / Travel | C62: ='South Corridor - Install'!I34 -> 20882.35 | D62: =IFERROR(C62/(1-F62),0) -> 24567.47 | E62: =IFERROR(D62-C62,0) -> 3685.12 | F62: 0.15
B63: Engineering & Permits | C63: ='South Corridor - Install'!I52 -> 4705.88 | D63: =IFERROR(C63/(1-F63),0) -> 5536.33 | E63: =IFERROR(D63-C63,0) -> 830.45 | F63: 0.15
B64: SUBTOTAL | C64: =SUM(C58:C63) -> 384775.56 | D64: =SUM(D58:D63) -> 441677.13 | E64: =IFERROR(D64-C64,0) -> 56901.57 | F64: =IFERROR(1-C64/D64,0) -> 0.128831
B65: TAX | C65: 0 | D65: 0 | E65: 0 | G65: 0
B66: BOND | C66: 0 | D66: 0 | E66: 0 | G66: 0
B67: TARIFF | C67: 0 | D67: 0 | E67: 0 | G67: 0
B68: GRAND TOTAL | C68: =C64+C65+C66+C67 -> 384775.56 | D68: =D64+D65+D66+D67 -> 441677.13 | E68: =IFERROR(D68-C68,0) -> 56901.57 | F68: =IFERROR(1-C68/D68,0) -> 0.12883069
B70: S.E Corridor — S.E Corridor | D70: Selling Price
B71: LED Hardware | C71: ='LED Cost Sheet'!T9 -> 185684.42 | D71: ='LED Cost Sheet'!V9 -> 218452.26 | E71: =IFERROR(D71-C71,0) -> 32767.84 | F71: 0.15
B72: Structural Materials | C72: ='S.E Corridor - Install'!I26 -> 7837.5 | D72: =IFERROR(C72/(1-F72),0) -> 9220.59 | E72: =IFERROR(D72-C72,0) -> 1383.09 | F72: 0.15
B73: Structural Labor & LED Installation | C73: ='S.E Corridor - Install'!I35-'S.E Corridor - Install'!I34 -> 32656.25 | D73: =IFERROR(C73/(1-F73),0) -> 38419.12 | E73: =IFERROR(D73-C73,0) -> 5762.87 | F73: 0.15
B74: Electrical & Data | C74: ='S.E Corridor - Install'!I44 -> 32656.25 | D74: =IFERROR(C74/(1-F74),0) -> 38419.12 | E74: =IFERROR(D74-C74,0) -> 5762.87 | F74: 0.15
B75: PM / General Conditions / Travel | C75: ='S.E Corridor - Install'!I34 -> 20882.35 | D75: =IFERROR(C75/(1-F75),0) -> 24567.47 | E75: =IFERROR(D75-C75,0) -> 3685.12 | F75: 0.15
B76: Engineering & Permits | C76: ='S.E Corridor - Install'!I52 -> 4705.88 | D76: =IFERROR(C76/(1-F76),0) -> 5536.33 | E76: =IFERROR(D76-C76,0) -> 830.45 | F76: 0.15
B77: SUBTOTAL | C77: =SUM(C71:C76) -> 284422.65 | D77: =SUM(D71:D76) -> 326614.88 | E77: =IFERROR(D77-C77,0) -> 42192.23 | F77: =IFERROR(1-C77/D77,0) -> 0.12918
B78: TAX | C78: 0 | D78: 0 | E78: 0 | G78: 0
B79: BOND | C79: 0 | D79: 0 | E79: 0 | G79: 0
B80: TARIFF | C80: 0 | D80: 0 | E80: 0 | G80: 0
B81: GRAND TOTAL | C81: =C77+C78+C79+C80 -> 284422.65 | D81: =D77+D78+D79+D80 -> 326614.88 | E81: =IFERROR(D81-C81,0) -> 42192.23 | F81: =IFERROR(1-C81/D81,0) -> 0.12918037
B83: East Corridor — East Corridor | D83: Selling Price
B84: LED Hardware | C84: ='LED Cost Sheet'!T10 -> 104162.34 | D84: ='LED Cost Sheet'!V10 -> 122543.93 | E84: =IFERROR(D84-C84,0) -> 18381.59 | F84: 0.15
B85: Structural Materials | C85: ='East Corridor - Install'!I26 -> 4151.25 | D85: =IFERROR(C85/(1-F85),0) -> 4883.82 | E85: =IFERROR(D85-C85,0) -> 732.57 | F85: 0.15
B86: Structural Labor & LED Installation | C86: ='East Corridor - Install'!I35-'East Corridor - Install'!I34 -> 17296.88 | D86: =IFERROR(C86/(1-F86),0) -> 20349.27 | E86: =IFERROR(D86-C86,0) -> 3052.39 | F86: 0.15
B87: Electrical & Data | C87: ='East Corridor - Install'!I44 -> 17296.88 | D87: =IFERROR(C87/(1-F87),0) -> 20349.27 | E87: =IFERROR(D87-C87,0) -> 3052.39 | F87: 0.15
B88: PM / General Conditions / Travel | C88: ='East Corridor - Install'!I34 -> 20882.35 | D88: =IFERROR(C88/(1-F88),0) -> 24567.47 | E88: =IFERROR(D88-C88,0) -> 3685.12 | F88: 0.15
B89: Engineering & Permits | C89: ='East Corridor - Install'!I52 -> 4705.88 | D89: =IFERROR(C89/(1-F89),0) -> 5536.33 | E89: =IFERROR(D89-C89,0) -> 830.45 | F89: 0.15
B90: SUBTOTAL | C90: =SUM(C84:C89) -> 168495.58 | D90: =SUM(D84:D89) -> 193994.8 | E90: =IFERROR(D90-C90,0) -> 25499.22 | F90: =IFERROR(1-C90/D90,0) -> 0.131443
B91: TAX | C91: 0 | D91: 0 | E91: 0 | G91: 0
B92: BOND | C92: 0 | D92: 0 | E92: 0 | G92: 0
B93: TARIFF | C93: 0 | D93: 0 | E93: 0 | G93: 0
B94: GRAND TOTAL | C94: =C90+C91+C92+C93 -> 168495.58 | D94: =D90+D91+D92+D93 -> 193994.8 | E94: =IFERROR(D94-C94,0) -> 25499.22 | F94: =IFERROR(1-C94/D94,0) -> 0.1314428
B96: N.E Corridor — N.E Corridor | D96: Selling Price
B97: LED Hardware | C97: ='LED Cost Sheet'!T11 -> 185684.42 | D97: ='LED Cost Sheet'!V11 -> 218452.26 | E97: =IFERROR(D97-C97,0) -> 32767.84 | F97: 0.15
B98: Structural Materials | C98: ='N.E Corridor - Install'!I26 -> 7837.5 | D98: =IFERROR(C98/(1-F98),0) -> 9220.59 | E98: =IFERROR(D98-C98,0) -> 1383.09 | F98: 0.15
B99: Structural Labor & LED Installation | C99: ='N.E Corridor - Install'!I35-'N.E Corridor - Install'!I34 -> 32656.25 | D99: =IFERROR(C99/(1-F99),0) -> 38419.12 | E99: =IFERROR(D99-C99,0) -> 5762.87 | F99: 0.15
B100: Electrical & Data | C100: ='N.E Corridor - Install'!I44 -> 32656.25 | D100: =IFERROR(C100/(1-F100),0) -> 38419.12 | E100: =IFERROR(D100-C100,0) -> 5762.87 | F100: 0.15
B101: PM / General Conditions / Travel | C101: ='N.E Corridor - Install'!I34 -> 20882.35 | D101: =IFERROR(C101/(1-F101),0) -> 24567.47 | E101: =IFERROR(D101-C101,0) -> 3685.12 | F101: 0.15
B102: Engineering & Permits | C102: ='N.E Corridor - Install'!I52 -> 4705.88 | D102: =IFERROR(C102/(1-F102),0) -> 5536.33 | E102: =IFERROR(D102-C102,0) -> 830.45 | F102: 0.15
B103: SUBTOTAL | C103: =SUM(C97:C102) -> 284422.65 | D103: =SUM(D97:D102) -> 326614.88 | E103: =IFERROR(D103-C103,0) -> 42192.23 | F103: =IFERROR(1-C103/D103,0) -> 0.12918
B104: TAX | C104: 0 | D104: 0 | E104: 0 | G104: 0
B105: BOND | C105: 0 | D105: 0 | E105: 0 | G105: 0
B106: TARIFF | C106: 0 | D106: 0 | E106: 0 | G106: 0
B107: GRAND TOTAL | C107: =C103+C104+C105+C106 -> 284422.65 | D107: =D103+D104+D105+D106 -> 326614.88 | E107: =IFERROR(D107-C107,0) -> 42192.23 | F107: =IFERROR(1-C107/D107,0) -> 0.12918037
B109: Elev Lobby — Elev Lobby | D109: Selling Price
...

Sheet Budget Summary
A1: Bank of America Stadium Modernization — Budget Summary
A2: Panthers Stadium, LLC | 2026-03-31 | By Category
B4: Category | C4: Cost | D4: Selling Price | E4: Margin $ | F4: Margin % | G4: Price / SqFt
B5: LED Hardware (all displays) | C5: =SUM('LED Cost Sheet'!Q4:Q28) -> 1853582.4 | D5: =SUM('LED Cost Sheet'!S4:S28) -> 2180685.2 | E5: =IFERROR(D5-C5,0) -> 327102.78 | F5: 0.15 | G5: =IFERROR(C5/6742.33,0) -> 274.92
B6: Structural Materials | C6: =SUM('Team Room - Install'!I26:I26)+SUM('Incident Command - Install'!I26:I26)+SUM('Def. Unit - Install'!I26:I26)+SUM('North Corridor - Install'!I26:I26)+SUM('South Corridor - Install'!I26:I26)+SUM('S.E Corridor - Install'!I26:I26)+SUM('East Corridor - Install'!I26:I26)+SUM('N.E Corridor - Install'!I26:I26)+SUM('Elev Lobby - Install'!I26:I26)+SUM('North Club - Install'!I26:I26)+SUM('Panthers Den - Install'!I26:I26)+SUM('Panthers Den12 - Install'!I26:I26)+SUM('Panthers Den13 - Install'!I26:I26)+SUM('Panthers Den14 - Install'!I26:I26)+SUM('South Club - Install'!I26:I26)+SUM('S.E Corridor16 - Install'!I26:I26)+SUM('N.E Corridor17 - Install'!I26:I26)+SUM('Panthers Den18 - Install'!I26:I26)+SUM('Panthers Den19 - Install'!I26:I26)+SUM('Panthers Den20 - Install'!I26:I26)+SUM('Elev Lobby21 - Install'!I26:I26)+SUM('Elev Lobby22 - Install'!I26:I26)+SUM('Elev Lobby23 - Install'!I26:I26)+SUM('North Club24 - Install'!I26:I26)+SUM('South Club25 - Install'!I26:I26) -> 77692.5 | D6: =SUM('Team Room - Install'!K26:K26)+SUM('Incident Command - Install'!K26:K26)+SUM('Def. Unit - Install'!K26:K26)+SUM('North Corridor - Install'!K26:K26)+SUM('South Corridor - Install'!K26:K26)+SUM('S.E Corridor - Install'!K26:K26)+SUM('East Corridor - Install'!K26:K26)+SUM('N.E Corridor - Install'!K26:K26)+SUM('Elev Lobby - Install'!K26:K26)+SUM('North Club - Install'!K26:K26)+SUM('Panthers Den - Install'!K26:K26)+SUM('Panthers Den12 - Install'!K26:K26)+SUM('Panthers Den13 - Install'!K26:K26)+SUM('Panthers Den14 - Install'!K26:K26)+SUM('South Club - Install'!K26:K26)+SUM('S.E Corridor16 - Install'!K26:K26)+SUM('N.E Corridor17 - Install'!K26:K26)+SUM('Panthers Den18 - Install'!K26:K26)+SUM('Panthers Den19 - Install'!K26:K26)+SUM('Panthers Den20 - Install'!K26:K26)+SUM('Elev Lobby21 - Install'!K26:K26)+SUM('Elev Lobby22 - Install'!K26:K26)+SUM('Elev Lobby23 - Install'!K26:K26)+SUM('North Club24 - Install'!K26:K26)+SUM('South Club25 - Install'!K26:K26) -> 91402.94 | E6: =IFERROR(D6-C6,0) -> 13710.44 | F6: 0.15 | G6: =IFERROR(C6/6742.33,0) -> 11.52
B7: Structural Labor & LED Installation | C7: =(SUM('Team Room - Install'!I35:I35)-SUM('Team Room - Install'!I34:I34))+(SUM('Incident Command - Install'!I35:I35)-SUM('Incident Command - Install'!I34:I34))+(SUM('Def. Unit - Install'!I35:I35)-SUM('Def. Unit - Install'!I34:I34))+(SUM('North Corridor - Install'!I35:I35)-SUM('North Corridor - Install'!I34:I34))+(SUM('South Corridor - Install'!I35:I35)-SUM('South Corridor - Install'!I34:I34))+(SUM('S.E Corridor - Install'!I35:I35)-SUM('S.E Corridor - Install'!I34:I34))+(SUM('East Corridor - Install'!I35:I35)-SUM('East Corridor - Install'!I34:I34))+(SUM('N.E Corridor - Install'!I35:I35)-SUM('N.E Corridor - Install'!I34:I34))+(SUM('Elev Lobby - Install'!I35:I35)-SUM('Elev Lobby - Install'!I34:I34))+(SUM('North Club - Install'!I35:I35)-SUM('North Club - Install'!I34:I34))+(SUM('Panthers Den - Install'!I35:I35)-SUM('Panthers Den - Install'!I34:I34))+(SUM('Panthers Den12 - Install'!I35:I35)-SUM('Panthers Den12 - Install'!I34:I34))+(SUM('Panthers Den13 - Install'!I35:I35)-SUM('Panthers Den13 - Install'!I34:I34))+(SUM('Panthers Den14 - Install'!I35:I35)-SUM('Panthers Den14 - Install'!I34:I34))+(SUM('South Club - Install'!I35:I35)-SUM('South Club - Install'!I34:I34))+(SUM('S.E Corridor16 - Install'!I35:I35)-SUM('S.E Corridor16 - Install'!I34:I34))+(SUM('N.E Corridor17 - Install'!I35:I35)-SUM('N.E Corridor17 - Install'!I34:I34))+(SUM('Panthers Den18 - Install'!I35:I35)-SUM('Panthers Den18 - Install'!I34:I34))+(SUM('Panthers Den19 - Install'!I35:I35)-SUM('Panthers Den19 - Install'!I34:I34))+(SUM('Panthers Den20 - Install'!I35:I35)-SUM('Panthers Den20 - Install'!I34:I34))+(SUM('Elev Lobby21 - Install'!I35:I35)-SUM('Elev Lobby21 - Install'!I34:I34))+(SUM('Elev Lobby22 - Install'!I35:I35)-SUM('Elev Lobby22 - Install'!I34:I34))+(SUM('Elev Lobby23 - Install'!I35:I35)-SUM('Elev Lobby23 - Install'!I34:I34))+(SUM('North Club24 - Install'!I35:I35)-SUM('North Club24 - Install'!I34:I34))+(SUM('South Club25 - Install'!I35:I35)-SUM('South Club25 - Install'!I34:I34)) -> 323718.78 | D7: =(SUM('Team Room - Install'!K35:K35)-SUM('Team Room - Install'!K34:K34))+(SUM('Incident Command - Install'!K35:K35)-SUM('Incident Command - Install'!K34:K34))+(SUM('Def. Unit - Install'!K35:K35)-SUM('Def. Unit - Install'!K34:K34))+(SUM('North Corridor - Install'!K35:K35)-SUM('North Corridor - Install'!K34:K34))+(SUM('South Corridor - Install'!K35:K35)-SUM('South Corridor - Install'!K34:K34))+(SUM('S.E Corridor - Install'!K35:K35)-SUM('S.E Corridor - Install'!K34:K34))+(SUM('East Corridor - Install'!K35:K35)-SUM('East Corridor - Install'!K34:K34))+(SUM('N.E Corridor - Install'!K35:K35)-SUM('N.E Corridor - Install'!K34:K34))+(SUM('Elev Lobby - Install'!K35:K35)-SUM('Elev Lobby - Install'!K34:K34))+(SUM('North Club - Install'!K35:K35)-SUM('North Club - Install'!K34:K34))+(SUM('Panthers Den - Install'!K35:K35)-SUM('Panthers Den - Install'!K34:K34))+(SUM('Panthers Den12 - Install'!K35:K35)-SUM('Panthers Den12 - Install'!K34:K34))+(SUM('Panthers Den13 - Install'!K35:K35)-SUM('Panthers Den13 - Install'!K34:K34))+(SUM('Panthers Den14 - Install'!K35:K35)-SUM('Panthers Den14 - Install'!K34:K34))+(SUM('South Club - Install'!K35:K35)-SUM('South Club - Install'!K34:K34))+(SUM('S.E Corridor16 - Install'!K35:K35)-SUM('S.E Corridor16 - Install'!K34:K34))+(SUM('N.E Corridor17 - Install'!K35:K35)-SUM('N.E Corridor17 - Install'!K34:K34))+(SUM('Panthers Den18 - Install'!K35:K35)-SUM('Panthers Den18 - Install'!K34:K34))+(SUM('Panthers Den19 - Install'!K35:K35)-SUM('Panthers Den19 - Install'!K34:K34))+(SUM('Panthers Den20 - Install'!K35:K35)-SUM('Panthers Den20 - Install'!K34:K34))+(SUM('Elev Lobby21 - Install'!K35:K35)-SUM('Elev Lobby21 - Install'!K34:K34))+(SUM('Elev Lobby22 - Install'!K35:K35)-SUM('Elev Lobby22 - Install'!K34:K34))+(SUM('Elev Lobby23 - Install'!K35:K35)-SUM('Elev Lobby23 - Install'!K34:K34))+(SUM('North Club24 - Install'!K35:K35)-SUM('North Club24 - Install'!K34:K34))+(SUM('South Club25 - Install'!K35:K35)-SUM('South Club25 - Install'!K34:K34)) -> 380845.62 | E7: =IFERROR(D7-C7,0) -> 57126.84 | F7: 0.15 | G7: =IFERROR(C7/6742.33,0) -> 48.01
B8: Electrical & Data | C8: =SUM('Team Room - Install'!I44:I44)+SUM('Incident Command - Install'!I44:I44)+SUM('Def. Unit - Install'!I44:I44)+SUM('North Corridor - Install'!I44:I44)+SUM('South Corridor - Install'!I44:I44)+SUM('S.E Corridor - Install'!I44:I44)+SUM('East Corridor - Install'!I44:I44)+SUM('N.E Corridor - Install'!I44:I44)+SUM('Elev Lobby - Install'!I44:I44)+SUM('North Club - Install'!I44:I44)+SUM('Panthers Den - Install'!I44:I44)+SUM('Panthers Den12 - Install'!I44:I44)+SUM('Panthers Den13 - Install'!I44:I44)+SUM('Panthers Den14 - Install'!I44:I44)+SUM('South Club - Install'!I44:I44)+SUM('S.E Corridor16 - Install'!I44:I44)+SUM('N.E Corridor17 - Install'!I44:I44)+SUM('Panthers Den18 - Install'!I44:I44)+SUM('Panthers Den19 - Install'!I44:I44)+SUM('Panthers Den20 - Install'!I44:I44)+SUM('Elev Lobby21 - Install'!I44:I44)+SUM('Elev Lobby22 - Install'!I44:I44)+SUM('Elev Lobby23 - Install'!I44:I44)+SUM('North Club24 - Install'!I44:I44)+SUM('South Club25 - Install'!I44:I44) -> 323718.78 | D8: =SUM('Team Room - Install'!K44:K44)+SUM('Incident Command - Install'!K44:K44)+SUM('Def. Unit - Install'!K44:K44)+SUM('North Corridor - Install'!K44:K44)+SUM('South Corridor - Install'!K44:K44)+SUM('S.E Corridor - Install'!K44:K44)+SUM('East Corridor - Install'!K44:K44)+SUM('N.E Corridor - Install'!K44:K44)+SUM('Elev Lobby - Install'!K44:K44)+SUM('North Club - Install'!K44:K44)+SUM('Panthers Den - Install'!K44:K44)+SUM('Panthers Den12 - Install'!K44:K44)+SUM('Panthers Den13 - Install'!K44:K44)+SUM('Panthers Den14 - Install'!K44:K44)+SUM('South Club - Install'!K44:K44)+SUM('S.E Corridor16 - Install'!K44:K44)+SUM('N.E Corridor17 - Install'!K44:K44)+SUM('Panthers Den18 - Install'!K44:K44)+SUM('Panthers Den19 - Install'!K44:K44)+SUM('Panthers Den20 - Install'!K44:K44)+SUM('Elev Lobby21 - Install'!K44:K44)+SUM('Elev Lobby22 - Install'!K44:K44)+SUM('Elev Lobby23 - Install'!K44:K44)+SUM('North Club24 - Install'!K44:K44)+SUM('South Club25 - Install'!K44:K44) -> 380845.62 | E8: =IFERROR(D8-C8,0) -> 57126.84 | F8: 0.15 | G8: =IFERROR(C8/6742.33,0) -> 48.01
B9: PM / General Conditions / Travel | C9: =SUM('Team Room - Install'!I34:I34)+SUM('Incident Command - Install'!I34:I34)+SUM('Def. Unit - Install'!I34:I34)+SUM('North Corridor - Install'!I34:I34)+SUM('South Corridor - Install'!I34:I34)+SUM('S.E Corridor - Install'!I34:I34)+SUM('East Corridor - Install'!I34:I34)+SUM('N.E Corridor - Install'!I34:I34)+SUM('Elev Lobby - Install'!I34:I34)+SUM('North Club - Install'!I34:I34)+SUM('Panthers Den - Install'!I34:I34)+SUM('Panthers Den12 - Install'!I34:I34)+SUM('Panthers Den13 - Install'!I34:I34)+SUM('Panthers Den14 - Install'!I34:I34)+SUM('South Club - Install'!I34:I34)+SUM('S.E Corridor16 - Install'!I34:I34)+SUM('N.E Corridor17 - Install'!I34:I34)+SUM('Panthers Den18 - Install'!I34:I34)+SUM('Panthers Den19 - Install'!I34:I34)+SUM('Panthers Den20 - Install'!I34:I34)+SUM('Elev Lobby21 - Install'!I34:I34)+SUM('Elev Lobby22 - Install'!I34:I34)+SUM('Elev Lobby23 - Install'!I34:I34)+SUM('North Club24 - Install'!I34:I34)+SUM('South Club25 - Install'!I34:I34) -> 522058.75 | D9: =SUM('Team Room - Install'!K34:K34)+SUM('Incident Command - Install'!K34:K34)+SUM('Def. Unit - Install'!K34:K34)+SUM('North Corridor - Install'!K34:K34)+SUM('South Corridor - Install'!K34:K34)+SUM('S.E Corridor - Install'!K34:K34)+SUM('East Corridor - Install'!K34:K34)+SUM('N.E Corridor - Install'!K34:K34)+SUM('Elev Lobby - Install'!K34:K34)+SUM('North Club - Install'!K34:K34)+SUM('Panthers Den - Install'!K34:K34)+SUM('Panthers Den12 - Install'!K34:K34)+SUM('Panthers Den13 - Install'!K34:K34)+SUM('Panthers Den14 - Install'!K34:K34)+SUM('South Club - Install'!K34:K34)+SUM('S.E Corridor16 - Install'!K34:K34)+SUM('N.E Corridor17 - Install'!K34:K34)+SUM('Panthers Den18 - Install'!K34:K34)+SUM('Panthers Den19 - Install'!K34:K34)+SUM('Panthers Den20 - Install'!K34:K34)+SUM('Elev Lobby21 - Install'!K34:K34)+SUM('Elev Lobby22 - Install'!K34:K34)+SUM('Elev Lobby23 - Install'!K34:K34)+SUM('North Club24 - Install'!K34:K34)+SUM('South Club25 - Install'!K34:K34) -> 614186.76 | E9: =IFERROR(D9-C9,0) -> 92128.01 | F9: 0.15
B10: Engineering & Permits | C10: =SUM('Team Room - Install'!I52:I52)+SUM('Incident Command - Install'!I52:I52)+SUM('Def. Unit - Install'!I52:I52)+SUM('North Corridor - Install'!I52:I52)+SUM('South Corridor - Install'!I52:I52)+SUM('S.E Corridor - Install'!I52:I52)+SUM('East Corridor - Install'!I52:I52)+SUM('N.E Corridor - Install'!I52:I52)+SUM('Elev Lobby - Install'!I52:I52)+SUM('North Club - Install'!I52:I52)+SUM('Panthers Den - Install'!I52:I52)+SUM('Panthers Den12 - Install'!I52:I52)+SUM('Panthers Den13 - Install'!I52:I52)+SUM('Panthers Den14 - Install'!I52:I52)+SUM('South Club - Install'!I52:I52)+SUM('S.E Corridor16 - Install'!I52:I52)+SUM('N.E Corridor17 - Install'!I52:I52)+SUM('Panthers Den18 - Install'!I52:I52)+SUM('Panthers Den19 - Install'!I52:I52)+SUM('Panthers Den20 - Install'!I52:I52)+SUM('Elev Lobby21 - Install'!I52:I52)+SUM('Elev Lobby22 - Install'!I52:I52)+SUM('Elev Lobby23 - Install'!I52:I52)+SUM('North Club24 - Install'!I52:I52)+SUM('South Club25 - Install'!I52:I52) -> 117647 | D10: =SUM('Team Room - Install'!K52:K52)+SUM('Incident Command - Install'!K52:K52)+SUM('Def. Unit - Install'!K52:K52)+SUM('North Corridor - Install'!K52:K52)+SUM('South Corridor - Install'!K52:K52)+SUM('S.E Corridor - Install'!K52:K52)+SUM('East Corridor - Install'!K52:K52)+SUM('N.E Corridor - Install'!K52:K52)+SUM('Elev Lobby - Install'!K52:K52)+SUM('North Club - Install'!K52:K52)+SUM('Panthers Den - Install'!K52:K52)+SUM('Panthers Den12 - Install'!K52:K52)+SUM('Panthers Den13 - Install'!K52:K52)+SUM('Panthers Den14 - Install'!K52:K52)+SUM('South Club - Install'!K52:K52)+SUM('S.E Corridor16 - Install'!K52:K52)+SUM('N.E Corridor17 - Install'!K52:K52)+SUM('Panthers Den18 - Install'!K52:K52)+SUM('Panthers Den19 - Install'!K52:K52)+SUM('Panthers Den20 - Install'!K52:K52)+SUM('Elev Lobby21 - Install'!K52:K52)+SUM('Elev Lobby22 - Install'!K52:K52)+SUM('Elev Lobby23 - Install'!K52:K52)+SUM('North Club24 - Install'!K52:K52)+SUM('South Club25 - Install'!K52:K52) -> 138408.24 | E10: =IFERROR(D10-C10,0) -> 20761.24 | F10: 0.15
B11: CMS (Content Management System) | C11: =SUM(CMS!F26:F26) -> 0 | D11: =SUM(CMS!H26:H26) -> 0 | E11: =IFERROR(D11-C11,0) -> 0 | F11: 0.15
B12: Scoring System | C12: =SUM(Scoring!F27:F27) -> 0 | D12: =SUM(Scoring!H27:H27) -> 0 | E12: =IFERROR(D12-C12,0) -> 0 | F12: 0.15
B13: Venue Services | C13: =SUM('Venue Services'!B17:B17) -> 0 | D13: =SUM('Venue Services'!C17:C17) -> 0 | E13: =IFERROR(D13-C13,0) -> 0 | F13: 0.15
B14: Game Clock | C14: =SUM('Additional Items'!F5:F5) -> 0 | D14: =SUM('Additional Items'!H5:H5) -> 0 | E14: =IFERROR(D14-C14,0) -> 0 | F14: 0.15
B15: Pitch Clocks | C15: =SUM('Additional Items'!F6:F6) -> 0 | D15: =SUM('Additional Items'!H6:H6) -> 0 | E15: =IFERROR(D15-C15,0) -> 0 | F15: 0.15
B16: OES / MIS / Timing | C16: =SUM('Additional Items'!F7:F7) -> 0 | D16: =SUM('Additional Items'!H7:H7) -> 0 | E16: =IFERROR(D16-C16,0) -> 0 | F16: 0.15
B17: DMX / Misc Equipment | C17: =SUM('Additional Items'!F8:F8) -> 0 | D17: =SUM('Additional Items'!H8:H8) -> 0 | E17: =IFERROR(D17-C17,0) -> 0 | F17: 0.15
B19: SUBTOTAL | C19: =SUM(C5:C17) -> 3218418.2 | D19: =SUM(D5:D17) -> 3706135.2 | E19: =IFERROR(D19-C19,0) -> 487717 | F19: =IFERROR(1-C19/D19,0) -> 0.13 | G19: =IFERROR(C19/6742.33,0) -> 477.35
B20: TAX | C20: 0 | D20: 0 | E20: 0 | F20: 0
B21: BOND | C21: 0 | D21: 0 | E21: 0 | F21: 0
B22: GRAND TOTAL | C22: =C19+C20+C21 -> 3218418.2 | D22: =D19+D20+D21 -> 3706135.2 | E22: =IFERROR(D22-C22,0) -> 487717 | F22: =IFERROR(1-C22/D22,0) -> 0.13 | G22: =IFERROR(C22/6742.33,0) -> 477.35

Sheet LED Cost Sheet
A1: Bank of America Stadium Modernization — LED Cost Sheet
U2: LED Margin Override → | V2: 0.15
A3: Display | B3: RFP H (ft) | C3: RFP W (ft) | D3: RFP NITs | E3: Vendor | F3: Product | G3: Pitch | H3: H (ft) | I3: W (ft) | J3: H (px) | K3: W (px) | L3: Qty | M3: Total SqFt | N3: Product NITs | O3: Service | P3: $/SqFt | Q3: Display Cost | R3: Processor | S3: Shipping | T3: Total Cost | U3: Margin % | V3: Selling Price | W3: ANC Margin | X3: Weight (lbs) | Y3: Total Power (W) | Z3: BTU/hr
A4: Team Room — Team Room | B4: 8 | C4: 14 | D4: 8000 | E4: Yaham | F4: Yaham Corona C2.5-MIP Indoor | G4: 3.9mm | H4: 8 | I4: 14 | J4: 625 | K4: 1094 | L4: 1 | M4: =H4*I4*L4 -> 112 | N4: 7500 | O4: Front | P4: 244.16 | Q4: 27345.53 | R4: =SUM('Bundle Equipment'!E10:E10) -> 517.2 | S4: 1120 | T4: 28982.73 | U4: =V$2 -> 0.135464 | V4: 77048.19 | W4: 10437.23 | X4: 523 | Y4: 4177 | Z4: =Y4*3.412 -> 14252
A5: Incident Command — Incident Command | B5: 5.3333 | C5: 22.6667 | D5: 8000 | E5: Yaham | F5: Yaham Corona C2.5-MIP Indoor | G5: 3.9mm | H5: 5.3333 | I5: 22.6667 | J5: 417 | K5: 1771 | L5: 1 | M5: =H5*I5*L5 -> 120.89 | N5: 7500 | O5: Front | P5: 244.16 | Q5: 29516.08 | R5: =SUM('Bundle Equipment'!E15:E15) -> 522.53 | S5: 1208.9 | T5: 31247.51 | U5: =V$2 -> 0.135023 | V5: 80719.82 | W5: 10899.07 | X5: 564 | Y5: 4509 | Z5: =Y5*3.412 -> 15385
A6: Def. Unit — Def. Unit | B6: 8 | C6: 14 | D6: 8000 | E6: Yaham | F6: Yaham Corona C2.5-MIP Indoor | G6: 3.9mm | H6: 8 | I6: 14 | J6: 625 | K6: 1094 | L6: 1 | M6: =H6*I6*L6 -> 112 | N6: 7500 | O6: Front | P6: 244.16 | Q6: 27345.53 | R6: =SUM('Bundle Equipment'!E20:E20) -> 517.2 | S6: 1120 | T6: 28982.73 | U6: =V$2 -> 0.135464 | V6: 77048.19 | W6: 10437.23 | X6: 523 | Y6: 4177 | Z6: =Y6*3.412 -> 14252
A7: North Corridor — North Corridor | B7: 11 | C7: 100 | D7: 8000 | E7: Yaham | F7: Yaham Corona C2.5-MIP Indoor | G7: 3.9mm | H7: 11 | I7: 100 | J7: 860 | K7: 7815 | L7: 1 | M7: =H7*I7*L7 -> 1100 | N7: 7500 | O7: Front | P7: 244.16 | Q7: 268572.15 | R7: =SUM('Bundle Equipment'!E26:E26) -> 21060 | S7: 11000 | T7: 300632.15 | U7: =V$2 -> 0.128434 | V7: 510065.17 | W7: 65509.78 | X7: 5135 | Y7: 41028 | Z7: =Y7*3.412 -> 139988
A8: South Corridor — South Corridor | B8: 11 | C8: 85 | D8: 8000 | E8: Yaham | F8: Yaham Corona C2.5-MIP Indoor | G8: 3.9mm | H8: 11 | I8: 85 | J8: 860 | K8: 6643 | L8: 1 | M8: =H8*I8*L8 -> 935 | N8: 7500 | O8: Front | P8: 244.16 | Q8: 228286.33 | R8: =SUM('Bundle Equipment'!E32:E32) -> 20961 | S8: 9350 | T8: 258597.33 | U8: =V$2 -> 0.128831 | V8: 441677.13 | W8: 56901.57 | X8: 4364 | Y8: 34874 | Z8: =Y8*3.412 -> 118990
A9: S.E Corridor — S.E Corridor | B9: 10 | C9: 34 | D9: 8000 | E9: Yaham | F9: Yaham Corona C2.5-MIP Indoor | G9: 3.9mm | H9: 10 | I9: 34 | J9: 782 | K9: 2657 | L9: 2 | M9: =H9*I9*L9 -> 680 | N9: 7500 | O9: Front | P9: 244.16 | Q9: 166026.42 | R9: =SUM('Bundle Equipment'!E38:E38) -> 12858 | S9: 6800 | T9: 185684.42 | U9: =V$2 -> 0.12918 | V9: 326614.88 | W9: 42192.23 | X9: 3174 | Y9: 25363 | Z9: =Y9*3.412 -> 86539
A10: East Corridor — East Corridor | B10: 10 | C10: 36 | D10: 8000 | E10: Yaham | F10: Yaham Corona C2.5-MIP Indoor | G10: 3.9mm | H10: 10 | I10: 36 | J10: 782 | K10: 2814 | L10: 1 | M10: =H10*I10*L10 -> 360 | N10: 7500 | O10: Front | P10: 244.16 | Q10: 87896.34 | R10: =SUM('Bundle Equipment'!E44:E44) -> 12666 | S10: 3600 | T10: 104162.34 | U10: =V$2 -> 0.131443 | V10: 193994.8 | W10: 25499.22 | X10: 1680 | Y10: 13427 | Z10: =Y10*3.412 -> 45813
A11: N.E Corridor — N.E Corridor | B11: 10 | C11: 34 | D11: 8000 | E11: Yaham | F11: Yaham Corona C2.5-MIP Indoor | G11: 3.9mm | H11: 10 | I11: 34 | J11: 782 | K11: 2657 | L11: 2 | M11: =H11*I11*L11 -> 680 | N11: 7500 | O11: Front | P11: 244.16 | Q11: 166026.42 | R11: =SUM('Bundle Equipment'!E50:E50) -> 12858 | S11: 6800 | T11: 185684.42 | U11: =V$2 -> 0.12918 | V11: 326614.88 | W11: 42192.23 | X11: 3174 | Y11: 25363 | Z11: =Y11*3.412 -> 86539
A12: Elev Lobby — Elev Lobby | B12: 4 | C12: 6 | D12: 8000 | E12: Yaham | F12: Yaham Corona C2.5-MIP Indoor | G12: 3.9mm | H12: 4 | I12: 6 | J12: 313 | K12: 469 | L12: 4 | M12: =H12*I12*L12 -> 96 | N12: 7500 | O12: Front | P12: 244.16 | Q12: 23439.02 | R12: =SUM('Bundle Equipment'!E55:E55) -> 507.6 | S12: 960 | T12: 24906.62 | U12: =V$2 -> 0.136376 | V12: 70464.54 | W12: 9609.69 | X12: 448 | Y12: 3581 | Z12: =Y12*3.412 -> 12218
A13: North Club — North Club | B13: 10 | C13: 16 | D13: 8000 | E13: Yaham | F13: Yaham Corona C2.5-MIP Indoor | G13: 3.9mm | H13: 10 | I13: 16 | J13: 782 | K13: 1250 | L13: 2 | M13: =H13*I13*L13 -> 320 | N13: 7500 | O13: Front | P13: 244.16 | Q13: 78130.08 | R13: =SUM('Bundle Equipment'!E61:E61) -> 12642 | S13: 3200 | T13: 93972.08 | U13: =V$2 -> 0.131963 | V13: 177412.13 | W13: 23411.82 | X13: 1494 | Y13: 11935 | Z13: =Y13*3.412 -> 40722
A14: Panthers Den — Panthers Den | B14: 22 | C14: 3 | D14: 8000 | E14: Yaham | F14: Yaham Corona C2.5-MIP Indoor | G14: 3.9mm | H14: 22 | I14: 3 | J14: 1719 | K14: 234 | L14: 3 | M14: =H14*I14*L14 -> 198 | N14: 7500 | O14: Front | P14: 244.16 | Q14: 48342.99 | R14: =SUM('Bundle Equipment'!E66:E66) -> 568.8 | S14: 1980 | T14: 50891.79 | U14: =V$2 -> 0.132416 | V14: 112600.03 | W14: 14910.01 | X14: 924 | Y14: 7385 | Z14: =Y14*3.412 -> 25198
A15: Panthers Den — Panthers Den | B15: 19 | C15: 3.1667 | D15: 8000 | E15: LG | F15: LG GSQA 3.9mm Indoor | G15: 3.9mm | H15: 19 | I15: 3.1667 | J15: 1485 | K15: 247 | L15: 1 | M15: =H15*I15*L15 -> 60.17 | N15: 7500 | O15: Front | P15: 244.16 | Q15: 14690.9 | R15: =SUM('Bundle Equipment'!E71:E71) -> 486.1 | S15: 601.7 | T15: 15778.7 | U15: =V$2 -> 0.139165 | V15: 55535.56 | W15: 7728.63 | X15: 254 | Y15: 2730 | Z15: =Y15*3.412 -> 9315
A16: Panthers Den — Panthers Den | B16: 22 | C16: 3 | D16: 8000 | E16: LG | F16: LG GSQA 3.9mm Indoor | G16: 3.9mm | H16: 22 | I16: 3 | J16: 1719 | K16: 234 | L16: 1 | M16: =H16*I16*L16 -> 66 | N16: 7500 | O16: Front | P16: 244.16 | Q16: 16114.33 | R16: =SUM('Bundle Equipment'!E76:E76) -> 489.6 | S16: 660 | T16: 17263.93 | U16: =V$2 -> 0.138612 | V16: 57955.49 | W16: 8033.33 | X16: 278 | Y16: 2994 | Z16: =Y16*3.412 -> 10216
A17: Panthers Den — Panthers Den | B17: 19 | C17: 3.1667 | D17: 8000 | E17: LG | F17: LG GSQA 3.9mm Indoor | G17: 3.9mm | H17: 19 | I17: 3.1667 | J17: 1485 | K17: 247 | L17: 1 | M17: =H17*I17*L17 -> 60.17 | N17: 7500 | O17: Front | P17: 244.16 | Q17: 14690.9 | R17: =SUM('Bundle Equipment'!E81:E81) -> 486.1 | S17: 601.7 | T17: 15778.7 | U17: =V$2 -> 0.139165 | V17: 55535.56 | W17: 7728.63 | X17: 254 | Y17: 2730 | Z17: =Y17*3.412 -> 9315
A18: South Club — South Club | B18: 10 | C18: 16 | D18: 8000 | E18: Yaham | F18: Yaham Corona C2.5-MIP Indoor | G18: 3.9mm | H18: 10 | I18: 16 | J18: 782 | K18: 1250 | L18: 2 | M18: =H18*I18*L18 -> 320 | N18: 7500 | O18: Front | P18: 244.16 | Q18: 78130.08 | R18: =SUM('Bundle Equipment'!E87:E87) -> 12642 | S18: 3200 | T18: 93972.08 | U18: =V$2 -> 0.131963 | V18: 177412.13 | W18: 23411.82 | X18: 1494 | Y18: 11935 | Z18: =Y18*3.412 -> 40722
A19: S.E Corridor — S.E Corridor | B19: 10 | C19: 34 | D19: 8000 | E19: LG | F19: LG GSQA 3.9mm Indoor | G19: 3.9mm | H19: 10 | I19: 34 | J19: 782 | K19: 2657 | L19: 1 | M19: =H19*I19*L19 -> 340 | N19: 7500 | O19: Front | P19: 244.16 | Q19: 83013.21 | R19: =SUM('Bundle Equipment'!E93:E93) -> 12654 | S19: 3400 | T19: 99067.21 | U19: =V$2 -> 0.131689 | V19: 185682.88 | W19: 24452.43 | X19: 1434 | Y19: 15424 | Z19: =Y19*3.412 -> 52627
A20: N.E Corridor — N.E Corridor | B20: 10 | C20: 34 | D20: 8000 | E20: LG | F20: LG GSQA 3.9mm Indoor | G20: 3.9mm | H20: 10 | I20: 34 | J20: 782 | K20: 2657 | L20: 1 | M20: =H20*I20*L20 -> 340 | N20: 7500 | O20: Front | P20: 244.16 | Q20: 83013.21 | R20: =SUM('Bundle Equipment'!E99:E99) -> 12654 | S20: 3400 | T20: 99067.21 | U20: =V$2 -> 0.131689 | V20: 185682.88 | W20: 24452.43 | X20: 1434 | Y20: 15424 | Z20: =Y20*3.412 -> 52627
A21: Panthers Den — Panthers Den | B21: 22 | C21: 3 | D21: 8000 | E21: LG | F21: LG GSQA 3.9mm Indoor | G21: 3.9mm | H21: 22 | I21: 3 | J21: 1719 | K21: 234 | L21: 1 | M21: =H21*I21*L21 -> 66 | N21: 7500 | O21: Front | P21: 244.16 | Q21: 16114.33 | R21: =SUM('Bundle Equipment'!E104:E104) -> 489.6 | S21: 660 | T21: 17263.93 | U21: =V$2 -> 0.138612 | V21: 57955.49 | W21: 8033.33 | X21: 278 | Y21: 2994 | Z21: =Y21*3.412 -> 10216
A22: Panthers Den — Panthers Den | B22: 8 | C22: 29 | D22: 8000 | E22: LG | F22: LG GSQA 3.9mm Indoor | G22: 3.9mm | H22: 8 | I22: 29 | J22: 625 | K22: 2266 | L22: 1 | M22: =H22*I22*L22 -> 232 | N22: 7500 | O22: Front | P22: 244.16 | Q22: 56644.31 | R22: =SUM('Bundle Equipment'!E109:E109) -> 589.2 | S22: 2320 | T22: 59553.51 | U22: =V$2 -> 0.131697 | V22: 126754.99 | W22: 16693.25 | X22: 979 | Y22: 10525 | Z22: =Y22*3.412 -> 35911
A23: Panthers Den — Panthers Den | B23: 4.0833 | C23: 37.25 | D23: 8000 | E23: LG | F23: LG GSQA 3.9mm Indoor | G23: 3.9mm | H23: 4.0833 | I23: 37.25 | J23: 319 | K23: 2911 | L23: 1 | M23: =H23*I23*L23 -> 152.1 | N23: 7500 | O23: Front | P23: 244.16 | Q23: 37136.2 | R23: =SUM('Bundle Equipment'!E114:E114) -> 541.26 | S23: 1521 | T23: 39198.46 | U23: =V$2 -> 0.13376 | V23: 93659.65 | W23: 12527.95 | X23: 642 | Y23: 6900 | Z23: =Y23*3.412 -> 23543
A24: Elev Lobby — Elev Lobby | B24: 4 | C24: 6 | D24: 8000 | E24: LG | F24: LG GSQA 3.9mm Indoor | G24: 3.9mm | H24: 4 | I24: 6 | J24: 313 | K24: 469 | L24: 1 | M24: =H24*I24*L24 -> 24 | N24: 7500 | O24: Front | P24: 244.16 | Q24: 5859.76 | R24: =SUM('Bundle Equipment'!E119:E119) -> 464.4 | S24: 500 | T24: 6824.16 | U24: =V$2 -> 0.137682 | V24: 40591.05 | W24: 5588.66 | X24: 101 | Y24: 1089 | Z24: =Y24*3.412 -> 3716
A25: Elev Lobby — Elev Lobby | B25: 4 | C25: 6 | D25: 8000 | E25: LG | F25: LG GSQA 3.9mm Indoor | G25: 3.9mm | H25: 4 | I25: 6 | J25: 313 | K25: 469 | L25: 1 | M25: =H25*I25*L25 -> 24 | N25: 7500 | O25: Front | P25: 244.16 | Q25: 5859.76 | R25: =SUM('Bundle Equipment'!E124:E124) -> 464.4 | S25: 500 | T25: 6824.16 | U25: =V$2 -> 0.137682 | V25: 40591.05 | W25: 5588.66 | X25: 101 | Y25: 1089 | Z25: =Y25*3.412 -> 3716
A26: Elev Lobby — Elev Lobby | B26: 4 | C26: 6 | D26: 8000 | E26: LG | F26: LG GSQA 3.9mm Indoor | G26: 3.9mm | H26: 4 | I26: 6 | J26: 313 | K26: 469 | L26: 1 | M26: =H26*I26*L26 -> 24 | N26: 7500 | O26: Front | P26: 244.16 | Q26: 5859.76 | R26: =SUM('Bundle Equipment'!E129:E129) -> 464.4 | S26: 500 | T26: 6824.16 | U26: =V$2 -> 0.137682 | V26: 40591.05 | W26: 5588.66 | X26: 101 | Y26: 1089 | Z26: =Y26*3.412 -> 3716
A27: North Club — North Club | B27: 10 | C27: 16 | D27: 8000 | E27: LG | F27: LG GSQA 3.9mm Indoor | G27: 3.9mm | H27: 10 | I27: 16 | J27: 782 | K27: 1250 | L27: 1 | M27: =H27*I27*L27 -> 160 | N27: 7500 | O27: Front | P27: 244.16 | Q27: 39065.04 | R27: =SUM('Bundle Equipment'!E134:E134) -> 546 | S27: 1600 | T27: 41211.04 | U27: =V$2 -> 0.133499 | V27: 96963.84 | W27: 12944.57 | X27: 675 | Y27: 7258 | Z27: =Y27*3.412 -> 24764
A28: South Club — South Club | B28: 10 | C28: 16 | D28: 8000 | E28: LG | F28: LG GSQA 3.9mm Indoor | G28: 3.9mm | H28: 10 | I28: 16 | J28: 782 | K28: 1250 | L28: 1 | M28: =H28*I28*L28 -> 160 | N28: 7500 | O28: Front | P28: 244.16 | Q28: 39065.04 | R28: =SUM('Bundle Equipment'!E139:E139) -> 546 | S28: 1600 | T28: 41211.04 | U28: =V$2 -> 0.133499 | V28: 96963.84 | W28: 12944.57 | X28: 675 | Y28: 7258 | Z28: =Y28*3.412 -> 24764
A30: TOTAL (25 displays) | M30: =M4+M5+M6+M7+M8+M9+M10+M11+M12+M13+M14+M15+M16+M17+M18+M19+M20+M21+M22+M23+M24+M25+M26+M27+M28 -> 6742.33 | Q30: =Q4+Q5+Q6+Q7+Q8+Q9+Q10+Q11+Q12+Q13+Q14+Q15+Q16+Q17+Q18+Q19+Q20+Q21+Q22+Q23+Q24+Q25+Q26+Q27+Q28 -> 1646183.7 | R30: =R4+R5+R6+R7+R8+R9+R10+R11+R12+R13+R14+R15+R16+R17+R18+R19+R20+R21+R22+R23+R24+R25+R26+R27+R28 -> 139195.39 | S30: =S4+S5+S6+S7+S8+S9+S10+S11+S12+S13+S14+S15+S16+S17+S18+S19+S20+S21+S22+S23+S24+S25+S26+S27+S28 -> 68203.3 | T30: =T4+T5+T6+T7+T8+T9+T10+T11+T12+T13+T14+T15+T16+T17+T18+T19+T20+T21+T22+T23+T24+T25+T26+T27+T28 -> 1853582.4 | U30: =IFERROR(1-T30/V30,0) -> 0.15 | V30: =V4+V5+V6+V7+V8+V9+V10+V11+V12+V13+V14+V15+V16+V17+V18+V19+V20+V21+V22+V23+V24+V25+V26+V27+V28 -> 2180685.2 | W30: =W4+W5+W6+W7+W8+W9+W10+W11+W12+W13+W14+W15+W16+W17+W18+W19+W20+W21+W22+W23+W24+W25+W26+W27+W28 -> 327102.8 | X30: =X4+X5+X6+X7+X8+X9+X10+X11+X12+X13+X14+X15+X16+X17+X18+X19+X20+X21+X22+X23+X24+X25+X26+X27+X28 -> 36675 | Y30: =Y4+Y5+Y6+Y7+Y8+Y9+Y10+Y11+Y12+Y13+Y14+Y15+Y16+Y17+Y18+Y19+Y20+Y21+Y22+Y23+Y24+Y25+Y26+Y27+Y28 -> 693005 | Z30: =Z4+Z5+Z6+Z7+Z8+Z9+Z10+Z11+Z12+Z13+Z14+Z15+Z16+Z17+Z18+Z19+Z20+Z21+Z22+Z23+Z24+Z25+Z26+Z27+Z28 -> 2364533

Sheet Tech Specs (Installers)
A1: Bank of America Stadium Modernization — LED Technical Specifications (No Pricing)
A2: Technical specifications only — no pricing data. Safe for installer/subcontractor distribution.
A4: Display Name | B4: Qty | C4: Pixel Pitch | D4: Height (ft) | E4: Width (ft) | F4: Pixels H | G4: Pixels W | H4: Sq Ft | I4: Brightness (nits) | J4: Service | K4: Environment | L4: Weight (lbs) | M4: Total Power (W) | N4: Fiber Strands | O4: BTU/hr
A5: ='LED Cost Sheet'!A4 -> Team Room — Team Room | B5: ='LED Cost Sheet'!I4 -> 1 | C5: ='LED Cost Sheet'!D4 -> 3.9mm | D5: ='LED Cost Sheet'!E4 -> 8 | E5: ='LED Cost Sheet'!F4 -> 14 | F5: ='LED Cost Sheet'!G4 -> 625 | G5: ='LED Cost Sheet'!H4 -> 1094 | H5: =D5*E5*B5 -> 112 | I5: ='LED Cost Sheet'!K4 -> 8000 | J5: ='LED Cost Sheet'!L4 -> Front | K5: indoor | L5: ='LED Cost Sheet'!U4 -> 523 | M5: ='LED Cost Sheet'!V4 -> 4177 | N5: =IFERROR((F5*G5*B5)/400000,0) -> 1.71 | O5: ='LED Cost Sheet'!W4 -> 14252
A6: ='LED Cost Sheet'!A5 -> Incident Command — Incident Command | B6: ='LED Cost Sheet'!I5 -> 1 | C6: ='LED Cost Sheet'!D5 -> 3.9mm | D6: ='LED Cost Sheet'!E5 -> 5.3333 | E6: ='LED Cost Sheet'!F5 -> 22.6667 | F6: ='LED Cost Sheet'!G5 -> 417 | G6: ='LED Cost Sheet'!H5 -> 1771 | H6: =D6*E6*B6 -> 120.89 | I6: ='LED Cost Sheet'!K5 -> 8000 | J6: ='LED Cost Sheet'!L5 -> Front | K6: indoor | L6: ='LED Cost Sheet'!U5 -> 564 | M6: ='LED Cost Sheet'!V5 -> 4509 | N6: =IFERROR((F6*G6*B6)/400000,0) -> 1.85 | O6: ='LED Cost Sheet'!W5 -> 15385
A7: ='LED Cost Sheet'!A6 -> Def. Unit — Def. Unit | B7: ='LED Cost Sheet'!I6 -> 1 | C7: ='LED Cost Sheet'!D6 -> 3.9mm | D7: ='LED Cost Sheet'!E6 -> 8 | E7: ='LED Cost Sheet'!F6 -> 14 | F7: ='LED Cost Sheet'!G6 -> 625 | G7: ='LED Cost Sheet'!H6 -> 1094 | H7: =D7*E7*B7 -> 112 | I7: ='LED Cost Sheet'!K6 -> 8000 | J7: ='LED Cost Sheet'!L6 -> Front | K7: indoor | L7: ='LED Cost Sheet'!U6 -> 523 | M7: ='LED Cost Sheet'!V6 -> 4177 | N7: =IFERROR((F7*G7*B7)/400000,0) -> 1.71 | O7: ='LED Cost Sheet'!W6 -> 14252
A8: ='LED Cost Sheet'!A7 -> North Corridor — North Corridor | B8: ='LED Cost Sheet'!I7 -> 1 | C8: ='LED Cost Sheet'!D7 -> 3.9mm | D8: ='LED Cost Sheet'!E7 -> 11 | E8: ='LED Cost Sheet'!F7 -> 100 | F8: ='LED Cost Sheet'!G7 -> 860 | G8: ='LED Cost Sheet'!H7 -> 7815 | H8: =D8*E8*B8 -> 1100 | I8: ='LED Cost Sheet'!K7 -> 8000 | J8: ='LED Cost Sheet'!L7 -> Front | K8: indoor | L8: ='LED Cost Sheet'!U7 -> 5135 | M8: ='LED Cost Sheet'!V7 -> 41028 | N8: =IFERROR((F8*G8*B8)/400000,0) -> 16.8 | O8: ='LED Cost Sheet'!W7 -> 139988
A9: ='LED Cost Sheet'!A8 -> South Corridor — South Corridor | B9: ='LED Cost Sheet'!I8 -> 1 | C9: ='LED Cost Sheet'!D8 -> 3.9mm | D9: ='LED Cost Sheet'!E8 -> 11 | E9: ='LED Cost Sheet'!F8 -> 85 | F9: ='LED Cost Sheet'!G8 -> 860 | G9: ='LED Cost Sheet'!H8 -> 6643 | H9: =D9*E9*B9 -> 935 | I9: ='LED Cost Sheet'!K8 -> 8000 | J9: ='LED Cost Sheet'!L8 -> Front | K9: indoor | L9: ='LED Cost Sheet'!U8 -> 4364 | M9: ='LED Cost Sheet'!V8 -> 34874 | N9: =IFERROR((F9*G9*B9)/400000,0) -> 14.28 | O9: ='LED Cost Sheet'!W8 -> 118990
A10: ='LED Cost Sheet'!A9 -> S.E Corridor — S.E Corridor | B10: ='LED Cost Sheet'!I9 -> 2 | C10: ='LED Cost Sheet'!D9 -> 3.9mm | D10: ='LED Cost Sheet'!E9 -> 10 | E10: ='LED Cost Sheet'!F9 -> 34 | F10: ='LED Cost Sheet'!G9 -> 782 | G10: ='LED Cost Sheet'!H9 -> 2657 | H10: =D10*E10*B10 -> 680 | I10: ='LED Cost Sheet'!K9 -> 8000 | J10: ='LED Cost Sheet'!L9 -> Front | K10: indoor | L10: ='LED Cost Sheet'!U9 -> 3174 | M10: ='LED Cost Sheet'!V9 -> 25363 | N10: =IFERROR((F10*G10*B10)/400000,0) -> 10.39 | O10: ='LED Cost Sheet'!W9 -> 86539
A11: ='LED Cost Sheet'!A10 -> East Corridor — East Corridor | B11: ='LED Cost Sheet'!I10 -> 1 | C11: ='LED Cost Sheet'!D10 -> 3.9mm | D11: ='LED Cost Sheet'!E10 -> 10 | E11: ='LED Cost Sheet'!F10 -> 36 | F11: ='LED Cost Sheet'!G10 -> 782 | G11: ='LED Cost Sheet'!H10 -> 2814 | H11: =D11*E11*B11 -> 360 | I11: ='LED Cost Sheet'!K10 -> 8000 | J11: ='LED Cost Sheet'!L10 -> Front | K11: indoor | L11: ='LED Cost Sheet'!U10 -> 1680 | M11: ='LED Cost Sheet'!V10 -> 13427 | N11: =IFERROR((F11*G11*B11)/400000,0) -> 5.5 | O11: ='LED Cost Sheet'!W10 -> 45813
A12: ='LED Cost Sheet'!A11 -> N.E Corridor — N.E Corridor | B12: ='LED Cost Sheet'!I11 -> 2 | C12: ='LED Cost Sheet'!D11 -> 3.9mm | D12: ='LED Cost Sheet'!E11 -> 10 | E12: ='LED Cost Sheet'!F11 -> 34 | F12: ='LED Cost Sheet'!G11 -> 782 | G12: ='LED Cost Sheet'!H11 -> 2657 | H12: =D12*E12*B12 -> 680 | I12: ='LED Cost Sheet'!K11 -> 8000 | J12: ='LED Cost Sheet'!L11 -> Front | K12: indoor | L12: ='LED Cost Sheet'!U11 -> 3174 | M12: ='LED Cost Sheet'!V11 -> 25363 | N12: =IFERROR((F12*G12*B12)/400000,0) -> 10.39 | O12: ='LED Cost Sheet'!W11 -> 86539
A13: ='LED Cost Sheet'!A12 -> Elev Lobby — Elev Lobby | B13: ='LED Cost Sheet'!I12 -> 4 | C13: ='LED Cost Sheet'!D12 -> 3.9mm | D13: ='LED Cost Sheet'!E12 -> 4 | E13: ='LED Cost Sheet'!F12 -> 6 | F13: ='LED Cost Sheet'!G12 -> 313 | G13: ='LED Cost Sheet'!H12 -> 469 | H13: =D13*E13*B13 -> 96 | I13: ='LED Cost Sheet'!K12 -> 8000 | J13: ='LED Cost Sheet'!L12 -> Front | K13: indoor | L13: ='LED Cost Sheet'!U12 -> 448 | M13: ='LED Cost Sheet'!V12 -> 3581 | N13: =IFERROR((F13*G13*B13)/400000,0) -> 1.47 | O13: ='LED Cost Sheet'!W12 -> 12218
A14: ='LED Cost Sheet'!A13 -> North Club — North Club | B14: ='LED Cost Sheet'!I13 -> 2 | C14: ='LED Cost Sheet'!D13 -> 3.9mm | D14: ='LED Cost Sheet'!E13 -> 10 | E14: ='LED Cost Sheet'!F13 -> 16 | F14: ='LED Cost Sheet'!G13 -> 782 | G14: ='LED Cost Sheet'!H13 -> 1250 | H14: =D14*E14*B14 -> 320 | I14: ='LED Cost Sheet'!K13 -> 8000 | J14: ='LED Cost Sheet'!L13 -> Front | K14: indoor | L14: ='LED Cost Sheet'!U13 -> 1494 | M14: ='LED Cost Sheet'!V13 -> 11935 | N14: =IFERROR((F14*G14*B14)/400000,0) -> 4.89 | O14: ='LED Cost Sheet'!W13 -> 40722
A15: ='LED Cost Sheet'!A14 -> Panthers Den — Panthers Den | B15: ='LED Cost Sheet'!I14 -> 3 | C15: ='LED Cost Sheet'!D14 -> 3.9mm | D15: ='LED Cost Sheet'!E14 -> 22 | E15: ='LED Cost Sheet'!F14 -> 3 | F15: ='LED Cost Sheet'!G14 -> 1719 | G15: ='LED Cost Sheet'!H14 -> 234 | H15: =D15*E15*B15 -> 198 | I15: ='LED Cost Sheet'!K14 -> 8000 | J15: ='LED Cost Sheet'!L14 -> Front | K15: indoor | L15: ='LED Cost Sheet'!U14 -> 924 | M15: ='LED Cost Sheet'!V14 -> 7385 | N15: =IFERROR((F15*G15*B15)/400000,0) -> 3.02 | O15: ='LED Cost Sheet'!W14 -> 25198
A16: ='LED Cost Sheet'!A15 -> Panthers Den — Panthers Den | B16: ='LED Cost Sheet'!I15 -> 1 | C16: ='LED Cost Sheet'!D15 -> 3.9mm | D16: ='LED Cost Sheet'!E15 -> 19 | E16: ='LED Cost Sheet'!F15 -> 3.1667 | F16: ='LED Cost Sheet'!G15 -> 1485 | G16: ='LED Cost Sheet'!H15 -> 247 | H16: =D16*E16*B16 -> 60.17 | I16: ='LED Cost Sheet'!K15 -> 8000 | J16: ='LED Cost Sheet'!L15 -> Front | K16: indoor | L16: ='LED Cost Sheet'!U15 -> 254 | M16: ='LED Cost Sheet'!V15 -> 2730 | N16: =IFERROR((F16*G16*B16)/400000,0) -> 0.92 | O16: ='LED Cost Sheet'!W15 -> 9315
... A29: ='LED Cost Sheet'!A28 -> South Club — South Club | B29: ='LED Cost Sheet'!I28 -> 1 | C29: ='LED Cost Sheet'!D28 -> 3.9mm | D29: ='LED Cost Sheet'!E28 -> 10 | E29: ='LED Cost Sheet'!F28 -> 16 | F29: ='LED Cost Sheet'!G28 -> 782 | G29: ='LED Cost Sheet'!H28 -> 1250 | H29: =D29*E29*B29 -> 160 | I29: ='LED Cost Sheet'!K28 -> 8000 | J29: ='LED Cost Sheet'!L28 -> Front | K29: indoor | L29: ='LED Cost Sheet'!U28 -> 675 | M29: ='LED Cost Sheet'!V28 -> 7258 | N29: =IFERROR((F29*G29*B29)/400000,0) -> 2.44 | O29: ='LED Cost Sheet'!W28 -> 24764

Sheet Team Room - Install
A3: Project Name: Bank of America Stadium Modernization
A4: 2026-03-31
A5: Revised By: ANC Proposal Engine
C7: Linked Margin Assignment
C8: Install Margin | D8: 0.15
C9: Electrical Margin | D9: 0.15
C10: ANC Margin | D10: 0.15
C11: Engineering and Permits | D11: 0.15
B15: Team Room
B16: Height | C16: Width | D16: Total Sq. Ft | E16: QTY
B17: 8 | C17: 14 | D17: 112 | E17: 1
B19: Structural Materials: | C19: Subcontractor 1 | D19: Subcontractor 2 | E19: Subcontractor 3 | F19: Selected | G19: Additional Contingency | I19: Total Cost | J19: Install Margin | K19: Selling Price
B20: FABRICATE PRIMARY STEEL | C20: 0 | D20: 0 | E20: 0 | F20: 0 | G20: 0 | I20: =SUM(C20:G20) -> 0 | J20: =$D$8 -> 0.15 | K20: =I20/(1-J20) -> 0
B21: SUPPLY AND INSTALL PRIMARY PLYWOOD | C21: 0 | D21: 0 | E21: 0 | F21: 0 | G21: 0 | I21: =SUM(C21:G21) -> 0 | J21: =$D$8 -> 0.15 | K21: =I21/(1-J21) -> 0
B22: FABRICATE SECONDARY STEEL SUBSTRUCTURE | C22: 1290 | D22: 0 | E22: 0 | F22: 0 | G22: 0 | I22: =SUM(C22:G22) -> 1290 | J22: =$D$8 -> 0.15 | K22: =I22/(1-J22) -> 1517.65
B23: FABRICATE CLADDING AND TRIM | C23: 0 | D23: 0 | E23: 0 | F23: 0 | G23: 0 | I23: =SUM(C23:G23) -> 0 | J23: =$D$8 -> 0.15 | K23: =I23/(1-J23) -> 0
B24: OTHER SCOPE ITEM | C24: 0 | D24: 0 | E24: 0 | F24: 0 | G24: 0 | I24: =SUM(C24:G24) -> 0 | J24: =$D$8 -> 0.15 | K24: =I24/(1-J24) -> 0
B25: OTHER SCOPE ITEM | C25: 0 | D25: 0 | E25: 0 | F25: 0 | G25: 0 | I25: =SUM(C25:G25) -> 0 | J25: =$D$8 -> 0.15 | K25: =I25/(1-J25) -> 0
B26: SUBTOTAL | I26: =SUM(I20:I25) -> 1290 | K26: =SUM(K20:K25) -> 1517.65
B28: Structural Labor and LED Installation | C28: Subcontractor 1 | D28: Subcontractor 2 | E28: Subcontractor 3 | F28: Selected | G28: Additional Contingency | I28: Total Cost | J28: Install Margin | K28: Selling Price
B29: REMOVAL AND DISPOSAL | C29: 0 | D29: 0 | E29: 0 | F29: 0 | G29: 0 | I29: =SUM(C29:G29) -> 0 | J29: =$D$8 -> 0.15 | K29: =I29/(1-J29) -> 0
B30: INSTALL SECONDARY STEEL SUBSTRUCTURE | C30: 0 | D30: 0 | E30: 0 | F30: 0 | G30: 0 | I30: =SUM(C30:G30) -> 0 | J30: =$D$8 -> 0.15 | K30: =I30/(1-J30) -> 0
B31: INSTALL LED DISPLAYS | C31: 5375 | D31: 0 | E31: 0 | F31: 0 | G31: 0 | I31: =SUM(C31:G31) -> 5375 | J31: =$D$8 -> 0.15 | K31: =I31/(1-J31) -> 6323.53
B32: INSTALL CLADDING AND TRIM | C32: 0 | D32: 0 | E32: 0 | F32: 0 | G32: 0 | I32: =SUM(C32:G32) -> 0 | J32: =$D$8 -> 0.15 | K32: =I32/(1-J32) -> 0
B33: HEAVY EQUIPMENT | C33: 0 | D33: 0 | E33: 0 | F33: 0 | G33: 0 | I33: =SUM(C33:G33) -> 0 | J33: =$D$8 -> 0.15 | K33: =I33/(1-J33) -> 0
B34: PM/GENERAL CONDITIONS/TRAVEL | C34: 20882.35 | D34: 0 | E34: 0 | F34: 0 | G34: 0 | I34: =SUM(C34:G34) -> 20882.35 | J34: =$D$8 -> 0.15 | K34: =I34/(1-J34) -> 24567.47
B35: SUBTOTAL | I35: =SUM(I29:I34) -> 26257.35 | K35: =SUM(K29:K34) -> 30891
B37: Electrical and Data - Materials and Subcontracting | C37: Subcontractor 1 | D37: Subcontractor 2 | E37: Subcontractor 3 | F37: Selected | G37: Additional Contingency | I37: Total Cost | J37: Install Margin | K37: Selling Price
B38: ELECTRICAL MATERIALS | C38: 5375 | D38: 0 | E38: 0 | F38: 0 | G38: 0 | I38: =SUM(C38:G38) -> 5375 | J38: =$D$9 -> 0.15 | K38: =I38/(1-J38) -> 6323.53
B39: DATA MATERIALS | C39: 0 | D39: 0 | E39: 0 | F39: 0 | G39: 0 | I39: =SUM(C39:G39) -> 0 | J39: =$D$9 -> 0.15 | K39: =I39/(1-J39) -> 0
B40: ELECTRICAL LABOR | C40: 0 | D40: 0 | E40: 0 | F40: 0 | G40: 0 | I40: =SUM(C40:G40) -> 0 | J40: =$D$9 -> 0.15 | K40: =I40/(1-J40) -> 0
B41: DATA LABOR | C41: 0 | D41: 0 | E41: 0 | F41: 0 | G41: 0 | I41: =SUM(C41:G41) -> 0 | J41: =$D$9 -> 0.15 | K41: =I41/(1-J41) -> 0
B42: SUB PANEL | C42: 0 | D42: 0 | E42: 0 | F42: 0 | G42: 0 | I42: =SUM(C42:G42) -> 0 | J42: =$D$9 -> 0.15 | K42: =I42/(1-J42) -> 0
B43: MISC | C43: 0 | D43: 0 | E43: 0 | F43: 0 | G43: 0 | I43: =SUM(C43:G43) -> 0 | J43: =$D$9 -> 0.15 | K43: =I43/(1-J43) -> 0
B44: SUBTOTAL | I44: =SUM(I38:I43) -> 5375 | K44: =SUM(K38:K43) -> 6323.53
B46: Submittals, Engineering, and Permits | C46: Subcontractor 1 | D46: Subcontractor 2 | E46: Subcontractor 3 | F46: Selected | G46: Additional Contingency | I46: Total Cost | J46: Install Margin | K46: Selling Price
B47: STRUCTURAL ENGINEERING | C47: 4705.88 | D47: 0 | E47: 0 | F47: 0 | G47: 0 | I47: =SUM(C47:G47) -> 4705.88 | J47: =$D$11 -> 0.15 | K47: =I47/(1-J47) -> 5536.33
B48: STRUCTURAL CERTIFICATION | C48: 0 | D48: 0 | E48: 0 | F48: 0 | G48: 0 | I48: =SUM(C48:G48) -> 0 | J48: =$D$11 -> 0.15 | K48: =I48/(1-J48) -> 0
B49: ELECTRICAL ENGINEERING | C49: 0 | D49: 0 | E49: 0 | F49: 0 | G49: 0 | I49: =SUM(C49:G49) -> 0 | J49: =$D$11 -> 0.15 | K49: =I49/(1-J49) -> 0
B50: ELECTRICAL CERTIFICATION | C50: 0 | D50: 0 | E50: 0 | F50: 0 | G50: 0 | I50: =SUM(C50:G50) -> 0 | J50: =$D$11 -> 0.15 | K50: =I50/(1-J50) -> 0
B51: PERMITS | C51: 0 | D51: 0 | E51: 0 | F51: 0 | G51: 0 | I51: =SUM(C51:G51) -> 0 | J51: =$D$11 -> 0.15 | K51: =I51/(1-J51) -> 0
B52: SUBTOTAL | I52: =SUM(I47:I51) -> 4705.88 | K52: =SUM(K47:K51) -> 5536.33
B54: ZONE GRAND TOTAL | I54: =I26+I35+I44+I52 -> 66610.96 | K54: =K26+K35+K44+K52 -> 77048.19

Sheet Incident Command - Install
A3: Project Name: Bank of America Stadium Modernization
A4: 2026-03-31
A5: Revised By: ANC Proposal Engine
C7: Linked Margin Assignment
C8: Install Margin | D8: 0.15
C9: Electrical Margin | D9: 0.15
C10: ANC Margin | D10: 0.15
C11: Engineering and Permits | D11: 0.15
B15: Incident Command
B16: Height | C16: Width | D16: Total Sq. Ft | E16: QTY
B17: 5.3333 | C17: 22.6667 | D17: 120.89 | E17: 1
B19: Structural Materials: | C19: Subcontractor 1 | D19: Subcontractor 2 | E19: Subcontractor 3 | F19: Selected | G19: Additional Contingency | I19: Total Cost | J19: Install Margin | K19: Selling Price
B20: FABRICATE PRIMARY STEEL | C20: 0 | D20: 0 | E20: 0 | F20: 0 | G20: 0 | I20: =SUM(C20:G20) -> 0 | J20: =$D$8 -> 0.15 | K20: =I20/(1-J20) -> 0
B21: SUPPLY AND INSTALL PRIMARY PLYWOOD | C21: 0 | D21: 0 | E21: 0 | F21: 0 | G21: 0 | I21: =SUM(C21:G21) -> 0 | J21: =$D$8 -> 0.15 | K21: =I21/(1-J21) -> 0
B22: FABRICATE SECONDARY STEEL SUBSTRUCTURE | C22: 1391.25 | D22: 0 | E22: 0 | F22: 0 | G22: 0 | I22: =SUM(C22:G22) -> 1391.25 | J22: =$D$8 -> 0.15 | K22: =I22/(1-J22) -> 1636.76
B23: FABRICATE CLADDING AND TRIM | C23: 0 | D23: 0 | E23: 0 | F23: 0 | G23: 0 | I23: =SUM(C23:G23) -> 0 | J23: =$D$8 -> 0.15 | K23: =I23/(1-J23) -> 0
B24: OTHER SCOPE ITEM | C24: 0 | D24: 0 | E24: 0 | F24: 0 | G24: 0 | I24: =SUM(C24:G24) -> 0 | J24: =$D$8 -> 0.15 | K24: =I24/(1-J24) -> 0
B25: OTHER SCOPE ITEM | C25: 0 | D25: 0 | E25: 0 | F25: 0 | G25: 0 | I25: =SUM(C25:G25) -> 0 | J25: =$D$8 -> 0.15 | K25: =I25/(1-J25) -> 0
B26: SUBTOTAL | I26: =SUM(I20:I25) -> 1391.25 | K26: =SUM(K20:K25) -> 1636.76
B28: Structural Labor and LED Installation | C28: Subcontractor 1 | D28: Subcontractor 2 | E28: Subcontractor 3 | F28: Selected | G28: Additional Contingency | I28: Total Cost | J28: Install Margin | K28: Selling Price
B29: REMOVAL AND DISPOSAL | C29: 0 | D29: 0 | E29: 0 | F29: 0 | G29: 0 | I29: =SUM(C29:G29) -> 0 | J29: =$D$8 -> 0.15 | K29: =I29/(1-J29) -> 0
B30: INSTALL SECONDARY STEEL SUBSTRUCTURE | C30: 0 | D30: 0 | E30: 0 | F30: 0 | G30: 0 | I30: =SUM(C30:G30) -> 0 | J30: =$D$8 -> 0.15 | K30: =I30/(1-J30) -> 0
B31: INSTALL LED DISPLAYS | C31: 5796.88 | D31: 0 | E31: 0 | F31: 0 | G31: 0 | I31: =SUM(C31:G31) -> 5796.88 | J31: =$D$8 -> 0.15 | K31: =I31/(1-J31) -> 6819.86
B32: INSTALL CLADDING AND TRIM | C32: 0 | D32: 0 | E32: 0 | F32: 0 | G32: 0 | I32: =SUM(C32:G32) -> 0 | J32: =$D$8 -> 0.15 | K32: =I32/(1-J32) -> 0
B33: HEAVY EQUIPMENT | C33: 0 | D33: 0 | E33: 0 | F33: 0 | G33: 0 | I33: =SUM(C33:G33) -> 0 | J33: =$D$8 -> 0.15 | K33: =I33/(1-J33) -> 0
B34: PM/GENERAL CONDITIONS/TRAVEL | C34: 20882.35 | D34: 0 | E34: 0 | F34: 0 | G34: 0 | I34: =SUM(C34:G34) -> 20882.35 | J34: =$D$8 -> 0.15 | K34: =I34/(1-J34) -> 24567.47
B35: SUBTOTAL | I35: =SUM(I29:I34) -> 26679.23 | K35: =SUM(K29:K34) -> 31387.33
B37: Electrical and Data - Materials and Subcontracting | C37: Subcontractor 1 | D37: Subcontractor 2 | E37: Subcontractor 3 | F37: Selected | G37: Additional Contingency | I37: Total Cost | J37: Install Margin | K37: Selling Price
B38: ELECTRICAL MATERIALS | C38: 5796.88 | D38: 0 | E38: 0 | F38: 0 | G38: 0 | I38: =SUM(C38:G38) -> 5796.88 | J38: =$D$9 -> 0.15 | K38: =I38/(1-J38) -> 6819.86
B39: DATA MATERIALS | C39: 0 | D39: 0 | E39: 0 | F39: 0 | G39: 0 | I39: =SUM(C39:G39) -> 0 | J39: =$D$9 -> 0.15 | K39: =I39/(1-J39) -> 0
B40: ELECTRICAL LABOR | C40: 0 | D40: 0 | E40: 0 | F40: 0 | G40: 0 | I40: =SUM(C40:G40) -> 0 | J40: =$D$9 -> 0.15 | K40: =I40/(1-J40) -> 0
B41: DATA LABOR | C41: 0 | D41: 0 | E41: 0 | F41: 0 | G41: 0 | I41: =SUM(C41:G41) -> 0 | J41: =$D$9 -> 0.15 | K41: =I41/(1-J41) -> 0
B42: SUB PANEL | C42: 0 | D42: 0 | E42: 0 | F42: 0 | G42: 0 | I42: =SUM(C42:G42) -> 0 | J42: =$D$9 -> 0.15 | K42: =I42/(1-J42) -> 0
B43: MISC | C43: 0 | D43: 0 | E43: 0 | F43: 0 | G43: 0 | I43: =SUM(C43:G43) -> 0 | J43: =$D$9 -> 0.15 | K43: =I43/(1-J43) -> 0
B44: SUBTOTAL | I44: =SUM(I38:I43) -> 5796.88 | K44: =SUM(K38:K43) -> 6819.86
B46: Submittals, Engineering, and Permits | C46: Subcontractor 1 | D46: Subcontractor 2 | E46: Subcontractor 3 | F46: Selected | G46: Additional Contingency | I46: Total Cost | J46: Install Margin | K46: Selling Price
B47: STRUCTURAL ENGINEERING | C47: 4705.88 | D47: 0 | E47: 0 | F47: 0 | G47: 0 | I47: =SUM(C47:G47) -> 4705.88 | J47: =$D$11 -> 0.15 | K47: =I47/(1-J47) -> 5536.33
B48: STRUCTURAL CERTIFICATION | C48: 0 | D48: 0 | E48: 0 | F48: 0 | G48: 0 | I48: =SUM(C48:G48) -> 0 | J48: =$D$11 -> 0.15 | K48: =I48/(1-J48) -> 0
B49: ELECTRICAL ENGINEERING | C49: 0 | D49: 0 | E49: 0 | F49: 0 | G49: 0 | I49: =SUM(C49:G49) -> 0 | J49: =$D$11 -> 0.15 | K49: =I49/(1-J49) -> 0
B50: ELECTRICAL CERTIFICATION | C50: 0 | D50: 0 | E50: 0 | F50: 0 | G50: 0 | I50: =SUM(C50:G50) -> 0 | J50: =$D$11 -> 0.15 | K50: =I50/(1-J50) -> 0
B51: PERMITS | C51: 0 | D51: 0 | E51: 0 | F51: 0 | G51: 0 | I51: =SUM(C51:G51) -> 0 | J51: =$D$11 -> 0.15 | K51: =I51/(1-J51) -> 0
B52: SUBTOTAL | I52: =SUM(I47:I51) -> 4705.88 | K52: =SUM(K47:K51) -> 5536.33
B54: ZONE GRAND TOTAL | I54: =I26+I35+I44+I52 -> 69820.75 | K54: =K26+K35+K44+K52 -> 80719.82

Sheet Def. Unit - Install
A3: Project Name: Bank of America Stadium Modernization
A4: 2026-03-31
A5: Revised By: ANC Proposal Engine
C7: Linked Margin Assignment
C8: Install Margin | D8: 0.15
C9: Electrical Margin | D9: 0.15
C10: ANC Margin | D10: 0.15
C11: Engineering and Permits | D11: 0.15
B15: Def. Unit
B16: Height | C16: Width | D16: Total Sq. Ft | E16: QTY
B17: 8 | C17: 14 | D17: 112 | E17: 1
B19: Structural Materials: | C19: Subcontractor 1 | D19: Subcontractor 2 | E19: Subcontractor 3 | F19: Selected | G19: Additional Contingency | I19: Total Cost | J19: Install Margin | K19: Selling Price
B20: FABRICATE PRIMARY STEEL | C20: 0 | D20: 0 | E20: 0 | F20: 0 | G20: 0 | I20: =SUM(C20:G20) -> 0 | J20: =$D$8 -> 0.15 | K20: =I20/(1-J20) -> 0
B21: SUPPLY AND INSTALL PRIMARY PLYWOOD | C21: 0 | D21: 0 | E21: 0 | F21: 0 | G21: 0 | I21: =SUM(C21:G21) -> 0 | J21: =$D$8 -> 0.15 | K21: =I21/(1-J21) -> 0
B22: FABRICATE SECONDARY STEEL SUBSTRUCTURE | C22: 1290 | D22: 0 | E22: 0 | F22: 0 | G22: 0 | I22: =SUM(C22:G22) -> 1290 | J22: =$D$8 -> 0.15 | K22: =I22/(1-J22) -> 1517.65
B23: FABRICATE CLADDING AND TRIM | C23: 0 | D23: 0 | E23: 0 | F23: 0 | G23: 0 | I23: =SUM(C23:G23) -> 0 | J23: =$D$8 -> 0.15 | K23: =I23/(1-J23) -> 0
B24: OTHER SCOPE ITEM | C24: 0 | D24: 0 | E24: 0 | F24: 0 | G24: 0 | I24: =SUM(C24:G24) -> 0 | J24: =$D$8 -> 0.15 | K24: =I24/(1-J24) -> 0
B25: OTHER SCOPE ITEM | C25: 0 | D25: 0 | E25: 0 | F25: 0 | G25: 0 | I25: =SUM(C25:G25) -> 0 | J25: =$D$8 -> 0.15 | K25: =I25/(1-J25) -> 0
B26: SUBTOTAL | I26: =SUM(I20:I25) -> 1290 | K26: =SUM(K20:K25) -> 1517.65
B28: Structural Labor and LED Installation | C28: Subcontractor 1 | D28: Subcontractor 2 | E28: Subcontractor 3 | F28: Selected | G28: Additional Contingency | I28: Total Cost | J28: Install Margin | K28: Selling Price
B29: REMOVAL AND DISPOSAL | C29: 0 | D29: 0 | E29: 0 | F29: 0 | G29: 0 | I29: =SUM(C29:G29) -> 0 | J29: =$D$8 -> 0.15 | K29: =I29/(1-J29) -> 0
B30: INSTALL SECONDARY STEEL SUBSTRUCTURE | C30: 0 | D30: 0 | E30: 0 | F30: 0 | G30: 0 | I30: =SUM(C30:G30) -> 0 | J30: =$D$8 -> 0.15 | K30: =I30/(1-J30) -> 0
B31: INSTALL LED DISPLAYS | C31: 5375 | D31: 0 | E31: 0 | F31: 0 | G31: 0 | I31: =SUM(C31:G31) -> 5375 | J31: =$D$8 -> 0.15 | K31: =I31/(1-J31) -> 6323.53
B32: INSTALL CLADDING AND TRIM | C32: 0 | D32: 0 | E32: 0 | F32: 0 | G32: 0 | I32: =SUM(C32:G32) -> 0 | J32: =$D$8 -> 0.15 | K32: =I32/(1-J32) -> 0
B33: HEAVY EQUIPMENT | C33: 0 | D33: 0 | E33: 0 | F33: 0 | G33: 0 | I33: =SUM(C33:G33) -> 0 | J33: =$D$8 -> 0.15 | K33: =I33/(1-J33) -> 0
B34: PM/GENERAL CONDITIONS/TRAVEL | C34: 20882.35 | D34: 0 | E34: 0 | F34: 0 | G34: 0 | I34: =SUM(C34:G34) -> 20882.35 | J34: =$D$8 -> 0.15 | K34: =I34/(1-J34) -> 24567.47
B35: SUBTOTAL | I35: =SUM(I29:I34) -> 26257.35 | K35: =SUM(K29:K34) -> 30891
B37: Electrical and Data - Materials and Subcontracting | C37: Subcontractor 1 | D37: Subcontractor 2 | E37: Subcontractor 3 | F37: Selected | G37: Additional Contingency | I37: Total Cost | J37: Install Margin | K37: Selling Price
B38: ELECTRICAL MATERIALS | C38: 5375 | D38: 0 | E38: 0 | F38: 0 | G38: 0 | I38: =SUM(C38:G38) -> 5375 | J38: =$D$9 -> 0.15 | K38: =I38/(1-J38) -> 6323.53
B39: DATA MATERIALS | C39: 0 | D39: 0 | E39: 0 | F39: 0 | G39: 0 | I39: =SUM(C39:G39) -> 0 | J39: =$D$9 -> 0.15 | K39: =I39/(1-J39) -> 0
B40: ELECTRICAL LABOR | C40: 0 | D40: 0 | E40: 0 | F40: 0 | G40: 0 | I40: =SUM(C40:G40) -> 0 | J40: =$D$9 -> 0.15 | K40: =I40/(1-J40) -> 0
B41: DATA LABOR | C41: 0 | D41: 0 | E41: 0 | F41: 0 | G41: 0 | I41: =SUM(C41:G41) -> 0 | J41: =$D$9 -> 0.15 | K41: =I41/(1-J41) -> 0
B42: SUB PANEL | C42: 0 | D42: 0 | E42: 0 | F42: 0 | G42: 0 | I42: =SUM(C42:G42) -> 0 | J42: =$D$9 -> 0.15 | K42: =I42/(1-J42) -> 0
B43: MISC | C43: 0 | D43: 0 | E43: 0 | F43: 0 | G43: 0 | I43: =SUM(C43:G43) -> 0 | J43: =$D$9 -> 0.15 | K43: =I43/(1-J43) -> 0
B44: SUBTOTAL | I44: =SUM(I38:I43) -> 5375 | K44: =SUM(K38:K43) -> 6323.53
B46: Submittals, Engineering, and Permits | C46: Subcontractor 1 | D46: Subcontractor 2 | E46: Subcontractor 3 | F46: Selected | G46: Additional Contingency | I46: Total Cost | J46: Install Margin | K46: Selling Price
B47: STRUCTURAL ENGINEERING | C47: 4705.88 | D47: 0 | E47: 0 | F47: 0 | G47: 0 | I47: =SUM(C47:G47) -> 4705.88 | J47: =$D$11 -> 0.15 | K47: =I47/(1-J47) -> 5536.33
B48: STRUCTURAL CERTIFICATION | C48: 0 | D48: 0 | E48: 0 | F48: 0 | G48: 0 | I48: =SUM(C48:G48) -> 0 | J48: =$D$11 -> 0.15 | K48: =I48/(1-J48) -> 0
B49: ELECTRICAL ENGINEERING | C49: 0 | D49: 0 | E49: 0 | F49: 0 | G49: 0 | I49: =SUM(C49:G49) -> 0 | J49: =$D$11 -> 0.15 | K49: =I49/(1-J49) -> 0
B50: ELECTRICAL CERTIFICATION | C50: 0 | D50: 0 | E50: 0 | F50: 0 | G50: 0 | I50: =SUM(C50:G50) -> 0 | J50: =$D$11 -> 0.15 | K50: =I50/(1-J50) -> 0
B51: PERMITS | C51: 0 | D51: 0 | E51: 0 | F51: 0 | G51: 0 | I51: =SUM(C51:G51) -> 0 | J51: =$D$11 -> 0.15 | K51: =I51/(1-J51) -> 0
B52: SUBTOTAL | I52: =SUM(I47:I51) -> 4705.88 | K52: =SUM(K47:K51) -> 5536.33
B54: ZONE GRAND TOTAL | I54: =I26+I35+I44+I52 -> 66610.96 | K54: =K26+K35+K44+K52 -> 77048.19

Sheet North Corridor - Install
A3: Project Name: Bank of America Stadium Modernization
A4: 2026-03-31
A5: Revised By: ANC Proposal Engine
C7: Linked Margin Assignment
C8: Install Margin | D8: 0.15
C9: Electrical Margin | D9: 0.15
C10: ANC Margin | D10: 0.15
C11: Engineering and Permits | D11: 0.15
B15: North Corridor
B16: Height | C16: Width | D16: Total Sq. Ft | E16: QTY
B17: 11 | C17: 100 | D17: 1100 | E17: 1
B19: Structural Materials: | C19: Subcontractor 1 | D19: Subcontractor 2 | E19: Subcontractor 3 | F19: Selected | G19: Additional Contingency | I19: Total Cost | J19: Install Margin | K19: Selling Price
B20: FABRICATE PRIMARY STEEL | C20: 0 | D20: 0 | E20: 0 | F20: 0 | G20: 0 | I20: =SUM(C20:G20) -> 0 | J20: =$D$8 -> 0.15 | K20: =I20/(1-J20) -> 0
B21: SUPPLY AND INSTALL PRIMARY PLYWOOD | C21: 0 | D21: 0 | E21: 0 | F21: 0 | G21: 0 | I21: =SUM(C21:G21) -> 0 | J21: =$D$8 -> 0.15 | K21: =I21/(1-J21) -> 0
B22: FABRICATE SECONDARY STEEL SUBSTRUCTURE | C22: 12678.75 | D22: 0 | E22: 0 | F22: 0 | G22: 0 | I22: =SUM(C22:G22) -> 12678.75 | J22: =$D$8 -> 0.15 | K22: =I22/(1-J22) -> 14916.18
B23: FABRICATE CLADDING AND TRIM | C23: 0 | D23: 0 | E23: 0 | F23: 0 | G23: 0 | I23: =SUM(C23:G23) -> 0 | J23: =$D$8 -> 0.15 | K23: =I23/(1-J23) -> 0
B24: OTHER SCOPE ITEM | C24: 0 | D24: 0 | E24: 0 | F24: 0 | G24: 0 | I24: =SUM(C24:G24) -> 0 | J24: =$D$8 -> 0.15 | K24: =I24/(1-J24) -> 0
B25: OTHER SCOPE ITEM | C25: 0 | D25: 0 | E25: 0 | F25: 0 | G25: 0 | I25: =SUM(C25:G25) -> 0 | J25: =$D$8 -> 0.15 | K25: =I25/(1-J25) -> 0
B26: SUBTOTAL | I26: =SUM(I20:I25) -> 12678.75 | K26: =SUM(K20:K25) -> 14916.18
B28: Structural Labor and LED Installation | C28: Subcontractor 1 | D28: Subcontractor 2 | E28: Subcontractor 3 | F28: Selected | G28: Additional Contingency | I28: Total Cost | J28: Install Margin | K28: Selling Price
B29: REMOVAL AND DISPOSAL | C29: 0 | D29: 0 | E29: 0 | F29: 0 | G29: 0 | I29: =SUM(C29:G29) -> 0 | J29: =$D$8 -> 0.15 | K29: =I29/(1-J29) -> 0
B30: INSTALL SECONDARY STEEL SUBSTRUCTURE | C30: 0 | D30: 0 | E30: 0 | F30: 0 | G30: 0 | I30: =SUM(C30:G30) -> 0 | J30: =$D$8 -> 0.15 | K30: =I30/(1-J30) -> 0
B31: INSTALL LED DISPLAYS | C31: 52828.13 | D31: 0 | E31: 0 | F31: 0 | G31: 0 | I31: =SUM(C31:G31) -> 52828.13 | J31: =$D$8 -> 0.15 | K31: =I31/(1-J31) -> 62150.74
B32: INSTALL CLADDING AND TRIM | C32: 0 | D32: 0 | E32: 0 | F32: 0 | G32: 0 | I32: =SUM(C32:G32) -> 0 | J32: =$D$8 -> 0.15 | K32: =I32/(1-J32) -> 0
B33: HEAVY EQUIPMENT | C33: 0 | D33: 0 | E33: 0 | F33: 0 | G33: 0 | I33: =SUM(C33:G33) -> 0 | J33: =$D$8 -> 0.15 | K33: =I33/(1-J33) -> 0
B34: PM/GENERAL CONDITIONS/TRAVEL | C34: 20882.35 | D34: 0 | E34: 0 | F34: 0 | G34: 0 | I34: =SUM(C34:G34) -> 20882.35 | J34: =$D$8 -> 0.15 | K34: =I34/(1-J34) -> 24567.47
B35: SUBTOTAL | I35: =SUM(I29:I34) -> 73710.48 | K35: =SUM(K29:K34) -> 86718.21
B37: Electrical and Data - Materials and Subcontracting | C37: Subcontractor 1 | D37: Subcontractor 2 | E37: Subcontractor 3 | F37: Selected | G37: Additional Contingency | I37: Total Cost | J37: Install Margin | K37: Selling Price
B38: ELECTRICAL MATERIALS | C38: 52828.13 | D38: 0 | E38: 0 | F38: 0 | G38: 0 | I38: =SUM(C38:G38) -> 52828.13 | J38: =$D$9 -> 0.15 | K38: =I38/(1-J38) -> 62150.74
B39: DATA MATERIALS | C39: 0 | D39: 0 | E39: 0 | F39: 0 | G39: 0 | I39: =SUM(C39:G39) -> 0 | J39: =$D$9 -> 0.15 | K39: =I39/(1-J39) -> 0
B40: ELECTRICAL LABOR | C40: 0 | D40: 0 | E40: 0 | F40: 0 | G40: 0 | I40: =SUM(C40:G40) -> 0 | J40: =$D$9 -> 0.15 | K40: =I40/(1-J40) -> 0
B41: DATA LABOR | C41: 0 | D41: 0 | E41: 0 | F41: 0 | G41: 0 | I41: =SUM(C41:G41) -> 0 | J41: =$D$9 -> 0.15 | K41: =I41/(1-J41) -> 0
B42: SUB PANEL | C42: 0 | D42: 0 | E42: 0 | F42: 0 | G42: 0 | I42: =SUM(C42:G42) -> 0 | J42: =$D$9 -> 0.15 | K42: =I42/(1-J42) -> 0
B43: MISC | C43: 0 | D43: 0 | E43: 0 | F43: 0 | G43: 0 | I43: =SUM(C43:G43) -> 0 | J43: =$D$9 -> 0.15 | K43: =I43/(1-J43) -> 0
B44: SUBTOTAL | I44: =SUM(I38:I43) -> 52828.13 | K44: =SUM(K38:K43) -> 62150.74
B46: Submittals, Engineering, and Permits | C46: Subcontractor 1 | D46: Subcontractor 2 | E46: Subcontractor 3 | F46: Selected | G46: Additional Contingency | I46: Total Cost | J46: Install Margin | K46: Selling Price
B47: STRUCTURAL ENGINEERING | C47: 4705.88 | D47: 0 | E47: 0 | F47: 0 | G47: 0 | I47: =SUM(C47:G47) -> 4705.88 | J47: =$D$11 -> 0.15 | K47: =I47/(1-J47) -> 5536.33
B48: STRUCTURAL CERTIFICATION | C48: 0 | D48: 0 | E48: 0 | F48: 0 | G48: 0 | I48: =SUM(C48:G48) -> 0 | J48: =$D$11 -> 0.15 | K48: =I48/(1-J48) -> 0
B49: ELECTRICAL ENGINEERING | C49: 0 | D49: 0 | E49: 0 | F49: 0 | G49: 0 | I49: =SUM(C49:G49) -> 0 | J49: =$D$11 -> 0.15 | K49: =I49/(1-J49) -> 0
B50: ELECTRICAL CERTIFICATION | C50: 0 | D50: 0 | E50: 0 | F50: 0 | G50: 0 | I50: =SUM(C50:G50) -> 0 | J50: =$D$11 -> 0.15 | K50: =I50/(1-J50) -> 0
B51: PERMITS | C51: 0 | D51: 0 | E51: 0 | F51: 0 | G51: 0 | I51: =SUM(C51:G51) -> 0 | J51: =$D$11 -> 0.15 | K51: =I51/(1-J51) -> 0
B52: SUBTOTAL | I52: =SUM(I47:I51) -> 4705.88 | K52: =SUM(K47:K51) -> 5536.33
B54: ZONE GRAND TOTAL | I54: =I26+I35+I44+I52 -> 444555.39 | K54: =K26+K35+K44+K52 -> 510065.17

Sheet South Corridor - Install
A3: Project Name: Bank of America Stadium Modernization
A4: 2026-03-31
A5: Revised By: ANC Proposal Engine
C7: Linked Margin Assignment
C8: Install Margin | D8: 0.15
C9: Electrical Margin | D9: 0.15
C10: ANC Margin | D10: 0.15
C11: Engineering and Permits | D11: 0.15
B15: South Corridor
B16: Height | C16: Width | D16: Total Sq. Ft | E16: QTY
B17: 11 | C17: 85 | D17: 935 | E17: 1
B19: Structural Materials: | C19: Subcontractor 1 | D19: Subcontractor 2 | E19: Subcontractor 3 | F19: Selected | G19: Additional Contingency | I19: Total Cost | J19: Install Margin | K19: Selling Price
B20: FABRICATE PRIMARY STEEL | C20: 0 | D20: 0 | E20: 0 | F20: 0 | G20: 0 | I20: =SUM(C20:G20) -> 0 | J20: =$D$8 -> 0.15 | K20: =I20/(1-J20) -> 0
B21: SUPPLY AND INSTALL PRIMARY PLYWOOD | C21: 0 | D21: 0 | E21: 0 | F21: 0 | G21: 0 | I21: =SUM(C21:G21) -> 0 | J21: =$D$8 -> 0.15 | K21: =I21/(1-J21) -> 0
B22: FABRICATE SECONDARY STEEL SUBSTRUCTURE | C22: 10777.5 | D22: 0 | E22: 0 | F22: 0 | G22: 0 | I22: =SUM(C22:G22) -> 10777.5 | J22: =$D$8 -> 0.15 | K22: =I22/(1-J22) -> 12679.41
B23: FABRICATE CLADDING AND TRIM | C23: 0 | D23: 0 | E23: 0 | F23: 0 | G23: 0 | I23: =SUM(C23:G23) -> 0 | J23: =$D$8 -> 0.15 | K23: =I23/(1-J23) -> 0
B24: OTHER SCOPE ITEM | C24: 0 | D24: 0 | E24: 0 | F24: 0 | G24: 0 | I24: =SUM(C24:G24) -> 0 | J24: =$D$8 -> 0.15 | K24: =I24/(1-J24) -> 0
B25: OTHER SCOPE ITEM | C25: 0 | D25: 0 | E25: 0 | F25: 0 | G25: 0 | I25: =SUM(C25:G25) -> 0 | J25: =$D$8 -> 0.15 | K25: =I25/(1-J25) -> 0
B26: SUBTOTAL | I26: =SUM(I20:I25) -> 10777.5 | K26: =SUM(K20:K25) -> 12679.41
B28: Structural Labor and LED Installation | C28: Subcontractor 1 | D28: Subcontractor 2 | E28: Subcontractor 3 | F28: Selected | G28: Additional Contingency | I28: Total Cost | J28: Install Margin | K28: Selling Price
B29: REMOVAL AND DISPOSAL | C29: 0 | D29: 0 | E29: 0 | F29: 0 | G29: 0 | I29: =SUM(C29:G29) -> 0 | J29: =$D$8 -> 0.15 | K29: =I29/(1-J29) -> 0
B30: INSTALL SECONDARY STEEL SUBSTRUCTURE | C30: 0 | D30: 0 | E30: 0 | F30: 0 | G30: 0 | I30: =SUM(C30:G30) -> 0 | J30: =$D$8 -> 0.15 | K30: =I30/(1-J30) -> 0
B31: INSTALL LED DISPLAYS | C31: 44906.25 | D31: 0 | E31: 0 | F31: 0 | G31: 0 | I31: =SUM(C31:G31) -> 44906.25 | J31: =$D$8 -> 0.15 | K31: =I31/(1-J31) -> 52830.88
B32: INSTALL CLADDING AND TRIM | C32: 0 | D32: 0 | E32: 0 | F32: 0 | G32: 0 | I32: =SUM(C32:G32) -> 0 | J32: =$D$8 -> 0.15 | K32: =I32/(1-J32) -> 0
B33: HEAVY EQUIPMENT | C33: 0 | D33: 0 | E33: 0 | F33: 0 | G33: 0 | I33: =SUM(C33:G33) -> 0 | J33: =$D$8 -> 0.15 | K33: =I33/(1-J33) -> 0
B34: PM/GENERAL CONDITIONS/TRAVEL | C34: 20882.35 | D34: 0 | E34: 0 | F34: 0 | G34: 0 | I34: =SUM(C34:G34) -> 20882.35 | J34: =$D$8 -> 0.15 | K34: =I34/(1-J34) -> 24567.47
B35: SUBTOTAL | I35: =SUM(I29:I34) -> 65788.6 | K35: =SUM(K29:K34) -> 77398.35
B37: Electrical and Data - Materials and Subcontracting | C37: Subcontractor 1 | D37: Subcontractor 2 | E37: Subcontractor 3 | F37: Selected | G37: Additional Contingency | I37: Total Cost | J37: Install Margin | K37: Selling Price
B38: ELECTRICAL MATERIALS | C38: 44906.25 | D38: 0 | E38: 0 | F38: 0 | G38: 0 | I38: =SUM(C38:G38) -> 44906.25 | J38: =$D$9 -> 0.15 | K38: =I38/(1-J38) -> 52830.88
B39: DATA MATERIALS | C39: 0 | D39: 0 | E39: 0 | F39: 0 | G39: 0 | I39: =SUM(C39:G39) -> 0 | J39: =$D$9 -> 0.15 | K39: =I39/(1-J39) -> 0
B40: ELECTRICAL LABOR | C40: 0 | D40: 0 | E40: 0 | F40: 0 | G40: 0 | I40: =SUM(C40:G40) -> 0 | J40: =$D$9 -> 0.15 | K40: =I40/(1-J40) -> 0
B41: DATA LABOR | C41: 0 | D41: 0 | E41: 0 | F41: 0 | G41: 0 | I41: =SUM(C41:G41) -> 0 | J41: =$D$9 -> 0.15 | K41: =I41/(1-J41) -> 0
B42: SUB PANEL | C42: 0 | D42: 0 | E42: 0 | F42: 0 | G42: 0 | I42: =SUM(C42:G42) -> 0 | J42: =$D$9 -> 0.15 | K42: =I42/(1-J42) -> 0
B43: MISC | C43: 0 | D43: 0 | E43: 0 | F43: 0 | G43: 0 | I43: =SUM(C43:G43) -> 0 | J43: =$D$9 -> 0.15 | K43: =I43/(1-J43) -> 0
B44: SUBTOTAL | I44: =SUM(I38:I43) -> 44906.25 | K44: =SUM(K38:K43) -> 52830.88
B46: Submittals, Engineering, and Permits | C46: Subcontractor 1 | D46: Subcontractor 2 | E46: Subcontractor 3 | F46: Selected | G46: Additional Contingency | I46: Total Cost | J46: Install Margin | K46: Selling Price
B47: STRUCTURAL ENGINEERING | C47: 4705.88 | D47: 0 | E47: 0 | F47: 0 | G47: 0 | I47: =SUM(C47:G47) -> 4705.88 | J47: =$D$11 -> 0.15 | K47: =I47/(1-J47) -> 5536.33
B48: STRUCTURAL CERTIFICATION | C48: 0 | D48: 0 | E48: 0 | F48: 0 | G48: 0 | I48: =SUM(C48:G48) -> 0 | J48: =$D$11 -> 0.15 | K48: =I48/(1-J48) -> 0
B49: ELECTRICAL ENGINEERING | C49: 0 | D49: 0 | E49: 0 | F49: 0 | G49: 0 | I49: =SUM(C49:G49) -> 0 | J49: =$D$11 -> 0.15 | K49: =I49/(1-J49) -> 0
B50: ELECTRICAL CERTIFICATION | C50: 0 | D50: 0 | E50: 0 | F50: 0 | G50: 0 | I50: =SUM(C50:G50) -> 0 | J50: =$D$11 -> 0.15 | K50: =I50/(1-J50) -> 0
B51: PERMITS | C51: 0 | D51: 0 | E51: 0 | F51: 0 | G51: 0 | I51: =SUM(C51:G51) -> 0 | J51: =$D$11 -> 0.15 | K51: =I51/(1-J51) -> 0
B52: SUBTOTAL | I52: =SUM(I47:I51) -> 4705.88 | K52: =SUM(K47:K51) -> 5536.33
B54: ZONE GRAND TOTAL | I54: =I26+I35+I44+I52 -> 384775.56 | K54: =K26+K35+K44+K52 -> 441677.13

Sheet S.E Corridor - Install
A3: Project Name: Bank of America Stadium Modernization
A4: 2026-03-31
A5: Revised By: ANC Proposal Engine
C7: Linked Margin Assignment
C8: Install Margin | D8: 0.15
C9: Electrical Margin | D9: 0.15
C10: ANC Margin | D10: 0.15
C11: Engineering and Permits | D11: 0.15
B15: S.E Corridor
B16: Height | C16: Width | D16: Total Sq. Ft | E16: QTY
B17: 10 | C17: 34 | D17: 680 | E17: 2
B19: Structural Materials: | C19: Subcontractor 1 | D19: Subcontractor 2 | E19: Subcontractor 3 | F19: Selected | G19: Additional Contingency | I19: Total Cost | J19: Install Margin | K19: Selling Price
B20: FABRICATE PRIMARY STEEL | C20: 0 | D20: 0 | E20: 0 | F20: 0 | G20: 0 | I20: =SUM(C20:G20) -> 0 | J20: =$D$8 -> 0.15 | K20: =I20/(1-J20) -> 0
B21: SUPPLY AND INSTALL PRIMARY PLYWOOD | C21: 0 | D21: 0 | E21: 0 | F21: 0 | G21: 0 | I21: =SUM(C21:G21) -> 0 | J21: =$D$8 -> 0.15 | K21: =I21/(1-J21) -> 0
B22: FABRICATE SECONDARY STEEL SUBSTRUCTURE | C22: 7837.5 | D22: 0 | E22: 0 | F22: 0 | G22: 0 | I22: =SUM(C22:G22) -> 7837.5 | J22: =$D$8 -> 0.15 | K22: =I22/(1-J22) -> 9220.59
B23: FABRICATE CLADDING AND TRIM | C23: 0 | D23: 0 | E23: 0 | F23: 0 | G23: 0 | I23: =SUM(C23:G23) -> 0 | J23: =$D$8 -> 0.15 | K23: =I23/(1-J23) -> 0
B24: OTHER SCOPE ITEM | C24: 0 | D24: 0 | E24: 0 | F24: 0 | G24: 0 | I24: =SUM(C24:G24) -> 0 | J24: =$D$8 -> 0.15 | K24: =I24/(1-J24) -> 0
B25: OTHER SCOPE ITEM | C25: 0 | D25: 0 | E25: 0 | F25: 0 | G25: 0 | I25: =SUM(C25:G25) -> 0 | J25: =$D$8 -> 0.15 | K25: =I25/(1-J25) -> 0
B26: SUBTOTAL | I26: =SUM(I20:I25) -> 7837.5 | K26: =SUM(K20:K25) -> 9220.59
B28: Structural Labor and LED Installation | C28: Subcontractor 1 | D28: Subcontractor 2 | E28: Subcontractor 3 | F28: Selected | G28: Additional Contingency | I28: Total Cost | J28: Install Margin | K28: Selling Price
B29: REMOVAL AND DISPOSAL | C29: 0 | D29: 0 | E29: 0 | F29: 0 | G29: 0 | I29: =SUM(C29:G29) -> 0 | J29: =$D$8 -> 0.15 | K29: =I29/(1-J29) -> 0
B30: INSTALL SECONDARY STEEL SUBSTRUCTURE | C30: 0 | D30: 0 | E30: 0 | F30: 0 | G30: 0 | I30: =SUM(C30:G30) -> 0 | J30: =$D$8 -> 0.15 | K30: =I30/(1-J30) -> 0
B31: INSTALL LED DISPLAYS | C31: 32656.25 | D31: 0 | E31: 0 | F31: 0 | G31: 0 | I31: =SUM(C31:G31) -> 32656.25 | J31: =$D$8 -> 0.15 | K31: =I31/(1-J31) -> 38419.12
B32: INSTALL CLADDING AND TRIM | C32: 0 | D32: 0 | E32: 0 | F32: 0 | G32: 0 | I32: =SUM(C32:G32) -> 0 | J32: =$D$8 -> 0.15 | K32: =I32/(1-J32) -> 0
B33: HEAVY EQUIPMENT | C33: 0 | D33: 0 | E33: 0 | F33: 0 | G33: 0 | I33: =SUM(C33:G33) -> 0 | J33: =$D$8 -> 0.15 | K33: =I33/(1-J33) -> 0
B34: PM/GENERAL CONDITIONS/TRAVEL | C34: 20882.35 | D34: 0 | E34: 0 | F34: 0 | G34: 0 | I34: =SUM(C34:G34) -> 20882.35 | J34: =$D$8 -> 0.15 | K34: =I34/(1-J34) -> 24567.47
B35: SUBTOTAL | I35: =SUM(I29:I34) -> 53538.6 | K35: =SUM(K29:K34) -> 62986.59
B37: Electrical and Data - Materials and Subcontracting | C37: Subcontractor 1 | D37: Subcontractor 2 | E37: Subcontractor 3 | F37: Selected | G37: Additional Contingency | I37: Total Cost | J37: Install Margin | K37: Selling Price
B38: ELECTRICAL MATERIALS | C38: 32656.25 | D38: 0 | E38: 0 | F38: 0 | G38: 0 | I38: =SUM(C38:G38) -> 32656.25 | J38: =$D$9 -> 0.15 | K38: =I38/(1-J38) -> 38419.12
B39: DATA MATERIALS | C39: 0 | D39: 0 | E39: 0 | F39: 0 | G39: 0 | I39: =SUM(C39:G39) -> 0 | J39: =$D$9 -> 0.15 | K39: =I39/(1-J39) -> 0
B40: ELECTRICAL LABOR | C40: 0 | D40: 0 | E40: 0 | F40: 0 | G40: 0 | I40: =SUM(C40:G40) -> 0 | J40: =$D$9 -> 0.15 | K40: =I40/(1-J40) -> 0
B41: DATA LABOR | C41: 0 | D41: 0 | E41: 0 | F41: 0 | G41: 0 | I41: =SUM(C41:G41) -> 0 | J41: =$D$9 -> 0.15 | K41: =I41/(1-J41) -> 0
B42: SUB PANEL | C42: 0 | D42: 0 | E42: 0 | F42: 0 | G42: 0 | I42: =SUM(C42:G42) -> 0 | J42: =$D$9 -> 0.15 | K42: =I42/(1-J42) -> 0
B43: MISC | C43: 0 | D43: 0 | E43: 0 | F43: 0 | G43: 0 | I43: =SUM(C43:G43) -> 0 | J43: =$D$9 -> 0.15 | K43: =I43/(1-J43) -> 0
B44: SUBTOTAL | I44: =SUM(I38:I43) -> 32656.25 | K44: =SUM(K38:K43) -> 38419.12
B46: Submittals, Engineering, and Permits | C46: Subcontractor 1 | D46: Subcontractor 2 | E46: Subcontractor 3 | F46: Selected | G46: Additional Contingency | I46: Total Cost | J46: Install Margin | K46: Selling Price
B47: STRUCTURAL ENGINEERING | C47: 4705.88 | D47: 0 | E47: 0 | F47: 0 | G47: 0 | I47: =SUM(C47:G47) -> 4705.88 | J47: =$D$11 -> 0.15 | K47: =I47/(1-J47) -> 5536.33
B48: STRUCTURAL CERTIFICATION | C48: 0 | D48: 0 | E48: 0 | F48: 0 | G48: 0 | I48: =SUM(C48:G48) -> 0 | J48: =$D$11 -> 0.15 | K48: =I48/(1-J48) -> 0
B49: ELECTRICAL ENGINEERING | C49: 0 | D49: 0 | E49: 0 | F49: 0 | G49: 0 | I49: =SUM(C49:G49) -> 0 | J49: =$D$11 -> 0.15 | K49: =I49/(1-J49) -> 0
B50: ELECTRICAL CERTIFICATION | C50: 0 | D50: 0 | E50: 0 | F50: 0 | G50: 0 | I50: =SUM(C50:G50) -> 0 | J50: =$D$11 -> 0.15 | K50: =I50/(1-J50) -> 0
B51: PERMITS | C51: 0 | D51: 0 | E51: 0 | F51: 0 | G51: 0 | I51: =SUM(C51:G51) -> 0 | J51: =$D$11 -> 0.15 | K51: =I51/(1-J51) -> 0
B52: SUBTOTAL | I52: =SUM(I47:I51) -> 4705.88 | K52: =SUM(K47:K51) -> 5536.33
B54: ZONE GRAND TOTAL | I54: =I26+I35+I44+I52 -> 284422.65 | K54: =K26+K35+K44+K52 -> 326614.88

Sheet East Corridor - Install
A3: Project Name: Bank of America Stadium Modernization
A4: 2026-03-31
A5: Revised By: ANC Proposal Engine
C7: Linked Margin Assignment
C8: Install Margin | D8: 0.15
C9: Electrical Margin | D9: 0.15
C10: ANC Margin | D10: 0.15
C11: Engineering and Permits | D11: 0.15
B15: East Corridor
B16: Height | C16: Width | D16: Total Sq. Ft | E16: QTY
B17: 10 | C17: 36 | D17: 360 | E17: 1
B19: Structural Materials: | C19: Subcontractor 1 | D19: Subcontractor 2 | E19: Subcontractor 3 | F19: Selected | G19: Additional Contingency | I19: Total Cost | J19: Install Margin | K19: Selling Price
B20: FABRICATE PRIMARY STEEL | C20: 0 | D20: 0 | E20: 0 | F20: 0 | G20: 0 | I20: =SUM(C20:G20) -> 0 | J20: =$D$8 -> 0.15 | K20: =I20/(1-J20) -> 0
B21: SUPPLY AND INSTALL PRIMARY PLYWOOD | C21: 0 | D21: 0 | E21: 0 | F21: 0 | G21: 0 | I21: =SUM(C21:G21) -> 0 | J21: =$D$8 -> 0.15 | K21: =I21/(1-J21) -> 0
B22: FABRICATE SECONDARY STEEL SUBSTRUCTURE | C22: 4151.25 | D22: 0 | E22: 0 | F22: 0 | G22: 0 | I22: =SUM(C22:G22) -> 4151.25 | J22: =$D$8 -> 0.15 | K22: =I22/(1-J22) -> 4883.82
B23: FABRICATE CLADDING AND TRIM | C23: 0 | D23: 0 | E23: 0 | F23: 0 | G23: 0 | I23: =SUM(C23:G23) -> 0 | J23: =$D$8 -> 0.15 | K23: =I23/(1-J23) -> 0
B24: OTHER SCOPE ITEM | C24: 0 | D24: 0 | E24: 0 | F24: 0 | G24: 0 | I24: =SUM(C24:G24) -> 0 | J24: =$D$8 -> 0.15 | K24: =I24/(1-J24) -> 0
B25: OTHER SCOPE ITEM | C25: 0 | D25: 0 | E25: 0 | F25: 0 | G25: 0 | I25: =SUM(C25:G25) -> 0 | J25: =$D$8 -> 0.15 | K25: =I25/(1-J25) -> 0
B26: SUBTOTAL | I26: =SUM(I20:I25) -> 4151.25 | K26: =SUM(K20:K25) -> 4883.82
B28: Structural Labor and LED Installation | C28: Subcontractor 1 | D28: Subcontractor 2 | E28: Subcontractor 3 | F28: Selected | G28: Additional Contingency | I28: Total Cost | J28: Install Margin | K28: Selling Price
B29: REMOVAL AND DISPOSAL | C29: 0 | D29: 0 | E29: 0 | F29: 0 | G29: 0 | I29: =SUM(C29:G29) -> 0 | J29: =$D$8 -> 0.15 | K29: =I29/(1-J29) -> 0
B30: INSTALL SECONDARY STEEL SUBSTRUCTURE | C30: 0 | D30: 0 | E30: 0 | F30: 0 | G30: 0 | I30: =SUM(C30:G30) -> 0 | J30: =$D$8 -> 0.15 | K30: =I30/(1-J30) -> 0
B31: INSTALL LED DISPLAYS | C31: 17296.88 | D31: 0 | E31: 0 | F31: 0 | G31: 0 | I31: =SUM(C31:G31) -> 17296.88 | J31: =$D$8 -> 0.15 | K31: =I31/(1-J31) -> 20349.27
B32: INSTALL CLADDING AND TRIM | C32: 0 | D32: 0 | E32: 0 | F32: 0 | G32: 0 | I32: =SUM(C32:G32) -> 0 | J32: =$D$8 -> 0.15 | K32: =I32/(1-J32) -> 0
B33: HEAVY EQUIPMENT | C33: 0 | D33: 0 | E33: 0 | F33: 0 | G33: 0 | I33: =SUM(C33:G33) -> 0 | J33: =$D$8 -> 0.15 | K33: =I33/(1-J33) -> 0
B34: PM/GENERAL CONDITIONS/TRAVEL | C34: 20882.35 | D34: 0 | E34: 0 | F34: 0 | G34: 0 | I34: =SUM(C34:G34) -> 20882.35 | J34: =$D$8 -> 0.15 | K34: =I34/(1-J34) -> 24567.47
B35: SUBTOTAL | I35: =SUM(I29:I34) -> 38179.23 | K35: =SUM(K29:K34) -> 44916.74
B37: Electrical and Data - Materials and Subcontracting | C37: Subcontractor 1 | D37: Subcontractor 2 | E37: Subcontractor 3 | F37: Selected | G37: Additional Contingency | I37: Total Cost | J37: Install Margin | K37: Selling Price
B38: ELECTRICAL MATERIALS | C38: 17296.88 | D38: 0 | E38: 0 | F38: 0 | G38: 0 | I38: =SUM(C38:G38) -> 17296.88 | J38: =$D$9 -> 0.15 | K38: =I38/(1-J38) -> 20349.27
B39: DATA MATERIALS | C39: 0 | D39: 0 | E39: 0 | F39: 0 | G39: 0 | I39: =SUM(C39:G39) -> 0 | J39: =$D$9 -> 0.15 | K39: =I39/(1-J39) -> 0
B40: ELECTRICAL LABOR | C40: 0 | D40: 0 | E40: 0 | F40: 0 | G40: 0 | I40: =SUM(C40:G40) -> 0 | J40: =$D$9 -> 0.15 | K40: =I40/(1-J40) -> 0
B41: DATA LABOR | C41: 0 | D41: 0 | E41: 0 | F41: 0 | G41: 0 | I41: =SUM(C41:G41) -> 0 | J41: =$D$9 -> 0.15 | K41: =I41/(1-J41) -> 0
B42: SUB PANEL | C42: 0 | D42: 0 | E42: 0 | F42: 0 | G42: 0 | I42: =SUM(C42:G42) -> 0 | J42: =$D$9 -> 0.15 | K42: =I42/(1-J42) -> 0
B43: MISC | C43: 0 | D43: 0 | E43: 0 | F43: 0 | G43: 0 | I43: =SUM(C43:G43) -> 0 | J43: =$D$9 -> 0.15 | K43: =I43/(1-J43) -> 0
B44: SUBTOTAL | I44: =SUM(I38:I43) -> 17296.88 | K44: =SUM(K38:K43) -> 20349.27
B46: Submittals, Engineering, and Permits | C46: Subcontractor 1 | D46: Subcontractor 2 | E46: Subcontractor 3 | F46: Selected | G46: Additional Contingency | I46: Total Cost | J46: Install Margin | K46: Selling Price
B47: STRUCTURAL ENGINEERING | C47: 4705.88 | D47: 0 | E47: 0 | F47: 0 | G47: 0 | I47: =SUM(C47:G47) -> 4705.88 | J47: =$D$11 -> 0.15 | K47: =I47/(1-J47) -> 5536.33
B48: STRUCTURAL CERTIFICATION | C48: 0 | D48: 0 | E48: 0 | F48: 0 | G48: 0 | I48: =SUM(C48:G48) -> 0 | J48: =$D$11 -> 0.15 | K48: =I48/(1-J48) -> 0
B49: ELECTRICAL ENGINEERING | C49: 0 | D49: 0 | E49: 0 | F49: 0 | G49: 0 | I49: =SUM(C49:G49) -> 0 | J49: =$D$11 -> 0.15 | K49: =I49/(1-J49) -> 0
B50: ELECTRICAL CERTIFICATION | C50: 0 | D50: 0 | E50: 0 | F50: 0 | G50: 0 | I50: =SUM(C50:G50) -> 0 | J50: =$D$11 -> 0.15 | K50: =I50/(1-J50) -> 0
B51: PERMITS | C51: 0 | D51: 0 | E51: 0 | F51: 0 | G51: 0 | I51: =SUM(C51:G51) -> 0 | J51: =$D$11 -> 0.15 | K51: =I51/(1-J51) -> 0
B52: SUBTOTAL | I52: =SUM(I47:I51) -> 4705.88 | K52: =SUM(K47:K51) -> 5536.33
B54: ZONE GRAND TOTAL | I54: =I26+I35+I44+I52 -> 168495.58 | K54: =K26+K35+K44+K52 -> 193994.8

Sheet N.E Corridor - Install
A3: Project Name: Bank of America Stadium Modernization
A4: 2026-03-31
A5: Revised By: ANC Proposal Engine
C7: Linked Margin Assignment
C8: Install Margin | D8: 0.15
C9: Electrical Margin | D9: 0.15
C10: ANC Margin | D10: 0.15
C11: Engineering and Permits | D11: 0.15
B15: N.E Corridor
B16: Height | C16: Width | D16: Total Sq. Ft | E16: QTY
B17: 10 | C17: 34 | D17: 680 | E17: 2
B19: Structural Materials: | C19: Subcontractor 1 | D19: Subcontractor 2 | E19: Subcontractor 3 | F19: Selected | G19: Additional Contingency | I19: Total Cost | J19: Install Margin | K19: Selling Price
B20: FABRICATE PRIMARY STEEL | C20: 0 | D20: 0 | E20: 0 | F20: 0 | G20: 0 | I20: =SUM(C20:G20) -> 0 | J20: =$D$8 -> 0.15 | K20: =I20/(1-J20) -> 0
B21: SUPPLY AND INSTALL PRIMARY PLYWOOD | C21: 0 | D21: 0 | E21: 0 | F21: 0 | G21: 0 | I21: =SUM(C21:G21) -> 0 | J21: =$D$8 -> 0.15 | K21: =I21/(1-J21) -> 0
B22: FABRICATE SECONDARY STEEL SUBSTRUCTURE | C22: 7837.5 | D22: 0 | E22: 0 | F22: 0 | G22: 0 | I22: =SUM(C22:G22) -> 7837.5 | J22: =$D$8 -> 0.15 | K22: =I22/(1-J22) -> 9220.59
B23: FABRICATE CLADDING AND TRIM | C23: 0 | D23: 0 | E23: 0 | F23: 0 | G23: 0 | I23: =SUM(C23:G23) -> 0 | J23: =$D$8 -> 0.15 | K23: =I23/(1-J23) -> 0
B24: OTHER SCOPE ITEM | C24: 0 | D24: 0 | E24: 0 | F24: 0 | G24: 0 | I24: =SUM(C24:G24) -> 0 | J24: =$D$8 -> 0.15 | K24: =I24/(1-J24) -> 0
B25: OTHER SCOPE ITEM | C25: 0 | D25: 0 | E25: 0 | F25: 0 | G25: 0 | I25: =SUM(C25:G25) -> 0 | J25: =$D$8 -> 0.15 | K25: =I25/(1-J25) -> 0
B26: SUBTOTAL | I26: =SUM(I20:I25) -> 7837.5 | K26: =SUM(K20:K25) -> 9220.59
B28: Structural Labor and LED Installation | C28: Subcontractor 1 | D28: Subcontractor 2 | E28: Subcontractor 3 | F28: Selected | G28: Additional Contingency | I28: Total Cost | J28: Install Margin | K28: Selling Price
B29: REMOVAL AND DISPOSAL | C29: 0 | D29: 0 | E29: 0 | F29: 0 | G29: 0 | I29: =SUM(C29:G29) -> 0 | J29: =$D$8 -> 0.15 | K29: =I29/(1-J29) -> 0
B30: INSTALL SECONDARY STEEL SUBSTRUCTURE | C30: 0 | D30: 0 | E30: 0 | F30: 0 | G30: 0 | I30: =SUM(C30:G30) -> 0 | J30: =$D$8 -> 0.15 | K30: =I30/(1-J30) -> 0
B31: INSTALL LED DISPLAYS | C31: 32656.25 | D31: 0 | E31: 0 | F31: 0 | G31: 0 | I31: =SUM(C31:G31) -> 32656.25 | J31: =$D$8 -> 0.15 | K31: =I31/(1-J31) -> 38419.12
B32: INSTALL CLADDING AND TRIM | C32: 0 | D32: 0 | E32: 0 | F32: 0 | G32: 0 | I32: =SUM(C32:G32) -> 0 | J32: =$D$8 -> 0.15 | K32: =I32/(1-J32) -> 0
B33: HEAVY EQUIPMENT | C33: 0 | D33: 0 | E33: 0 | F33: 0 | G33: 0 | I33: =SUM(C33:G33) -> 0 | J33: =$D$8 -> 0.15 | K33: =I33/(1-J33) -> 0
B34: PM/GENERAL CONDITIONS/TRAVEL | C34: 20882.35 | D34: 0 | E34: 0 | F34: 0 | G34: 0 | I34: =SUM(C34:G34) -> 20882.35 | J34: =$D$8 -> 0.15 | K34: =I34/(1-J34) -> 24567.47
B35: SUBTOTAL | I35: =SUM(I29:I34) -> 53538.6 | K35: =SUM(K29:K34) -> 62986.59
B37: Electrical and Data - Materials and Subcontracting | C37: Subcontractor 1 | D37: Subcontractor 2 | E37: Subcontractor 3 | F37: Selected | G37: Additional Contingency | I37: Total Cost | J37: Install Margin | K37: Selling Price
B38: ELECTRICAL MATERIALS | C38: 32656.25 | D38: 0 | E38: 0 | F38: 0 | G38: 0 | I38: =SUM(C38:G38) -> 32656.25 | J38: =$D$9 -> 0.15 | K38: =I38/(1-J38) -> 38419.12
B39: DATA MATERIALS | C39: 0 | D39: 0 | E39: 0 | F39: 0 | G39: 0 | I39: =SUM(C39:G39) -> 0 | J39: =$D$9 -> 0.15 | K39: =I39/(1-J39) -> 0
B40: ELECTRICAL LABOR | C40: 0 | D40: 0 | E40: 0 | F40: 0 | G40: 0 | I40: =SUM(C40:G40) -> 0 | J40: =$D$9 -> 0.15 | K40: =I40/(1-J40) -> 0
B41: DATA LABOR | C41: 0 | D41: 0 | E41: 0 | F41: 0 | G41: 0 | I41: =SUM(C41:G41) -> 0 | J41: =$D$9 -> 0.15 | K41: =I41/(1-J41) -> 0
B42: SUB PANEL | C42: 0 | D42: 0 | E42: 0 | F42: 0 | G42: 0 | I42: =SUM(C42:G42) -> 0 | J42: =$D$9 -> 0.15 | K42: =I42/(1-J42) -> 0
B43: MISC | C43: 0 | D43: 0 | E43: 0 | F43: 0 | G43: 0 | I43: =SUM(C43:G43) -> 0 | J43: =$D$9 -> 0.15 | K43: =I43/(1-J43) -> 0
B44: SUBTOTAL | I44: =SUM(I38:I43) -> 32656.25 | K44: =SUM(K38:K43) -> 38419.12
B46: Submittals, Engineering, and Permits | C46: Subcontractor 1 | D46: Subcontractor 2 | E46: Subcontractor 3 | F46: Selected | G46: Additional Contingency | I46: Total Cost | J46: Install Margin | K46: Selling Price
B47: STRUCTURAL ENGINEERING | C47: 4705.88 | D47: 0 | E47: 0 | F47: 0 | G47: 0 | I47: =SUM(C47:G47) -> 4705.88 | J47: =$D$11 -> 0.15 | K47: =I47/(1-J47) -> 5536.33
B48: STRUCTURAL CERTIFICATION | C48: 0 | D48: 0 | E48: 0 | F48: 0 | G48: 0 | I48: =SUM(C48:G48) -> 0 | J48: =$D$11 -> 0.15 | K48: =I48/(1-J48) -> 0
B49: ELECTRICAL ENGINEERING | C49: 0 | D49: 0 | E49: 0 | F49: 0 | G49: 0 | I49: =SUM(C49:G49) -> 0 | J49: =$D$11 -> 0.15 | K49: =I49/(1-J49) -> 0
B50: ELECTRICAL CERTIFICATION | C50: 0 | D50: 0 | E50: 0 | F50: 0 | G50: 0 | I50: =SUM(C50:G50) -> 0 | J50: =$D$11 -> 0.15 | K50: =I50/(1-J50) -> 0
B51: PERMITS | C51: 0 | D51: 0 | E51: 0 | F51: 0 | G51: 0 | I51: =SUM(C51:G51) -> 0 | J51: =$D$11 -> 0.15 | K51: =I51/(1-J51) -> 0
B52: SUBTOTAL | I52: =SUM(I47:I51) -> 4705.88 | K52: =SUM(K47:K51) -> 5536.33
B54: ZONE GRAND TOTAL | I54: =I26+I35+I44+I52 -> 284422.65 | K54: =K26+K35+K44+K52 -> 326614.88

Sheet Elev Lobby - Install
A3: Project Name: Bank of America Stadium Modernization
A4: 2026-03-31
A5: Revised By: ANC Proposal Engine
C7: Linked Margin Assignment
C8: Install Margin | D8: 0.15
C9: Electrical Margin | D9: 0.15
C10: ANC Margin | D10: 0.15
C11: Engineering and Permits | D11: 0.15
B15: Elev Lobby
B16: Height | C16: Width | D16: Total Sq. Ft | E16: QTY
B17: 4 | C17: 6 | D17: 96 | E17: 4
B19: Structural Materials: | C19: Subcontractor 1 | D19: Subcontractor 2 | E19: Subcontractor 3 | F19: Selected | G19: Additional Contingency | I19: Total Cost | J19: Install Margin | K19: Selling Price
B20: FABRICATE PRIMARY STEEL | C20: 0 | D20: 0 | E20: 0 | F20: 0 | G20: 0 | I20: =SUM(C20:G20) -> 0 | J20: =$D$8 -> 0.15 | K20: =I20/(1-J20) -> 0
B21: SUPPLY AND INSTALL PRIMARY PLYWOOD | C21: 0 | D21: 0 | E21: 0 | F21: 0 | G21: 0 | I21: =SUM(C21:G21) -> 0 | J21: =$D$8 -> 0.15 | K21: =I21/(1-J21) -> 0
B22: FABRICATE SECONDARY STEEL SUBSTRUCTURE | C22: 1110 | D22: 0 | E22: 0 | F22: 0 | G22: 0 | I22: =SUM(C22:G22) -> 1110 | J22: =$D$8 -> 0.15 | K22: =I22/(1-J22) -> 1305.88
B23: FABRICATE CLADDING AND TRIM | C23: 0 | D23: 0 | E23: 0 | F23: 0 | G23: 0 | I23: =SUM(C23:G23) -> 0 | J23: =$D$8 -> 0.15 | K23: =I23/(1-J23) -> 0
B24: OTHER SCOPE ITEM | C24: 0 | D24: 0 | E24: 0 | F24: 0 | G24: 0 | I24: =SUM(C24:G24) -> 0 | J24: =$D$8 -> 0.15 | K24: =I24/(1-J24) -> 0
B25: OTHER SCOPE ITEM | C25: 0 | D25: 0 | E25: 0 | F25: 0 | G25: 0 | I25: =SUM(C25:G25) -> 0 | J25: =$D$8 -> 0.15 | K25: =I25/(1-J25) -> 0
B26: SUBTOTAL | I26: =SUM(I20:I25) -> 1110 | K26: =SUM(K20:K25) -> 1305.88
B28: Structural Labor and LED Installation | C28: Subcontractor 1 | D28: Subcontractor 2 | E28: Subcontractor 3 | F28: Selected | G28: Additional Contingency | I28: Total Cost | J28: Install Margin | K28: Selling Price
B29: REMOVAL AND DISPOSAL | C29: 0 | D29: 0 | E29: 0 | F29: 0 | G29: 0 | I29: =SUM(C29:G29) -> 0 | J29: =$D$8 -> 0.15 | K29: =I29/(1-J29) -> 0
B30: INSTALL SECONDARY STEEL SUBSTRUCTURE | C30: 0 | D30: 0 | E30: 0 | F30: 0 | G30: 0 | I30: =SUM(C30:G30) -> 0 | J30: =$D$8 -> 0.15 | K30: =I30/(1-J30) -> 0
B31: INSTALL LED DISPLAYS | C31: 4625 | D31: 0 | E31: 0 | F31: 0 | G31: 0 | I31: =SUM(C31:G31) -> 4625 | J31: =$D$8 -> 0.15 | K31: =I31/(1-J31) -> 5441.18
B32: INSTALL CLADDING AND TRIM | C32: 0 | D32: 0 | E32: 0 | F32: 0 | G32: 0 | I32: =SUM(C32:G32) -> 0 | J32: =$D$8 -> 0.15 | K32: =I32/(1-J32) -> 0
B33: HEAVY EQUIPMENT | C33: 0 | D33: 0 | E33: 0 | F33: 0 | G33: 0 | I33: =SUM(C33:G33) -> 0 | J33: =$D$8 -> 0.15 | K33: =I33/(1-J33) -> 0
B34: PM/GENERAL CONDITIONS/TRAVEL | C34: 20882.35 | D34: 0 | E34: 0 | F34: 0 | G34: 0 | I34: =SUM(C34:G34) -> 20882.35 | J34: =$D$8 -> 0.15 | K34: =I34/(1-J34) -> 24567.47
B35: SUBTOTAL | I35: =SUM(I29:I34) -> 25507.35 | K35: =SUM(K29:K34) -> 30008.65
B37: Electrical and Data - Materials and Subcontracting | C37: Subcontractor 1 | D37: Subcontractor 2 | E37: Subcontractor 3 | F37: Selected | G37: Additional Contingency | I37: Total Cost | J37: Install Margin | K37: Selling Price
B38: ELECTRICAL MATERIALS | C38: 4625 | D38: 0 | E38: 0 | F38: 0 | G38: 0 | I38: =SUM(C38:G38) -> 4625 | J38: =$D$9 -> 0.15 | K38: =I38/(1-J38) -> 5441.18
B39: DATA MATERIALS | C39: 0 | D39: 0 | E39: 0 | F39: 0 | G39: 0 | I39: =SUM(C39:G39) -> 0 | J39: =$D$9 -> 0.15 | K39: =I39/(1-J39) -> 0
B40: ELECTRICAL LABOR | C40: 0 | D40: 0 | E40: 0 | F40: 0 | G40: 0 | I40: =SUM(C40:G40) -> 0 | J40: =$D$9 -> 0.15 | K40: =I40/(1-J40) -> 0
B41: DATA LABOR | C41: 0 | D41: 0 | E41: 0 | F41: 0 | G41: 0 | I41: =SUM(C41:G41) -> 0 | J41: =$D$9 -> 0.15 | K41: =I41/(1-J41) -> 0
B42: SUB PANEL | C42: 0 | D42: 0 | E42: 0 | F42: 0 | G42: 0 | I42: =SUM(C42:G42) -> 0 | J42: =$D$9 -> 0.15 | K42: =I42/(1-J42) -> 0
B43: MISC | C43: 0 | D43: 0 | E43: 0 | F43: 0 | G43: 0 | I43: =SUM(C43:G43) -> 0 | J43: =$D$9 -> 0.15 | K43: =I43/(1-J43) -> 0
B44: SUBTOTAL | I44: =SUM(I38:I43) -> 4625 | K44: =SUM(K38:K43) -> 5441.18
B46: Submittals, Engineering, and Permits | C46: Subcontractor 1 | D46: Subcontractor 2 | E46: Subcontractor 3 | F46: Selected | G46: Additional Contingency | I46: Total Cost | J46: Install Margin | K46: Selling Price
B47: STRUCTURAL ENGINEERING | C47: 4705.88 | D47: 0 | E47: 0 | F47: 0 | G47: 0 | I47: =SUM(C47:G47) -> 4705.88 | J47: =$D$11 -> 0.15 | K47: =I47/(1-J47) -> 5536.33
B48: STRUCTURAL CERTIFICATION | C48: 0 | D48: 0 | E48: 0 | F48: 0 | G48: 0 | I48: =SUM(C48:G48) -> 0 | J48: =$D$11 -> 0.15 | K48: =I48/(1-J48) -> 0
B49: ELECTRICAL ENGINEERING | C49: 0 | D49: 0 | E49: 0 | F49: 0 | G49: 0 | I49: =SUM(C49:G49) -> 0 | J49: =$D$11 -> 0.15 | K49: =I49/(1-J49) -> 0
B50: ELECTRICAL CERTIFICATION | C50: 0 | D50: 0 | E50: 0 | F50: 0 | G50: 0 | I50: =SUM(C50:G50) -> 0 | J50: =$D$11 -> 0.15 | K50: =I50/(1-J50) -> 0
B51: PERMITS | C51: 0 | D51: 0 | E51: 0 | F51: 0 | G51: 0 | I51: =SUM(C51:G51) -> 0 | J51: =$D$11 -> 0.15 | K51: =I51/(1-J51) -> 0
B52: SUBTOTAL | I52: =SUM(I47:I51) -> 4705.88 | K52: =SUM(K47:K51) -> 5536.33
B54: ZONE GRAND TOTAL | I54: =I26+I35+I44+I52 -> 60854.85 | K54: =K26+K35+K44+K52 -> 70464.54

Sheet North Club - Install
A3: Project Name: Bank of America Stadium Modernization
A4: 2026-03-31
A5: Revised By: ANC Proposal Engine
C7: Linked Margin Assignment
C8: Install Margin | D8: 0.15
C9: Electrical Margin | D9: 0.15
C10: ANC Margin | D10: 0.15
C11: Engineering and Permits | D11: 0.15
B15: North Club
B16: Height | C16: Width | D16: Total Sq. Ft | E16: QTY
B17: 10 | C17: 16 | D17: 320 | E17: 2
B19: Structural Materials: | C19: Subcontractor 1 | D19: Subcontractor 2 | E19: Subcontractor 3 | F19: Selected | G19: Additional Contingency | I19: Total Cost | J19: Install Margin | K19: Selling Price
B20: FABRICATE PRIMARY STEEL | C20: 0 | D20: 0 | E20: 0 | F20: 0 | G20: 0 | I20: =SUM(C20:G20) -> 0 | J20: =$D$8 -> 0.15 | K20: =I20/(1-J20) -> 0
B21: SUPPLY AND INSTALL PRIMARY PLYWOOD | C21: 0 | D21: 0 | E21: 0 | F21: 0 | G21: 0 | I21: =SUM(C21:G21) -> 0 | J21: =$D$8 -> 0.15 | K21: =I21/(1-J21) -> 0
B22: FABRICATE SECONDARY STEEL SUBSTRUCTURE | C22: 3690 | D22: 0 | E22: 0 | F22: 0 | G22: 0 | I22: =SUM(C22:G22) -> 3690 | J22: =$D$8 -> 0.15 | K22: =I22/(1-J22) -> 4341.18
B23: FABRICATE CLADDING AND TRIM | C23: 0 | D23: 0 | E23: 0 | F23: 0 | G23: 0 | I23: =SUM(C23:G23) -> 0 | J23: =$D$8 -> 0.15 | K23: =I23/(1-J23) -> 0
B24: OTHER SCOPE ITEM | C24: 0 | D24: 0 | E24: 0 | F24: 0 | G24: 0 | I24: =SUM(C24:G24) -> 0 | J24: =$D$8 -> 0.15 | K24: =I24/(1-J24) -> 0
B25: OTHER SCOPE ITEM | C25: 0 | D25: 0 | E25: 0 | F25: 0 | G25: 0 | I25: =SUM(C25:G25) -> 0 | J25: =$D$8 -> 0.15 | K25: =I25/(1-J25) -> 0
B26: SUBTOTAL | I26: =SUM(I20:I25) -> 3690 | K26: =SUM(K20:K25) -> 4341.18
B28: Structural Labor and LED Installation | C28: Subcontractor 1 | D28: Subcontractor 2 | E28: Subcontractor 3 | F28: Selected | G28: Additional Contingency | I28: Total Cost | J28: Install Margin | K28: Selling Price
B29: REMOVAL AND DISPOSAL | C29: 0 | D29: 0 | E29: 0 | F29: 0 | G29: 0 | I29: =SUM(C29:G29) -> 0 | J29: =$D$8 -> 0.15 | K29: =I29/(1-J29) -> 0
B30: INSTALL SECONDARY STEEL SUBSTRUCTURE | C30: 0 | D30: 0 | E30: 0 | F30: 0 | G30: 0 | I30: =SUM(C30:G30) -> 0 | J30: =$D$8 -> 0.15 | K30: =I30/(1-J30) -> 0
B31: INSTALL LED DISPLAYS | C31: 15375 | D31: 0 | E31: 0 | F31: 0 | G31: 0 | I31: =SUM(C31:G31) -> 15375 | J31: =$D$8 -> 0.15 | K31: =I31/(1-J31) -> 18088.24
B32: INSTALL CLADDING AND TRIM | C32: 0 | D32: 0 | E32: 0 | F32: 0 | G32: 0 | I32: =SUM(C32:G32) -> 0 | J32: =$D$8 -> 0.15 | K32: =I32/(1-J32) -> 0
B33: HEAVY EQUIPMENT | C33: 0 | D33: 0 | E33: 0 | F33: 0 | G33: 0 | I33: =SUM(C33:G33) -> 0 | J33: =$D$8 -> 0.15 | K33: =I33/(1-J33) -> 0
B34: PM/GENERAL CONDITIONS/TRAVEL | C34: 20882.35 | D34: 0 | E34: 0 | F34: 0 | G34: 0 | I34: =SUM(C34:G34) -> 20882.35 | J34: =$D$8 -> 0.15 | K34: =I34/(1-J34) -> 24567.47
B35: SUBTOTAL | I35: =SUM(I29:I34) -> 36257.35 | K35: =SUM(K29:K34) -> 42655.71
B37: Electrical and Data - Materials and Subcontracting | C37: Subcontractor 1 | D37: Subcontractor 2 | E37: Subcontractor 3 | F37: Selected | G37: Additional Contingency | I37: Total Cost | J37: Install Margin | K37: Selling Price
B38: ELECTRICAL MATERIALS | C38: 15375 | D38: 0 | E38: 0 | F38: 0 | G38: 0 | I38: =SUM(C38:G38) -> 15375 | J38: =$D$9 -> 0.15 | K38: =I38/(1-J38) -> 18088.24
B39: DATA MATERIALS | C39: 0 | D39: 0 | E39: 0 | F39: 0 | G39: 0 | I39: =SUM(C39:G39) -> 0 | J39: =$D$9 -> 0.15 | K39: =I39/(1-J39) -> 0
B40: ELECTRICAL LABOR | C40: 0 | D40: 0 | E40: 0 | F40: 0 | G40: 0 | I40: =SUM(C40:G40) -> 0 | J40: =$D$9 -> 0.15 | K40: =I40/(1-J40) -> 0
B41: DATA LABOR | C41: 0 | D41: 0 | E41: 0 | F41: 0 | G41: 0 | I41: =SUM(C41:G41) -> 0 | J41: =$D$9 -> 0.15 | K41: =I41/(1-J41) -> 0
B42: SUB PANEL | C42: 0 | D42: 0 | E42: 0 | F42: 0 | G42: 0 | I42: =SUM(C42:G42) -> 0 | J42: =$D$9 -> 0.15 | K42: =I42/(1-J42) -> 0
B43: MISC | C43: 0 | D43: 0 | E43: 0 | F43: 0 | G43: 0 | I43: =SUM(C43:G43) -> 0 | J43: =$D$9 -> 0.15 | K43: =I43/(1-J43) -> 0
B44: SUBTOTAL | I44: =SUM(I38:I43) -> 15375 | K44: =SUM(K38:K43) -> 18088.24
B46: Submittals, Engineering, and Permits | C46: Subcontractor 1 | D46: Subcontractor 2 | E46: Subcontractor 3 | F46: Selected | G46: Additional Contingency | I46: Total Cost | J46: Install Margin | K46: Selling Price
B47: STRUCTURAL ENGINEERING | C47: 4705.88 | D47: 0 | E47: 0 | F47: 0 | G47: 0 | I47: =SUM(C47:G47) -> 4705.88 | J47: =$D$11 -> 0.15 | K47: =I47/(1-J47) -> 5536.33
B48: STRUCTURAL CERTIFICATION | C48: 0 | D48: 0 | E48: 0 | F48: 0 | G48: 0 | I48: =SUM(C48:G48) -> 0 | J48: =$D$11 -> 0.15 | K48: =I48/(1-J48) -> 0
B49: ELECTRICAL ENGINEERING | C49: 0 | D49: 0 | E49: 0 | F49: 0 | G49: 0 | I49: =SUM(C49:G49) -> 0 | J49: =$D$11 -> 0.15 | K49: =I49/(1-J49) -> 0
B50: ELECTRICAL CERTIFICATION | C50: 0 | D50: 0 | E50: 0 | F50: 0 | G50: 0 | I50: =SUM(C50:G50) -> 0 | J50: =$D$11 -> 0.15 | K50: =I50/(1-J50) -> 0
B51: PERMITS | C51: 0 | D51: 0 | E51: 0 | F51: 0 | G51: 0 | I51: =SUM(C51:G51) -> 0 | J51: =$D$11 -> 0.15 | K51: =I51/(1-J51) -> 0
B52: SUBTOTAL | I52: =SUM(I47:I51) -> 4705.88 | K52: =SUM(K47:K51) -> 5536.33
B54: ZONE GRAND TOTAL | I54: =I26+I35+I44+I52 -> 154000.31 | K54: =K26+K35+K44+K52 -> 177412.13

Sheet Panthers Den - Install
A3: Project Name: Bank of America Stadium Modernization
A4: 2026-03-31
A5: Revised By: ANC Proposal Engine
C7: Linked Margin Assignment
C8: Install Margin | D8: 0.15
C9: Electrical Margin | D9: 0.15
C10: ANC Margin | D10: 0.15
C11: Engineering and Permits | D11: 0.15
B15: Panthers Den
B16: Height | C16: Width | D16: Total Sq. Ft | E16: QTY
B17: 22 | C17: 3 | D17: 198 | E17: 3
B19: Structural Materials: | C19: Subcontractor 1 | D19: Subcontractor 2 | E19: Subcontractor 3 | F19: Selected | G19: Additional Contingency | I19: Total Cost | J19: Install Margin | K19: Selling Price
B20: FABRICATE PRIMARY STEEL | C20: 0 | D20: 0 | E20: 0 | F20: 0 | G20: 0 | I20: =SUM(C20:G20) -> 0 | J20: =$D$8 -> 0.15 | K20: =I20/(1-J20) -> 0
B21: SUPPLY AND INSTALL PRIMARY PLYWOOD | C21: 0 | D21: 0 | E21: 0 | F21: 0 | G21: 0 | I21: =SUM(C21:G21) -> 0 | J21: =$D$8 -> 0.15 | K21: =I21/(1-J21) -> 0
B22: FABRICATE SECONDARY STEEL SUBSTRUCTURE | C22: 2272.5 | D22: 0 | E22: 0 | F22: 0 | G22: 0 | I22: =SUM(C22:G22) -> 2272.5 | J22: =$D$8 -> 0.15 | K22: =I22/(1-J22) -> 2673.53
B23: FABRICATE CLADDING AND TRIM | C23: 0 | D23: 0 | E23: 0 | F23: 0 | G23: 0 | I23: =SUM(C23:G23) -> 0 | J23: =$D$8 -> 0.15 | K23: =I23/(1-J23) -> 0
B24: OTHER SCOPE ITEM | C24: 0 | D24: 0 | E24: 0 | F24: 0 | G24: 0 | I24: =SUM(C24:G24) -> 0 | J24: =$D$8 -> 0.15 | K24: =I24/(1-J24) -> 0
B25: OTHER SCOPE ITEM | C25: 0 | D25: 0 | E25: 0 | F25: 0 | G25: 0 | I25: =SUM(C25:G25) -> 0 | J25: =$D$8 -> 0.15 | K25: =I25/(1-J25) -> 0
B26: SUBTOTAL | I26: =SUM(I20:I25) -> 2272.5 | K26: =SUM(K20:K25) -> 2673.53
B28: Structural Labor and LED Installation | C28: Subcontractor 1 | D28: Subcontractor 2 | E28: Subcontractor 3 | F28: Selected | G28: Additional Contingency | I28: Total Cost | J28: Install Margin | K28: Selling Price
B29: REMOVAL AND DISPOSAL | C29: 0 | D29: 0 | E29: 0 | F29: 0 | G29: 0 | I29: =SUM(C29:G29) -> 0 | J29: =$D$8 -> 0.15 | K29: =I29/(1-J29) -> 0
B30: INSTALL SECONDARY STEEL SUBSTRUCTURE | C30: 0 | D30: 0 | E30: 0 | F30: 0 | G30: 0 | I30: =SUM(C30:G30) -> 0 | J30: =$D$8 -> 0.15 | K30: =I30/(1-J30) -> 0
B31: INSTALL LED DISPLAYS | C31: 9468.75 | D31: 0 | E31: 0 | F31: 0 | G31: 0 | I31: =SUM(C31:G31) -> 9468.75 | J31: =$D$8 -> 0.15 | K31: =I31/(1-J31) -> 11139.71
B32: INSTALL CLADDING AND TRIM | C32: 0 | D32: 0 | E32: 0 | F32: 0 | G32: 0 | I32: =SUM(C32:G32) -> 0 | J32: =$D$8 -> 0.15 | K32: =I32/(1-J32) -> 0
B33: HEAVY EQUIPMENT | C33: 0 | D33: 0 | E33: 0 | F33: 0 | G33: 0 | I33: =SUM(C33:G33) -> 0 | J33: =$D$8 -> 0.15 | K33: =I33/(1-J33) -> 0
B34: PM/GENERAL CONDITIONS/TRAVEL | C34: 20882.35 | D34: 0 | E34: 0 | F34: 0 | G34: 0 | I34: =SUM(C34:G34) -> 20882.35 | J34: =$D$8 -> 0.15 | K34: =I34/(1-J34) -> 24567.47
B35: SUBTOTAL | I35: =SUM(I29:I34) -> 30351.1 | K35: =SUM(K29:K34) -> 35707.18
B37: Electrical and Data - Materials and Subcontracting | C37: Subcontractor 1 | D37: Subcontractor 2 | E37: Subcontractor 3 | F37: Selected | G37: Additional Contingency | I37: Total Cost | J37: Install Margin | K37: Selling Price
B38: ELECTRICAL MATERIALS | C38: 9468.75 | D38: 0 | E38: 0 | F38: 0 | G38: 0 | I38: =SUM(C38:G38) -> 9468.75 | J38: =$D$9 -> 0.15 | K38: =I38/(1-J38) -> 11139.71
B39: DATA MATERIALS | C39: 0 | D39: 0 | E39: 0 | F39: 0 | G39: 0 | I39: =SUM(C39:G39) -> 0 | J39: =$D$9 -> 0.15 | K39: =I39/(1-J39) -> 0
B40: ELECTRICAL LABOR | C40: 0 | D40: 0 | E40: 0 | F40: 0 | G40: 0 | I40: =SUM(C40:G40) -> 0 | J40: =$D$9 -> 0.15 | K40: =I40/(1-J40) -> 0
B41: DATA LABOR | C41: 0 | D41: 0 | E41: 0 | F41: 0 | G41: 0 | I41: =SUM(C41:G41) -> 0 | J41: =$D$9 -> 0.15 | K41: =I41/(1-J41) -> 0
B42: SUB PANEL | C42: 0 | D42: 0 | E42: 0 | F42: 0 | G42: 0 | I42: =SUM(C42:G42) -> 0 | J42: =$D$9 -> 0.15 | K42: =I42/(1-J42) -> 0
B43: MISC | C43: 0 | D43: 0 | E43: 0 | F43: 0 | G43: 0 | I43: =SUM(C43:G43) -> 0 | J43: =$D$9 -> 0.15 | K43: =I43/(1-J43) -> 0
B44: SUBTOTAL | I44: =SUM(I38:I43) -> 9468.75 | K44: =SUM(K38:K43) -> 11139.71
B46: Submittals, Engineering, and Permits | C46: Subcontractor 1 | D46: Subcontractor 2 | E46: Subcontractor 3 | F46: Selected | G46: Additional Contingency | I46: Total Cost | J46: Install Margin | K46: Selling Price
B47: STRUCTURAL ENGINEERING | C47: 4705.88 | D47: 0 | E47: 0 | F47: 0 | G47: 0 | I47: =SUM(C47:G47) -> 4705.88 | J47: =$D$11 -> 0.15 | K47: =I47/(1-J47) -> 5536.33
B48: STRUCTURAL CERTIFICATION | C48: 0 | D48: 0 | E48: 0 | F48: 0 | G48: 0 | I48: =SUM(C48:G48) -> 0 | J48: =$D$11 -> 0.15 | K48: =I48/(1-J48) -> 0
B49: ELECTRICAL ENGINEERING | C49: 0 | D49: 0 | E49: 0 | F49: 0 | G49: 0 | I49: =SUM(C49:G49) -> 0 | J49: =$D$11 -> 0.15 | K49: =I49/(1-J49) -> 0
B50: ELECTRICAL CERTIFICATION | C50: 0 | D50: 0 | E50: 0 | F50: 0 | G50: 0 | I50: =SUM(C50:G50) -> 0 | J50: =$D$11 -> 0.15 | K50: =I50/(1-J50) -> 0
B51: PERMITS | C51: 0 | D51: 0 | E51: 0 | F51: 0 | G51: 0 | I51: =SUM(C51:G51) -> 0 | J51: =$D$11 -> 0.15 | K51: =I51/(1-J51) -> 0
B52: SUBTOTAL | I52: =SUM(I47:I51) -> 4705.88 | K52: =SUM(K47:K51) -> 5536.33
B54: ZONE GRAND TOTAL | I54: =I26+I35+I44+I52 -> 97690.02 | K54: =K26+K35+K44+K52 -> 112600.03

Sheet Panthers Den12 - Install
A3: Project Name: Bank of America Stadium Modernization
A4: 2026-03-31
A5: Revised By: ANC Proposal Engine
C7: Linked Margin Assignment
C8: Install Margin | D8: 0.15
C9: Electrical Margin | D9: 0.15
C10: ANC Margin | D10: 0.15
C11: Engineering and Permits | D11: 0.15
B15: Panthers Den
B16: Height | C16: Width | D16: Total Sq. Ft | E16: QTY
B17: 19 | C17: 3.1667 | D17: 60.17 | E17: 1
B19: Structural Materials: | C19: Subcontractor 1 | D19: Subcontractor 2 | E19: Subcontractor 3 | F19: Selected | G19: Additional Contingency | I19: Total Cost | J19: Install Margin | K19: Selling Price
B20: FABRICATE PRIMARY STEEL | C20: 0 | D20: 0 | E20: 0 | F20: 0 | G20: 0 | I20: =SUM(C20:G20) -> 0 | J20: =$D$8 -> 0.15 | K20: =I20/(1-J20) -> 0
B21: SUPPLY AND INSTALL PRIMARY PLYWOOD | C21: 0 | D21: 0 | E21: 0 | F21: 0 | G21: 0 | I21: =SUM(C21:G21) -> 0 | J21: =$D$8 -> 0.15 | K21: =I21/(1-J21) -> 0
B22: FABRICATE SECONDARY STEEL SUBSTRUCTURE | C22: 690 | D22: 0 | E22: 0 | F22: 0 | G22: 0 | I22: =SUM(C22:G22) -> 690 | J22: =$D$8 -> 0.15 | K22: =I22/(1-J22) -> 811.76
B23: FABRICATE CLADDING AND TRIM | C23: 0 | D23: 0 | E23: 0 | F23: 0 | G23: 0 | I23: =SUM(C23:G23) -> 0 | J23: =$D$8 -> 0.15 | K23: =I23/(1-J23) -> 0
B24: OTHER SCOPE ITEM | C24: 0 | D24: 0 | E24: 0 | F24: 0 | G24: 0 | I24: =SUM(C24:G24) -> 0 | J24: =$D$8 -> 0.15 | K24: =I24/(1-J24) -> 0
B25: OTHER SCOPE ITEM | C25: 0 | D25: 0 | E25: 0 | F25: 0 | G25: 0 | I25: =SUM(C25:G25) -> 0 | J25: =$D$8 -> 0.15 | K25: =I25/(1-J25) -> 0
B26: SUBTOTAL | I26: =SUM(I20:I25) -> 690 | K26: =SUM(K20:K25) -> 811.76
B28: Structural Labor and LED Installation | C28: Subcontractor 1 | D28: Subcontractor 2 | E28: Subcontractor 3 | F28: Selected | G28: Additional Contingency | I28: Total Cost | J28: Install Margin | K28: Selling Price
B29: REMOVAL AND DISPOSAL | C29: 0 | D29: 0 | E29: 0 | F29: 0 | G29: 0 | I29: =SUM(C29:G29) -> 0 | J29: =$D$8 -> 0.15 | K29: =I29/(1-J29) -> 0
B30: INSTALL SECONDARY STEEL SUBSTRUCTURE | C30: 0 | D30: 0 | E30: 0 | F30: 0 | G30: 0 | I30: =SUM(C30:G30) -> 0 | J30: =$D$8 -> 0.15 | K30: =I30/(1-J30) -> 0
B31: INSTALL LED DISPLAYS | C31: 2875 | D31: 0 | E31: 0 | F31: 0 | G31: 0 | I31: =SUM(C31:G31) -> 2875 | J31: =$D$8 -> 0.15 | K31: =I31/(1-J31) -> 3382.35
B32: INSTALL CLADDING AND TRIM | C32: 0 | D32: 0 | E32: 0 | F32: 0 | G32: 0 | I32: =SUM(C32:G32) -> 0 | J32: =$D$8 -> 0.15 | K32: =I32/(1-J32) -> 0
B33: HEAVY EQUIPMENT | C33: 0 | D33: 0 | E33: 0 | F33: 0 | G33: 0 | I33: =SUM(C33:G33) -> 0 | J33: =$D$8 -> 0.15 | K33: =I33/(1-J33) -> 0
B34: PM/GENERAL CONDITIONS/TRAVEL | C34: 20882.35 | D34: 0 | E34: 0 | F34: 0 | G34: 0 | I34: =SUM(C34:G34) -> 20882.35 | J34: =$D$8 -> 0.15 | K34: =I34/(1-J34) -> 24567.47
B35: SUBTOTAL | I35: =SUM(I29:I34) -> 23757.35 | K35: =SUM(K29:K34) -> 27949.82
B37: Electrical and Data - Materials and Subcontracting | C37: Subcontractor 1 | D37: Subcontractor 2 | E37: Subcontractor 3 | F37: Selected | G37: Additional Contingency | I37: Total Cost | J37: Install Margin | K37: Selling Price
B38: ELECTRICAL MATERIALS | C38: 2875 | D38: 0 | E38: 0 | F38: 0 | G38: 0 | I38: =SUM(C38:G38) -> 2875 | J38: =$D$9 -> 0.15 | K38: =I38/(1-J38) -> 3382.35
B39: DATA MATERIALS | C39: 0 | D39: 0 | E39: 0 | F39: 0 | G39: 0 | I39: =SUM(C39:G39) -> 0 | J39: =$D$9 -> 0.15 | K39: =I39/(1-J39) -> 0
B40: ELECTRICAL LABOR | C40: 0 | D40: 0 | E40: 0 | F40: 0 | G40: 0 | I40: =SUM(C40:G40) -> 0 | J40: =$D$9 -> 0.15 | K40: =I40/(1-J40) -> 0
B41: DATA LABOR | C41: 0 | D41: 0 | E41: 0 | F41: 0 | G41: 0 | I41: =SUM(C41:G41) -> 0 | J41: =$D$9 -> 0.15 | K41: =I41/(1-J41) -> 0
B42: SUB PANEL | C42: 0 | D42: 0 | E42: 0 | F42: 0 | G42: 0 | I42: =SUM(C42:G42) -> 0 | J42: =$D$9 -> 0.15 | K42: =I42/(1-J42) -> 0
B43: MISC | C43: 0 | D43: 0 | E43: 0 | F43: 0 | G43: 0 | I43: =SUM(C43:G43) -> 0 | J43: =$D$9 -> 0.15 | K43: =I43/(1-J43) -> 0
B44: SUBTOTAL | I44: =SUM(I38:I43) -> 2875 | K44: =SUM(K38:K43) -> 3382.35
B46: Submittals, Engineering, and Permits | C46: Subcontractor 1 | D46: Subcontractor 2 | E46: Subcontractor 3 | F46: Selected | G46: Additional Contingency | I46: Total Cost | J46: Install Margin | K46: Selling Price
B47: STRUCTURAL ENGINEERING | C47: 4705.88 | D47: 0 | E47: 0 | F47: 0 | G47: 0 | I47: =SUM(C47:G47) -> 4705.88 | J47: =$D$11 -> 0.15 | K47: =I47/(1-J47) -> 5536.33
B48: STRUCTURAL CERTIFICATION | C48: 0 | D48: 0 | E48: 0 | F48: 0 | G48: 0 | I48: =SUM(C48:G48) -> 0 | J48: =$D$11 -> 0.15 | K48: =I48/(1-J48) -> 0
B49: ELECTRICAL ENGINEERING | C49: 0 | D49: 0 | E49: 0 | F49: 0 | G49: 0 | I49: =SUM(C49:G49) -> 0 | J49: =$D$11 -> 0.15 | K49: =I49/(1-J49) -> 0
B50: ELECTRICAL CERTIFICATION | C50: 0 | D50: 0 | E50: 0 | F50: 0 | G50: 0 | I50: =SUM(C50:G50) -> 0 | J50: =$D$11 -> 0.15 | K50: =I50/(1-J50) -> 0
B51: PERMITS | C51: 0 | D51: 0 | E51: 0 | F51: 0 | G51: 0 | I51: =SUM(C51:G51) -> 0 | J51: =$D$11 -> 0.15 | K51: =I51/(1-J51) -> 0
B52: SUBTOTAL | I52: =SUM(I47:I51) -> 4705.88 | K52: =SUM(K47:K51) -> 5536.33
B54: ZONE GRAND TOTAL | I54: =I26+I35+I44+I52 -> 47806.93 | K54: =K26+K35+K44+K52 -> 55535.56

Sheet Panthers Den13 - Install
A3: Project Name: Bank of America Stadium Modernization
A4: 2026-03-31
A5: Revised By: ANC Proposal Engine
C7: Linked Margin Assignment
C8: Install Margin | D8: 0.15
C9: Electrical Margin | D9: 0.15
C10: ANC Margin | D10: 0.15
C11: Engineering and Permits | D11: 0.15
B15: Panthers Den
B16: Height | C16: Width | D16: Total Sq. Ft | E16: QTY
B17: 22 | C17: 3 | D17: 66 | E17: 1
B19: Structural Materials: | C19: Subcontractor 1 | D19: Subcontractor 2 | E19: Subcontractor 3 | F19: Selected | G19: Additional Contingency | I19: Total Cost | J19: Install Margin | K19: Selling Price
B20: FABRICATE PRIMARY STEEL | C20: 0 | D20: 0 | E20: 0 | F20: 0 | G20: 0 | I20: =SUM(C20:G20) -> 0 | J20: =$D$8 -> 0.15 | K20: =I20/(1-J20) -> 0
B21: SUPPLY AND INSTALL PRIMARY PLYWOOD | C21: 0 | D21: 0 | E21: 0 | F21: 0 | G21: 0 | I21: =SUM(C21:G21) -> 0 | J21: =$D$8 -> 0.15 | K21: =I21/(1-J21) -> 0
B22: FABRICATE SECONDARY STEEL SUBSTRUCTURE | C22: 757.5 | D22: 0 | E22: 0 | F22: 0 | G22: 0 | I22: =SUM(C22:G22) -> 757.5 | J22: =$D$8 -> 0.15 | K22: =I22/(1-J22) -> 891.18
B23: FABRICATE CLADDING AND TRIM | C23: 0 | D23: 0 | E23: 0 | F23: 0 | G23: 0 | I23: =SUM(C23:G23) -> 0 | J23: =$D$8 -> 0.15 | K23: =I23/(1-J23) -> 0
B24: OTHER SCOPE ITEM | C24: 0 | D24: 0 | E24: 0 | F24: 0 | G24: 0 | I24: =SUM(C24:G24) -> 0 | J24: =$D$8 -> 0.15 | K24: =I24/(1-J24) -> 0
B25: OTHER SCOPE ITEM | C25: 0 | D25: 0 | E25: 0 | F25: 0 | G25: 0 | I25: =SUM(C25:G25) -> 0 | J25: =$D$8 -> 0.15 | K25: =I25/(1-J25) -> 0
B26: SUBTOTAL | I26: =SUM(I20:I25) -> 757.5 | K26: =SUM(K20:K25) -> 891.18
B28: Structural Labor and LED Installation | C28: Subcontractor 1 | D28: Subcontractor 2 | E28: Subcontractor 3 | F28: Selected | G28: Additional Contingency | I28: Total Cost | J28: Install Margin | K28: Selling Price
B29: REMOVAL AND DISPOSAL | C29: 0 | D29: 0 | E29: 0 | F29: 0 | G29: 0 | I29: =SUM(C29:G29) -> 0 | J29: =$D$8 -> 0.15 | K29: =I29/(1-J29) -> 0
B30: INSTALL SECONDARY STEEL SUBSTRUCTURE | C30: 0 | D30: 0 | E30: 0 | F30: 0 | G30: 0 | I30: =SUM(C30:G30) -> 0 | J30: =$D$8 -> 0.15 | K30: =I30/(1-J30) -> 0
B31: INSTALL LED DISPLAYS | C31: 3156.25 | D31: 0 | E31: 0 | F31: 0 | G31: 0 | I31: =SUM(C31:G31) -> 3156.25 | J31: =$D$8 -> 0.15 | K31: =I31/(1-J31) -> 3713.24
B32: INSTALL CLADDING AND TRIM | C32: 0 | D32: 0 | E32: 0 | F32: 0 | G32: 0 | I32: =SUM(C32:G32) -> 0 | J32: =$D$8 -> 0.15 | K32: =I32/(1-J32) -> 0
B33: HEAVY EQUIPMENT | C33: 0 | D33: 0 | E33: 0 | F33: 0 | G33: 0 | I33: =SUM(C33:G33) -> 0 | J33: =$D$8 -> 0.15 | K33: =I33/(1-J33) -> 0
B34: PM/GENERAL CONDITIONS/TRAVEL | C34: 20882.35 | D34: 0 | E34: 0 | F34: 0 | G34: 0 | I34: =SUM(C34:G34) -> 20882.35 | J34: =$D$8 -> 0.15 | K34: =I34/(1-J34) -> 24567.47
B35: SUBTOTAL | I35: =SUM(I29:I34) -> 24038.6 | K35: =SUM(K29:K34) -> 28280.71
B37: Electrical and Data - Materials and Subcontracting | C37: Subcontractor 1 | D37: Subcontractor 2 | E37: Subcontractor 3 | F37: Selected | G37: Additional Contingency | I37: Total Cost | J37: Install Margin | K37: Selling Price
B38: ELECTRICAL MATERIALS | C38: 3156.25 | D38: 0 | E38: 0 | F38: 0 | G38: 0 | I38: =SUM(C38:G38) -> 3156.25 | J38: =$D$9 -> 0.15 | K38: =I38/(1-J38) -> 3713.24
B39: DATA MATERIALS | C39: 0 | D39: 0 | E39: 0 | F39: 0 | G39: 0 | I39: =SUM(C39:G39) -> 0 | J39: =$D$9 -> 0.15 | K39: =I39/(1-J39) -> 0
B40: ELECTRICAL LABOR | C40: 0 | D40: 0 | E40: 0 | F40: 0 | G40: 0 | I40: =SUM(C40:G40) -> 0 | J40: =$D$9 -> 0.15 | K40: =I40/(1-J40) -> 0
B41: DATA LABOR | C41: 0 | D41: 0 | E41: 0 | F41: 0 | G41: 0 | I41: =SUM(C41:G41) -> 0 | J41: =$D$9 -> 0.15 | K41: =I41/(1-J41) -> 0
B42: SUB PANEL | C42: 0 | D42: 0 | E42: 0 | F42: 0 | G42: 0 | I42: =SUM(C42:G42) -> 0 | J42: =$D$9 -> 0.15 | K42: =I42/(1-J42) -> 0
B43: MISC | C43: 0 | D43: 0 | E43: 0 | F43: 0 | G43: 0 | I43: =SUM(C43:G43) -> 0 | J43: =$D$9 -> 0.15 | K43: =I43/(1-J43) -> 0
B44: SUBTOTAL | I44: =SUM(I38:I43) -> 3156.25 | K44: =SUM(K38:K43) -> 3713.24
B46: Submittals, Engineering, and Permits | C46: Subcontractor 1 | D46: Subcontractor 2 | E46: Subcontractor 3 | F46: Selected | G46: Additional Contingency | I46: Total Cost | J46: Install Margin | K46: Selling Price
B47: STRUCTURAL ENGINEERING | C47: 4705.88 | D47: 0 | E47: 0 | F47: 0 | G47: 0 | I47: =SUM(C47:G47) -> 4705.88 | J47: =$D$11 -> 0.15 | K47: =I47/(1-J47) -> 5536.33
B48: STRUCTURAL CERTIFICATION | C48: 0 | D48: 0 | E48: 0 | F48: 0 | G48: 0 | I48: =SUM(C48:G48) -> 0 | J48: =$D$11 -> 0.15 | K48: =I48/(1-J48) -> 0
B49: ELECTRICAL ENGINEERING | C49: 0 | D49: 0 | E49: 0 | F49: 0 | G49: 0 | I49: =SUM(C49:G49) -> 0 | J49: =$D$11 -> 0.15 | K49: =I49/(1-J49) -> 0
B50: ELECTRICAL CERTIFICATION | C50: 0 | D50: 0 | E50: 0 | F50: 0 | G50: 0 | I50: =SUM(C50:G50) -> 0 | J50: =$D$11 -> 0.15 | K50: =I50/(1-J50) -> 0
B51: PERMITS | C51: 0 | D51: 0 | E51: 0 | F51: 0 | G51: 0 | I51: =SUM(C51:G51) -> 0 | J51: =$D$11 -> 0.15 | K51: =I51/(1-J51) -> 0
B52: SUBTOTAL | I52: =SUM(I47:I51) -> 4705.88 | K52: =SUM(K47:K51) -> 5536.33
B54: ZONE GRAND TOTAL | I54: =I26+I35+I44+I52 -> 49922.16 | K54: =K26+K35+K44+K52 -> 57955.49

Sheet Panthers Den14 - Install
A3: Project Name: Bank of America Stadium Modernization
A4: 2026-03-31
A5: Revised By: ANC Proposal Engine
C7: Linked Margin Assignment
C8: Install Margin | D8: 0.15
C9: Electrical Margin | D9: 0.15
C10: ANC Margin | D10: 0.15
C11: Engineering and Permits | D11: 0.15
B15: Panthers Den
B16: Height | C16: Width | D16: Total Sq. Ft | E16: QTY
B17: 19 | C17: 3.1667 | D17: 60.17 | E17: 1
B19: Structural Materials: | C19: Subcontractor 1 | D19: Subcontractor 2 | E19: Subcontractor 3 | F19: Selected | G19: Additional Contingency | I19: Total Cost | J19: Install Margin | K19: Selling Price
B20: FABRICATE PRIMARY STEEL | C20: 0 | D20: 0 | E20: 0 | F20: 0 | G20: 0 | I20: =SUM(C20:G20) -> 0 | J20: =$D$8 -> 0.15 | K20: =I20/(1-J20) -> 0
B21: SUPPLY AND INSTALL PRIMARY PLYWOOD | C21: 0 | D21: 0 | E21: 0 | F21: 0 | G21: 0 | I21: =SUM(C21:G21) -> 0 | J21: =$D$8 -> 0.15 | K21: =I21/(1-J21) -> 0
B22: FABRICATE SECONDARY STEEL SUBSTRUCTURE | C22: 690 | D22: 0 | E22: 0 | F22: 0 | G22: 0 | I22: =SUM(C22:G22) -> 690 | J22: =$D$8 -> 0.15 | K22: =I22/(1-J22) -> 811.76
B23: FABRICATE CLADDING AND TRIM | C23: 0 | D23: 0 | E23: 0 | F23: 0 | G23: 0 | I23: =SUM(C23:G23) -> 0 | J23: =$D$8 -> 0.15 | K23: =I23/(1-J23) -> 0
B24: OTHER SCOPE ITEM | C24: 0 | D24: 0 | E24: 0 | F24: 0 | G24: 0 | I24: =SUM(C24:G24) -> 0 | J24: =$D$8 -> 0.15 | K24: =I24/(1-J24) -> 0
B25: OTHER SCOPE ITEM | C25: 0 | D25: 0 | E25: 0 | F25: 0 | G25: 0 | I25: =SUM(C25:G25) -> 0 | J25: =$D$8 -> 0.15 | K25: =I25/(1-J25) -> 0
B26: SUBTOTAL | I26: =SUM(I20:I25) -> 690 | K26: =SUM(K20:K25) -> 811.76
B28: Structural Labor and LED Installation | C28: Subcontractor 1 | D28: Subcontractor 2 | E28: Subcontractor 3 | F28: Selected | G28: Additional Contingency | I28: Total Cost | J28: Install Margin | K28: Selling Price
B29: REMOVAL AND DISPOSAL | C29: 0 | D29: 0 | E29: 0 | F29: 0 | G29: 0 | I29: =SUM(C29:G29) -> 0 | J29: =$D$8 -> 0.15 | K29: =I29/(1-J29) -> 0
B30: INSTALL SECONDARY STEEL SUBSTRUCTURE | C30: 0 | D30: 0 | E30: 0 | F30: 0 | G30: 0 | I30: =SUM(C30:G30) -> 0 | J30: =$D$8 -> 0.15 | K30: =I30/(1-J30) -> 0
B31: INSTALL LED DISPLAYS | C31: 2875 | D31: 0 | E31: 0 | F31: 0 | G31: 0 | I31: =SUM(C31:G31) -> 2875 | J31: =$D$8 -> 0.15 | K31: =I31/(1-J31) -> 3382.35
B32: INSTALL CLADDING AND TRIM | C32: 0 | D32: 0 | E32: 0 | F32: 0 | G32: 0 | I32: =SUM(C32:G32) -> 0 | J32: =$D$8 -> 0.15 | K32: =I32/(1-J32) -> 0
B33: HEAVY EQUIPMENT | C33: 0 | D33: 0 | E33: 0 | F33: 0 | G33: 0 | I33: =SUM(C33:G33) -> 0 | J33: =$D$8 -> 0.15 | K33: =I33/(1-J33) -> 0
B34: PM/GENERAL CONDITIONS/TRAVEL | C34: 20882.35 | D34: 0 | E34: 0 | F34: 0 | G34: 0 | I34: =SUM(C34:G34) -> 20882.35 | J34: =$D$8 -> 0.15 | K34: =I34/(1-J34) -> 24567.47
B35: SUBTOTAL | I35: =SUM(I29:I34) -> 23757.35 | K35: =SUM(K29:K34) -> 27949.82
B37: Electrical and Data - Materials and Subcontracting | C37: Subcontractor 1 | D37: Subcontractor 2 | E37: Subcontractor 3 | F37: Selected | G37: Additional Contingency | I37: Total Cost | J37: Install Margin | K37: Selling Price
B38: ELECTRICAL MATERIALS | C38: 2875 | D38: 0 | E38: 0 | F38: 0 | G38: 0 | I38: =SUM(C38:G38) -> 2875 | J38: =$D$9 -> 0.15 | K38: =I38/(1-J38) -> 3382.35
B39: DATA MATERIALS | C39: 0 | D39: 0 | E39: 0 | F39: 0 | G39: 0 | I39: =SUM(C39:G39) -> 0 | J39: =$D$9 -> 0.15 | K39: =I39/(1-J39) -> 0
B40: ELECTRICAL LABOR | C40: 0 | D40: 0 | E40: 0 | F40: 0 | G40: 0 | I40: =SUM(C40:G40) -> 0 | J40: =$D$9 -> 0.15 | K40: =I40/(1-J40) -> 0
B41: DATA LABOR | C41: 0 | D41: 0 | E41: 0 | F41: 0 | G41: 0 | I41: =SUM(C41:G41) -> 0 | J41: =$D$9 -> 0.15 | K41: =I41/(1-J41) -> 0
B42: SUB PANEL | C42: 0 | D42: 0 | E42: 0 | F42: 0 | G42: 0 | I42: =SUM(C42:G42) -> 0 | J42: =$D$9 -> 0.15 | K42: =I42/(1-J42) -> 0
B43: MISC | C43: 0 | D43: 0 | E43: 0 | F43: 0 | G43: 0 | I43: =SUM(C43:G43) -> 0 | J43: =$D$9 -> 0.15 | K43: =I43/(1-J43) -> 0
B44: SUBTOTAL | I44: =SUM(I38:I43) -> 2875 | K44: =SUM(K38:K43) -> 3382.35
B46: Submittals, Engineering, and Permits | C46: Subcontractor 1 | D46: Subcontractor 2 | E46: Subcontractor 3 | F46: Selected | G46: Additional Contingency | I46: Total Cost | J46: Install Margin | K46: Selling Price
B47: STRUCTURAL ENGINEERING | C47: 4705.88 | D47: 0 | E47: 0 | F47: 0 | G47: 0 | I47: =SUM(C47:G47) -> 4705.88 | J47: =$D$11 -> 0.15 | K47: =I47/(1-J47) -> 5536.33
B48: STRUCTURAL CERTIFICATION | C48: 0 | D48: 0 | E48: 0 | F48: 0 | G48: 0 | I48: =SUM(C48:G48) -> 0 | J48: =$D$11 -> 0.15 | K48: =I48/(1-J48) -> 0
B49: ELECTRICAL ENGINEERING | C49: 0 | D49: 0 | E49: 0 | F49: 0 | G49: 0 | I49: =SUM(C49:G49) -> 0 | J49: =$D$11 -> 0.15 | K49: =I49/(1-J49) -> 0
B50: ELECTRICAL CERTIFICATION | C50: 0 | D50: 0 | E50: 0 | F50: 0 | G50: 0 | I50: =SUM(C50:G50) -> 0 | J50: =$D$11 -> 0.15 | K50: =I50/(1-J50) -> 0
B51: PERMITS | C51: 0 | D51: 0 | E51: 0 | F51: 0 | G51: 0 | I51: =SUM(C51:G51) -> 0 | J51: =$D$11 -> 0.15 | K51: =I51/(1-J51) -> 0
B52: SUBTOTAL | I52: =SUM(I47:I51) -> 4705.88 | K52: =SUM(K47:K51) -> 5536.33
B54: ZONE GRAND TOTAL | I54: =I26+I35+I44+I52 -> 47806.93 | K54: =K26+K35+K44+K52 -> 55535.56

Sheet South Club - Install
A3: Project Name: Bank of America Stadium Modernization
A4: 2026-03-31
A5: Revised By: ANC Proposal Engine
C7: Linked Margin Assignment
C8: Install Margin | D8: 0.15
C9: Electrical Margin | D9: 0.15
C10: ANC Margin | D10: 0.15
C11: Engineering and Permits | D11: 0.15
B15: South Club
B16: Height | C16: Width | D16: Total Sq. Ft | E16: QTY
B17: 10 | C17: 16 | D17: 320 | E17: 2
B19: Structural Materials: | C19: Subcontractor 1 | D19: Subcontractor 2 | E19: Subcontractor 3 | F19: Selected | G19: Additional Contingency | I19: Total Cost | J19: Install Margin | K19: Selling Price
B20: FABRICATE PRIMARY STEEL | C20: 0 | D20: 0 | E20: 0 | F20: 0 | G20: 0 | I20: =SUM(C20:G20) -> 0 | J20: =$D$8 -> 0.15 | K20: =I20/(1-J20) -> 0
B21: SUPPLY AND INSTALL PRIMARY PLYWOOD | C21: 0 | D21: 0 | E21: 0 | F21: 0 | G21: 0 | I21: =SUM(C21:G21) -> 0 | J21: =$D$8 -> 0.15 | K21: =I21/(1-J21) -> 0
B22: FABRICATE SECONDARY STEEL SUBSTRUCTURE | C22: 3690 | D22: 0 | E22: 0 | F22: 0 | G22: 0 | I22: =SUM(C22:G22) -> 3690 | J22: =$D$8 -> 0.15 | K22: =I22/(1-J22) -> 4341.18
B23: FABRICATE CLADDING AND TRIM | C23: 0 | D23: 0 | E23: 0 | F23: 0 | G23: 0 | I23: =SUM(C23:G23) -> 0 | J23: =$D$8 -> 0.15 | K23: =I23/(1-J23) -> 0
B24: OTHER SCOPE ITEM | C24: 0 | D24: 0 | E24: 0 | F24: 0 | G24: 0 | I24: =SUM(C24:G24) -> 0 | J24: =$D$8 -> 0.15 | K24: =I24/(1-J24) -> 0
B25: OTHER SCOPE ITEM | C25: 0 | D25: 0 | E25: 0 | F25: 0 | G25: 0 | I25: =SUM(C25:G25) -> 0 | J25: =$D$8 -> 0.15 | K25: =I25/(1-J25) -> 0
B26: SUBTOTAL | I26: =SUM(I20:I25) -> 3690 | K26: =SUM(K20:K25) -> 4341.18
B28: Structural Labor and LED Installation | C28: Subcontractor 1 | D28: Subcontractor 2 | E28: Subcontractor 3 | F28: Selected | G28: Additional Contingency | I28: Total Cost | J28: Install Margin | K28: Selling Price
B29: REMOVAL AND DISPOSAL | C29: 0 | D29: 0 | E29: 0 | F29: 0 | G29: 0 | I29: =SUM(C29:G29) -> 0 | J29: =$D$8 -> 0.15 | K29: =I29/(1-J29) -> 0
B30: INSTALL SECONDARY STEEL SUBSTRUCTURE | C30: 0 | D30: 0 | E30: 0 | F30: 0 | G30: 0 | I30: =SUM(C30:G30) -> 0 | J30: =$D$8 -> 0.15 | K30: =I30/(1-J30) -> 0
B31: INSTALL LED DISPLAYS | C31: 15375 | D31: 0 | E31: 0 | F31: 0 | G31: 0 | I31: =SUM(C31:G31) -> 15375 | J31: =$D$8 -> 0.15 | K31: =I31/(1-J31) -> 18088.24
B32: INSTALL CLADDING AND TRIM | C32: 0 | D32: 0 | E32: 0 | F32: 0 | G32: 0 | I32: =SUM(C32:G32) -> 0 | J32: =$D$8 -> 0.15 | K32: =I32/(1-J32) -> 0
B33: HEAVY EQUIPMENT | C33: 0 | D33: 0 | E33: 0 | F33: 0 | G33: 0 | I33: =SUM(C33:G33) -> 0 | J33: =$D$8 -> 0.15 | K33: =I33/(1-J33) -> 0
B34: PM/GENERAL CONDITIONS/TRAVEL | C34: 20882.35 | D34: 0 | E34: 0 | F34: 0 | G34: 0 | I34: =SUM(C34:G34) -> 20882.35 | J34: =$D$8 -> 0.15 | K34: =I34/(1-J34) -> 24567.47
B35: SUBTOTAL | I35: =SUM(I29:I34) -> 36257.35 | K35: =SUM(K29:K34) -> 42655.71
B37: Electrical and Data - Materials and Subcontracting | C37: Subcontractor 1 | D37: Subcontractor 2 | E37: Subcontractor 3 | F37: Selected | G37: Additional Contingency | I37: Total Cost | J37: Install Margin | K37: Selling Price
B38: ELECTRICAL MATERIALS | C38: 15375 | D38: 0 | E38: 0 | F38: 0 | G38: 0 | I38: =SUM(C38:G38) -> 15375 | J38: =$D$9 -> 0.15 | K38: =I38/(1-J38) -> 18088.24
B39: DATA MATERIALS | C39: 0 | D39: 0 | E39: 0 | F39: 0 | G39: 0 | I39: =SUM(C39:G39) -> 0 | J39: =$D$9 -> 0.15 | K39: =I39/(1-J39) -> 0
B40: ELECTRICAL LABOR | C40: 0 | D40: 0 | E40: 0 | F40: 0 | G40: 0 | I40: =SUM(C40:G40) -> 0 | J40: =$D$9 -> 0.15 | K40: =I40/(1-J40) -> 0
B41: DATA LABOR | C41: 0 | D41: 0 | E41: 0 | F41: 0 | G41: 0 | I41: =SUM(C41:G41) -> 0 | J41: =$D$9 -> 0.15 | K41: =I41/(1-J41) -> 0
B42: SUB PANEL | C42: 0 | D42: 0 | E42: 0 | F42: 0 | G42: 0 | I42: =SUM(C42:G42) -> 0 | J42: =$D$9 -> 0.15 | K42: =I42/(1-J42) -> 0
B43: MISC | C43: 0 | D43: 0 | E43: 0 | F43: 0 | G43: 0 | I43: =SUM(C43:G43) -> 0 | J43: =$D$9 -> 0.15 | K43: =I43/(1-J43) -> 0
B44: SUBTOTAL | I44: =SUM(I38:I43) -> 15375 | K44: =SUM(K38:K43) -> 18088.24
B46: Submittals, Engineering, and Permits | C46: Subcontractor 1 | D46: Subcontractor 2 | E46: Subcontractor 3 | F46: Selected | G46: Additional Contingency | I46: Total Cost | J46: Install Margin | K46: Selling Price
B47: STRUCTURAL ENGINEERING | C47: 4705.88 | D47: 0 | E47: 0 | F47: 0 | G47: 0 | I47: =SUM(C47:G47) -> 4705.88 | J47: =$D$11 -> 0.15 | K47: =I47/(1-J47) -> 5536.33
B48: STRUCTURAL CERTIFICATION | C48: 0 | D48: 0 | E48: 0 | F48: 0 | G48: 0 | I48: =SUM(C48:G48) -> 0 | J48: =$D$11 -> 0.15 | K48: =I48/(1-J48) -> 0
B49: ELECTRICAL ENGINEERING | C49: 0 | D49: 0 | E49: 0 | F49: 0 | G49: 0 | I49: =SUM(C49:G49) -> 0 | J49: =$D$11 -> 0.15 | K49: =I49/(1-J49) -> 0
B50: ELECTRICAL CERTIFICATION | C50: 0 | D50: 0 | E50: 0 | F50: 0 | G50: 0 | I50: =SUM(C50:G50) -> 0 | J50: =$D$11 -> 0.15 | K50: =I50/(1-J50) -> 0
B51: PERMITS | C51: 0 | D51: 0 | E51: 0 | F51: 0 | G51: 0 | I51: =SUM(C51:G51) -> 0 | J51: =$D$11 -> 0.15 | K51: =I51/(1-J51) -> 0
B52: SUBTOTAL | I52: =SUM(I47:I51) -> 4705.88 | K52: =SUM(K47:K51) -> 5536.33
B54: ZONE GRAND TOTAL | I54: =I26+I35+I44+I52 -> 154000.31 | K54: =K26+K35+K44+K52 -> 177412.13

Sheet S.E Corridor16 - Install
A3: Project Name: Bank of America Stadium Modernization
A4: 2026-03-31
A5: Revised By: ANC Proposal Engine
C7: Linked Margin Assignment
C8: Install Margin | D8: 0.15
C9: Electrical Margin | D9: 0.15
C10: ANC Margin | D10: 0.15
C11: Engineering and Permits | D11: 0.15
B15: S.E Corridor
B16: Height | C16: Width | D16: Total Sq. Ft | E16: QTY
B17: 10 | C17: 34 | D17: 340 | E17: 1
B19: Structural Materials: | C19: Subcontractor 1 | D19: Subcontractor 2 | E19: Subcontractor 3 | F19: Selected | G19: Additional Contingency | I19: Total Cost | J19: Install Margin | K19: Selling Price
B20: FABRICATE PRIMARY STEEL | C20: 0 | D20: 0 | E20: 0 | F20: 0 | G20: 0 | I20: =SUM(C20:G20) -> 0 | J20: =$D$8 -> 0.15 | K20: =I20/(1-J20) -> 0
B21: SUPPLY AND INSTALL PRIMARY PLYWOOD | C21: 0 | D21: 0 | E21: 0 | F21: 0 | G21: 0 | I21: =SUM(C21:G21) -> 0 | J21: =$D$8 -> 0.15 | K21: =I21/(1-J21) -> 0
B22: FABRICATE SECONDARY STEEL SUBSTRUCTURE | C22: 3918.75 | D22: 0 | E22: 0 | F22: 0 | G22: 0 | I22: =SUM(C22:G22) -> 3918.75 | J22: =$D$8 -> 0.15 | K22: =I22/(1-J22) -> 4610.29
B23: FABRICATE CLADDING AND TRIM | C23: 0 | D23: 0 | E23: 0 | F23: 0 | G23: 0 | I23: =SUM(C23:G23) -> 0 | J23: =$D$8 -> 0.15 | K23: =I23/(1-J23) -> 0
B24: OTHER SCOPE ITEM | C24: 0 | D24: 0 | E24: 0 | F24: 0 | G24: 0 | I24: =SUM(C24:G24) -> 0 | J24: =$D$8 -> 0.15 | K24: =I24/(1-J24) -> 0
B25: OTHER SCOPE ITEM | C25: 0 | D25: 0 | E25: 0 | F25: 0 | G25: 0 | I25: =SUM(C25:G25) -> 0 | J25: =$D$8 -> 0.15 | K25: =I25/(1-J25) -> 0
B26: SUBTOTAL | I26: =SUM(I20:I25) -> 3918.75 | K26: =SUM(K20:K25) -> 4610.29
B28: Structural Labor and LED Installation | C28: Subcontractor 1 | D28: Subcontractor 2 | E28: Subcontractor 3 | F28: Selected | G28: Additional Contingency | I28: Total Cost | J28: Install Margin | K28: Selling Price
B29: REMOVAL AND DISPOSAL | C29: 0 | D29: 0 | E29: 0 | F29: 0 | G29: 0 | I29: =SUM(C29:G29) -> 0 | J29: =$D$8 -> 0.15 | K29: =I29/(1-J29) -> 0
B30: INSTALL SECONDARY STEEL SUBSTRUCTURE | C30: 0 | D30: 0 | E30: 0 | F30: 0 | G30: 0 | I30: =SUM(C30:G30) -> 0 | J30: =$D$8 -> 0.15 | K30: =I30/(1-J30) -> 0
B31: INSTALL LED DISPLAYS | C31: 16328.13 | D31: 0 | E31: 0 | F31: 0 | G31: 0 | I31: =SUM(C31:G31) -> 16328.13 | J31: =$D$8 -> 0.15 | K31: =I31/(1-J31) -> 19209.56
B32: INSTALL CLADDING AND TRIM | C32: 0 | D32: 0 | E32: 0 | F32: 0 | G32: 0 | I32: =SUM(C32:G32) -> 0 | J32: =$D$8 -> 0.15 | K32: =I32/(1-J32) -> 0
B33: HEAVY EQUIPMENT | C33: 0 | D33: 0 | E33: 0 | F33: 0 | G33: 0 | I33: =SUM(C33:G33) -> 0 | J33: =$D$8 -> 0.15 | K33: =I33/(1-J33) -> 0
B34: PM/GENERAL CONDITIONS/TRAVEL | C34: 20882.35 | D34: 0 | E34: 0 | F34: 0 | G34: 0 | I34: =SUM(C34:G34) -> 20882.35 | J34: =$D$8 -> 0.15 | K34: =I34/(1-J34) -> 24567.47
B35: SUBTOTAL | I35: =SUM(I29:I34) -> 37210.48 | K35: =SUM(K29:K34) -> 43777.04
B37: Electrical and Data - Materials and Subcontracting | C37: Subcontractor 1 | D37: Subcontractor 2 | E37: Subcontractor 3 | F37: Selected | G37: Additional Contingency | I37: Total Cost | J37: Install Margin | K37: Selling Price
B38: ELECTRICAL MATERIALS | C38: 16328.13 | D38: 0 | E38: 0 | F38: 0 | G38: 0 | I38: =SUM(C38:G38) -> 16328.13 | J38: =$D$9 -> 0.15 | K38: =I38/(1-J38) -> 19209.56
B39: DATA MATERIALS | C39: 0 | D39: 0 | E39: 0 | F39: 0 | G39: 0 | I39: =SUM(C39:G39) -> 0 | J39: =$D$9 -> 0.15 | K39: =I39/(1-J39) -> 0
B40: ELECTRICAL LABOR | C40: 0 | D40: 0 | E40: 0 | F40: 0 | G40: 0 | I40: =SUM(C40:G40) -> 0 | J40: =$D$9 -> 0.15 | K40: =I40/(1-J40) -> 0
B41: DATA LABOR | C41: 0 | D41: 0 | E41: 0 | F41: 0 | G41: 0 | I41: =SUM(C41:G41) -> 0 | J41: =$D$9 -> 0.15 | K41: =I41/(1-J41) -> 0
B42: SUB PANEL | C42: 0 | D42: 0 | E42: 0 | F42: 0 | G42: 0 | I42: =SUM(C42:G42) -> 0 | J42: =$D$9 -> 0.15 | K42: =I42/(1-J42) -> 0
B43: MISC | C43: 0 | D43: 0 | E43: 0 | F43: 0 | G43: 0 | I43: =SUM(C43:G43) -> 0 | J43: =$D$9 -> 0.15 | K43: =I43/(1-J43) -> 0
B44: SUBTOTAL | I44: =SUM(I38:I43) -> 16328.13 | K44: =SUM(K38:K43) -> 19209.56
B46: Submittals, Engineering, and Permits | C46: Subcontractor 1 | D46: Subcontractor 2 | E46: Subcontractor 3 | F46: Selected | G46: Additional Contingency | I46: Total Cost | J46: Install Margin | K46: Selling Price
B47: STRUCTURAL ENGINEERING | C47: 4705.88 | D47: 0 | E47: 0 | F47: 0 | G47: 0 | I47: =SUM(C47:G47) -> 4705.88 | J47: =$D$11 -> 0.15 | K47: =I47/(1-J47) -> 5536.33
B48: STRUCTURAL CERTIFICATION | C48: 0 | D48: 0 | E48: 0 | F48: 0 | G48: 0 | I48: =SUM(C48:G48) -> 0 | J48: =$D$11 -> 0.15 | K48: =I48/(1-J48) -> 0
B49: ELECTRICAL ENGINEERING | C49: 0 | D49: 0 | E49: 0 | F49: 0 | G49: 0 | I49: =SUM(C49:G49) -> 0 | J49: =$D$11 -> 0.15 | K49: =I49/(1-J49) -> 0
B50: ELECTRICAL CERTIFICATION | C50: 0 | D50: 0 | E50: 0 | F50: 0 | G50: 0 | I50: =SUM(C50:G50) -> 0 | J50: =$D$11 -> 0.15 | K50: =I50/(1-J50) -> 0
B51: PERMITS | C51: 0 | D51: 0 | E51: 0 | F51: 0 | G51: 0 | I51: =SUM(C51:G51) -> 0 | J51: =$D$11 -> 0.15 | K51: =I51/(1-J51) -> 0
B52: SUBTOTAL | I52: =SUM(I47:I51) -> 4705.88 | K52: =SUM(K47:K51) -> 5536.33
B54: ZONE GRAND TOTAL | I54: =I26+I35+I44+I52 -> 161230.45 | K54: =K26+K35+K44+K52 -> 185682.88

Sheet N.E Corridor17 - Install
A3: Project Name: Bank of America Stadium Modernization
A4: 2026-03-31
A5: Revised By: ANC Proposal Engine
C7: Linked Margin Assignment
C8: Install Margin | D8: 0.15
C9: Electrical Margin | D9: 0.15
C10: ANC Margin | D10: 0.15
C11: Engineering and Permits | D11: 0.15
B15: N.E Corridor
B16: Height | C16: Width | D16: Total Sq. Ft | E16: QTY
B17: 10 | C17: 34 | D17: 340 | E17: 1
B19: Structural Materials: | C19: Subcontractor 1 | D19: Subcontractor 2 | E19: Subcontractor 3 | F19: Selected | G19: Additional Contingency | I19: Total Cost | J19: Install Margin | K19: Selling Price
B20: FABRICATE PRIMARY STEEL | C20: 0 | D20: 0 | E20: 0 | F20: 0 | G20: 0 | I20: =SUM(C20:G20) -> 0 | J20: =$D$8 -> 0.15 | K20: =I20/(1-J20) -> 0
B21: SUPPLY AND INSTALL PRIMARY PLYWOOD | C21: 0 | D21: 0 | E21: 0 | F21: 0 | G21: 0 | I21: =SUM(C21:G21) -> 0 | J21: =$D$8 -> 0.15 | K21: =I21/(1-J21) -> 0
B22: FABRICATE SECONDARY STEEL SUBSTRUCTURE | C22: 3918.75 | D22: 0 | E22: 0 | F22: 0 | G22: 0 | I22: =SUM(C22:G22) -> 3918.75 | J22: =$D$8 -> 0.15 | K22: =I22/(1-J22) -> 4610.29
B23: FABRICATE CLADDING AND TRIM | C23: 0 | D23: 0 | E23: 0 | F23: 0 | G23: 0 | I23: =SUM(C23:G23) -> 0 | J23: =$D$8 -> 0.15 | K23: =I23/(1-J23) -> 0
B24: OTHER SCOPE ITEM | C24: 0 | D24: 0 | E24: 0 | F24: 0 | G24: 0 | I24: =SUM(C24:G24) -> 0 | J24: =$D$8 -> 0.15 | K24: =I24/(1-J24) -> 0
B25: OTHER SCOPE ITEM | C25: 0 | D25: 0 | E25: 0 | F25: 0 | G25: 0 | I25: =SUM(C25:G25) -> 0 | J25: =$D$8 -> 0.15 | K25: =I25/(1-J25) -> 0
B26: SUBTOTAL | I26: =SUM(I20:I25) -> 3918.75 | K26: =SUM(K20:K25) -> 4610.29
B28: Structural Labor and LED Installation | C28: Subcontractor 1 | D28: Subcontractor 2 | E28: Subcontractor 3 | F28: Selected | G28: Additional Contingency | I28: Total Cost | J28: Install Margin | K28: Selling Price
B29: REMOVAL AND DISPOSAL | C29: 0 | D29: 0 | E29: 0 | F29: 0 | G29: 0 | I29: =SUM(C29:G29) -> 0 | J29: =$D$8 -> 0.15 | K29: =I29/(1-J29) -> 0
B30: INSTALL SECONDARY STEEL SUBSTRUCTURE | C30: 0 | D30: 0 | E30: 0 | F30: 0 | G30: 0 | I30: =SUM(C30:G30) -> 0 | J30: =$D$8 -> 0.15 | K30: =I30/(1-J30) -> 0
B31: INSTALL LED DISPLAYS | C31: 16328.13 | D31: 0 | E31: 0 | F31: 0 | G31: 0 | I31: =SUM(C31:G31) -> 16328.13 | J31: =$D$8 -> 0.15 | K31: =I31/(1-J31) -> 19209.56
B32: INSTALL CLADDING AND TRIM | C32: 0 | D32: 0 | E32: 0 | F32: 0 | G32: 0 | I32: =SUM(C32:G32) -> 0 | J32: =$D$8 -> 0.15 | K32: =I32/(1-J32) -> 0
B33: HEAVY EQUIPMENT | C33: 0 | D33: 0 | E33: 0 | F33: 0 | G33: 0 | I33: =SUM(C33:G33) -> 0 | J33: =$D$8 -> 0.15 | K33: =I33/(1-J33) -> 0
B34: PM/GENERAL CONDITIONS/TRAVEL | C34: 20882.35 | D34: 0 | E34: 0 | F34: 0 | G34: 0 | I34: =SUM(C34:G34) -> 20882.35 | J34: =$D$8 -> 0.15 | K34: =I34/(1-J34) -> 24567.47
B35: SUBTOTAL | I35: =SUM(I29:I34) -> 37210.48 | K35: =SUM(K29:K34) -> 43777.04
B37: Electrical and Data - Materials and Subcontracting | C37: Subcontractor 1 | D37: Subcontractor 2 | E37: Subcontractor 3 | F37: Selected | G37: Additional Contingency | I37: Total Cost | J37: Install Margin | K37: Selling Price
B38: ELECTRICAL MATERIALS | C38: 16328.13 | D38: 0 | E38: 0 | F38: 0 | G38: 0 | I38: =SUM(C38:G38) -> 16328.13 | J38: =$D$9 -> 0.15 | K38: =I38/(1-J38) -> 19209.56
B39: DATA MATERIALS | C39: 0 | D39: 0 | E39: 0 | F39: 0 | G39: 0 | I39: =SUM(C39:G39) -> 0 | J39: =$D$9 -> 0.15 | K39: =I39/(1-J39) -> 0
B40: ELECTRICAL LABOR | C40: 0 | D40: 0 | E40: 0 | F40: 0 | G40: 0 | I40: =SUM(C40:G40) -> 0 | J40: =$D$9 -> 0.15 | K40: =I40/(1-J40) -> 0
B41: DATA LABOR | C41: 0 | D41: 0 | E41: 0 | F41: 0 | G41: 0 | I41: =SUM(C41:G41) -> 0 | J41: =$D$9 -> 0.15 | K41: =I41/(1-J41) -> 0
B42: SUB PANEL | C42: 0 | D42: 0 | E42: 0 | F42: 0 | G42: 0 | I42: =SUM(C42:G42) -> 0 | J42: =$D$9 -> 0.15 | K42: =I42/(1-J42) -> 0
B43: MISC | C43: 0 | D43: 0 | E43: 0 | F43: 0 | G43: 0 | I43: =SUM(C43:G43) -> 0 | J43: =$D$9 -> 0.15 | K43: =I43/(1-J43) -> 0
B44: SUBTOTAL | I44: =SUM(I38:I43) -> 16328.13 | K44: =SUM(K38:K43) -> 19209.56
B46: Submittals, Engineering, and Permits | C46: Subcontractor 1 | D46: Subcontractor 2 | E46: Subcontractor 3 | F46: Selected | G46: Additional Contingency | I46: Total Cost | J46: Install Margin | K46: Selling Price
B47: STRUCTURAL ENGINEERING | C47: 4705.88 | D47: 0 | E47: 0 | F47: 0 | G47: 0 | I47: =SUM(C47:G47) -> 4705.88 | J47: =$D$11 -> 0.15 | K47: =I47/(1-J47) -> 5536.33
B48: STRUCTURAL CERTIFICATION | C48: 0 | D48: 0 | E48: 0 | F48: 0 | G48: 0 | I48: =SUM(C48:G48) -> 0 | J48: =$D$11 -> 0.15 | K48: =I48/(1-J48) -> 0
B49: ELECTRICAL ENGINEERING | C49: 0 | D49: 0 | E49: 0 | F49: 0 | G49: 0 | I49: =SUM(C49:G49) -> 0 | J49: =$D$11 -> 0.15 | K49: =I49/(1-J49) -> 0
B50: ELECTRICAL CERTIFICATION | C50: 0 | D50: 0 | E50: 0 | F50: 0 | G50: 0 | I50: =SUM(C50:G50) -> 0 | J50: =$D$11 -> 0.15 | K50: =I50/(1-J50) -> 0
B51: PERMITS | C51: 0 | D51: 0 | E51: 0 | F51: 0 | G51: 0 | I51: =SUM(C51:G51) -> 0 | J51: =$D$11 -> 0.15 | K51: =I51/(1-J51) -> 0
B52: SUBTOTAL | I52: =SUM(I47:I51) -> 4705.88 | K52: =SUM(K47:K51) -> 5536.33
B54: ZONE GRAND TOTAL | I54: =I26+I35+I44+I52 -> 161230.45 | K54: =K26+K35+K44+K52 -> 185682.88

Sheet Panthers Den18 - Install
A3: Project Name: Bank of America Stadium Modernization
A4: 2026-03-31
A5: Revised By: ANC Proposal Engine
C7: Linked Margin Assignment
C8: Install Margin | D8: 0.15
C9: Electrical Margin | D9: 0.15
C10: ANC Margin | D10: 0.15
C11: Engineering and Permits | D11: 0.15
B15: Panthers Den
B16: Height | C16: Width | D16: Total Sq. Ft | E16: QTY
B17: 22 | C17: 3 | D17: 66 | E17: 1
B19: Structural Materials: | C19: Subcontractor 1 | D19: Subcontractor 2 | E19: Subcontractor 3 | F19: Selected | G19: Additional Contingency | I19: Total Cost | J19: Install Margin | K19: Selling Price
B20: FABRICATE PRIMARY STEEL | C20: 0 | D20: 0 | E20: 0 | F20: 0 | G20: 0 | I20: =SUM(C20:G20) -> 0 | J20: =$D$8 -> 0.15 | K20: =I20/(1-J20) -> 0
B21: SUPPLY AND INSTALL PRIMARY PLYWOOD | C21: 0 | D21: 0 | E21: 0 | F21: 0 | G21: 0 | I21: =SUM(C21:G21) -> 0 | J21: =$D$8 -> 0.15 | K21: =I21/(1-J21) -> 0
B22: FABRICATE SECONDARY STEEL SUBSTRUCTURE | C22: 757.5 | D22: 0 | E22: 0 | F22: 0 | G22: 0 | I22: =SUM(C22:G22) -> 757.5 | J22: =$D$8 -> 0.15 | K22: =I22/(1-J22) -> 891.18
B23: FABRICATE CLADDING AND TRIM | C23: 0 | D23: 0 | E23: 0 | F23: 0 | G23: 0 | I23: =SUM(C23:G23) -> 0 | J23: =$D$8 -> 0.15 | K23: =I23/(1-J23) -> 0
B24: OTHER SCOPE ITEM | C24: 0 | D24: 0 | E24: 0 | F24: 0 | G24: 0 | I24: =SUM(C24:G24) -> 0 | J24: =$D$8 -> 0.15 | K24: =I24/(1-J24) -> 0
B25: OTHER SCOPE ITEM | C25: 0 | D25: 0 | E25: 0 | F25: 0 | G25: 0 | I25: =SUM(C25:G25) -> 0 | J25: =$D$8 -> 0.15 | K25: =I25/(1-J25) -> 0
B26: SUBTOTAL | I26: =SUM(I20:I25) -> 757.5 | K26: =SUM(K20:K25) -> 891.18
B28: Structural Labor and LED Installation | C28: Subcontractor 1 | D28: Subcontractor 2 | E28: Subcontractor 3 | F28: Selected | G28: Additional Contingency | I28: Total Cost | J28: Install Margin | K28: Selling Price
B29: REMOVAL AND DISPOSAL | C29: 0 | D29: 0 | E29: 0 | F29: 0 | G29: 0 | I29: =SUM(C29:G29) -> 0 | J29: =$D$8 -> 0.15 | K29: =I29/(1-J29) -> 0
B30: INSTALL SECONDARY STEEL SUBSTRUCTURE | C30: 0 | D30: 0 | E30: 0 | F30: 0 | G30: 0 | I30: =SUM(C30:G30) -> 0 | J30: =$D$8 -> 0.15 | K30: =I30/(1-J30) -> 0
B31: INSTALL LED DISPLAYS | C31: 3156.25 | D31: 0 | E31: 0 | F31: 0 | G31: 0 | I31: =SUM(C31:G31) -> 3156.25 | J31: =$D$8 -> 0.15 | K31: =I31/(1-J31) -> 3713.24
B32: INSTALL CLADDING AND TRIM | C32: 0 | D32: 0 | E32: 0 | F32: 0 | G32: 0 | I32: =SUM(C32:G32) -> 0 | J32: =$D$8 -> 0.15 | K32: =I32/(1-J32) -> 0
B33: HEAVY EQUIPMENT | C33: 0 | D33: 0 | E33: 0 | F33: 0 | G33: 0 | I33: =SUM(C33:G33) -> 0 | J33: =$D$8 -> 0.15 | K33: =I33/(1-J33) -> 0
B34: PM/GENERAL CONDITIONS/TRAVEL | C34: 20882.35 | D34: 0 | E34: 0 | F34: 0 | G34: 0 | I34: =SUM(C34:G34) -> 20882.35 | J34: =$D$8 -> 0.15 | K34: =I34/(1-J34) -> 24567.47
B35: SUBTOTAL | I35: =SUM(I29:I34) -> 24038.6 | K35: =SUM(K29:K34) -> 28280.71
B37: Electrical and Data - Materials and Subcontracting | C37: Subcontractor 1 | D37: Subcontractor 2 | E37: Subcontractor 3 | F37: Selected | G37: Additional Contingency | I37: Total Cost | J37: Install Margin | K37: Selling Price
B38: ELECTRICAL MATERIALS | C38: 3156.25 | D38: 0 | E38: 0 | F38: 0 | G38: 0 | I38: =SUM(C38:G38) -> 3156.25 | J38: =$D$9 -> 0.15 | K38: =I38/(1-J38) -> 3713.24
B39: DATA MATERIALS | C39: 0 | D39: 0 | E39: 0 | F39: 0 | G39: 0 | I39: =SUM(C39:G39) -> 0 | J39: =$D$9 -> 0.15 | K39: =I39/(1-J39) -> 0
B40: ELECTRICAL LABOR | C40: 0 | D40: 0 | E40: 0 | F40: 0 | G40: 0 | I40: =SUM(C40:G40) -> 0 | J40: =$D$9 -> 0.15 | K40: =I40/(1-J40) -> 0
B41: DATA LABOR | C41: 0 | D41: 0 | E41: 0 | F41: 0 | G41: 0 | I41: =SUM(C41:G41) -> 0 | J41: =$D$9 -> 0.15 | K41: =I41/(1-J41) -> 0
B42: SUB PANEL | C42: 0 | D42: 0 | E42: 0 | F42: 0 | G42: 0 | I42: =SUM(C42:G42) -> 0 | J42: =$D$9 -> 0.15 | K42: =I42/(1-J42) -> 0
B43: MISC | C43: 0 | D43: 0 | E43: 0 | F43: 0 | G43: 0 | I43: =SUM(C43:G43) -> 0 | J43: =$D$9 -> 0.15 | K43: =I43/(1-J43) -> 0
B44: SUBTOTAL | I44: =SUM(I38:I43) -> 3156.25 | K44: =SUM(K38:K43) -> 3713.24
B46: Submittals, Engineering, and Permits | C46: Subcontractor 1 | D46: Subcontractor 2 | E46: Subcontractor 3 | F46: Selected | G46: Additional Contingency | I46: Total Cost | J46: Install Margin | K46: Selling Price
B47: STRUCTURAL ENGINEERING | C47: 4705.88 | D47: 0 | E47: 0 | F47: 0 | G47: 0 | I47: =SUM(C47:G47) -> 4705.88 | J47: =$D$11 -> 0.15 | K47: =I47/(1-J47) -> 5536.33
B48: STRUCTURAL CERTIFICATION | C48: 0 | D48: 0 | E48: 0 | F48: 0 | G48: 0 | I48: =SUM(C48:G48) -> 0 | J48: =$D$11 -> 0.15 | K48: =I48/(1-J48) -> 0
B49: ELECTRICAL ENGINEERING | C49: 0 | D49: 0 | E49: 0 | F49: 0 | G49: 0 | I49: =SUM(C49:G49) -> 0 | J49: =$D$11 -> 0.15 | K49: =I49/(1-J49) -> 0
B50: ELECTRICAL CERTIFICATION | C50: 0 | D50: 0 | E50: 0 | F50: 0 | G50: 0 | I50: =SUM(C50:G50) -> 0 | J50: =$D$11 -> 0.15 | K50: =I50/(1-J50) -> 0
B51: PERMITS | C51: 0 | D51: 0 | E51: 0 | F51: 0 | G51: 0 | I51: =SUM(C51:G51) -> 0 | J51: =$D$11 -> 0.15 | K51: =I51/(1-J51) -> 0
B52: SUBTOTAL | I52: =SUM(I47:I51) -> 4705.88 | K52: =SUM(K47:K51) -> 5536.33
B54: ZONE GRAND TOTAL | I54: =I26+I35+I44+I52 -> 49922.16 | K54: =K26+K35+K44+K52 -> 57955.49

Sheet Panthers Den19 - Install
A3: Project Name: Bank of America Stadium Modernization
A4: 2026-03-31
A5: Revised By: ANC Proposal Engine
C7: Linked Margin Assignment
C8: Install Margin | D8: 0.15
C9: Electrical Margin | D9: 0.15
C10: ANC Margin | D10: 0.15
C11: Engineering and Permits | D11: 0.15
B15: Panthers Den
B16: Height | C16: Width | D16: Total Sq. Ft | E16: QTY
B17: 8 | C17: 29 | D17: 232 | E17: 1
B19: Structural Materials: | C19: Subcontractor 1 | D19: Subcontractor 2 | E19: Subcontractor 3 | F19: Selected | G19: Additional Contingency | I19: Total Cost | J19: Install Margin | K19: Selling Price
B20: FABRICATE PRIMARY STEEL | C20: 0 | D20: 0 | E20: 0 | F20: 0 | G20: 0 | I20: =SUM(C20:G20) -> 0 | J20: =$D$8 -> 0.15 | K20: =I20/(1-J20) -> 0
B21: SUPPLY AND INSTALL PRIMARY PLYWOOD | C21: 0 | D21: 0 | E21: 0 | F21: 0 | G21: 0 | I21: =SUM(C21:G21) -> 0 | J21: =$D$8 -> 0.15 | K21: =I21/(1-J21) -> 0
B22: FABRICATE SECONDARY STEEL SUBSTRUCTURE | C22: 2670 | D22: 0 | E22: 0 | F22: 0 | G22: 0 | I22: =SUM(C22:G22) -> 2670 | J22: =$D$8 -> 0.15 | K22: =I22/(1-J22) -> 3141.18
B23: FABRICATE CLADDING AND TRIM | C23: 0 | D23: 0 | E23: 0 | F23: 0 | G23: 0 | I23: =SUM(C23:G23) -> 0 | J23: =$D$8 -> 0.15 | K23: =I23/(1-J23) -> 0
B24: OTHER SCOPE ITEM | C24: 0 | D24: 0 | E24: 0 | F24: 0 | G24: 0 | I24: =SUM(C24:G24) -> 0 | J24: =$D$8 -> 0.15 | K24: =I24/(1-J24) -> 0
B25: OTHER SCOPE ITEM | C25: 0 | D25: 0 | E25: 0 | F25: 0 | G25: 0 | I25: =SUM(C25:G25) -> 0 | J25: =$D$8 -> 0.15 | K25: =I25/(1-J25) -> 0
B26: SUBTOTAL | I26: =SUM(I20:I25) -> 2670 | K26: =SUM(K20:K25) -> 3141.18
B28: Structural Labor and LED Installation | C28: Subcontractor 1 | D28: Subcontractor 2 | E28: Subcontractor 3 | F28: Selected | G28: Additional Contingency | I28: Total Cost | J28: Install Margin | K28: Selling Price
B29: REMOVAL AND DISPOSAL | C29: 0 | D29: 0 | E29: 0 | F29: 0 | G29: 0 | I29: =SUM(C29:G29) -> 0 | J29: =$D$8 -> 0.15 | K29: =I29/(1-J29) -> 0
B30: INSTALL SECONDARY STEEL SUBSTRUCTURE | C30: 0 | D30: 0 | E30: 0 | F30: 0 | G30: 0 | I30: =SUM(C30:G30) -> 0 | J30: =$D$8 -> 0.15 | K30: =I30/(1-J30) -> 0
B31: INSTALL LED DISPLAYS | C31: 11125 | D31: 0 | E31: 0 | F31: 0 | G31: 0 | I31: =SUM(C31:G31) -> 11125 | J31: =$D$8 -> 0.15 | K31: =I31/(1-J31) -> 13088.24
B32: INSTALL CLADDING AND TRIM | C32: 0 | D32: 0 | E32: 0 | F32: 0 | G32: 0 | I32: =SUM(C32:G32) -> 0 | J32: =$D$8 -> 0.15 | K32: =I32/(1-J32) -> 0
B33: HEAVY EQUIPMENT | C33: 0 | D33: 0 | E33: 0 | F33: 0 | G33: 0 | I33: =SUM(C33:G33) -> 0 | J33: =$D$8 -> 0.15 | K33: =I33/(1-J33) -> 0
B34: PM/GENERAL CONDITIONS/TRAVEL | C34: 20882.35 | D34: 0 | E34: 0 | F34: 0 | G34: 0 | I34: =SUM(C34:G34) -> 20882.35 | J34: =$D$8 -> 0.15 | K34: =I34/(1-J34) -> 24567.47
B35: SUBTOTAL | I35: =SUM(I29:I34) -> 32007.35 | K35: =SUM(K29:K34) -> 37655.71
B37: Electrical and Data - Materials and Subcontracting | C37: Subcontractor 1 | D37: Subcontractor 2 | E37: Subcontractor 3 | F37: Selected | G37: Additional Contingency | I37: Total Cost | J37: Install Margin | K37: Selling Price
B38: ELECTRICAL MATERIALS | C38: 11125 | D38: 0 | E38: 0 | F38: 0 | G38: 0 | I38: =SUM(C38:G38) -> 11125 | J38: =$D$9 -> 0.15 | K38: =I38/(1-J38) -> 13088.24
B39: DATA MATERIALS | C39: 0 | D39: 0 | E39: 0 | F39: 0 | G39: 0 | I39: =SUM(C39:G39) -> 0 | J39: =$D$9 -> 0.15 | K39: =I39/(1-J39) -> 0
B40: ELECTRICAL LABOR | C40: 0 | D40: 0 | E40: 0 | F40: 0 | G40: 0 | I40: =SUM(C40:G40) -> 0 | J40: =$D$9 -> 0.15 | K40: =I40/(1-J40) -> 0
B41: DATA LABOR | C41: 0 | D41: 0 | E41: 0 | F41: 0 | G41: 0 | I41: =SUM(C41:G41) -> 0 | J41: =$D$9 -> 0.15 | K41: =I41/(1-J41) -> 0
B42: SUB PANEL | C42: 0 | D42: 0 | E42: 0 | F42: 0 | G42: 0 | I42: =SUM(C42:G42) -> 0 | J42: =$D$9 -> 0.15 | K42: =I42/(1-J42) -> 0
B43: MISC | C43: 0 | D43: 0 | E43: 0 | F43: 0 | G43: 0 | I43: =SUM(C43:G43) -> 0 | J43: =$D$9 -> 0.15 | K43: =I43/(1-J43) -> 0
B44: SUBTOTAL | I44: =SUM(I38:I43) -> 11125 | K44: =SUM(K38:K43) -> 13088.24
B46: Submittals, Engineering, and Permits | C46: Subcontractor 1 | D46: Subcontractor 2 | E46: Subcontractor 3 | F46: Selected | G46: Additional Contingency | I46: Total Cost | J46: Install Margin | K46: Selling Price
B47: STRUCTURAL ENGINEERING | C47: 4705.88 | D47: 0 | E47: 0 | F47: 0 | G47: 0 | I47: =SUM(C47:G47) -> 4705.88 | J47: =$D$11 -> 0.15 | K47: =I47/(1-J47) -> 5536.33
B48: STRUCTURAL CERTIFICATION | C48: 0 | D48: 0 | E48: 0 | F48: 0 | G48: 0 | I48: =SUM(C48:G48) -> 0 | J48: =$D$11 -> 0.15 | K48: =I48/(1-J48) -> 0
B49: ELECTRICAL ENGINEERING | C49: 0 | D49: 0 | E49: 0 | F49: 0 | G49: 0 | I49: =SUM(C49:G49) -> 0 | J49: =$D$11 -> 0.15 | K49: =I49/(1-J49) -> 0
B50: ELECTRICAL CERTIFICATION | C50: 0 | D50: 0 | E50: 0 | F50: 0 | G50: 0 | I50: =SUM(C50:G50) -> 0 | J50: =$D$11 -> 0.15 | K50: =I50/(1-J50) -> 0
B51: PERMITS | C51: 0 | D51: 0 | E51: 0 | F51: 0 | G51: 0 | I51: =SUM(C51:G51) -> 0 | J51: =$D$11 -> 0.15 | K51: =I51/(1-J51) -> 0
B52: SUBTOTAL | I52: =SUM(I47:I51) -> 4705.88 | K52: =SUM(K47:K51) -> 5536.33
B54: ZONE GRAND TOTAL | I54: =I26+I35+I44+I52 -> 110061.74 | K54: =K26+K35+K44+K52 -> 126754.99

Sheet Panthers Den20 - Install
A3: Project Name: Bank of America Stadium Modernization
A4: 2026-03-31
A5: Revised By: ANC Proposal Engine
C7: Linked Margin Assignment
C8: Install Margin | D8: 0.15
C9: Electrical Margin | D9: 0.15
C10: ANC Margin | D10: 0.15
C11: Engineering and Permits | D11: 0.15
B15: Panthers Den
B16: Height | C16: Width | D16: Total Sq. Ft | E16: QTY
B17: 4.0833 | C17: 37.25 | D17: 152.1 | E17: 1
B19: Structural Materials: | C19: Subcontractor 1 | D19: Subcontractor 2 | E19: Subcontractor 3 | F19: Selected | G19: Additional Contingency | I19: Total Cost | J19: Install Margin | K19: Selling Price
B20: FABRICATE PRIMARY STEEL | C20: 0 | D20: 0 | E20: 0 | F20: 0 | G20: 0 | I20: =SUM(C20:G20) -> 0 | J20: =$D$8 -> 0.15 | K20: =I20/(1-J20) -> 0
B21: SUPPLY AND INSTALL PRIMARY PLYWOOD | C21: 0 | D21: 0 | E21: 0 | F21: 0 | G21: 0 | I21: =SUM(C21:G21) -> 0 | J21: =$D$8 -> 0.15 | K21: =I21/(1-J21) -> 0
B22: FABRICATE SECONDARY STEEL SUBSTRUCTURE | C22: 1751.25 | D22: 0 | E22: 0 | F22: 0 | G22: 0 | I22: =SUM(C22:G22) -> 1751.25 | J22: =$D$8 -> 0.15 | K22: =I22/(1-J22) -> 2060.29
B23: FABRICATE CLADDING AND TRIM | C23: 0 | D23: 0 | E23: 0 | F23: 0 | G23: 0 | I23: =SUM(C23:G23) -> 0 | J23: =$D$8 -> 0.15 | K23: =I23/(1-J23) -> 0
B24: OTHER SCOPE ITEM | C24: 0 | D24: 0 | E24: 0 | F24: 0 | G24: 0 | I24: =SUM(C24:G24) -> 0 | J24: =$D$8 -> 0.15 | K24: =I24/(1-J24) -> 0
B25: OTHER SCOPE ITEM | C25: 0 | D25: 0 | E25: 0 | F25: 0 | G25: 0 | I25: =SUM(C25:G25) -> 0 | J25: =$D$8 -> 0.15 | K25: =I25/(1-J25) -> 0
B26: SUBTOTAL | I26: =SUM(I20:I25) -> 1751.25 | K26: =SUM(K20:K25) -> 2060.29
B28: Structural Labor and LED Installation | C28: Subcontractor 1 | D28: Subcontractor 2 | E28: Subcontractor 3 | F28: Selected | G28: Additional Contingency | I28: Total Cost | J28: Install Margin | K28: Selling Price
B29: REMOVAL AND DISPOSAL | C29: 0 | D29: 0 | E29: 0 | F29: 0 | G29: 0 | I29: =SUM(C29:G29) -> 0 | J29: =$D$8 -> 0.15 | K29: =I29/(1-J29) -> 0
B30: INSTALL SECONDARY STEEL SUBSTRUCTURE | C30: 0 | D30: 0 | E30: 0 | F30: 0 | G30: 0 | I30: =SUM(C30:G30) -> 0 | J30: =$D$8 -> 0.15 | K30: =I30/(1-J30) -> 0
B31: INSTALL LED DISPLAYS | C31: 7296.88 | D31: 0 | E31: 0 | F31: 0 | G31: 0 | I31: =SUM(C31:G31) -> 7296.88 | J31: =$D$8 -> 0.15 | K31: =I31/(1-J31) -> 8584.56
B32: INSTALL CLADDING AND TRIM | C32: 0 | D32: 0 | E32: 0 | F32: 0 | G32: 0 | I32: =SUM(C32:G32) -> 0 | J32: =$D$8 -> 0.15 | K32: =I32/(1-J32) -> 0
B33: HEAVY EQUIPMENT | C33: 0 | D33: 0 | E33: 0 | F33: 0 | G33: 0 | I33: =SUM(C33:G33) -> 0 | J33: =$D$8 -> 0.15 | K33: =I33/(1-J33) -> 0
B34: PM/GENERAL CONDITIONS/TRAVEL | C34: 20882.35 | D34: 0 | E34: 0 | F34: 0 | G34: 0 | I34: =SUM(C34:G34) -> 20882.35 | J34: =$D$8 -> 0.15 | K34: =I34/(1-J34) -> 24567.47
B35: SUBTOTAL | I35: =SUM(I29:I34) -> 28179.23 | K35: =SUM(K29:K34) -> 33152.04
B37: Electrical and Data - Materials and Subcontracting | C37: Subcontractor 1 | D37: Subcontractor 2 | E37: Subcontractor 3 | F37: Selected | G37: Additional Contingency | I37: Total Cost | J37: Install Margin | K37: Selling Price
B38: ELECTRICAL MATERIALS | C38: 7296.88 | D38: 0 | E38: 0 | F38: 0 | G38: 0 | I38: =SUM(C38:G38) -> 7296.88 | J38: =$D$9 -> 0.15 | K38: =I38/(1-J38) -> 8584.56
B39: DATA MATERIALS | C39: 0 | D39: 0 | E39: 0 | F39: 0 | G39: 0 | I39: =SUM(C39:G39) -> 0 | J39: =$D$9 -> 0.15 | K39: =I39/(1-J39) -> 0
B40: ELECTRICAL LABOR | C40: 0 | D40: 0 | E40: 0 | F40: 0 | G40: 0 | I40: =SUM(C40:G40) -> 0 | J40: =$D$9 -> 0.15 | K40: =I40/(1-J40) -> 0
B41: DATA LABOR | C41: 0 | D41: 0 | E41: 0 | F41: 0 | G41: 0 | I41: =SUM(C41:G41) -> 0 | J41: =$D$9 -> 0.15 | K41: =I41/(1-J41) -> 0
B42: SUB PANEL | C42: 0 | D42: 0 | E42: 0 | F42: 0 | G42: 0 | I42: =SUM(C42:G42) -> 0 | J42: =$D$9 -> 0.15 | K42: =I42/(1-J42) -> 0
B43: MISC | C43: 0 | D43: 0 | E43: 0 | F43: 0 | G43: 0 | I43: =SUM(C43:G43) -> 0 | J43: =$D$9 -> 0.15 | K43: =I43/(1-J43) -> 0
B44: SUBTOTAL | I44: =SUM(I38:I43) -> 7296.88 | K44: =SUM(K38:K43) -> 8584.56
B46: Submittals, Engineering, and Permits | C46: Subcontractor 1 | D46: Subcontractor 2 | E46: Subcontractor 3 | F46: Selected | G46: Additional Contingency | I46: Total Cost | J46: Install Margin | K46: Selling Price
B47: STRUCTURAL ENGINEERING | C47: 4705.88 | D47: 0 | E47: 0 | F47: 0 | G47: 0 | I47: =SUM(C47:G47) -> 4705.88 | J47: =$D$11 -> 0.15 | K47: =I47/(1-J47) -> 5536.33
B48: STRUCTURAL CERTIFICATION | C48: 0 | D48: 0 | E48: 0 | F48: 0 | G48: 0 | I48: =SUM(C48:G48) -> 0 | J48: =$D$11 -> 0.15 | K48: =I48/(1-J48) -> 0
B49: ELECTRICAL ENGINEERING | C49: 0 | D49: 0 | E49: 0 | F49: 0 | G49: 0 | I49: =SUM(C49:G49) -> 0 | J49: =$D$11 -> 0.15 | K49: =I49/(1-J49) -> 0
B50: ELECTRICAL CERTIFICATION | C50: 0 | D50: 0 | E50: 0 | F50: 0 | G50: 0 | I50: =SUM(C50:G50) -> 0 | J50: =$D$11 -> 0.15 | K50: =I50/(1-J50) -> 0
B51: PERMITS | C51: 0 | D51: 0 | E51: 0 | F51: 0 | G51: 0 | I51: =SUM(C51:G51) -> 0 | J51: =$D$11 -> 0.15 | K51: =I51/(1-J51) -> 0
B52: SUBTOTAL | I52: =SUM(I47:I51) -> 4705.88 | K52: =SUM(K47:K51) -> 5536.33
B54: ZONE GRAND TOTAL | I54: =I26+I35+I44+I52 -> 81131.7 | K54: =K26+K35+K44+K52 -> 93659.65

Sheet Elev Lobby21 - Install
A3: Project Name: Bank of America Stadium Modernization
A4: 2026-03-31
A5: Revised By: ANC Proposal Engine
C7: Linked Margin Assignment
C8: Install Margin | D8: 0.15
C9: Electrical Margin | D9: 0.15
C10: ANC Margin | D10: 0.15
C11: Engineering and Permits | D11: 0.15
B15: Elev Lobby
B16: Height | C16: Width | D16: Total Sq. Ft | E16: QTY
B17: 4 | C17: 6 | D17: 24 | E17: 1
B19: Structural Materials: | C19: Subcontractor 1 | D19: Subcontractor 2 | E19: Subcontractor 3 | F19: Selected | G19: Additional Contingency | I19: Total Cost | J19: Install Margin | K19: Selling Price
B20: FABRICATE PRIMARY STEEL | C20: 0 | D20: 0 | E20: 0 | F20: 0 | G20: 0 | I20: =SUM(C20:G20) -> 0 | J20: =$D$8 -> 0.15 | K20: =I20/(1-J20) -> 0
B21: SUPPLY AND INSTALL PRIMARY PLYWOOD | C21: 0 | D21: 0 | E21: 0 | F21: 0 | G21: 0 | I21: =SUM(C21:G21) -> 0 | J21: =$D$8 -> 0.15 | K21: =I21/(1-J21) -> 0
B22: FABRICATE SECONDARY STEEL SUBSTRUCTURE | C22: 277.5 | D22: 0 | E22: 0 | F22: 0 | G22: 0 | I22: =SUM(C22:G22) -> 277.5 | J22: =$D$8 -> 0.15 | K22: =I22/(1-J22) -> 326.47
B23: FABRICATE CLADDING AND TRIM | C23: 0 | D23: 0 | E23: 0 | F23: 0 | G23: 0 | I23: =SUM(C23:G23) -> 0 | J23: =$D$8 -> 0.15 | K23: =I23/(1-J23) -> 0
B24: OTHER SCOPE ITEM | C24: 0 | D24: 0 | E24: 0 | F24: 0 | G24: 0 | I24: =SUM(C24:G24) -> 0 | J24: =$D$8 -> 0.15 | K24: =I24/(1-J24) -> 0
B25: OTHER SCOPE ITEM | C25: 0 | D25: 0 | E25: 0 | F25: 0 | G25: 0 | I25: =SUM(C25:G25) -> 0 | J25: =$D$8 -> 0.15 | K25: =I25/(1-J25) -> 0
B26: SUBTOTAL | I26: =SUM(I20:I25) -> 277.5 | K26: =SUM(K20:K25) -> 326.47
B28: Structural Labor and LED Installation | C28: Subcontractor 1 | D28: Subcontractor 2 | E28: Subcontractor 3 | F28: Selected | G28: Additional Contingency | I28: Total Cost | J28: Install Margin | K28: Selling Price
B29: REMOVAL AND DISPOSAL | C29: 0 | D29: 0 | E29: 0 | F29: 0 | G29: 0 | I29: =SUM(C29:G29) -> 0 | J29: =$D$8 -> 0.15 | K29: =I29/(1-J29) -> 0
B30: INSTALL SECONDARY STEEL SUBSTRUCTURE | C30: 0 | D30: 0 | E30: 0 | F30: 0 | G30: 0 | I30: =SUM(C30:G30) -> 0 | J30: =$D$8 -> 0.15 | K30: =I30/(1-J30) -> 0
B31: INSTALL LED DISPLAYS | C31: 1156.25 | D31: 0 | E31: 0 | F31: 0 | G31: 0 | I31: =SUM(C31:G31) -> 1156.25 | J31: =$D$8 -> 0.15 | K31: =I31/(1-J31) -> 1360.29
B32: INSTALL CLADDING AND TRIM | C32: 0 | D32: 0 | E32: 0 | F32: 0 | G32: 0 | I32: =SUM(C32:G32) -> 0 | J32: =$D$8 -> 0.15 | K32: =I32/(1-J32) -> 0
B33: HEAVY EQUIPMENT | C33: 0 | D33: 0 | E33: 0 | F33: 0 | G33: 0 | I33: =SUM(C33:G33) -> 0 | J33: =$D$8 -> 0.15 | K33: =I33/(1-J33) -> 0
B34: PM/GENERAL CONDITIONS/TRAVEL | C34: 20882.35 | D34: 0 | E34: 0 | F34: 0 | G34: 0 | I34: =SUM(C34:G34) -> 20882.35 | J34: =$D$8 -> 0.15 | K34: =I34/(1-J34) -> 24567.47
B35: SUBTOTAL | I35: =SUM(I29:I34) -> 22038.6 | K35: =SUM(K29:K34) -> 25927.76
B37: Electrical and Data - Materials and Subcontracting | C37: Subcontractor 1 | D37: Subcontractor 2 | E37: Subcontractor 3 | F37: Selected | G37: Additional Contingency | I37: Total Cost | J37: Install Margin | K37: Selling Price
B38: ELECTRICAL MATERIALS | C38: 1156.25 | D38: 0 | E38: 0 | F38: 0 | G38: 0 | I38: =SUM(C38:G38) -> 1156.25 | J38: =$D$9 -> 0.15 | K38: =I38/(1-J38) -> 1360.29
B39: DATA MATERIALS | C39: 0 | D39: 0 | E39: 0 | F39: 0 | G39: 0 | I39: =SUM(C39:G39) -> 0 | J39: =$D$9 -> 0.15 | K39: =I39/(1-J39) -> 0
B40: ELECTRICAL LABOR | C40: 0 | D40: 0 | E40: 0 | F40: 0 | G40: 0 | I40: =SUM(C40:G40) -> 0 | J40: =$D$9 -> 0.15 | K40: =I40/(1-J40) -> 0
B41: DATA LABOR | C41: 0 | D41: 0 | E41: 0 | F41: 0 | G41: 0 | I41: =SUM(C41:G41) -> 0 | J41: =$D$9 -> 0.15 | K41: =I41/(1-J41) -> 0
B42: SUB PANEL | C42: 0 | D42: 0 | E42: 0 | F42: 0 | G42: 0 | I42: =SUM(C42:G42) -> 0 | J42: =$D$9 -> 0.15 | K42: =I42/(1-J42) -> 0
B43: MISC | C43: 0 | D43: 0 | E43: 0 | F43: 0 | G43: 0 | I43: =SUM(C43:G43) -> 0 | J43: =$D$9 -> 0.15 | K43: =I43/(1-J43) -> 0
B44: SUBTOTAL | I44: =SUM(I38:I43) -> 1156.25 | K44: =SUM(K38:K43) -> 1360.29
B46: Submittals, Engineering, and Permits | C46: Subcontractor 1 | D46: Subcontractor 2 | E46: Subcontractor 3 | F46: Selected | G46: Additional Contingency | I46: Total Cost | J46: Install Margin | K46: Selling Price
B47: STRUCTURAL ENGINEERING | C47: 4705.88 | D47: 0 | E47: 0 | F47: 0 | G47: 0 | I47: =SUM(C47:G47) -> 4705.88 | J47: =$D$11 -> 0.15 | K47: =I47/(1-J47) -> 5536.33
B48: STRUCTURAL CERTIFICATION | C48: 0 | D48: 0 | E48: 0 | F48: 0 | G48: 0 | I48: =SUM(C48:G48) -> 0 | J48: =$D$11 -> 0.15 | K48: =I48/(1-J48) -> 0
B49: ELECTRICAL ENGINEERING | C49: 0 | D49: 0 | E49: 0 | F49: 0 | G49: 0 | I49: =SUM(C49:G49) -> 0 | J49: =$D$11 -> 0.15 | K49: =I49/(1-J49) -> 0
B50: ELECTRICAL CERTIFICATION | C50: 0 | D50: 0 | E50: 0 | F50: 0 | G50: 0 | I50: =SUM(C50:G50) -> 0 | J50: =$D$11 -> 0.15 | K50: =I50/(1-J50) -> 0
B51: PERMITS | C51: 0 | D51: 0 | E51: 0 | F51: 0 | G51: 0 | I51: =SUM(C51:G51) -> 0 | J51: =$D$11 -> 0.15 | K51: =I51/(1-J51) -> 0
B52: SUBTOTAL | I52: =SUM(I47:I51) -> 4705.88 | K52: =SUM(K47:K51) -> 5536.33
B54: ZONE GRAND TOTAL | I54: =I26+I35+I44+I52 -> 35002.39 | K54: =K26+K35+K44+K52 -> 40591.05

Sheet Elev Lobby22 - Install
A3: Project Name: Bank of America Stadium Modernization
A4: 2026-03-31
A5: Revised By: ANC Proposal Engine
C7: Linked Margin Assignment
C8: Install Margin | D8: 0.15
C9: Electrical Margin | D9: 0.15
C10: ANC Margin | D10: 0.15
C11: Engineering and Permits | D11: 0.15
B15: Elev Lobby
B16: Height | C16: Width | D16: Total Sq. Ft | E16: QTY
B17: 4 | C17: 6 | D17: 24 | E17: 1
B19: Structural Materials: | C19: Subcontractor 1 | D19: Subcontractor 2 | E19: Subcontractor 3 | F19: Selected | G19: Additional Contingency | I19: Total Cost | J19: Install Margin | K19: Selling Price
B20: FABRICATE PRIMARY STEEL | C20: 0 | D20: 0 | E20: 0 | F20: 0 | G20: 0 | I20: =SUM(C20:G20) -> 0 | J20: =$D$8 -> 0.15 | K20: =I20/(1-J20) -> 0
B21: SUPPLY AND INSTALL PRIMARY PLYWOOD | C21: 0 | D21: 0 | E21: 0 | F21: 0 | G21: 0 | I21: =SUM(C21:G21) -> 0 | J21: =$D$8 -> 0.15 | K21: =I21/(1-J21) -> 0
B22: FABRICATE SECONDARY STEEL SUBSTRUCTURE | C22: 277.5 | D22: 0 | E22: 0 | F22: 0 | G22: 0 | I22: =SUM(C22:G22) -> 277.5 | J22: =$D$8 -> 0.15 | K22: =I22/(1-J22) -> 326.47
B23: FABRICATE CLADDING AND TRIM | C23: 0 | D23: 0 | E23: 0 | F23: 0 | G23: 0 | I23: =SUM(C23:G23) -> 0 | J23: =$D$8 -> 0.15 | K23: =I23/(1-J23) -> 0
B24: OTHER SCOPE ITEM | C24: 0 | D24: 0 | E24: 0 | F24: 0 | G24: 0 | I24: =SUM(C24:G24) -> 0 | J24: =$D$8 -> 0.15 | K24: =I24/(1-J24) -> 0
B25: OTHER SCOPE ITEM | C25: 0 | D25: 0 | E25: 0 | F25: 0 | G25: 0 | I25: =SUM(C25:G25) -> 0 | J25: =$D$8 -> 0.15 | K25: =I25/(1-J25) -> 0
B26: SUBTOTAL | I26: =SUM(I20:I25) -> 277.5 | K26: =SUM(K20:K25) -> 326.47
B28: Structural Labor and LED Installation | C28: Subcontractor 1 | D28: Subcontractor 2 | E28: Subcontractor 3 | F28: Selected | G28: Additional Contingency | I28: Total Cost | J28: Install Margin | K28: Selling Price
B29: REMOVAL AND DISPOSAL | C29: 0 | D29: 0 | E29: 0 | F29: 0 | G29: 0 | I29: =SUM(C29:G29) -> 0 | J29: =$D$8 -> 0.15 | K29: =I29/(1-J29) -> 0
B30: INSTALL SECONDARY STEEL SUBSTRUCTURE | C30: 0 | D30: 0 | E30: 0 | F30: 0 | G30: 0 | I30: =SUM(C30:G30) -> 0 | J30: =$D$8 -> 0.15 | K30: =I30/(1-J30) -> 0
B31: INSTALL LED DISPLAYS | C31: 1156.25 | D31: 0 | E31: 0 | F31: 0 | G31: 0 | I31: =SUM(C31:G31) -> 1156.25 | J31: =$D$8 -> 0.15 | K31: =I31/(1-J31) -> 1360.29
B32: INSTALL CLADDING AND TRIM | C32: 0 | D32: 0 | E32: 0 | F32: 0 | G32: 0 | I32: =SUM(C32:G32) -> 0 | J32: =$D$8 -> 0.15 | K32: =I32/(1-J32) -> 0
B33: HEAVY EQUIPMENT | C33: 0 | D33: 0 | E33: 0 | F33: 0 | G33: 0 | I33: =SUM(C33:G33) -> 0 | J33: =$D$8 -> 0.15 | K33: =I33/(1-J33) -> 0
B34: PM/GENERAL CONDITIONS/TRAVEL | C34: 20882.35 | D34: 0 | E34: 0 | F34: 0 | G34: 0 | I34: =SUM(C34:G34) -> 20882.35 | J34: =$D$8 -> 0.15 | K34: =I34/(1-J34) -> 24567.47
B35: SUBTOTAL | I35: =SUM(I29:I34) -> 22038.6 | K35: =SUM(K29:K34) -> 25927.76
B37: Electrical and Data - Materials and Subcontracting | C37: Subcontractor 1 | D37: Subcontractor 2 | E37: Subcontractor 3 | F37: Selected | G37: Additional Contingency | I37: Total Cost | J37: Install Margin | K37: Selling Price
B38: ELECTRICAL MATERIALS | C38: 1156.25 | D38: 0 | E38: 0 | F38: 0 | G38: 0 | I38: =SUM(C38:G38) -> 1156.25 | J38: =$D$9 -> 0.15 | K38: =I38/(1-J38) -> 1360.29
B39: DATA MATERIALS | C39: 0 | D39: 0 | E39: 0 | F39: 0 | G39: 0 | I39: =SUM(C39:G39) -> 0 | J39: =$D$9 -> 0.15 | K39: =I39/(1-J39) -> 0
B40: ELECTRICAL LABOR | C40: 0 | D40: 0 | E40: 0 | F40: 0 | G40: 0 | I40: =SUM(C40:G40) -> 0 | J40: =$D$9 -> 0.15 | K40: =I40/(1-J40) -> 0
B41: DATA LABOR | C41: 0 | D41: 0 | E41: 0 | F41: 0 | G41: 0 | I41: =SUM(C41:G41) -> 0 | J41: =$D$9 -> 0.15 | K41: =I41/(1-J41) -> 0
B42: SUB PANEL | C42: 0 | D42: 0 | E42: 0 | F42: 0 | G42: 0 | I42: =SUM(C42:G42) -> 0 | J42: =$D$9 -> 0.15 | K42: =I42/(1-J42) -> 0
B43: MISC | C43: 0 | D43: 0 | E43: 0 | F43: 0 | G43: 0 | I43: =SUM(C43:G43) -> 0 | J43: =$D$9 -> 0.15 | K43: =I43/(1-J43) -> 0
B44: SUBTOTAL | I44: =SUM(I38:I43) -> 1156.25 | K44: =SUM(K38:K43) -> 1360.29
B46: Submittals, Engineering, and Permits | C46: Subcontractor 1 | D46: Subcontractor 2 | E46: Subcontractor 3 | F46: Selected | G46: Additional Contingency | I46: Total Cost | J46: Install Margin | K46: Selling Price
B47: STRUCTURAL ENGINEERING | C47: 4705.88 | D47: 0 | E47: 0 | F47: 0 | G47: 0 | I47: =SUM(C47:G47) -> 4705.88 | J47: =$D$11 -> 0.15 | K47: =I47/(1-J47) -> 5536.33
B48: STRUCTURAL CERTIFICATION | C48: 0 | D48: 0 | E48: 0 | F48: 0 | G48: 0 | I48: =SUM(C48:G48) -> 0 | J48: =$D$11 -> 0.15 | K48: =I48/(1-J48) -> 0
B49: ELECTRICAL ENGINEERING | C49: 0 | D49: 0 | E49: 0 | F49: 0 | G49: 0 | I49: =SUM(C49:G49) -> 0 | J49: =$D$11 -> 0.15 | K49: =I49/(1-J49) -> 0
B50: ELECTRICAL CERTIFICATION | C50: 0 | D50: 0 | E50: 0 | F50: 0 | G50: 0 | I50: =SUM(C50:G50) -> 0 | J50: =$D$11 -> 0.15 | K50: =I50/(1-J50) -> 0
B51: PERMITS | C51: 0 | D51: 0 | E51: 0 | F51: 0 | G51: 0 | I51: =SUM(C51:G51) -> 0 | J51: =$D$11 -> 0.15 | K51: =I51/(1-J51) -> 0
B52: SUBTOTAL | I52: =SUM(I47:I51) -> 4705.88 | K52: =SUM(K47:K51) -> 5536.33
B54: ZONE GRAND TOTAL | I54: =I26+I35+I44+I52 -> 35002.39 | K54: =K26+K35+K44+K52 -> 40591.05

Sheet Elev Lobby23 - Install
A3: Project Name: Bank of America Stadium Modernization
A4: 2026-03-31
A5: Revised By: ANC Proposal Engine
C7: Linked Margin Assignment
C8: Install Margin | D8: 0.15
C9: Electrical Margin | D9: 0.15
C10: ANC Margin | D10: 0.15
C11: Engineering and Permits | D11: 0.15
B15: Elev Lobby
B16: Height | C16: Width | D16: Total Sq. Ft | E16: QTY
B17: 4 | C17: 6 | D17: 24 | E17: 1
B19: Structural Materials: | C19: Subcontractor 1 | D19: Subcontractor 2 | E19: Subcontractor 3 | F19: Selected | G19: Additional Contingency | I19: Total Cost | J19: Install Margin | K19: Selling Price
B20: FABRICATE PRIMARY STEEL | C20: 0 | D20: 0 | E20: 0 | F20: 0 | G20: 0 | I20: =SUM(C20:G20) -> 0 | J20: =$D$8 -> 0.15 | K20: =I20/(1-J20) -> 0
B21: SUPPLY AND INSTALL PRIMARY PLYWOOD | C21: 0 | D21: 0 | E21: 0 | F21: 0 | G21: 0 | I21: =SUM(C21:G21) -> 0 | J21: =$D$8 -> 0.15 | K21: =I21/(1-J21) -> 0
B22: FABRICATE SECONDARY STEEL SUBSTRUCTURE | C22: 277.5 | D22: 0 | E22: 0 | F22: 0 | G22: 0 | I22: =SUM(C22:G22) -> 277.5 | J22: =$D$8 -> 0.15 | K22: =I22/(1-J22) -> 326.47
B23: FABRICATE CLADDING AND TRIM | C23: 0 | D23: 0 | E23: 0 | F23: 0 | G23: 0 | I23: =SUM(C23:G23) -> 0 | J23: =$D$8 -> 0.15 | K23: =I23/(1-J23) -> 0
B24: OTHER SCOPE ITEM | C24: 0 | D24: 0 | E24: 0 | F24: 0 | G24: 0 | I24: =SUM(C24:G24) -> 0 | J24: =$D$8 -> 0.15 | K24: =I24/(1-J24) -> 0
B25: OTHER SCOPE ITEM | C25: 0 | D25: 0 | E25: 0 | F25: 0 | G25: 0 | I25: =SUM(C25:G25) -> 0 | J25: =$D$8 -> 0.15 | K25: =I25/(1-J25) -> 0
B26: SUBTOTAL | I26: =SUM(I20:I25) -> 277.5 | K26: =SUM(K20:K25) -> 326.47
B28: Structural Labor and LED Installation | C28: Subcontractor 1 | D28: Subcontractor 2 | E28: Subcontractor 3 | F28: Selected | G28: Additional Contingency | I28: Total Cost | J28: Install Margin | K28: Selling Price
B29: REMOVAL AND DISPOSAL | C29: 0 | D29: 0 | E29: 0 | F29: 0 | G29: 0 | I29: =SUM(C29:G29) -> 0 | J29: =$D$8 -> 0.15 | K29: =I29/(1-J29) -> 0
B30: INSTALL SECONDARY STEEL SUBSTRUCTURE | C30: 0 | D30: 0 | E30: 0 | F30: 0 | G30: 0 | I30: =SUM(C30:G30) -> 0 | J30: =$D$8 -> 0.15 | K30: =I30/(1-J30) -> 0
B31: INSTALL LED DISPLAYS | C31: 1156.25 | D31: 0 | E31: 0 | F31: 0 | G31: 0 | I31: =SUM(C31:G31) -> 1156.25 | J31: =$D$8 -> 0.15 | K31: =I31/(1-J31) -> 1360.29
B32: INSTALL CLADDING AND TRIM | C32: 0 | D32: 0 | E32: 0 | F32: 0 | G32: 0 | I32: =SUM(C32:G32) -> 0 | J32: =$D$8 -> 0.15 | K32: =I32/(1-J32) -> 0
B33: HEAVY EQUIPMENT | C33: 0 | D33: 0 | E33: 0 | F33: 0 | G33: 0 | I33: =SUM(C33:G33) -> 0 | J33: =$D$8 -> 0.15 | K33: =I33/(1-J33) -> 0
B34: PM/GENERAL CONDITIONS/TRAVEL | C34: 20882.35 | D34: 0 | E34: 0 | F34: 0 | G34: 0 | I34: =SUM(C34:G34) -> 20882.35 | J34: =$D$8 -> 0.15 | K34: =I34/(1-J34) -> 24567.47
B35: SUBTOTAL | I35: =SUM(I29:I34) -> 22038.6 | K35: =SUM(K29:K34) -> 25927.76
B37: Electrical and Data - Materials and Subcontracting | C37: Subcontractor 1 | D37: Subcontractor 2 | E37: Subcontractor 3 | F37: Selected | G37: Additional Contingency | I37: Total Cost | J37: Install Margin | K37: Selling Price
B38: ELECTRICAL MATERIALS | C38: 1156.25 | D38: 0 | E38: 0 | F38: 0 | G38: 0 | I38: =SUM(C38:G38) -> 1156.25 | J38: =$D$9 -> 0.15 | K38: =I38/(1-J38) -> 1360.29
B39: DATA MATERIALS | C39: 0 | D39: 0 | E39: 0 | F39: 0 | G39: 0 | I39: =SUM(C39:G39) -> 0 | J39: =$D$9 -> 0.15 | K39: =I39/(1-J39) -> 0
B40: ELECTRICAL LABOR | C40: 0 | D40: 0 | E40: 0 | F40: 0 | G40: 0 | I40: =SUM(C40:G40) -> 0 | J40: =$D$9 -> 0.15 | K40: =I40/(1-J40) -> 0
B41: DATA LABOR | C41: 0 | D41: 0 | E41: 0 | F41: 0 | G41: 0 | I41: =SUM(C41:G41) -> 0 | J41: =$D$9 -> 0.15 | K41: =I41/(1-J41) -> 0
B42: SUB PANEL | C42: 0 | D42: 0 | E42: 0 | F42: 0 | G42: 0 | I42: =SUM(C42:G42) -> 0 | J42: =$D$9 -> 0.15 | K42: =I42/(1-J42) -> 0
B43: MISC | C43: 0 | D43: 0 | E43: 0 | F43: 0 | G43: 0 | I43: =SUM(C43:G43) -> 0 | J43: =$D$9 -> 0.15 | K43: =I43/(1-J43) -> 0
B44: SUBTOTAL | I44: =SUM(I38:I43) -> 1156.25 | K44: =SUM(K38:K43) -> 1360.29
B46: Submittals, Engineering, and Permits | C46: Subcontractor 1 | D46: Subcontractor 2 | E46: Subcontractor 3 | F46: Selected | G46: Additional Contingency | I46: Total Cost | J46: Install Margin | K46: Selling Price
B47: STRUCTURAL ENGINEERING | C47: 4705.88 | D47: 0 | E47: 0 | F47: 0 | G47: 0 | I47: =SUM(C47:G47) -> 4705.88 | J47: =$D$11 -> 0.15 | K47: =I47/(1-J47) -> 5536.33
B48: STRUCTURAL CERTIFICATION | C48: 0 | D48: 0 | E48: 0 | F48: 0 | G48: 0 | I48: =SUM(C48:G48) -> 0 | J48: =$D$11 -> 0.15 | K48: =I48/(1-J48) -> 0
B49: ELECTRICAL ENGINEERING | C49: 0 | D49: 0 | E49: 0 | F49: 0 | G49: 0 | I49: =SUM(C49:G49) -> 0 | J49: =$D$11 -> 0.15 | K49: =I49/(1-J49) -> 0
B50: ELECTRICAL CERTIFICATION | C50: 0 | D50: 0 | E50: 0 | F50: 0 | G50: 0 | I50: =SUM(C50:G50) -> 0 | J50: =$D$11 -> 0.15 | K50: =I50/(1-J50) -> 0
B51: PERMITS | C51: 0 | D51: 0 | E51: 0 | F51: 0 | G51: 0 | I51: =SUM(C51:G51) -> 0 | J51: =$D$11 -> 0.15 | K51: =I51/(1-J51) -> 0
B52: SUBTOTAL | I52: =SUM(I47:I51) -> 4705.88 | K52: =SUM(K47:K51) -> 5536.33
B54: ZONE GRAND TOTAL | I54: =I26+I35+I44+I52 -> 35002.39 | K54: =K26+K35+K44+K52 -> 40591.05

Sheet North Club24 - Install
A3: Project Name: Bank of America Stadium Modernization
A4: 2026-03-31
A5: Revised By: ANC Proposal Engine
C7: Linked Margin Assignment
C8: Install Margin | D8: 0.15
C9: Electrical Margin | D9: 0.15
C10: ANC Margin | D10: 0.15
C11: Engineering and Permits | D11: 0.15
B15: North Club
B16: Height | C16: Width | D16: Total Sq. Ft | E16: QTY
B17: 10 | C17: 16 | D17: 160 | E17: 1
B19: Structural Materials: | C19: Subcontractor 1 | D19: Subcontractor 2 | E19: Subcontractor 3 | F19: Selected | G19: Additional Contingency | I19: Total Cost | J19: Install Margin | K19: Selling Price
B20: FABRICATE PRIMARY STEEL | C20: 0 | D20: 0 | E20: 0 | F20: 0 | G20: 0 | I20: =SUM(C20:G20) -> 0 | J20: =$D$8 -> 0.15 | K20: =I20/(1-J20) -> 0
B21: SUPPLY AND INSTALL PRIMARY PLYWOOD | C21: 0 | D21: 0 | E21: 0 | F21: 0 | G21: 0 | I21: =SUM(C21:G21) -> 0 | J21: =$D$8 -> 0.15 | K21: =I21/(1-J21) -> 0
B22: FABRICATE SECONDARY STEEL SUBSTRUCTURE | C22: 1845 | D22: 0 | E22: 0 | F22: 0 | G22: 0 | I22: =SUM(C22:G22) -> 1845 | J22: =$D$8 -> 0.15 | K22: =I22/(1-J22) -> 2170.59
B23: FABRICATE CLADDING AND TRIM | C23: 0 | D23: 0 | E23: 0 | F23: 0 | G23: 0 | I23: =SUM(C23:G23) -> 0 | J23: =$D$8 -> 0.15 | K23: =I23/(1-J23) -> 0
B24: OTHER SCOPE ITEM | C24: 0 | D24: 0 | E24: 0 | F24: 0 | G24: 0 | I24: =SUM(C24:G24) -> 0 | J24: =$D$8 -> 0.15 | K24: =I24/(1-J24) -> 0
B25: OTHER SCOPE ITEM | C25: 0 | D25: 0 | E25: 0 | F25: 0 | G25: 0 | I25: =SUM(C25:G25) -> 0 | J25: =$D$8 -> 0.15 | K25: =I25/(1-J25) -> 0
B26: SUBTOTAL | I26: =SUM(I20:I25) -> 1845 | K26: =SUM(K20:K25) -> 2170.59
B28: Structural Labor and LED Installation | C28: Subcontractor 1 | D28: Subcontractor 2 | E28: Subcontractor 3 | F28: Selected | G28: Additional Contingency | I28: Total Cost | J28: Install Margin | K28: Selling Price
B29: REMOVAL AND DISPOSAL | C29: 0 | D29: 0 | E29: 0 | F29: 0 | G29: 0 | I29: =SUM(C29:G29) -> 0 | J29: =$D$8 -> 0.15 | K29: =I29/(1-J29) -> 0
B30: INSTALL SECONDARY STEEL SUBSTRUCTURE | C30: 0 | D30: 0 | E30: 0 | F30: 0 | G30: 0 | I30: =SUM(C30:G30) -> 0 | J30: =$D$8 -> 0.15 | K30: =I30/(1-J30) -> 0
B31: INSTALL LED DISPLAYS | C31: 7687.5 | D31: 0 | E31: 0 | F31: 0 | G31: 0 | I31: =SUM(C31:G31) -> 7687.5 | J31: =$D$8 -> 0.15 | K31: =I31/(1-J31) -> 9044.12
B32: INSTALL CLADDING AND TRIM | C32: 0 | D32: 0 | E32: 0 | F32: 0 | G32: 0 | I32: =SUM(C32:G32) -> 0 | J32: =$D$8 -> 0.15 | K32: =I32/(1-J32) -> 0
B33: HEAVY EQUIPMENT | C33: 0 | D33: 0 | E33: 0 | F33: 0 | G33: 0 | I33: =SUM(C33:G33) -> 0 | J33: =$D$8 -> 0.15 | K33: =I33/(1-J33) -> 0
B34: PM/GENERAL CONDITIONS/TRAVEL | C34: 20882.35 | D34: 0 | E34: 0 | F34: 0 | G34: 0 | I34: =SUM(C34:G34) -> 20882.35 | J34: =$D$8 -> 0.15 | K34: =I34/(1-J34) -> 24567.47
B35: SUBTOTAL | I35: =SUM(I29:I34) -> 28569.85 | K35: =SUM(K29:K34) -> 33611.59
B37: Electrical and Data - Materials and Subcontracting | C37: Subcontractor 1 | D37: Subcontractor 2 | E37: Subcontractor 3 | F37: Selected | G37: Additional Contingency | I37: Total Cost | J37: Install Margin | K37: Selling Price
B38: ELECTRICAL MATERIALS | C38: 7687.5 | D38: 0 | E38: 0 | F38: 0 | G38: 0 | I38: =SUM(C38:G38) -> 7687.5 | J38: =$D$9 -> 0.15 | K38: =I38/(1-J38) -> 9044.12
B39: DATA MATERIALS | C39: 0 | D39: 0 | E39: 0 | F39: 0 | G39: 0 | I39: =SUM(C39:G39) -> 0 | J39: =$D$9 -> 0.15 | K39: =I39/(1-J39) -> 0
B40: ELECTRICAL LABOR | C40: 0 | D40: 0 | E40: 0 | F40: 0 | G40: 0 | I40: =SUM(C40:G40) -> 0 | J40: =$D$9 -> 0.15 | K40: =I40/(1-J40) -> 0
B41: DATA LABOR | C41: 0 | D41: 0 | E41: 0 | F41: 0 | G41: 0 | I41: =SUM(C41:G41) -> 0 | J41: =$D$9 -> 0.15 | K41: =I41/(1-J41) -> 0
B42: SUB PANEL | C42: 0 | D42: 0 | E42: 0 | F42: 0 | G42: 0 | I42: =SUM(C42:G42) -> 0 | J42: =$D$9 -> 0.15 | K42: =I42/(1-J42) -> 0
B43: MISC | C43: 0 | D43: 0 | E43: 0 | F43: 0 | G43: 0 | I43: =SUM(C43:G43) -> 0 | J43: =$D$9 -> 0.15 | K43: =I43/(1-J43) -> 0
B44: SUBTOTAL | I44: =SUM(I38:I43) -> 7687.5 | K44: =SUM(K38:K43) -> 9044.12
B46: Submittals, Engineering, and Permits | C46: Subcontractor 1 | D46: Subcontractor 2 | E46: Subcontractor 3 | F46: Selected | G46: Additional Contingency | I46: Total Cost | J46: Install Margin | K46: Selling Price
B47: STRUCTURAL ENGINEERING | C47: 4705.88 | D47: 0 | E47: 0 | F47: 0 | G47: 0 | I47: =SUM(C47:G47) -> 4705.88 | J47: =$D$11 -> 0.15 | K47: =I47/(1-J47) -> 5536.33
B48: STRUCTURAL CERTIFICATION | C48: 0 | D48: 0 | E48: 0 | F48: 0 | G48: 0 | I48: =SUM(C48:G48) -> 0 | J48: =$D$11 -> 0.15 | K48: =I48/(1-J48) -> 0
B49: ELECTRICAL ENGINEERING | C49: 0 | D49: 0 | E49: 0 | F49: 0 | G49: 0 | I49: =SUM(C49:G49) -> 0 | J49: =$D$11 -> 0.15 | K49: =I49/(1-J49) -> 0
B50: ELECTRICAL CERTIFICATION | C50: 0 | D50: 0 | E50: 0 | F50: 0 | G50: 0 | I50: =SUM(C50:G50) -> 0 | J50: =$D$11 -> 0.15 | K50: =I50/(1-J50) -> 0
B51: PERMITS | C51: 0 | D51: 0 | E51: 0 | F51: 0 | G51: 0 | I51: =SUM(C51:G51) -> 0 | J51: =$D$11 -> 0.15 | K51: =I51/(1-J51) -> 0
B52: SUBTOTAL | I52: =SUM(I47:I51) -> 4705.88 | K52: =SUM(K47:K51) -> 5536.33
B54: ZONE GRAND TOTAL | I54: =I26+I35+I44+I52 -> 84019.27 | K54: =K26+K35+K44+K52 -> 96963.84

Sheet South Club25 - Install
A3: Project Name: Bank of America Stadium Modernization
A4: 2026-03-31
A5: Revised By: ANC Proposal Engine
C7: Linked Margin Assignment
C8: Install Margin | D8: 0.15
C9: Electrical Margin | D9: 0.15
C10: ANC Margin | D10: 0.15
C11: Engineering and Permits | D11: 0.15
B15: South Club
B16: Height | C16: Width | D16: Total Sq. Ft | E16: QTY
B17: 10 | C17: 16 | D17: 160 | E17: 1
B19: Structural Materials: | C19: Subcontractor 1 | D19: Subcontractor 2 | E19: Subcontractor 3 | F19: Selected | G19: Additional Contingency | I19: Total Cost | J19: Install Margin | K19: Selling Price
B20: FABRICATE PRIMARY STEEL | C20: 0 | D20: 0 | E20: 0 | F20: 0 | G20: 0 | I20: =SUM(C20:G20) -> 0 | J20: =$D$8 -> 0.15 | K20: =I20/(1-J20) -> 0
B21: SUPPLY AND INSTALL PRIMARY PLYWOOD | C21: 0 | D21: 0 | E21: 0 | F21: 0 | G21: 0 | I21: =SUM(C21:G21) -> 0 | J21: =$D$8 -> 0.15 | K21: =I21/(1-J21) -> 0
B22: FABRICATE SECONDARY STEEL SUBSTRUCTURE | C22: 1845 | D22: 0 | E22: 0 | F22: 0 | G22: 0 | I22: =SUM(C22:G22) -> 1845 | J22: =$D$8 -> 0.15 | K22: =I22/(1-J22) -> 2170.59
B23: FABRICATE CLADDING AND TRIM | C23: 0 | D23: 0 | E23: 0 | F23: 0 | G23: 0 | I23: =SUM(C23:G23) -> 0 | J23: =$D$8 -> 0.15 | K23: =I23/(1-J23) -> 0
B24: OTHER SCOPE ITEM | C24: 0 | D24: 0 | E24: 0 | F24: 0 | G24: 0 | I24: =SUM(C24:G24) -> 0 | J24: =$D$8 -> 0.15 | K24: =I24/(1-J24) -> 0
B25: OTHER SCOPE ITEM | C25: 0 | D25: 0 | E25: 0 | F25: 0 | G25: 0 | I25: =SUM(C25:G25) -> 0 | J25: =$D$8 -> 0.15 | K25: =I25/(1-J25) -> 0
B26: SUBTOTAL | I26: =SUM(I20:I25) -> 1845 | K26: =SUM(K20:K25) -> 2170.59
B28: Structural Labor and LED Installation | C28: Subcontractor 1 | D28: Subcontractor 2 | E28: Subcontractor 3 | F28: Selected | G28: Additional Contingency | I28: Total Cost | J28: Install Margin | K28: Selling Price
B29: REMOVAL AND DISPOSAL | C29: 0 | D29: 0 | E29: 0 | F29: 0 | G29: 0 | I29: =SUM(C29:G29) -> 0 | J29: =$D$8 -> 0.15 | K29: =I29/(1-J29) -> 0
B30: INSTALL SECONDARY STEEL SUBSTRUCTURE | C30: 0 | D30: 0 | E30: 0 | F30: 0 | G30: 0 | I30: =SUM(C30:G30) -> 0 | J30: =$D$8 -> 0.15 | K30: =I30/(1-J30) -> 0
B31: INSTALL LED DISPLAYS | C31: 7687.5 | D31: 0 | E31: 0 | F31: 0 | G31: 0 | I31: =SUM(C31:G31) -> 7687.5 | J31: =$D$8 -> 0.15 | K31: =I31/(1-J31) -> 9044.12
B32: INSTALL CLADDING AND TRIM | C32: 0 | D32: 0 | E32: 0 | F32: 0 | G32: 0 | I32: =SUM(C32:G32) -> 0 | J32: =$D$8 -> 0.15 | K32: =I32/(1-J32) -> 0
B33: HEAVY EQUIPMENT | C33: 0 | D33: 0 | E33: 0 | F33: 0 | G33: 0 | I33: =SUM(C33:G33) -> 0 | J33: =$D$8 -> 0.15 | K33: =I33/(1-J33) -> 0
B34: PM/GENERAL CONDITIONS/TRAVEL | C34: 20882.35 | D34: 0 | E34: 0 | F34: 0 | G34: 0 | I34: =SUM(C34:G34) -> 20882.35 | J34: =$D$8 -> 0.15 | K34: =I34/(1-J34) -> 24567.47
B35: SUBTOTAL | I35: =SUM(I29:I34) -> 28569.85 | K35: =SUM(K29:K34) -> 33611.59
B37: Electrical and Data - Materials and Subcontracting | C37: Subcontractor 1 | D37: Subcontractor 2 | E37: Subcontractor 3 | F37: Selected | G37: Additional Contingency | I37: Total Cost | J37: Install Margin | K37: Selling Price
B38: ELECTRICAL MATERIALS | C38: 7687.5 | D38: 0 | E38: 0 | F38: 0 | G38: 0 | I38: =SUM(C38:G38) -> 7687.5 | J38: =$D$9 -> 0.15 | K38: =I38/(1-J38) -> 9044.12
B39: DATA MATERIALS | C39: 0 | D39: 0 | E39: 0 | F39: 0 | G39: 0 | I39: =SUM(C39:G39) -> 0 | J39: =$D$9 -> 0.15 | K39: =I39/(1-J39) -> 0
B40: ELECTRICAL LABOR | C40: 0 | D40: 0 | E40: 0 | F40: 0 | G40: 0 | I40: =SUM(C40:G40) -> 0 | J40: =$D$9 -> 0.15 | K40: =I40/(1-J40) -> 0
B41: DATA LABOR | C41: 0 | D41: 0 | E41: 0 | F41: 0 | G41: 0 | I41: =SUM(C41:G41) -> 0 | J41: =$D$9 -> 0.15 | K41: =I41/(1-J41) -> 0
B42: SUB PANEL | C42: 0 | D42: 0 | E42: 0 | F42: 0 | G42: 0 | I42: =SUM(C42:G42) -> 0 | J42: =$D$9 -> 0.15 | K42: =I42/(1-J42) -> 0
B43: MISC | C43: 0 | D43: 0 | E43: 0 | F43: 0 | G43: 0 | I43: =SUM(C43:G43) -> 0 | J43: =$D$9 -> 0.15 | K43: =I43/(1-J43) -> 0
B44: SUBTOTAL | I44: =SUM(I38:I43) -> 7687.5 | K44: =SUM(K38:K43) -> 9044.12
B46: Submittals, Engineering, and Permits | C46: Subcontractor 1 | D46: Subcontractor 2 | E46: Subcontractor 3 | F46: Selected | G46: Additional Contingency | I46: Total Cost | J46: Install Margin | K46: Selling Price
B47: STRUCTURAL ENGINEERING | C47: 4705.88 | D47: 0 | E47: 0 | F47: 0 | G47: 0 | I47: =SUM(C47:G47) -> 4705.88 | J47: =$D$11 -> 0.15 | K47: =I47/(1-J47) -> 5536.33
B48: STRUCTURAL CERTIFICATION | C48: 0 | D48: 0 | E48: 0 | F48: 0 | G48: 0 | I48: =SUM(C48:G48) -> 0 | J48: =$D$11 -> 0.15 | K48: =I48/(1-J48) -> 0
B49: ELECTRICAL ENGINEERING | C49: 0 | D49: 0 | E49: 0 | F49: 0 | G49: 0 | I49: =SUM(C49:G49) -> 0 | J49: =$D$11 -> 0.15 | K49: =I49/(1-J49) -> 0
B50: ELECTRICAL CERTIFICATION | C50: 0 | D50: 0 | E50: 0 | F50: 0 | G50: 0 | I50: =SUM(C50:G50) -> 0 | J50: =$D$11 -> 0.15 | K50: =I50/(1-J50) -> 0
B51: PERMITS | C51: 0 | D51: 0 | E51: 0 | F51: 0 | G51: 0 | I51: =SUM(C51:G51) -> 0 | J51: =$D$11 -> 0.15 | K51: =I51/(1-J51) -> 0
B52: SUBTOTAL | I52: =SUM(I47:I51) -> 4705.88 | K52: =SUM(K47:K51) -> 5536.33
B54: ZONE GRAND TOTAL | I54: =I26+I35+I44+I52 -> 84019.27 | K54: =K26+K35+K44+K52 -> 96963.84

Sheet Processor Count
A1: Bank of America Stadium Modernization — Processor Count
B4: Display | C4: Width (px) | D4: Height (px) | E4: Ports | F4: Ports (80%) | G4: 8-bit Video | H4: 8-bit (80%) | I4: 10/12/HDR bit
B5: 660 Pro | C5: 1920 | D5: 1080 | E5: 8 | G5: 650000 | H5: 455000 | I5: 320000
B6: MCTRL4K | C6: 3840 | D6: 2160 | E6: 16 | G6: 650000 | H6: 455000 | I6: 320000
B7: H9 Enhanced | C7: 7680 | D7: 4320 | E7: 20 | G7: 1200000 | H7: 960000 | I7: 650000
B10: DISPLAY PROCESSOR REQUIREMENTS
B11: Display | C11: Width (px) | D11: Height (px) | E11: Qty | F11: Total Pixels | G11: Ports Needed | H11: Processor Type | I11: Processors Needed
B12: ='LED Cost Sheet'!A4 -> Team Room | C12: ='LED Cost Sheet'!H4 -> 0 | D12: ='LED Cost Sheet'!G4 -> 0 | E12: ='LED Cost Sheet'!I4 -> 1 | F12: =C12*D12*E12 -> 683750 | G12: =IFERROR(CEILING(F12/650000,1),0) -> 2 | H12: =IF(G12>8,"MCTRL4K","660 Pro") -> 660 Pro | I12: =IFERROR(CEILING(G12/IF(G12>8,16,8),1),0) -> 1
B13: ='LED Cost Sheet'!A5 -> Incident Command | C13: ='LED Cost Sheet'!H5 -> 0 | D13: ='LED Cost Sheet'!G5 -> 0 | E13: ='LED Cost Sheet'!I5 -> 1 | F13: =C13*D13*E13 -> 738507 | G13: =IFERROR(CEILING(F13/650000,1),0) -> 2 | H13: =IF(G13>8,"MCTRL4K","660 Pro") -> 660 Pro | I13: =IFERROR(CEILING(G13/IF(G13>8,16,8),1),0) -> 1
B14: ='LED Cost Sheet'!A6 -> Def. Unit | C14: ='LED Cost Sheet'!H6 -> 0 | D14: ='LED Cost Sheet'!G6 -> 0 | E14: ='LED Cost Sheet'!I6 -> 1 | F14: =C14*D14*E14 -> 683750 | G14: =IFERROR(CEILING(F14/650000,1),0) -> 2 | H14: =IF(G14>8,"MCTRL4K","660 Pro") -> 660 Pro | I14: =IFERROR(CEILING(G14/IF(G14>8,16,8),1),0) -> 1
B15: ='LED Cost Sheet'!A7 -> North Corridor | C15: ='LED Cost Sheet'!H7 -> 0 | D15: ='LED Cost Sheet'!G7 -> 0 | E15: ='LED Cost Sheet'!I7 -> 1 | F15: =C15*D15*E15 -> 6720900 | G15: =IFERROR(CEILING(F15/650000,1),0) -> 11 | H15: =IF(G15>8,"MCTRL4K","660 Pro") -> MCTRL4K | I15: =IFERROR(CEILING(G15/IF(G15>8,16,8),1),0) -> 1
B16: ='LED Cost Sheet'!A8 -> South Corridor | C16: ='LED Cost Sheet'!H8 -> 0 | D16: ='LED Cost Sheet'!G8 -> 0 | E16: ='LED Cost Sheet'!I8 -> 1 | F16: =C16*D16*E16 -> 5712980 | G16: =IFERROR(CEILING(F16/650000,1),0) -> 9 | H16: =IF(G16>8,"MCTRL4K","660 Pro") -> MCTRL4K | I16: =IFERROR(CEILING(G16/IF(G16>8,16,8),1),0) -> 1
B17: ='LED Cost Sheet'!A9 -> S.E Corridor | C17: ='LED Cost Sheet'!H9 -> 0 | D17: ='LED Cost Sheet'!G9 -> 0 | E17: ='LED Cost Sheet'!I9 -> 2 | F17: =C17*D17*E17 -> 4155548 | G17: =IFERROR(CEILING(F17/650000,1),0) -> 7 | H17: =IF(G17>8,"MCTRL4K","660 Pro") -> 660 Pro | I17: =IFERROR(CEILING(G17/IF(G17>8,16,8),1),0) -> 1
B18: ='LED Cost Sheet'!A10 -> East Corridor | C18: ='LED Cost Sheet'!H10 -> 0 | D18: ='LED Cost Sheet'!G10 -> 0 | E18: ='LED Cost Sheet'!I10 -> 1 | F18: =C18*D18*E18 -> 2200548 | G18: =IFERROR(CEILING(F18/650000,1),0) -> 4 | H18: =IF(G18>8,"MCTRL4K","660 Pro") -> 660 Pro | I18: =IFERROR(CEILING(G18/IF(G18>8,16,8),1),0) -> 1
B19: ='LED Cost Sheet'!A11 -> N.E Corridor | C19: ='LED Cost Sheet'!H11 -> 0 | D19: ='LED Cost Sheet'!G11 -> 0 | E19: ='LED Cost Sheet'!I11 -> 2 | F19: =C19*D19*E19 -> 4155548 | G19: =IFERROR(CEILING(F19/650000,1),0) -> 7 | H19: =IF(G19>8,"MCTRL4K","660 Pro") -> 660 Pro | I19: =IFERROR(CEILING(G19/IF(G19>8,16,8),1),0) -> 1
B20: ='LED Cost Sheet'!A12 -> Elev Lobby | C20: ='LED Cost Sheet'!H12 -> 0 | D20: ='LED Cost Sheet'!G12 -> 0 | E20: ='LED Cost Sheet'!I12 -> 4 | F20: =C20*D20*E20 -> 587188 | G20: =IFERROR(CEILING(F20/650000,1),0) -> 1 | H20: =IF(G20>8,"MCTRL4K","660 Pro") -> 660 Pro | I20: =IFERROR(CEILING(G20/IF(G20>8,16,8),1),0) -> 1
B21: ='LED Cost Sheet'!A13 -> North Club | C21: ='LED Cost Sheet'!H13 -> 0 | D21: ='LED Cost Sheet'!G13 -> 0 | E21: ='LED Cost Sheet'!I13 -> 2 | F21: =C21*D21*E21 -> 1955000 | G21: =IFERROR(CEILING(F21/650000,1),0) -> 4 | H21: =IF(G21>8,"MCTRL4K","660 Pro") -> 660 Pro | I21: =IFERROR(CEILING(G21/IF(G21>8,16,8),1),0) -> 1
B22: ='LED Cost Sheet'!A14 -> Panthers Den | C22: ='LED Cost Sheet'!H14 -> 0 | D22: ='LED Cost Sheet'!G14 -> 0 | E22: ='LED Cost Sheet'!I14 -> 3 | F22: =C22*D22*E22 -> 1206738 | G22: =IFERROR(CEILING(F22/650000,1),0) -> 2 | H22: =IF(G22>8,"MCTRL4K","660 Pro") -> 660 Pro | I22: =IFERROR(CEILING(G22/IF(G22>8,16,8),1),0) -> 1
B23: ='LED Cost Sheet'!A15 -> Panthers Den | C23: ='LED Cost Sheet'!H15 -> 0 | D23: ='LED Cost Sheet'!G15 -> 0 | E23: ='LED Cost Sheet'!I15 -> 1 | F23: =C23*D23*E23 -> 366795 | G23: =IFERROR(CEILING(F23/650000,1),0) -> 1 | H23: =IF(G23>8,"MCTRL4K","660 Pro") -> 660 Pro | I23: =IFERROR(CEILING(G23/IF(G23>8,16,8),1),0) -> 1
... B36: ='LED Cost Sheet'!A28 -> South Club | C36: ='LED Cost Sheet'!H28 -> 0 | D36: ='LED Cost Sheet'!G28 -> 0 | E36: ='LED Cost Sheet'!I28 -> 1 | F36: =C36*D36*E36 -> 977500 | G36: =IFERROR(CEILING(F36/650000,1),0) -> 2 | H36: =IF(G36>8,"MCTRL4K","660 Pro") -> 660 Pro | I36: =IFERROR(CEILING(G36/IF(G36>8,16,8),1),0) -> 1
B37: TOTAL | F37: =SUM(F12:F36) -> 41189337 | G37: =SUM(G12:G36) -> 79 | I37: =SUM(I12:I36) -> 25

Sheet Bundle Equipment
A1: Bank of America Stadium Modernization — Processor & Equipment Breakdown
A2: Editable — adjust component costs per display zone. Totals roll into Margin Analysis.
A6: Category | B6: Component | C6: Cost | D6: Qty | E6: Total Cost | F6: Margin | G6: Selling Price | H6: Margin $
A7: Team Room — Team Room
A8: EQUIPMENT | B8: Sending Card | C8: 450 | D8: 1 | E8: =C8*D8 -> 450 | F8: 0.15 | G8: =IFERROR(E8/(1-F8),0) -> 529.41 | H8: =IFERROR(G8-E8,0) -> 79.41
A9: EQUIPMENT | B9: Signal Cable Kit | C9: 67.2 | D9: 1 | E9: =C9*D9 -> 67.2 | F9: 0.15 | G9: =IFERROR(E9/(1-F9),0) -> 79.06 | H9: =IFERROR(G9-E9,0) -> 11.86
B10: Zone Subtotal | E10: =SUM(E8:E9) -> 517.2 | G10: =SUM(G8:G9) -> 608.47 | H10: =IFERROR(G10-E10,0) -> 91.27
A12: Incident Command — Incident Command
A13: EQUIPMENT | B13: Sending Card | C13: 450 | D13: 1 | E13: =C13*D13 -> 450 | F13: 0.15 | G13: =IFERROR(E13/(1-F13),0) -> 529.41 | H13: =IFERROR(G13-E13,0) -> 79.41
A14: EQUIPMENT | B14: Signal Cable Kit | C14: 72.53 | D14: 1 | E14: =C14*D14 -> 72.53 | F14: 0.15 | G14: =IFERROR(E14/(1-F14),0) -> 85.33 | H14: =IFERROR(G14-E14,0) -> 12.8
B15: Zone Subtotal | E15: =SUM(E13:E14) -> 522.53 | G15: =SUM(G13:G14) -> 614.74 | H15: =IFERROR(G15-E15,0) -> 92.21
A17: Def. Unit — Def. Unit
A18: EQUIPMENT | B18: Sending Card | C18: 450 | D18: 1 | E18: =C18*D18 -> 450 | F18: 0.15 | G18: =IFERROR(E18/(1-F18),0) -> 529.41 | H18: =IFERROR(G18-E18,0) -> 79.41
A19: EQUIPMENT | B19: Signal Cable Kit | C19: 67.2 | D19: 1 | E19: =C19*D19 -> 67.2 | F19: 0.15 | G19: =IFERROR(E19/(1-F19),0) -> 79.06 | H19: =IFERROR(G19-E19,0) -> 11.86
B20: Zone Subtotal | E20: =SUM(E18:E19) -> 517.2 | G20: =SUM(G18:G19) -> 608.47 | H20: =IFERROR(G20-E20,0) -> 91.27
A22: North Corridor — North Corridor
A23: EQUIPMENT | B23: Sending Card | C23: 8400 | D23: 1 | E23: =C23*D23 -> 8400 | F23: 0.15 | G23: =IFERROR(E23/(1-F23),0) -> 9882.35 | H23: =IFERROR(G23-E23,0) -> 1482.35
A24: EQUIPMENT | B24: Signal Cable Kit | C24: 660 | D24: 1 | E24: =C24*D24 -> 660 | F24: 0.15 | G24: =IFERROR(E24/(1-F24),0) -> 776.47 | H24: =IFERROR(G24-E24,0) -> 116.47
A25: EQUIPMENT | B25: Backup Video Processor | C25: 12000 | D25: 1 | E25: =C25*D25 -> 12000 | F25: 0.15 | G25: =IFERROR(E25/(1-F25),0) -> 14117.65 | H25: =IFERROR(G25-E25,0) -> 2117.65
B26: Zone Subtotal | E26: =SUM(E23:E25) -> 21060 | G26: =SUM(G23:G25) -> 24776.47 | H26: =IFERROR(G26-E26,0) -> 3716.47
A28: South Corridor — South Corridor
A29: EQUIPMENT | B29: Sending Card | C29: 8400 | D29: 1 | E29: =C29*D29 -> 8400 | F29: 0.15 | G29: =IFERROR(E29/(1-F29),0) -> 9882.35 | H29: =IFERROR(G29-E29,0) -> 1482.35
A30: EQUIPMENT | B30: Signal Cable Kit | C30: 561 | D30: 1 | E30: =C30*D30 -> 561 | F30: 0.15 | G30: =IFERROR(E30/(1-F30),0) -> 660 | H30: =IFERROR(G30-E30,0) -> 99
A31: EQUIPMENT | B31: Backup Video Processor | C31: 12000 | D31: 1 | E31: =C31*D31 -> 12000 | F31: 0.15 | G31: =IFERROR(E31/(1-F31),0) -> 14117.65 | H31: =IFERROR(G31-E31,0) -> 2117.65
B32: Zone Subtotal | E32: =SUM(E29:E31) -> 20961 | G32: =SUM(G29:G31) -> 24660 | H32: =IFERROR(G32-E32,0) -> 3699
A34: S.E Corridor — S.E Corridor
A35: EQUIPMENT | B35: Sending Card | C35: 450 | D35: 1 | E35: =C35*D35 -> 450 | F35: 0.15 | G35: =IFERROR(E35/(1-F35),0) -> 529.41 | H35: =IFERROR(G35-E35,0) -> 79.41
A36: EQUIPMENT | B36: Signal Cable Kit | C36: 408 | D36: 1 | E36: =C36*D36 -> 408 | F36: 0.15 | G36: =IFERROR(E36/(1-F36),0) -> 480 | H36: =IFERROR(G36-E36,0) -> 72
A37: EQUIPMENT | B37: Backup Video Processor | C37: 12000 | D37: 1 | E37: =C37*D37 -> 12000 | F37: 0.15 | G37: =IFERROR(E37/(1-F37),0) -> 14117.65 | H37: =IFERROR(G37-E37,0) -> 2117.65
B38: Zone Subtotal | E38: =SUM(E35:E37) -> 12858 | G38: =SUM(G35:G37) -> 15127.06 | H38: =IFERROR(G38-E38,0) -> 2269.06
A40: East Corridor — East Corridor
A41: EQUIPMENT | B41: Sending Card | C41: 450 | D41: 1 | E41: =C41*D41 -> 450 | F41: 0.15 | G41: =IFERROR(E41/(1-F41),0) -> 529.41 | H41: =IFERROR(G41-E41,0) -> 79.41
A42: EQUIPMENT | B42: Signal Cable Kit | C42: 216 | D42: 1 | E42: =C42*D42 -> 216 | F42: 0.15 | G42: =IFERROR(E42/(1-F42),0) -> 254.12 | H42: =IFERROR(G42-E42,0) -> 38.12
A43: EQUIPMENT | B43: Backup Video Processor | C43: 12000 | D43: 1 | E43: =C43*D43 -> 12000 | F43: 0.15 | G43: =IFERROR(E43/(1-F43),0) -> 14117.65 | H43: =IFERROR(G43-E43,0) -> 2117.65
B44: Zone Subtotal | E44: =SUM(E41:E43) -> 12666 | G44: =SUM(G41:G43) -> 14901.18 | H44: =IFERROR(G44-E44,0) -> 2235.18
A46: N.E Corridor — N.E Corridor
A47: EQUIPMENT | B47: Sending Card | C47: 450 | D47: 1 | E47: =C47*D47 -> 450 | F47: 0.15 | G47: =IFERROR(E47/(1-F47),0) -> 529.41 | H47: =IFERROR(G47-E47,0) -> 79.41
A48: EQUIPMENT | B48: Signal Cable Kit | C48: 408 | D48: 1 | E48: =C48*D48 -> 408 | F48: 0.15 | G48: =IFERROR(E48/(1-F48),0) -> 480 | H48: =IFERROR(G48-E48,0) -> 72
A49: EQUIPMENT | B49: Backup Video Processor | C49: 12000 | D49: 1 | E49: =C49*D49 -> 12000 | F49: 0.15 | G49: =IFERROR(E49/(1-F49),0) -> 14117.65 | H49: =IFERROR(G49-E49,0) -> 2117.65
B50: Zone Subtotal | E50: =SUM(E47:E49) -> 12858 | G50: =SUM(G47:G49) -> 15127.06 | H50: =IFERROR(G50-E50,0) -> 2269.06
A52: Elev Lobby — Elev Lobby
A53: EQUIPMENT | B53: Sending Card | C53: 450 | D53: 1 | E53: =C53*D53 -> 450 | F53: 0.15 | G53: =IFERROR(E53/(1-F53),0) -> 529.41 | H53: =IFERROR(G53-E53,0) -> 79.41
A54: EQUIPMENT | B54: Signal Cable Kit | C54: 57.6 | D54: 1 | E54: =C54*D54 -> 57.6 | F54: 0.15 | G54: =IFERROR(E54/(1-F54),0) -> 67.76 | H54: =IFERROR(G54-E54,0) -> 10.16
B55: Zone Subtotal | E55: =SUM(E53:E54) -> 507.6 | G55: =SUM(G53:G54) -> 597.17 | H55: =IFERROR(G55-E55,0) -> 89.57
A57: North Club — North Club
A58: EQUIPMENT | B58: Sending Card | C58: 450 | D58: 1 | E58: =C58*D58 -> 450 | F58: 0.15 | G58: =IFERROR(E58/(1-F58),0) -> 529.41 | H58: =IFERROR(G58-E58,0) -> 79.41
A59: EQUIPMENT | B59: Signal Cable Kit | C59: 192 | D59: 1 | E59: =C59*D59 -> 192 | F59: 0.15 | G59: =IFERROR(E59/(1-F59),0) -> 225.88 | H59: =IFERROR(G59-E59,0) -> 33.88
A60: EQUIPMENT | B60: Backup Video Processor | C60: 12000 | D60: 1 | E60: =C60*D60 -> 12000 | F60: 0.15 | G60: =IFERROR(E60/(1-F60),0) -> 14117.65 | H60: =IFERROR(G60-E60,0) -> 2117.65
B61: Zone Subtotal | E61: =SUM(E58:E60) -> 12642 | G61: =SUM(G58:G60) -> 14872.94 | H61: =IFERROR(G61-E61,0) -> 2230.94
A63: Panthers Den — Panthers Den
A64: EQUIPMENT | B64: Sending Card | C64: 450 | D64: 1 | E64: =C64*D64 -> 450 | F64: 0.15 | G64: =IFERROR(E64/(1-F64),0) -> 529.41 | H64: =IFERROR(G64-E64,0) -> 79.41
A65: EQUIPMENT | B65: Signal Cable Kit | C65: 118.8 | D65: 1 | E65: =C65*D65 -> 118.8 | F65: 0.15 | G65: =IFERROR(E65/(1-F65),0) -> 139.76 | H65: =IFERROR(G65-E65,0) -> 20.96
B66: Zone Subtotal | E66: =SUM(E64:E65) -> 568.8 | G66: =SUM(G64:G65) -> 669.17 | H66: =IFERROR(G66-E66,0) -> 100.37
A68: Panthers Den — Panthers Den
A69: EQUIPMENT | B69: Sending Card | C69: 450 | D69: 1 | E69: =C69*D69 -> 450 | F69: 0.15 | G69: =IFERROR(E69/(1-F69),0) -> 529.41 | H69: =IFERROR(G69-E69,0) -> 79.41
A70: EQUIPMENT | B70: Signal Cable Kit | C70: 36.1 | D70: 1 | E70: =C70*D70 -> 36.1 | F70: 0.15 | G70: =IFERROR(E70/(1-F70),0) -> 42.47 | H70: =IFERROR(G70-E70,0) -> 6.37
B71: Zone Subtotal | E71: =SUM(E69:E70) -> 486.1 | G71: =SUM(G69:G70) -> 571.88 | H71: =IFERROR(G71-E71,0) -> 85.78
A73: Panthers Den — Panthers Den
A74: EQUIPMENT | B74: Sending Card | C74: 450 | D74: 1 | E74: =C74*D74 -> 450 | F74: 0.15 | G74: =IFERROR(E74/(1-F74),0) -> 529.41 | H74: =IFERROR(G74-E74,0) -> 79.41
A75: EQUIPMENT | B75: Signal Cable Kit | C75: 39.6 | D75: 1 | E75: =C75*D75 -> 39.6 | F75: 0.15 | G75: =IFERROR(E75/(1-F75),0) -> 46.59 | H75: =IFERROR(G75-E75,0) -> 6.99
B76: Zone Subtotal | E76: =SUM(E74:E75) -> 489.6 | G76: =SUM(G74:G75) -> 576 | H76: =IFERROR(G76-E76,0) -> 86.4
A78: Panthers Den — Panthers Den
A79: EQUIPMENT | B79: Sending Card | C79: 450 | D79: 1 | E79: =C79*D79 -> 450 | F79: 0.15 | G79: =IFERROR(E79/(1-F79),0) -> 529.41 | H79: =IFERROR(G79-E79,0) -> 79.41
A80: EQUIPMENT | B80: Signal Cable Kit | C80: 36.1 | D80: 1 | E80: =C80*D80 -> 36.1 | F80: 0.15 | G80: =IFERROR(E80/(1-F80),0) -> 42.47 | H80: =IFERROR(G80-E80,0) -> 6.37
B81: Zone Subtotal | E81: =SUM(E79:E80) -> 486.1 | G81: =SUM(G79:G80) -> 571.88 | H81: =IFERROR(G81-E81,0) -> 85.78
A83: South Club — South Club
A84: EQUIPMENT | B84: Sending Card | C84: 450 | D84: 1 | E84: =C84*D84 -> 450 | F84: 0.15 | G84: =IFERROR(E84/(1-F84),0) -> 529.41 | H84: =IFERROR(G84-E84,0) -> 79.41
A85: EQUIPMENT | B85: Signal Cable Kit | C85: 192 | D85: 1 | E85: =C85*D85 -> 192 | F85: 0.15 | G85: =IFERROR(E85/(1-F85),0) -> 225.88 | H85: =IFERROR(G85-E85,0) -> 33.88
A86: EQUIPMENT | B86: Backup Video Processor | C86: 12000 | D86: 1 | E86: =C86*D86 -> 12000 | F86: 0.15 | G86: =IFERROR(E86/(1-F86),0) -> 14117.65 | H86: =IFERROR(G86-E86,0) -> 2117.65
B87: Zone Subtotal | E87: =SUM(E84:E86) -> 12642 | G87: =SUM(G84:G86) -> 14872.94 | H87: =IFERROR(G87-E87,0) -> 2230.94
A89: S.E Corridor — S.E Corridor
A90: EQUIPMENT | B90: Sending Card | C90: 450 | D90: 1 | E90: =C90*D90 -> 450 | F90: 0.15 | G90: =IFERROR(E90/(1-F90),0) -> 529.41 | H90: =IFERROR(G90-E90,0) -> 79.41
A91: EQUIPMENT | B91: Signal Cable Kit | C91: 204 | D91: 1 | E91: =C91*D91 -> 204 | F91: 0.15 | G91: =IFERROR(E91/(1-F91),0) -> 240 | H91: =IFERROR(G91-E91,0) -> 36
A92: EQUIPMENT | B92: Backup Video Processor | C92: 12000 | D92: 1 | E92: =C92*D92 -> 12000 | F92: 0.15 | G92: =IFERROR(E92/(1-F92),0) -> 14117.65 | H92: =IFERROR(G92-E92,0) -> 2117.65
B93: Zone Subtotal | E93: =SUM(E90:E92) -> 12654 | G93: =SUM(G90:G92) -> 14887.06 | H93: =IFERROR(G93-E93,0) -> 2233.06
A95: N.E Corridor — N.E Corridor
A96: EQUIPMENT | B96: Sending Card | C96: 450 | D96: 1 | E96: =C96*D96 -> 450 | F96: 0.15 | G96: =IFERROR(E96/(1-F96),0) -> 529.41 | H96: =IFERROR(G96-E96,0) -> 79.41
A97: EQUIPMENT | B97: Signal Cable Kit | C97: 204 | D97: 1 | E97: =C97*D97 -> 204 | F97: 0.15 | G97: =IFERROR(E97/(1-F97),0) -> 240 | H97: =IFERROR(G97-E97,0) -> 36
A98: EQUIPMENT | B98: Backup Video Processor | C98: 12000 | D98: 1 | E98: =C98*D98 -> 12000 | F98: 0.15 | G98: =IFERROR(E98/(1-F98),0) -> 14117.65 | H98: =IFERROR(G98-E98,0) -> 2117.65
B99: Zone Subtotal | E99: =SUM(E96:E98) -> 12654 | G99: =SUM(G96:G98) -> 14887.06 | H99: =IFERROR(G99-E99,0) -> 2233.06
A101: Panthers Den — Panthers Den
A102: EQUIPMENT | B102: Sending Card | C102: 450 | D102: 1 | E102: =C102*D102 -> 450 | F102: 0.15 | G102: =IFERROR(E102/(1-F102),0) -> 529.41 | H102: =IFERROR(G102-E102,0) -> 79.41
A103: EQUIPMENT | B103: Signal Cable Kit | C103: 39.6 | D103: 1 | E103: =C103*D103 -> 39.6 | F103: 0.15 | G103: =IFERROR(E103/(1-F103),0) -> 46.59 | H103: =IFERROR(G103-E103,0) -> 6.99
B104: Zone Subtotal | E104: =SUM(E102:E103) -> 489.6 | G104: =SUM(G102:G103) -> 576 | H104: =IFERROR(G104-E104,0) -> 86.4
A106: Panthers Den — Panthers Den
A107: EQUIPMENT | B107: Sending Card | C107: 450 | D107: 1 | E107: =C107*D107 -> 450 | F107: 0.15 | G107: =IFERROR(E107/(1-F107),0) -> 529.41 | H107: =IFERROR(G107-E107,0) -> 79.41
A108: EQUIPMENT | B108: Signal Cable Kit | C108: 139.2 | D108: 1 | E108: =C108*D108 -> 139.2 | F108: 0.15 | G108: =IFERROR(E108/(1-F108),0) -> 163.76 | H108: =IFERROR(G108-E108,0) -> 24.56
B109: Zone Subtotal | E109: =SUM(E107:E108) -> 589.2 | G109: =SUM(G107:G108) -> 693.17 | H109: =IFERROR(G109-E109,0) -> 103.97
A111: Panthers Den — Panthers Den
A112: EQUIPMENT | B112: Sending Card | C112: 450 | D112: 1 | E112: =C112*D112 -> 450 | F112: 0.15 | G112: =IFERROR(E112/(1-F112),0) -> 529.41 | H112: =IFERROR(G112-E112,0) -> 79.41
A113: EQUIPMENT | B113: Signal Cable Kit | C113: 91.26 | D113: 1 | E113: =C113*D113 -> 91.26 | F113: 0.15 | G113: =IFERROR(E113/(1-F113),0) -> 107.36 | H113: =IFERROR(G113-E113,0) -> 16.1
B114: Zone Subtotal | E114: =SUM(E112:E113) -> 541.26 | G114: =SUM(G112:G113) -> 636.77 | H114: =IFERROR(G114-E114,0) -> 95.51
A116: Elev Lobby — Elev Lobby
A117: EQUIPMENT | B117: Sending Card | C117: 450 | D117: 1 | E117: =C117*D117 -> 450 | F117: 0.15 | G117: =IFERROR(E117/(1-F117),0) -> 529.41 | H117: =IFERROR(G117-E117,0) -> 79.41
A118: EQUIPMENT | B118: Signal Cable Kit | C118: 14.4 | D118: 1 | E118: =C118*D118 -> 14.4 | F118: 0.15 | G118: =IFERROR(E118/(1-F118),0) -> 16.94 | H118: =IFERROR(G118-E118,0) -> 2.54
B119: Zone Subtotal | E119: =SUM(E117:E118) -> 464.4 | G119: =SUM(G117:G118) -> 546.35 | H119: =IFERROR(G119-E119,0) -> 81.95
A121: Elev Lobby — Elev Lobby
A122: EQUIPMENT | B122: Sending Card | C122: 450 | D122: 1 | E122: =C122*D122 -> 450 | F122: 0.15 | G122: =IFERROR(E122/(1-F122),0) -> 529.41 | H122: =IFERROR(G122-E122,0) -> 79.41
A123: EQUIPMENT | B123: Signal Cable Kit | C123: 14.4 | D123: 1 | E123: =C123*D123 -> 14.4 | F123: 0.15 | G123: =IFERROR(E123/(1-F123),0) -> 16.94 | H123: =IFERROR(G123-E123,0) -> 2.54
B124: Zone Subtotal | E124: =SUM(E122:E123) -> 464.4 | G124: =SUM(G122:G123) -> 546.35 | H124: =IFERROR(G124-E124,0) -> 81.95
...

Sheet ANC Travel
A1: Bank of America Stadium Modernization — ANC Travel
B4: Travel - Installation | C4: Cost | D4: Quantity | E4: Total Cost
B5: Hotel | C5: 300 | D5: 0 | E5: 0
B6: Airfare | C6: 1000 | D6: 0 | E6: 0
B7: Car | C7: 125 | D7: 0 | E7: 0
B8: Per Diem | C8: 100 | D8: 0 | E8: 0
B9: Bundled | C9: 10000 | D9: 0 | E9: 0 | G9: Account for freelancer
B10: Total | E10: 0
B11: TOTAL | C11: USD: | E11: 0
B13: Travel - Commissioning | C13: Cost | D13: Quantity | E13: Total Cost
B14: Hotel | C14: 300 | D14: 0 | E14: 0
B15: Airfare | C15: 1000 | D15: 0 | E15: 0
B16: Car | C16: 125 | D16: 0 | E16: 0
B17: Per Diem | C17: 100 | D17: 0 | E17: 0
B18: Bundled | C18: 10000 | D18: 0 | E18: 0 | G18: Account for freelancer
B19: Total | E19: 0
B20: TOTAL | C20: USD: | E20: 0
B22: Game Support | C22: Cost | D22: Quantity | E22: Total Cost
B23: Hotel | C23: 300 | D23: 0 | E23: 0
B24: Airfare | C24: 1000 | D24: 0 | E24: 0
B25: Car | C25: 125 | D25: 0 | E25: 0
B26: Per Diem | C26: 100 | D26: 0 | E26: 0
B27: Bundled | C27: 10000 | D27: 0 | E27: 0 | G27: Account for freelancer
B28: Game Day Support | C28: 1500 | D28: 0 | E28: 0
B29: Total | E29: 0
B30: TOTAL | C30: USD: | E30: 0

Sheet CMS
A1: Bank of America Stadium Modernization — Content Management System
B4: CMS Platform
B5: All costs require project-specific pricing — update items below based on RFP requirements
B6: Category | C6: Item | D6: Cost | E6: Quantity | F6: Total Cost | G6: Margin | H6: Selling Price | I6: Margin $
B7: PRIMARY | C7: DESIGN & CONTROL SOFTWARE | D7: 0 | E7: 0 | F7: =D7*E7 -> 0 | G7: 0.1 | H7: =IFERROR(F7/(1-G7),0) -> 0 | I7: =IFERROR(H7-F7,0) -> 0
B8: PRIMARY | C8: GRAPHICS PLAYBACK ENGINE | D8: 0 | E8: 0 | F8: =D8*E8 -> 0 | G8: 0.1 | H8: =IFERROR(F8/(1-G8),0) -> 0 | I8: =IFERROR(H8-F8,0) -> 0
B9: PRIMARY | C9: IMAGE PROCESSING | D9: 0 | E9: 0 | F9: =D9*E9 -> 0 | G9: 0.1 | H9: =IFERROR(F9/(1-G9),0) -> 0 | I9: =IFERROR(H9-F9,0) -> 0
B10: PRIMARY | C10: DEDICATED LED ROUTER / SWITCH | D10: 0 | E10: 0 | F10: =D10*E10 -> 0 | G10: 0.1 | H10: =IFERROR(F10/(1-G10),0) -> 0 | I10: =IFERROR(H10-F10,0) -> 0
B11: REDUNDANT | C11: DESIGN & CONTROL SOFTWARE | D11: 0 | E11: 0 | F11: =D11*E11 -> 0 | G11: 0.1 | H11: =IFERROR(F11/(1-G11),0) -> 0 | I11: =IFERROR(H11-F11,0) -> 0
B12: REDUNDANT | C12: GRAPHICS PLAYBACK ENGINE | D12: 0 | E12: 0 | F12: =D12*E12 -> 0 | G12: 0.1 | H12: =IFERROR(F12/(1-G12),0) -> 0 | I12: =IFERROR(H12-F12,0) -> 0
B13: REDUNDANT | C13: IMAGE PROCESSING | D13: 0 | E13: 0 | F13: =D13*E13 -> 0 | G13: 0.1 | H13: =IFERROR(F13/(1-G13),0) -> 0 | I13: =IFERROR(H13-F13,0) -> 0
B14: STANDARD SERVICES | C14: COMMISSIONING | D14: 0 | E14: 0 | F14: =D14*E14 -> 0 | G14: 0.1 | H14: =IFERROR(F14/(1-G14),0) -> 0 | I14: =IFERROR(H14-F14,0) -> 0
B15: STANDARD SERVICES | C15: EVENT SUPPORT | D15: 0 | E15: 0 | F15: =D15*E15 -> 0 | G15: 0.1 | H15: =IFERROR(F15/(1-G15),0) -> 0 | I15: =IFERROR(H15-F15,0) -> 0
B16: STANDARD SERVICES | C16: PROJECT MANAGEMENT | D16: 0 | E16: 0 | F16: =D16*E16 -> 0 | G16: 0.1 | H16: =IFERROR(F16/(1-G16),0) -> 0 | I16: =IFERROR(H16-F16,0) -> 0
C17: Integration Hardware | D17: 0 | E17: 0 | F17: =D17*E17 -> 0 | G17: 0.1 | H17: =IFERROR(F17/(1-G17),0) -> 0 | I17: =IFERROR(H17-F17,0) -> 0
C18: Integration Labor | D18: 0 | E18: 0 | F18: =D18*E18 -> 0 | G18: 0.1 | H18: =IFERROR(F18/(1-G18),0) -> 0 | I18: =IFERROR(H18-F18,0) -> 0
C19: Shipping | D19: 0 | E19: 0 | F19: =D19*E19 -> 0 | G19: 0.1 | H19: =IFERROR(F19/(1-G19),0) -> 0 | I19: =IFERROR(H19-F19,0) -> 0
C20: Travel | D20: 0 | E20: 0 | F20: =D20*E20 -> 0 | G20: 0.1 | H20: =IFERROR(F20/(1-G20),0) -> 0 | I20: =IFERROR(H20-F20,0) -> 0
C22: CMS TOTAL | F22: =SUM(F7:F20) -> 0 | H22: =SUM(H7:H20) -> 0 | I22: =IFERROR(H22-F22,0) -> 0
B24: TAX | F24: 0
B25: BOND | F25: 0
B26: SUB TOTAL | C26: USD: | F26: =F22+F24+F25 -> 0 | H26: =H22 -> 0 | I26: =IFERROR(H26-F26,0) -> 0

Sheet Scoring
A1: Bank of America Stadium Modernization — Scoring System
B4: Scoring Platform
B5: All costs require project-specific pricing — update items below based on RFP requirements
B6: Category | C6: Item | D6: Cost | E6: Quantity | F6: Total Cost | G6: Margin | H6: Selling Price | I6: Margin $
B7: HARDWARE | C7: SCORING CONTROLLER / SERVER | D7: 0 | E7: 0 | F7: =D7*E7 -> 0 | G7: 0.1 | H7: =IFERROR(F7/(1-G7),0) -> 0 | I7: =IFERROR(H7-F7,0) -> 0
B8: HARDWARE | C8: OPERATOR WORKSTATION(S) | D8: 0 | E8: 0 | F8: =D8*E8 -> 0 | G8: 0.1 | H8: =IFERROR(F8/(1-G8),0) -> 0 | I8: =IFERROR(H8-F8,0) -> 0
B9: HARDWARE | C9: SCOREBOARD INPUT DEVICES | D9: 0 | E9: 0 | F9: =D9*E9 -> 0 | G9: 0.1 | H9: =IFERROR(F9/(1-G9),0) -> 0 | I9: =IFERROR(H9-F9,0) -> 0
B10: HARDWARE | C10: SHOT CLOCK / GAME CLOCK INTERFACE | D10: 0 | E10: 0 | F10: =D10*E10 -> 0 | G10: 0.1 | H10: =IFERROR(F10/(1-G10),0) -> 0 | I10: =IFERROR(H10-F10,0) -> 0
B11: HARDWARE | C11: STATISTICS INTERFACE | D11: 0 | E11: 0 | F11: =D11*E11 -> 0 | G11: 0.1 | H11: =IFERROR(F11/(1-G11),0) -> 0 | I11: =IFERROR(H11-F11,0) -> 0
B12: SOFTWARE | C12: SCORING SOFTWARE LICENSE | D12: 0 | E12: 0 | F12: =D12*E12 -> 0 | G12: 0.1 | H12: =IFERROR(F12/(1-G12),0) -> 0 | I12: =IFERROR(H12-F12,0) -> 0
B13: SOFTWARE | C13: GRAPHICS / ANIMATION PACKAGE | D13: 0 | E13: 0 | F13: =D13*E13 -> 0 | G13: 0.1 | H13: =IFERROR(F13/(1-G13),0) -> 0 | I13: =IFERROR(H13-F13,0) -> 0
B14: SOFTWARE | C14: STATISTICS INTEGRATION | D14: 0 | E14: 0 | F14: =D14*E14 -> 0 | G14: 0.1 | H14: =IFERROR(F14/(1-G14),0) -> 0 | I14: =IFERROR(H14-F14,0) -> 0
B15: SERVICES | C15: COMMISSIONING | D15: 0 | E15: 0 | F15: =D15*E15 -> 0 | G15: 0.1 | H15: =IFERROR(F15/(1-G15),0) -> 0 | I15: =IFERROR(H15-F15,0) -> 0
B16: SERVICES | C16: TRAINING | D16: 0 | E16: 0 | F16: =D16*E16 -> 0 | G16: 0.1 | H16: =IFERROR(F16/(1-G16),0) -> 0 | I16: =IFERROR(H16-F16,0) -> 0
B17: SERVICES | C17: PROJECT MANAGEMENT | D17: 0 | E17: 0 | F17: =D17*E17 -> 0 | G17: 0.1 | H17: =IFERROR(F17/(1-G17),0) -> 0 | I17: =IFERROR(H17-F17,0) -> 0
C18: Integration Hardware | D18: 0 | E18: 0 | F18: =D18*E18 -> 0 | G18: 0.1 | H18: =IFERROR(F18/(1-G18),0) -> 0 | I18: =IFERROR(H18-F18,0) -> 0
C19: Integration Labor | D19: 0 | E19: 0 | F19: =D19*E19 -> 0 | G19: 0.1 | H19: =IFERROR(F19/(1-G19),0) -> 0 | I19: =IFERROR(H19-F19,0) -> 0
C20: Shipping | D20: 0 | E20: 0 | F20: =D20*E20 -> 0 | G20: 0.1 | H20: =IFERROR(F20/(1-G20),0) -> 0 | I20: =IFERROR(H20-F20,0) -> 0
C21: Travel | D21: 0 | E21: 0 | F21: =D21*E21 -> 0 | G21: 0.1 | H21: =IFERROR(F21/(1-G21),0) -> 0 | I21: =IFERROR(H21-F21,0) -> 0
C23: SCORING TOTAL | F23: =SUM(F7:F21) -> 0 | H23: =SUM(H7:H21) -> 0 | I23: =IFERROR(H23-F23,0) -> 0
B25: TAX | F25: 0
B26: BOND | F26: 0
B27: SUB TOTAL | C27: USD: | F27: =F23+F25+F26 -> 0 | H27: =H23 -> 0 | I27: =IFERROR(H27-F27,0) -> 0

Sheet Venue Services
A1: Bank of America Stadium Modernization — Venue Services
A2: Multi-year service contract calculator
A4: Contract Years | B4: 3 | C4: Editable service term
