Workbook

Sheet Project Overview
A1: WTC Digital Signage Upgrade — Project Overview
A2: Westfield | 2026-03-31 | ANC Proposal Engine
B4: PROJECT INFORMATION
B5: Client | C5: Westfield
B6: Project Name | C6: WTC Digital Signage Upgrade
B7: Location | C7: New York, NY
B8: Date Created | C8: 2026-03-31
B9: Currency | C9: USD
B10: Environment | C10: Indoor
B11: Union Labor | C11: No
B12: Bond Required | C12: No
B13: Number of Displays | C13: =SUM('LED Cost Sheet'!I4:I14) -> 447.24
B15: FINANCIAL PARAMETERS
B16: LED Hardware Margin | C16: 15%
B17: Install / Services Margin | C17: 15%
B18: Engineering Margin | C18: 15%
B19: Equipment Margin | C19: 15%
B20: CMS Margin | C20: 15%
B21: Bond Rate | C21: N/A
B22: Tax Rate | C22: Per zone (editable on MA)
B23: Tariff Rate | C23: Per zone (editable on MA)
B25: SUMMARY TOTALS
B26: Total Cost | C26: ='Margin Analysis'!C158 -> 2829644.1
B27: Total Selling Price | C27: ='Margin Analysis'!D158 -> 4636569.2
B28: Project Margin $ | C28: ='Margin Analysis'!E158 -> 1806925.1
B29: Project Margin % | C29: ='Margin Analysis'!F158 -> 0.38971166
B30: DOCUMENT TOTAL | C30: ='Margin Analysis'!D158 -> 4636569.2

Sheet Margin Analysis
A1: WTC Digital Signage Upgrade — Margin Analysis
A2: Westfield | 2026-03-31 | ANC Proposal Engine
B4: Zone / Category | C4: Cost | D4: Selling Price | E4: Margin $ | F4: Margin %
B5: Underpass 1 — 9A Underpass 1-4 | D5: Selling Price
B6: LED Hardware | C6: ='LED Cost Sheet'!T4 -> 34909.51 | D6: ='LED Cost Sheet'!V4 -> 92766.89 | E6: =IFERROR(D6-C6,0) -> 57857.38 | F6: 0.15
B7: Structural Materials | C7: ='Underpass 1 - Install'!I26 -> 2088.75 | D7: =IFERROR(C7/(1-F7),0) -> 2457.3529 | E7: =IFERROR(D7-C7,0) -> 368.60294 | F7: 0.15
B8: Structural Labor & LED Installation | C8: ='Underpass 1 - Install'!I35-'Underpass 1 - Install'!I34 -> 8703.13 | D8: =IFERROR(C8/(1-F8),0) -> 10238.976 | E8: =IFERROR(D8-C8,0) -> 1535.8465 | F8: 0.15
B9: Electrical & Data | C9: ='Underpass 1 - Install'!I44 -> 8703.13 | D9: =IFERROR(C9/(1-F9),0) -> 10238.976 | E9: =IFERROR(D9-C9,0) -> 1535.8465 | F9: 0.15
B10: PM / General Conditions / Travel | C10: ='Underpass 1 - Install'!I34 -> 20882.35 | D10: =IFERROR(C10/(1-F10),0) -> 24567.471 | E10: =IFERROR(D10-C10,0) -> 3685.1206 | F10: 0.15
B11: Engineering & Permits | C11: ='Underpass 1 - Install'!I52 -> 4705.88 | D11: =IFERROR(C11/(1-F11),0) -> 5536.3294 | E11: =IFERROR(D11-C11,0) -> 830.44941 | F11: 0.15
B12: SUBTOTAL | C12: =SUM(C6:C11) -> 79992.75 | D12: =SUM(D6:D11) -> 145806 | E12: =IFERROR(D12-C12,0) -> 65813.246 | F12: =IFERROR(1-C12/D12,0) -> 0.45137544
B13: TAX | C13: 0 | D13: 0 | E13: 0 | G13: 0
B14: BOND | C14: 0 | D14: 0 | E14: 0 | G14: 0
B15: TARIFF | C15: 0 | D15: 0 | E15: 0 | G15: 0
B16: GRAND TOTAL | C16: =C12+C13+C14+C15 -> 79992.75 | D16: =D12+D13+D14+D15 -> 145806 | E16: =IFERROR(D16-C16,0) -> 65813.246 | F16: =IFERROR(1-C16/D16,0) -> 0.45137544
B18: Underpass 2 — 9A Underpass 1-4 | D18: Selling Price
B19: LED Hardware | C19: ='LED Cost Sheet'!T5 -> 68046.11 | D19: ='LED Cost Sheet'!V5 -> 152572.17 | E19: =IFERROR(D19-C19,0) -> 84526.06 | F19: 0.15
B20: Structural Materials | C20: ='Underpass 2 - Install'!I26 -> 4102.5 | D20: =IFERROR(C20/(1-F20),0) -> 4826.4706 | E20: =IFERROR(D20-C20,0) -> 723.97059 | F20: 0.15
B21: Structural Labor & LED Installation | C21: ='Underpass 2 - Install'!I35-'Underpass 2 - Install'!I34 -> 17093.75 | D21: =IFERROR(C21/(1-F21),0) -> 20110.294 | E21: =IFERROR(D21-C21,0) -> 3016.5441 | F21: 0.15
B22: Electrical & Data | C22: ='Underpass 2 - Install'!I44 -> 17093.75 | D22: =IFERROR(C22/(1-F22),0) -> 20110.294 | E22: =IFERROR(D22-C22,0) -> 3016.5441 | F22: 0.15
B23: PM / General Conditions / Travel | C23: ='Underpass 2 - Install'!I34 -> 20882.35 | D23: =IFERROR(C23/(1-F23),0) -> 24567.471 | E23: =IFERROR(D23-C23,0) -> 3685.1206 | F23: 0.15
B24: Engineering & Permits | C24: ='Underpass 2 - Install'!I52 -> 4705.88 | D24: =IFERROR(C24/(1-F24),0) -> 5536.3294 | E24: =IFERROR(D24-C24,0) -> 830.44941 | F24: 0.15
B25: SUBTOTAL | C25: =SUM(C19:C24) -> 131924.34 | D25: =SUM(D19:D24) -> 227723.03 | E25: =IFERROR(D25-C25,0) -> 95798.689 | F25: =IFERROR(1-C25/D25,0) -> 0.42068072
B26: TAX | C26: 0 | D26: 0 | E26: 0 | G26: 0
B27: BOND | C27: 0 | D27: 0 | E27: 0 | G27: 0
B28: TARIFF | C28: 0 | D28: 0 | E28: 0 | G28: 0
B29: GRAND TOTAL | C29: =C25+C26+C27+C28 -> 131924.34 | D29: =D25+D26+D27+D28 -> 227723.03 | E29: =IFERROR(D29-C29,0) -> 95798.689 | F29: =IFERROR(1-C29/D29,0) -> 0.42068072
B31: Underpass 3 — 9A Underpass 1-4 | D31: Selling Price
B32: LED Hardware | C32: ='LED Cost Sheet'!T6 -> 68046.11 | D32: ='LED Cost Sheet'!V6 -> 152572.17 | E32: =IFERROR(D32-C32,0) -> 84526.06 | F32: 0.15
B33: Structural Materials | C33: ='Underpass 3 - Install'!I26 -> 4102.5 | D33: =IFERROR(C33/(1-F33),0) -> 4826.4706 | E33: =IFERROR(D33-C33,0) -> 723.97059 | F33: 0.15
B34: Structural Labor & LED Installation | C34: ='Underpass 3 - Install'!I35-'Underpass 3 - Install'!I34 -> 17093.75 | D34: =IFERROR(C34/(1-F34),0) -> 20110.294 | E34: =IFERROR(D34-C34,0) -> 3016.5441 | F34: 0.15
B35: Electrical & Data | C35: ='Underpass 3 - Install'!I44 -> 17093.75 | D35: =IFERROR(C35/(1-F35),0) -> 20110.294 | E35: =IFERROR(D35-C35,0) -> 3016.5441 | F35: 0.15
B36: PM / General Conditions / Travel | C36: ='Underpass 3 - Install'!I34 -> 20882.35 | D36: =IFERROR(C36/(1-F36),0) -> 24567.471 | E36: =IFERROR(D36-C36,0) -> 3685.1206 | F36: 0.15
B37: Engineering & Permits | C37: ='Underpass 3 - Install'!I52 -> 4705.88 | D37: =IFERROR(C37/(1-F37),0) -> 5536.3294 | E37: =IFERROR(D37-C37,0) -> 830.44941 | F37: 0.15
B38: SUBTOTAL | C38: =SUM(C32:C37) -> 131924.34 | D38: =SUM(D32:D37) -> 227723.03 | E38: =IFERROR(D38-C38,0) -> 95798.689 | F38: =IFERROR(1-C38/D38,0) -> 0.42068072
B39: TAX | C39: 0 | D39: 0 | E39: 0 | G39: 0
B40: BOND | C40: 0 | D40: 0 | E40: 0 | G40: 0
B41: TARIFF | C41: 0 | D41: 0 | E41: 0 | G41: 0
B42: GRAND TOTAL | C42: =C38+C39+C40+C41 -> 131924.34 | D42: =D38+D39+D40+D41 -> 227723.03 | E42: =IFERROR(D42-C42,0) -> 95798.689 | F42: =IFERROR(1-C42/D42,0) -> 0.42068072
B44: Underpass 4 — 9A Underpass 1-4 | D44: Selling Price
B45: LED Hardware | C45: ='LED Cost Sheet'!T7 -> 134265.3 | D45: ='LED Cost Sheet'!V7 -> 259474.86 | E45: =IFERROR(D45-C45,0) -> 125209.56 | F45: 0.15
B46: Structural Materials | C46: ='Underpass 4 - Install'!I26 -> 6907.5 | D46: =IFERROR(C46/(1-F46),0) -> 8126.4706 | E46: =IFERROR(D46-C46,0) -> 1218.9706 | F46: 0.15
B47: Structural Labor & LED Installation | C47: ='Underpass 4 - Install'!I35-'Underpass 4 - Install'!I34 -> 28781.25 | D47: =IFERROR(C47/(1-F47),0) -> 33860.294 | E47: =IFERROR(D47-C47,0) -> 5079.0441 | F47: 0.15
B48: Electrical & Data | C48: ='Underpass 4 - Install'!I44 -> 28781.25 | D48: =IFERROR(C48/(1-F48),0) -> 33860.294 | E48: =IFERROR(D48-C48,0) -> 5079.0441 | F48: 0.15
B49: PM / General Conditions / Travel | C49: ='Underpass 4 - Install'!I34 -> 20882.35 | D49: =IFERROR(C49/(1-F49),0) -> 24567.471 | E49: =IFERROR(D49-C49,0) -> 3685.1206 | F49: 0.15
B50: Engineering & Permits | C50: ='Underpass 4 - Install'!I52 -> 4705.88 | D50: =IFERROR(C50/(1-F50),0) -> 5536.3294 | E50: =IFERROR(D50-C50,0) -> 830.44941 | F50: 0.15
B51: SUBTOTAL | C51: =SUM(C45:C50) -> 224323.53 | D51: =SUM(D45:D50) -> 365425.72 | E51: =IFERROR(D51-C51,0) -> 141102.19 | F51: =IFERROR(1-C51/D51,0) -> 0.38613097
B52: TAX | C52: 0 | D52: 0 | E52: 0 | G52: 0
B53: BOND | C53: 0 | D53: 0 | E53: 0 | G53: 0
B54: TARIFF | C54: 0 | D54: 0 | E54: 0 | G54: 0
B55: GRAND TOTAL | C55: =C51+C52+C53+C54 -> 224323.53 | D55: =D51+D52+D53+D54 -> 365425.72 | E55: =IFERROR(D55-C55,0) -> 141102.19 | F55: =IFERROR(1-C55/D55,0) -> 0.38613097
B57: Concourse — Concourse | D57: Selling Price
B58: LED Hardware | C58: ='LED Cost Sheet'!T8 -> 845677.52 | D58: ='LED Cost Sheet'!V8 -> 1526801.7 | E58: =IFERROR(D58-C58,0) -> 681124.19 | F58: 0.15
B59: Structural Materials | C59: ='Concourse - Install'!I26 -> 48536.25 | D59: =IFERROR(C59/(1-F59),0) -> 57101.471 | E59: =IFERROR(D59-C59,0) -> 8565.2206 | F59: 0.15
B60: Structural Labor & LED Installation | C60: ='Concourse - Install'!I35-'Concourse - Install'!I34 -> 202234.38 | D60: =IFERROR(C60/(1-F60),0) -> 237922.8 | E60: =IFERROR(D60-C60,0) -> 35688.42 | F60: 0.15
B61: Electrical & Data | C61: ='Concourse - Install'!I44 -> 202234.38 | D61: =IFERROR(C61/(1-F61),0) -> 237922.8 | E61: =IFERROR(D61-C61,0) -> 35688.42 | F61: 0.15
B62: PM / General Conditions / Travel | C62: ='Concourse - Install'!I34 -> 20882.35 | D62: =IFERROR(C62/(1-F62),0) -> 24567.471 | E62: =IFERROR(D62-C62,0) -> 3685.1206 | F62: 0.15
B63: Engineering & Permits | C63: ='Concourse - Install'!I52 -> 4705.88 | D63: =IFERROR(C63/(1-F63),0) -> 5536.3294 | E63: =IFERROR(D63-C63,0) -> 830.44941 | F63: 0.15
B64: SUBTOTAL | C64: =SUM(C58:C63) -> 1324270.8 | D64: =SUM(D58:D63) -> 2089852.6 | E64: =IFERROR(D64-C64,0) -> 765581.82 | F64: =IFERROR(1-C64/D64,0) -> 0.36633293
B65: TAX | C65: 0 | D65: 0 | E65: 0 | G65: 0
B66: BOND | C66: 0 | D66: 0 | E66: 0 | G66: 0
B67: TARIFF | C67: 0 | D67: 0 | E67: 0 | G67: 0
B68: GRAND TOTAL | C68: =C64+C65+C66+C67 -> 1324270.8 | D68: =D64+D65+D66+D67 -> 2089852.6 | E68: =IFERROR(D68-C68,0) -> 765581.82 | F68: =IFERROR(1-C68/D68,0) -> 0.36633293
B70: T4-B1 (6-9) — T4-B1 | D70: Selling Price
B71: LED Hardware | C71: ='LED Cost Sheet'!T9 -> 82785.77 | D71: ='LED Cost Sheet'!V9 -> 179138.59 | E71: =IFERROR(D71-C71,0) -> 96352.82 | F71: 0.15
B72: Structural Materials | C72: ='T4-B1 (6-9) - Install'!I26 -> 4995 | D72: =IFERROR(C72/(1-F72),0) -> 5876.4706 | E72: =IFERROR(D72-C72,0) -> 881.47059 | F72: 0.15
B73: Structural Labor & LED Installation | C73: ='T4-B1 (6-9) - Install'!I35-'T4-B1 (6-9) - Install'!I34 -> 20812.5 | D73: =IFERROR(C73/(1-F73),0) -> 24485.294 | E73: =IFERROR(D73-C73,0) -> 3672.7941 | F73: 0.15
B74: Electrical & Data | C74: ='T4-B1 (6-9) - Install'!I44 -> 20812.5 | D74: =IFERROR(C74/(1-F74),0) -> 24485.294 | E74: =IFERROR(D74-C74,0) -> 3672.7941 | F74: 0.15
B75: PM / General Conditions / Travel | C75: ='T4-B1 (6-9) - Install'!I34 -> 20882.35 | D75: =IFERROR(C75/(1-F75),0) -> 24567.471 | E75: =IFERROR(D75-C75,0) -> 3685.1206 | F75: 0.15
B76: Engineering & Permits | C76: ='T4-B1 (6-9) - Install'!I52 -> 4705.88 | D76: =IFERROR(C76/(1-F76),0) -> 5536.3294 | E76: =IFERROR(D76-C76,0) -> 830.44941 | F76: 0.15
B77: SUBTOTAL | C77: =SUM(C71:C76) -> 154994 | D77: =SUM(D71:D76) -> 264089.45 | E77: =IFERROR(D77-C77,0) -> 109095.45 | F77: =IFERROR(1-C77/D77,0) -> 0.41310037
B78: TAX | C78: 0 | D78: 0 | E78: 0 | G78: 0
B79: BOND | C79: 0 | D79: 0 | E79: 0 | G79: 0
B80: TARIFF | C80: 0 | D80: 0 | E80: 0 | G80: 0
B81: GRAND TOTAL | C81: =C77+C78+C79+C80 -> 154994 | D81: =D77+D78+D79+D80 -> 264089.45 | E81: =IFERROR(D81-C81,0) -> 109095.45 | F81: =IFERROR(1-C81/D81,0) -> 0.41310037
B83: T4-B2 (10-18) — T4-B2 | D83: Selling Price
B84: LED Hardware | C84: ='LED Cost Sheet'!T10 -> 205655.43 | D84: ='LED Cost Sheet'!V10 -> 388240.91 | E84: =IFERROR(D84-C84,0) -> 182585.48 | F84: 0.15
B85: Structural Materials | C85: ='T4-B2 (10-18) - Install'!I26 -> 11238.75 | D85: =IFERROR(C85/(1-F85),0) -> 13222.059 | E85: =IFERROR(D85-C85,0) -> 1983.3088 | F85: 0.15
B86: Structural Labor & LED Installation | C86: ='T4-B2 (10-18) - Install'!I35-'T4-B2 (10-18) - Install'!I34 -> 46828.13 | D86: =IFERROR(C86/(1-F86),0) -> 55091.918 | E86: =IFERROR(D86-C86,0) -> 8263.7876 | F86: 0.15
B87: Electrical & Data | C87: ='T4-B2 (10-18) - Install'!I44 -> 46828.13 | D87: =IFERROR(C87/(1-F87),0) -> 55091.918 | E87: =IFERROR(D87-C87,0) -> 8263.7876 | F87: 0.15
B88: PM / General Conditions / Travel | C88: ='T4-B2 (10-18) - Install'!I34 -> 20882.35 | D88: =IFERROR(C88/(1-F88),0) -> 24567.471 | E88: =IFERROR(D88-C88,0) -> 3685.1206 | F88: 0.15
B89: Engineering & Permits | C89: ='T4-B2 (10-18) - Install'!I52 -> 4705.88 | D89: =IFERROR(C89/(1-F89),0) -> 5536.3294 | E89: =IFERROR(D89-C89,0) -> 830.44941 | F89: 0.15
B90: SUBTOTAL | C90: =SUM(C84:C89) -> 336138.67 | D90: =SUM(D84:D89) -> 541750.6 | E90: =IFERROR(D90-C90,0) -> 205611.93 | F90: =IFERROR(1-C90/D90,0) -> 0.37953245
B91: TAX | C91: 0 | D91: 0 | E91: 0 | G91: 0
B92: BOND | C92: 0 | D92: 0 | E92: 0 | G92: 0
B93: TARIFF | C93: 0 | D93: 0 | E93: 0 | G93: 0
B94: GRAND TOTAL | C94: =C90+C91+C92+C93 -> 336138.67 | D94: =D90+D91+D92+D93 -> 541750.6 | E94: =IFERROR(D94-C94,0) -> 205611.93 | F94: =IFERROR(1-C94/D94,0) -> 0.37953245
B96: T4 Lobby Elevator — T4 Lobby Elevator | D96: Selling Price
B97: LED Hardware | C97: ='LED Cost Sheet'!T11 -> 139342.57 | D97: ='LED Cost Sheet'!V11 -> 268709.18 | E97: =IFERROR(D97-C97,0) -> 129366.61 | F97: 0.15
B98: Structural Materials | C98: ='T4 Lobby Elevator - Install'!I26 -> 7222.5 | D98: =IFERROR(C98/(1-F98),0) -> 8497.0588 | E98: =IFERROR(D98-C98,0) -> 1274.5588 | F98: 0.15
B99: Structural Labor & LED Installation | C99: ='T4 Lobby Elevator - Install'!I35-'T4 Lobby Elevator - Install'!I34 -> 30093.75 | D99: =IFERROR(C99/(1-F99),0) -> 35404.412 | E99: =IFERROR(D99-C99,0) -> 5310.6618 | F99: 0.15
B100: Electrical & Data | C100: ='T4 Lobby Elevator - Install'!I44 -> 30093.75 | D100: =IFERROR(C100/(1-F100),0) -> 35404.412 | E100: =IFERROR(D100-C100,0) -> 5310.6618 | F100: 0.15
B101: PM / General Conditions / Travel | C101: ='T4 Lobby Elevator - Install'!I34 -> 20882.35 | D101: =IFERROR(C101/(1-F101),0) -> 24567.471 | E101: =IFERROR(D101-C101,0) -> 3685.1206 | F101: 0.15
B102: Engineering & Permits | C102: ='T4 Lobby Elevator - Install'!I52 -> 4705.88 | D102: =IFERROR(C102/(1-F102),0) -> 5536.3294 | E102: =IFERROR(D102-C102,0) -> 830.44941 | F102: 0.15
B103: SUBTOTAL | C103: =SUM(C97:C102) -> 232340.8 | D103: =SUM(D97:D102) -> 378118.86 | E103: =IFERROR(D103-C103,0) -> 145778.06 | F103: =IFERROR(1-C103/D103,0) -> 0.38553502
B104: TAX | C104: 0 | D104: 0 | E104: 0 | G104: 0
B105: BOND | C105: 0 | D105: 0 | E105: 0 | G105: 0
B106: TARIFF | C106: 0 | D106: 0 | E106: 0 | G106: 0
B107: GRAND TOTAL | C107: =C103+C104+C105+C106 -> 232340.8 | D107: =D103+D104+D105+D106 -> 378118.86 | E107: =IFERROR(D107-C107,0) -> 145778.06 | F107: =IFERROR(1-C107/D107,0) -> 0.38553502
B109: T2-B1M Screen 20 — T2-B1M | D109: Selling Price
...

Sheet Budget Summary
A1: WTC Digital Signage Upgrade — Budget Summary
A2: Westfield | 2026-03-31 | By Category
B4: Category | C4: Cost | D4: Selling Price | E4: Margin $ | F4: Margin % | G4: Price / SqFt
B5: LED Hardware (all displays) | C5: =SUM('LED Cost Sheet'!Q4:Q14) -> 1502080.2 | D5: =SUM('LED Cost Sheet'!S4:S14) -> 51540.9 | E5: =IFERROR(D5-C5,0) -> -1450539.3 | F5: 0.15 | G5: =IFERROR(C5/5154.09,0) -> 291.43461
B6: Structural Materials | C6: =SUM('Underpass 1 - Install'!I26:I26)+SUM('Underpass 2 - Install'!I26:I26)+SUM('Underpass 3 - Install'!I26:I26)+SUM('Underpass 4 - Install'!I26:I26)+SUM('Concourse - Install'!I26:I26)+SUM('T4-B1 (6-9) - Install'!I26:I26)+SUM('T4-B2 (10-18) - Install'!I26:I26)+SUM('T4 Lobby Elevator - Install'!I26:I26)+SUM('T2-B1M Screen 20 - Install'!I26:I26)+SUM('T2-B1M Screen 21 - Install'!I26:I26)+SUM('T2-B1M Screen 22 - Install'!I26:I26) -> 94447.5 | D6: =SUM('Underpass 1 - Install'!K26:K26)+SUM('Underpass 2 - Install'!K26:K26)+SUM('Underpass 3 - Install'!K26:K26)+SUM('Underpass 4 - Install'!K26:K26)+SUM('Concourse - Install'!K26:K26)+SUM('T4-B1 (6-9) - Install'!K26:K26)+SUM('T4-B2 (10-18) - Install'!K26:K26)+SUM('T4 Lobby Elevator - Install'!K26:K26)+SUM('T2-B1M Screen 20 - Install'!K26:K26)+SUM('T2-B1M Screen 21 - Install'!K26:K26)+SUM('T2-B1M Screen 22 - Install'!K26:K26) -> 111114.71 | E6: =IFERROR(D6-C6,0) -> 16667.206 | F6: 0.15 | G6: =IFERROR(C6/5154.09,0) -> 18.324767
B7: Structural Labor & LED Installation | C7: =(SUM('Underpass 1 - Install'!I35:I35)-SUM('Underpass 1 - Install'!I34:I34))+(SUM('Underpass 2 - Install'!I35:I35)-SUM('Underpass 2 - Install'!I34:I34))+(SUM('Underpass 3 - Install'!I35:I35)-SUM('Underpass 3 - Install'!I34:I34))+(SUM('Underpass 4 - Install'!I35:I35)-SUM('Underpass 4 - Install'!I34:I34))+(SUM('Concourse - Install'!I35:I35)-SUM('Concourse - Install'!I34:I34))+(SUM('T4-B1 (6-9) - Install'!I35:I35)-SUM('T4-B1 (6-9) - Install'!I34:I34))+(SUM('T4-B2 (10-18) - Install'!I35:I35)-SUM('T4-B2 (10-18) - Install'!I34:I34))+(SUM('T4 Lobby Elevator - Install'!I35:I35)-SUM('T4 Lobby Elevator - Install'!I34:I34))+(SUM('T2-B1M Screen 20 - Install'!I35:I35)-SUM('T2-B1M Screen 20 - Install'!I34:I34))+(SUM('T2-B1M Screen 21 - Install'!I35:I35)-SUM('T2-B1M Screen 21 - Install'!I34:I34))+(SUM('T2-B1M Screen 22 - Install'!I35:I35)-SUM('T2-B1M Screen 22 - Install'!I34:I34)) -> 393531.27 | D7: =(SUM('Underpass 1 - Install'!K35:K35)-SUM('Underpass 1 - Install'!K34:K34))+(SUM('Underpass 2 - Install'!K35:K35)-SUM('Underpass 2 - Install'!K34:K34))+(SUM('Underpass 3 - Install'!K35:K35)-SUM('Underpass 3 - Install'!K34:K34))+(SUM('Underpass 4 - Install'!K35:K35)-SUM('Underpass 4 - Install'!K34:K34))+(SUM('Concourse - Install'!K35:K35)-SUM('Concourse - Install'!K34:K34))+(SUM('T4-B1 (6-9) - Install'!K35:K35)-SUM('T4-B1 (6-9) - Install'!K34:K34))+(SUM('T4-B2 (10-18) - Install'!K35:K35)-SUM('T4-B2 (10-18) - Install'!K34:K34))+(SUM('T4 Lobby Elevator - Install'!K35:K35)-SUM('T4 Lobby Elevator - Install'!K34:K34))+(SUM('T2-B1M Screen 20 - Install'!K35:K35)-SUM('T2-B1M Screen 20 - Install'!K34:K34))+(SUM('T2-B1M Screen 21 - Install'!K35:K35)-SUM('T2-B1M Screen 21 - Install'!K34:K34))+(SUM('T2-B1M Screen 22 - Install'!K35:K35)-SUM('T2-B1M Screen 22 - Install'!K34:K34)) -> 462977.96 | E7: =IFERROR(D7-C7,0) -> 69446.695 | F7: 0.15 | G7: =IFERROR(C7/5154.09,0) -> 76.353201
B8: Electrical & Data | C8: =SUM('Underpass 1 - Install'!I44:I44)+SUM('Underpass 2 - Install'!I44:I44)+SUM('Underpass 3 - Install'!I44:I44)+SUM('Underpass 4 - Install'!I44:I44)+SUM('Concourse - Install'!I44:I44)+SUM('T4-B1 (6-9) - Install'!I44:I44)+SUM('T4-B2 (10-18) - Install'!I44:I44)+SUM('T4 Lobby Elevator - Install'!I44:I44)+SUM('T2-B1M Screen 20 - Install'!I44:I44)+SUM('T2-B1M Screen 21 - Install'!I44:I44)+SUM('T2-B1M Screen 22 - Install'!I44:I44) -> 393531.27 | D8: =SUM('Underpass 1 - Install'!K44:K44)+SUM('Underpass 2 - Install'!K44:K44)+SUM('Underpass 3 - Install'!K44:K44)+SUM('Underpass 4 - Install'!K44:K44)+SUM('Concourse - Install'!K44:K44)+SUM('T4-B1 (6-9) - Install'!K44:K44)+SUM('T4-B2 (10-18) - Install'!K44:K44)+SUM('T4 Lobby Elevator - Install'!K44:K44)+SUM('T2-B1M Screen 20 - Install'!K44:K44)+SUM('T2-B1M Screen 21 - Install'!K44:K44)+SUM('T2-B1M Screen 22 - Install'!K44:K44) -> 462977.96 | E8: =IFERROR(D8-C8,0) -> 69446.695 | F8: 0.15 | G8: =IFERROR(C8/5154.09,0) -> 76.353201
B9: PM / General Conditions / Travel | C9: =SUM('Underpass 1 - Install'!I34:I34)+SUM('Underpass 2 - Install'!I34:I34)+SUM('Underpass 3 - Install'!I34:I34)+SUM('Underpass 4 - Install'!I34:I34)+SUM('Concourse - Install'!I34:I34)+SUM('T4-B1 (6-9) - Install'!I34:I34)+SUM('T4-B2 (10-18) - Install'!I34:I34)+SUM('T4 Lobby Elevator - Install'!I34:I34)+SUM('T2-B1M Screen 20 - Install'!I34:I34)+SUM('T2-B1M Screen 21 - Install'!I34:I34)+SUM('T2-B1M Screen 22 - Install'!I34:I34) -> 229705.85 | D9: =SUM('Underpass 1 - Install'!K34:K34)+SUM('Underpass 2 - Install'!K34:K34)+SUM('Underpass 3 - Install'!K34:K34)+SUM('Underpass 4 - Install'!K34:K34)+SUM('Concourse - Install'!K34:K34)+SUM('T4-B1 (6-9) - Install'!K34:K34)+SUM('T4-B2 (10-18) - Install'!K34:K34)+SUM('T4 Lobby Elevator - Install'!K34:K34)+SUM('T2-B1M Screen 20 - Install'!K34:K34)+SUM('T2-B1M Screen 21 - Install'!K34:K34)+SUM('T2-B1M Screen 22 - Install'!K34:K34) -> 270242.18 | E9: =IFERROR(D9-C9,0) -> 40536.326 | F9: 0.15
B10: Engineering & Permits | C10: =SUM('Underpass 1 - Install'!I52:I52)+SUM('Underpass 2 - Install'!I52:I52)+SUM('Underpass 3 - Install'!I52:I52)+SUM('Underpass 4 - Install'!I52:I52)+SUM('Concourse - Install'!I52:I52)+SUM('T4-B1 (6-9) - Install'!I52:I52)+SUM('T4-B2 (10-18) - Install'!I52:I52)+SUM('T4 Lobby Elevator - Install'!I52:I52)+SUM('T2-B1M Screen 20 - Install'!I52:I52)+SUM('T2-B1M Screen 21 - Install'!I52:I52)+SUM('T2-B1M Screen 22 - Install'!I52:I52) -> 51764.68 | D10: =SUM('Underpass 1 - Install'!K52:K52)+SUM('Underpass 2 - Install'!K52:K52)+SUM('Underpass 3 - Install'!K52:K52)+SUM('Underpass 4 - Install'!K52:K52)+SUM('Concourse - Install'!K52:K52)+SUM('T4-B1 (6-9) - Install'!K52:K52)+SUM('T4-B2 (10-18) - Install'!K52:K52)+SUM('T4 Lobby Elevator - Install'!K52:K52)+SUM('T2-B1M Screen 20 - Install'!K52:K52)+SUM('T2-B1M Screen 21 - Install'!K52:K52)+SUM('T2-B1M Screen 22 - Install'!K52:K52) -> 60899.624 | E10: =IFERROR(D10-C10,0) -> 9134.9435 | F10: 0.15
B11: CMS (Content Management System) | C11: =SUM(CMS!F26:F26) -> 0 | D11: =SUM(CMS!H26:H26) -> 0 | E11: =IFERROR(D11-C11,0) -> 0 | F11: 0.15
B12: Scoring System | C12: =SUM(Scoring!F27:F27) -> 0 | D12: =SUM(Scoring!H27:H27) -> 0 | E12: =IFERROR(D12-C12,0) -> 0 | F12: 0.15
B13: Venue Services | C13: =SUM('Venue Services'!B17:B17) -> 0 | D13: =SUM('Venue Services'!C17:C17) -> 0 | E13: =IFERROR(D13-C13,0) -> 0 | F13: 0.15
B14: Game Clock | C14: =SUM('Additional Items'!F5:F5) -> 0 | D14: =SUM('Additional Items'!H5:H5) -> 0 | E14: =IFERROR(D14-C14,0) -> 0 | F14: 0.15
B15: Pitch Clocks | C15: =SUM('Additional Items'!F6:F6) -> 0 | D15: =SUM('Additional Items'!H6:H6) -> 0 | E15: =IFERROR(D15-C15,0) -> 0 | F15: 0.15
B16: OES / MIS / Timing | C16: =SUM('Additional Items'!F7:F7) -> 0 | D16: =SUM('Additional Items'!H7:H7) -> 0 | E16: =IFERROR(D16-C16,0) -> 0 | F16: 0.15
B17: DMX / Misc Equipment | C17: =SUM('Additional Items'!F8:F8) -> 0 | D17: =SUM('Additional Items'!H8:H8) -> 0 | E17: =IFERROR(D17-C17,0) -> 0 | F17: 0.15
B19: SUBTOTAL | C19: =SUM(C5:C17) -> 2665060.8 | D19: =SUM(D5:D17) -> 1419753.3 | E19: =IFERROR(D19-C19,0) -> -1245307.4 | F19: =IFERROR(1-C19/D19,0) -> -0.87712944 | G19: =IFERROR(C19/5154.09,0) -> 517.07688
B20: TAX | C20: 0 | D20: 0 | E20: 0 | F20: 0
B21: BOND | C21: 0 | D21: 0 | E21: 0 | F21: 0
B22: GRAND TOTAL | C22: =C19+C20+C21 -> 2665060.8 | D22: =D19+D20+D21 -> 1419753.3 | E22: =IFERROR(D22-C22,0) -> -1245307.4 | F22: =IFERROR(1-C22/D22,0) -> -0.87712944 | G22: =IFERROR(C22/5154.09,0) -> 517.07688

Sheet LED Cost Sheet
A1: WTC Digital Signage Upgrade — LED Cost Sheet
U2: LED Margin Override → | V2: 0.15
A3: Display | B3: RFP H (ft) | C3: RFP W (ft) | D3: RFP NITs | E3: Vendor | F3: Product | G3: Pitch | H3: H (ft) | I3: W (ft) | J3: H (px) | K3: W (px) | L3: Qty | M3: Total SqFt | N3: Product NITs | O3: Service | P3: $/SqFt | Q3: Display Cost | R3: Processor | S3: Shipping | T3: Total Cost | U3: Margin % | V3: Selling Price | W3: ANC Margin | X3: Weight (lbs) | Y3: Total Power (W) | Z3: BTU/hr
A4: Underpass 1 — 9A Underpass 1-4 | B4: 6.3 | C4: 18.11 | E4: LG/Yaham | F4: C2.5-MIP 2.5mm Indoor (Alt) | G4: 2.5mm | H4: 6.3 | I4: 18.11 | J4: 768 | K4: 2208 | L4: 1 | M4: =H4*I4*L4 -> 114.093 | N4: 2000 | O4: front | P4: 291.44 | Q4: 33250.16 | R4: =SUM('Bundle Equipment'!E10:E10) -> 518.45 | S4: 1140.9 | T4: 34909.51 | U4: =V$2 -> 0.15 | V4: 92766.89 | W4: 12774.14 | X4: 558 | Y4: 4140 | Z4: =Y4*3.412 -> 14125.68
A5: Underpass 2 — 9A Underpass 1-4 | B5: 7.48 | C5: 29.92 | E5: LG/Yaham | F5: C2.5-MIP 2.5mm Indoor (Alt) | G5: 2.5mm | H5: 7.48 | I5: 29.92 | J5: 912 | K5: 3648 | L5: 1 | M5: =H5*I5*L5 -> 223.8016 | N5: 2000 | O5: front | P5: 291.44 | Q5: 65223.83 | R5: =SUM('Bundle Equipment'!E15:E15) -> 584.28 | S5: 2238 | T5: 68046.11 | U5: =V$2 -> 0.15 | V5: 152572.17 | W5: 20647.83 | X5: 1094 | Y5: 8121 | Z5: =Y5*3.412 -> 27708.852
A6: Underpass 3 — 9A Underpass 1-4 | B6: 7.48 | C6: 29.92 | E6: LG/Yaham | F6: C2.5-MIP 2.5mm Indoor (Alt) | G6: 2.5mm | H6: 7.48 | I6: 29.92 | J6: 912 | K6: 3648 | L6: 1 | M6: =H6*I6*L6 -> 223.8016 | N6: 2000 | O6: front | P6: 291.44 | Q6: 65223.83 | R6: =SUM('Bundle Equipment'!E20:E20) -> 584.28 | S6: 2238 | T6: 68046.11 | U6: =V$2 -> 0.15 | V6: 152572.17 | W6: 20647.83 | X6: 1094 | Y6: 8121 | Z6: =Y6*3.412 -> 27708.852
A7: Underpass 4 — 9A Underpass 1-4 | B7: 12.6 | C7: 29.92 | E7: LG/Yaham | F7: C2.5-MIP 2.5mm Indoor (Alt) | G7: 2.5mm | H7: 12.6 | I7: 29.92 | J7: 1536 | K7: 3648 | L7: 1 | M7: =H7*I7*L7 -> 376.992 | N7: 2000 | O7: front | P7: 291.44 | Q7: 109869.21 | R7: =SUM('Bundle Equipment'!E26:E26) -> 20626.19 | S7: 3769.9 | T7: 134265.3 | U7: =V$2 -> 0.15 | V7: 259474.86 | W7: 35151.33 | X7: 1842 | Y7: 13680 | Z7: =Y7*3.412 -> 46676.16
A8: Concourse — Concourse | B8: 9.45 | C8: 280.31 | E8: LG/Yaham | F8: C2.5-MIP 2.5mm Indoor (Alt) | G8: 2.5mm | H8: 9.45 | I8: 280.31 | J8: 1152 | K8: 34175 | L8: 1 | M8: =H8*I8*L8 -> 2648.9295 | N8: 2000 | O8: front | P8: 291.44 | Q8: 771998.86 | R8: =SUM('Bundle Equipment'!E32:E32) -> 47189.36 | S8: 26489.3 | T8: 845677.52 | U8: =V$2 -> 0.15 | V8: 1526801.7 | W8: 202530.95 | X8: 12945 | Y8: 96124 | Z8: =Y8*3.412 -> 327975.09
A9: T4-B1 (6-9) — T4-B1 | B9: 7.87 | C9: 8.66 | E9: LG/Yaham | F9: C2.5-MIP 2.5mm Indoor (Alt) | G9: 2.5mm | H9: 7.87 | I9: 8.66 | J9: 960 | K9: 1056 | L9: 4 | M9: =H9*I9*L9 -> 272.6168 | N9: 2000 | O9: front | P9: 291.42 | Q9: 79446 | R9: =SUM('Bundle Equipment'!E37:E37) -> 613.57 | S9: 2726.2 | T9: 82785.77 | U9: =V$2 -> 0.15 | V9: 179138.59 | W9: 24144.59 | X9: 1332 | Y9: 9893 | Z9: =Y9*3.412 -> 33754.916
A10: T4-B2 (10-18) — T4-B2 | B10: 7.87 | C10: 8.66 | E10: LG/Yaham | F10: C2.5-MIP 2.5mm Indoor (Alt) | G10: 2.5mm | H10: 7.87 | I10: 8.66 | J10: 960 | K10: 1056 | L10: 9 | M10: =H10*I10*L10 -> 613.3878 | N10: 2000 | O10: front | P10: 291.42 | Q10: 178753.5 | R10: =SUM('Bundle Equipment'!E43:E43) -> 20768.03 | S10: 6133.9 | T10: 205655.43 | U10: =V$2 -> 0.15 | V10: 388240.91 | W10: 52102.24 | X10: 2997 | Y10: 22259 | Z10: =Y10*3.412 -> 75947.708
A11: T4 Lobby Elevator — T4 Lobby Elevator | B11: 71.6 | C11: 5.5 | E11: LG/Yaham | F11: C2.5-MIP 2.5mm Indoor (Alt) | G11: 2.5mm | H11: 71.6 | I11: 5.5 | J11: 8729 | K11: 671 | L11: 1 | M11: =H11*I11*L11 -> 393.8 | N11: 2000 | O11: front | P11: 291.44 | Q11: 114768.29 | R11: =SUM('Bundle Equipment'!E49:E49) -> 20636.28 | S11: 3938 | T11: 139342.57 | U11: =V$2 -> 0.15 | V11: 268709.18 | W11: 36368.38 | X11: 1924 | Y11: 14290 | Z11: =Y11*3.412 -> 48757.48
A12: T2-B1M Screen 20 — T2-B1M | B12: 7.91 | C12: 16.5 | E12: LG/Yaham | F12: C2.5-MIP 2.5mm Indoor (Alt) | G12: 2.5mm | H12: 7.91 | I12: 16.5 | J12: 964 | K12: 2012 | L12: 1 | M12: =H12*I12*L12 -> 130.515 | N12: 2000 | O12: front | P12: 291.44 | Q12: 38038.49 | R12: =SUM('Bundle Equipment'!E54:E54) -> 528.31 | S12: 1305.2 | T12: 39872 | U12: =V$2 -> 0.15 | V12: 101747.09 | W12: 13956.86 | X12: 638 | Y12: 4736 | Z12: =Y12*3.412 -> 16159.232
A13: T2-B1M Screen 21 — T2-B1M | B13: 7.91 | C13: 11.83 | E13: LG/Yaham | F13: C2.5-MIP 2.5mm Indoor (Alt) | G13: 2.5mm | H13: 7.91 | I13: 11.83 | J13: 964 | K13: 1442 | L13: 1 | M13: =H13*I13*L13 -> 93.5753 | N13: 2000 | O13: front | P13: 291.44 | Q13: 27272.76 | R13: =SUM('Bundle Equipment'!E59:E59) -> 506.15 | S13: 935.8 | T13: 28714.71 | U13: =V$2 -> 0.15 | V13: 81602.53 | W13: 11304.58 | X13: 457 | Y13: 3396 | Z13: =Y13*3.412 -> 11587.152
A14: T2-B1M Screen 22 — T2-B1M | B14: 7.91 | C14: 7.91 | E14: LG/Yaham | F14: C2.5-MIP 2.5mm Indoor (Alt) | G14: 2.5mm | H14: 7.91 | I14: 7.91 | J14: 964 | K14: 964 | L14: 1 | M14: =H14*I14*L14 -> 62.5681 | N14: 2000 | O14: front | P14: 291.44 | Q14: 18235.28 | R14: =SUM('Bundle Equipment'!E64:E64) -> 487.54 | S14: 625.7 | T14: 19348.52 | U14: =V$2 -> 0.15 | V14: 64730.65 | W14: 9083.9 | X14: 306 | Y14: 2271 | Z14: =Y14*3.412 -> 7748.652
A16: TOTAL (11 displays) | M16: =M4+M5+M6+M7+M8+M9+M10+M11+M12+M13+M14 -> 5154.0807 | Q16: =Q4+Q5+Q6+Q7+Q8+Q9+Q10+Q11+Q12+Q13+Q14 -> 1502080.2 | R16: =R4+R5+R6+R7+R8+R9+R10+R11+R12+R13+R14 -> 113042.44 | S16: =S4+S5+S6+S7+S8+S9+S10+S11+S12+S13+S14 -> 51540.9 | T16: =T4+T5+T6+T7+T8+T9+T10+T11+T12+T13+T14 -> 1666663.6 | U16: =IFERROR(1-T16/V16,0) -> 0.4900607 | V16: =V4+V5+V6+V7+V8+V9+V10+V11+V12+V13+V14 -> 3268356.7 | W16: =W4+W5+W6+W7+W8+W9+W10+W11+W12+W13+W14 -> 438712.63 | X16: =X4+X5+X6+X7+X8+X9+X10+X11+X12+X13+X14 -> 25187 | Y16: =Y4+Y5+Y6+Y7+Y8+Y9+Y10+Y11+Y12+Y13+Y14 -> 187031 | Z16: =Z4+Z5+Z6+Z7+Z8+Z9+Z10+Z11+Z12+Z13+Z14 -> 638149.77

Sheet Tech Specs (Installers)
A1: WTC Digital Signage Upgrade — LED Technical Specifications (No Pricing)
A2: Technical specifications only — no pricing data. Safe for installer/subcontractor distribution.
A4: Display Name | B4: Qty | C4: Pixel Pitch | D4: Height (ft) | E4: Width (ft) | F4: Pixels H | G4: Pixels W | H4: Sq Ft | I4: Brightness (nits) | J4: Service | K4: Environment | L4: Weight (lbs) | M4: Total Power (W) | N4: Fiber Strands | O4: BTU/hr
A5: ='LED Cost Sheet'!A4 -> Underpass 1 — 9A Underpass 1-4 | B5: ='LED Cost Sheet'!I4 -> 18.11 | C5: ='LED Cost Sheet'!D4 | D5: ='LED Cost Sheet'!E4 -> LG/Yaham | E5: ='LED Cost Sheet'!F4 -> C2.5-MIP 2.5mm Indoor (Alt) | F5: ='LED Cost Sheet'!G4 -> 2.5mm | G5: ='LED Cost Sheet'!H4 -> 6.3 | H5: =D5*E5*B5 -> #VALUE! | I5: ='LED Cost Sheet'!K4 -> 2208 | J5: ='LED Cost Sheet'!L4 -> 1 | K5: indoor | L5: ='LED Cost Sheet'!U4 -> 0.15 | M5: ='LED Cost Sheet'!V4 -> 92766.89 | N5: =IFERROR((F5*G5*B5)/400000,0) -> 0 | O5: ='LED Cost Sheet'!W4 -> 12774.14
A6: ='LED Cost Sheet'!A5 -> Underpass 2 — 9A Underpass 1-4 | B6: ='LED Cost Sheet'!I5 -> 29.92 | C6: ='LED Cost Sheet'!D5 | D6: ='LED Cost Sheet'!E5 -> LG/Yaham | E6: ='LED Cost Sheet'!F5 -> C2.5-MIP 2.5mm Indoor (Alt) | F6: ='LED Cost Sheet'!G5 -> 2.5mm | G6: ='LED Cost Sheet'!H5 -> 7.48 | H6: =D6*E6*B6 -> #VALUE! | I6: ='LED Cost Sheet'!K5 -> 3648 | J6: ='LED Cost Sheet'!L5 -> 1 | K6: indoor | L6: ='LED Cost Sheet'!U5 -> 0.15 | M6: ='LED Cost Sheet'!V5 -> 152572.17 | N6: =IFERROR((F6*G6*B6)/400000,0) -> 0 | O6: ='LED Cost Sheet'!W5 -> 20647.83
A7: ='LED Cost Sheet'!A6 -> Underpass 3 — 9A Underpass 1-4 | B7: ='LED Cost Sheet'!I6 -> 29.92 | C7: ='LED Cost Sheet'!D6 | D7: ='LED Cost Sheet'!E6 -> LG/Yaham | E7: ='LED Cost Sheet'!F6 -> C2.5-MIP 2.5mm Indoor (Alt) | F7: ='LED Cost Sheet'!G6 -> 2.5mm | G7: ='LED Cost Sheet'!H6 -> 7.48 | H7: =D7*E7*B7 -> #VALUE! | I7: ='LED Cost Sheet'!K6 -> 3648 | J7: ='LED Cost Sheet'!L6 -> 1 | K7: indoor | L7: ='LED Cost Sheet'!U6 -> 0.15 | M7: ='LED Cost Sheet'!V6 -> 152572.17 | N7: =IFERROR((F7*G7*B7)/400000,0) -> 0 | O7: ='LED Cost Sheet'!W6 -> 20647.83
A8: ='LED Cost Sheet'!A7 -> Underpass 4 — 9A Underpass 1-4 | B8: ='LED Cost Sheet'!I7 -> 29.92 | C8: ='LED Cost Sheet'!D7 | D8: ='LED Cost Sheet'!E7 -> LG/Yaham | E8: ='LED Cost Sheet'!F7 -> C2.5-MIP 2.5mm Indoor (Alt) | F8: ='LED Cost Sheet'!G7 -> 2.5mm | G8: ='LED Cost Sheet'!H7 -> 12.6 | H8: =D8*E8*B8 -> #VALUE! | I8: ='LED Cost Sheet'!K7 -> 3648 | J8: ='LED Cost Sheet'!L7 -> 1 | K8: indoor | L8: ='LED Cost Sheet'!U7 -> 0.15 | M8: ='LED Cost Sheet'!V7 -> 259474.86 | N8: =IFERROR((F8*G8*B8)/400000,0) -> 0 | O8: ='LED Cost Sheet'!W7 -> 35151.33
A9: ='LED Cost Sheet'!A8 -> Concourse — Concourse | B9: ='LED Cost Sheet'!I8 -> 280.31 | C9: ='LED Cost Sheet'!D8 | D9: ='LED Cost Sheet'!E8 -> LG/Yaham | E9: ='LED Cost Sheet'!F8 -> C2.5-MIP 2.5mm Indoor (Alt) | F9: ='LED Cost Sheet'!G8 -> 2.5mm | G9: ='LED Cost Sheet'!H8 -> 9.45 | H9: =D9*E9*B9 -> #VALUE! | I9: ='LED Cost Sheet'!K8 -> 34175 | J9: ='LED Cost Sheet'!L8 -> 1 | K9: indoor | L9: ='LED Cost Sheet'!U8 -> 0.15 | M9: ='LED Cost Sheet'!V8 -> 1526801.7 | N9: =IFERROR((F9*G9*B9)/400000,0) -> 0 | O9: ='LED Cost Sheet'!W8 -> 202530.95
A10: ='LED Cost Sheet'!A9 -> T4-B1 (6-9) — T4-B1 | B10: ='LED Cost Sheet'!I9 -> 8.66 | C10: ='LED Cost Sheet'!D9 | D10: ='LED Cost Sheet'!E9 -> LG/Yaham | E10: ='LED Cost Sheet'!F9 -> C2.5-MIP 2.5mm Indoor (Alt) | F10: ='LED Cost Sheet'!G9 -> 2.5mm | G10: ='LED Cost Sheet'!H9 -> 7.87 | H10: =D10*E10*B10 -> #VALUE! | I10: ='LED Cost Sheet'!K9 -> 1056 | J10: ='LED Cost Sheet'!L9 -> 4 | K10: indoor | L10: ='LED Cost Sheet'!U9 -> 0.15 | M10: ='LED Cost Sheet'!V9 -> 179138.59 | N10: =IFERROR((F10*G10*B10)/400000,0) -> 0 | O10: ='LED Cost Sheet'!W9 -> 24144.59
A11: ='LED Cost Sheet'!A10 -> T4-B2 (10-18) — T4-B2 | B11: ='LED Cost Sheet'!I10 -> 8.66 | C11: ='LED Cost Sheet'!D10 | D11: ='LED Cost Sheet'!E10 -> LG/Yaham | E11: ='LED Cost Sheet'!F10 -> C2.5-MIP 2.5mm Indoor (Alt) | F11: ='LED Cost Sheet'!G10 -> 2.5mm | G11: ='LED Cost Sheet'!H10 -> 7.87 | H11: =D11*E11*B11 -> #VALUE! | I11: ='LED Cost Sheet'!K10 -> 1056 | J11: ='LED Cost Sheet'!L10 -> 9 | K11: indoor | L11: ='LED Cost Sheet'!U10 -> 0.15 | M11: ='LED Cost Sheet'!V10 -> 388240.91 | N11: =IFERROR((F11*G11*B11)/400000,0) -> 0 | O11: ='LED Cost Sheet'!W10 -> 52102.24
A12: ='LED Cost Sheet'!A11 -> T4 Lobby Elevator — T4 Lobby Elevator | B12: ='LED Cost Sheet'!I11 -> 5.5 | C12: ='LED Cost Sheet'!D11 | D12: ='LED Cost Sheet'!E11 -> LG/Yaham | E12: ='LED Cost Sheet'!F11 -> C2.5-MIP 2.5mm Indoor (Alt) | F12: ='LED Cost Sheet'!G11 -> 2.5mm | G12: ='LED Cost Sheet'!H11 -> 71.6 | H12: =D12*E12*B12 -> #VALUE! | I12: ='LED Cost Sheet'!K11 -> 671 | J12: ='LED Cost Sheet'!L11 -> 1 | K12: indoor | L12: ='LED Cost Sheet'!U11 -> 0.15 | M12: ='LED Cost Sheet'!V11 -> 268709.18 | N12: =IFERROR((F12*G12*B12)/400000,0) -> 0 | O12: ='LED Cost Sheet'!W11 -> 36368.38
A13: ='LED Cost Sheet'!A12 -> T2-B1M Screen 20 — T2-B1M | B13: ='LED Cost Sheet'!I12 -> 16.5 | C13: ='LED Cost Sheet'!D12 | D13: ='LED Cost Sheet'!E12 -> LG/Yaham | E13: ='LED Cost Sheet'!F12 -> C2.5-MIP 2.5mm Indoor (Alt) | F13: ='LED Cost Sheet'!G12 -> 2.5mm | G13: ='LED Cost Sheet'!H12 -> 7.91 | H13: =D13*E13*B13 -> #VALUE! | I13: ='LED Cost Sheet'!K12 -> 2012 | J13: ='LED Cost Sheet'!L12 -> 1 | K13: indoor | L13: ='LED Cost Sheet'!U12 -> 0.15 | M13: ='LED Cost Sheet'!V12 -> 101747.09 | N13: =IFERROR((F13*G13*B13)/400000,0) -> 0 | O13: ='LED Cost Sheet'!W12 -> 13956.86
A14: ='LED Cost Sheet'!A13 -> T2-B1M Screen 21 — T2-B1M | B14: ='LED Cost Sheet'!I13 -> 11.83 | C14: ='LED Cost Sheet'!D13 | D14: ='LED Cost Sheet'!E13 -> LG/Yaham | E14: ='LED Cost Sheet'!F13 -> C2.5-MIP 2.5mm Indoor (Alt) | F14: ='LED Cost Sheet'!G13 -> 2.5mm | G14: ='LED Cost Sheet'!H13 -> 7.91 | H14: =D14*E14*B14 -> #VALUE! | I14: ='LED Cost Sheet'!K13 -> 1442 | J14: ='LED Cost Sheet'!L13 -> 1 | K14: indoor | L14: ='LED Cost Sheet'!U13 -> 0.15 | M14: ='LED Cost Sheet'!V13 -> 81602.53 | N14: =IFERROR((F14*G14*B14)/400000,0) -> 0 | O14: ='LED Cost Sheet'!W13 -> 11304.58
A15: ='LED Cost Sheet'!A14 -> T2-B1M Screen 22 — T2-B1M | B15: ='LED Cost Sheet'!I14 -> 7.91 | C15: ='LED Cost Sheet'!D14 | D15: ='LED Cost Sheet'!E14 -> LG/Yaham | E15: ='LED Cost Sheet'!F14 -> C2.5-MIP 2.5mm Indoor (Alt) | F15: ='LED Cost Sheet'!G14 -> 2.5mm | G15: ='LED Cost Sheet'!H14 -> 7.91 | H15: =D15*E15*B15 -> #VALUE! | I15: ='LED Cost Sheet'!K14 -> 964 | J15: ='LED Cost Sheet'!L14 -> 1 | K15: indoor | L15: ='LED Cost Sheet'!U14 -> 0.15 | M15: ='LED Cost Sheet'!V14 -> 64730.65 | N15: =IFERROR((F15*G15*B15)/400000,0) -> 0 | O15: ='LED Cost Sheet'!W14 -> 9083.9

Sheet Underpass 1 - Install
A3: Project Name: WTC Digital Signage Upgrade
A4: 2026-03-31
A5: Revised By: ANC Proposal Engine
C7: Linked Margin Assignment
C8: Install Margin | D8: 0.15
C9: Electrical Margin | D9: 0.15
C10: ANC Margin | D10: 0.15
C11: Engineering and Permits | D11: 0.15
B15: Underpass 1
B16: Height | C16: Width | D16: Total Sq. Ft | E16: QTY
B17: 6.3 | C17: 18.11 | D17: 114.09 | E17: 1
B19: Structural Materials: | C19: Subcontractor 1 | D19: Subcontractor 2 | E19: Subcontractor 3 | F19: Selected | G19: Additional Contingency | I19: Total Cost | J19: Install Margin | K19: Selling Price
B20: FABRICATE PRIMARY STEEL | C20: 0 | D20: 0 | E20: 0 | F20: 0 | G20: 0 | I20: =SUM(C20:G20) -> 0 | J20: =$D$8 -> 0.15 | K20: =I20/(1-J20) -> 0
B21: SUPPLY AND INSTALL PRIMARY PLYWOOD | C21: 0 | D21: 0 | E21: 0 | F21: 0 | G21: 0 | I21: =SUM(C21:G21) -> 0 | J21: =$D$8 -> 0.15 | K21: =I21/(1-J21) -> 0
B22: FABRICATE SECONDARY STEEL SUBSTRUCTURE | C22: 2088.75 | D22: 0 | E22: 0 | F22: 0 | G22: 0 | I22: =SUM(C22:G22) -> 2088.75 | J22: =$D$8 -> 0.15 | K22: =I22/(1-J22) -> 2457.3529
B23: FABRICATE CLADDING AND TRIM | C23: 0 | D23: 0 | E23: 0 | F23: 0 | G23: 0 | I23: =SUM(C23:G23) -> 0 | J23: =$D$8 -> 0.15 | K23: =I23/(1-J23) -> 0
B24: OTHER SCOPE ITEM | C24: 0 | D24: 0 | E24: 0 | F24: 0 | G24: 0 | I24: =SUM(C24:G24) -> 0 | J24: =$D$8 -> 0.15 | K24: =I24/(1-J24) -> 0
B25: OTHER SCOPE ITEM | C25: 0 | D25: 0 | E25: 0 | F25: 0 | G25: 0 | I25: =SUM(C25:G25) -> 0 | J25: =$D$8 -> 0.15 | K25: =I25/(1-J25) -> 0
B26: SUBTOTAL | I26: =SUM(I20:I25) -> 2088.75 | K26: =SUM(K20:K25) -> 2457.3529
B28: Structural Labor and LED Installation | C28: Subcontractor 1 | D28: Subcontractor 2 | E28: Subcontractor 3 | F28: Selected | G28: Additional Contingency | I28: Total Cost | J28: Install Margin | K28: Selling Price
B29: REMOVAL AND DISPOSAL | C29: 0 | D29: 0 | E29: 0 | F29: 0 | G29: 0 | I29: =SUM(C29:G29) -> 0 | J29: =$D$8 -> 0.15 | K29: =I29/(1-J29) -> 0
B30: INSTALL SECONDARY STEEL SUBSTRUCTURE | C30: 0 | D30: 0 | E30: 0 | F30: 0 | G30: 0 | I30: =SUM(C30:G30) -> 0 | J30: =$D$8 -> 0.15 | K30: =I30/(1-J30) -> 0
B31: INSTALL LED DISPLAYS | C31: 8703.13 | D31: 0 | E31: 0 | F31: 0 | G31: 0 | I31: =SUM(C31:G31) -> 8703.13 | J31: =$D$8 -> 0.15 | K31: =I31/(1-J31) -> 10238.976
B32: INSTALL CLADDING AND TRIM | C32: 0 | D32: 0 | E32: 0 | F32: 0 | G32: 0 | I32: =SUM(C32:G32) -> 0 | J32: =$D$8 -> 0.15 | K32: =I32/(1-J32) -> 0
B33: HEAVY EQUIPMENT | C33: 0 | D33: 0 | E33: 0 | F33: 0 | G33: 0 | I33: =SUM(C33:G33) -> 0 | J33: =$D$8 -> 0.15 | K33: =I33/(1-J33) -> 0
B34: PM/GENERAL CONDITIONS/TRAVEL | C34: 20882.35 | D34: 0 | E34: 0 | F34: 0 | G34: 0 | I34: =SUM(C34:G34) -> 20882.35 | J34: =$D$8 -> 0.15 | K34: =I34/(1-J34) -> 24567.471
B35: SUBTOTAL | I35: =SUM(I29:I34) -> 29585.48 | K35: =SUM(K29:K34) -> 34806.447
B37: Electrical and Data - Materials and Subcontracting | C37: Subcontractor 1 | D37: Subcontractor 2 | E37: Subcontractor 3 | F37: Selected | G37: Additional Contingency | I37: Total Cost | J37: Install Margin | K37: Selling Price
B38: ELECTRICAL MATERIALS | C38: 8703.13 | D38: 0 | E38: 0 | F38: 0 | G38: 0 | I38: =SUM(C38:G38) -> 8703.13 | J38: =$D$9 -> 0.15 | K38: =I38/(1-J38) -> 10238.976
B39: DATA MATERIALS | C39: 0 | D39: 0 | E39: 0 | F39: 0 | G39: 0 | I39: =SUM(C39:G39) -> 0 | J39: =$D$9 -> 0.15 | K39: =I39/(1-J39) -> 0
B40: ELECTRICAL LABOR | C40: 0 | D40: 0 | E40: 0 | F40: 0 | G40: 0 | I40: =SUM(C40:G40) -> 0 | J40: =$D$9 -> 0.15 | K40: =I40/(1-J40) -> 0
B41: DATA LABOR | C41: 0 | D41: 0 | E41: 0 | F41: 0 | G41: 0 | I41: =SUM(C41:G41) -> 0 | J41: =$D$9 -> 0.15 | K41: =I41/(1-J41) -> 0
B42: SUB PANEL | C42: 0 | D42: 0 | E42: 0 | F42: 0 | G42: 0 | I42: =SUM(C42:G42) -> 0 | J42: =$D$9 -> 0.15 | K42: =I42/(1-J42) -> 0
B43: MISC | C43: 0 | D43: 0 | E43: 0 | F43: 0 | G43: 0 | I43: =SUM(C43:G43) -> 0 | J43: =$D$9 -> 0.15 | K43: =I43/(1-J43) -> 0
B44: SUBTOTAL | I44: =SUM(I38:I43) -> 8703.13 | K44: =SUM(K38:K43) -> 10238.976
B46: Submittals, Engineering, and Permits | C46: Subcontractor 1 | D46: Subcontractor 2 | E46: Subcontractor 3 | F46: Selected | G46: Additional Contingency | I46: Total Cost | J46: Install Margin | K46: Selling Price
B47: STRUCTURAL ENGINEERING | C47: 4705.88 | D47: 0 | E47: 0 | F47: 0 | G47: 0 | I47: =SUM(C47:G47) -> 4705.88 | J47: =$D$11 -> 0.15 | K47: =I47/(1-J47) -> 5536.3294
B48: STRUCTURAL CERTIFICATION | C48: 0 | D48: 0 | E48: 0 | F48: 0 | G48: 0 | I48: =SUM(C48:G48) -> 0 | J48: =$D$11 -> 0.15 | K48: =I48/(1-J48) -> 0
B49: ELECTRICAL ENGINEERING | C49: 0 | D49: 0 | E49: 0 | F49: 0 | G49: 0 | I49: =SUM(C49:G49) -> 0 | J49: =$D$11 -> 0.15 | K49: =I49/(1-J49) -> 0
B50: ELECTRICAL CERTIFICATION | C50: 0 | D50: 0 | E50: 0 | F50: 0 | G50: 0 | I50: =SUM(C50:G50) -> 0 | J50: =$D$11 -> 0.15 | K50: =I50/(1-J50) -> 0
B51: PERMITS | C51: 0 | D51: 0 | E51: 0 | F51: 0 | G51: 0 | I51: =SUM(C51:G51) -> 0 | J51: =$D$11 -> 0.15 | K51: =I51/(1-J51) -> 0
B52: SUBTOTAL | I52: =SUM(I47:I51) -> 4705.88 | K52: =SUM(K47:K51) -> 5536.3294
B54: ZONE GRAND TOTAL | I54: =I26+I35+I44+I52 -> 45083.24 | K54: =K26+K35+K44+K52 -> 53039.106

Sheet Underpass 2 - Install
A3: Project Name: WTC Digital Signage Upgrade
A4: 2026-03-31
A5: Revised By: ANC Proposal Engine
C7: Linked Margin Assignment
C8: Install Margin | D8: 0.15
C9: Electrical Margin | D9: 0.15
C10: ANC Margin | D10: 0.15
C11: Engineering and Permits | D11: 0.15
B15: Underpass 2
B16: Height | C16: Width | D16: Total Sq. Ft | E16: QTY
B17: 7.48 | C17: 29.92 | D17: 223.8 | E17: 1
B19: Structural Materials: | C19: Subcontractor 1 | D19: Subcontractor 2 | E19: Subcontractor 3 | F19: Selected | G19: Additional Contingency | I19: Total Cost | J19: Install Margin | K19: Selling Price
B20: FABRICATE PRIMARY STEEL | C20: 0 | D20: 0 | E20: 0 | F20: 0 | G20: 0 | I20: =SUM(C20:G20) -> 0 | J20: =$D$8 -> 0.15 | K20: =I20/(1-J20) -> 0
B21: SUPPLY AND INSTALL PRIMARY PLYWOOD | C21: 0 | D21: 0 | E21: 0 | F21: 0 | G21: 0 | I21: =SUM(C21:G21) -> 0 | J21: =$D$8 -> 0.15 | K21: =I21/(1-J21) -> 0
B22: FABRICATE SECONDARY STEEL SUBSTRUCTURE | C22: 4102.5 | D22: 0 | E22: 0 | F22: 0 | G22: 0 | I22: =SUM(C22:G22) -> 4102.5 | J22: =$D$8 -> 0.15 | K22: =I22/(1-J22) -> 4826.4706
B23: FABRICATE CLADDING AND TRIM | C23: 0 | D23: 0 | E23: 0 | F23: 0 | G23: 0 | I23: =SUM(C23:G23) -> 0 | J23: =$D$8 -> 0.15 | K23: =I23/(1-J23) -> 0
B24: OTHER SCOPE ITEM | C24: 0 | D24: 0 | E24: 0 | F24: 0 | G24: 0 | I24: =SUM(C24:G24) -> 0 | J24: =$D$8 -> 0.15 | K24: =I24/(1-J24) -> 0
B25: OTHER SCOPE ITEM | C25: 0 | D25: 0 | E25: 0 | F25: 0 | G25: 0 | I25: =SUM(C25:G25) -> 0 | J25: =$D$8 -> 0.15 | K25: =I25/(1-J25) -> 0
B26: SUBTOTAL | I26: =SUM(I20:I25) -> 4102.5 | K26: =SUM(K20:K25) -> 4826.4706
B28: Structural Labor and LED Installation | C28: Subcontractor 1 | D28: Subcontractor 2 | E28: Subcontractor 3 | F28: Selected | G28: Additional Contingency | I28: Total Cost | J28: Install Margin | K28: Selling Price
B29: REMOVAL AND DISPOSAL | C29: 0 | D29: 0 | E29: 0 | F29: 0 | G29: 0 | I29: =SUM(C29:G29) -> 0 | J29: =$D$8 -> 0.15 | K29: =I29/(1-J29) -> 0
B30: INSTALL SECONDARY STEEL SUBSTRUCTURE | C30: 0 | D30: 0 | E30: 0 | F30: 0 | G30: 0 | I30: =SUM(C30:G30) -> 0 | J30: =$D$8 -> 0.15 | K30: =I30/(1-J30) -> 0
B31: INSTALL LED DISPLAYS | C31: 17093.75 | D31: 0 | E31: 0 | F31: 0 | G31: 0 | I31: =SUM(C31:G31) -> 17093.75 | J31: =$D$8 -> 0.15 | K31: =I31/(1-J31) -> 20110.294
B32: INSTALL CLADDING AND TRIM | C32: 0 | D32: 0 | E32: 0 | F32: 0 | G32: 0 | I32: =SUM(C32:G32) -> 0 | J32: =$D$8 -> 0.15 | K32: =I32/(1-J32) -> 0
B33: HEAVY EQUIPMENT | C33: 0 | D33: 0 | E33: 0 | F33: 0 | G33: 0 | I33: =SUM(C33:G33) -> 0 | J33: =$D$8 -> 0.15 | K33: =I33/(1-J33) -> 0
B34: PM/GENERAL CONDITIONS/TRAVEL | C34: 20882.35 | D34: 0 | E34: 0 | F34: 0 | G34: 0 | I34: =SUM(C34:G34) -> 20882.35 | J34: =$D$8 -> 0.15 | K34: =I34/(1-J34) -> 24567.471
B35: SUBTOTAL | I35: =SUM(I29:I34) -> 37976.1 | K35: =SUM(K29:K34) -> 44677.765
B37: Electrical and Data - Materials and Subcontracting | C37: Subcontractor 1 | D37: Subcontractor 2 | E37: Subcontractor 3 | F37: Selected | G37: Additional Contingency | I37: Total Cost | J37: Install Margin | K37: Selling Price
B38: ELECTRICAL MATERIALS | C38: 17093.75 | D38: 0 | E38: 0 | F38: 0 | G38: 0 | I38: =SUM(C38:G38) -> 17093.75 | J38: =$D$9 -> 0.15 | K38: =I38/(1-J38) -> 20110.294
B39: DATA MATERIALS | C39: 0 | D39: 0 | E39: 0 | F39: 0 | G39: 0 | I39: =SUM(C39:G39) -> 0 | J39: =$D$9 -> 0.15 | K39: =I39/(1-J39) -> 0
B40: ELECTRICAL LABOR | C40: 0 | D40: 0 | E40: 0 | F40: 0 | G40: 0 | I40: =SUM(C40:G40) -> 0 | J40: =$D$9 -> 0.15 | K40: =I40/(1-J40) -> 0
B41: DATA LABOR | C41: 0 | D41: 0 | E41: 0 | F41: 0 | G41: 0 | I41: =SUM(C41:G41) -> 0 | J41: =$D$9 -> 0.15 | K41: =I41/(1-J41) -> 0
B42: SUB PANEL | C42: 0 | D42: 0 | E42: 0 | F42: 0 | G42: 0 | I42: =SUM(C42:G42) -> 0 | J42: =$D$9 -> 0.15 | K42: =I42/(1-J42) -> 0
B43: MISC | C43: 0 | D43: 0 | E43: 0 | F43: 0 | G43: 0 | I43: =SUM(C43:G43) -> 0 | J43: =$D$9 -> 0.15 | K43: =I43/(1-J43) -> 0
B44: SUBTOTAL | I44: =SUM(I38:I43) -> 17093.75 | K44: =SUM(K38:K43) -> 20110.294
B46: Submittals, Engineering, and Permits | C46: Subcontractor 1 | D46: Subcontractor 2 | E46: Subcontractor 3 | F46: Selected | G46: Additional Contingency | I46: Total Cost | J46: Install Margin | K46: Selling Price
B47: STRUCTURAL ENGINEERING | C47: 4705.88 | D47: 0 | E47: 0 | F47: 0 | G47: 0 | I47: =SUM(C47:G47) -> 4705.88 | J47: =$D$11 -> 0.15 | K47: =I47/(1-J47) -> 5536.3294
B48: STRUCTURAL CERTIFICATION | C48: 0 | D48: 0 | E48: 0 | F48: 0 | G48: 0 | I48: =SUM(C48:G48) -> 0 | J48: =$D$11 -> 0.15 | K48: =I48/(1-J48) -> 0
B49: ELECTRICAL ENGINEERING | C49: 0 | D49: 0 | E49: 0 | F49: 0 | G49: 0 | I49: =SUM(C49:G49) -> 0 | J49: =$D$11 -> 0.15 | K49: =I49/(1-J49) -> 0
B50: ELECTRICAL CERTIFICATION | C50: 0 | D50: 0 | E50: 0 | F50: 0 | G50: 0 | I50: =SUM(C50:G50) -> 0 | J50: =$D$11 -> 0.15 | K50: =I50/(1-J50) -> 0
B51: PERMITS | C51: 0 | D51: 0 | E51: 0 | F51: 0 | G51: 0 | I51: =SUM(C51:G51) -> 0 | J51: =$D$11 -> 0.15 | K51: =I51/(1-J51) -> 0
B52: SUBTOTAL | I52: =SUM(I47:I51) -> 4705.88 | K52: =SUM(K47:K51) -> 5536.3294
B54: ZONE GRAND TOTAL | I54: =I26+I35+I44+I52 -> 63878.23 | K54: =K26+K35+K44+K52 -> 75150.859

Sheet Underpass 3 - Install
A3: Project Name: WTC Digital Signage Upgrade
A4: 2026-03-31
A5: Revised By: ANC Proposal Engine
C7: Linked Margin Assignment
C8: Install Margin | D8: 0.15
C9: Electrical Margin | D9: 0.15
C10: ANC Margin | D10: 0.15
C11: Engineering and Permits | D11: 0.15
B15: Underpass 3
B16: Height | C16: Width | D16: Total Sq. Ft | E16: QTY
B17: 7.48 | C17: 29.92 | D17: 223.8 | E17: 1
B19: Structural Materials: | C19: Subcontractor 1 | D19: Subcontractor 2 | E19: Subcontractor 3 | F19: Selected | G19: Additional Contingency | I19: Total Cost | J19: Install Margin | K19: Selling Price
B20: FABRICATE PRIMARY STEEL | C20: 0 | D20: 0 | E20: 0 | F20: 0 | G20: 0 | I20: =SUM(C20:G20) -> 0 | J20: =$D$8 -> 0.15 | K20: =I20/(1-J20) -> 0
B21: SUPPLY AND INSTALL PRIMARY PLYWOOD | C21: 0 | D21: 0 | E21: 0 | F21: 0 | G21: 0 | I21: =SUM(C21:G21) -> 0 | J21: =$D$8 -> 0.15 | K21: =I21/(1-J21) -> 0
B22: FABRICATE SECONDARY STEEL SUBSTRUCTURE | C22: 4102.5 | D22: 0 | E22: 0 | F22: 0 | G22: 0 | I22: =SUM(C22:G22) -> 4102.5 | J22: =$D$8 -> 0.15 | K22: =I22/(1-J22) -> 4826.4706
B23: FABRICATE CLADDING AND TRIM | C23: 0 | D23: 0 | E23: 0 | F23: 0 | G23: 0 | I23: =SUM(C23:G23) -> 0 | J23: =$D$8 -> 0.15 | K23: =I23/(1-J23) -> 0
B24: OTHER SCOPE ITEM | C24: 0 | D24: 0 | E24: 0 | F24: 0 | G24: 0 | I24: =SUM(C24:G24) -> 0 | J24: =$D$8 -> 0.15 | K24: =I24/(1-J24) -> 0
B25: OTHER SCOPE ITEM | C25: 0 | D25: 0 | E25: 0 | F25: 0 | G25: 0 | I25: =SUM(C25:G25) -> 0 | J25: =$D$8 -> 0.15 | K25: =I25/(1-J25) -> 0
B26: SUBTOTAL | I26: =SUM(I20:I25) -> 4102.5 | K26: =SUM(K20:K25) -> 4826.4706
B28: Structural Labor and LED Installation | C28: Subcontractor 1 | D28: Subcontractor 2 | E28: Subcontractor 3 | F28: Selected | G28: Additional Contingency | I28: Total Cost | J28: Install Margin | K28: Selling Price
B29: REMOVAL AND DISPOSAL | C29: 0 | D29: 0 | E29: 0 | F29: 0 | G29: 0 | I29: =SUM(C29:G29) -> 0 | J29: =$D$8 -> 0.15 | K29: =I29/(1-J29) -> 0
B30: INSTALL SECONDARY STEEL SUBSTRUCTURE | C30: 0 | D30: 0 | E30: 0 | F30: 0 | G30: 0 | I30: =SUM(C30:G30) -> 0 | J30: =$D$8 -> 0.15 | K30: =I30/(1-J30) -> 0
B31: INSTALL LED DISPLAYS | C31: 17093.75 | D31: 0 | E31: 0 | F31: 0 | G31: 0 | I31: =SUM(C31:G31) -> 17093.75 | J31: =$D$8 -> 0.15 | K31: =I31/(1-J31) -> 20110.294
B32: INSTALL CLADDING AND TRIM | C32: 0 | D32: 0 | E32: 0 | F32: 0 | G32: 0 | I32: =SUM(C32:G32) -> 0 | J32: =$D$8 -> 0.15 | K32: =I32/(1-J32) -> 0
B33: HEAVY EQUIPMENT | C33: 0 | D33: 0 | E33: 0 | F33: 0 | G33: 0 | I33: =SUM(C33:G33) -> 0 | J33: =$D$8 -> 0.15 | K33: =I33/(1-J33) -> 0
B34: PM/GENERAL CONDITIONS/TRAVEL | C34: 20882.35 | D34: 0 | E34: 0 | F34: 0 | G34: 0 | I34: =SUM(C34:G34) -> 20882.35 | J34: =$D$8 -> 0.15 | K34: =I34/(1-J34) -> 24567.471
B35: SUBTOTAL | I35: =SUM(I29:I34) -> 37976.1 | K35: =SUM(K29:K34) -> 44677.765
B37: Electrical and Data - Materials and Subcontracting | C37: Subcontractor 1 | D37: Subcontractor 2 | E37: Subcontractor 3 | F37: Selected | G37: Additional Contingency | I37: Total Cost | J37: Install Margin | K37: Selling Price
B38: ELECTRICAL MATERIALS | C38: 17093.75 | D38: 0 | E38: 0 | F38: 0 | G38: 0 | I38: =SUM(C38:G38) -> 17093.75 | J38: =$D$9 -> 0.15 | K38: =I38/(1-J38) -> 20110.294
B39: DATA MATERIALS | C39: 0 | D39: 0 | E39: 0 | F39: 0 | G39: 0 | I39: =SUM(C39:G39) -> 0 | J39: =$D$9 -> 0.15 | K39: =I39/(1-J39) -> 0
B40: ELECTRICAL LABOR | C40: 0 | D40: 0 | E40: 0 | F40: 0 | G40: 0 | I40: =SUM(C40:G40) -> 0 | J40: =$D$9 -> 0.15 | K40: =I40/(1-J40) -> 0
B41: DATA LABOR | C41: 0 | D41: 0 | E41: 0 | F41: 0 | G41: 0 | I41: =SUM(C41:G41) -> 0 | J41: =$D$9 -> 0.15 | K41: =I41/(1-J41) -> 0
B42: SUB PANEL | C42: 0 | D42: 0 | E42: 0 | F42: 0 | G42: 0 | I42: =SUM(C42:G42) -> 0 | J42: =$D$9 -> 0.15 | K42: =I42/(1-J42) -> 0
B43: MISC | C43: 0 | D43: 0 | E43: 0 | F43: 0 | G43: 0 | I43: =SUM(C43:G43) -> 0 | J43: =$D$9 -> 0.15 | K43: =I43/(1-J43) -> 0
B44: SUBTOTAL | I44: =SUM(I38:I43) -> 17093.75 | K44: =SUM(K38:K43) -> 20110.294
B46: Submittals, Engineering, and Permits | C46: Subcontractor 1 | D46: Subcontractor 2 | E46: Subcontractor 3 | F46: Selected | G46: Additional Contingency | I46: Total Cost | J46: Install Margin | K46: Selling Price
B47: STRUCTURAL ENGINEERING | C47: 4705.88 | D47: 0 | E47: 0 | F47: 0 | G47: 0 | I47: =SUM(C47:G47) -> 4705.88 | J47: =$D$11 -> 0.15 | K47: =I47/(1-J47) -> 5536.3294
B48: STRUCTURAL CERTIFICATION | C48: 0 | D48: 0 | E48: 0 | F48: 0 | G48: 0 | I48: =SUM(C48:G48) -> 0 | J48: =$D$11 -> 0.15 | K48: =I48/(1-J48) -> 0
B49: ELECTRICAL ENGINEERING | C49: 0 | D49: 0 | E49: 0 | F49: 0 | G49: 0 | I49: =SUM(C49:G49) -> 0 | J49: =$D$11 -> 0.15 | K49: =I49/(1-J49) -> 0
B50: ELECTRICAL CERTIFICATION | C50: 0 | D50: 0 | E50: 0 | F50: 0 | G50: 0 | I50: =SUM(C50:G50) -> 0 | J50: =$D$11 -> 0.15 | K50: =I50/(1-J50) -> 0
B51: PERMITS | C51: 0 | D51: 0 | E51: 0 | F51: 0 | G51: 0 | I51: =SUM(C51:G51) -> 0 | J51: =$D$11 -> 0.15 | K51: =I51/(1-J51) -> 0
B52: SUBTOTAL | I52: =SUM(I47:I51) -> 4705.88 | K52: =SUM(K47:K51) -> 5536.3294
B54: ZONE GRAND TOTAL | I54: =I26+I35+I44+I52 -> 63878.23 | K54: =K26+K35+K44+K52 -> 75150.859

Sheet Underpass 4 - Install
A3: Project Name: WTC Digital Signage Upgrade
A4: 2026-03-31
A5: Revised By: ANC Proposal Engine
C7: Linked Margin Assignment
C8: Install Margin | D8: 0.15
C9: Electrical Margin | D9: 0.15
C10: ANC Margin | D10: 0.15
C11: Engineering and Permits | D11: 0.15
B15: Underpass 4
B16: Height | C16: Width | D16: Total Sq. Ft | E16: QTY
B17: 12.6 | C17: 29.92 | D17: 376.99 | E17: 1
B19: Structural Materials: | C19: Subcontractor 1 | D19: Subcontractor 2 | E19: Subcontractor 3 | F19: Selected | G19: Additional Contingency | I19: Total Cost | J19: Install Margin | K19: Selling Price
B20: FABRICATE PRIMARY STEEL | C20: 0 | D20: 0 | E20: 0 | F20: 0 | G20: 0 | I20: =SUM(C20:G20) -> 0 | J20: =$D$8 -> 0.15 | K20: =I20/(1-J20) -> 0
B21: SUPPLY AND INSTALL PRIMARY PLYWOOD | C21: 0 | D21: 0 | E21: 0 | F21: 0 | G21: 0 | I21: =SUM(C21:G21) -> 0 | J21: =$D$8 -> 0.15 | K21: =I21/(1-J21) -> 0
B22: FABRICATE SECONDARY STEEL SUBSTRUCTURE | C22: 6907.5 | D22: 0 | E22: 0 | F22: 0 | G22: 0 | I22: =SUM(C22:G22) -> 6907.5 | J22: =$D$8 -> 0.15 | K22: =I22/(1-J22) -> 8126.4706
B23: FABRICATE CLADDING AND TRIM | C23: 0 | D23: 0 | E23: 0 | F23: 0 | G23: 0 | I23: =SUM(C23:G23) -> 0 | J23: =$D$8 -> 0.15 | K23: =I23/(1-J23) -> 0
B24: OTHER SCOPE ITEM | C24: 0 | D24: 0 | E24: 0 | F24: 0 | G24: 0 | I24: =SUM(C24:G24) -> 0 | J24: =$D$8 -> 0.15 | K24: =I24/(1-J24) -> 0
B25: OTHER SCOPE ITEM | C25: 0 | D25: 0 | E25: 0 | F25: 0 | G25: 0 | I25: =SUM(C25:G25) -> 0 | J25: =$D$8 -> 0.15 | K25: =I25/(1-J25) -> 0
B26: SUBTOTAL | I26: =SUM(I20:I25) -> 6907.5 | K26: =SUM(K20:K25) -> 8126.4706
B28: Structural Labor and LED Installation | C28: Subcontractor 1 | D28: Subcontractor 2 | E28: Subcontractor 3 | F28: Selected | G28: Additional Contingency | I28: Total Cost | J28: Install Margin | K28: Selling Price
B29: REMOVAL AND DISPOSAL | C29: 0 | D29: 0 | E29: 0 | F29: 0 | G29: 0 | I29: =SUM(C29:G29) -> 0 | J29: =$D$8 -> 0.15 | K29: =I29/(1-J29) -> 0
B30: INSTALL SECONDARY STEEL SUBSTRUCTURE | C30: 0 | D30: 0 | E30: 0 | F30: 0 | G30: 0 | I30: =SUM(C30:G30) -> 0 | J30: =$D$8 -> 0.15 | K30: =I30/(1-J30) -> 0
B31: INSTALL LED DISPLAYS | C31: 28781.25 | D31: 0 | E31: 0 | F31: 0 | G31: 0 | I31: =SUM(C31:G31) -> 28781.25 | J31: =$D$8 -> 0.15 | K31: =I31/(1-J31) -> 33860.294
B32: INSTALL CLADDING AND TRIM | C32: 0 | D32: 0 | E32: 0 | F32: 0 | G32: 0 | I32: =SUM(C32:G32) -> 0 | J32: =$D$8 -> 0.15 | K32: =I32/(1-J32) -> 0
B33: HEAVY EQUIPMENT | C33: 0 | D33: 0 | E33: 0 | F33: 0 | G33: 0 | I33: =SUM(C33:G33) -> 0 | J33: =$D$8 -> 0.15 | K33: =I33/(1-J33) -> 0
B34: PM/GENERAL CONDITIONS/TRAVEL | C34: 20882.35 | D34: 0 | E34: 0 | F34: 0 | G34: 0 | I34: =SUM(C34:G34) -> 20882.35 | J34: =$D$8 -> 0.15 | K34: =I34/(1-J34) -> 24567.471
B35: SUBTOTAL | I35: =SUM(I29:I34) -> 49663.6 | K35: =SUM(K29:K34) -> 58427.765
B37: Electrical and Data - Materials and Subcontracting | C37: Subcontractor 1 | D37: Subcontractor 2 | E37: Subcontractor 3 | F37: Selected | G37: Additional Contingency | I37: Total Cost | J37: Install Margin | K37: Selling Price
B38: ELECTRICAL MATERIALS | C38: 28781.25 | D38: 0 | E38: 0 | F38: 0 | G38: 0 | I38: =SUM(C38:G38) -> 28781.25 | J38: =$D$9 -> 0.15 | K38: =I38/(1-J38) -> 33860.294
B39: DATA MATERIALS | C39: 0 | D39: 0 | E39: 0 | F39: 0 | G39: 0 | I39: =SUM(C39:G39) -> 0 | J39: =$D$9 -> 0.15 | K39: =I39/(1-J39) -> 0
B40: ELECTRICAL LABOR | C40: 0 | D40: 0 | E40: 0 | F40: 0 | G40: 0 | I40: =SUM(C40:G40) -> 0 | J40: =$D$9 -> 0.15 | K40: =I40/(1-J40) -> 0
B41: DATA LABOR | C41: 0 | D41: 0 | E41: 0 | F41: 0 | G41: 0 | I41: =SUM(C41:G41) -> 0 | J41: =$D$9 -> 0.15 | K41: =I41/(1-J41) -> 0
B42: SUB PANEL | C42: 0 | D42: 0 | E42: 0 | F42: 0 | G42: 0 | I42: =SUM(C42:G42) -> 0 | J42: =$D$9 -> 0.15 | K42: =I42/(1-J42) -> 0
B43: MISC | C43: 0 | D43: 0 | E43: 0 | F43: 0 | G43: 0 | I43: =SUM(C43:G43) -> 0 | J43: =$D$9 -> 0.15 | K43: =I43/(1-J43) -> 0
B44: SUBTOTAL | I44: =SUM(I38:I43) -> 28781.25 | K44: =SUM(K38:K43) -> 33860.294
B46: Submittals, Engineering, and Permits | C46: Subcontractor 1 | D46: Subcontractor 2 | E46: Subcontractor 3 | F46: Selected | G46: Additional Contingency | I46: Total Cost | J46: Install Margin | K46: Selling Price
B47: STRUCTURAL ENGINEERING | C47: 4705.88 | D47: 0 | E47: 0 | F47: 0 | G47: 0 | I47: =SUM(C47:G47) -> 4705.88 | J47: =$D$11 -> 0.15 | K47: =I47/(1-J47) -> 5536.3294
B48: STRUCTURAL CERTIFICATION | C48: 0 | D48: 0 | E48: 0 | F48: 0 | G48: 0 | I48: =SUM(C48:G48) -> 0 | J48: =$D$11 -> 0.15 | K48: =I48/(1-J48) -> 0
B49: ELECTRICAL ENGINEERING | C49: 0 | D49: 0 | E49: 0 | F49: 0 | G49: 0 | I49: =SUM(C49:G49) -> 0 | J49: =$D$11 -> 0.15 | K49: =I49/(1-J49) -> 0
B50: ELECTRICAL CERTIFICATION | C50: 0 | D50: 0 | E50: 0 | F50: 0 | G50: 0 | I50: =SUM(C50:G50) -> 0 | J50: =$D$11 -> 0.15 | K50: =I50/(1-J50) -> 0
B51: PERMITS | C51: 0 | D51: 0 | E51: 0 | F51: 0 | G51: 0 | I51: =SUM(C51:G51) -> 0 | J51: =$D$11 -> 0.15 | K51: =I51/(1-J51) -> 0
B52: SUBTOTAL | I52: =SUM(I47:I51) -> 4705.88 | K52: =SUM(K47:K51) -> 5536.3294
B54: ZONE GRAND TOTAL | I54: =I26+I35+I44+I52 -> 90058.23 | K54: =K26+K35+K44+K52 -> 105950.86

Sheet Concourse - Install
A3: Project Name: WTC Digital Signage Upgrade
A4: 2026-03-31
A5: Revised By: ANC Proposal Engine
C7: Linked Margin Assignment
C8: Install Margin | D8: 0.15
C9: Electrical Margin | D9: 0.15
C10: ANC Margin | D10: 0.15
C11: Engineering and Permits | D11: 0.15
B15: Concourse
B16: Height | C16: Width | D16: Total Sq. Ft | E16: QTY
B17: 9.45 | C17: 280.31 | D17: 2648.93 | E17: 1
B19: Structural Materials: | C19: Subcontractor 1 | D19: Subcontractor 2 | E19: Subcontractor 3 | F19: Selected | G19: Additional Contingency | I19: Total Cost | J19: Install Margin | K19: Selling Price
B20: FABRICATE PRIMARY STEEL | C20: 0 | D20: 0 | E20: 0 | F20: 0 | G20: 0 | I20: =SUM(C20:G20) -> 0 | J20: =$D$8 -> 0.15 | K20: =I20/(1-J20) -> 0
B21: SUPPLY AND INSTALL PRIMARY PLYWOOD | C21: 0 | D21: 0 | E21: 0 | F21: 0 | G21: 0 | I21: =SUM(C21:G21) -> 0 | J21: =$D$8 -> 0.15 | K21: =I21/(1-J21) -> 0
B22: FABRICATE SECONDARY STEEL SUBSTRUCTURE | C22: 48536.25 | D22: 0 | E22: 0 | F22: 0 | G22: 0 | I22: =SUM(C22:G22) -> 48536.25 | J22: =$D$8 -> 0.15 | K22: =I22/(1-J22) -> 57101.471
B23: FABRICATE CLADDING AND TRIM | C23: 0 | D23: 0 | E23: 0 | F23: 0 | G23: 0 | I23: =SUM(C23:G23) -> 0 | J23: =$D$8 -> 0.15 | K23: =I23/(1-J23) -> 0
B24: OTHER SCOPE ITEM | C24: 0 | D24: 0 | E24: 0 | F24: 0 | G24: 0 | I24: =SUM(C24:G24) -> 0 | J24: =$D$8 -> 0.15 | K24: =I24/(1-J24) -> 0
B25: OTHER SCOPE ITEM | C25: 0 | D25: 0 | E25: 0 | F25: 0 | G25: 0 | I25: =SUM(C25:G25) -> 0 | J25: =$D$8 -> 0.15 | K25: =I25/(1-J25) -> 0
B26: SUBTOTAL | I26: =SUM(I20:I25) -> 48536.25 | K26: =SUM(K20:K25) -> 57101.471
B28: Structural Labor and LED Installation | C28: Subcontractor 1 | D28: Subcontractor 2 | E28: Subcontractor 3 | F28: Selected | G28: Additional Contingency | I28: Total Cost | J28: Install Margin | K28: Selling Price
B29: REMOVAL AND DISPOSAL | C29: 0 | D29: 0 | E29: 0 | F29: 0 | G29: 0 | I29: =SUM(C29:G29) -> 0 | J29: =$D$8 -> 0.15 | K29: =I29/(1-J29) -> 0
B30: INSTALL SECONDARY STEEL SUBSTRUCTURE | C30: 0 | D30: 0 | E30: 0 | F30: 0 | G30: 0 | I30: =SUM(C30:G30) -> 0 | J30: =$D$8 -> 0.15 | K30: =I30/(1-J30) -> 0
B31: INSTALL LED DISPLAYS | C31: 202234.38 | D31: 0 | E31: 0 | F31: 0 | G31: 0 | I31: =SUM(C31:G31) -> 202234.38 | J31: =$D$8 -> 0.15 | K31: =I31/(1-J31) -> 237922.8
B32: INSTALL CLADDING AND TRIM | C32: 0 | D32: 0 | E32: 0 | F32: 0 | G32: 0 | I32: =SUM(C32:G32) -> 0 | J32: =$D$8 -> 0.15 | K32: =I32/(1-J32) -> 0
B33: HEAVY EQUIPMENT | C33: 0 | D33: 0 | E33: 0 | F33: 0 | G33: 0 | I33: =SUM(C33:G33) -> 0 | J33: =$D$8 -> 0.15 | K33: =I33/(1-J33) -> 0
B34: PM/GENERAL CONDITIONS/TRAVEL | C34: 20882.35 | D34: 0 | E34: 0 | F34: 0 | G34: 0 | I34: =SUM(C34:G34) -> 20882.35 | J34: =$D$8 -> 0.15 | K34: =I34/(1-J34) -> 24567.471
B35: SUBTOTAL | I35: =SUM(I29:I34) -> 223116.73 | K35: =SUM(K29:K34) -> 262490.27
B37: Electrical and Data - Materials and Subcontracting | C37: Subcontractor 1 | D37: Subcontractor 2 | E37: Subcontractor 3 | F37: Selected | G37: Additional Contingency | I37: Total Cost | J37: Install Margin | K37: Selling Price
B38: ELECTRICAL MATERIALS | C38: 202234.38 | D38: 0 | E38: 0 | F38: 0 | G38: 0 | I38: =SUM(C38:G38) -> 202234.38 | J38: =$D$9 -> 0.15 | K38: =I38/(1-J38) -> 237922.8
B39: DATA MATERIALS | C39: 0 | D39: 0 | E39: 0 | F39: 0 | G39: 0 | I39: =SUM(C39:G39) -> 0 | J39: =$D$9 -> 0.15 | K39: =I39/(1-J39) -> 0
B40: ELECTRICAL LABOR | C40: 0 | D40: 0 | E40: 0 | F40: 0 | G40: 0 | I40: =SUM(C40:G40) -> 0 | J40: =$D$9 -> 0.15 | K40: =I40/(1-J40) -> 0
B41: DATA LABOR | C41: 0 | D41: 0 | E41: 0 | F41: 0 | G41: 0 | I41: =SUM(C41:G41) -> 0 | J41: =$D$9 -> 0.15 | K41: =I41/(1-J41) -> 0
B42: SUB PANEL | C42: 0 | D42: 0 | E42: 0 | F42: 0 | G42: 0 | I42: =SUM(C42:G42) -> 0 | J42: =$D$9 -> 0.15 | K42: =I42/(1-J42) -> 0
B43: MISC | C43: 0 | D43: 0 | E43: 0 | F43: 0 | G43: 0 | I43: =SUM(C43:G43) -> 0 | J43: =$D$9 -> 0.15 | K43: =I43/(1-J43) -> 0
B44: SUBTOTAL | I44: =SUM(I38:I43) -> 202234.38 | K44: =SUM(K38:K43) -> 237922.8
B46: Submittals, Engineering, and Permits | C46: Subcontractor 1 | D46: Subcontractor 2 | E46: Subcontractor 3 | F46: Selected | G46: Additional Contingency | I46: Total Cost | J46: Install Margin | K46: Selling Price
B47: STRUCTURAL ENGINEERING | C47: 4705.88 | D47: 0 | E47: 0 | F47: 0 | G47: 0 | I47: =SUM(C47:G47) -> 4705.88 | J47: =$D$11 -> 0.15 | K47: =I47/(1-J47) -> 5536.3294
B48: STRUCTURAL CERTIFICATION | C48: 0 | D48: 0 | E48: 0 | F48: 0 | G48: 0 | I48: =SUM(C48:G48) -> 0 | J48: =$D$11 -> 0.15 | K48: =I48/(1-J48) -> 0
B49: ELECTRICAL ENGINEERING | C49: 0 | D49: 0 | E49: 0 | F49: 0 | G49: 0 | I49: =SUM(C49:G49) -> 0 | J49: =$D$11 -> 0.15 | K49: =I49/(1-J49) -> 0
B50: ELECTRICAL CERTIFICATION | C50: 0 | D50: 0 | E50: 0 | F50: 0 | G50: 0 | I50: =SUM(C50:G50) -> 0 | J50: =$D$11 -> 0.15 | K50: =I50/(1-J50) -> 0
B51: PERMITS | C51: 0 | D51: 0 | E51: 0 | F51: 0 | G51: 0 | I51: =SUM(C51:G51) -> 0 | J51: =$D$11 -> 0.15 | K51: =I51/(1-J51) -> 0
B52: SUBTOTAL | I52: =SUM(I47:I51) -> 4705.88 | K52: =SUM(K47:K51) -> 5536.3294
B54: ZONE GRAND TOTAL | I54: =I26+I35+I44+I52 -> 478593.24 | K54: =K26+K35+K44+K52 -> 563050.87

Sheet T4-B1 (6-9) - Install
A3: Project Name: WTC Digital Signage Upgrade
A4: 2026-03-31
A5: Revised By: ANC Proposal Engine
C7: Linked Margin Assignment
C8: Install Margin | D8: 0.15
C9: Electrical Margin | D9: 0.15
C10: ANC Margin | D10: 0.15
C11: Engineering and Permits | D11: 0.15
B15: T4-B1 (6-9)
B16: Height | C16: Width | D16: Total Sq. Ft | E16: QTY
B17: 7.87 | C17: 8.66 | D17: 272.62 | E17: 4
B19: Structural Materials: | C19: Subcontractor 1 | D19: Subcontractor 2 | E19: Subcontractor 3 | F19: Selected | G19: Additional Contingency | I19: Total Cost | J19: Install Margin | K19: Selling Price
B20: FABRICATE PRIMARY STEEL | C20: 0 | D20: 0 | E20: 0 | F20: 0 | G20: 0 | I20: =SUM(C20:G20) -> 0 | J20: =$D$8 -> 0.15 | K20: =I20/(1-J20) -> 0
B21: SUPPLY AND INSTALL PRIMARY PLYWOOD | C21: 0 | D21: 0 | E21: 0 | F21: 0 | G21: 0 | I21: =SUM(C21:G21) -> 0 | J21: =$D$8 -> 0.15 | K21: =I21/(1-J21) -> 0
B22: FABRICATE SECONDARY STEEL SUBSTRUCTURE | C22: 4995 | D22: 0 | E22: 0 | F22: 0 | G22: 0 | I22: =SUM(C22:G22) -> 4995 | J22: =$D$8 -> 0.15 | K22: =I22/(1-J22) -> 5876.4706
B23: FABRICATE CLADDING AND TRIM | C23: 0 | D23: 0 | E23: 0 | F23: 0 | G23: 0 | I23: =SUM(C23:G23) -> 0 | J23: =$D$8 -> 0.15 | K23: =I23/(1-J23) -> 0
B24: OTHER SCOPE ITEM | C24: 0 | D24: 0 | E24: 0 | F24: 0 | G24: 0 | I24: =SUM(C24:G24) -> 0 | J24: =$D$8 -> 0.15 | K24: =I24/(1-J24) -> 0
B25: OTHER SCOPE ITEM | C25: 0 | D25: 0 | E25: 0 | F25: 0 | G25: 0 | I25: =SUM(C25:G25) -> 0 | J25: =$D$8 -> 0.15 | K25: =I25/(1-J25) -> 0
B26: SUBTOTAL | I26: =SUM(I20:I25) -> 4995 | K26: =SUM(K20:K25) -> 5876.4706
B28: Structural Labor and LED Installation | C28: Subcontractor 1 | D28: Subcontractor 2 | E28: Subcontractor 3 | F28: Selected | G28: Additional Contingency | I28: Total Cost | J28: Install Margin | K28: Selling Price
B29: REMOVAL AND DISPOSAL | C29: 0 | D29: 0 | E29: 0 | F29: 0 | G29: 0 | I29: =SUM(C29:G29) -> 0 | J29: =$D$8 -> 0.15 | K29: =I29/(1-J29) -> 0
B30: INSTALL SECONDARY STEEL SUBSTRUCTURE | C30: 0 | D30: 0 | E30: 0 | F30: 0 | G30: 0 | I30: =SUM(C30:G30) -> 0 | J30: =$D$8 -> 0.15 | K30: =I30/(1-J30) -> 0
B31: INSTALL LED DISPLAYS | C31: 20812.5 | D31: 0 | E31: 0 | F31: 0 | G31: 0 | I31: =SUM(C31:G31) -> 20812.5 | J31: =$D$8 -> 0.15 | K31: =I31/(1-J31) -> 24485.294
B32: INSTALL CLADDING AND TRIM | C32: 0 | D32: 0 | E32: 0 | F32: 0 | G32: 0 | I32: =SUM(C32:G32) -> 0 | J32: =$D$8 -> 0.15 | K32: =I32/(1-J32) -> 0
B33: HEAVY EQUIPMENT | C33: 0 | D33: 0 | E33: 0 | F33: 0 | G33: 0 | I33: =SUM(C33:G33) -> 0 | J33: =$D$8 -> 0.15 | K33: =I33/(1-J33) -> 0
B34: PM/GENERAL CONDITIONS/TRAVEL | C34: 20882.35 | D34: 0 | E34: 0 | F34: 0 | G34: 0 | I34: =SUM(C34:G34) -> 20882.35 | J34: =$D$8 -> 0.15 | K34: =I34/(1-J34) -> 24567.471
B35: SUBTOTAL | I35: =SUM(I29:I34) -> 41694.85 | K35: =SUM(K29:K34) -> 49052.765
B37: Electrical and Data - Materials and Subcontracting | C37: Subcontractor 1 | D37: Subcontractor 2 | E37: Subcontractor 3 | F37: Selected | G37: Additional Contingency | I37: Total Cost | J37: Install Margin | K37: Selling Price
B38: ELECTRICAL MATERIALS | C38: 20812.5 | D38: 0 | E38: 0 | F38: 0 | G38: 0 | I38: =SUM(C38:G38) -> 20812.5 | J38: =$D$9 -> 0.15 | K38: =I38/(1-J38) -> 24485.294
B39: DATA MATERIALS | C39: 0 | D39: 0 | E39: 0 | F39: 0 | G39: 0 | I39: =SUM(C39:G39) -> 0 | J39: =$D$9 -> 0.15 | K39: =I39/(1-J39) -> 0
B40: ELECTRICAL LABOR | C40: 0 | D40: 0 | E40: 0 | F40: 0 | G40: 0 | I40: =SUM(C40:G40) -> 0 | J40: =$D$9 -> 0.15 | K40: =I40/(1-J40) -> 0
B41: DATA LABOR | C41: 0 | D41: 0 | E41: 0 | F41: 0 | G41: 0 | I41: =SUM(C41:G41) -> 0 | J41: =$D$9 -> 0.15 | K41: =I41/(1-J41) -> 0
B42: SUB PANEL | C42: 0 | D42: 0 | E42: 0 | F42: 0 | G42: 0 | I42: =SUM(C42:G42) -> 0 | J42: =$D$9 -> 0.15 | K42: =I42/(1-J42) -> 0
B43: MISC | C43: 0 | D43: 0 | E43: 0 | F43: 0 | G43: 0 | I43: =SUM(C43:G43) -> 0 | J43: =$D$9 -> 0.15 | K43: =I43/(1-J43) -> 0
B44: SUBTOTAL | I44: =SUM(I38:I43) -> 20812.5 | K44: =SUM(K38:K43) -> 24485.294
B46: Submittals, Engineering, and Permits | C46: Subcontractor 1 | D46: Subcontractor 2 | E46: Subcontractor 3 | F46: Selected | G46: Additional Contingency | I46: Total Cost | J46: Install Margin | K46: Selling Price
B47: STRUCTURAL ENGINEERING | C47: 4705.88 | D47: 0 | E47: 0 | F47: 0 | G47: 0 | I47: =SUM(C47:G47) -> 4705.88 | J47: =$D$11 -> 0.15 | K47: =I47/(1-J47) -> 5536.3294
B48: STRUCTURAL CERTIFICATION | C48: 0 | D48: 0 | E48: 0 | F48: 0 | G48: 0 | I48: =SUM(C48:G48) -> 0 | J48: =$D$11 -> 0.15 | K48: =I48/(1-J48) -> 0
B49: ELECTRICAL ENGINEERING | C49: 0 | D49: 0 | E49: 0 | F49: 0 | G49: 0 | I49: =SUM(C49:G49) -> 0 | J49: =$D$11 -> 0.15 | K49: =I49/(1-J49) -> 0
B50: ELECTRICAL CERTIFICATION | C50: 0 | D50: 0 | E50: 0 | F50: 0 | G50: 0 | I50: =SUM(C50:G50) -> 0 | J50: =$D$11 -> 0.15 | K50: =I50/(1-J50) -> 0
B51: PERMITS | C51: 0 | D51: 0 | E51: 0 | F51: 0 | G51: 0 | I51: =SUM(C51:G51) -> 0 | J51: =$D$11 -> 0.15 | K51: =I51/(1-J51) -> 0
B52: SUBTOTAL | I52: =SUM(I47:I51) -> 4705.88 | K52: =SUM(K47:K51) -> 5536.3294
B54: ZONE GRAND TOTAL | I54: =I26+I35+I44+I52 -> 72208.23 | K54: =K26+K35+K44+K52 -> 84950.859

Sheet T4-B2 (10-18) - Install
A3: Project Name: WTC Digital Signage Upgrade
A4: 2026-03-31
A5: Revised By: ANC Proposal Engine
C7: Linked Margin Assignment
C8: Install Margin | D8: 0.15
C9: Electrical Margin | D9: 0.15
C10: ANC Margin | D10: 0.15
C11: Engineering and Permits | D11: 0.15
B15: T4-B2 (10-18)
B16: Height | C16: Width | D16: Total Sq. Ft | E16: QTY
B17: 7.87 | C17: 8.66 | D17: 613.39 | E17: 9
B19: Structural Materials: | C19: Subcontractor 1 | D19: Subcontractor 2 | E19: Subcontractor 3 | F19: Selected | G19: Additional Contingency | I19: Total Cost | J19: Install Margin | K19: Selling Price
B20: FABRICATE PRIMARY STEEL | C20: 0 | D20: 0 | E20: 0 | F20: 0 | G20: 0 | I20: =SUM(C20:G20) -> 0 | J20: =$D$8 -> 0.15 | K20: =I20/(1-J20) -> 0
B21: SUPPLY AND INSTALL PRIMARY PLYWOOD | C21: 0 | D21: 0 | E21: 0 | F21: 0 | G21: 0 | I21: =SUM(C21:G21) -> 0 | J21: =$D$8 -> 0.15 | K21: =I21/(1-J21) -> 0
B22: FABRICATE SECONDARY STEEL SUBSTRUCTURE | C22: 11238.75 | D22: 0 | E22: 0 | F22: 0 | G22: 0 | I22: =SUM(C22:G22) -> 11238.75 | J22: =$D$8 -> 0.15 | K22: =I22/(1-J22) -> 13222.059
B23: FABRICATE CLADDING AND TRIM | C23: 0 | D23: 0 | E23: 0 | F23: 0 | G23: 0 | I23: =SUM(C23:G23) -> 0 | J23: =$D$8 -> 0.15 | K23: =I23/(1-J23) -> 0
B24: OTHER SCOPE ITEM | C24: 0 | D24: 0 | E24: 0 | F24: 0 | G24: 0 | I24: =SUM(C24:G24) -> 0 | J24: =$D$8 -> 0.15 | K24: =I24/(1-J24) -> 0
B25: OTHER SCOPE ITEM | C25: 0 | D25: 0 | E25: 0 | F25: 0 | G25: 0 | I25: =SUM(C25:G25) -> 0 | J25: =$D$8 -> 0.15 | K25: =I25/(1-J25) -> 0
B26: SUBTOTAL | I26: =SUM(I20:I25) -> 11238.75 | K26: =SUM(K20:K25) -> 13222.059
B28: Structural Labor and LED Installation | C28: Subcontractor 1 | D28: Subcontractor 2 | E28: Subcontractor 3 | F28: Selected | G28: Additional Contingency | I28: Total Cost | J28: Install Margin | K28: Selling Price
B29: REMOVAL AND DISPOSAL | C29: 0 | D29: 0 | E29: 0 | F29: 0 | G29: 0 | I29: =SUM(C29:G29) -> 0 | J29: =$D$8 -> 0.15 | K29: =I29/(1-J29) -> 0
B30: INSTALL SECONDARY STEEL SUBSTRUCTURE | C30: 0 | D30: 0 | E30: 0 | F30: 0 | G30: 0 | I30: =SUM(C30:G30) -> 0 | J30: =$D$8 -> 0.15 | K30: =I30/(1-J30) -> 0
B31: INSTALL LED DISPLAYS | C31: 46828.13 | D31: 0 | E31: 0 | F31: 0 | G31: 0 | I31: =SUM(C31:G31) -> 46828.13 | J31: =$D$8 -> 0.15 | K31: =I31/(1-J31) -> 55091.918
B32: INSTALL CLADDING AND TRIM | C32: 0 | D32: 0 | E32: 0 | F32: 0 | G32: 0 | I32: =SUM(C32:G32) -> 0 | J32: =$D$8 -> 0.15 | K32: =I32/(1-J32) -> 0
B33: HEAVY EQUIPMENT | C33: 0 | D33: 0 | E33: 0 | F33: 0 | G33: 0 | I33: =SUM(C33:G33) -> 0 | J33: =$D$8 -> 0.15 | K33: =I33/(1-J33) -> 0
B34: PM/GENERAL CONDITIONS/TRAVEL | C34: 20882.35 | D34: 0 | E34: 0 | F34: 0 | G34: 0 | I34: =SUM(C34:G34) -> 20882.35 | J34: =$D$8 -> 0.15 | K34: =I34/(1-J34) -> 24567.471
B35: SUBTOTAL | I35: =SUM(I29:I34) -> 67710.48 | K35: =SUM(K29:K34) -> 79659.388
B37: Electrical and Data - Materials and Subcontracting | C37: Subcontractor 1 | D37: Subcontractor 2 | E37: Subcontractor 3 | F37: Selected | G37: Additional Contingency | I37: Total Cost | J37: Install Margin | K37: Selling Price
B38: ELECTRICAL MATERIALS | C38: 46828.13 | D38: 0 | E38: 0 | F38: 0 | G38: 0 | I38: =SUM(C38:G38) -> 46828.13 | J38: =$D$9 -> 0.15 | K38: =I38/(1-J38) -> 55091.918
B39: DATA MATERIALS | C39: 0 | D39: 0 | E39: 0 | F39: 0 | G39: 0 | I39: =SUM(C39:G39) -> 0 | J39: =$D$9 -> 0.15 | K39: =I39/(1-J39) -> 0
B40: ELECTRICAL LABOR | C40: 0 | D40: 0 | E40: 0 | F40: 0 | G40: 0 | I40: =SUM(C40:G40) -> 0 | J40: =$D$9 -> 0.15 | K40: =I40/(1-J40) -> 0
B41: DATA LABOR | C41: 0 | D41: 0 | E41: 0 | F41: 0 | G41: 0 | I41: =SUM(C41:G41) -> 0 | J41: =$D$9 -> 0.15 | K41: =I41/(1-J41) -> 0
B42: SUB PANEL | C42: 0 | D42: 0 | E42: 0 | F42: 0 | G42: 0 | I42: =SUM(C42:G42) -> 0 | J42: =$D$9 -> 0.15 | K42: =I42/(1-J42) -> 0
B43: MISC | C43: 0 | D43: 0 | E43: 0 | F43: 0 | G43: 0 | I43: =SUM(C43:G43) -> 0 | J43: =$D$9 -> 0.15 | K43: =I43/(1-J43) -> 0
B44: SUBTOTAL | I44: =SUM(I38:I43) -> 46828.13 | K44: =SUM(K38:K43) -> 55091.918
B46: Submittals, Engineering, and Permits | C46: Subcontractor 1 | D46: Subcontractor 2 | E46: Subcontractor 3 | F46: Selected | G46: Additional Contingency | I46: Total Cost | J46: Install Margin | K46: Selling Price
B47: STRUCTURAL ENGINEERING | C47: 4705.88 | D47: 0 | E47: 0 | F47: 0 | G47: 0 | I47: =SUM(C47:G47) -> 4705.88 | J47: =$D$11 -> 0.15 | K47: =I47/(1-J47) -> 5536.3294
B48: STRUCTURAL CERTIFICATION | C48: 0 | D48: 0 | E48: 0 | F48: 0 | G48: 0 | I48: =SUM(C48:G48) -> 0 | J48: =$D$11 -> 0.15 | K48: =I48/(1-J48) -> 0
B49: ELECTRICAL ENGINEERING | C49: 0 | D49: 0 | E49: 0 | F49: 0 | G49: 0 | I49: =SUM(C49:G49) -> 0 | J49: =$D$11 -> 0.15 | K49: =I49/(1-J49) -> 0
B50: ELECTRICAL CERTIFICATION | C50: 0 | D50: 0 | E50: 0 | F50: 0 | G50: 0 | I50: =SUM(C50:G50) -> 0 | J50: =$D$11 -> 0.15 | K50: =I50/(1-J50) -> 0
B51: PERMITS | C51: 0 | D51: 0 | E51: 0 | F51: 0 | G51: 0 | I51: =SUM(C51:G51) -> 0 | J51: =$D$11 -> 0.15 | K51: =I51/(1-J51) -> 0
B52: SUBTOTAL | I52: =SUM(I47:I51) -> 4705.88 | K52: =SUM(K47:K51) -> 5536.3294
B54: ZONE GRAND TOTAL | I54: =I26+I35+I44+I52 -> 130483.24 | K54: =K26+K35+K44+K52 -> 153509.69

Sheet T4 Lobby Elevator - Install
A3: Project Name: WTC Digital Signage Upgrade
A4: 2026-03-31
A5: Revised By: ANC Proposal Engine
C7: Linked Margin Assignment
C8: Install Margin | D8: 0.15
C9: Electrical Margin | D9: 0.15
C10: ANC Margin | D10: 0.15
C11: Engineering and Permits | D11: 0.15
B15: T4 Lobby Elevator
B16: Height | C16: Width | D16: Total Sq. Ft | E16: QTY
B17: 71.6 | C17: 5.5 | D17: 393.8 | E17: 1
B19: Structural Materials: | C19: Subcontractor 1 | D19: Subcontractor 2 | E19: Subcontractor 3 | F19: Selected | G19: Additional Contingency | I19: Total Cost | J19: Install Margin | K19: Selling Price
B20: FABRICATE PRIMARY STEEL | C20: 0 | D20: 0 | E20: 0 | F20: 0 | G20: 0 | I20: =SUM(C20:G20) -> 0 | J20: =$D$8 -> 0.15 | K20: =I20/(1-J20) -> 0
B21: SUPPLY AND INSTALL PRIMARY PLYWOOD | C21: 0 | D21: 0 | E21: 0 | F21: 0 | G21: 0 | I21: =SUM(C21:G21) -> 0 | J21: =$D$8 -> 0.15 | K21: =I21/(1-J21) -> 0
B22: FABRICATE SECONDARY STEEL SUBSTRUCTURE | C22: 7222.5 | D22: 0 | E22: 0 | F22: 0 | G22: 0 | I22: =SUM(C22:G22) -> 7222.5 | J22: =$D$8 -> 0.15 | K22: =I22/(1-J22) -> 8497.0588
B23: FABRICATE CLADDING AND TRIM | C23: 0 | D23: 0 | E23: 0 | F23: 0 | G23: 0 | I23: =SUM(C23:G23) -> 0 | J23: =$D$8 -> 0.15 | K23: =I23/(1-J23) -> 0
B24: OTHER SCOPE ITEM | C24: 0 | D24: 0 | E24: 0 | F24: 0 | G24: 0 | I24: =SUM(C24:G24) -> 0 | J24: =$D$8 -> 0.15 | K24: =I24/(1-J24) -> 0
B25: OTHER SCOPE ITEM | C25: 0 | D25: 0 | E25: 0 | F25: 0 | G25: 0 | I25: =SUM(C25:G25) -> 0 | J25: =$D$8 -> 0.15 | K25: =I25/(1-J25) -> 0
B26: SUBTOTAL | I26: =SUM(I20:I25) -> 7222.5 | K26: =SUM(K20:K25) -> 8497.0588
B28: Structural Labor and LED Installation | C28: Subcontractor 1 | D28: Subcontractor 2 | E28: Subcontractor 3 | F28: Selected | G28: Additional Contingency | I28: Total Cost | J28: Install Margin | K28: Selling Price
B29: REMOVAL AND DISPOSAL | C29: 0 | D29: 0 | E29: 0 | F29: 0 | G29: 0 | I29: =SUM(C29:G29) -> 0 | J29: =$D$8 -> 0.15 | K29: =I29/(1-J29) -> 0
B30: INSTALL SECONDARY STEEL SUBSTRUCTURE | C30: 0 | D30: 0 | E30: 0 | F30: 0 | G30: 0 | I30: =SUM(C30:G30) -> 0 | J30: =$D$8 -> 0.15 | K30: =I30/(1-J30) -> 0
B31: INSTALL LED DISPLAYS | C31: 30093.75 | D31: 0 | E31: 0 | F31: 0 | G31: 0 | I31: =SUM(C31:G31) -> 30093.75 | J31: =$D$8 -> 0.15 | K31: =I31/(1-J31) -> 35404.412
B32: INSTALL CLADDING AND TRIM | C32: 0 | D32: 0 | E32: 0 | F32: 0 | G32: 0 | I32: =SUM(C32:G32) -> 0 | J32: =$D$8 -> 0.15 | K32: =I32/(1-J32) -> 0
B33: HEAVY EQUIPMENT | C33: 0 | D33: 0 | E33: 0 | F33: 0 | G33: 0 | I33: =SUM(C33:G33) -> 0 | J33: =$D$8 -> 0.15 | K33: =I33/(1-J33) -> 0
B34: PM/GENERAL CONDITIONS/TRAVEL | C34: 20882.35 | D34: 0 | E34: 0 | F34: 0 | G34: 0 | I34: =SUM(C34:G34) -> 20882.35 | J34: =$D$8 -> 0.15 | K34: =I34/(1-J34) -> 24567.471
B35: SUBTOTAL | I35: =SUM(I29:I34) -> 50976.1 | K35: =SUM(K29:K34) -> 59971.882
B37: Electrical and Data - Materials and Subcontracting | C37: Subcontractor 1 | D37: Subcontractor 2 | E37: Subcontractor 3 | F37: Selected | G37: Additional Contingency | I37: Total Cost | J37: Install Margin | K37: Selling Price
B38: ELECTRICAL MATERIALS | C38: 30093.75 | D38: 0 | E38: 0 | F38: 0 | G38: 0 | I38: =SUM(C38:G38) -> 30093.75 | J38: =$D$9 -> 0.15 | K38: =I38/(1-J38) -> 35404.412
B39: DATA MATERIALS | C39: 0 | D39: 0 | E39: 0 | F39: 0 | G39: 0 | I39: =SUM(C39:G39) -> 0 | J39: =$D$9 -> 0.15 | K39: =I39/(1-J39) -> 0
B40: ELECTRICAL LABOR | C40: 0 | D40: 0 | E40: 0 | F40: 0 | G40: 0 | I40: =SUM(C40:G40) -> 0 | J40: =$D$9 -> 0.15 | K40: =I40/(1-J40) -> 0
B41: DATA LABOR | C41: 0 | D41: 0 | E41: 0 | F41: 0 | G41: 0 | I41: =SUM(C41:G41) -> 0 | J41: =$D$9 -> 0.15 | K41: =I41/(1-J41) -> 0
B42: SUB PANEL | C42: 0 | D42: 0 | E42: 0 | F42: 0 | G42: 0 | I42: =SUM(C42:G42) -> 0 | J42: =$D$9 -> 0.15 | K42: =I42/(1-J42) -> 0
B43: MISC | C43: 0 | D43: 0 | E43: 0 | F43: 0 | G43: 0 | I43: =SUM(C43:G43) -> 0 | J43: =$D$9 -> 0.15 | K43: =I43/(1-J43) -> 0
B44: SUBTOTAL | I44: =SUM(I38:I43) -> 30093.75 | K44: =SUM(K38:K43) -> 35404.412
B46: Submittals, Engineering, and Permits | C46: Subcontractor 1 | D46: Subcontractor 2 | E46: Subcontractor 3 | F46: Selected | G46: Additional Contingency | I46: Total Cost | J46: Install Margin | K46: Selling Price
B47: STRUCTURAL ENGINEERING | C47: 4705.88 | D47: 0 | E47: 0 | F47: 0 | G47: 0 | I47: =SUM(C47:G47) -> 4705.88 | J47: =$D$11 -> 0.15 | K47: =I47/(1-J47) -> 5536.3294
B48: STRUCTURAL CERTIFICATION | C48: 0 | D48: 0 | E48: 0 | F48: 0 | G48: 0 | I48: =SUM(C48:G48) -> 0 | J48: =$D$11 -> 0.15 | K48: =I48/(1-J48) -> 0
B49: ELECTRICAL ENGINEERING | C49: 0 | D49: 0 | E49: 0 | F49: 0 | G49: 0 | I49: =SUM(C49:G49) -> 0 | J49: =$D$11 -> 0.15 | K49: =I49/(1-J49) -> 0
B50: ELECTRICAL CERTIFICATION | C50: 0 | D50: 0 | E50: 0 | F50: 0 | G50: 0 | I50: =SUM(C50:G50) -> 0 | J50: =$D$11 -> 0.15 | K50: =I50/(1-J50) -> 0
B51: PERMITS | C51: 0 | D51: 0 | E51: 0 | F51: 0 | G51: 0 | I51: =SUM(C51:G51) -> 0 | J51: =$D$11 -> 0.15 | K51: =I51/(1-J51) -> 0
B52: SUBTOTAL | I52: =SUM(I47:I51) -> 4705.88 | K52: =SUM(K47:K51) -> 5536.3294
B54: ZONE GRAND TOTAL | I54: =I26+I35+I44+I52 -> 92998.23 | K54: =K26+K35+K44+K52 -> 109409.68

Sheet T2-B1M Screen 20 - Install
A3: Project Name: WTC Digital Signage Upgrade
A4: 2026-03-31
A5: Revised By: ANC Proposal Engine
C7: Linked Margin Assignment
C8: Install Margin | D8: 0.15
C9: Electrical Margin | D9: 0.15
C10: ANC Margin | D10: 0.15
C11: Engineering and Permits | D11: 0.15
B15: T2-B1M Screen 20
B16: Height | C16: Width | D16: Total Sq. Ft | E16: QTY
B17: 7.91 | C17: 16.5 | D17: 130.52 | E17: 1
B19: Structural Materials: | C19: Subcontractor 1 | D19: Subcontractor 2 | E19: Subcontractor 3 | F19: Selected | G19: Additional Contingency | I19: Total Cost | J19: Install Margin | K19: Selling Price
B20: FABRICATE PRIMARY STEEL | C20: 0 | D20: 0 | E20: 0 | F20: 0 | G20: 0 | I20: =SUM(C20:G20) -> 0 | J20: =$D$8 -> 0.15 | K20: =I20/(1-J20) -> 0
B21: SUPPLY AND INSTALL PRIMARY PLYWOOD | C21: 0 | D21: 0 | E21: 0 | F21: 0 | G21: 0 | I21: =SUM(C21:G21) -> 0 | J21: =$D$8 -> 0.15 | K21: =I21/(1-J21) -> 0
B22: FABRICATE SECONDARY STEEL SUBSTRUCTURE | C22: 2392.5 | D22: 0 | E22: 0 | F22: 0 | G22: 0 | I22: =SUM(C22:G22) -> 2392.5 | J22: =$D$8 -> 0.15 | K22: =I22/(1-J22) -> 2814.7059
B23: FABRICATE CLADDING AND TRIM | C23: 0 | D23: 0 | E23: 0 | F23: 0 | G23: 0 | I23: =SUM(C23:G23) -> 0 | J23: =$D$8 -> 0.15 | K23: =I23/(1-J23) -> 0
B24: OTHER SCOPE ITEM | C24: 0 | D24: 0 | E24: 0 | F24: 0 | G24: 0 | I24: =SUM(C24:G24) -> 0 | J24: =$D$8 -> 0.15 | K24: =I24/(1-J24) -> 0
B25: OTHER SCOPE ITEM | C25: 0 | D25: 0 | E25: 0 | F25: 0 | G25: 0 | I25: =SUM(C25:G25) -> 0 | J25: =$D$8 -> 0.15 | K25: =I25/(1-J25) -> 0
B26: SUBTOTAL | I26: =SUM(I20:I25) -> 2392.5 | K26: =SUM(K20:K25) -> 2814.7059
B28: Structural Labor and LED Installation | C28: Subcontractor 1 | D28: Subcontractor 2 | E28: Subcontractor 3 | F28: Selected | G28: Additional Contingency | I28: Total Cost | J28: Install Margin | K28: Selling Price
B29: REMOVAL AND DISPOSAL | C29: 0 | D29: 0 | E29: 0 | F29: 0 | G29: 0 | I29: =SUM(C29:G29) -> 0 | J29: =$D$8 -> 0.15 | K29: =I29/(1-J29) -> 0
B30: INSTALL SECONDARY STEEL SUBSTRUCTURE | C30: 0 | D30: 0 | E30: 0 | F30: 0 | G30: 0 | I30: =SUM(C30:G30) -> 0 | J30: =$D$8 -> 0.15 | K30: =I30/(1-J30) -> 0
B31: INSTALL LED DISPLAYS | C31: 9968.75 | D31: 0 | E31: 0 | F31: 0 | G31: 0 | I31: =SUM(C31:G31) -> 9968.75 | J31: =$D$8 -> 0.15 | K31: =I31/(1-J31) -> 11727.941
B32: INSTALL CLADDING AND TRIM | C32: 0 | D32: 0 | E32: 0 | F32: 0 | G32: 0 | I32: =SUM(C32:G32) -> 0 | J32: =$D$8 -> 0.15 | K32: =I32/(1-J32) -> 0
B33: HEAVY EQUIPMENT | C33: 0 | D33: 0 | E33: 0 | F33: 0 | G33: 0 | I33: =SUM(C33:G33) -> 0 | J33: =$D$8 -> 0.15 | K33: =I33/(1-J33) -> 0
B34: PM/GENERAL CONDITIONS/TRAVEL | C34: 20882.35 | D34: 0 | E34: 0 | F34: 0 | G34: 0 | I34: =SUM(C34:G34) -> 20882.35 | J34: =$D$8 -> 0.15 | K34: =I34/(1-J34) -> 24567.471
B35: SUBTOTAL | I35: =SUM(I29:I34) -> 30851.1 | K35: =SUM(K29:K34) -> 36295.412
B37: Electrical and Data - Materials and Subcontracting | C37: Subcontractor 1 | D37: Subcontractor 2 | E37: Subcontractor 3 | F37: Selected | G37: Additional Contingency | I37: Total Cost | J37: Install Margin | K37: Selling Price
B38: ELECTRICAL MATERIALS | C38: 9968.75 | D38: 0 | E38: 0 | F38: 0 | G38: 0 | I38: =SUM(C38:G38) -> 9968.75 | J38: =$D$9 -> 0.15 | K38: =I38/(1-J38) -> 11727.941
B39: DATA MATERIALS | C39: 0 | D39: 0 | E39: 0 | F39: 0 | G39: 0 | I39: =SUM(C39:G39) -> 0 | J39: =$D$9 -> 0.15 | K39: =I39/(1-J39) -> 0
B40: ELECTRICAL LABOR | C40: 0 | D40: 0 | E40: 0 | F40: 0 | G40: 0 | I40: =SUM(C40:G40) -> 0 | J40: =$D$9 -> 0.15 | K40: =I40/(1-J40) -> 0
B41: DATA LABOR | C41: 0 | D41: 0 | E41: 0 | F41: 0 | G41: 0 | I41: =SUM(C41:G41) -> 0 | J41: =$D$9 -> 0.15 | K41: =I41/(1-J41) -> 0
B42: SUB PANEL | C42: 0 | D42: 0 | E42: 0 | F42: 0 | G42: 0 | I42: =SUM(C42:G42) -> 0 | J42: =$D$9 -> 0.15 | K42: =I42/(1-J42) -> 0
B43: MISC | C43: 0 | D43: 0 | E43: 0 | F43: 0 | G43: 0 | I43: =SUM(C43:G43) -> 0 | J43: =$D$9 -> 0.15 | K43: =I43/(1-J43) -> 0
B44: SUBTOTAL | I44: =SUM(I38:I43) -> 9968.75 | K44: =SUM(K38:K43) -> 11727.941
B46: Submittals, Engineering, and Permits | C46: Subcontractor 1 | D46: Subcontractor 2 | E46: Subcontractor 3 | F46: Selected | G46: Additional Contingency | I46: Total Cost | J46: Install Margin | K46: Selling Price
B47: STRUCTURAL ENGINEERING | C47: 4705.88 | D47: 0 | E47: 0 | F47: 0 | G47: 0 | I47: =SUM(C47:G47) -> 4705.88 | J47: =$D$11 -> 0.15 | K47: =I47/(1-J47) -> 5536.3294
B48: STRUCTURAL CERTIFICATION | C48: 0 | D48: 0 | E48: 0 | F48: 0 | G48: 0 | I48: =SUM(C48:G48) -> 0 | J48: =$D$11 -> 0.15 | K48: =I48/(1-J48) -> 0
B49: ELECTRICAL ENGINEERING | C49: 0 | D49: 0 | E49: 0 | F49: 0 | G49: 0 | I49: =SUM(C49:G49) -> 0 | J49: =$D$11 -> 0.15 | K49: =I49/(1-J49) -> 0
B50: ELECTRICAL CERTIFICATION | C50: 0 | D50: 0 | E50: 0 | F50: 0 | G50: 0 | I50: =SUM(C50:G50) -> 0 | J50: =$D$11 -> 0.15 | K50: =I50/(1-J50) -> 0
B51: PERMITS | C51: 0 | D51: 0 | E51: 0 | F51: 0 | G51: 0 | I51: =SUM(C51:G51) -> 0 | J51: =$D$11 -> 0.15 | K51: =I51/(1-J51) -> 0
B52: SUBTOTAL | I52: =SUM(I47:I51) -> 4705.88 | K52: =SUM(K47:K51) -> 5536.3294
B54: ZONE GRAND TOTAL | I54: =I26+I35+I44+I52 -> 47918.23 | K54: =K26+K35+K44+K52 -> 56374.388

Sheet T2-B1M Screen 21 - Install
A3: Project Name: WTC Digital Signage Upgrade
A4: 2026-03-31
A5: Revised By: ANC Proposal Engine
C7: Linked Margin Assignment
C8: Install Margin | D8: 0.15
C9: Electrical Margin | D9: 0.15
C10: ANC Margin | D10: 0.15
C11: Engineering and Permits | D11: 0.15
B15: T2-B1M Screen 21
B16: Height | C16: Width | D16: Total Sq. Ft | E16: QTY
B17: 7.91 | C17: 11.83 | D17: 93.58 | E17: 1
B19: Structural Materials: | C19: Subcontractor 1 | D19: Subcontractor 2 | E19: Subcontractor 3 | F19: Selected | G19: Additional Contingency | I19: Total Cost | J19: Install Margin | K19: Selling Price
B20: FABRICATE PRIMARY STEEL | C20: 0 | D20: 0 | E20: 0 | F20: 0 | G20: 0 | I20: =SUM(C20:G20) -> 0 | J20: =$D$8 -> 0.15 | K20: =I20/(1-J20) -> 0
B21: SUPPLY AND INSTALL PRIMARY PLYWOOD | C21: 0 | D21: 0 | E21: 0 | F21: 0 | G21: 0 | I21: =SUM(C21:G21) -> 0 | J21: =$D$8 -> 0.15 | K21: =I21/(1-J21) -> 0
B22: FABRICATE SECONDARY STEEL SUBSTRUCTURE | C22: 1713.75 | D22: 0 | E22: 0 | F22: 0 | G22: 0 | I22: =SUM(C22:G22) -> 1713.75 | J22: =$D$8 -> 0.15 | K22: =I22/(1-J22) -> 2016.1765
B23: FABRICATE CLADDING AND TRIM | C23: 0 | D23: 0 | E23: 0 | F23: 0 | G23: 0 | I23: =SUM(C23:G23) -> 0 | J23: =$D$8 -> 0.15 | K23: =I23/(1-J23) -> 0
B24: OTHER SCOPE ITEM | C24: 0 | D24: 0 | E24: 0 | F24: 0 | G24: 0 | I24: =SUM(C24:G24) -> 0 | J24: =$D$8 -> 0.15 | K24: =I24/(1-J24) -> 0
B25: OTHER SCOPE ITEM | C25: 0 | D25: 0 | E25: 0 | F25: 0 | G25: 0 | I25: =SUM(C25:G25) -> 0 | J25: =$D$8 -> 0.15 | K25: =I25/(1-J25) -> 0
B26: SUBTOTAL | I26: =SUM(I20:I25) -> 1713.75 | K26: =SUM(K20:K25) -> 2016.1765
B28: Structural Labor and LED Installation | C28: Subcontractor 1 | D28: Subcontractor 2 | E28: Subcontractor 3 | F28: Selected | G28: Additional Contingency | I28: Total Cost | J28: Install Margin | K28: Selling Price
B29: REMOVAL AND DISPOSAL | C29: 0 | D29: 0 | E29: 0 | F29: 0 | G29: 0 | I29: =SUM(C29:G29) -> 0 | J29: =$D$8 -> 0.15 | K29: =I29/(1-J29) -> 0
B30: INSTALL SECONDARY STEEL SUBSTRUCTURE | C30: 0 | D30: 0 | E30: 0 | F30: 0 | G30: 0 | I30: =SUM(C30:G30) -> 0 | J30: =$D$8 -> 0.15 | K30: =I30/(1-J30) -> 0
B31: INSTALL LED DISPLAYS | C31: 7140.63 | D31: 0 | E31: 0 | F31: 0 | G31: 0 | I31: =SUM(C31:G31) -> 7140.63 | J31: =$D$8 -> 0.15 | K31: =I31/(1-J31) -> 8400.7412
B32: INSTALL CLADDING AND TRIM | C32: 0 | D32: 0 | E32: 0 | F32: 0 | G32: 0 | I32: =SUM(C32:G32) -> 0 | J32: =$D$8 -> 0.15 | K32: =I32/(1-J32) -> 0
B33: HEAVY EQUIPMENT | C33: 0 | D33: 0 | E33: 0 | F33: 0 | G33: 0 | I33: =SUM(C33:G33) -> 0 | J33: =$D$8 -> 0.15 | K33: =I33/(1-J33) -> 0
B34: PM/GENERAL CONDITIONS/TRAVEL | C34: 20882.35 | D34: 0 | E34: 0 | F34: 0 | G34: 0 | I34: =SUM(C34:G34) -> 20882.35 | J34: =$D$8 -> 0.15 | K34: =I34/(1-J34) -> 24567.471
B35: SUBTOTAL | I35: =SUM(I29:I34) -> 28022.98 | K35: =SUM(K29:K34) -> 32968.212
B37: Electrical and Data - Materials and Subcontracting | C37: Subcontractor 1 | D37: Subcontractor 2 | E37: Subcontractor 3 | F37: Selected | G37: Additional Contingency | I37: Total Cost | J37: Install Margin | K37: Selling Price
B38: ELECTRICAL MATERIALS | C38: 7140.63 | D38: 0 | E38: 0 | F38: 0 | G38: 0 | I38: =SUM(C38:G38) -> 7140.63 | J38: =$D$9 -> 0.15 | K38: =I38/(1-J38) -> 8400.7412
B39: DATA MATERIALS | C39: 0 | D39: 0 | E39: 0 | F39: 0 | G39: 0 | I39: =SUM(C39:G39) -> 0 | J39: =$D$9 -> 0.15 | K39: =I39/(1-J39) -> 0
B40: ELECTRICAL LABOR | C40: 0 | D40: 0 | E40: 0 | F40: 0 | G40: 0 | I40: =SUM(C40:G40) -> 0 | J40: =$D$9 -> 0.15 | K40: =I40/(1-J40) -> 0
B41: DATA LABOR | C41: 0 | D41: 0 | E41: 0 | F41: 0 | G41: 0 | I41: =SUM(C41:G41) -> 0 | J41: =$D$9 -> 0.15 | K41: =I41/(1-J41) -> 0
B42: SUB PANEL | C42: 0 | D42: 0 | E42: 0 | F42: 0 | G42: 0 | I42: =SUM(C42:G42) -> 0 | J42: =$D$9 -> 0.15 | K42: =I42/(1-J42) -> 0
B43: MISC | C43: 0 | D43: 0 | E43: 0 | F43: 0 | G43: 0 | I43: =SUM(C43:G43) -> 0 | J43: =$D$9 -> 0.15 | K43: =I43/(1-J43) -> 0
B44: SUBTOTAL | I44: =SUM(I38:I43) -> 7140.63 | K44: =SUM(K38:K43) -> 8400.7412
B46: Submittals, Engineering, and Permits | C46: Subcontractor 1 | D46: Subcontractor 2 | E46: Subcontractor 3 | F46: Selected | G46: Additional Contingency | I46: Total Cost | J46: Install Margin | K46: Selling Price
B47: STRUCTURAL ENGINEERING | C47: 4705.88 | D47: 0 | E47: 0 | F47: 0 | G47: 0 | I47: =SUM(C47:G47) -> 4705.88 | J47: =$D$11 -> 0.15 | K47: =I47/(1-J47) -> 5536.3294
B48: STRUCTURAL CERTIFICATION | C48: 0 | D48: 0 | E48: 0 | F48: 0 | G48: 0 | I48: =SUM(C48:G48) -> 0 | J48: =$D$11 -> 0.15 | K48: =I48/(1-J48) -> 0
B49: ELECTRICAL ENGINEERING | C49: 0 | D49: 0 | E49: 0 | F49: 0 | G49: 0 | I49: =SUM(C49:G49) -> 0 | J49: =$D$11 -> 0.15 | K49: =I49/(1-J49) -> 0
B50: ELECTRICAL CERTIFICATION | C50: 0 | D50: 0 | E50: 0 | F50: 0 | G50: 0 | I50: =SUM(C50:G50) -> 0 | J50: =$D$11 -> 0.15 | K50: =I50/(1-J50) -> 0
B51: PERMITS | C51: 0 | D51: 0 | E51: 0 | F51: 0 | G51: 0 | I51: =SUM(C51:G51) -> 0 | J51: =$D$11 -> 0.15 | K51: =I51/(1-J51) -> 0
B52: SUBTOTAL | I52: =SUM(I47:I51) -> 4705.88 | K52: =SUM(K47:K51) -> 5536.3294
B54: ZONE GRAND TOTAL | I54: =I26+I35+I44+I52 -> 41583.24 | K54: =K26+K35+K44+K52 -> 48921.459

Sheet T2-B1M Screen 22 - Install
A3: Project Name: WTC Digital Signage Upgrade
A4: 2026-03-31
A5: Revised By: ANC Proposal Engine
C7: Linked Margin Assignment
C8: Install Margin | D8: 0.15
C9: Electrical Margin | D9: 0.15
C10: ANC Margin | D10: 0.15
C11: Engineering and Permits | D11: 0.15
B15: T2-B1M Screen 22
B16: Height | C16: Width | D16: Total Sq. Ft | E16: QTY
B17: 7.91 | C17: 7.91 | D17: 62.57 | E17: 1
B19: Structural Materials: | C19: Subcontractor 1 | D19: Subcontractor 2 | E19: Subcontractor 3 | F19: Selected | G19: Additional Contingency | I19: Total Cost | J19: Install Margin | K19: Selling Price
B20: FABRICATE PRIMARY STEEL | C20: 0 | D20: 0 | E20: 0 | F20: 0 | G20: 0 | I20: =SUM(C20:G20) -> 0 | J20: =$D$8 -> 0.15 | K20: =I20/(1-J20) -> 0
B21: SUPPLY AND INSTALL PRIMARY PLYWOOD | C21: 0 | D21: 0 | E21: 0 | F21: 0 | G21: 0 | I21: =SUM(C21:G21) -> 0 | J21: =$D$8 -> 0.15 | K21: =I21/(1-J21) -> 0
B22: FABRICATE SECONDARY STEEL SUBSTRUCTURE | C22: 1147.5 | D22: 0 | E22: 0 | F22: 0 | G22: 0 | I22: =SUM(C22:G22) -> 1147.5 | J22: =$D$8 -> 0.15 | K22: =I22/(1-J22) -> 1350
B23: FABRICATE CLADDING AND TRIM | C23: 0 | D23: 0 | E23: 0 | F23: 0 | G23: 0 | I23: =SUM(C23:G23) -> 0 | J23: =$D$8 -> 0.15 | K23: =I23/(1-J23) -> 0
B24: OTHER SCOPE ITEM | C24: 0 | D24: 0 | E24: 0 | F24: 0 | G24: 0 | I24: =SUM(C24:G24) -> 0 | J24: =$D$8 -> 0.15 | K24: =I24/(1-J24) -> 0
B25: OTHER SCOPE ITEM | C25: 0 | D25: 0 | E25: 0 | F25: 0 | G25: 0 | I25: =SUM(C25:G25) -> 0 | J25: =$D$8 -> 0.15 | K25: =I25/(1-J25) -> 0
B26: SUBTOTAL | I26: =SUM(I20:I25) -> 1147.5 | K26: =SUM(K20:K25) -> 1350
B28: Structural Labor and LED Installation | C28: Subcontractor 1 | D28: Subcontractor 2 | E28: Subcontractor 3 | F28: Selected | G28: Additional Contingency | I28: Total Cost | J28: Install Margin | K28: Selling Price
B29: REMOVAL AND DISPOSAL | C29: 0 | D29: 0 | E29: 0 | F29: 0 | G29: 0 | I29: =SUM(C29:G29) -> 0 | J29: =$D$8 -> 0.15 | K29: =I29/(1-J29) -> 0
B30: INSTALL SECONDARY STEEL SUBSTRUCTURE | C30: 0 | D30: 0 | E30: 0 | F30: 0 | G30: 0 | I30: =SUM(C30:G30) -> 0 | J30: =$D$8 -> 0.15 | K30: =I30/(1-J30) -> 0
B31: INSTALL LED DISPLAYS | C31: 4781.25 | D31: 0 | E31: 0 | F31: 0 | G31: 0 | I31: =SUM(C31:G31) -> 4781.25 | J31: =$D$8 -> 0.15 | K31: =I31/(1-J31) -> 5625
B32: INSTALL CLADDING AND TRIM | C32: 0 | D32: 0 | E32: 0 | F32: 0 | G32: 0 | I32: =SUM(C32:G32) -> 0 | J32: =$D$8 -> 0.15 | K32: =I32/(1-J32) -> 0
B33: HEAVY EQUIPMENT | C33: 0 | D33: 0 | E33: 0 | F33: 0 | G33: 0 | I33: =SUM(C33:G33) -> 0 | J33: =$D$8 -> 0.15 | K33: =I33/(1-J33) -> 0
B34: PM/GENERAL CONDITIONS/TRAVEL | C34: 20882.35 | D34: 0 | E34: 0 | F34: 0 | G34: 0 | I34: =SUM(C34:G34) -> 20882.35 | J34: =$D$8 -> 0.15 | K34: =I34/(1-J34) -> 24567.471
B35: SUBTOTAL | I35: =SUM(I29:I34) -> 25663.6 | K35: =SUM(K29:K34) -> 30192.471
B37: Electrical and Data - Materials and Subcontracting | C37: Subcontractor 1 | D37: Subcontractor 2 | E37: Subcontractor 3 | F37: Selected | G37: Additional Contingency | I37: Total Cost | J37: Install Margin | K37: Selling Price
B38: ELECTRICAL MATERIALS | C38: 4781.25 | D38: 0 | E38: 0 | F38: 0 | G38: 0 | I38: =SUM(C38:G38) -> 4781.25 | J38: =$D$9 -> 0.15 | K38: =I38/(1-J38) -> 5625
B39: DATA MATERIALS | C39: 0 | D39: 0 | E39: 0 | F39: 0 | G39: 0 | I39: =SUM(C39:G39) -> 0 | J39: =$D$9 -> 0.15 | K39: =I39/(1-J39) -> 0
B40: ELECTRICAL LABOR | C40: 0 | D40: 0 | E40: 0 | F40: 0 | G40: 0 | I40: =SUM(C40:G40) -> 0 | J40: =$D$9 -> 0.15 | K40: =I40/(1-J40) -> 0
B41: DATA LABOR | C41: 0 | D41: 0 | E41: 0 | F41: 0 | G41: 0 | I41: =SUM(C41:G41) -> 0 | J41: =$D$9 -> 0.15 | K41: =I41/(1-J41) -> 0
B42: SUB PANEL | C42: 0 | D42: 0 | E42: 0 | F42: 0 | G42: 0 | I42: =SUM(C42:G42) -> 0 | J42: =$D$9 -> 0.15 | K42: =I42/(1-J42) -> 0
B43: MISC | C43: 0 | D43: 0 | E43: 0 | F43: 0 | G43: 0 | I43: =SUM(C43:G43) -> 0 | J43: =$D$9 -> 0.15 | K43: =I43/(1-J43) -> 0
B44: SUBTOTAL | I44: =SUM(I38:I43) -> 4781.25 | K44: =SUM(K38:K43) -> 5625
B46: Submittals, Engineering, and Permits | C46: Subcontractor 1 | D46: Subcontractor 2 | E46: Subcontractor 3 | F46: Selected | G46: Additional Contingency | I46: Total Cost | J46: Install Margin | K46: Selling Price
B47: STRUCTURAL ENGINEERING | C47: 4705.88 | D47: 0 | E47: 0 | F47: 0 | G47: 0 | I47: =SUM(C47:G47) -> 4705.88 | J47: =$D$11 -> 0.15 | K47: =I47/(1-J47) -> 5536.3294
B48: STRUCTURAL CERTIFICATION | C48: 0 | D48: 0 | E48: 0 | F48: 0 | G48: 0 | I48: =SUM(C48:G48) -> 0 | J48: =$D$11 -> 0.15 | K48: =I48/(1-J48) -> 0
B49: ELECTRICAL ENGINEERING | C49: 0 | D49: 0 | E49: 0 | F49: 0 | G49: 0 | I49: =SUM(C49:G49) -> 0 | J49: =$D$11 -> 0.15 | K49: =I49/(1-J49) -> 0
B50: ELECTRICAL CERTIFICATION | C50: 0 | D50: 0 | E50: 0 | F50: 0 | G50: 0 | I50: =SUM(C50:G50) -> 0 | J50: =$D$11 -> 0.15 | K50: =I50/(1-J50) -> 0
B51: PERMITS | C51: 0 | D51: 0 | E51: 0 | F51: 0 | G51: 0 | I51: =SUM(C51:G51) -> 0 | J51: =$D$11 -> 0.15 | K51: =I51/(1-J51) -> 0
B52: SUBTOTAL | I52: =SUM(I47:I51) -> 4705.88 | K52: =SUM(K47:K51) -> 5536.3294
B54: ZONE GRAND TOTAL | I54: =I26+I35+I44+I52 -> 36298.23 | K54: =K26+K35+K44+K52 -> 42703.8

Sheet Processor Count
A1: WTC Digital Signage Upgrade — Processor Count
B4: Display | C4: Width (px) | D4: Height (px) | E4: Ports | F4: Ports (80%) | G4: 8-bit Video | H4: 8-bit (80%) | I4: 10/12/HDR bit
B5: 660 Pro | C5: 1920 | D5: 1080 | E5: 8 | G5: 650000 | H5: 455000 | I5: 320000
B6: MCTRL4K | C6: 3840 | D6: 2160 | E6: 16 | G6: 650000 | H6: 455000 | I6: 320000
B7: H9 Enhanced | C7: 7680 | D7: 4320 | E7: 20 | G7: 1200000 | H7: 960000 | I7: 650000
B10: DISPLAY PROCESSOR REQUIREMENTS
B11: Display | C11: Width (px) | D11: Height (px) | E11: Qty | F11: Total Pixels | G11: Ports Needed | H11: Processor Type | I11: Processors Needed
B12: ='LED Cost Sheet'!A4 -> Underpass 1 — 9A Underpass 1-4 | C12: ='LED Cost Sheet'!H4 -> 6.3 | D12: ='LED Cost Sheet'!G4 -> 2.5mm | E12: ='LED Cost Sheet'!I4 -> 18.11 | F12: =C12*D12*E12 -> #VALUE! | G12: =IFERROR(CEILING(F12/650000,1),0) -> 0 | H12: =IF(G12>8,"MCTRL4K","660 Pro") -> 660 Pro | I12: =IFERROR(CEILING(G12/IF(G12>8,16,8),1),0) -> 0
B13: ='LED Cost Sheet'!A5 -> Underpass 2 — 9A Underpass 1-4 | C13: ='LED Cost Sheet'!H5 -> 7.48 | D13: ='LED Cost Sheet'!G5 -> 2.5mm | E13: ='LED Cost Sheet'!I5 -> 29.92 | F13: =C13*D13*E13 -> #VALUE! | G13: =IFERROR(CEILING(F13/650000,1),0) -> 0 | H13: =IF(G13>8,"MCTRL4K","660 Pro") -> 660 Pro | I13: =IFERROR(CEILING(G13/IF(G13>8,16,8),1),0) -> 0
B14: ='LED Cost Sheet'!A6 -> Underpass 3 — 9A Underpass 1-4 | C14: ='LED Cost Sheet'!H6 -> 7.48 | D14: ='LED Cost Sheet'!G6 -> 2.5mm | E14: ='LED Cost Sheet'!I6 -> 29.92 | F14: =C14*D14*E14 -> #VALUE! | G14: =IFERROR(CEILING(F14/650000,1),0) -> 0 | H14: =IF(G14>8,"MCTRL4K","660 Pro") -> 660 Pro | I14: =IFERROR(CEILING(G14/IF(G14>8,16,8),1),0) -> 0
B15: ='LED Cost Sheet'!A7 -> Underpass 4 — 9A Underpass 1-4 | C15: ='LED Cost Sheet'!H7 -> 12.6 | D15: ='LED Cost Sheet'!G7 -> 2.5mm | E15: ='LED Cost Sheet'!I7 -> 29.92 | F15: =C15*D15*E15 -> #VALUE! | G15: =IFERROR(CEILING(F15/650000,1),0) -> 0 | H15: =IF(G15>8,"MCTRL4K","660 Pro") -> 660 Pro | I15: =IFERROR(CEILING(G15/IF(G15>8,16,8),1),0) -> 0
B16: ='LED Cost Sheet'!A8 -> Concourse — Concourse | C16: ='LED Cost Sheet'!H8 -> 9.45 | D16: ='LED Cost Sheet'!G8 -> 2.5mm | E16: ='LED Cost Sheet'!I8 -> 280.31 | F16: =C16*D16*E16 -> #VALUE! | G16: =IFERROR(CEILING(F16/650000,1),0) -> 0 | H16: =IF(G16>8,"MCTRL4K","660 Pro") -> 660 Pro | I16: =IFERROR(CEILING(G16/IF(G16>8,16,8),1),0) -> 0
B17: ='LED Cost Sheet'!A9 -> T4-B1 (6-9) — T4-B1 | C17: ='LED Cost Sheet'!H9 -> 7.87 | D17: ='LED Cost Sheet'!G9 -> 2.5mm | E17: ='LED Cost Sheet'!I9 -> 8.66 | F17: =C17*D17*E17 -> #VALUE! | G17: =IFERROR(CEILING(F17/650000,1),0) -> 0 | H17: =IF(G17>8,"MCTRL4K","660 Pro") -> 660 Pro | I17: =IFERROR(CEILING(G17/IF(G17>8,16,8),1),0) -> 0
B18: ='LED Cost Sheet'!A10 -> T4-B2 (10-18) — T4-B2 | C18: ='LED Cost Sheet'!H10 -> 7.87 | D18: ='LED Cost Sheet'!G10 -> 2.5mm | E18: ='LED Cost Sheet'!I10 -> 8.66 | F18: =C18*D18*E18 -> #VALUE! | G18: =IFERROR(CEILING(F18/650000,1),0) -> 0 | H18: =IF(G18>8,"MCTRL4K","660 Pro") -> 660 Pro | I18: =IFERROR(CEILING(G18/IF(G18>8,16,8),1),0) -> 0
B19: ='LED Cost Sheet'!A11 -> T4 Lobby Elevator — T4 Lobby Elevator | C19: ='LED Cost Sheet'!H11 -> 71.6 | D19: ='LED Cost Sheet'!G11 -> 2.5mm | E19: ='LED Cost Sheet'!I11 -> 5.5 | F19: =C19*D19*E19 -> #VALUE! | G19: =IFERROR(CEILING(F19/650000,1),0) -> 0 | H19: =IF(G19>8,"MCTRL4K","660 Pro") -> 660 Pro | I19: =IFERROR(CEILING(G19/IF(G19>8,16,8),1),0) -> 0
B20: ='LED Cost Sheet'!A12 -> T2-B1M Screen 20 — T2-B1M | C20: ='LED Cost Sheet'!H12 -> 7.91 | D20: ='LED Cost Sheet'!G12 -> 2.5mm | E20: ='LED Cost Sheet'!I12 -> 16.5 | F20: =C20*D20*E20 -> #VALUE! | G20: =IFERROR(CEILING(F20/650000,1),0) -> 0 | H20: =IF(G20>8,"MCTRL4K","660 Pro") -> 660 Pro | I20: =IFERROR(CEILING(G20/IF(G20>8,16,8),1),0) -> 0
B21: ='LED Cost Sheet'!A13 -> T2-B1M Screen 21 — T2-B1M | C21: ='LED Cost Sheet'!H13 -> 7.91 | D21: ='LED Cost Sheet'!G13 -> 2.5mm | E21: ='LED Cost Sheet'!I13 -> 11.83 | F21: =C21*D21*E21 -> #VALUE! | G21: =IFERROR(CEILING(F21/650000,1),0) -> 0 | H21: =IF(G21>8,"MCTRL4K","660 Pro") -> 660 Pro | I21: =IFERROR(CEILING(G21/IF(G21>8,16,8),1),0) -> 0
B22: ='LED Cost Sheet'!A14 -> T2-B1M Screen 22 — T2-B1M | C22: ='LED Cost Sheet'!H14 -> 7.91 | D22: ='LED Cost Sheet'!G14 -> 2.5mm | E22: ='LED Cost Sheet'!I14 -> 7.91 | F22: =C22*D22*E22 -> #VALUE! | G22: =IFERROR(CEILING(F22/650000,1),0) -> 0 | H22: =IF(G22>8,"MCTRL4K","660 Pro") -> 660 Pro | I22: =IFERROR(CEILING(G22/IF(G22>8,16,8),1),0) -> 0
B23: TOTAL | F23: =SUM(F12:F22) -> #VALUE! | G23: =SUM(G12:G22) -> 0 | I23: =SUM(I12:I22) -> 0

Sheet Bundle Equipment
A1: WTC Digital Signage Upgrade — Processor & Equipment Breakdown
A2: Editable — adjust component costs per display zone. Totals roll into Margin Analysis.
A6: Category | B6: Component | C6: Cost | D6: Qty | E6: Total Cost | F6: Margin | G6: Selling Price | H6: Margin $
A7: Underpass 1 — 9A Underpass 1-4
A8: EQUIPMENT | B8: Sending Card | C8: 450 | D8: 1 | E8: =C8*D8 -> 450 | F8: 0.15 | G8: =IFERROR(E8/(1-F8),0) -> 529.41176 | H8: =IFERROR(G8-E8,0) -> 79.411765
A9: EQUIPMENT | B9: Signal Cable Kit | C9: 68.45 | D9: 1 | E9: =C9*D9 -> 68.45 | F9: 0.15 | G9: =IFERROR(E9/(1-F9),0) -> 80.529412 | H9: =IFERROR(G9-E9,0) -> 12.079412
B10: Zone Subtotal | E10: =SUM(E8:E9) -> 518.45 | G10: =SUM(G8:G9) -> 609.94118 | H10: =IFERROR(G10-E10,0) -> 91.491176
A12: Underpass 2 — 9A Underpass 1-4
A13: EQUIPMENT | B13: Sending Card | C13: 450 | D13: 1 | E13: =C13*D13 -> 450 | F13: 0.15 | G13: =IFERROR(E13/(1-F13),0) -> 529.41176 | H13: =IFERROR(G13-E13,0) -> 79.411765
A14: EQUIPMENT | B14: Signal Cable Kit | C14: 134.28 | D14: 1 | E14: =C14*D14 -> 134.28 | F14: 0.15 | G14: =IFERROR(E14/(1-F14),0) -> 157.97647 | H14: =IFERROR(G14-E14,0) -> 23.696471
B15: Zone Subtotal | E15: =SUM(E13:E14) -> 584.28 | G15: =SUM(G13:G14) -> 687.38824 | H15: =IFERROR(G15-E15,0) -> 103.10824
A17: Underpass 3 — 9A Underpass 1-4
A18: EQUIPMENT | B18: Sending Card | C18: 450 | D18: 1 | E18: =C18*D18 -> 450 | F18: 0.15 | G18: =IFERROR(E18/(1-F18),0) -> 529.41176 | H18: =IFERROR(G18-E18,0) -> 79.411765
A19: EQUIPMENT | B19: Signal Cable Kit | C19: 134.28 | D19: 1 | E19: =C19*D19 -> 134.28 | F19: 0.15 | G19: =IFERROR(E19/(1-F19),0) -> 157.97647 | H19: =IFERROR(G19-E19,0) -> 23.696471
B20: Zone Subtotal | E20: =SUM(E18:E19) -> 584.28 | G20: =SUM(G18:G19) -> 687.38824 | H20: =IFERROR(G20-E20,0) -> 103.10824
A22: Underpass 4 — 9A Underpass 1-4
A23: EQUIPMENT | B23: Sending Card | C23: 8400 | D23: 1 | E23: =C23*D23 -> 8400 | F23: 0.15 | G23: =IFERROR(E23/(1-F23),0) -> 9882.3529 | H23: =IFERROR(G23-E23,0) -> 1482.3529
A24: EQUIPMENT | B24: Signal Cable Kit | C24: 226.19 | D24: 1 | E24: =C24*D24 -> 226.19 | F24: 0.15 | G24: =IFERROR(E24/(1-F24),0) -> 266.10588 | H24: =IFERROR(G24-E24,0) -> 39.915882
A25: EQUIPMENT | B25: Backup Video Processor | C25: 12000 | D25: 1 | E25: =C25*D25 -> 12000 | F25: 0.15 | G25: =IFERROR(E25/(1-F25),0) -> 14117.647 | H25: =IFERROR(G25-E25,0) -> 2117.6471
B26: Zone Subtotal | E26: =SUM(E23:E25) -> 20626.19 | G26: =SUM(G23:G25) -> 24266.106 | H26: =IFERROR(G26-E26,0) -> 3639.9159
A28: Concourse — Concourse
A29: EQUIPMENT | B29: Sending Card | C29: 33600 | D29: 1 | E29: =C29*D29 -> 33600 | F29: 0.15 | G29: =IFERROR(E29/(1-F29),0) -> 39529.412 | H29: =IFERROR(G29-E29,0) -> 5929.4118
A30: EQUIPMENT | B30: Signal Cable Kit | C30: 1589.36 | D30: 1 | E30: =C30*D30 -> 1589.36 | F30: 0.15 | G30: =IFERROR(E30/(1-F30),0) -> 1869.8353 | H30: =IFERROR(G30-E30,0) -> 280.47529
A31: EQUIPMENT | B31: Backup Video Processor | C31: 12000 | D31: 1 | E31: =C31*D31 -> 12000 | F31: 0.15 | G31: =IFERROR(E31/(1-F31),0) -> 14117.647 | H31: =IFERROR(G31-E31,0) -> 2117.6471
B32: Zone Subtotal | E32: =SUM(E29:E31) -> 47189.36 | G32: =SUM(G29:G31) -> 55516.894 | H32: =IFERROR(G32-E32,0) -> 8327.5341
A34: T4-B1 (6-9) — T4-B1
A35: EQUIPMENT | B35: Sending Card | C35: 450 | D35: 1 | E35: =C35*D35 -> 450 | F35: 0.15 | G35: =IFERROR(E35/(1-F35),0) -> 529.41176 | H35: =IFERROR(G35-E35,0) -> 79.411765
A36: EQUIPMENT | B36: Signal Cable Kit | C36: 163.57 | D36: 1 | E36: =C36*D36 -> 163.57 | F36: 0.15 | G36: =IFERROR(E36/(1-F36),0) -> 192.43529 | H36: =IFERROR(G36-E36,0) -> 28.865294
B37: Zone Subtotal | E37: =SUM(E35:E36) -> 613.57 | G37: =SUM(G35:G36) -> 721.84706 | H37: =IFERROR(G37-E37,0) -> 108.27706
A39: T4-B2 (10-18) — T4-B2
A40: EQUIPMENT | B40: Sending Card | C40: 8400 | D40: 1 | E40: =C40*D40 -> 8400 | F40: 0.15 | G40: =IFERROR(E40/(1-F40),0) -> 9882.3529 | H40: =IFERROR(G40-E40,0) -> 1482.3529
A41: EQUIPMENT | B41: Signal Cable Kit | C41: 368.03 | D41: 1 | E41: =C41*D41 -> 368.03 | F41: 0.15 | G41: =IFERROR(E41/(1-F41),0) -> 432.97647 | H41: =IFERROR(G41-E41,0) -> 64.946471
A42: EQUIPMENT | B42: Backup Video Processor | C42: 12000 | D42: 1 | E42: =C42*D42 -> 12000 | F42: 0.15 | G42: =IFERROR(E42/(1-F42),0) -> 14117.647 | H42: =IFERROR(G42-E42,0) -> 2117.6471
B43: Zone Subtotal | E43: =SUM(E40:E42) -> 20768.03 | G43: =SUM(G40:G42) -> 24432.976 | H43: =IFERROR(G43-E43,0) -> 3664.9465
A45: T4 Lobby Elevator — T4 Lobby Elevator
A46: EQUIPMENT | B46: Sending Card | C46: 8400 | D46: 1 | E46: =C46*D46 -> 8400 | F46: 0.15 | G46: =IFERROR(E46/(1-F46),0) -> 9882.3529 | H46: =IFERROR(G46-E46,0) -> 1482.3529
A47: EQUIPMENT | B47: Signal Cable Kit | C47: 236.28 | D47: 1 | E47: =C47*D47 -> 236.28 | F47: 0.15 | G47: =IFERROR(E47/(1-F47),0) -> 277.97647 | H47: =IFERROR(G47-E47,0) -> 41.696471
A48: EQUIPMENT | B48: Backup Video Processor | C48: 12000 | D48: 1 | E48: =C48*D48 -> 12000 | F48: 0.15 | G48: =IFERROR(E48/(1-F48),0) -> 14117.647 | H48: =IFERROR(G48-E48,0) -> 2117.6471
B49: Zone Subtotal | E49: =SUM(E46:E48) -> 20636.28 | G49: =SUM(G46:G48) -> 24277.976 | H49: =IFERROR(G49-E49,0) -> 3641.6965
A51: T2-B1M Screen 20 — T2-B1M
A52: EQUIPMENT | B52: Sending Card | C52: 450 | D52: 1 | E52: =C52*D52 -> 450 | F52: 0.15 | G52: =IFERROR(E52/(1-F52),0) -> 529.41176 | H52: =IFERROR(G52-E52,0) -> 79.411765
A53: EQUIPMENT | B53: Signal Cable Kit | C53: 78.31 | D53: 1 | E53: =C53*D53 -> 78.31 | F53: 0.15 | G53: =IFERROR(E53/(1-F53),0) -> 92.129412 | H53: =IFERROR(G53-E53,0) -> 13.819412
B54: Zone Subtotal | E54: =SUM(E52:E53) -> 528.31 | G54: =SUM(G52:G53) -> 621.54118 | H54: =IFERROR(G54-E54,0) -> 93.231176
A56: T2-B1M Screen 21 — T2-B1M
A57: EQUIPMENT | B57: Sending Card | C57: 450 | D57: 1 | E57: =C57*D57 -> 450 | F57: 0.15 | G57: =IFERROR(E57/(1-F57),0) -> 529.41176 | H57: =IFERROR(G57-E57,0) -> 79.411765
A58: EQUIPMENT | B58: Signal Cable Kit | C58: 56.15 | D58: 1 | E58: =C58*D58 -> 56.15 | F58: 0.15 | G58: =IFERROR(E58/(1-F58),0) -> 66.058824 | H58: =IFERROR(G58-E58,0) -> 9.9088235
B59: Zone Subtotal | E59: =SUM(E57:E58) -> 506.15 | G59: =SUM(G57:G58) -> 595.47059 | H59: =IFERROR(G59-E59,0) -> 89.320588
A61: T2-B1M Screen 22 — T2-B1M
A62: EQUIPMENT | B62: Sending Card | C62: 450 | D62: 1 | E62: =C62*D62 -> 450 | F62: 0.15 | G62: =IFERROR(E62/(1-F62),0) -> 529.41176 | H62: =IFERROR(G62-E62,0) -> 79.411765
A63: EQUIPMENT | B63: Signal Cable Kit | C63: 37.54 | D63: 1 | E63: =C63*D63 -> 37.54 | F63: 0.15 | G63: =IFERROR(E63/(1-F63),0) -> 44.164706 | H63: =IFERROR(G63-E63,0) -> 6.6247059
B64: Zone Subtotal | E64: =SUM(E62:E63) -> 487.54 | G64: =SUM(G62:G63) -> 573.57647 | H64: =IFERROR(G64-E64,0) -> 86.036471
A66: EQUIPMENT GRAND TOTAL | E66: =E10+E15+E20+E26+E32+E37+E43+E49+E54+E59+E64 -> 113042.44 | G66: =G10+G15+G20+G26+G32+G37+G43+G49+G54+G59+G64 -> 132991.11 | H66: =IFERROR(G66-E66,0) -> 19948.666

Sheet ANC Travel
A1: WTC Digital Signage Upgrade — ANC Travel
B4: Travel - Installation | C4: Cost | D4: Quantity | E4: Total Cost
B5: Hotel | C5: 300 | D5: 0 | E5: 0
B6: Airfare | C6: 1000 | D6: 0 | E6: 0
B7: Car | C7: 125 | D7: 0 | E7: 0
B8: Per Diem | C8: 100 | D8: 0 | E8: 0
B9: Bundled | C9: 10000 | D9: 0 | E9: 0 | G9: Account for freelancer
B10: Total | E10: 0
B11: TOTAL | C11: USD: | E11: 0
B13: Travel - Commissioning | C13: Cost | D13: Quantity | E13: Total Cost
B14: Hotel | C14: 300 | D14: 0 | E14: 0
B15: Airfare | C15: 1000 | D15: 0 | E15: 0
B16: Car | C16: 125 | D16: 0 | E16: 0
B17: Per Diem | C17: 100 | D17: 0 | E17: 0
B18: Bundled | C18: 10000 | D18: 0 | E18: 0 | G18: Account for freelancer
B19: Total | E19: 0
B20: TOTAL | C20: USD: | E20: 0
B22: Game Support | C22: Cost | D22: Quantity | E22: Total Cost
B23: Hotel | C23: 300 | D23: 0 | E23: 0
B24: Airfare | C24: 1000 | D24: 0 | E24: 0
B25: Car | C25: 125 | D25: 0 | E25: 0
B26: Per Diem | C26: 100 | D26: 0 | E26: 0
B27: Bundled | C27: 10000 | D27: 0 | E27: 0 | G27: Account for freelancer
B28: Game Day Support | C28: 1500 | D28: 0 | E28: 0
B29: Total | E29: 0
B30: TOTAL | C30: USD: | E30: 0

Sheet CMS
A1: WTC Digital Signage Upgrade — Content Management System
B4: CMS Platform
B5: All costs require project-specific pricing — update items below based on RFP requirements
B6: Category | C6: Item | D6: Cost | E6: Quantity | F6: Total Cost | G6: Margin | H6: Selling Price | I6: Margin $
B7: PRIMARY | C7: DESIGN & CONTROL SOFTWARE | D7: 0 | E7: 0 | F7: =D7*E7 -> 0 | G7: 0.1 | H7: =IFERROR(F7/(1-G7),0) -> 0 | I7: =IFERROR(H7-F7,0) -> 0
B8: PRIMARY | C8: GRAPHICS PLAYBACK ENGINE | D8: 0 | E8: 0 | F8: =D8*E8 -> 0 | G8: 0.1 | H8: =IFERROR(F8/(1-G8),0) -> 0 | I8: =IFERROR(H8-F8,0) -> 0
B9: PRIMARY | C9: IMAGE PROCESSING | D9: 0 | E9: 0 | F9: =D9*E9 -> 0 | G9: 0.1 | H9: =IFERROR(F9/(1-G9),0) -> 0 | I9: =IFERROR(H9-F9,0) -> 0
B10: PRIMARY | C10: DEDICATED LED ROUTER / SWITCH | D10: 0 | E10: 0 | F10: =D10*E10 -> 0 | G10: 0.1 | H10: =IFERROR(F10/(1-G10),0) -> 0 | I10: =IFERROR(H10-F10,0) -> 0
B11: REDUNDANT | C11: DESIGN & CONTROL SOFTWARE | D11: 0 | E11: 0 | F11: =D11*E11 -> 0 | G11: 0.1 | H11: =IFERROR(F11/(1-G11),0) -> 0 | I11: =IFERROR(H11-F11,0) -> 0
B12: REDUNDANT | C12: GRAPHICS PLAYBACK ENGINE | D12: 0 | E12: 0 | F12: =D12*E12 -> 0 | G12: 0.1 | H12: =IFERROR(F12/(1-G12),0) -> 0 | I12: =IFERROR(H12-F12,0) -> 0
B13: REDUNDANT | C13: IMAGE PROCESSING | D13: 0 | E13: 0 | F13: =D13*E13 -> 0 | G13: 0.1 | H13: =IFERROR(F13/(1-G13),0) -> 0 | I13: =IFERROR(H13-F13,0) -> 0
B14: STANDARD SERVICES | C14: COMMISSIONING | D14: 0 | E14: 0 | F14: =D14*E14 -> 0 | G14: 0.1 | H14: =IFERROR(F14/(1-G14),0) -> 0 | I14: =IFERROR(H14-F14,0) -> 0
B15: STANDARD SERVICES | C15: EVENT SUPPORT | D15: 0 | E15: 0 | F15: =D15*E15 -> 0 | G15: 0.1 | H15: =IFERROR(F15/(1-G15),0) -> 0 | I15: =IFERROR(H15-F15,0) -> 0
B16: STANDARD SERVICES | C16: PROJECT MANAGEMENT | D16: 0 | E16: 0 | F16: =D16*E16 -> 0 | G16: 0.1 | H16: =IFERROR(F16/(1-G16),0) -> 0 | I16: =IFERROR(H16-F16,0) -> 0
C17: Integration Hardware | D17: 0 | E17: 0 | F17: =D17*E17 -> 0 | G17: 0.1 | H17: =IFERROR(F17/(1-G17),0) -> 0 | I17: =IFERROR(H17-F17,0) -> 0
C18: Integration Labor | D18: 0 | E18: 0 | F18: =D18*E18 -> 0 | G18: 0.1 | H18: =IFERROR(F18/(1-G18),0) -> 0 | I18: =IFERROR(H18-F18,0) -> 0
C19: Shipping | D19: 0 | E19: 0 | F19: =D19*E19 -> 0 | G19: 0.1 | H19: =IFERROR(F19/(1-G19),0) -> 0 | I19: =IFERROR(H19-F19,0) -> 0
C20: Travel | D20: 0 | E20: 0 | F20: =D20*E20 -> 0 | G20: 0.1 | H20: =IFERROR(F20/(1-G20),0) -> 0 | I20: =IFERROR(H20-F20,0) -> 0
C22: CMS TOTAL | F22: =SUM(F7:F20) -> 0 | H22: =SUM(H7:H20) -> 0 | I22: =IFERROR(H22-F22,0) -> 0
B24: TAX | F24: 0
B25: BOND | F25: 0
B26: SUB TOTAL | C26: USD: | F26: =F22+F24+F25 -> 0 | H26: =H22 -> 0 | I26: =IFERROR(H26-F26,0) -> 0

Sheet Scoring
A1: WTC Digital Signage Upgrade — Scoring System
B4: Scoring Platform
B5: All costs require project-specific pricing — update items below based on RFP requirements
B6: Category | C6: Item | D6: Cost | E6: Quantity | F6: Total Cost | G6: Margin | H6: Selling Price | I6: Margin $
B7: HARDWARE | C7: SCORING CONTROLLER / SERVER | D7: 0 | E7: 0 | F7: =D7*E7 -> 0 | G7: 0.1 | H7: =IFERROR(F7/(1-G7),0) -> 0 | I7: =IFERROR(H7-F7,0) -> 0
B8: HARDWARE | C8: OPERATOR WORKSTATION(S) | D8: 0 | E8: 0 | F8: =D8*E8 -> 0 | G8: 0.1 | H8: =IFERROR(F8/(1-G8),0) -> 0 | I8: =IFERROR(H8-F8,0) -> 0
B9: HARDWARE | C9: SCOREBOARD INPUT DEVICES | D9: 0 | E9: 0 | F9: =D9*E9 -> 0 | G9: 0.1 | H9: =IFERROR(F9/(1-G9),0) -> 0 | I9: =IFERROR(H9-F9,0) -> 0
B10: HARDWARE | C10: SHOT CLOCK / GAME CLOCK INTERFACE | D10: 0 | E10: 0 | F10: =D10*E10 -> 0 | G10: 0.1 | H10: =IFERROR(F10/(1-G10),0) -> 0 | I10: =IFERROR(H10-F10,0) -> 0
B11: HARDWARE | C11: STATISTICS INTERFACE | D11: 0 | E11: 0 | F11: =D11*E11 -> 0 | G11: 0.1 | H11: =IFERROR(F11/(1-G11),0) -> 0 | I11: =IFERROR(H11-F11,0) -> 0
B12: SOFTWARE | C12: SCORING SOFTWARE LICENSE | D12: 0 | E12: 0 | F12: =D12*E12 -> 0 | G12: 0.1 | H12: =IFERROR(F12/(1-G12),0) -> 0 | I12: =IFERROR(H12-F12,0) -> 0
B13: SOFTWARE | C13: GRAPHICS / ANIMATION PACKAGE | D13: 0 | E13: 0 | F13: =D13*E13 -> 0 | G13: 0.1 | H13: =IFERROR(F13/(1-G13),0) -> 0 | I13: =IFERROR(H13-F13,0) -> 0
B14: SOFTWARE | C14: STATISTICS INTEGRATION | D14: 0 | E14: 0 | F14: =D14*E14 -> 0 | G14: 0.1 | H14: =IFERROR(F14/(1-G14),0) -> 0 | I14: =IFERROR(H14-F14,0) -> 0
B15: SERVICES | C15: COMMISSIONING | D15: 0 | E15: 0 | F15: =D15*E15 -> 0 | G15: 0.1 | H15: =IFERROR(F15/(1-G15),0) -> 0 | I15: =IFERROR(H15-F15,0) -> 0
B16: SERVICES | C16: TRAINING | D16: 0 | E16: 0 | F16: =D16*E16 -> 0 | G16: 0.1 | H16: =IFERROR(F16/(1-G16),0) -> 0 | I16: =IFERROR(H16-F16,0) -> 0
B17: SERVICES | C17: PROJECT MANAGEMENT | D17: 0 | E17: 0 | F17: =D17*E17 -> 0 | G17: 0.1 | H17: =IFERROR(F17/(1-G17),0) -> 0 | I17: =IFERROR(H17-F17,0) -> 0
C18: Integration Hardware | D18: 0 | E18: 0 | F18: =D18*E18 -> 0 | G18: 0.1 | H18: =IFERROR(F18/(1-G18),0) -> 0 | I18: =IFERROR(H18-F18,0) -> 0
C19: Integration Labor | D19: 0 | E19: 0 | F19: =D19*E19 -> 0 | G19: 0.1 | H19: =IFERROR(F19/(1-G19),0) -> 0 | I19: =IFERROR(H19-F19,0) -> 0
C20: Shipping | D20: 0 | E20: 0 | F20: =D20*E20 -> 0 | G20: 0.1 | H20: =IFERROR(F20/(1-G20),0) -> 0 | I20: =IFERROR(H20-F20,0) -> 0
C21: Travel | D21: 0 | E21: 0 | F21: =D21*E21 -> 0 | G21: 0.1 | H21: =IFERROR(F21/(1-G21),0) -> 0 | I21: =IFERROR(H21-F21,0) -> 0
C23: SCORING TOTAL | F23: =SUM(F7:F21) -> 0 | H23: =SUM(H7:H21) -> 0 | I23: =IFERROR(H23-F23,0) -> 0
B25: TAX | F25: 0
B26: BOND | F26: 0
B27: SUB TOTAL | C27: USD: | F27: =F23+F25+F26 -> 0 | H27: =H23 -> 0 | I27: =IFERROR(H27-F27,0) -> 0

Sheet Venue Services
A1: WTC Digital Signage Upgrade — Venue Services
A2: Multi-year service contract calculator
A4: Contract Years | B4: 3 | C4: Editable service term
A5: Year 1 Cost | B5: 0 | C5: Base annual contract value
A6: Annual Escalation % | B6: 0.03 | C6: Applied to each renewal year
A7: Margin % | B7: 0.15 | C7: Target service-contract margin
A10: Year | B10: Cost | C10: Selling Price | D10: Margin $ | E10: Notes
A11: =IF($B$4>=1,"Year 1","") -> Year 1 | B11: =$B$5 -> 0 | C11: =IF(A11="",0,IFERROR(B11/(1-$B$7),0)) -> 0 | D11: =IF(A11="",0,IFERROR(C11-B11,0)) -> 0 | E11: Escalated annual term
A12: =IF($B$4>=2,"Year 2","") -> Year 2 | B12: =IF(A12="",0,B11*(1+$B$6)) -> 0 | C12: =IF(A12="",0,IFERROR(B12/(1-$B$7),0)) -> 0 | D12: =IF(A12="",0,IFERROR(C12-B12,0)) -> 0 | E12: Escalated annual term
A13: =IF($B$4>=3,"Year 3","") -> Year 3 | B13: =IF(A13="",0,B12*(1+$B$6)) -> 0 | C13: =IF(A13="",0,IFERROR(B13/(1-$B$7),0)) -> 0 | D13: =IF(A13="",0,IFERROR(C13-B13,0)) -> 0 | E13: Escalated annual term
A14: =IF($B$4>=4,"Year 4","") | B14: =IF(A14="",0,B13*(1+$B$6)) -> 0 | C14: =IF(A14="",0,IFERROR(B14/(1-$B$7),0)) -> 0 | D14: =IF(A14="",0,IFERROR(C14-B14,0)) -> 0
A15: =IF($B$4>=5,"Year 5","") | B15: =IF(A15="",0,B14*(1+$B$6)) -> 0 | C15: =IF(A15="",0,IFERROR(B15/(1-$B$7),0)) -> 0 | D15: =IF(A15="",0,IFERROR(C15-B15,0)) -> 0
A17: VENUE SERVICES TOTAL | B17: =SUM(B11:B15) -> 0 | C17: =SUM(C11:C15) -> 0 | D17: =IFERROR(C17-B17,0) -> 0

Sheet Additional Items
A1: WTC Digital Signage Upgrade — Additional Non-LED Items
B4: Category | C4: Item | D4: Cost | E4: Quantity | F4: Total Cost | G4: Margin | H4: Selling Price | I4: Margin $
B5: GAME CLOCK | C5: Six-Digit Game Clocks | D5: 0 | E5: 1 | F5: =D5*E5 -> 0 | G5: 0.15 | H5: =IFERROR(F5/(1-G5),0) -> 0 | I5: =IFERROR(H5-F5,0) -> 0
B6: PITCH CLOCK | C6: Pitch Clocks | D6: 0 | E6: 1 | F6: =D6*E6 -> 0 | G6: 0.15 | H6: =IFERROR(F6/(1-G6),0) -> 0 | I6: =IFERROR(H6-F6,0) -> 0
B7: OES / MIS | C7: OES / MIS / Timing | D7: 0 | E7: 1 | F7: =D7*E7 -> 0 | G7: 0.15 | H7: =IFERROR(F7/(1-G7),0) -> 0 | I7: =IFERROR(H7-F7,0) -> 0
B8: MISC | C8: DMX / Misc Equipment | D8: 0 | E8: 1 | F8: =D8*E8 -> 0 | G8: 0.15 | H8: =IFERROR(F8/(1-G8),0) -> 0 | I8: =IFERROR(H8-F8,0) -> 0
C10: ADDITIONAL ITEMS TOTAL | F10: =SUM(F5:F8) -> 0 | H10: =SUM(H5:H8) -> 0 | I10: =IFERROR(H10-F10,0) -> 0

Sheet Resp Matrix
B1: Project: WTC Digital Signage Upgrade
B2: Date: 3/31/2026
B4: Administrative | C4: ANC | D4: Purchaser
B5: Provide accurate architectural, structural engineering, and AV drawings. | D5: X
B6: Provide Payment and Performance Bond. | C6: NA
B7: All required zoning, building, street or sidewalk permits. | C7: NA
B8: Shipping of all equipment to site. | C8: X
B9: Receive, unload, and inspect all new equipment upon arrival. | C9: X
B10: Provide safe storage of video equipment and control room. | D10: X
B11: Unobstructed access to equipment and control room. | D11: X
B13: Engineering & Submittals | C13: ANC | D13: Purchaser
B14: Customer responsible to ensure existing structure supports new equipment. | D14: X
B15: Provide mechanical drawings, electrical drawings, and load calculations. | C15: X
B16: Engineering and certification for new equipment attachments. | C16: X
B17: Provide approval of all mechanical/electrical drawings. | D17: X
B18: Responsible to ensure structural integrity of existing conditions. | D18: X
B20: Physical Installation | C20: ANC | D20: Purchaser
B21: ANC assumes all base building structure is provided by others. | C21: Include Statement
B22: ANC has included removal and disposal of existing equipment. | D22: X
B23: ANC assumes reasonable access will be provided to the work area. | C23: Include Statement
B24: Fabricate, deliver, and install support structure. | C24: X
B25: Provide & Install LED components. | C25: X
B26: Provide all required Floor/Site Protection. | D26: X
B28: Electrical & Data Installation | C28: ANC | D28: Purchaser
B29: Submit electrical engineering drawings. | C29: X
B30: Provide primary power feed to each display location. | D30: X
B31: Provide secondary electrical panels and/or remote disconnects. | D31: X
B32: Furnish signal cables as specified by ANC. | C32: X
B33: Provide and install signal cable conduit. | D33: X
B34: Labor to pull signal cable. | C34: X
B35: Terminate signal cable at control system equipment. | C35: X
B36: Mount and install data patch panel. | C36: X
B37: Provide high speed internet connection to control room. | D37: X
B39: Control System | C39: ANC | D39: Purchaser
B40: ANC has provided display processors only. | C40: Include Statement
B41: Provide climate controlled control room. | D41: X
B42: Supply static IP address five (5) days prior to installation. | D42: X
B44: Training | C44: ANC | D44: Purchaser
B45: Provide appropriate on-site operation and maintenance training. | C45: X
B46: Provide sign off list for all training. | C46: X
B47: Perform one (1) day of maintenance training. | C47: X
B48: Perform final systems testing and commissioning. | C48: X
B50: General Conditions | C50: ANC | D50: Purchaser
B51: ANC has provided a parts only warranty, excluding labor. | C51: Include Statement
B52: ANC has included installation pricing with prevailing labor rates. | D52: X
B53: ANC has not included bonding of any kind. | C53: Include Statement
B54: ANC has not included any tax in the proposal. | C54: Include Statement
B55: Shipping included in quoted pricing. | C55: Include Statement

Sheet P&L
A1: WTC Digital Signage Upgrade — P&L
A3: Project #: | D3: 50/20/20/10
B5: PROJECTS BUDGET | I5: CONTRACT BUDGET
B6: Revenue | C6: Budgeted Cost | D6: Margin | I6: Revenue | J6: Budgeted Cost
A7: Base Contract | B7: 3268356.7 | C7: 2829644.1 | D7: 438712.63 | H7: TOTAL BASE CONTRACT | I7: 3268356.7 | J7: 2829644.1
A8: TOTAL BASE CONTRACT | B8: 3268356.7 | C8: 2829644.1 | D8: 438712.63
A10: Change Orders
A11: Total Change Order(s) Amount | B11: 0 | C11: 0 | D11: 0
A13: Grand Total | B13: 3268356.7 | C13: 2829644.1 | D13: 438712.63
A16: Cost Category | B16: Revenue | C16: Budget | D16: Committed POs | E16: Budget Remaining
A17: LED | B17: 0 | C17: 1430552.6 | D17: 0 | E17: 1430552.6
A18: Install | B18: 0 | C18: 487978.77 | D18: 0 | E18: 487978.77
A19: Electrical | B19: 0 | C19: 393531.27 | D19: 0 | E19: 393531.27
A20: ANC Travel | B20: 0 | C20: 165000 | D20: 0 | E20: 165000
A21: Structural Engineering | B21: 0 | C21: 51764.68 | D21: 0 | E21: 51764.68
A22: Electrical Engineering | B22: 0 | C22: 0 | D22: 0 | E22: 0
A23: CMS | B23: 0 | C23: 0 | D23: 0 | E23: 0
A24: Parts/Labor | B24: 0 | C24: 0 | D24: 0 | E24: 0
A25: Tax | B25: 0 | C25: 0 | D25: 0 | E25: 0
A26: Bond | B26: 0 | C26: 0 | D26: 0 | E26: 0
A27: BASE CONTRACT TOTAL | C27: 2829644.1 | D27: 0 | E27: 2829644.1

Sheet Cash Flow
A1: WTC Digital Signage Upgrade — Cash Flow
D3: Payment Terms: 50/20/20/10
D4: Payment Phases | E4: Contract Signed | F4: Product Shipping | G4: Substantial Completion | H4: Sign Off
D5: Percentages | E5: 0.5 | F5: 0.2 | G5: 0.2 | H5: 0.1
B6: Contract Award Date | C6: TBD
B7: Scheduled Completion | C7: TBD
B9: Revenue | C9: Expenses | D9: Gross Profit | E9: Gross Profit % | F9: Budget Tracking (+/-)
B10: 3268356.7 | C10: 2829644.1 | D10: 438712.63 | E10: 0.13423034 | F10: 0
A12: Month | E12: Month 1 | F12: Month 2 | G12: Month 3 | H12: Month 4 | I12: Month 5 | J12: Month 6 | K12: Month 7 | L12: Month 8 | M12: Month 9 | N12: Month 10
A13: Revenue | C13: Amount | D13: Date Submitted
A14: 1 | C14: 0 | E14: 0 | F14: 0 | G14: 0 | H14: 0 | I14: 0 | J14: 0 | K14: 0 | L14: 0 | M14: 0 | N14: 0
A15: 2 | C15: 0 | E15: 0 | F15: 0 | G15: 0 | H15: 0 | I15: 0 | J15: 0 | K15: 0 | L15: 0 | M15: 0 | N15: 0
A16: 3 | C16: 0 | E16: 0 | F16: 0 | G16: 0 | H16: 0 | I16: 0 | J16: 0 | K16: 0 | L16: 0 | M16: 0 | N16: 0
A17: 4 | C17: 0 | E17: 0 | F17: 0 | G17: 0 | H17: 0 | I17: 0 | J17: 0 | K17: 0 | L17: 0 | M17: 0 | N17: 0
A18: 5 | C18: 0 | E18: 0 | F18: 0 | G18: 0 | H18: 0 | I18: 0 | J18: 0 | K18: 0 | L18: 0 | M18: 0 | N18: 0
A19: 6 | C19: 0 | E19: 0 | F19: 0 | G19: 0 | H19: 0 | I19: 0 | J19: 0 | K19: 0 | L19: 0 | M19: 0 | N19: 0
A20: 7 | C20: 0 | E20: 0 | F20: 0 | G20: 0 | H20: 0 | I20: 0 | J20: 0 | K20: 0 | L20: 0 | M20: 0 | N20: 0
A21: 8 | C21: 0 | E21: 0 | F21: 0 | G21: 0 | H21: 0 | I21: 0 | J21: 0 | K21: 0 | L21: 0 | M21: 0 | N21: 0
A22: 9 | C22: 0 | E22: 0 | F22: 0 | G22: 0 | H22: 0 | I22: 0 | J22: 0 | K22: 0 | L22: 0 | M22: 0 | N22: 0
A23: 10 | C23: 0 | E23: 0 | F23: 0 | G23: 0 | H23: 0 | I23: 0 | J23: 0 | K23: 0 | L23: 0 | M23: 0 | N23: 0
A24: Total Revenue | C24: 0

Sheet PO's
A1: WTC Digital Signage Upgrade — Purchase Orders
A3: PO Number | B3: Vendor | C3: Title / Description | D3: Original Contract Amount | E3: Category
D4: 0
D5: 0
D6: 0
D7: 0
D8: 0
D9: 0
D10: 0
D11: 0
D12: 0
D13: 0
D14: 0
D15: 0
... D33: 0

Sheet Alternates
A1: WTC Digital Signage Upgrade — Cost Alternates (Reference Only)
A2: These alternates are NOT included in the base bid budget. Shown for reference only.
A4: Alt ID | B4: Display Name | C4: Location | D4: Width (ft) | E4: Height (ft) | F4: Pitch (mm) | G4: Env | H4: Qty | I4: Est. Cost | J4: Notes
A5: Option 1 | B5: New Path Hall Option 1 | C5: Path Hall | D5: 14 | E5: 48 | F5: 2.5mm | G5: indoor | H5: 1 | I5: 363897.77 | J5: 14' x 48' display for Path Hall
A6: Option 2 | B6: New Path Hall Option 2 | C6: Path Hall | D6: 13 | E6: 65 | F6: 2.5mm | G6: indoor | H6: 1 | I6: 454125.35 | J6: 13' x 65' display for Path Hall
A9: NOTE: These alternates are optional add-ons or substitute configurations. They are NOT included in the base bid budget totals.
