Workbook

Sheet Project Overview
A1: Amended RFP Exhibit I — Project Overview
A2: Westfield | 2026-03-31 | ANC Proposal Engine
B4: PROJECT INFORMATION
B5: Client | C5: Westfield
B6: Project Name | C6: Amended RFP Exhibit I
B7: Location | C7: WTC
B8: Date Created | C8: 2026-03-31
B9: Currency | C9: USD
B10: Environment | C10: Indoor
B11: Union Labor | C11: No
B12: Bond Required | C12: No
B13: Number of Displays | C13: =SUM('LED Cost Sheet'!I4:I13) -> 10
B15: FINANCIAL PARAMETERS
B16: LED Hardware Margin | C16: 15%
B17: Install / Services Margin | C17: 15%
B18: Engineering Margin | C18: 15%
B19: Equipment Margin | C19: 15%
B20: CMS Margin | C20: 15%
B21: Bond Rate | C21: N/A
B22: Tax Rate | C22: Per zone (editable on MA)
B23: Tariff Rate | C23: Per zone (editable on MA)
B25: SUMMARY TOTALS
B26: Total Cost | C26: ='Margin Analysis'!C145 -> 2338109.6
B27: Total Selling Price | C27: ='Margin Analysis'!D145 -> 2685228.3
B28: Project Margin $ | C28: ='Margin Analysis'!E145 -> 347118.63
B29: Project Margin % | C29: ='Margin Analysis'!F145 -> 0.13
B30: DOCUMENT TOTAL | C30: ='Margin Analysis'!D145 -> 2685228.3

Sheet Margin Analysis
A1: Amended RFP Exhibit I — Margin Analysis
A2: Westfield | 2026-03-31 | ANC Proposal Engine
B4: Zone / Category | C4: Cost | D4: Selling Price | E4: Margin $ | F4: Margin %
B5: 9A Underpass 1 — Underpass 1 | D5: Selling Price
B6: LED Hardware | C6: ='LED Cost Sheet'!T4 -> 29515.17 | D6: ='LED Cost Sheet'!V4 -> 34723.73 | E6: =IFERROR(D6-C6,0) -> 5208.56 | F6: 0.15
B7: Structural Materials | C7: ='9A Underpass 1 - Install'!I26 -> 1312.5 | D7: =IFERROR(C7/(1-F7),0) -> 1544.12 | E7: =IFERROR(D7-C7,0) -> 231.62 | F7: 0.15
B8: Structural Labor & LED Installation | C8: ='9A Underpass 1 - Install'!I35-'9A Underpass 1 - Install'!I34 -> 5468.75 | D8: =IFERROR(C8/(1-F8),0) -> 6433.82 | E8: =IFERROR(D8-C8,0) -> 965.07 | F8: 0.15
B9: Electrical & Data | C9: ='9A Underpass 1 - Install'!I44 -> 5468.75 | D9: =IFERROR(C9/(1-F9),0) -> 6433.82 | E9: =IFERROR(D9-C9,0) -> 965.07 | F9: 0.15
B10: PM / General Conditions / Travel | C10: ='9A Underpass 1 - Install'!I34 -> 20882.35 | D10: =IFERROR(C10/(1-F10),0) -> 24567.47 | E10: =IFERROR(D10-C10,0) -> 3685.12 | F10: 0.15
B11: Engineering & Permits | C11: ='9A Underpass 1 - Install'!I52 -> 4705.88 | D11: =IFERROR(C11/(1-F11),0) -> 5536.33 | E11: =IFERROR(D11-C11,0) -> 830.45 | F11: 0.15
B12: SUBTOTAL | C12: =SUM(C6:C11) -> 67353.4 | D12: =SUM(D6:D11) -> 77897.05 | E12: =IFERROR(D12-C12,0) -> 10543.65 | F12: =IFERROR(1-C12/D12,0) -> 0.135354
B13: TAX | C13: 0 | D13: 0 | E13: 0 | G13: 0
B14: BOND | C14: 0 | D14: 0 | E14: 0 | G14: 0
B15: TARIFF | C15: 0 | D15: 0 | E15: 0 | G15: 0
B16: GRAND TOTAL | C16: =C12+C13+C14+C15 -> 67353.4 | D16: =D12+D13+D14+D15 -> 77897.05 | E16: =IFERROR(D16-C16,0) -> 10543.65 | F16: =IFERROR(1-C16/D16,0) -> 0.13535365
B18: 9A Underpass 2 — Underpass 2 | D18: Selling Price
B19: LED Hardware | C19: ='LED Cost Sheet'!T5 -> 57464.5 | D19: ='LED Cost Sheet'!V5 -> 67605.29 | E19: =IFERROR(D19-C19,0) -> 10140.79 | F19: 0.15
B20: Structural Materials | C20: ='9A Underpass 2 - Install'!I26 -> 2580 | D20: =IFERROR(C20/(1-F20),0) -> 3035.29 | E20: =IFERROR(D20-C20,0) -> 455.29 | F20: 0.15
B21: Structural Labor & LED Installation | C21: ='9A Underpass 2 - Install'!I35-'9A Underpass 2 - Install'!I34 -> 10750 | D21: =IFERROR(C21/(1-F21),0) -> 12647.06 | E21: =IFERROR(D21-C21,0) -> 1897.06 | F21: 0.15
B22: Electrical & Data | C22: ='9A Underpass 2 - Install'!I44 -> 10750 | D22: =IFERROR(C22/(1-F22),0) -> 12647.06 | E22: =IFERROR(D22-C22,0) -> 1897.06 | F22: 0.15
B23: PM / General Conditions / Travel | C23: ='9A Underpass 2 - Install'!I34 -> 20882.35 | D23: =IFERROR(C23/(1-F23),0) -> 24567.47 | E23: =IFERROR(D23-C23,0) -> 3685.12 | F23: 0.15
B24: Engineering & Permits | C24: ='9A Underpass 2 - Install'!I52 -> 4705.88 | D24: =IFERROR(C24/(1-F24),0) -> 5536.33 | E24: =IFERROR(D24-C24,0) -> 830.45 | F24: 0.15
B25: SUBTOTAL | C25: =SUM(C19:C24) -> 107132.73 | D25: =SUM(D19:D24) -> 123405.56 | E25: =IFERROR(D25-C25,0) -> 16272.83 | F25: =IFERROR(1-C25/D25,0) -> 0.131865
B26: TAX | C26: 0 | D26: 0 | E26: 0 | G26: 0
B27: BOND | C27: 0 | D27: 0 | E27: 0 | G27: 0
B28: TARIFF | C28: 0 | D28: 0 | E28: 0 | G28: 0
B29: GRAND TOTAL | C29: =C25+C26+C27+C28 -> 107132.73 | D29: =D25+D26+D27+D28 -> 123405.56 | E29: =IFERROR(D29-C29,0) -> 16272.83 | F29: =IFERROR(1-C29/D29,0) -> 0.13186464
B31: 9A Underpass 3 — Underpass 3 | D31: Selling Price
B32: LED Hardware | C32: ='LED Cost Sheet'!T6 -> 57464.5 | D32: ='LED Cost Sheet'!V6 -> 67605.29 | E32: =IFERROR(D32-C32,0) -> 10140.79 | F32: 0.15
B33: Structural Materials | C33: ='9A Underpass 3 - Install'!I26 -> 2580 | D33: =IFERROR(C33/(1-F33),0) -> 3035.29 | E33: =IFERROR(D33-C33,0) -> 455.29 | F33: 0.15
B34: Structural Labor & LED Installation | C34: ='9A Underpass 3 - Install'!I35-'9A Underpass 3 - Install'!I34 -> 10750 | D34: =IFERROR(C34/(1-F34),0) -> 12647.06 | E34: =IFERROR(D34-C34,0) -> 1897.06 | F34: 0.15
B35: Electrical & Data | C35: ='9A Underpass 3 - Install'!I44 -> 10750 | D35: =IFERROR(C35/(1-F35),0) -> 12647.06 | E35: =IFERROR(D35-C35,0) -> 1897.06 | F35: 0.15
B36: PM / General Conditions / Travel | C36: ='9A Underpass 3 - Install'!I34 -> 20882.35 | D36: =IFERROR(C36/(1-F36),0) -> 24567.47 | E36: =IFERROR(D36-C36,0) -> 3685.12 | F36: 0.15
B37: Engineering & Permits | C37: ='9A Underpass 3 - Install'!I52 -> 4705.88 | D37: =IFERROR(C37/(1-F37),0) -> 5536.33 | E37: =IFERROR(D37-C37,0) -> 830.45 | F37: 0.15
B38: SUBTOTAL | C38: =SUM(C32:C37) -> 107132.73 | D38: =SUM(D32:D37) -> 123405.56 | E38: =IFERROR(D38-C38,0) -> 16272.83 | F38: =IFERROR(1-C38/D38,0) -> 0.131865
B39: TAX | C39: 0 | D39: 0 | E39: 0 | G39: 0
B40: BOND | C40: 0 | D40: 0 | E40: 0 | G40: 0
B41: TARIFF | C41: 0 | D41: 0 | E41: 0 | G41: 0
B42: GRAND TOTAL | C42: =C38+C39+C40+C41 -> 107132.73 | D42: =D38+D39+D40+D41 -> 123405.56 | E42: =IFERROR(D42-C42,0) -> 16272.83 | F42: =IFERROR(1-C42/D42,0) -> 0.13186464
B44: 9A Underpass 4 — Underpass 4 | D44: Selling Price
B45: LED Hardware | C45: ='LED Cost Sheet'!T7 -> 108490.64 | D45: ='LED Cost Sheet'!V7 -> 127636.05 | E45: =IFERROR(D45-C45,0) -> 19145.41 | F45: 0.15
B46: Structural Materials | C46: ='9A Underpass 4 - Install'!I26 -> 4342.5 | D46: =IFERROR(C46/(1-F46),0) -> 5108.82 | E46: =IFERROR(D46-C46,0) -> 766.32 | F46: 0.15
B47: Structural Labor & LED Installation | C47: ='9A Underpass 4 - Install'!I35-'9A Underpass 4 - Install'!I34 -> 18093.75 | D47: =IFERROR(C47/(1-F47),0) -> 21286.76 | E47: =IFERROR(D47-C47,0) -> 3193.01 | F47: 0.15
B48: Electrical & Data | C48: ='9A Underpass 4 - Install'!I44 -> 18093.75 | D48: =IFERROR(C48/(1-F48),0) -> 21286.76 | E48: =IFERROR(D48-C48,0) -> 3193.01 | F48: 0.15
B49: PM / General Conditions / Travel | C49: ='9A Underpass 4 - Install'!I34 -> 20882.35 | D49: =IFERROR(C49/(1-F49),0) -> 24567.47 | E49: =IFERROR(D49-C49,0) -> 3685.12 | F49: 0.15
B50: Engineering & Permits | C50: ='9A Underpass 4 - Install'!I52 -> 4705.88 | D50: =IFERROR(C50/(1-F50),0) -> 5536.33 | E50: =IFERROR(D50-C50,0) -> 830.45 | F50: 0.15
B51: SUBTOTAL | C51: =SUM(C45:C50) -> 174608.87 | D51: =SUM(D45:D50) -> 200987.02 | E51: =IFERROR(D51-C51,0) -> 26378.15 | F51: =IFERROR(1-C51/D51,0) -> 0.131243
B52: TAX | C52: 0 | D52: 0 | E52: 0 | G52: 0
B53: BOND | C53: 0 | D53: 0 | E53: 0 | G53: 0
B54: TARIFF | C54: 0 | D54: 0 | E54: 0 | G54: 0
B55: GRAND TOTAL | C55: =C51+C52+C53+C54 -> 174608.87 | D55: =D51+D52+D53+D54 -> 200987.02 | E55: =IFERROR(D55-C55,0) -> 26378.15 | F55: =IFERROR(1-C55/D55,0) -> 0.13124305
B57: Concourse — Concourse | D57: Selling Price
B58: LED Hardware | C58: ='LED Cost Sheet'!T8 -> 703632.13 | D58: ='LED Cost Sheet'!V8 -> 827802.51 | E58: =IFERROR(D58-C58,0) -> 124170.38 | F58: 0.15
B59: Structural Materials | C59: ='Concourse - Install'!I26 -> 30536.25 | D59: =IFERROR(C59/(1-F59),0) -> 35925 | E59: =IFERROR(D59-C59,0) -> 5388.75 | F59: 0.15
B60: Structural Labor & LED Installation | C60: ='Concourse - Install'!I35-'Concourse - Install'!I34 -> 127234.38 | D60: =IFERROR(C60/(1-F60),0) -> 149687.51 | E60: =IFERROR(D60-C60,0) -> 22453.13 | F60: 0.15
B61: Electrical & Data | C61: ='Concourse - Install'!I44 -> 127234.38 | D61: =IFERROR(C61/(1-F61),0) -> 149687.51 | E61: =IFERROR(D61-C61,0) -> 22453.13 | F61: 0.15
B62: PM / General Conditions / Travel | C62: ='Concourse - Install'!I34 -> 20882.35 | D62: =IFERROR(C62/(1-F62),0) -> 24567.47 | E62: =IFERROR(D62-C62,0) -> 3685.12 | F62: 0.15
B63: Engineering & Permits | C63: ='Concourse - Install'!I52 -> 4705.88 | D63: =IFERROR(C63/(1-F63),0) -> 5536.33 | E63: =IFERROR(D63-C63,0) -> 830.45 | F63: 0.15
B64: SUBTOTAL | C64: =SUM(C58:C63) -> 1014225.4 | D64: =SUM(D58:D63) -> 1162042.4 | E64: =IFERROR(D64-C64,0) -> 147817.07 | F64: =IFERROR(1-C64/D64,0) -> 0.127205
B65: TAX | C65: 0 | D65: 0 | E65: 0 | G65: 0
B66: BOND | C66: 0 | D66: 0 | E66: 0 | G66: 0
B67: TARIFF | C67: 0 | D67: 0 | E67: 0 | G67: 0
B68: GRAND TOTAL | C68: =C64+C65+C66+C67 -> 1014225.4 | D68: =D64+D65+D66+D67 -> 1162042.4 | E68: =IFERROR(D68-C68,0) -> 147817.07 | F68: =IFERROR(1-C68/D68,0) -> 0.12720454
B70: T4 Elevator — T4 Lobby Elevator | D70: Selling Price
B71: LED Hardware | C71: ='LED Cost Sheet'!T9 -> 112773.11 | D71: ='LED Cost Sheet'!V9 -> 132674.25 | E71: =IFERROR(D71-C71,0) -> 19901.14 | F71: 0.15
B72: Structural Materials | C72: ='T4 Elevator - Install'!I26 -> 4537.5 | D72: =IFERROR(C72/(1-F72),0) -> 5338.24 | E72: =IFERROR(D72-C72,0) -> 800.74 | F72: 0.15
B73: Structural Labor & LED Installation | C73: ='T4 Elevator - Install'!I35-'T4 Elevator - Install'!I34 -> 18906.25 | D73: =IFERROR(C73/(1-F73),0) -> 22242.65 | E73: =IFERROR(D73-C73,0) -> 3336.4 | F73: 0.15
B74: Electrical & Data | C74: ='T4 Elevator - Install'!I44 -> 18906.25 | D74: =IFERROR(C74/(1-F74),0) -> 22242.65 | E74: =IFERROR(D74-C74,0) -> 3336.4 | F74: 0.15
B75: PM / General Conditions / Travel | C75: ='T4 Elevator - Install'!I34 -> 20882.35 | D75: =IFERROR(C75/(1-F75),0) -> 24567.47 | E75: =IFERROR(D75-C75,0) -> 3685.12 | F75: 0.15
B76: Engineering & Permits | C76: ='T4 Elevator - Install'!I52 -> 4705.88 | D76: =IFERROR(C76/(1-F76),0) -> 5536.33 | E76: =IFERROR(D76-C76,0) -> 830.45 | F76: 0.15
B77: SUBTOTAL | C77: =SUM(C71:C76) -> 180711.34 | D77: =SUM(D71:D76) -> 207968.64 | E77: =IFERROR(D77-C77,0) -> 27257.3 | F77: =IFERROR(1-C77/D77,0) -> 0.131064
B78: TAX | C78: 0 | D78: 0 | E78: 0 | G78: 0
B79: BOND | C79: 0 | D79: 0 | E79: 0 | G79: 0
B80: TARIFF | C80: 0 | D80: 0 | E80: 0 | G80: 0
B81: GRAND TOTAL | C81: =C77+C78+C79+C80 -> 180711.34 | D81: =D77+D78+D79+D80 -> 207968.64 | E81: =IFERROR(D81-C81,0) -> 27257.3 | F81: =IFERROR(1-C81/D81,0) -> 0.13106447
B83: New Path Hall Option 1 — Path Hall | D83: Selling Price
B84: LED Hardware | C84: ='LED Cost Sheet'!T10 -> 183646.37 | D84: ='LED Cost Sheet'!V10 -> 216054.55 | E84: =IFERROR(D84-C84,0) -> 32408.18 | F84: 0.15
B85: Structural Materials | C85: ='New Path Hall Option 1 - Instal'!I26 -> 7740 | D85: =IFERROR(C85/(1-F85),0) -> 9105.88 | E85: =IFERROR(D85-C85,0) -> 1365.88 | F85: 0.15
B86: Structural Labor & LED Installation | C86: ='New Path Hall Option 1 - Instal'!I35-'New Path Hall Option 1 - Instal'!I34 -> 32250 | D86: =IFERROR(C86/(1-F86),0) -> 37941.18 | E86: =IFERROR(D86-C86,0) -> 5691.18 | F86: 0.15
B87: Electrical & Data | C87: ='New Path Hall Option 1 - Instal'!I44 -> 32250 | D87: =IFERROR(C87/(1-F87),0) -> 37941.18 | E87: =IFERROR(D87-C87,0) -> 5691.18 | F87: 0.15
B88: PM / General Conditions / Travel | C88: ='New Path Hall Option 1 - Instal'!I34 -> 20882.35 | D88: =IFERROR(C88/(1-F88),0) -> 24567.47 | E88: =IFERROR(D88-C88,0) -> 3685.12 | F88: 0.15
B89: Engineering & Permits | C89: ='New Path Hall Option 1 - Instal'!I52 -> 4705.88 | D89: =IFERROR(C89/(1-F89),0) -> 5536.33 | E89: =IFERROR(D89-C89,0) -> 830.45 | F89: 0.15
B90: SUBTOTAL | C90: =SUM(C84:C89) -> 281474.6 | D90: =SUM(D84:D89) -> 323240.71 | E90: =IFERROR(D90-C90,0) -> 41766.11 | F90: =IFERROR(1-C90/D90,0) -> 0.129211
B91: TAX | C91: 0 | D91: 0 | E91: 0 | G91: 0
B92: BOND | C92: 0 | D92: 0 | E92: 0 | G92: 0
B93: TARIFF | C93: 0 | D93: 0 | E93: 0 | G93: 0
B94: GRAND TOTAL | C94: =C90+C91+C92+C93 -> 281474.6 | D94: =D90+D91+D92+D93 -> 323240.71 | E94: =IFERROR(D94-C94,0) -> 41766.11 | F94: =IFERROR(1-C94/D94,0) -> 0.12921055
B96: New Path Hall Option 2 — Path Hall | D96: Selling Price
B97: LED Hardware | C97: ='LED Cost Sheet'!T11 -> 227719.24 | D97: ='LED Cost Sheet'!V11 -> 267904.99 | E97: =IFERROR(D97-C97,0) -> 40185.75 | F97: 0.15
B98: Structural Materials | C98: ='New Path Hall Option 2 - Instal'!I26 -> 9735 | D98: =IFERROR(C98/(1-F98),0) -> 11452.94 | E98: =IFERROR(D98-C98,0) -> 1717.94 | F98: 0.15
B99: Structural Labor & LED Installation | C99: ='New Path Hall Option 2 - Instal'!I35-'New Path Hall Option 2 - Instal'!I34 -> 40562.5 | D99: =IFERROR(C99/(1-F99),0) -> 47720.59 | E99: =IFERROR(D99-C99,0) -> 7158.09 | F99: 0.15
B100: Electrical & Data | C100: ='New Path Hall Option 2 - Instal'!I44 -> 40562.5 | D100: =IFERROR(C100/(1-F100),0) -> 47720.59 | E100: =IFERROR(D100-C100,0) -> 7158.09 | F100: 0.15
B101: PM / General Conditions / Travel | C101: ='New Path Hall Option 2 - Instal'!I34 -> 20882.35 | D101: =IFERROR(C101/(1-F101),0) -> 24567.47 | E101: =IFERROR(D101-C101,0) -> 3685.12 | F101: 0.15
B102: Engineering & Permits | C102: ='New Path Hall Option 2 - Instal'!I52 -> 4705.88 | D102: =IFERROR(C102/(1-F102),0) -> 5536.33 | E102: =IFERROR(D102-C102,0) -> 830.45 | F102: 0.15
B103: SUBTOTAL | C103: =SUM(C97:C102) -> 344167.47 | D103: =SUM(D97:D102) -> 394961.73 | E103: =IFERROR(D103-C103,0) -> 50794.26 | F103: =IFERROR(1-C103/D103,0) -> 0.128606
B104: TAX | C104: 0 | D104: 0 | E104: 0 | G104: 0
B105: BOND | C105: 0 | D105: 0 | E105: 0 | G105: 0
B106: TARIFF | C106: 0 | D106: 0 | E106: 0 | G106: 0
B107: GRAND TOTAL | C107: =C103+C104+C105+C106 -> 344167.47 | D107: =D103+D104+D105+D106 -> 394961.73 | E107: =IFERROR(D107-C107,0) -> 50794.26 | F107: =IFERROR(1-C107/D107,0) -> 0.12860552
B109: One Train — One Train | D109: Selling Price
...

Sheet Budget Summary
A1: Amended RFP Exhibit I — Budget Summary
A2: Westfield | 2026-03-31 | By Category
B4: Category | C4: Cost | D4: Selling Price | E4: Margin $ | F4: Margin % | G4: Price / SqFt
B5: LED Hardware (all displays) | C5: =SUM('LED Cost Sheet'!Q4:Q13) -> 1498517.3 | D5: =SUM('LED Cost Sheet'!S4:S13) -> 1762961.6 | E5: =IFERROR(D5-C5,0) -> 264444.23 | F5: 0.15 | G5: =IFERROR(C5/5566.5599999999995,0) -> 269.2
B6: Structural Materials | C6: =SUM('9A Underpass 1 - Install'!I26:I26)+SUM('9A Underpass 2 - Install'!I26:I26)+SUM('9A Underpass 3 - Install'!I26:I26)+SUM('9A Underpass 4 - Install'!I26:I26)+SUM('Concourse - Install'!I26:I26)+SUM('T4 Elevator - Install'!I26:I26)+SUM('New Path Hall Option 1 - Instal'!I26:I26)+SUM('New Path Hall Option 2 - Instal'!I26:I26)+SUM('One Train - Install'!I26:I26)+SUM('T4-B2 - Install'!I26:I26) -> 64147.5 | D6: =SUM('9A Underpass 1 - Install'!K26:K26)+SUM('9A Underpass 2 - Install'!K26:K26)+SUM('9A Underpass 3 - Install'!K26:K26)+SUM('9A Underpass 4 - Install'!K26:K26)+SUM('Concourse - Install'!K26:K26)+SUM('T4 Elevator - Install'!K26:K26)+SUM('New Path Hall Option 1 - Instal'!K26:K26)+SUM('New Path Hall Option 2 - Instal'!K26:K26)+SUM('One Train - Install'!K26:K26)+SUM('T4-B2 - Install'!K26:K26) -> 75467.65 | E6: =IFERROR(D6-C6,0) -> 11320.15 | F6: 0.15 | G6: =IFERROR(C6/5566.5599999999995,0) -> 11.52
B7: Structural Labor & LED Installation | C7: =(SUM('9A Underpass 1 - Install'!I35:I35)-SUM('9A Underpass 1 - Install'!I34:I34))+(SUM('9A Underpass 2 - Install'!I35:I35)-SUM('9A Underpass 2 - Install'!I34:I34))+(SUM('9A Underpass 3 - Install'!I35:I35)-SUM('9A Underpass 3 - Install'!I34:I34))+(SUM('9A Underpass 4 - Install'!I35:I35)-SUM('9A Underpass 4 - Install'!I34:I34))+(SUM('Concourse - Install'!I35:I35)-SUM('Concourse - Install'!I34:I34))+(SUM('T4 Elevator - Install'!I35:I35)-SUM('T4 Elevator - Install'!I34:I34))+(SUM('New Path Hall Option 1 - Instal'!I35:I35)-SUM('New Path Hall Option 1 - Instal'!I34:I34))+(SUM('New Path Hall Option 2 - Instal'!I35:I35)-SUM('New Path Hall Option 2 - Instal'!I34:I34))+(SUM('One Train - Install'!I35:I35)-SUM('One Train - Install'!I34:I34))+(SUM('T4-B2 - Install'!I35:I35)-SUM('T4-B2 - Install'!I34:I34)) -> 267281.26 | D7: =(SUM('9A Underpass 1 - Install'!K35:K35)-SUM('9A Underpass 1 - Install'!K34:K34))+(SUM('9A Underpass 2 - Install'!K35:K35)-SUM('9A Underpass 2 - Install'!K34:K34))+(SUM('9A Underpass 3 - Install'!K35:K35)-SUM('9A Underpass 3 - Install'!K34:K34))+(SUM('9A Underpass 4 - Install'!K35:K35)-SUM('9A Underpass 4 - Install'!K34:K34))+(SUM('Concourse - Install'!K35:K35)-SUM('Concourse - Install'!K34:K34))+(SUM('T4 Elevator - Install'!K35:K35)-SUM('T4 Elevator - Install'!K34:K34))+(SUM('New Path Hall Option 1 - Instal'!K35:K35)-SUM('New Path Hall Option 1 - Instal'!K34:K34))+(SUM('New Path Hall Option 2 - Instal'!K35:K35)-SUM('New Path Hall Option 2 - Instal'!K34:K34))+(SUM('One Train - Install'!K35:K35)-SUM('One Train - Install'!K34:K34))+(SUM('T4-B2 - Install'!K35:K35)-SUM('T4-B2 - Install'!K34:K34)) -> 314448.54 | E7: =IFERROR(D7-C7,0) -> 47167.28 | F7: 0.15 | G7: =IFERROR(C7/5566.5599999999995,0) -> 48.02
B8: Electrical & Data | C8: =SUM('9A Underpass 1 - Install'!I44:I44)+SUM('9A Underpass 2 - Install'!I44:I44)+SUM('9A Underpass 3 - Install'!I44:I44)+SUM('9A Underpass 4 - Install'!I44:I44)+SUM('Concourse - Install'!I44:I44)+SUM('T4 Elevator - Install'!I44:I44)+SUM('New Path Hall Option 1 - Instal'!I44:I44)+SUM('New Path Hall Option 2 - Instal'!I44:I44)+SUM('One Train - Install'!I44:I44)+SUM('T4-B2 - Install'!I44:I44) -> 267281.26 | D8: =SUM('9A Underpass 1 - Install'!K44:K44)+SUM('9A Underpass 2 - Install'!K44:K44)+SUM('9A Underpass 3 - Install'!K44:K44)+SUM('9A Underpass 4 - Install'!K44:K44)+SUM('Concourse - Install'!K44:K44)+SUM('T4 Elevator - Install'!K44:K44)+SUM('New Path Hall Option 1 - Instal'!K44:K44)+SUM('New Path Hall Option 2 - Instal'!K44:K44)+SUM('One Train - Install'!K44:K44)+SUM('T4-B2 - Install'!K44:K44) -> 314448.54 | E8: =IFERROR(D8-C8,0) -> 47167.28 | F8: 0.15 | G8: =IFERROR(C8/5566.5599999999995,0) -> 48.02
B9: PM / General Conditions / Travel | C9: =SUM('9A Underpass 1 - Install'!I34:I34)+SUM('9A Underpass 2 - Install'!I34:I34)+SUM('9A Underpass 3 - Install'!I34:I34)+SUM('9A Underpass 4 - Install'!I34:I34)+SUM('Concourse - Install'!I34:I34)+SUM('T4 Elevator - Install'!I34:I34)+SUM('New Path Hall Option 1 - Instal'!I34:I34)+SUM('New Path Hall Option 2 - Instal'!I34:I34)+SUM('One Train - Install'!I34:I34)+SUM('T4-B2 - Install'!I34:I34) -> 193823.5 | D9: =SUM('9A Underpass 1 - Install'!K34:K34)+SUM('9A Underpass 2 - Install'!K34:K34)+SUM('9A Underpass 3 - Install'!K34:K34)+SUM('9A Underpass 4 - Install'!K34:K34)+SUM('Concourse - Install'!K34:K34)+SUM('T4 Elevator - Install'!K34:K34)+SUM('New Path Hall Option 1 - Instal'!K34:K34)+SUM('New Path Hall Option 2 - Instal'!K34:K34)+SUM('One Train - Install'!K34:K34)+SUM('T4-B2 - Install'!K34:K34) -> 228027.65 | E9: =IFERROR(D9-C9,0) -> 34204.15 | F9: 0.15
B10: Engineering & Permits | C10: =SUM('9A Underpass 1 - Install'!I52:I52)+SUM('9A Underpass 2 - Install'!I52:I52)+SUM('9A Underpass 3 - Install'!I52:I52)+SUM('9A Underpass 4 - Install'!I52:I52)+SUM('Concourse - Install'!I52:I52)+SUM('T4 Elevator - Install'!I52:I52)+SUM('New Path Hall Option 1 - Instal'!I52:I52)+SUM('New Path Hall Option 2 - Instal'!I52:I52)+SUM('One Train - Install'!I52:I52)+SUM('T4-B2 - Install'!I52:I52) -> 47058.8 | D10: =SUM('9A Underpass 1 - Install'!K52:K52)+SUM('9A Underpass 2 - Install'!K52:K52)+SUM('9A Underpass 3 - Install'!K52:K52)+SUM('9A Underpass 4 - Install'!K52:K52)+SUM('Concourse - Install'!K52:K52)+SUM('T4 Elevator - Install'!K52:K52)+SUM('New Path Hall Option 1 - Instal'!K52:K52)+SUM('New Path Hall Option 2 - Instal'!K52:K52)+SUM('One Train - Install'!K52:K52)+SUM('T4-B2 - Install'!K52:K52) -> 55363.29 | E10: =IFERROR(D10-C10,0) -> 8304.49 | F10: 0.15
B11: CMS (Content Management System) | C11: =SUM(CMS!F26:F26) -> 0 | D11: =SUM(CMS!H26:H26) -> 0 | E11: =IFERROR(D11-C11,0) -> 0 | F11: 0.15
B12: Scoring System | C12: =SUM(Scoring!F27:F27) -> 0 | D12: =SUM(Scoring!H27:H27) -> 0 | E12: =IFERROR(D12-C12,0) -> 0 | F12: 0.15
B13: Venue Services | C13: =SUM('Venue Services'!B17:B17) -> 0 | D13: =SUM('Venue Services'!C17:C17) -> 0 | E13: =IFERROR(D13-C13,0) -> 0 | F13: 0.15
B14: Game Clock | C14: =SUM('Additional Items'!F5:F5) -> 0 | D14: =SUM('Additional Items'!H5:H5) -> 0 | E14: =IFERROR(D14-C14,0) -> 0 | F14: 0.15
B15: Pitch Clocks | C15: =SUM('Additional Items'!F6:F6) -> 0 | D15: =SUM('Additional Items'!H6:H6) -> 0 | E15: =IFERROR(D15-C15,0) -> 0 | F15: 0.15
B16: OES / MIS / Timing | C16: =SUM('Additional Items'!F7:F7) -> 0 | D16: =SUM('Additional Items'!H7:H7) -> 0 | E16: =IFERROR(D16-C16,0) -> 0 | F16: 0.15
B17: DMX / Misc Equipment | C17: =SUM('Additional Items'!F8:F8) -> 0 | D17: =SUM('Additional Items'!H8:H8) -> 0 | E17: =IFERROR(D17-C17,0) -> 0 | F17: 0.15
B19: SUBTOTAL | C19: =SUM(C5:C17) -> 2338109.6 | D19: =SUM(D5:D17) -> 2685228.3 | E19: =IFERROR(D19-C19,0) -> 347118.63 | F19: =IFERROR(1-C19/D19,0) -> 0.13 | G19: =IFERROR(C19/5566.5599999999995,0) -> 420.03
B20: TAX | C20: 0 | D20: 0 | E20: 0 | F20: 0
B21: BOND | C21: 0 | D21: 0 | E21: 0 | F21: 0
B22: GRAND TOTAL | C22: =C19+C20+C21 -> 2338109.6 | D22: =D19+D20+D21 -> 2685228.3 | E22: =IFERROR(D22-C22,0) -> 347118.63 | F22: =IFERROR(1-C22/D22,0) -> 0.13 | G22: =IFERROR(C22/5566.5599999999995,0) -> 420.03

Sheet LED Cost Sheet
A1: Amended RFP Exhibit I — LED Cost Sheet
U2: LED Margin Override → | V2: 0.15
A3: Display | B3: RFP H (ft) | C3: RFP W (ft) | D3: RFP NITs | E3: Vendor | F3: Product | G3: Pitch | H3: H (ft) | I3: W (ft) | J3: H (px) | K3: W (px) | L3: Qty | M3: Total SqFt | N3: Product NITs | O3: Service | P3: $/SqFt | Q3: Display Cost | R3: Processor | S3: Shipping | T3: Total Cost | U3: Margin % | V3: Selling Price | W3: ANC Margin | X3: Weight (lbs) | Y3: Total Power (W) | Z3: BTU/hr
A4: 9A Underpass 1 — Underpass 1 | B4: 6.3 | C4: 18.11 | D4: 8000 | E4: LG/Yaham | F4: C2.5-MIP 2.5mm Indoor (Alt) | G4: 3.9mm | H4: 6.3 | I4: 18.11 | J4: 492 | K4: 1415 | L4: 1 | M4: =H4*I4*L4 -> 114.09 | N4: 7500 | O4: Front | P4: 244.16 | Q4: 27855.82 | R4: =SUM('Bundle Equipment'!E10:E10) -> 518.45 | S4: 1140.9 | T4: 29515.17 | U4: =V$2 -> 0.135354 | V4: 77897.05 | W4: 10543.65 | X4: 577 | Y4: 5234 | Z4: =Y4*3.412 -> 17858
A5: 9A Underpass 2 — Underpass 2 | B5: 7.48 | C5: 29.92 | D5: 8000 | E5: LG/Yaham | F5: C2.5-MIP 2.5mm Indoor (Alt) | G5: 3.9mm | H5: 7.48 | I5: 29.92 | J5: 585 | K5: 2338 | L5: 1 | M5: =H5*I5*L5 -> 223.8 | N5: 7500 | O5: Front | P5: 244.16 | Q5: 54642.22 | R5: =SUM('Bundle Equipment'!E15:E15) -> 584.28 | S5: 2238 | T5: 57464.5 | U5: =V$2 -> 0.131865 | V5: 123405.56 | W5: 16272.83 | X5: 1132 | Y5: 10268 | Z5: =Y5*3.412 -> 35034
A6: 9A Underpass 3 — Underpass 3 | B6: 7.48 | C6: 29.92 | D6: 8000 | E6: LG/Yaham | F6: C2.5-MIP 2.5mm Indoor (Alt) | G6: 3.9mm | H6: 7.48 | I6: 29.92 | J6: 585 | K6: 2338 | L6: 1 | M6: =H6*I6*L6 -> 223.8 | N6: 7500 | O6: Front | P6: 244.16 | Q6: 54642.22 | R6: =SUM('Bundle Equipment'!E20:E20) -> 584.28 | S6: 2238 | T6: 57464.5 | U6: =V$2 -> 0.131865 | V6: 123405.56 | W6: 16272.83 | X6: 1132 | Y6: 10268 | Z6: =Y6*3.412 -> 35034
A7: 9A Underpass 4 — Underpass 4 | B7: 12.6 | C7: 29.92 | D7: 8000 | E7: LG/Yaham | F7: C2.5-MIP 2.5mm Indoor (Alt) | G7: 3.9mm | H7: 12.6 | I7: 29.92 | J7: 985 | K7: 2338 | L7: 1 | M7: =H7*I7*L7 -> 376.99 | N7: 7500 | O7: Front | P7: 244.16 | Q7: 92044.55 | R7: =SUM('Bundle Equipment'!E26:E26) -> 12676.19 | S7: 3769.9 | T7: 108490.64 | U7: =V$2 -> 0.131243 | V7: 200987.02 | W7: 26378.15 | X7: 1907 | Y7: 17296 | Z7: =Y7*3.412 -> 59014
A8: Concourse — Concourse | B8: 9.45 | C8: 280.31 | D8: 8000 | E8: LG/Yaham | F8: C2.5-MIP 2.5mm Indoor (Alt) | G8: 3.9mm | H8: 9.45 | I8: 280.31 | J8: 739 | K8: 21907 | L8: 1 | M8: =H8*I8*L8 -> 2648.93 | N8: 7500 | O8: Front | P8: 244.16 | Q8: 646753.47 | R8: =SUM('Bundle Equipment'!E32:E32) -> 30389.36 | S8: 26489.3 | T8: 703632.13 | U8: =V$2 -> 0.127205 | V8: 1162042.4 | W8: 147817.07 | X8: 13398 | Y8: 121528 | Z8: =Y8*3.412 -> 414654
A9: T4 Elevator — T4 Lobby Elevator | B9: 71.6 | C9: 5.5 | D9: 8000 | E9: LG/Yaham | F9: C2.5-MIP 2.5mm Indoor (Alt) | G9: 3.9mm | H9: 71.6 | I9: 5.5 | J9: 5596 | K9: 430 | L9: 1 | M9: =H9*I9*L9 -> 393.8 | N9: 7500 | O9: Front | P9: 244.16 | Q9: 96148.83 | R9: =SUM('Bundle Equipment'!E38:E38) -> 12686.28 | S9: 3938 | T9: 112773.11 | U9: =V$2 -> 0.131064 | V9: 207968.64 | W9: 27257.3 | X9: 1992 | Y9: 18067 | Z9: =Y9*3.412 -> 61645
A10: New Path Hall Option 1 — Path Hall | B10: 48 | C10: 14 | D10: 8000 | E10: LG/Yaham | F10: C2.5-MIP 2.5mm Indoor (Alt) | G10: 3.9mm | H10: 48 | I10: 14 | J10: 3751 | K10: 1094 | L10: 1 | M10: =H10*I10*L10 -> 672 | N10: 7500 | O10: Front | P10: 244.16 | Q10: 164073.17 | R10: =SUM('Bundle Equipment'!E44:E44) -> 12853.2 | S10: 6720 | T10: 183646.37 | U10: =V$2 -> 0.129211 | V10: 323240.71 | W10: 41766.11 | X10: 3399 | Y10: 30830 | Z10: =Y10*3.412 -> 105192
A11: New Path Hall Option 2 — Path Hall | B11: 65 | C11: 13 | D11: 8000 | E11: LG/Yaham | F11: C2.5-MIP 2.5mm Indoor (Alt) | G11: 3.9mm | H11: 65 | I11: 13 | J11: 5080 | K11: 1016 | L11: 1 | M11: =H11*I11*L11 -> 845 | N11: 7500 | O11: Front | P11: 244.16 | Q11: 206312.24 | R11: =SUM('Bundle Equipment'!E50:E50) -> 12957 | S11: 8450 | T11: 227719.24 | U11: =V$2 -> 0.128606 | V11: 394961.73 | W11: 50794.26 | X11: 4274 | Y11: 38767 | Z11: =Y11*3.412 -> 132273
A12: One Train — One Train | D12: 8000 | E12: LG/Yaham | F12: C2.5-MIP 2.5mm Indoor (Alt) | G12: 3.9mm | H12: 0 | I12: 0 | J12: 0 | K12: 0 | L12: 1 | M12: =H12*I12*L12 -> 0 | N12: 7500 | O12: Front | P12: 0 | Q12: 0 | R12: =SUM('Bundle Equipment'!E54:E54) -> 0 | S12: 0 | T12: 0 | U12: =V$2 -> 0.15 | V12: 12456.74 | W12: 1868.51
A13: T4-B2 — T4-B2 | B13: 7.87 | C13: 8.66 | D13: 8000 | E13: LG/Yaham | F13: C2.5-MIP 2.5mm Indoor (Alt) | G13: 3.9mm | H13: 7.87 | I13: 8.66 | J13: 615 | K13: 677 | L13: 1 | M13: =H13*I13*L13 -> 68.15 | N13: 7500 | O13: Front | P13: 244.16 | Q13: 16639.27 | R13: =SUM('Bundle Equipment'!E59:E59) -> 490.89 | S13: 681.5 | T13: 17811.66 | U13: =V$2 -> 0.138422 | V13: 58862.82 | W13: 8147.92 | X13: 345 | Y13: 3127 | Z13: =Y13*3.412 -> 10669
A15: TOTAL (10 displays) | M15: =M4+M5+M6+M7+M8+M9+M10+M11+M12+M13 -> 5566.56 | Q15: =Q4+Q5+Q6+Q7+Q8+Q9+Q10+Q11+Q12+Q13 -> 1359111.8 | R15: =R4+R5+R6+R7+R8+R9+R10+R11+R12+R13 -> 83739.93 | S15: =S4+S5+S6+S7+S8+S9+S10+S11+S12+S13 -> 55665.6 | T15: =T4+T5+T6+T7+T8+T9+T10+T11+T12+T13 -> 1498517.3 | U15: =IFERROR(1-T15/V15,0) -> 0.15 | V15: =V4+V5+V6+V7+V8+V9+V10+V11+V12+V13 -> 1762961.6 | W15: =W4+W5+W6+W7+W8+W9+W10+W11+W12+W13 -> 264444.23 | X15: =X4+X5+X6+X7+X8+X9+X10+X11+X12+X13 -> 38032 | Y15: =Y4+Y5+Y6+Y7+Y8+Y9+Y10+Y11+Y12+Y13 -> 718675 | Z15: =Z4+Z5+Z6+Z7+Z8+Z9+Z10+Z11+Z12+Z13 -> 2452119

Sheet Tech Specs (Installers)
A1: Amended RFP Exhibit I — LED Technical Specifications (No Pricing)
A2: Technical specifications only — no pricing data. Safe for installer/subcontractor distribution.
A4: Display Name | B4: Qty | C4: Pixel Pitch | D4: Height (ft) | E4: Width (ft) | F4: Pixels H | G4: Pixels W | H4: Sq Ft | I4: Brightness (nits) | J4: Service | K4: Environment | L4: Weight (lbs) | M4: Total Power (W) | N4: Fiber Strands | O4: BTU/hr
A5: ='LED Cost Sheet'!A4 -> 9A Underpass 1 — Underpass 1 | B5: ='LED Cost Sheet'!I4 -> 1 | C5: ='LED Cost Sheet'!D4 -> 3.9mm | D5: ='LED Cost Sheet'!E4 -> 6.3 | E5: ='LED Cost Sheet'!F4 -> 18.11 | F5: ='LED Cost Sheet'!G4 -> 492 | G5: ='LED Cost Sheet'!H4 -> 1415 | H5: =D5*E5*B5 -> 114.09 | I5: ='LED Cost Sheet'!K4 -> 8000 | J5: ='LED Cost Sheet'!L4 -> Front | K5: indoor | L5: ='LED Cost Sheet'!U4 -> 577 | M5: ='LED Cost Sheet'!V4 -> 5234 | N5: =IFERROR((F5*G5*B5)/400000,0) -> 1.74 | O5: ='LED Cost Sheet'!W4 -> 17858
A6: ='LED Cost Sheet'!A5 -> 9A Underpass 2 — Underpass 2 | B6: ='LED Cost Sheet'!I5 -> 1 | C6: ='LED Cost Sheet'!D5 -> 3.9mm | D6: ='LED Cost Sheet'!E5 -> 7.48 | E6: ='LED Cost Sheet'!F5 -> 29.92 | F6: ='LED Cost Sheet'!G5 -> 585 | G6: ='LED Cost Sheet'!H5 -> 2338 | H6: =D6*E6*B6 -> 223.8 | I6: ='LED Cost Sheet'!K5 -> 8000 | J6: ='LED Cost Sheet'!L5 -> Front | K6: indoor | L6: ='LED Cost Sheet'!U5 -> 1132 | M6: ='LED Cost Sheet'!V5 -> 10268 | N6: =IFERROR((F6*G6*B6)/400000,0) -> 3.42 | O6: ='LED Cost Sheet'!W5 -> 35034
A7: ='LED Cost Sheet'!A6 -> 9A Underpass 3 — Underpass 3 | B7: ='LED Cost Sheet'!I6 -> 1 | C7: ='LED Cost Sheet'!D6 -> 3.9mm | D7: ='LED Cost Sheet'!E6 -> 7.48 | E7: ='LED Cost Sheet'!F6 -> 29.92 | F7: ='LED Cost Sheet'!G6 -> 585 | G7: ='LED Cost Sheet'!H6 -> 2338 | H7: =D7*E7*B7 -> 223.8 | I7: ='LED Cost Sheet'!K6 -> 8000 | J7: ='LED Cost Sheet'!L6 -> Front | K7: indoor | L7: ='LED Cost Sheet'!U6 -> 1132 | M7: ='LED Cost Sheet'!V6 -> 10268 | N7: =IFERROR((F7*G7*B7)/400000,0) -> 3.42 | O7: ='LED Cost Sheet'!W6 -> 35034
A8: ='LED Cost Sheet'!A7 -> 9A Underpass 4 — Underpass 4 | B8: ='LED Cost Sheet'!I7 -> 1 | C8: ='LED Cost Sheet'!D7 -> 3.9mm | D8: ='LED Cost Sheet'!E7 -> 12.6 | E8: ='LED Cost Sheet'!F7 -> 29.92 | F8: ='LED Cost Sheet'!G7 -> 985 | G8: ='LED Cost Sheet'!H7 -> 2338 | H8: =D8*E8*B8 -> 376.99 | I8: ='LED Cost Sheet'!K7 -> 8000 | J8: ='LED Cost Sheet'!L7 -> Front | K8: indoor | L8: ='LED Cost Sheet'!U7 -> 1907 | M8: ='LED Cost Sheet'!V7 -> 17296 | N8: =IFERROR((F8*G8*B8)/400000,0) -> 5.76 | O8: ='LED Cost Sheet'!W7 -> 59014
A9: ='LED Cost Sheet'!A8 -> Concourse — Concourse | B9: ='LED Cost Sheet'!I8 -> 1 | C9: ='LED Cost Sheet'!D8 -> 3.9mm | D9: ='LED Cost Sheet'!E8 -> 9.45 | E9: ='LED Cost Sheet'!F8 -> 280.31 | F9: ='LED Cost Sheet'!G8 -> 739 | G9: ='LED Cost Sheet'!H8 -> 21907 | H9: =D9*E9*B9 -> 2648.93 | I9: ='LED Cost Sheet'!K8 -> 8000 | J9: ='LED Cost Sheet'!L8 -> Front | K9: indoor | L9: ='LED Cost Sheet'!U8 -> 13398 | M9: ='LED Cost Sheet'!V8 -> 121528 | N9: =IFERROR((F9*G9*B9)/400000,0) -> 40.47 | O9: ='LED Cost Sheet'!W8 -> 414654
A10: ='LED Cost Sheet'!A9 -> T4 Elevator — T4 Lobby Elevator | B10: ='LED Cost Sheet'!I9 -> 1 | C10: ='LED Cost Sheet'!D9 -> 3.9mm | D10: ='LED Cost Sheet'!E9 -> 71.6 | E10: ='LED Cost Sheet'!F9 -> 5.5 | F10: ='LED Cost Sheet'!G9 -> 5596 | G10: ='LED Cost Sheet'!H9 -> 430 | H10: =D10*E10*B10 -> 393.8 | I10: ='LED Cost Sheet'!K9 -> 8000 | J10: ='LED Cost Sheet'!L9 -> Front | K10: indoor | L10: ='LED Cost Sheet'!U9 -> 1992 | M10: ='LED Cost Sheet'!V9 -> 18067 | N10: =IFERROR((F10*G10*B10)/400000,0) -> 6.02 | O10: ='LED Cost Sheet'!W9 -> 61645
A11: ='LED Cost Sheet'!A10 -> New Path Hall Option 1 — Path Hall | B11: ='LED Cost Sheet'!I10 -> 1 | C11: ='LED Cost Sheet'!D10 -> 3.9mm | D11: ='LED Cost Sheet'!E10 -> 48 | E11: ='LED Cost Sheet'!F10 -> 14 | F11: ='LED Cost Sheet'!G10 -> 3751 | G11: ='LED Cost Sheet'!H10 -> 1094 | H11: =D11*E11*B11 -> 672 | I11: ='LED Cost Sheet'!K10 -> 8000 | J11: ='LED Cost Sheet'!L10 -> Front | K11: indoor | L11: ='LED Cost Sheet'!U10 -> 3399 | M11: ='LED Cost Sheet'!V10 -> 30830 | N11: =IFERROR((F11*G11*B11)/400000,0) -> 10.26 | O11: ='LED Cost Sheet'!W10 -> 105192
A12: ='LED Cost Sheet'!A11 -> New Path Hall Option 2 — Path Hall | B12: ='LED Cost Sheet'!I11 -> 1 | C12: ='LED Cost Sheet'!D11 -> 3.9mm | D12: ='LED Cost Sheet'!E11 -> 65 | E12: ='LED Cost Sheet'!F11 -> 13 | F12: ='LED Cost Sheet'!G11 -> 5080 | G12: ='LED Cost Sheet'!H11 -> 1016 | H12: =D12*E12*B12 -> 845 | I12: ='LED Cost Sheet'!K11 -> 8000 | J12: ='LED Cost Sheet'!L11 -> Front | K12: indoor | L12: ='LED Cost Sheet'!U11 -> 4274 | M12: ='LED Cost Sheet'!V11 -> 38767 | N12: =IFERROR((F12*G12*B12)/400000,0) -> 12.9 | O12: ='LED Cost Sheet'!W11 -> 132273
A13: ='LED Cost Sheet'!A12 -> One Train — One Train | B13: ='LED Cost Sheet'!I12 -> 1 | C13: ='LED Cost Sheet'!D12 -> 3.9mm | D13: ='LED Cost Sheet'!E12 -> 0 | E13: ='LED Cost Sheet'!F12 -> 0 | F13: ='LED Cost Sheet'!G12 -> 0 | G13: ='LED Cost Sheet'!H12 -> 0 | H13: =D13*E13*B13 -> 0 | I13: ='LED Cost Sheet'!K12 -> 8000 | J13: ='LED Cost Sheet'!L12 -> Front | K13: indoor | L13: ='LED Cost Sheet'!U12 -> 0 | M13: ='LED Cost Sheet'!V12 -> 0 | N13: =IFERROR((F13*G13*B13)/400000,0) -> 0 | O13: ='LED Cost Sheet'!W12 -> 0
A14: ='LED Cost Sheet'!A13 -> T4-B2 — T4-B2 | B14: ='LED Cost Sheet'!I13 -> 1 | C14: ='LED Cost Sheet'!D13 -> 3.9mm | D14: ='LED Cost Sheet'!E13 -> 7.87 | E14: ='LED Cost Sheet'!F13 -> 8.66 | F14: ='LED Cost Sheet'!G13 -> 615 | G14: ='LED Cost Sheet'!H13 -> 677 | H14: =D14*E14*B14 -> 68.15 | I14: ='LED Cost Sheet'!K13 -> 8000 | J14: ='LED Cost Sheet'!L13 -> Front | K14: indoor | L14: ='LED Cost Sheet'!U13 -> 345 | M14: ='LED Cost Sheet'!V13 -> 3127 | N14: =IFERROR((F14*G14*B14)/400000,0) -> 1.04 | O14: ='LED Cost Sheet'!W13 -> 10669

Sheet 9A Underpass 1 - Install
A3: Project Name: Amended RFP Exhibit I
A4: 2026-03-31
A5: Revised By: ANC Proposal Engine
C7: Linked Margin Assignment
C8: Install Margin | D8: 0.15
C9: Electrical Margin | D9: 0.15
C10: ANC Margin | D10: 0.15
C11: Engineering and Permits | D11: 0.15
B15: 9A Underpass 1
B16: Height | C16: Width | D16: Total Sq. Ft | E16: QTY
B17: 6.3 | C17: 18.11 | D17: 114.09 | E17: 1
B19: Structural Materials: | C19: Subcontractor 1 | D19: Subcontractor 2 | E19: Subcontractor 3 | F19: Selected | G19: Additional Contingency | I19: Total Cost | J19: Install Margin | K19: Selling Price
B20: FABRICATE PRIMARY STEEL | C20: 0 | D20: 0 | E20: 0 | F20: 0 | G20: 0 | I20: =SUM(C20:G20) -> 0 | J20: =$D$8 -> 0.15 | K20: =I20/(1-J20) -> 0
B21: SUPPLY AND INSTALL PRIMARY PLYWOOD | C21: 0 | D21: 0 | E21: 0 | F21: 0 | G21: 0 | I21: =SUM(C21:G21) -> 0 | J21: =$D$8 -> 0.15 | K21: =I21/(1-J21) -> 0
B22: FABRICATE SECONDARY STEEL SUBSTRUCTURE | C22: 1312.5 | D22: 0 | E22: 0 | F22: 0 | G22: 0 | I22: =SUM(C22:G22) -> 1312.5 | J22: =$D$8 -> 0.15 | K22: =I22/(1-J22) -> 1544.12
B23: FABRICATE CLADDING AND TRIM | C23: 0 | D23: 0 | E23: 0 | F23: 0 | G23: 0 | I23: =SUM(C23:G23) -> 0 | J23: =$D$8 -> 0.15 | K23: =I23/(1-J23) -> 0
B24: OTHER SCOPE ITEM | C24: 0 | D24: 0 | E24: 0 | F24: 0 | G24: 0 | I24: =SUM(C24:G24) -> 0 | J24: =$D$8 -> 0.15 | K24: =I24/(1-J24) -> 0
B25: OTHER SCOPE ITEM | C25: 0 | D25: 0 | E25: 0 | F25: 0 | G25: 0 | I25: =SUM(C25:G25) -> 0 | J25: =$D$8 -> 0.15 | K25: =I25/(1-J25) -> 0
B26: SUBTOTAL | I26: =SUM(I20:I25) -> 1312.5 | K26: =SUM(K20:K25) -> 1544.12
B28: Structural Labor and LED Installation | C28: Subcontractor 1 | D28: Subcontractor 2 | E28: Subcontractor 3 | F28: Selected | G28: Additional Contingency | I28: Total Cost | J28: Install Margin | K28: Selling Price
B29: REMOVAL AND DISPOSAL | C29: 0 | D29: 0 | E29: 0 | F29: 0 | G29: 0 | I29: =SUM(C29:G29) -> 0 | J29: =$D$8 -> 0.15 | K29: =I29/(1-J29) -> 0
B30: INSTALL SECONDARY STEEL SUBSTRUCTURE | C30: 0 | D30: 0 | E30: 0 | F30: 0 | G30: 0 | I30: =SUM(C30:G30) -> 0 | J30: =$D$8 -> 0.15 | K30: =I30/(1-J30) -> 0
B31: INSTALL LED DISPLAYS | C31: 5468.75 | D31: 0 | E31: 0 | F31: 0 | G31: 0 | I31: =SUM(C31:G31) -> 5468.75 | J31: =$D$8 -> 0.15 | K31: =I31/(1-J31) -> 6433.82
B32: INSTALL CLADDING AND TRIM | C32: 0 | D32: 0 | E32: 0 | F32: 0 | G32: 0 | I32: =SUM(C32:G32) -> 0 | J32: =$D$8 -> 0.15 | K32: =I32/(1-J32) -> 0
B33: HEAVY EQUIPMENT | C33: 0 | D33: 0 | E33: 0 | F33: 0 | G33: 0 | I33: =SUM(C33:G33) -> 0 | J33: =$D$8 -> 0.15 | K33: =I33/(1-J33) -> 0
B34: PM/GENERAL CONDITIONS/TRAVEL | C34: 20882.35 | D34: 0 | E34: 0 | F34: 0 | G34: 0 | I34: =SUM(C34:G34) -> 20882.35 | J34: =$D$8 -> 0.15 | K34: =I34/(1-J34) -> 24567.47
B35: SUBTOTAL | I35: =SUM(I29:I34) -> 26351.1 | K35: =SUM(K29:K34) -> 31001.29
B37: Electrical and Data - Materials and Subcontracting | C37: Subcontractor 1 | D37: Subcontractor 2 | E37: Subcontractor 3 | F37: Selected | G37: Additional Contingency | I37: Total Cost | J37: Install Margin | K37: Selling Price
B38: ELECTRICAL MATERIALS | C38: 5468.75 | D38: 0 | E38: 0 | F38: 0 | G38: 0 | I38: =SUM(C38:G38) -> 5468.75 | J38: =$D$9 -> 0.15 | K38: =I38/(1-J38) -> 6433.82
B39: DATA MATERIALS | C39: 0 | D39: 0 | E39: 0 | F39: 0 | G39: 0 | I39: =SUM(C39:G39) -> 0 | J39: =$D$9 -> 0.15 | K39: =I39/(1-J39) -> 0
B40: ELECTRICAL LABOR | C40: 0 | D40: 0 | E40: 0 | F40: 0 | G40: 0 | I40: =SUM(C40:G40) -> 0 | J40: =$D$9 -> 0.15 | K40: =I40/(1-J40) -> 0
B41: DATA LABOR | C41: 0 | D41: 0 | E41: 0 | F41: 0 | G41: 0 | I41: =SUM(C41:G41) -> 0 | J41: =$D$9 -> 0.15 | K41: =I41/(1-J41) -> 0
B42: SUB PANEL | C42: 0 | D42: 0 | E42: 0 | F42: 0 | G42: 0 | I42: =SUM(C42:G42) -> 0 | J42: =$D$9 -> 0.15 | K42: =I42/(1-J42) -> 0
B43: MISC | C43: 0 | D43: 0 | E43: 0 | F43: 0 | G43: 0 | I43: =SUM(C43:G43) -> 0 | J43: =$D$9 -> 0.15 | K43: =I43/(1-J43) -> 0
B44: SUBTOTAL | I44: =SUM(I38:I43) -> 5468.75 | K44: =SUM(K38:K43) -> 6433.82
B46: Submittals, Engineering, and Permits | C46: Subcontractor 1 | D46: Subcontractor 2 | E46: Subcontractor 3 | F46: Selected | G46: Additional Contingency | I46: Total Cost | J46: Install Margin | K46: Selling Price
B47: STRUCTURAL ENGINEERING | C47: 4705.88 | D47: 0 | E47: 0 | F47: 0 | G47: 0 | I47: =SUM(C47:G47) -> 4705.88 | J47: =$D$11 -> 0.15 | K47: =I47/(1-J47) -> 5536.33
B48: STRUCTURAL CERTIFICATION | C48: 0 | D48: 0 | E48: 0 | F48: 0 | G48: 0 | I48: =SUM(C48:G48) -> 0 | J48: =$D$11 -> 0.15 | K48: =I48/(1-J48) -> 0
B49: ELECTRICAL ENGINEERING | C49: 0 | D49: 0 | E49: 0 | F49: 0 | G49: 0 | I49: =SUM(C49:G49) -> 0 | J49: =$D$11 -> 0.15 | K49: =I49/(1-J49) -> 0
B50: ELECTRICAL CERTIFICATION | C50: 0 | D50: 0 | E50: 0 | F50: 0 | G50: 0 | I50: =SUM(C50:G50) -> 0 | J50: =$D$11 -> 0.15 | K50: =I50/(1-J50) -> 0
B51: PERMITS | C51: 0 | D51: 0 | E51: 0 | F51: 0 | G51: 0 | I51: =SUM(C51:G51) -> 0 | J51: =$D$11 -> 0.15 | K51: =I51/(1-J51) -> 0
B52: SUBTOTAL | I52: =SUM(I47:I51) -> 4705.88 | K52: =SUM(K47:K51) -> 5536.33
B54: ZONE GRAND TOTAL | I54: =I26+I35+I44+I52 -> 67353.4 | K54: =K26+K35+K44+K52 -> 77897.05

Sheet 9A Underpass 2 - Install
A3: Project Name: Amended RFP Exhibit I
A4: 2026-03-31
A5: Revised By: ANC Proposal Engine
C7: Linked Margin Assignment
C8: Install Margin | D8: 0.15
C9: Electrical Margin | D9: 0.15
C10: ANC Margin | D10: 0.15
C11: Engineering and Permits | D11: 0.15
B15: 9A Underpass 2
B16: Height | C16: Width | D16: Total Sq. Ft | E16: QTY
B17: 7.48 | C17: 29.92 | D17: 223.8 | E17: 1
B19: Structural Materials: | C19: Subcontractor 1 | D19: Subcontractor 2 | E19: Subcontractor 3 | F19: Selected | G19: Additional Contingency | I19: Total Cost | J19: Install Margin | K19: Selling Price
B20: FABRICATE PRIMARY STEEL | C20: 0 | D20: 0 | E20: 0 | F20: 0 | G20: 0 | I20: =SUM(C20:G20) -> 0 | J20: =$D$8 -> 0.15 | K20: =I20/(1-J20) -> 0
B21: SUPPLY AND INSTALL PRIMARY PLYWOOD | C21: 0 | D21: 0 | E21: 0 | F21: 0 | G21: 0 | I21: =SUM(C21:G21) -> 0 | J21: =$D$8 -> 0.15 | K21: =I21/(1-J21) -> 0
B22: FABRICATE SECONDARY STEEL SUBSTRUCTURE | C22: 2580 | D22: 0 | E22: 0 | F22: 0 | G22: 0 | I22: =SUM(C22:G22) -> 2580 | J22: =$D$8 -> 0.15 | K22: =I22/(1-J22) -> 3035.29
B23: FABRICATE CLADDING AND TRIM | C23: 0 | D23: 0 | E23: 0 | F23: 0 | G23: 0 | I23: =SUM(C23:G23) -> 0 | J23: =$D$8 -> 0.15 | K23: =I23/(1-J23) -> 0
B24: OTHER SCOPE ITEM | C24: 0 | D24: 0 | E24: 0 | F24: 0 | G24: 0 | I24: =SUM(C24:G24) -> 0 | J24: =$D$8 -> 0.15 | K24: =I24/(1-J24) -> 0
B25: OTHER SCOPE ITEM | C25: 0 | D25: 0 | E25: 0 | F25: 0 | G25: 0 | I25: =SUM(C25:G25) -> 0 | J25: =$D$8 -> 0.15 | K25: =I25/(1-J25) -> 0
B26: SUBTOTAL | I26: =SUM(I20:I25) -> 2580 | K26: =SUM(K20:K25) -> 3035.29
B28: Structural Labor and LED Installation | C28: Subcontractor 1 | D28: Subcontractor 2 | E28: Subcontractor 3 | F28: Selected | G28: Additional Contingency | I28: Total Cost | J28: Install Margin | K28: Selling Price
B29: REMOVAL AND DISPOSAL | C29: 0 | D29: 0 | E29: 0 | F29: 0 | G29: 0 | I29: =SUM(C29:G29) -> 0 | J29: =$D$8 -> 0.15 | K29: =I29/(1-J29) -> 0
B30: INSTALL SECONDARY STEEL SUBSTRUCTURE | C30: 0 | D30: 0 | E30: 0 | F30: 0 | G30: 0 | I30: =SUM(C30:G30) -> 0 | J30: =$D$8 -> 0.15 | K30: =I30/(1-J30) -> 0
B31: INSTALL LED DISPLAYS | C31: 10750 | D31: 0 | E31: 0 | F31: 0 | G31: 0 | I31: =SUM(C31:G31) -> 10750 | J31: =$D$8 -> 0.15 | K31: =I31/(1-J31) -> 12647.06
B32: INSTALL CLADDING AND TRIM | C32: 0 | D32: 0 | E32: 0 | F32: 0 | G32: 0 | I32: =SUM(C32:G32) -> 0 | J32: =$D$8 -> 0.15 | K32: =I32/(1-J32) -> 0
B33: HEAVY EQUIPMENT | C33: 0 | D33: 0 | E33: 0 | F33: 0 | G33: 0 | I33: =SUM(C33:G33) -> 0 | J33: =$D$8 -> 0.15 | K33: =I33/(1-J33) -> 0
B34: PM/GENERAL CONDITIONS/TRAVEL | C34: 20882.35 | D34: 0 | E34: 0 | F34: 0 | G34: 0 | I34: =SUM(C34:G34) -> 20882.35 | J34: =$D$8 -> 0.15 | K34: =I34/(1-J34) -> 24567.47
B35: SUBTOTAL | I35: =SUM(I29:I34) -> 31632.35 | K35: =SUM(K29:K34) -> 37214.53
B37: Electrical and Data - Materials and Subcontracting | C37: Subcontractor 1 | D37: Subcontractor 2 | E37: Subcontractor 3 | F37: Selected | G37: Additional Contingency | I37: Total Cost | J37: Install Margin | K37: Selling Price
B38: ELECTRICAL MATERIALS | C38: 10750 | D38: 0 | E38: 0 | F38: 0 | G38: 0 | I38: =SUM(C38:G38) -> 10750 | J38: =$D$9 -> 0.15 | K38: =I38/(1-J38) -> 12647.06
B39: DATA MATERIALS | C39: 0 | D39: 0 | E39: 0 | F39: 0 | G39: 0 | I39: =SUM(C39:G39) -> 0 | J39: =$D$9 -> 0.15 | K39: =I39/(1-J39) -> 0
B40: ELECTRICAL LABOR | C40: 0 | D40: 0 | E40: 0 | F40: 0 | G40: 0 | I40: =SUM(C40:G40) -> 0 | J40: =$D$9 -> 0.15 | K40: =I40/(1-J40) -> 0
B41: DATA LABOR | C41: 0 | D41: 0 | E41: 0 | F41: 0 | G41: 0 | I41: =SUM(C41:G41) -> 0 | J41: =$D$9 -> 0.15 | K41: =I41/(1-J41) -> 0
B42: SUB PANEL | C42: 0 | D42: 0 | E42: 0 | F42: 0 | G42: 0 | I42: =SUM(C42:G42) -> 0 | J42: =$D$9 -> 0.15 | K42: =I42/(1-J42) -> 0
B43: MISC | C43: 0 | D43: 0 | E43: 0 | F43: 0 | G43: 0 | I43: =SUM(C43:G43) -> 0 | J43: =$D$9 -> 0.15 | K43: =I43/(1-J43) -> 0
B44: SUBTOTAL | I44: =SUM(I38:I43) -> 10750 | K44: =SUM(K38:K43) -> 12647.06
B46: Submittals, Engineering, and Permits | C46: Subcontractor 1 | D46: Subcontractor 2 | E46: Subcontractor 3 | F46: Selected | G46: Additional Contingency | I46: Total Cost | J46: Install Margin | K46: Selling Price
B47: STRUCTURAL ENGINEERING | C47: 4705.88 | D47: 0 | E47: 0 | F47: 0 | G47: 0 | I47: =SUM(C47:G47) -> 4705.88 | J47: =$D$11 -> 0.15 | K47: =I47/(1-J47) -> 5536.33
B48: STRUCTURAL CERTIFICATION | C48: 0 | D48: 0 | E48: 0 | F48: 0 | G48: 0 | I48: =SUM(C48:G48) -> 0 | J48: =$D$11 -> 0.15 | K48: =I48/(1-J48) -> 0
B49: ELECTRICAL ENGINEERING | C49: 0 | D49: 0 | E49: 0 | F49: 0 | G49: 0 | I49: =SUM(C49:G49) -> 0 | J49: =$D$11 -> 0.15 | K49: =I49/(1-J49) -> 0
B50: ELECTRICAL CERTIFICATION | C50: 0 | D50: 0 | E50: 0 | F50: 0 | G50: 0 | I50: =SUM(C50:G50) -> 0 | J50: =$D$11 -> 0.15 | K50: =I50/(1-J50) -> 0
B51: PERMITS | C51: 0 | D51: 0 | E51: 0 | F51: 0 | G51: 0 | I51: =SUM(C51:G51) -> 0 | J51: =$D$11 -> 0.15 | K51: =I51/(1-J51) -> 0
B52: SUBTOTAL | I52: =SUM(I47:I51) -> 4705.88 | K52: =SUM(K47:K51) -> 5536.33
B54: ZONE GRAND TOTAL | I54: =I26+I35+I44+I52 -> 107132.73 | K54: =K26+K35+K44+K52 -> 123405.56

Sheet 9A Underpass 3 - Install
A3: Project Name: Amended RFP Exhibit I
A4: 2026-03-31
A5: Revised By: ANC Proposal Engine
C7: Linked Margin Assignment
C8: Install Margin | D8: 0.15
C9: Electrical Margin | D9: 0.15
C10: ANC Margin | D10: 0.15
C11: Engineering and Permits | D11: 0.15
B15: 9A Underpass 3
B16: Height | C16: Width | D16: Total Sq. Ft | E16: QTY
B17: 7.48 | C17: 29.92 | D17: 223.8 | E17: 1
B19: Structural Materials: | C19: Subcontractor 1 | D19: Subcontractor 2 | E19: Subcontractor 3 | F19: Selected | G19: Additional Contingency | I19: Total Cost | J19: Install Margin | K19: Selling Price
B20: FABRICATE PRIMARY STEEL | C20: 0 | D20: 0 | E20: 0 | F20: 0 | G20: 0 | I20: =SUM(C20:G20) -> 0 | J20: =$D$8 -> 0.15 | K20: =I20/(1-J20) -> 0
B21: SUPPLY AND INSTALL PRIMARY PLYWOOD | C21: 0 | D21: 0 | E21: 0 | F21: 0 | G21: 0 | I21: =SUM(C21:G21) -> 0 | J21: =$D$8 -> 0.15 | K21: =I21/(1-J21) -> 0
B22: FABRICATE SECONDARY STEEL SUBSTRUCTURE | C22: 2580 | D22: 0 | E22: 0 | F22: 0 | G22: 0 | I22: =SUM(C22:G22) -> 2580 | J22: =$D$8 -> 0.15 | K22: =I22/(1-J22) -> 3035.29
B23: FABRICATE CLADDING AND TRIM | C23: 0 | D23: 0 | E23: 0 | F23: 0 | G23: 0 | I23: =SUM(C23:G23) -> 0 | J23: =$D$8 -> 0.15 | K23: =I23/(1-J23) -> 0
B24: OTHER SCOPE ITEM | C24: 0 | D24: 0 | E24: 0 | F24: 0 | G24: 0 | I24: =SUM(C24:G24) -> 0 | J24: =$D$8 -> 0.15 | K24: =I24/(1-J24) -> 0
B25: OTHER SCOPE ITEM | C25: 0 | D25: 0 | E25: 0 | F25: 0 | G25: 0 | I25: =SUM(C25:G25) -> 0 | J25: =$D$8 -> 0.15 | K25: =I25/(1-J25) -> 0
B26: SUBTOTAL | I26: =SUM(I20:I25) -> 2580 | K26: =SUM(K20:K25) -> 3035.29
B28: Structural Labor and LED Installation | C28: Subcontractor 1 | D28: Subcontractor 2 | E28: Subcontractor 3 | F28: Selected | G28: Additional Contingency | I28: Total Cost | J28: Install Margin | K28: Selling Price
B29: REMOVAL AND DISPOSAL | C29: 0 | D29: 0 | E29: 0 | F29: 0 | G29: 0 | I29: =SUM(C29:G29) -> 0 | J29: =$D$8 -> 0.15 | K29: =I29/(1-J29) -> 0
B30: INSTALL SECONDARY STEEL SUBSTRUCTURE | C30: 0 | D30: 0 | E30: 0 | F30: 0 | G30: 0 | I30: =SUM(C30:G30) -> 0 | J30: =$D$8 -> 0.15 | K30: =I30/(1-J30) -> 0
B31: INSTALL LED DISPLAYS | C31: 10750 | D31: 0 | E31: 0 | F31: 0 | G31: 0 | I31: =SUM(C31:G31) -> 10750 | J31: =$D$8 -> 0.15 | K31: =I31/(1-J31) -> 12647.06
B32: INSTALL CLADDING AND TRIM | C32: 0 | D32: 0 | E32: 0 | F32: 0 | G32: 0 | I32: =SUM(C32:G32) -> 0 | J32: =$D$8 -> 0.15 | K32: =I32/(1-J32) -> 0
B33: HEAVY EQUIPMENT | C33: 0 | D33: 0 | E33: 0 | F33: 0 | G33: 0 | I33: =SUM(C33:G33) -> 0 | J33: =$D$8 -> 0.15 | K33: =I33/(1-J33) -> 0
B34: PM/GENERAL CONDITIONS/TRAVEL | C34: 20882.35 | D34: 0 | E34: 0 | F34: 0 | G34: 0 | I34: =SUM(C34:G34) -> 20882.35 | J34: =$D$8 -> 0.15 | K34: =I34/(1-J34) -> 24567.47
B35: SUBTOTAL | I35: =SUM(I29:I34) -> 31632.35 | K35: =SUM(K29:K34) -> 37214.53
B37: Electrical and Data - Materials and Subcontracting | C37: Subcontractor 1 | D37: Subcontractor 2 | E37: Subcontractor 3 | F37: Selected | G37: Additional Contingency | I37: Total Cost | J37: Install Margin | K37: Selling Price
B38: ELECTRICAL MATERIALS | C38: 10750 | D38: 0 | E38: 0 | F38: 0 | G38: 0 | I38: =SUM(C38:G38) -> 10750 | J38: =$D$9 -> 0.15 | K38: =I38/(1-J38) -> 12647.06
B39: DATA MATERIALS | C39: 0 | D39: 0 | E39: 0 | F39: 0 | G39: 0 | I39: =SUM(C39:G39) -> 0 | J39: =$D$9 -> 0.15 | K39: =I39/(1-J39) -> 0
B40: ELECTRICAL LABOR | C40: 0 | D40: 0 | E40: 0 | F40: 0 | G40: 0 | I40: =SUM(C40:G40) -> 0 | J40: =$D$9 -> 0.15 | K40: =I40/(1-J40) -> 0
B41: DATA LABOR | C41: 0 | D41: 0 | E41: 0 | F41: 0 | G41: 0 | I41: =SUM(C41:G41) -> 0 | J41: =$D$9 -> 0.15 | K41: =I41/(1-J41) -> 0
B42: SUB PANEL | C42: 0 | D42: 0 | E42: 0 | F42: 0 | G42: 0 | I42: =SUM(C42:G42) -> 0 | J42: =$D$9 -> 0.15 | K42: =I42/(1-J42) -> 0
B43: MISC | C43: 0 | D43: 0 | E43: 0 | F43: 0 | G43: 0 | I43: =SUM(C43:G43) -> 0 | J43: =$D$9 -> 0.15 | K43: =I43/(1-J43) -> 0
B44: SUBTOTAL | I44: =SUM(I38:I43) -> 10750 | K44: =SUM(K38:K43) -> 12647.06
B46: Submittals, Engineering, and Permits | C46: Subcontractor 1 | D46: Subcontractor 2 | E46: Subcontractor 3 | F46: Selected | G46: Additional Contingency | I46: Total Cost | J46: Install Margin | K46: Selling Price
B47: STRUCTURAL ENGINEERING | C47: 4705.88 | D47: 0 | E47: 0 | F47: 0 | G47: 0 | I47: =SUM(C47:G47) -> 4705.88 | J47: =$D$11 -> 0.15 | K47: =I47/(1-J47) -> 5536.33
B48: STRUCTURAL CERTIFICATION | C48: 0 | D48: 0 | E48: 0 | F48: 0 | G48: 0 | I48: =SUM(C48:G48) -> 0 | J48: =$D$11 -> 0.15 | K48: =I48/(1-J48) -> 0
B49: ELECTRICAL ENGINEERING | C49: 0 | D49: 0 | E49: 0 | F49: 0 | G49: 0 | I49: =SUM(C49:G49) -> 0 | J49: =$D$11 -> 0.15 | K49: =I49/(1-J49) -> 0
B50: ELECTRICAL CERTIFICATION | C50: 0 | D50: 0 | E50: 0 | F50: 0 | G50: 0 | I50: =SUM(C50:G50) -> 0 | J50: =$D$11 -> 0.15 | K50: =I50/(1-J50) -> 0
B51: PERMITS | C51: 0 | D51: 0 | E51: 0 | F51: 0 | G51: 0 | I51: =SUM(C51:G51) -> 0 | J51: =$D$11 -> 0.15 | K51: =I51/(1-J51) -> 0
B52: SUBTOTAL | I52: =SUM(I47:I51) -> 4705.88 | K52: =SUM(K47:K51) -> 5536.33
B54: ZONE GRAND TOTAL | I54: =I26+I35+I44+I52 -> 107132.73 | K54: =K26+K35+K44+K52 -> 123405.56

Sheet 9A Underpass 4 - Install
A3: Project Name: Amended RFP Exhibit I
A4: 2026-03-31
A5: Revised By: ANC Proposal Engine
C7: Linked Margin Assignment
C8: Install Margin | D8: 0.15
C9: Electrical Margin | D9: 0.15
C10: ANC Margin | D10: 0.15
C11: Engineering and Permits | D11: 0.15
B15: 9A Underpass 4
B16: Height | C16: Width | D16: Total Sq. Ft | E16: QTY
B17: 12.6 | C17: 29.92 | D17: 376.99 | E17: 1
B19: Structural Materials: | C19: Subcontractor 1 | D19: Subcontractor 2 | E19: Subcontractor 3 | F19: Selected | G19: Additional Contingency | I19: Total Cost | J19: Install Margin | K19: Selling Price
B20: FABRICATE PRIMARY STEEL | C20: 0 | D20: 0 | E20: 0 | F20: 0 | G20: 0 | I20: =SUM(C20:G20) -> 0 | J20: =$D$8 -> 0.15 | K20: =I20/(1-J20) -> 0
B21: SUPPLY AND INSTALL PRIMARY PLYWOOD | C21: 0 | D21: 0 | E21: 0 | F21: 0 | G21: 0 | I21: =SUM(C21:G21) -> 0 | J21: =$D$8 -> 0.15 | K21: =I21/(1-J21) -> 0
B22: FABRICATE SECONDARY STEEL SUBSTRUCTURE | C22: 4342.5 | D22: 0 | E22: 0 | F22: 0 | G22: 0 | I22: =SUM(C22:G22) -> 4342.5 | J22: =$D$8 -> 0.15 | K22: =I22/(1-J22) -> 5108.82
B23: FABRICATE CLADDING AND TRIM | C23: 0 | D23: 0 | E23: 0 | F23: 0 | G23: 0 | I23: =SUM(C23:G23) -> 0 | J23: =$D$8 -> 0.15 | K23: =I23/(1-J23) -> 0
B24: OTHER SCOPE ITEM | C24: 0 | D24: 0 | E24: 0 | F24: 0 | G24: 0 | I24: =SUM(C24:G24) -> 0 | J24: =$D$8 -> 0.15 | K24: =I24/(1-J24) -> 0
B25: OTHER SCOPE ITEM | C25: 0 | D25: 0 | E25: 0 | F25: 0 | G25: 0 | I25: =SUM(C25:G25) -> 0 | J25: =$D$8 -> 0.15 | K25: =I25/(1-J25) -> 0
B26: SUBTOTAL | I26: =SUM(I20:I25) -> 4342.5 | K26: =SUM(K20:K25) -> 5108.82
B28: Structural Labor and LED Installation | C28: Subcontractor 1 | D28: Subcontractor 2 | E28: Subcontractor 3 | F28: Selected | G28: Additional Contingency | I28: Total Cost | J28: Install Margin | K28: Selling Price
B29: REMOVAL AND DISPOSAL | C29: 0 | D29: 0 | E29: 0 | F29: 0 | G29: 0 | I29: =SUM(C29:G29) -> 0 | J29: =$D$8 -> 0.15 | K29: =I29/(1-J29) -> 0
B30: INSTALL SECONDARY STEEL SUBSTRUCTURE | C30: 0 | D30: 0 | E30: 0 | F30: 0 | G30: 0 | I30: =SUM(C30:G30) -> 0 | J30: =$D$8 -> 0.15 | K30: =I30/(1-J30) -> 0
B31: INSTALL LED DISPLAYS | C31: 18093.75 | D31: 0 | E31: 0 | F31: 0 | G31: 0 | I31: =SUM(C31:G31) -> 18093.75 | J31: =$D$8 -> 0.15 | K31: =I31/(1-J31) -> 21286.76
B32: INSTALL CLADDING AND TRIM | C32: 0 | D32: 0 | E32: 0 | F32: 0 | G32: 0 | I32: =SUM(C32:G32) -> 0 | J32: =$D$8 -> 0.15 | K32: =I32/(1-J32) -> 0
B33: HEAVY EQUIPMENT | C33: 0 | D33: 0 | E33: 0 | F33: 0 | G33: 0 | I33: =SUM(C33:G33) -> 0 | J33: =$D$8 -> 0.15 | K33: =I33/(1-J33) -> 0
B34: PM/GENERAL CONDITIONS/TRAVEL | C34: 20882.35 | D34: 0 | E34: 0 | F34: 0 | G34: 0 | I34: =SUM(C34:G34) -> 20882.35 | J34: =$D$8 -> 0.15 | K34: =I34/(1-J34) -> 24567.47
B35: SUBTOTAL | I35: =SUM(I29:I34) -> 38976.1 | K35: =SUM(K29:K34) -> 45854.24
B37: Electrical and Data - Materials and Subcontracting | C37: Subcontractor 1 | D37: Subcontractor 2 | E37: Subcontractor 3 | F37: Selected | G37: Additional Contingency | I37: Total Cost | J37: Install Margin | K37: Selling Price
B38: ELECTRICAL MATERIALS | C38: 18093.75 | D38: 0 | E38: 0 | F38: 0 | G38: 0 | I38: =SUM(C38:G38) -> 18093.75 | J38: =$D$9 -> 0.15 | K38: =I38/(1-J38) -> 21286.76
B39: DATA MATERIALS | C39: 0 | D39: 0 | E39: 0 | F39: 0 | G39: 0 | I39: =SUM(C39:G39) -> 0 | J39: =$D$9 -> 0.15 | K39: =I39/(1-J39) -> 0
B40: ELECTRICAL LABOR | C40: 0 | D40: 0 | E40: 0 | F40: 0 | G40: 0 | I40: =SUM(C40:G40) -> 0 | J40: =$D$9 -> 0.15 | K40: =I40/(1-J40) -> 0
B41: DATA LABOR | C41: 0 | D41: 0 | E41: 0 | F41: 0 | G41: 0 | I41: =SUM(C41:G41) -> 0 | J41: =$D$9 -> 0.15 | K41: =I41/(1-J41) -> 0
B42: SUB PANEL | C42: 0 | D42: 0 | E42: 0 | F42: 0 | G42: 0 | I42: =SUM(C42:G42) -> 0 | J42: =$D$9 -> 0.15 | K42: =I42/(1-J42) -> 0
B43: MISC | C43: 0 | D43: 0 | E43: 0 | F43: 0 | G43: 0 | I43: =SUM(C43:G43) -> 0 | J43: =$D$9 -> 0.15 | K43: =I43/(1-J43) -> 0
B44: SUBTOTAL | I44: =SUM(I38:I43) -> 18093.75 | K44: =SUM(K38:K43) -> 21286.76
B46: Submittals, Engineering, and Permits | C46: Subcontractor 1 | D46: Subcontractor 2 | E46: Subcontractor 3 | F46: Selected | G46: Additional Contingency | I46: Total Cost | J46: Install Margin | K46: Selling Price
B47: STRUCTURAL ENGINEERING | C47: 4705.88 | D47: 0 | E47: 0 | F47: 0 | G47: 0 | I47: =SUM(C47:G47) -> 4705.88 | J47: =$D$11 -> 0.15 | K47: =I47/(1-J47) -> 5536.33
B48: STRUCTURAL CERTIFICATION | C48: 0 | D48: 0 | E48: 0 | F48: 0 | G48: 0 | I48: =SUM(C48:G48) -> 0 | J48: =$D$11 -> 0.15 | K48: =I48/(1-J48) -> 0
B49: ELECTRICAL ENGINEERING | C49: 0 | D49: 0 | E49: 0 | F49: 0 | G49: 0 | I49: =SUM(C49:G49) -> 0 | J49: =$D$11 -> 0.15 | K49: =I49/(1-J49) -> 0
B50: ELECTRICAL CERTIFICATION | C50: 0 | D50: 0 | E50: 0 | F50: 0 | G50: 0 | I50: =SUM(C50:G50) -> 0 | J50: =$D$11 -> 0.15 | K50: =I50/(1-J50) -> 0
B51: PERMITS | C51: 0 | D51: 0 | E51: 0 | F51: 0 | G51: 0 | I51: =SUM(C51:G51) -> 0 | J51: =$D$11 -> 0.15 | K51: =I51/(1-J51) -> 0
B52: SUBTOTAL | I52: =SUM(I47:I51) -> 4705.88 | K52: =SUM(K47:K51) -> 5536.33
B54: ZONE GRAND TOTAL | I54: =I26+I35+I44+I52 -> 174608.87 | K54: =K26+K35+K44+K52 -> 200987.02

Sheet Concourse - Install
A3: Project Name: Amended RFP Exhibit I
A4: 2026-03-31
A5: Revised By: ANC Proposal Engine
C7: Linked Margin Assignment
C8: Install Margin | D8: 0.15
C9: Electrical Margin | D9: 0.15
C10: ANC Margin | D10: 0.15
C11: Engineering and Permits | D11: 0.15
B15: Concourse
B16: Height | C16: Width | D16: Total Sq. Ft | E16: QTY
B17: 9.45 | C17: 280.31 | D17: 2648.93 | E17: 1
B19: Structural Materials: | C19: Subcontractor 1 | D19: Subcontractor 2 | E19: Subcontractor 3 | F19: Selected | G19: Additional Contingency | I19: Total Cost | J19: Install Margin | K19: Selling Price
B20: FABRICATE PRIMARY STEEL | C20: 0 | D20: 0 | E20: 0 | F20: 0 | G20: 0 | I20: =SUM(C20:G20) -> 0 | J20: =$D$8 -> 0.15 | K20: =I20/(1-J20) -> 0
B21: SUPPLY AND INSTALL PRIMARY PLYWOOD | C21: 0 | D21: 0 | E21: 0 | F21: 0 | G21: 0 | I21: =SUM(C21:G21) -> 0 | J21: =$D$8 -> 0.15 | K21: =I21/(1-J21) -> 0
B22: FABRICATE SECONDARY STEEL SUBSTRUCTURE | C22: 30536.25 | D22: 0 | E22: 0 | F22: 0 | G22: 0 | I22: =SUM(C22:G22) -> 30536.25 | J22: =$D$8 -> 0.15 | K22: =I22/(1-J22) -> 35925
B23: FABRICATE CLADDING AND TRIM | C23: 0 | D23: 0 | E23: 0 | F23: 0 | G23: 0 | I23: =SUM(C23:G23) -> 0 | J23: =$D$8 -> 0.15 | K23: =I23/(1-J23) -> 0
B24: OTHER SCOPE ITEM | C24: 0 | D24: 0 | E24: 0 | F24: 0 | G24: 0 | I24: =SUM(C24:G24) -> 0 | J24: =$D$8 -> 0.15 | K24: =I24/(1-J24) -> 0
B25: OTHER SCOPE ITEM | C25: 0 | D25: 0 | E25: 0 | F25: 0 | G25: 0 | I25: =SUM(C25:G25) -> 0 | J25: =$D$8 -> 0.15 | K25: =I25/(1-J25) -> 0
B26: SUBTOTAL | I26: =SUM(I20:I25) -> 30536.25 | K26: =SUM(K20:K25) -> 35925
B28: Structural Labor and LED Installation | C28: Subcontractor 1 | D28: Subcontractor 2 | E28: Subcontractor 3 | F28: Selected | G28: Additional Contingency | I28: Total Cost | J28: Install Margin | K28: Selling Price
B29: REMOVAL AND DISPOSAL | C29: 0 | D29: 0 | E29: 0 | F29: 0 | G29: 0 | I29: =SUM(C29:G29) -> 0 | J29: =$D$8 -> 0.15 | K29: =I29/(1-J29) -> 0
B30: INSTALL SECONDARY STEEL SUBSTRUCTURE | C30: 0 | D30: 0 | E30: 0 | F30: 0 | G30: 0 | I30: =SUM(C30:G30) -> 0 | J30: =$D$8 -> 0.15 | K30: =I30/(1-J30) -> 0
B31: INSTALL LED DISPLAYS | C31: 127234.38 | D31: 0 | E31: 0 | F31: 0 | G31: 0 | I31: =SUM(C31:G31) -> 127234.38 | J31: =$D$8 -> 0.15 | K31: =I31/(1-J31) -> 149687.51
B32: INSTALL CLADDING AND TRIM | C32: 0 | D32: 0 | E32: 0 | F32: 0 | G32: 0 | I32: =SUM(C32:G32) -> 0 | J32: =$D$8 -> 0.15 | K32: =I32/(1-J32) -> 0
B33: HEAVY EQUIPMENT | C33: 0 | D33: 0 | E33: 0 | F33: 0 | G33: 0 | I33: =SUM(C33:G33) -> 0 | J33: =$D$8 -> 0.15 | K33: =I33/(1-J33) -> 0
B34: PM/GENERAL CONDITIONS/TRAVEL | C34: 20882.35 | D34: 0 | E34: 0 | F34: 0 | G34: 0 | I34: =SUM(C34:G34) -> 20882.35 | J34: =$D$8 -> 0.15 | K34: =I34/(1-J34) -> 24567.47
B35: SUBTOTAL | I35: =SUM(I29:I34) -> 148116.73 | K35: =SUM(K29:K34) -> 174254.98
B37: Electrical and Data - Materials and Subcontracting | C37: Subcontractor 1 | D37: Subcontractor 2 | E37: Subcontractor 3 | F37: Selected | G37: Additional Contingency | I37: Total Cost | J37: Install Margin | K37: Selling Price
B38: ELECTRICAL MATERIALS | C38: 127234.38 | D38: 0 | E38: 0 | F38: 0 | G38: 0 | I38: =SUM(C38:G38) -> 127234.38 | J38: =$D$9 -> 0.15 | K38: =I38/(1-J38) -> 149687.51
B39: DATA MATERIALS | C39: 0 | D39: 0 | E39: 0 | F39: 0 | G39: 0 | I39: =SUM(C39:G39) -> 0 | J39: =$D$9 -> 0.15 | K39: =I39/(1-J39) -> 0
B40: ELECTRICAL LABOR | C40: 0 | D40: 0 | E40: 0 | F40: 0 | G40: 0 | I40: =SUM(C40:G40) -> 0 | J40: =$D$9 -> 0.15 | K40: =I40/(1-J40) -> 0
B41: DATA LABOR | C41: 0 | D41: 0 | E41: 0 | F41: 0 | G41: 0 | I41: =SUM(C41:G41) -> 0 | J41: =$D$9 -> 0.15 | K41: =I41/(1-J41) -> 0
B42: SUB PANEL | C42: 0 | D42: 0 | E42: 0 | F42: 0 | G42: 0 | I42: =SUM(C42:G42) -> 0 | J42: =$D$9 -> 0.15 | K42: =I42/(1-J42) -> 0
B43: MISC | C43: 0 | D43: 0 | E43: 0 | F43: 0 | G43: 0 | I43: =SUM(C43:G43) -> 0 | J43: =$D$9 -> 0.15 | K43: =I43/(1-J43) -> 0
B44: SUBTOTAL | I44: =SUM(I38:I43) -> 127234.38 | K44: =SUM(K38:K43) -> 149687.51
B46: Submittals, Engineering, and Permits | C46: Subcontractor 1 | D46: Subcontractor 2 | E46: Subcontractor 3 | F46: Selected | G46: Additional Contingency | I46: Total Cost | J46: Install Margin | K46: Selling Price
B47: STRUCTURAL ENGINEERING | C47: 4705.88 | D47: 0 | E47: 0 | F47: 0 | G47: 0 | I47: =SUM(C47:G47) -> 4705.88 | J47: =$D$11 -> 0.15 | K47: =I47/(1-J47) -> 5536.33
B48: STRUCTURAL CERTIFICATION | C48: 0 | D48: 0 | E48: 0 | F48: 0 | G48: 0 | I48: =SUM(C48:G48) -> 0 | J48: =$D$11 -> 0.15 | K48: =I48/(1-J48) -> 0
B49: ELECTRICAL ENGINEERING | C49: 0 | D49: 0 | E49: 0 | F49: 0 | G49: 0 | I49: =SUM(C49:G49) -> 0 | J49: =$D$11 -> 0.15 | K49: =I49/(1-J49) -> 0
B50: ELECTRICAL CERTIFICATION | C50: 0 | D50: 0 | E50: 0 | F50: 0 | G50: 0 | I50: =SUM(C50:G50) -> 0 | J50: =$D$11 -> 0.15 | K50: =I50/(1-J50) -> 0
B51: PERMITS | C51: 0 | D51: 0 | E51: 0 | F51: 0 | G51: 0 | I51: =SUM(C51:G51) -> 0 | J51: =$D$11 -> 0.15 | K51: =I51/(1-J51) -> 0
B52: SUBTOTAL | I52: =SUM(I47:I51) -> 4705.88 | K52: =SUM(K47:K51) -> 5536.33
B54: ZONE GRAND TOTAL | I54: =I26+I35+I44+I52 -> 1014225.4 | K54: =K26+K35+K44+K52 -> 1162042.4

Sheet T4 Elevator - Install
A3: Project Name: Amended RFP Exhibit I
A4: 2026-03-31
A5: Revised By: ANC Proposal Engine
C7: Linked Margin Assignment
C8: Install Margin | D8: 0.15
C9: Electrical Margin | D9: 0.15
C10: ANC Margin | D10: 0.15
C11: Engineering and Permits | D11: 0.15
B15: T4 Elevator
B16: Height | C16: Width | D16: Total Sq. Ft | E16: QTY
B17: 71.6 | C17: 5.5 | D17: 393.8 | E17: 1
B19: Structural Materials: | C19: Subcontractor 1 | D19: Subcontractor 2 | E19: Subcontractor 3 | F19: Selected | G19: Additional Contingency | I19: Total Cost | J19: Install Margin | K19: Selling Price
B20: FABRICATE PRIMARY STEEL | C20: 0 | D20: 0 | E20: 0 | F20: 0 | G20: 0 | I20: =SUM(C20:G20) -> 0 | J20: =$D$8 -> 0.15 | K20: =I20/(1-J20) -> 0
B21: SUPPLY AND INSTALL PRIMARY PLYWOOD | C21: 0 | D21: 0 | E21: 0 | F21: 0 | G21: 0 | I21: =SUM(C21:G21) -> 0 | J21: =$D$8 -> 0.15 | K21: =I21/(1-J21) -> 0
B22: FABRICATE SECONDARY STEEL SUBSTRUCTURE | C22: 4537.5 | D22: 0 | E22: 0 | F22: 0 | G22: 0 | I22: =SUM(C22:G22) -> 4537.5 | J22: =$D$8 -> 0.15 | K22: =I22/(1-J22) -> 5338.24
B23: FABRICATE CLADDING AND TRIM | C23: 0 | D23: 0 | E23: 0 | F23: 0 | G23: 0 | I23: =SUM(C23:G23) -> 0 | J23: =$D$8 -> 0.15 | K23: =I23/(1-J23) -> 0
B24: OTHER SCOPE ITEM | C24: 0 | D24: 0 | E24: 0 | F24: 0 | G24: 0 | I24: =SUM(C24:G24) -> 0 | J24: =$D$8 -> 0.15 | K24: =I24/(1-J24) -> 0
B25: OTHER SCOPE ITEM | C25: 0 | D25: 0 | E25: 0 | F25: 0 | G25: 0 | I25: =SUM(C25:G25) -> 0 | J25: =$D$8 -> 0.15 | K25: =I25/(1-J25) -> 0
B26: SUBTOTAL | I26: =SUM(I20:I25) -> 4537.5 | K26: =SUM(K20:K25) -> 5338.24
B28: Structural Labor and LED Installation | C28: Subcontractor 1 | D28: Subcontractor 2 | E28: Subcontractor 3 | F28: Selected | G28: Additional Contingency | I28: Total Cost | J28: Install Margin | K28: Selling Price
B29: REMOVAL AND DISPOSAL | C29: 0 | D29: 0 | E29: 0 | F29: 0 | G29: 0 | I29: =SUM(C29:G29) -> 0 | J29: =$D$8 -> 0.15 | K29: =I29/(1-J29) -> 0
B30: INSTALL SECONDARY STEEL SUBSTRUCTURE | C30: 0 | D30: 0 | E30: 0 | F30: 0 | G30: 0 | I30: =SUM(C30:G30) -> 0 | J30: =$D$8 -> 0.15 | K30: =I30/(1-J30) -> 0
B31: INSTALL LED DISPLAYS | C31: 18906.25 | D31: 0 | E31: 0 | F31: 0 | G31: 0 | I31: =SUM(C31:G31) -> 18906.25 | J31: =$D$8 -> 0.15 | K31: =I31/(1-J31) -> 22242.65
B32: INSTALL CLADDING AND TRIM | C32: 0 | D32: 0 | E32: 0 | F32: 0 | G32: 0 | I32: =SUM(C32:G32) -> 0 | J32: =$D$8 -> 0.15 | K32: =I32/(1-J32) -> 0
B33: HEAVY EQUIPMENT | C33: 0 | D33: 0 | E33: 0 | F33: 0 | G33: 0 | I33: =SUM(C33:G33) -> 0 | J33: =$D$8 -> 0.15 | K33: =I33/(1-J33) -> 0
B34: PM/GENERAL CONDITIONS/TRAVEL | C34: 20882.35 | D34: 0 | E34: 0 | F34: 0 | G34: 0 | I34: =SUM(C34:G34) -> 20882.35 | J34: =$D$8 -> 0.15 | K34: =I34/(1-J34) -> 24567.47
B35: SUBTOTAL | I35: =SUM(I29:I34) -> 39788.6 | K35: =SUM(K29:K34) -> 46810.12
B37: Electrical and Data - Materials and Subcontracting | C37: Subcontractor 1 | D37: Subcontractor 2 | E37: Subcontractor 3 | F37: Selected | G37: Additional Contingency | I37: Total Cost | J37: Install Margin | K37: Selling Price
B38: ELECTRICAL MATERIALS | C38: 18906.25 | D38: 0 | E38: 0 | F38: 0 | G38: 0 | I38: =SUM(C38:G38) -> 18906.25 | J38: =$D$9 -> 0.15 | K38: =I38/(1-J38) -> 22242.65
B39: DATA MATERIALS | C39: 0 | D39: 0 | E39: 0 | F39: 0 | G39: 0 | I39: =SUM(C39:G39) -> 0 | J39: =$D$9 -> 0.15 | K39: =I39/(1-J39) -> 0
B40: ELECTRICAL LABOR | C40: 0 | D40: 0 | E40: 0 | F40: 0 | G40: 0 | I40: =SUM(C40:G40) -> 0 | J40: =$D$9 -> 0.15 | K40: =I40/(1-J40) -> 0
B41: DATA LABOR | C41: 0 | D41: 0 | E41: 0 | F41: 0 | G41: 0 | I41: =SUM(C41:G41) -> 0 | J41: =$D$9 -> 0.15 | K41: =I41/(1-J41) -> 0
B42: SUB PANEL | C42: 0 | D42: 0 | E42: 0 | F42: 0 | G42: 0 | I42: =SUM(C42:G42) -> 0 | J42: =$D$9 -> 0.15 | K42: =I42/(1-J42) -> 0
B43: MISC | C43: 0 | D43: 0 | E43: 0 | F43: 0 | G43: 0 | I43: =SUM(C43:G43) -> 0 | J43: =$D$9 -> 0.15 | K43: =I43/(1-J43) -> 0
B44: SUBTOTAL | I44: =SUM(I38:I43) -> 18906.25 | K44: =SUM(K38:K43) -> 22242.65
B46: Submittals, Engineering, and Permits | C46: Subcontractor 1 | D46: Subcontractor 2 | E46: Subcontractor 3 | F46: Selected | G46: Additional Contingency | I46: Total Cost | J46: Install Margin | K46: Selling Price
B47: STRUCTURAL ENGINEERING | C47: 4705.88 | D47: 0 | E47: 0 | F47: 0 | G47: 0 | I47: =SUM(C47:G47) -> 4705.88 | J47: =$D$11 -> 0.15 | K47: =I47/(1-J47) -> 5536.33
B48: STRUCTURAL CERTIFICATION | C48: 0 | D48: 0 | E48: 0 | F48: 0 | G48: 0 | I48: =SUM(C48:G48) -> 0 | J48: =$D$11 -> 0.15 | K48: =I48/(1-J48) -> 0
B49: ELECTRICAL ENGINEERING | C49: 0 | D49: 0 | E49: 0 | F49: 0 | G49: 0 | I49: =SUM(C49:G49) -> 0 | J49: =$D$11 -> 0.15 | K49: =I49/(1-J49) -> 0
B50: ELECTRICAL CERTIFICATION | C50: 0 | D50: 0 | E50: 0 | F50: 0 | G50: 0 | I50: =SUM(C50:G50) -> 0 | J50: =$D$11 -> 0.15 | K50: =I50/(1-J50) -> 0
B51: PERMITS | C51: 0 | D51: 0 | E51: 0 | F51: 0 | G51: 0 | I51: =SUM(C51:G51) -> 0 | J51: =$D$11 -> 0.15 | K51: =I51/(1-J51) -> 0
B52: SUBTOTAL | I52: =SUM(I47:I51) -> 4705.88 | K52: =SUM(K47:K51) -> 5536.33
B54: ZONE GRAND TOTAL | I54: =I26+I35+I44+I52 -> 180711.34 | K54: =K26+K35+K44+K52 -> 207968.64

Sheet New Path Hall Option 1 - Instal
A3: Project Name: Amended RFP Exhibit I
A4: 2026-03-31
A5: Revised By: ANC Proposal Engine
C7: Linked Margin Assignment
C8: Install Margin | D8: 0.15
C9: Electrical Margin | D9: 0.15
C10: ANC Margin | D10: 0.15
C11: Engineering and Permits | D11: 0.15
B15: New Path Hall Option 1
B16: Height | C16: Width | D16: Total Sq. Ft | E16: QTY
B17: 48 | C17: 14 | D17: 672 | E17: 1
B19: Structural Materials: | C19: Subcontractor 1 | D19: Subcontractor 2 | E19: Subcontractor 3 | F19: Selected | G19: Additional Contingency | I19: Total Cost | J19: Install Margin | K19: Selling Price
B20: FABRICATE PRIMARY STEEL | C20: 0 | D20: 0 | E20: 0 | F20: 0 | G20: 0 | I20: =SUM(C20:G20) -> 0 | J20: =$D$8 -> 0.15 | K20: =I20/(1-J20) -> 0
B21: SUPPLY AND INSTALL PRIMARY PLYWOOD | C21: 0 | D21: 0 | E21: 0 | F21: 0 | G21: 0 | I21: =SUM(C21:G21) -> 0 | J21: =$D$8 -> 0.15 | K21: =I21/(1-J21) -> 0
B22: FABRICATE SECONDARY STEEL SUBSTRUCTURE | C22: 7740 | D22: 0 | E22: 0 | F22: 0 | G22: 0 | I22: =SUM(C22:G22) -> 7740 | J22: =$D$8 -> 0.15 | K22: =I22/(1-J22) -> 9105.88
B23: FABRICATE CLADDING AND TRIM | C23: 0 | D23: 0 | E23: 0 | F23: 0 | G23: 0 | I23: =SUM(C23:G23) -> 0 | J23: =$D$8 -> 0.15 | K23: =I23/(1-J23) -> 0
B24: OTHER SCOPE ITEM | C24: 0 | D24: 0 | E24: 0 | F24: 0 | G24: 0 | I24: =SUM(C24:G24) -> 0 | J24: =$D$8 -> 0.15 | K24: =I24/(1-J24) -> 0
B25: OTHER SCOPE ITEM | C25: 0 | D25: 0 | E25: 0 | F25: 0 | G25: 0 | I25: =SUM(C25:G25) -> 0 | J25: =$D$8 -> 0.15 | K25: =I25/(1-J25) -> 0
B26: SUBTOTAL | I26: =SUM(I20:I25) -> 7740 | K26: =SUM(K20:K25) -> 9105.88
B28: Structural Labor and LED Installation | C28: Subcontractor 1 | D28: Subcontractor 2 | E28: Subcontractor 3 | F28: Selected | G28: Additional Contingency | I28: Total Cost | J28: Install Margin | K28: Selling Price
B29: REMOVAL AND DISPOSAL | C29: 0 | D29: 0 | E29: 0 | F29: 0 | G29: 0 | I29: =SUM(C29:G29) -> 0 | J29: =$D$8 -> 0.15 | K29: =I29/(1-J29) -> 0
B30: INSTALL SECONDARY STEEL SUBSTRUCTURE | C30: 0 | D30: 0 | E30: 0 | F30: 0 | G30: 0 | I30: =SUM(C30:G30) -> 0 | J30: =$D$8 -> 0.15 | K30: =I30/(1-J30) -> 0
B31: INSTALL LED DISPLAYS | C31: 32250 | D31: 0 | E31: 0 | F31: 0 | G31: 0 | I31: =SUM(C31:G31) -> 32250 | J31: =$D$8 -> 0.15 | K31: =I31/(1-J31) -> 37941.18
B32: INSTALL CLADDING AND TRIM | C32: 0 | D32: 0 | E32: 0 | F32: 0 | G32: 0 | I32: =SUM(C32:G32) -> 0 | J32: =$D$8 -> 0.15 | K32: =I32/(1-J32) -> 0
B33: HEAVY EQUIPMENT | C33: 0 | D33: 0 | E33: 0 | F33: 0 | G33: 0 | I33: =SUM(C33:G33) -> 0 | J33: =$D$8 -> 0.15 | K33: =I33/(1-J33) -> 0
B34: PM/GENERAL CONDITIONS/TRAVEL | C34: 20882.35 | D34: 0 | E34: 0 | F34: 0 | G34: 0 | I34: =SUM(C34:G34) -> 20882.35 | J34: =$D$8 -> 0.15 | K34: =I34/(1-J34) -> 24567.47
B35: SUBTOTAL | I35: =SUM(I29:I34) -> 53132.35 | K35: =SUM(K29:K34) -> 62508.65
B37: Electrical and Data - Materials and Subcontracting | C37: Subcontractor 1 | D37: Subcontractor 2 | E37: Subcontractor 3 | F37: Selected | G37: Additional Contingency | I37: Total Cost | J37: Install Margin | K37: Selling Price
B38: ELECTRICAL MATERIALS | C38: 32250 | D38: 0 | E38: 0 | F38: 0 | G38: 0 | I38: =SUM(C38:G38) -> 32250 | J38: =$D$9 -> 0.15 | K38: =I38/(1-J38) -> 37941.18
B39: DATA MATERIALS | C39: 0 | D39: 0 | E39: 0 | F39: 0 | G39: 0 | I39: =SUM(C39:G39) -> 0 | J39: =$D$9 -> 0.15 | K39: =I39/(1-J39) -> 0
B40: ELECTRICAL LABOR | C40: 0 | D40: 0 | E40: 0 | F40: 0 | G40: 0 | I40: =SUM(C40:G40) -> 0 | J40: =$D$9 -> 0.15 | K40: =I40/(1-J40) -> 0
B41: DATA LABOR | C41: 0 | D41: 0 | E41: 0 | F41: 0 | G41: 0 | I41: =SUM(C41:G41) -> 0 | J41: =$D$9 -> 0.15 | K41: =I41/(1-J41) -> 0
B42: SUB PANEL | C42: 0 | D42: 0 | E42: 0 | F42: 0 | G42: 0 | I42: =SUM(C42:G42) -> 0 | J42: =$D$9 -> 0.15 | K42: =I42/(1-J42) -> 0
B43: MISC | C43: 0 | D43: 0 | E43: 0 | F43: 0 | G43: 0 | I43: =SUM(C43:G43) -> 0 | J43: =$D$9 -> 0.15 | K43: =I43/(1-J43) -> 0
B44: SUBTOTAL | I44: =SUM(I38:I43) -> 32250 | K44: =SUM(K38:K43) -> 37941.18
B46: Submittals, Engineering, and Permits | C46: Subcontractor 1 | D46: Subcontractor 2 | E46: Subcontractor 3 | F46: Selected | G46: Additional Contingency | I46: Total Cost | J46: Install Margin | K46: Selling Price
B47: STRUCTURAL ENGINEERING | C47: 4705.88 | D47: 0 | E47: 0 | F47: 0 | G47: 0 | I47: =SUM(C47:G47) -> 4705.88 | J47: =$D$11 -> 0.15 | K47: =I47/(1-J47) -> 5536.33
B48: STRUCTURAL CERTIFICATION | C48: 0 | D48: 0 | E48: 0 | F48: 0 | G48: 0 | I48: =SUM(C48:G48) -> 0 | J48: =$D$11 -> 0.15 | K48: =I48/(1-J48) -> 0
B49: ELECTRICAL ENGINEERING | C49: 0 | D49: 0 | E49: 0 | F49: 0 | G49: 0 | I49: =SUM(C49:G49) -> 0 | J49: =$D$11 -> 0.15 | K49: =I49/(1-J49) -> 0
B50: ELECTRICAL CERTIFICATION | C50: 0 | D50: 0 | E50: 0 | F50: 0 | G50: 0 | I50: =SUM(C50:G50) -> 0 | J50: =$D$11 -> 0.15 | K50: =I50/(1-J50) -> 0
B51: PERMITS | C51: 0 | D51: 0 | E51: 0 | F51: 0 | G51: 0 | I51: =SUM(C51:G51) -> 0 | J51: =$D$11 -> 0.15 | K51: =I51/(1-J51) -> 0
B52: SUBTOTAL | I52: =SUM(I47:I51) -> 4705.88 | K52: =SUM(K47:K51) -> 5536.33
B54: ZONE GRAND TOTAL | I54: =I26+I35+I44+I52 -> 281474.6 | K54: =K26+K35+K44+K52 -> 323240.71

Sheet New Path Hall Option 2 - Instal
A3: Project Name: Amended RFP Exhibit I
A4: 2026-03-31
A5: Revised By: ANC Proposal Engine
C7: Linked Margin Assignment
C8: Install Margin | D8: 0.15
C9: Electrical Margin | D9: 0.15
C10: ANC Margin | D10: 0.15
C11: Engineering and Permits | D11: 0.15
B15: New Path Hall Option 2
B16: Height | C16: Width | D16: Total Sq. Ft | E16: QTY
B17: 65 | C17: 13 | D17: 845 | E17: 1
B19: Structural Materials: | C19: Subcontractor 1 | D19: Subcontractor 2 | E19: Subcontractor 3 | F19: Selected | G19: Additional Contingency | I19: Total Cost | J19: Install Margin | K19: Selling Price
B20: FABRICATE PRIMARY STEEL | C20: 0 | D20: 0 | E20: 0 | F20: 0 | G20: 0 | I20: =SUM(C20:G20) -> 0 | J20: =$D$8 -> 0.15 | K20: =I20/(1-J20) -> 0
B21: SUPPLY AND INSTALL PRIMARY PLYWOOD | C21: 0 | D21: 0 | E21: 0 | F21: 0 | G21: 0 | I21: =SUM(C21:G21) -> 0 | J21: =$D$8 -> 0.15 | K21: =I21/(1-J21) -> 0
B22: FABRICATE SECONDARY STEEL SUBSTRUCTURE | C22: 9735 | D22: 0 | E22: 0 | F22: 0 | G22: 0 | I22: =SUM(C22:G22) -> 9735 | J22: =$D$8 -> 0.15 | K22: =I22/(1-J22) -> 11452.94
B23: FABRICATE CLADDING AND TRIM | C23: 0 | D23: 0 | E23: 0 | F23: 0 | G23: 0 | I23: =SUM(C23:G23) -> 0 | J23: =$D$8 -> 0.15 | K23: =I23/(1-J23) -> 0
B24: OTHER SCOPE ITEM | C24: 0 | D24: 0 | E24: 0 | F24: 0 | G24: 0 | I24: =SUM(C24:G24) -> 0 | J24: =$D$8 -> 0.15 | K24: =I24/(1-J24) -> 0
B25: OTHER SCOPE ITEM | C25: 0 | D25: 0 | E25: 0 | F25: 0 | G25: 0 | I25: =SUM(C25:G25) -> 0 | J25: =$D$8 -> 0.15 | K25: =I25/(1-J25) -> 0
B26: SUBTOTAL | I26: =SUM(I20:I25) -> 9735 | K26: =SUM(K20:K25) -> 11452.94
B28: Structural Labor and LED Installation | C28: Subcontractor 1 | D28: Subcontractor 2 | E28: Subcontractor 3 | F28: Selected | G28: Additional Contingency | I28: Total Cost | J28: Install Margin | K28: Selling Price
B29: REMOVAL AND DISPOSAL | C29: 0 | D29: 0 | E29: 0 | F29: 0 | G29: 0 | I29: =SUM(C29:G29) -> 0 | J29: =$D$8 -> 0.15 | K29: =I29/(1-J29) -> 0
B30: INSTALL SECONDARY STEEL SUBSTRUCTURE | C30: 0 | D30: 0 | E30: 0 | F30: 0 | G30: 0 | I30: =SUM(C30:G30) -> 0 | J30: =$D$8 -> 0.15 | K30: =I30/(1-J30) -> 0
B31: INSTALL LED DISPLAYS | C31: 40562.5 | D31: 0 | E31: 0 | F31: 0 | G31: 0 | I31: =SUM(C31:G31) -> 40562.5 | J31: =$D$8 -> 0.15 | K31: =I31/(1-J31) -> 47720.59
B32: INSTALL CLADDING AND TRIM | C32: 0 | D32: 0 | E32: 0 | F32: 0 | G32: 0 | I32: =SUM(C32:G32) -> 0 | J32: =$D$8 -> 0.15 | K32: =I32/(1-J32) -> 0
B33: HEAVY EQUIPMENT | C33: 0 | D33: 0 | E33: 0 | F33: 0 | G33: 0 | I33: =SUM(C33:G33) -> 0 | J33: =$D$8 -> 0.15 | K33: =I33/(1-J33) -> 0
B34: PM/GENERAL CONDITIONS/TRAVEL | C34: 20882.35 | D34: 0 | E34: 0 | F34: 0 | G34: 0 | I34: =SUM(C34:G34) -> 20882.35 | J34: =$D$8 -> 0.15 | K34: =I34/(1-J34) -> 24567.47
B35: SUBTOTAL | I35: =SUM(I29:I34) -> 61444.85 | K35: =SUM(K29:K34) -> 72288.06
B37: Electrical and Data - Materials and Subcontracting | C37: Subcontractor 1 | D37: Subcontractor 2 | E37: Subcontractor 3 | F37: Selected | G37: Additional Contingency | I37: Total Cost | J37: Install Margin | K37: Selling Price
B38: ELECTRICAL MATERIALS | C38: 40562.5 | D38: 0 | E38: 0 | F38: 0 | G38: 0 | I38: =SUM(C38:G38) -> 40562.5 | J38: =$D$9 -> 0.15 | K38: =I38/(1-J38) -> 47720.59
B39: DATA MATERIALS | C39: 0 | D39: 0 | E39: 0 | F39: 0 | G39: 0 | I39: =SUM(C39:G39) -> 0 | J39: =$D$9 -> 0.15 | K39: =I39/(1-J39) -> 0
B40: ELECTRICAL LABOR | C40: 0 | D40: 0 | E40: 0 | F40: 0 | G40: 0 | I40: =SUM(C40:G40) -> 0 | J40: =$D$9 -> 0.15 | K40: =I40/(1-J40) -> 0
B41: DATA LABOR | C41: 0 | D41: 0 | E41: 0 | F41: 0 | G41: 0 | I41: =SUM(C41:G41) -> 0 | J41: =$D$9 -> 0.15 | K41: =I41/(1-J41) -> 0
B42: SUB PANEL | C42: 0 | D42: 0 | E42: 0 | F42: 0 | G42: 0 | I42: =SUM(C42:G42) -> 0 | J42: =$D$9 -> 0.15 | K42: =I42/(1-J42) -> 0
B43: MISC | C43: 0 | D43: 0 | E43: 0 | F43: 0 | G43: 0 | I43: =SUM(C43:G43) -> 0 | J43: =$D$9 -> 0.15 | K43: =I43/(1-J43) -> 0
B44: SUBTOTAL | I44: =SUM(I38:I43) -> 40562.5 | K44: =SUM(K38:K43) -> 47720.59
B46: Submittals, Engineering, and Permits | C46: Subcontractor 1 | D46: Subcontractor 2 | E46: Subcontractor 3 | F46: Selected | G46: Additional Contingency | I46: Total Cost | J46: Install Margin | K46: Selling Price
B47: STRUCTURAL ENGINEERING | C47: 4705.88 | D47: 0 | E47: 0 | F47: 0 | G47: 0 | I47: =SUM(C47:G47) -> 4705.88 | J47: =$D$11 -> 0.15 | K47: =I47/(1-J47) -> 5536.33
B48: STRUCTURAL CERTIFICATION | C48: 0 | D48: 0 | E48: 0 | F48: 0 | G48: 0 | I48: =SUM(C48:G48) -> 0 | J48: =$D$11 -> 0.15 | K48: =I48/(1-J48) -> 0
B49: ELECTRICAL ENGINEERING | C49: 0 | D49: 0 | E49: 0 | F49: 0 | G49: 0 | I49: =SUM(C49:G49) -> 0 | J49: =$D$11 -> 0.15 | K49: =I49/(1-J49) -> 0
B50: ELECTRICAL CERTIFICATION | C50: 0 | D50: 0 | E50: 0 | F50: 0 | G50: 0 | I50: =SUM(C50:G50) -> 0 | J50: =$D$11 -> 0.15 | K50: =I50/(1-J50) -> 0
B51: PERMITS | C51: 0 | D51: 0 | E51: 0 | F51: 0 | G51: 0 | I51: =SUM(C51:G51) -> 0 | J51: =$D$11 -> 0.15 | K51: =I51/(1-J51) -> 0
B52: SUBTOTAL | I52: =SUM(I47:I51) -> 4705.88 | K52: =SUM(K47:K51) -> 5536.33
B54: ZONE GRAND TOTAL | I54: =I26+I35+I44+I52 -> 344167.47 | K54: =K26+K35+K44+K52 -> 394961.73

Sheet One Train - Install
A3: Project Name: Amended RFP Exhibit I
A4: 2026-03-31
A5: Revised By: ANC Proposal Engine
C7: Linked Margin Assignment
C8: Install Margin | D8: 0.15
C9: Electrical Margin | D9: 0.15
C10: ANC Margin | D10: 0.15
C11: Engineering and Permits | D11: 0.15
B15: One Train
B16: Height | C16: Width | D16: Total Sq. Ft | E16: QTY
B17: 0 | C17: 0 | D17: 0 | E17: 1
B19: Structural Materials: | C19: Subcontractor 1 | D19: Subcontractor 2 | E19: Subcontractor 3 | F19: Selected | G19: Additional Contingency | I19: Total Cost | J19: Install Margin | K19: Selling Price
B20: FABRICATE PRIMARY STEEL | C20: 0 | D20: 0 | E20: 0 | F20: 0 | G20: 0 | I20: =SUM(C20:G20) -> 0 | J20: =$D$8 -> 0.15 | K20: =I20/(1-J20) -> 0
B21: SUPPLY AND INSTALL PRIMARY PLYWOOD | C21: 0 | D21: 0 | E21: 0 | F21: 0 | G21: 0 | I21: =SUM(C21:G21) -> 0 | J21: =$D$8 -> 0.15 | K21: =I21/(1-J21) -> 0
B22: FABRICATE SECONDARY STEEL SUBSTRUCTURE | C22: 0 | D22: 0 | E22: 0 | F22: 0 | G22: 0 | I22: =SUM(C22:G22) -> 0 | J22: =$D$8 -> 0.15 | K22: =I22/(1-J22) -> 0
B23: FABRICATE CLADDING AND TRIM | C23: 0 | D23: 0 | E23: 0 | F23: 0 | G23: 0 | I23: =SUM(C23:G23) -> 0 | J23: =$D$8 -> 0.15 | K23: =I23/(1-J23) -> 0
B24: OTHER SCOPE ITEM | C24: 0 | D24: 0 | E24: 0 | F24: 0 | G24: 0 | I24: =SUM(C24:G24) -> 0 | J24: =$D$8 -> 0.15 | K24: =I24/(1-J24) -> 0
B25: OTHER SCOPE ITEM | C25: 0 | D25: 0 | E25: 0 | F25: 0 | G25: 0 | I25: =SUM(C25:G25) -> 0 | J25: =$D$8 -> 0.15 | K25: =I25/(1-J25) -> 0
B26: SUBTOTAL | I26: =SUM(I20:I25) -> 0 | K26: =SUM(K20:K25) -> 0
B28: Structural Labor and LED Installation | C28: Subcontractor 1 | D28: Subcontractor 2 | E28: Subcontractor 3 | F28: Selected | G28: Additional Contingency | I28: Total Cost | J28: Install Margin | K28: Selling Price
B29: REMOVAL AND DISPOSAL | C29: 0 | D29: 0 | E29: 0 | F29: 0 | G29: 0 | I29: =SUM(C29:G29) -> 0 | J29: =$D$8 -> 0.15 | K29: =I29/(1-J29) -> 0
B30: INSTALL SECONDARY STEEL SUBSTRUCTURE | C30: 0 | D30: 0 | E30: 0 | F30: 0 | G30: 0 | I30: =SUM(C30:G30) -> 0 | J30: =$D$8 -> 0.15 | K30: =I30/(1-J30) -> 0
B31: INSTALL LED DISPLAYS | C31: 0 | D31: 0 | E31: 0 | F31: 0 | G31: 0 | I31: =SUM(C31:G31) -> 0 | J31: =$D$8 -> 0.15 | K31: =I31/(1-J31) -> 0
B32: INSTALL CLADDING AND TRIM | C32: 0 | D32: 0 | E32: 0 | F32: 0 | G32: 0 | I32: =SUM(C32:G32) -> 0 | J32: =$D$8 -> 0.15 | K32: =I32/(1-J32) -> 0
B33: HEAVY EQUIPMENT | C33: 0 | D33: 0 | E33: 0 | F33: 0 | G33: 0 | I33: =SUM(C33:G33) -> 0 | J33: =$D$8 -> 0.15 | K33: =I33/(1-J33) -> 0
B34: PM/GENERAL CONDITIONS/TRAVEL | C34: 5882.35 | D34: 0 | E34: 0 | F34: 0 | G34: 0 | I34: =SUM(C34:G34) -> 5882.35 | J34: =$D$8 -> 0.15 | K34: =I34/(1-J34) -> 6920.41
B35: SUBTOTAL | I35: =SUM(I29:I34) -> 5882.35 | K35: =SUM(K29:K34) -> 6920.41
B37: Electrical and Data - Materials and Subcontracting | C37: Subcontractor 1 | D37: Subcontractor 2 | E37: Subcontractor 3 | F37: Selected | G37: Additional Contingency | I37: Total Cost | J37: Install Margin | K37: Selling Price
B38: ELECTRICAL MATERIALS | C38: 0 | D38: 0 | E38: 0 | F38: 0 | G38: 0 | I38: =SUM(C38:G38) -> 0 | J38: =$D$9 -> 0.15 | K38: =I38/(1-J38) -> 0
B39: DATA MATERIALS | C39: 0 | D39: 0 | E39: 0 | F39: 0 | G39: 0 | I39: =SUM(C39:G39) -> 0 | J39: =$D$9 -> 0.15 | K39: =I39/(1-J39) -> 0
B40: ELECTRICAL LABOR | C40: 0 | D40: 0 | E40: 0 | F40: 0 | G40: 0 | I40: =SUM(C40:G40) -> 0 | J40: =$D$9 -> 0.15 | K40: =I40/(1-J40) -> 0
B41: DATA LABOR | C41: 0 | D41: 0 | E41: 0 | F41: 0 | G41: 0 | I41: =SUM(C41:G41) -> 0 | J41: =$D$9 -> 0.15 | K41: =I41/(1-J41) -> 0
B42: SUB PANEL | C42: 0 | D42: 0 | E42: 0 | F42: 0 | G42: 0 | I42: =SUM(C42:G42) -> 0 | J42: =$D$9 -> 0.15 | K42: =I42/(1-J42) -> 0
B43: MISC | C43: 0 | D43: 0 | E43: 0 | F43: 0 | G43: 0 | I43: =SUM(C43:G43) -> 0 | J43: =$D$9 -> 0.15 | K43: =I43/(1-J43) -> 0
B44: SUBTOTAL | I44: =SUM(I38:I43) -> 0 | K44: =SUM(K38:K43) -> 0
B46: Submittals, Engineering, and Permits | C46: Subcontractor 1 | D46: Subcontractor 2 | E46: Subcontractor 3 | F46: Selected | G46: Additional Contingency | I46: Total Cost | J46: Install Margin | K46: Selling Price
B47: STRUCTURAL ENGINEERING | C47: 4705.88 | D47: 0 | E47: 0 | F47: 0 | G47: 0 | I47: =SUM(C47:G47) -> 4705.88 | J47: =$D$11 -> 0.15 | K47: =I47/(1-J47) -> 5536.33
B48: STRUCTURAL CERTIFICATION | C48: 0 | D48: 0 | E48: 0 | F48: 0 | G48: 0 | I48: =SUM(C48:G48) -> 0 | J48: =$D$11 -> 0.15 | K48: =I48/(1-J48) -> 0
B49: ELECTRICAL ENGINEERING | C49: 0 | D49: 0 | E49: 0 | F49: 0 | G49: 0 | I49: =SUM(C49:G49) -> 0 | J49: =$D$11 -> 0.15 | K49: =I49/(1-J49) -> 0
B50: ELECTRICAL CERTIFICATION | C50: 0 | D50: 0 | E50: 0 | F50: 0 | G50: 0 | I50: =SUM(C50:G50) -> 0 | J50: =$D$11 -> 0.15 | K50: =I50/(1-J50) -> 0
B51: PERMITS | C51: 0 | D51: 0 | E51: 0 | F51: 0 | G51: 0 | I51: =SUM(C51:G51) -> 0 | J51: =$D$11 -> 0.15 | K51: =I51/(1-J51) -> 0
B52: SUBTOTAL | I52: =SUM(I47:I51) -> 4705.88 | K52: =SUM(K47:K51) -> 5536.33
B54: ZONE GRAND TOTAL | I54: =I26+I35+I44+I52 -> 10588.23 | K54: =K26+K35+K44+K52 -> 12456.74

Sheet T4-B2 - Install
A3: Project Name: Amended RFP Exhibit I
A4: 2026-03-31
A5: Revised By: ANC Proposal Engine
C7: Linked Margin Assignment
C8: Install Margin | D8: 0.15
C9: Electrical Margin | D9: 0.15
C10: ANC Margin | D10: 0.15
C11: Engineering and Permits | D11: 0.15
B15: T4-B2
B16: Height | C16: Width | D16: Total Sq. Ft | E16: QTY
B17: 7.87 | C17: 8.66 | D17: 68.15 | E17: 1
B19: Structural Materials: | C19: Subcontractor 1 | D19: Subcontractor 2 | E19: Subcontractor 3 | F19: Selected | G19: Additional Contingency | I19: Total Cost | J19: Install Margin | K19: Selling Price
B20: FABRICATE PRIMARY STEEL | C20: 0 | D20: 0 | E20: 0 | F20: 0 | G20: 0 | I20: =SUM(C20:G20) -> 0 | J20: =$D$8 -> 0.15 | K20: =I20/(1-J20) -> 0
B21: SUPPLY AND INSTALL PRIMARY PLYWOOD | C21: 0 | D21: 0 | E21: 0 | F21: 0 | G21: 0 | I21: =SUM(C21:G21) -> 0 | J21: =$D$8 -> 0.15 | K21: =I21/(1-J21) -> 0
B22: FABRICATE SECONDARY STEEL SUBSTRUCTURE | C22: 783.75 | D22: 0 | E22: 0 | F22: 0 | G22: 0 | I22: =SUM(C22:G22) -> 783.75 | J22: =$D$8 -> 0.15 | K22: =I22/(1-J22) -> 922.06
B23: FABRICATE CLADDING AND TRIM | C23: 0 | D23: 0 | E23: 0 | F23: 0 | G23: 0 | I23: =SUM(C23:G23) -> 0 | J23: =$D$8 -> 0.15 | K23: =I23/(1-J23) -> 0
B24: OTHER SCOPE ITEM | C24: 0 | D24: 0 | E24: 0 | F24: 0 | G24: 0 | I24: =SUM(C24:G24) -> 0 | J24: =$D$8 -> 0.15 | K24: =I24/(1-J24) -> 0
B25: OTHER SCOPE ITEM | C25: 0 | D25: 0 | E25: 0 | F25: 0 | G25: 0 | I25: =SUM(C25:G25) -> 0 | J25: =$D$8 -> 0.15 | K25: =I25/(1-J25) -> 0
B26: SUBTOTAL | I26: =SUM(I20:I25) -> 783.75 | K26: =SUM(K20:K25) -> 922.06
B28: Structural Labor and LED Installation | C28: Subcontractor 1 | D28: Subcontractor 2 | E28: Subcontractor 3 | F28: Selected | G28: Additional Contingency | I28: Total Cost | J28: Install Margin | K28: Selling Price
B29: REMOVAL AND DISPOSAL | C29: 0 | D29: 0 | E29: 0 | F29: 0 | G29: 0 | I29: =SUM(C29:G29) -> 0 | J29: =$D$8 -> 0.15 | K29: =I29/(1-J29) -> 0
B30: INSTALL SECONDARY STEEL SUBSTRUCTURE | C30: 0 | D30: 0 | E30: 0 | F30: 0 | G30: 0 | I30: =SUM(C30:G30) -> 0 | J30: =$D$8 -> 0.15 | K30: =I30/(1-J30) -> 0
B31: INSTALL LED DISPLAYS | C31: 3265.63 | D31: 0 | E31: 0 | F31: 0 | G31: 0 | I31: =SUM(C31:G31) -> 3265.63 | J31: =$D$8 -> 0.15 | K31: =I31/(1-J31) -> 3841.92
B32: INSTALL CLADDING AND TRIM | C32: 0 | D32: 0 | E32: 0 | F32: 0 | G32: 0 | I32: =SUM(C32:G32) -> 0 | J32: =$D$8 -> 0.15 | K32: =I32/(1-J32) -> 0
B33: HEAVY EQUIPMENT | C33: 0 | D33: 0 | E33: 0 | F33: 0 | G33: 0 | I33: =SUM(C33:G33) -> 0 | J33: =$D$8 -> 0.15 | K33: =I33/(1-J33) -> 0
B34: PM/GENERAL CONDITIONS/TRAVEL | C34: 20882.35 | D34: 0 | E34: 0 | F34: 0 | G34: 0 | I34: =SUM(C34:G34) -> 20882.35 | J34: =$D$8 -> 0.15 | K34: =I34/(1-J34) -> 24567.47
B35: SUBTOTAL | I35: =SUM(I29:I34) -> 24147.98 | K35: =SUM(K29:K34) -> 28409.39
B37: Electrical and Data - Materials and Subcontracting | C37: Subcontractor 1 | D37: Subcontractor 2 | E37: Subcontractor 3 | F37: Selected | G37: Additional Contingency | I37: Total Cost | J37: Install Margin | K37: Selling Price
B38: ELECTRICAL MATERIALS | C38: 3265.63 | D38: 0 | E38: 0 | F38: 0 | G38: 0 | I38: =SUM(C38:G38) -> 3265.63 | J38: =$D$9 -> 0.15 | K38: =I38/(1-J38) -> 3841.92
B39: DATA MATERIALS | C39: 0 | D39: 0 | E39: 0 | F39: 0 | G39: 0 | I39: =SUM(C39:G39) -> 0 | J39: =$D$9 -> 0.15 | K39: =I39/(1-J39) -> 0
B40: ELECTRICAL LABOR | C40: 0 | D40: 0 | E40: 0 | F40: 0 | G40: 0 | I40: =SUM(C40:G40) -> 0 | J40: =$D$9 -> 0.15 | K40: =I40/(1-J40) -> 0
B41: DATA LABOR | C41: 0 | D41: 0 | E41: 0 | F41: 0 | G41: 0 | I41: =SUM(C41:G41) -> 0 | J41: =$D$9 -> 0.15 | K41: =I41/(1-J41) -> 0
B42: SUB PANEL | C42: 0 | D42: 0 | E42: 0 | F42: 0 | G42: 0 | I42: =SUM(C42:G42) -> 0 | J42: =$D$9 -> 0.15 | K42: =I42/(1-J42) -> 0
B43: MISC | C43: 0 | D43: 0 | E43: 0 | F43: 0 | G43: 0 | I43: =SUM(C43:G43) -> 0 | J43: =$D$9 -> 0.15 | K43: =I43/(1-J43) -> 0
B44: SUBTOTAL | I44: =SUM(I38:I43) -> 3265.63 | K44: =SUM(K38:K43) -> 3841.92
B46: Submittals, Engineering, and Permits | C46: Subcontractor 1 | D46: Subcontractor 2 | E46: Subcontractor 3 | F46: Selected | G46: Additional Contingency | I46: Total Cost | J46: Install Margin | K46: Selling Price
B47: STRUCTURAL ENGINEERING | C47: 4705.88 | D47: 0 | E47: 0 | F47: 0 | G47: 0 | I47: =SUM(C47:G47) -> 4705.88 | J47: =$D$11 -> 0.15 | K47: =I47/(1-J47) -> 5536.33
B48: STRUCTURAL CERTIFICATION | C48: 0 | D48: 0 | E48: 0 | F48: 0 | G48: 0 | I48: =SUM(C48:G48) -> 0 | J48: =$D$11 -> 0.15 | K48: =I48/(1-J48) -> 0
B49: ELECTRICAL ENGINEERING | C49: 0 | D49: 0 | E49: 0 | F49: 0 | G49: 0 | I49: =SUM(C49:G49) -> 0 | J49: =$D$11 -> 0.15 | K49: =I49/(1-J49) -> 0
B50: ELECTRICAL CERTIFICATION | C50: 0 | D50: 0 | E50: 0 | F50: 0 | G50: 0 | I50: =SUM(C50:G50) -> 0 | J50: =$D$11 -> 0.15 | K50: =I50/(1-J50) -> 0
B51: PERMITS | C51: 0 | D51: 0 | E51: 0 | F51: 0 | G51: 0 | I51: =SUM(C51:G51) -> 0 | J51: =$D$11 -> 0.15 | K51: =I51/(1-J51) -> 0
B52: SUBTOTAL | I52: =SUM(I47:I51) -> 4705.88 | K52: =SUM(K47:K51) -> 5536.33
B54: ZONE GRAND TOTAL | I54: =I26+I35+I44+I52 -> 50714.9 | K54: =K26+K35+K44+K52 -> 58862.82

Sheet Processor Count
A1: Amended RFP Exhibit I — Processor Count
B4: Display | C4: Width (px) | D4: Height (px) | E4: Ports | F4: Ports (80%) | G4: 8-bit Video | H4: 8-bit (80%) | I4: 10/12/HDR bit
B5: 660 Pro | C5: 1920 | D5: 1080 | E5: 8 | G5: 650000 | H5: 455000 | I5: 320000
B6: MCTRL4K | C6: 3840 | D6: 2160 | E6: 16 | G6: 650000 | H6: 455000 | I6: 320000
B7: H9 Enhanced | C7: 7680 | D7: 4320 | E7: 20 | G7: 1200000 | H7: 960000 | I7: 650000
B10: DISPLAY PROCESSOR REQUIREMENTS
B11: Display | C11: Width (px) | D11: Height (px) | E11: Qty | F11: Total Pixels | G11: Ports Needed | H11: Processor Type | I11: Processors Needed
B12: ='LED Cost Sheet'!A4 -> 9A Underpass 1 | C12: ='LED Cost Sheet'!H4 -> 0 | D12: ='LED Cost Sheet'!G4 -> 0 | E12: ='LED Cost Sheet'!I4 -> 1 | F12: =C12*D12*E12 -> 696180 | G12: =IFERROR(CEILING(F12/650000,1),0) -> 2 | H12: =IF(G12>8,"MCTRL4K","660 Pro") -> 660 Pro | I12: =IFERROR(CEILING(G12/IF(G12>8,16,8),1),0) -> 1
B13: ='LED Cost Sheet'!A5 -> 9A Underpass 2 | C13: ='LED Cost Sheet'!H5 -> 0 | D13: ='LED Cost Sheet'!G5 -> 0 | E13: ='LED Cost Sheet'!I5 -> 1 | F13: =C13*D13*E13 -> 1367730 | G13: =IFERROR(CEILING(F13/650000,1),0) -> 3 | H13: =IF(G13>8,"MCTRL4K","660 Pro") -> 660 Pro | I13: =IFERROR(CEILING(G13/IF(G13>8,16,8),1),0) -> 1
B14: ='LED Cost Sheet'!A6 -> 9A Underpass 3 | C14: ='LED Cost Sheet'!H6 -> 0 | D14: ='LED Cost Sheet'!G6 -> 0 | E14: ='LED Cost Sheet'!I6 -> 1 | F14: =C14*D14*E14 -> 1367730 | G14: =IFERROR(CEILING(F14/650000,1),0) -> 3 | H14: =IF(G14>8,"MCTRL4K","660 Pro") -> 660 Pro | I14: =IFERROR(CEILING(G14/IF(G14>8,16,8),1),0) -> 1
B15: ='LED Cost Sheet'!A7 -> 9A Underpass 4 | C15: ='LED Cost Sheet'!H7 -> 0 | D15: ='LED Cost Sheet'!G7 -> 0 | E15: ='LED Cost Sheet'!I7 -> 1 | F15: =C15*D15*E15 -> 2302930 | G15: =IFERROR(CEILING(F15/650000,1),0) -> 4 | H15: =IF(G15>8,"MCTRL4K","660 Pro") -> 660 Pro | I15: =IFERROR(CEILING(G15/IF(G15>8,16,8),1),0) -> 1
B16: ='LED Cost Sheet'!A8 -> Concourse | C16: ='LED Cost Sheet'!H8 -> 0 | D16: ='LED Cost Sheet'!G8 -> 0 | E16: ='LED Cost Sheet'!I8 -> 1 | F16: =C16*D16*E16 -> 16189273 | G16: =IFERROR(CEILING(F16/650000,1),0) -> 25 | H16: =IF(G16>8,"MCTRL4K","660 Pro") -> MCTRL4K | I16: =IFERROR(CEILING(G16/IF(G16>8,16,8),1),0) -> 2
B17: ='LED Cost Sheet'!A9 -> T4 Elevator | C17: ='LED Cost Sheet'!H9 -> 0 | D17: ='LED Cost Sheet'!G9 -> 0 | E17: ='LED Cost Sheet'!I9 -> 1 | F17: =C17*D17*E17 -> 2406280 | G17: =IFERROR(CEILING(F17/650000,1),0) -> 4 | H17: =IF(G17>8,"MCTRL4K","660 Pro") -> 660 Pro | I17: =IFERROR(CEILING(G17/IF(G17>8,16,8),1),0) -> 1
B18: ='LED Cost Sheet'!A10 -> New Path Hall Option 1 | C18: ='LED Cost Sheet'!H10 -> 0 | D18: ='LED Cost Sheet'!G10 -> 0 | E18: ='LED Cost Sheet'!I10 -> 1 | F18: =C18*D18*E18 -> 4103594 | G18: =IFERROR(CEILING(F18/650000,1),0) -> 7 | H18: =IF(G18>8,"MCTRL4K","660 Pro") -> 660 Pro | I18: =IFERROR(CEILING(G18/IF(G18>8,16,8),1),0) -> 1
B19: ='LED Cost Sheet'!A11 -> New Path Hall Option 2 | C19: ='LED Cost Sheet'!H11 -> 0 | D19: ='LED Cost Sheet'!G11 -> 0 | E19: ='LED Cost Sheet'!I11 -> 1 | F19: =C19*D19*E19 -> 5161280 | G19: =IFERROR(CEILING(F19/650000,1),0) -> 8 | H19: =IF(G19>8,"MCTRL4K","660 Pro") -> 660 Pro | I19: =IFERROR(CEILING(G19/IF(G19>8,16,8),1),0) -> 1
B20: ='LED Cost Sheet'!A12 -> One Train | C20: ='LED Cost Sheet'!H12 -> 0 | D20: ='LED Cost Sheet'!G12 -> 0 | E20: ='LED Cost Sheet'!I12 -> 1 | F20: =C20*D20*E20 -> 0 | G20: =IFERROR(CEILING(F20/650000,1),0) -> 0 | H20: =IF(G20>8,"MCTRL4K","660 Pro") -> 660 Pro | I20: =IFERROR(CEILING(G20/IF(G20>8,16,8),1),0) -> 0
B21: ='LED Cost Sheet'!A13 -> T4-B2 | C21: ='LED Cost Sheet'!H13 -> 0 | D21: ='LED Cost Sheet'!G13 -> 0 | E21: ='LED Cost Sheet'!I13 -> 1 | F21: =C21*D21*E21 -> 416355 | G21: =IFERROR(CEILING(F21/650000,1),0) -> 1 | H21: =IF(G21>8,"MCTRL4K","660 Pro") -> 660 Pro | I21: =IFERROR(CEILING(G21/IF(G21>8,16,8),1),0) -> 1
B22: TOTAL | F22: =SUM(F12:F21) -> 34011352 | G22: =SUM(G12:G21) -> 57 | I22: =SUM(I12:I21) -> 10

Sheet Bundle Equipment
A1: Amended RFP Exhibit I — Processor & Equipment Breakdown
A2: Editable — adjust component costs per display zone. Totals roll into Margin Analysis.
A6: Category | B6: Component | C6: Cost | D6: Qty | E6: Total Cost | F6: Margin | G6: Selling Price | H6: Margin $
A7: 9A Underpass 1 — Underpass 1
A8: EQUIPMENT | B8: Sending Card | C8: 450 | D8: 1 | E8: =C8*D8 -> 450 | F8: 0.15 | G8: =IFERROR(E8/(1-F8),0) -> 529.41 | H8: =IFERROR(G8-E8,0) -> 79.41
A9: EQUIPMENT | B9: Signal Cable Kit | C9: 68.45 | D9: 1 | E9: =C9*D9 -> 68.45 | F9: 0.15 | G9: =IFERROR(E9/(1-F9),0) -> 80.53 | H9: =IFERROR(G9-E9,0) -> 12.08
B10: Zone Subtotal | E10: =SUM(E8:E9) -> 518.45 | G10: =SUM(G8:G9) -> 609.94 | H10: =IFERROR(G10-E10,0) -> 91.49
A12: 9A Underpass 2 — Underpass 2
A13: EQUIPMENT | B13: Sending Card | C13: 450 | D13: 1 | E13: =C13*D13 -> 450 | F13: 0.15 | G13: =IFERROR(E13/(1-F13),0) -> 529.41 | H13: =IFERROR(G13-E13,0) -> 79.41
A14: EQUIPMENT | B14: Signal Cable Kit | C14: 134.28 | D14: 1 | E14: =C14*D14 -> 134.28 | F14: 0.15 | G14: =IFERROR(E14/(1-F14),0) -> 157.98 | H14: =IFERROR(G14-E14,0) -> 23.7
B15: Zone Subtotal | E15: =SUM(E13:E14) -> 584.28 | G15: =SUM(G13:G14) -> 687.39 | H15: =IFERROR(G15-E15,0) -> 103.11
A17: 9A Underpass 3 — Underpass 3
A18: EQUIPMENT | B18: Sending Card | C18: 450 | D18: 1 | E18: =C18*D18 -> 450 | F18: 0.15 | G18: =IFERROR(E18/(1-F18),0) -> 529.41 | H18: =IFERROR(G18-E18,0) -> 79.41
A19: EQUIPMENT | B19: Signal Cable Kit | C19: 134.28 | D19: 1 | E19: =C19*D19 -> 134.28 | F19: 0.15 | G19: =IFERROR(E19/(1-F19),0) -> 157.98 | H19: =IFERROR(G19-E19,0) -> 23.7
B20: Zone Subtotal | E20: =SUM(E18:E19) -> 584.28 | G20: =SUM(G18:G19) -> 687.39 | H20: =IFERROR(G20-E20,0) -> 103.11
A22: 9A Underpass 4 — Underpass 4
A23: EQUIPMENT | B23: Sending Card | C23: 450 | D23: 1 | E23: =C23*D23 -> 450 | F23: 0.15 | G23: =IFERROR(E23/(1-F23),0) -> 529.41 | H23: =IFERROR(G23-E23,0) -> 79.41
A24: EQUIPMENT | B24: Signal Cable Kit | C24: 226.19 | D24: 1 | E24: =C24*D24 -> 226.19 | F24: 0.15 | G24: =IFERROR(E24/(1-F24),0) -> 266.11 | H24: =IFERROR(G24-E24,0) -> 39.92
A25: EQUIPMENT | B25: Backup Video Processor | C25: 12000 | D25: 1 | E25: =C25*D25 -> 12000 | F25: 0.15 | G25: =IFERROR(E25/(1-F25),0) -> 14117.65 | H25: =IFERROR(G25-E25,0) -> 2117.65
B26: Zone Subtotal | E26: =SUM(E23:E25) -> 12676.19 | G26: =SUM(G23:G25) -> 14913.17 | H26: =IFERROR(G26-E26,0) -> 2236.98
A28: Concourse — Concourse
A29: EQUIPMENT | B29: Sending Card | C29: 16800 | D29: 1 | E29: =C29*D29 -> 16800 | F29: 0.15 | G29: =IFERROR(E29/(1-F29),0) -> 19764.71 | H29: =IFERROR(G29-E29,0) -> 2964.71
A30: EQUIPMENT | B30: Signal Cable Kit | C30: 1589.36 | D30: 1 | E30: =C30*D30 -> 1589.36 | F30: 0.15 | G30: =IFERROR(E30/(1-F30),0) -> 1869.84 | H30: =IFERROR(G30-E30,0) -> 280.48
A31: EQUIPMENT | B31: Backup Video Processor | C31: 12000 | D31: 1 | E31: =C31*D31 -> 12000 | F31: 0.15 | G31: =IFERROR(E31/(1-F31),0) -> 14117.65 | H31: =IFERROR(G31-E31,0) -> 2117.65
B32: Zone Subtotal | E32: =SUM(E29:E31) -> 30389.36 | G32: =SUM(G29:G31) -> 35752.2 | H32: =IFERROR(G32-E32,0) -> 5362.84
A34: T4 Elevator — T4 Lobby Elevator
A35: EQUIPMENT | B35: Sending Card | C35: 450 | D35: 1 | E35: =C35*D35 -> 450 | F35: 0.15 | G35: =IFERROR(E35/(1-F35),0) -> 529.41 | H35: =IFERROR(G35-E35,0) -> 79.41
A36: EQUIPMENT | B36: Signal Cable Kit | C36: 236.28 | D36: 1 | E36: =C36*D36 -> 236.28 | F36: 0.15 | G36: =IFERROR(E36/(1-F36),0) -> 277.98 | H36: =IFERROR(G36-E36,0) -> 41.7
A37: EQUIPMENT | B37: Backup Video Processor | C37: 12000 | D37: 1 | E37: =C37*D37 -> 12000 | F37: 0.15 | G37: =IFERROR(E37/(1-F37),0) -> 14117.65 | H37: =IFERROR(G37-E37,0) -> 2117.65
B38: Zone Subtotal | E38: =SUM(E35:E37) -> 12686.28 | G38: =SUM(G35:G37) -> 14925.04 | H38: =IFERROR(G38-E38,0) -> 2238.76
A40: New Path Hall Option 1 — Path Hall
A41: EQUIPMENT | B41: Sending Card | C41: 450 | D41: 1 | E41: =C41*D41 -> 450 | F41: 0.15 | G41: =IFERROR(E41/(1-F41),0) -> 529.41 | H41: =IFERROR(G41-E41,0) -> 79.41
A42: EQUIPMENT | B42: Signal Cable Kit | C42: 403.2 | D42: 1 | E42: =C42*D42 -> 403.2 | F42: 0.15 | G42: =IFERROR(E42/(1-F42),0) -> 474.35 | H42: =IFERROR(G42-E42,0) -> 71.15
A43: EQUIPMENT | B43: Backup Video Processor | C43: 12000 | D43: 1 | E43: =C43*D43 -> 12000 | F43: 0.15 | G43: =IFERROR(E43/(1-F43),0) -> 14117.65 | H43: =IFERROR(G43-E43,0) -> 2117.65
B44: Zone Subtotal | E44: =SUM(E41:E43) -> 12853.2 | G44: =SUM(G41:G43) -> 15121.41 | H44: =IFERROR(G44-E44,0) -> 2268.21
A46: New Path Hall Option 2 — Path Hall
A47: EQUIPMENT | B47: Sending Card | C47: 450 | D47: 1 | E47: =C47*D47 -> 450 | F47: 0.15 | G47: =IFERROR(E47/(1-F47),0) -> 529.41 | H47: =IFERROR(G47-E47,0) -> 79.41
A48: EQUIPMENT | B48: Signal Cable Kit | C48: 507 | D48: 1 | E48: =C48*D48 -> 507 | F48: 0.15 | G48: =IFERROR(E48/(1-F48),0) -> 596.47 | H48: =IFERROR(G48-E48,0) -> 89.47
A49: EQUIPMENT | B49: Backup Video Processor | C49: 12000 | D49: 1 | E49: =C49*D49 -> 12000 | F49: 0.15 | G49: =IFERROR(E49/(1-F49),0) -> 14117.65 | H49: =IFERROR(G49-E49,0) -> 2117.65
B50: Zone Subtotal | E50: =SUM(E47:E49) -> 12957 | G50: =SUM(G47:G49) -> 15243.53 | H50: =IFERROR(G50-E50,0) -> 2286.53
A52: One Train — One Train
B53: (no equipment for this zone)
B54: Zone Subtotal | E54: =0 -> 0 | G54: =0 -> 0 | H54: =IFERROR(G54-E54,0) -> 0
A56: T4-B2 — T4-B2
A57: EQUIPMENT | B57: Sending Card | C57: 450 | D57: 1 | E57: =C57*D57 -> 450 | F57: 0.15 | G57: =IFERROR(E57/(1-F57),0) -> 529.41 | H57: =IFERROR(G57-E57,0) -> 79.41
A58: EQUIPMENT | B58: Signal Cable Kit | C58: 40.89 | D58: 1 | E58: =C58*D58 -> 40.89 | F58: 0.15 | G58: =IFERROR(E58/(1-F58),0) -> 48.11 | H58: =IFERROR(G58-E58,0) -> 7.22
B59: Zone Subtotal | E59: =SUM(E57:E58) -> 490.89 | G59: =SUM(G57:G58) -> 577.52 | H59: =IFERROR(G59-E59,0) -> 86.63
A61: EQUIPMENT GRAND TOTAL | E61: =E10+E15+E20+E26+E32+E38+E44+E50+E54+E59 -> 83739.93 | G61: =G10+G15+G20+G26+G32+G38+G44+G50+G54+G59 -> 98517.57 | H61: =IFERROR(G61-E61,0) -> 14777.64

Sheet ANC Travel
A1: Amended RFP Exhibit I — ANC Travel
B4: Travel - Installation | C4: Cost | D4: Quantity | E4: Total Cost
B5: Hotel | C5: 300 | D5: 0 | E5: 0
B6: Airfare | C6: 1000 | D6: 0 | E6: 0
B7: Car | C7: 125 | D7: 0 | E7: 0
B8: Per Diem | C8: 100 | D8: 0 | E8: 0
B9: Bundled | C9: 10000 | D9: 0 | E9: 0 | G9: Account for freelancer
B10: Total | E10: 0
B11: TOTAL | C11: USD: | E11: 0
B13: Travel - Commissioning | C13: Cost | D13: Quantity | E13: Total Cost
B14: Hotel | C14: 300 | D14: 0 | E14: 0
B15: Airfare | C15: 1000 | D15: 0 | E15: 0
B16: Car | C16: 125 | D16: 0 | E16: 0
B17: Per Diem | C17: 100 | D17: 0 | E17: 0
B18: Bundled | C18: 10000 | D18: 0 | E18: 0 | G18: Account for freelancer
B19: Total | E19: 0
B20: TOTAL | C20: USD: | E20: 0
B22: Game Support | C22: Cost | D22: Quantity | E22: Total Cost
B23: Hotel | C23: 300 | D23: 0 | E23: 0
B24: Airfare | C24: 1000 | D24: 0 | E24: 0
B25: Car | C25: 125 | D25: 0 | E25: 0
B26: Per Diem | C26: 100 | D26: 0 | E26: 0
B27: Bundled | C27: 10000 | D27: 0 | E27: 0 | G27: Account for freelancer
B28: Game Day Support | C28: 1500 | D28: 0 | E28: 0
B29: Total | E29: 0
B30: TOTAL | C30: USD: | E30: 0

Sheet CMS
A1: Amended RFP Exhibit I — Content Management System
B4: CMS Platform
B5: All costs require project-specific pricing — update items below based on RFP requirements
B6: Category | C6: Item | D6: Cost | E6: Quantity | F6: Total Cost | G6: Margin | H6: Selling Price | I6: Margin $
B7: PRIMARY | C7: DESIGN & CONTROL SOFTWARE | D7: 0 | E7: 0 | F7: =D7*E7 -> 0 | G7: 0.1 | H7: =IFERROR(F7/(1-G7),0) -> 0 | I7: =IFERROR(H7-F7,0) -> 0
B8: PRIMARY | C8: GRAPHICS PLAYBACK ENGINE | D8: 0 | E8: 0 | F8: =D8*E8 -> 0 | G8: 0.1 | H8: =IFERROR(F8/(1-G8),0) -> 0 | I8: =IFERROR(H8-F8,0) -> 0
B9: PRIMARY | C9: IMAGE PROCESSING | D9: 0 | E9: 0 | F9: =D9*E9 -> 0 | G9: 0.1 | H9: =IFERROR(F9/(1-G9),0) -> 0 | I9: =IFERROR(H9-F9,0) -> 0
B10: PRIMARY | C10: DEDICATED LED ROUTER / SWITCH | D10: 0 | E10: 0 | F10: =D10*E10 -> 0 | G10: 0.1 | H10: =IFERROR(F10/(1-G10),0) -> 0 | I10: =IFERROR(H10-F10,0) -> 0
B11: REDUNDANT | C11: DESIGN & CONTROL SOFTWARE | D11: 0 | E11: 0 | F11: =D11*E11 -> 0 | G11: 0.1 | H11: =IFERROR(F11/(1-G11),0) -> 0 | I11: =IFERROR(H11-F11,0) -> 0
B12: REDUNDANT | C12: GRAPHICS PLAYBACK ENGINE | D12: 0 | E12: 0 | F12: =D12*E12 -> 0 | G12: 0.1 | H12: =IFERROR(F12/(1-G12),0) -> 0 | I12: =IFERROR(H12-F12,0) -> 0
B13: REDUNDANT | C13: IMAGE PROCESSING | D13: 0 | E13: 0 | F13: =D13*E13 -> 0 | G13: 0.1 | H13: =IFERROR(F13/(1-G13),0) -> 0 | I13: =IFERROR(H13-F13,0) -> 0
B14: STANDARD SERVICES | C14: COMMISSIONING | D14: 0 | E14: 0 | F14: =D14*E14 -> 0 | G14: 0.1 | H14: =IFERROR(F14/(1-G14),0) -> 0 | I14: =IFERROR(H14-F14,0) -> 0
B15: STANDARD SERVICES | C15: EVENT SUPPORT | D15: 0 | E15: 0 | F15: =D15*E15 -> 0 | G15: 0.1 | H15: =IFERROR(F15/(1-G15),0) -> 0 | I15: =IFERROR(H15-F15,0) -> 0
B16: STANDARD SERVICES | C16: PROJECT MANAGEMENT | D16: 0 | E16: 0 | F16: =D16*E16 -> 0 | G16: 0.1 | H16: =IFERROR(F16/(1-G16),0) -> 0 | I16: =IFERROR(H16-F16,0) -> 0
C17: Integration Hardware | D17: 0 | E17: 0 | F17: =D17*E17 -> 0 | G17: 0.1 | H17: =IFERROR(F17/(1-G17),0) -> 0 | I17: =IFERROR(H17-F17,0) -> 0
C18: Integration Labor | D18: 0 | E18: 0 | F18: =D18*E18 -> 0 | G18: 0.1 | H18: =IFERROR(F18/(1-G18),0) -> 0 | I18: =IFERROR(H18-F18,0) -> 0
C19: Shipping | D19: 0 | E19: 0 | F19: =D19*E19 -> 0 | G19: 0.1 | H19: =IFERROR(F19/(1-G19),0) -> 0 | I19: =IFERROR(H19-F19,0) -> 0
C20: Travel | D20: 0 | E20: 0 | F20: =D20*E20 -> 0 | G20: 0.1 | H20: =IFERROR(F20/(1-G20),0) -> 0 | I20: =IFERROR(H20-F20,0) -> 0
C22: CMS TOTAL | F22: =SUM(F7:F20) -> 0 | H22: =SUM(H7:H20) -> 0 | I22: =IFERROR(H22-F22,0) -> 0
B24: TAX | F24: 0
B25: BOND | F25: 0
B26: SUB TOTAL | C26: USD: | F26: =F22+F24+F25 -> 0 | H26: =H22 -> 0 | I26: =IFERROR(H26-F26,0) -> 0

Sheet Scoring
A1: Amended RFP Exhibit I — Scoring System
B4: Scoring Platform
B5: All costs require project-specific pricing — update items below based on RFP requirements
B6: Category | C6: Item | D6: Cost | E6: Quantity | F6: Total Cost | G6: Margin | H6: Selling Price | I6: Margin $
B7: HARDWARE | C7: SCORING CONTROLLER / SERVER | D7: 0 | E7: 0 | F7: =D7*E7 -> 0 | G7: 0.1 | H7: =IFERROR(F7/(1-G7),0) -> 0 | I7: =IFERROR(H7-F7,0) -> 0
B8: HARDWARE | C8: OPERATOR WORKSTATION(S) | D8: 0 | E8: 0 | F8: =D8*E8 -> 0 | G8: 0.1 | H8: =IFERROR(F8/(1-G8),0) -> 0 | I8: =IFERROR(H8-F8,0) -> 0
B9: HARDWARE | C9: SCOREBOARD INPUT DEVICES | D9: 0 | E9: 0 | F9: =D9*E9 -> 0 | G9: 0.1 | H9: =IFERROR(F9/(1-G9),0) -> 0 | I9: =IFERROR(H9-F9,0) -> 0
B10: HARDWARE | C10: SHOT CLOCK / GAME CLOCK INTERFACE | D10: 0 | E10: 0 | F10: =D10*E10 -> 0 | G10: 0.1 | H10: =IFERROR(F10/(1-G10),0) -> 0 | I10: =IFERROR(H10-F10,0) -> 0
B11: HARDWARE | C11: STATISTICS INTERFACE | D11: 0 | E11: 0 | F11: =D11*E11 -> 0 | G11: 0.1 | H11: =IFERROR(F11/(1-G11),0) -> 0 | I11: =IFERROR(H11-F11,0) -> 0
B12: SOFTWARE | C12: SCORING SOFTWARE LICENSE | D12: 0 | E12: 0 | F12: =D12*E12 -> 0 | G12: 0.1 | H12: =IFERROR(F12/(1-G12),0) -> 0 | I12: =IFERROR(H12-F12,0) -> 0
B13: SOFTWARE | C13: GRAPHICS / ANIMATION PACKAGE | D13: 0 | E13: 0 | F13: =D13*E13 -> 0 | G13: 0.1 | H13: =IFERROR(F13/(1-G13),0) -> 0 | I13: =IFERROR(H13-F13,0) -> 0
B14: SOFTWARE | C14: STATISTICS INTEGRATION | D14: 0 | E14: 0 | F14: =D14*E14 -> 0 | G14: 0.1 | H14: =IFERROR(F14/(1-G14),0) -> 0 | I14: =IFERROR(H14-F14,0) -> 0
B15: SERVICES | C15: COMMISSIONING | D15: 0 | E15: 0 | F15: =D15*E15 -> 0 | G15: 0.1 | H15: =IFERROR(F15/(1-G15),0) -> 0 | I15: =IFERROR(H15-F15,0) -> 0
B16: SERVICES | C16: TRAINING | D16: 0 | E16: 0 | F16: =D16*E16 -> 0 | G16: 0.1 | H16: =IFERROR(F16/(1-G16),0) -> 0 | I16: =IFERROR(H16-F16,0) -> 0
B17: SERVICES | C17: PROJECT MANAGEMENT | D17: 0 | E17: 0 | F17: =D17*E17 -> 0 | G17: 0.1 | H17: =IFERROR(F17/(1-G17),0) -> 0 | I17: =IFERROR(H17-F17,0) -> 0
C18: Integration Hardware | D18: 0 | E18: 0 | F18: =D18*E18 -> 0 | G18: 0.1 | H18: =IFERROR(F18/(1-G18),0) -> 0 | I18: =IFERROR(H18-F18,0) -> 0
C19: Integration Labor | D19: 0 | E19: 0 | F19: =D19*E19 -> 0 | G19: 0.1 | H19: =IFERROR(F19/(1-G19),0) -> 0 | I19: =IFERROR(H19-F19,0) -> 0
C20: Shipping | D20: 0 | E20: 0 | F20: =D20*E20 -> 0 | G20: 0.1 | H20: =IFERROR(F20/(1-G20),0) -> 0 | I20: =IFERROR(H20-F20,0) -> 0
C21: Travel | D21: 0 | E21: 0 | F21: =D21*E21 -> 0 | G21: 0.1 | H21: =IFERROR(F21/(1-G21),0) -> 0 | I21: =IFERROR(H21-F21,0) -> 0
C23: SCORING TOTAL | F23: =SUM(F7:F21) -> 0 | H23: =SUM(H7:H21) -> 0 | I23: =IFERROR(H23-F23,0) -> 0
B25: TAX | F25: 0
B26: BOND | F26: 0
B27: SUB TOTAL | C27: USD: | F27: =F23+F25+F26 -> 0 | H27: =H23 -> 0 | I27: =IFERROR(H27-F27,0) -> 0

Sheet Venue Services
A1: Amended RFP Exhibit I — Venue Services
A2: Multi-year service contract calculator
A4: Contract Years | B4: 3 | C4: Editable service term
A5: Year 1 Cost | B5: 0 | C5: Base annual contract value
A6: Annual Escalation % | B6: 0.03 | C6: Applied to each renewal year
A7: Margin % | B7: 0.15 | C7: Target service-contract margin
A10: Year | B10: Cost | C10: Selling Price | D10: Margin $ | E10: Notes
A11: =IF($B$4>=1,"Year 1","") -> Year 1 | B11: =$B$5 -> 0 | C11: =IF(A11="",0,IFERROR(B11/(1-$B$7),0)) -> 0 | D11: =IF(A11="",0,IFERROR(C11-B11,0)) -> 0 | E11: Escalated annual term
A12: =IF($B$4>=2,"Year 2","") -> Year 2 | B12: =IF(A12="",0,B11*(1+$B$6)) -> 0 | C12: =IF(A12="",0,IFERROR(B12/(1-$B$7),0)) -> 0 | D12: =IF(A12="",0,IFERROR(C12-B12,0)) -> 0 | E12: Escalated annual term
A13: =IF($B$4>=3,"Year 3","") -> Year 3 | B13: =IF(A13="",0,B12*(1+$B$6)) -> 0 | C13: =IF(A13="",0,IFERROR(B13/(1-$B$7),0)) -> 0 | D13: =IF(A13="",0,IFERROR(C13-B13,0)) -> 0 | E13: Escalated annual term
A14: =IF($B$4>=4,"Year 4","") | B14: =IF(A14="",0,B13*(1+$B$6)) -> 0 | C14: =IF(A14="",0,IFERROR(B14/(1-$B$7),0)) -> 0 | D14: =IF(A14="",0,IFERROR(C14-B14,0)) -> 0
A15: =IF($B$4>=5,"Year 5","") | B15: =IF(A15="",0,B14*(1+$B$6)) -> 0 | C15: =IF(A15="",0,IFERROR(B15/(1-$B$7),0)) -> 0 | D15: =IF(A15="",0,IFERROR(C15-B15,0)) -> 0
A17: VENUE SERVICES TOTAL | B17: =SUM(B11:B15) -> 0 | C17: =SUM(C11:C15) -> 0 | D17: =IFERROR(C17-B17,0) -> 0

Sheet Additional Items
A1: Amended RFP Exhibit I — Additional Non-LED Items
B4: Category | C4: Item | D4: Cost | E4: Quantity | F4: Total Cost | G4: Margin | H4: Selling Price | I4: Margin $
B5: GAME CLOCK | C5: Six-Digit Game Clocks | D5: 0 | E5: 1 | F5: =D5*E5 -> 0 | G5: 0.15 | H5: =IFERROR(F5/(1-G5),0) -> 0 | I5: =IFERROR(H5-F5,0) -> 0
B6: PITCH CLOCK | C6: Pitch Clocks | D6: 0 | E6: 1 | F6: =D6*E6 -> 0 | G6: 0.15 | H6: =IFERROR(F6/(1-G6),0) -> 0 | I6: =IFERROR(H6-F6,0) -> 0
B7: OES / MIS | C7: OES / MIS / Timing | D7: 0 | E7: 1 | F7: =D7*E7 -> 0 | G7: 0.15 | H7: =IFERROR(F7/(1-G7),0) -> 0 | I7: =IFERROR(H7-F7,0) -> 0
B8: MISC | C8: DMX / Misc Equipment | D8: 0 | E8: 1 | F8: =D8*E8 -> 0 | G8: 0.15 | H8: =IFERROR(F8/(1-G8),0) -> 0 | I8: =IFERROR(H8-F8,0) -> 0
C10: ADDITIONAL ITEMS TOTAL | F10: =SUM(F5:F8) -> 0 | H10: =SUM(H5:H8) -> 0 | I10: =IFERROR(H10-F10,0) -> 0

Sheet Resp Matrix
B1: Project: Amended RFP Exhibit I
B2: Date: 3/31/2026
B4: Administrative | C4: ANC | D4: Purchaser
B5: Provide accurate architectural, structural engineering, and AV drawings. | D5: X
B6: Provide Payment and Performance Bond. | C6: NA
B7: All required zoning, building, street or sidewalk permits. | C7: NA
B8: Shipping of all equipment to site. | C8: X
B9: Receive, unload, and inspect all new equipment upon arrival. | C9: X
B10: Provide safe storage of video equipment and control room. | D10: X
B11: Unobstructed access to equipment and control room. | D11: X
B13: Engineering & Submittals | C13: ANC | D13: Purchaser
B14: Customer responsible to ensure existing structure supports new equipment. | D14: X
B15: Provide mechanical drawings, electrical drawings, and load calculations. | C15: X
B16: Engineering and certification for new equipment attachments. | C16: X
B17: Provide approval of all mechanical/electrical drawings. | D17: X
B18: Responsible to ensure structural integrity of existing conditions. | D18: X
B20: Physical Installation | C20: ANC | D20: Purchaser
B21: ANC assumes all base building structure is provided by others. | C21: Include Statement
B22: ANC has included removal and disposal of existing equipment. | D22: X
B23: ANC assumes reasonable access will be provided to the work area. | C23: Include Statement
B24: Fabricate, deliver, and install support structure. | C24: X
B25: Provide & Install LED components. | C25: X
B26: Provide all required Floor/Site Protection. | D26: X
B28: Electrical & Data Installation | C28: ANC | D28: Purchaser
B29: Submit electrical engineering drawings. | C29: X
B30: Provide primary power feed to each display location. | D30: X
B31: Provide secondary electrical panels and/or remote disconnects. | D31: X
B32: Furnish signal cables as specified by ANC. | C32: X
B33: Provide and install signal cable conduit. | D33: X
B34: Labor to pull signal cable. | C34: X
B35: Terminate signal cable at control system equipment. | C35: X
B36: Mount and install data patch panel. | C36: X
B37: Provide high speed internet connection to control room. | D37: X
B39: Control System | C39: ANC | D39: Purchaser
B40: ANC has provided display processors only. | C40: Include Statement
B41: Provide climate controlled control room. | D41: X
B42: Supply static IP address five (5) days prior to installation. | D42: X
B44: Training | C44: ANC | D44: Purchaser
B45: Provide appropriate on-site operation and maintenance training. | C45: X
B46: Provide sign off list for all training. | C46: X
B47: Perform one (1) day of maintenance training. | C47: X
B48: Perform final systems testing and commissioning. | C48: X
B50: General Conditions | C50: ANC | D50: Purchaser
B51: ANC has provided a parts only warranty, excluding labor. | C51: Include Statement
B52: ANC has included installation pricing with prevailing labor rates. | D52: X
B53: ANC has not included bonding of any kind. | C53: Include Statement
B54: ANC has not included any tax in the proposal. | C54: Include Statement
B55: Shipping included in quoted pricing. | C55: Include Statement

Sheet P&L
A1: Amended RFP Exhibit I — P&L
A3: Project #: | D3: 50/20/20/10
B5: PROJECTS BUDGET | I5: CONTRACT BUDGET
B6: Revenue | C6: Budgeted Cost | D6: Margin | I6: Revenue | J6: Budgeted Cost
A7: Base Contract | B7: 2685228.3 | C7: 2338109.6 | D7: 347118.63 | H7: TOTAL BASE CONTRACT | I7: 2685228.3 | J7: 2338109.6
A8: TOTAL BASE CONTRACT | B8: 2685228.3 | C8: 2338109.6 | D8: 347118.63
A10: Change Orders
A11: Total Change Order(s) Amount | B11: 0 | C11: 0 | D11: 0
A13: Grand Total | B13: 2685228.3 | C13: 2338109.6 | D13: 347118.63
A16: Cost Category | B16: Revenue | C16: Budget | D16: Committed POs | E16: Budget Remaining
A17: LED | B17: 0 | C17: 1294392.2 | D17: 0 | E17: 1294392.2
A18: Install | B18: 0 | C18: 331428.76 | D18: 0 | E18: 331428.76
A19: Electrical | B19: 0 | C19: 267281.26 | D19: 0 | E19: 267281.26
A20: ANC Travel | B20: 0 | C20: 135000 | D20: 0 | E20: 135000
A21: Structural Engineering | B21: 0 | C21: 47058.8 | D21: 0 | E21: 47058.8
A22: Electrical Engineering | B22: 0 | C22: 0 | D22: 0 | E22: 0
A23: CMS | B23: 0 | C23: 0 | D23: 0 | E23: 0
A24: Parts/Labor | B24: 0 | C24: 0 | D24: 0 | E24: 0
A25: Tax | B25: 0 | C25: 0 | D25: 0 | E25: 0
A26: Bond | B26: 0 | C26: 0 | D26: 0 | E26: 0
A27: BASE CONTRACT TOTAL | C27: 2338109.6 | D27: 0 | E27: 2338109.6

Sheet Cash Flow
A1: Amended RFP Exhibit I — Cash Flow
D3: Payment Terms: 50/20/20/10
D4: Payment Phases | E4: Contract Signed | F4: Product Shipping | G4: Substantial Completion | H4: Sign Off
D5: Percentages | E5: 0.5 | F5: 0.2 | G5: 0.2 | H5: 0.1
B6: Contract Award Date | C6: TBD
B7: Scheduled Completion | C7: TBD
B9: Revenue | C9: Expenses | D9: Gross Profit | E9: Gross Profit % | F9: Budget Tracking (+/-)
B10: 2685228.3 | C10: 2338109.6 | D10: 347118.63 | E10: 0.12926969 | F10: 0
A12: Month | E12: Month 1 | F12: Month 2 | G12: Month 3 | H12: Month 4 | I12: Month 5 | J12: Month 6 | K12: Month 7 | L12: Month 8 | M12: Month 9 | N12: Month 10
A13: Revenue | C13: Amount | D13: Date Submitted
A14: 1 | C14: 0 | E14: 0 | F14: 0 | G14: 0 | H14: 0 | I14: 0 | J14: 0 | K14: 0 | L14: 0 | M14: 0 | N14: 0
A15: 2 | C15: 0 | E15: 0 | F15: 0 | G15: 0 | H15: 0 | I15: 0 | J15: 0 | K15: 0 | L15: 0 | M15: 0 | N15: 0
A16: 3 | C16: 0 | E16: 0 | F16: 0 | G16: 0 | H16: 0 | I16: 0 | J16: 0 | K16: 0 | L16: 0 | M16: 0 | N16: 0
A17: 4 | C17: 0 | E17: 0 | F17: 0 | G17: 0 | H17: 0 | I17: 0 | J17: 0 | K17: 0 | L17: 0 | M17: 0 | N17: 0
A18: 5 | C18: 0 | E18: 0 | F18: 0 | G18: 0 | H18: 0 | I18: 0 | J18: 0 | K18: 0 | L18: 0 | M18: 0 | N18: 0
A19: 6 | C19: 0 | E19: 0 | F19: 0 | G19: 0 | H19: 0 | I19: 0 | J19: 0 | K19: 0 | L19: 0 | M19: 0 | N19: 0
A20: 7 | C20: 0 | E20: 0 | F20: 0 | G20: 0 | H20: 0 | I20: 0 | J20: 0 | K20: 0 | L20: 0 | M20: 0 | N20: 0
A21: 8 | C21: 0 | E21: 0 | F21: 0 | G21: 0 | H21: 0 | I21: 0 | J21: 0 | K21: 0 | L21: 0 | M21: 0 | N21: 0
A22: 9 | C22: 0 | E22: 0 | F22: 0 | G22: 0 | H22: 0 | I22: 0 | J22: 0 | K22: 0 | L22: 0 | M22: 0 | N22: 0
A23: 10 | C23: 0 | E23: 0 | F23: 0 | G23: 0 | H23: 0 | I23: 0 | J23: 0 | K23: 0 | L23: 0 | M23: 0 | N23: 0
A24: Total Revenue | C24: 0

Sheet PO's
A1: Amended RFP Exhibit I — Purchase Orders
A3: PO Number | B3: Vendor | C3: Title / Description | D3: Original Contract Amount | E3: Category
D4: 0
D5: 0
D6: 0
D7: 0
D8: 0
D9: 0
D10: 0
D11: 0
D12: 0
D13: 0
D14: 0
D15: 0
... D33: 0
