Workbook

Sheet Project Overview
A1: WTC Digital Signage Upgrade — Project Overview
A2: Westfield | 2026-04-01 | ANC Proposal Engine
B4: PROJECT INFORMATION
B5: Client | C5: Westfield
B6: Project Name | C6: WTC Digital Signage Upgrade
B7: Location | C7: New York, NY
B8: Date Created | C8: 2026-04-01
B9: Currency | C9: USD
B10: Environment | C10: Indoor
B11: Union Labor | C11: No
B12: Bond Required | C12: No
B13: Number of Displays | C13: =SUM('LED Cost Sheet'!I4:I14) -> 22
B15: FINANCIAL PARAMETERS
B16: LED Hardware Margin | C16: 15%
B17: Install / Services Margin | C17: 15%
B18: Engineering Margin | C18: 15%
B19: Equipment Margin | C19: 15%
B20: CMS Margin | C20: 15%
B21: Bond Rate | C21: N/A
B22: Tax Rate | C22: Per zone (editable on MA)
B23: Tariff Rate | C23: Per zone (editable on MA)
B25: SUMMARY TOTALS
B26: Total Cost | C26: ='Margin Analysis'!C158 -> 3435750.1
B27: Total Selling Price | C27: ='Margin Analysis'!D158 -> 3967550.8
B28: Project Margin $ | C28: ='Margin Analysis'!E158 -> 531800.62
B29: Project Margin % | C29: ='Margin Analysis'!F158 -> 0.13
B30: DOCUMENT TOTAL | C30: ='Margin Analysis'!D158 -> 3967550.8

Sheet Margin Analysis
A1: WTC Digital Signage Upgrade — Margin Analysis
A2: Westfield | 2026-04-01 | ANC Proposal Engine
B4: Zone / Category | C4: Cost | D4: Selling Price | E4: Margin $ | F4: Margin %
B5: Underpass 3 — Underpass 1-4, WTC | D5: Selling Price
B6: LED Hardware | C6: ='LED Cost Sheet'!T4 -> 68046.11 | D6: ='LED Cost Sheet'!V4 -> 80054.25 | E6: =IFERROR(D6-C6,0) -> 12008.14 | F6: 0.15
B7: Structural Materials | C7: ='Underpass 3 - Install'!I26 -> 4102.5 | D7: =IFERROR(C7/(1-F7),0) -> 4826.47 | E7: =IFERROR(D7-C7,0) -> 723.97 | F7: 0.15
B8: Structural Labor & LED Installation | C8: ='Underpass 3 - Install'!I35-'Underpass 3 - Install'!I34 -> 17093.75 | D8: =IFERROR(C8/(1-F8),0) -> 20110.29 | E8: =IFERROR(D8-C8,0) -> 3016.54 | F8: 0.15
B9: Electrical & Data | C9: ='Underpass 3 - Install'!I44 -> 17093.75 | D9: =IFERROR(C9/(1-F9),0) -> 20110.29 | E9: =IFERROR(D9-C9,0) -> 3016.54 | F9: 0.15
B10: PM / General Conditions / Travel | C10: ='Underpass 3 - Install'!I34 -> 20882.35 | D10: =IFERROR(C10/(1-F10),0) -> 24567.47 | E10: =IFERROR(D10-C10,0) -> 3685.12 | F10: 0.15
B11: Engineering & Permits | C11: ='Underpass 3 - Install'!I52 -> 4705.88 | D11: =IFERROR(C11/(1-F11),0) -> 5536.33 | E11: =IFERROR(D11-C11,0) -> 830.45 | F11: 0.15
B12: SUBTOTAL | C12: =SUM(C6:C11) -> 131924.34 | D12: =SUM(D6:D11) -> 152572.17 | E12: =IFERROR(D12-C12,0) -> 20647.83 | F12: =IFERROR(1-C12/D12,0) -> 0.135332
B13: TAX | C13: 0 | D13: 0 | E13: 0 | G13: 0
B14: BOND | C14: 0 | D14: 0 | E14: 0 | G14: 0
B15: TARIFF | C15: 0 | D15: 0 | E15: 0 | G15: 0
B16: GRAND TOTAL | C16: =C12+C13+C14+C15 -> 131924.34 | D16: =D12+D13+D14+D15 -> 152572.17 | E16: =IFERROR(D16-C16,0) -> 20647.83 | F16: =IFERROR(1-C16/D16,0) -> 0.13533156
B18: Underpass 4 — Underpass 1-4, WTC | D18: Selling Price
B19: LED Hardware | C19: ='LED Cost Sheet'!T5 -> 134265.3 | D19: ='LED Cost Sheet'!V5 -> 157959.18 | E19: =IFERROR(D19-C19,0) -> 23693.88 | F19: 0.15
B20: Structural Materials | C20: ='Underpass 4 - Install'!I26 -> 6907.5 | D20: =IFERROR(C20/(1-F20),0) -> 8126.47 | E20: =IFERROR(D20-C20,0) -> 1218.97 | F20: 0.15
B21: Structural Labor & LED Installation | C21: ='Underpass 4 - Install'!I35-'Underpass 4 - Install'!I34 -> 28781.25 | D21: =IFERROR(C21/(1-F21),0) -> 33860.29 | E21: =IFERROR(D21-C21,0) -> 5079.04 | F21: 0.15
B22: Electrical & Data | C22: ='Underpass 4 - Install'!I44 -> 28781.25 | D22: =IFERROR(C22/(1-F22),0) -> 33860.29 | E22: =IFERROR(D22-C22,0) -> 5079.04 | F22: 0.15
B23: PM / General Conditions / Travel | C23: ='Underpass 4 - Install'!I34 -> 20882.35 | D23: =IFERROR(C23/(1-F23),0) -> 24567.47 | E23: =IFERROR(D23-C23,0) -> 3685.12 | F23: 0.15
B24: Engineering & Permits | C24: ='Underpass 4 - Install'!I52 -> 4705.88 | D24: =IFERROR(C24/(1-F24),0) -> 5536.33 | E24: =IFERROR(D24-C24,0) -> 830.45 | F24: 0.15
B25: SUBTOTAL | C25: =SUM(C19:C24) -> 224323.53 | D25: =SUM(D19:D24) -> 259474.86 | E25: =IFERROR(D25-C25,0) -> 35151.33 | F25: =IFERROR(1-C25/D25,0) -> 0.135471
B26: TAX | C26: 0 | D26: 0 | E26: 0 | G26: 0
B27: BOND | C27: 0 | D27: 0 | E27: 0 | G27: 0
B28: TARIFF | C28: 0 | D28: 0 | E28: 0 | G28: 0
B29: GRAND TOTAL | C29: =C25+C26+C27+C28 -> 224323.53 | D29: =D25+D26+D27+D28 -> 259474.86 | E29: =IFERROR(D29-C29,0) -> 35151.33 | F29: =IFERROR(1-C29/D29,0) -> 0.13547104
B31: Concourse — Concourse, WTC | D31: Selling Price
B32: LED Hardware | C32: ='LED Cost Sheet'!T6 -> 845677.52 | D32: ='LED Cost Sheet'!V6 -> 994914.73 | E32: =IFERROR(D32-C32,0) -> 149237.21 | F32: 0.15
B33: Structural Materials | C33: ='Concourse - Install'!I26 -> 48536.25 | D33: =IFERROR(C33/(1-F33),0) -> 57101.47 | E33: =IFERROR(D33-C33,0) -> 8565.22 | F33: 0.15
B34: Structural Labor & LED Installation | C34: ='Concourse - Install'!I35-'Concourse - Install'!I34 -> 202234.38 | D34: =IFERROR(C34/(1-F34),0) -> 237922.8 | E34: =IFERROR(D34-C34,0) -> 35688.42 | F34: 0.15
B35: Electrical & Data | C35: ='Concourse - Install'!I44 -> 202234.38 | D35: =IFERROR(C35/(1-F35),0) -> 237922.8 | E35: =IFERROR(D35-C35,0) -> 35688.42 | F35: 0.15
B36: PM / General Conditions / Travel | C36: ='Concourse - Install'!I34 -> 20882.35 | D36: =IFERROR(C36/(1-F36),0) -> 24567.47 | E36: =IFERROR(D36-C36,0) -> 3685.12 | F36: 0.15
B37: Engineering & Permits | C37: ='Concourse - Install'!I52 -> 4705.88 | D37: =IFERROR(C37/(1-F37),0) -> 5536.33 | E37: =IFERROR(D37-C37,0) -> 830.45 | F37: 0.15
B38: SUBTOTAL | C38: =SUM(C32:C37) -> 1324270.8 | D38: =SUM(D32:D37) -> 1526801.7 | E38: =IFERROR(D38-C38,0) -> 202530.95 | F38: =IFERROR(1-C38/D38,0) -> 0.13265
B39: TAX | C39: 0 | D39: 0 | E39: 0 | G39: 0
B40: BOND | C40: 0 | D40: 0 | E40: 0 | G40: 0
B41: TARIFF | C41: 0 | D41: 0 | E41: 0 | G41: 0
B42: GRAND TOTAL | C42: =C38+C39+C40+C41 -> 1324270.8 | D42: =D38+D39+D40+D41 -> 1526801.7 | E42: =IFERROR(D42-C42,0) -> 202530.95 | F42: =IFERROR(1-C42/D42,0) -> 0.13265046
B44: T4-B1 (6-9) — T4-B1, WTC | D44: Selling Price
B45: LED Hardware | C45: ='LED Cost Sheet'!T7 -> 82785.77 | D45: ='LED Cost Sheet'!V7 -> 97395.02 | E45: =IFERROR(D45-C45,0) -> 14609.25 | F45: 0.15
B46: Structural Materials | C46: ='T4-B1 (6-9) - Install'!I26 -> 4995 | D46: =IFERROR(C46/(1-F46),0) -> 5876.47 | E46: =IFERROR(D46-C46,0) -> 881.47 | F46: 0.15
B47: Structural Labor & LED Installation | C47: ='T4-B1 (6-9) - Install'!I35-'T4-B1 (6-9) - Install'!I34 -> 20812.5 | D47: =IFERROR(C47/(1-F47),0) -> 24485.29 | E47: =IFERROR(D47-C47,0) -> 3672.79 | F47: 0.15
B48: Electrical & Data | C48: ='T4-B1 (6-9) - Install'!I44 -> 20812.5 | D48: =IFERROR(C48/(1-F48),0) -> 24485.29 | E48: =IFERROR(D48-C48,0) -> 3672.79 | F48: 0.15
B49: PM / General Conditions / Travel | C49: ='T4-B1 (6-9) - Install'!I34 -> 20882.35 | D49: =IFERROR(C49/(1-F49),0) -> 24567.47 | E49: =IFERROR(D49-C49,0) -> 3685.12 | F49: 0.15
B50: Engineering & Permits | C50: ='T4-B1 (6-9) - Install'!I52 -> 4705.88 | D50: =IFERROR(C50/(1-F50),0) -> 5536.33 | E50: =IFERROR(D50-C50,0) -> 830.45 | F50: 0.15
B51: SUBTOTAL | C51: =SUM(C45:C50) -> 154994 | D51: =SUM(D45:D50) -> 179138.59 | E51: =IFERROR(D51-C51,0) -> 24144.59 | F51: =IFERROR(1-C51/D51,0) -> 0.134782
B52: TAX | C52: 0 | D52: 0 | E52: 0 | G52: 0
B53: BOND | C53: 0 | D53: 0 | E53: 0 | G53: 0
B54: TARIFF | C54: 0 | D54: 0 | E54: 0 | G54: 0
B55: GRAND TOTAL | C55: =C51+C52+C53+C54 -> 154994 | D55: =D51+D52+D53+D54 -> 179138.59 | E55: =IFERROR(D55-C55,0) -> 24144.59 | F55: =IFERROR(1-C55/D55,0) -> 0.13478162
B57: T4-B2 (10-18) — T4-B2, WTC | D57: Selling Price
B58: LED Hardware | C58: ='LED Cost Sheet'!T8 -> 205655.43 | D58: ='LED Cost Sheet'!V8 -> 241947.56 | E58: =IFERROR(D58-C58,0) -> 36292.13 | F58: 0.15
B59: Structural Materials | C59: ='T4-B2 (10-18) - Install'!I26 -> 11238.75 | D59: =IFERROR(C59/(1-F59),0) -> 13222.06 | E59: =IFERROR(D59-C59,0) -> 1983.31 | F59: 0.15
B60: Structural Labor & LED Installation | C60: ='T4-B2 (10-18) - Install'!I35-'T4-B2 (10-18) - Install'!I34 -> 46828.13 | D60: =IFERROR(C60/(1-F60),0) -> 55091.92 | E60: =IFERROR(D60-C60,0) -> 8263.79 | F60: 0.15
B61: Electrical & Data | C61: ='T4-B2 (10-18) - Install'!I44 -> 46828.13 | D61: =IFERROR(C61/(1-F61),0) -> 55091.92 | E61: =IFERROR(D61-C61,0) -> 8263.79 | F61: 0.15
B62: PM / General Conditions / Travel | C62: ='T4-B2 (10-18) - Install'!I34 -> 20882.35 | D62: =IFERROR(C62/(1-F62),0) -> 24567.47 | E62: =IFERROR(D62-C62,0) -> 3685.12 | F62: 0.15
B63: Engineering & Permits | C63: ='T4-B2 (10-18) - Install'!I52 -> 4705.88 | D63: =IFERROR(C63/(1-F63),0) -> 5536.33 | E63: =IFERROR(D63-C63,0) -> 830.45 | F63: 0.15
B64: SUBTOTAL | C64: =SUM(C58:C63) -> 336138.67 | D64: =SUM(D58:D63) -> 388240.91 | E64: =IFERROR(D64-C64,0) -> 52102.24 | F64: =IFERROR(1-C64/D64,0) -> 0.134201
B65: TAX | C65: 0 | D65: 0 | E65: 0 | G65: 0
B66: BOND | C66: 0 | D66: 0 | E66: 0 | G66: 0
B67: TARIFF | C67: 0 | D67: 0 | E67: 0 | G67: 0
B68: GRAND TOTAL | C68: =C64+C65+C66+C67 -> 336138.67 | D68: =D64+D65+D66+D67 -> 388240.91 | E68: =IFERROR(D68-C68,0) -> 52102.24 | F68: =IFERROR(1-C68/D68,0) -> 0.1342008
B70: T4 Lobby Elevator — T4 Lobby Elevator, WTC | D70: Selling Price
B71: LED Hardware | C71: ='LED Cost Sheet'!T9 -> 139342.57 | D71: ='LED Cost Sheet'!V9 -> 163932.44 | E71: =IFERROR(D71-C71,0) -> 24589.87 | F71: 0.15
B72: Structural Materials | C72: ='T4 Lobby Elevator - Install'!I26 -> 7222.5 | D72: =IFERROR(C72/(1-F72),0) -> 8497.06 | E72: =IFERROR(D72-C72,0) -> 1274.56 | F72: 0.15
B73: Structural Labor & LED Installation | C73: ='T4 Lobby Elevator - Install'!I35-'T4 Lobby Elevator - Install'!I34 -> 30093.75 | D73: =IFERROR(C73/(1-F73),0) -> 35404.41 | E73: =IFERROR(D73-C73,0) -> 5310.66 | F73: 0.15
B74: Electrical & Data | C74: ='T4 Lobby Elevator - Install'!I44 -> 30093.75 | D74: =IFERROR(C74/(1-F74),0) -> 35404.41 | E74: =IFERROR(D74-C74,0) -> 5310.66 | F74: 0.15
B75: PM / General Conditions / Travel | C75: ='T4 Lobby Elevator - Install'!I34 -> 20882.35 | D75: =IFERROR(C75/(1-F75),0) -> 24567.47 | E75: =IFERROR(D75-C75,0) -> 3685.12 | F75: 0.15
B76: Engineering & Permits | C76: ='T4 Lobby Elevator - Install'!I52 -> 4705.88 | D76: =IFERROR(C76/(1-F76),0) -> 5536.33 | E76: =IFERROR(D76-C76,0) -> 830.45 | F76: 0.15
B77: SUBTOTAL | C77: =SUM(C71:C76) -> 232340.8 | D77: =SUM(D71:D76) -> 268709.18 | E77: =IFERROR(D77-C77,0) -> 36368.38 | F77: =IFERROR(1-C77/D77,0) -> 0.135345
B78: TAX | C78: 0 | D78: 0 | E78: 0 | G78: 0
B79: BOND | C79: 0 | D79: 0 | E79: 0 | G79: 0
B80: TARIFF | C80: 0 | D80: 0 | E80: 0 | G80: 0
B81: GRAND TOTAL | C81: =C77+C78+C79+C80 -> 232340.8 | D81: =D77+D78+D79+D80 -> 268709.18 | E81: =IFERROR(D81-C81,0) -> 36368.38 | F81: =IFERROR(1-C81/D81,0) -> 0.13534476
B83: T2-B1M Screen 20 — T2-B1M, WTC | D83: Selling Price
B84: LED Hardware | C84: ='LED Cost Sheet'!T10 -> 39872 | D84: ='LED Cost Sheet'!V10 -> 46908.24 | E84: =IFERROR(D84-C84,0) -> 7036.24 | F84: 0.15
B85: Structural Materials | C85: ='T2-B1M Screen 20 - Install'!I26 -> 2392.5 | D85: =IFERROR(C85/(1-F85),0) -> 2814.71 | E85: =IFERROR(D85-C85,0) -> 422.21 | F85: 0.15
B86: Structural Labor & LED Installation | C86: ='T2-B1M Screen 20 - Install'!I35-'T2-B1M Screen 20 - Install'!I34 -> 9968.75 | D86: =IFERROR(C86/(1-F86),0) -> 11727.94 | E86: =IFERROR(D86-C86,0) -> 1759.19 | F86: 0.15
B87: Electrical & Data | C87: ='T2-B1M Screen 20 - Install'!I44 -> 9968.75 | D87: =IFERROR(C87/(1-F87),0) -> 11727.94 | E87: =IFERROR(D87-C87,0) -> 1759.19 | F87: 0.15
B88: PM / General Conditions / Travel | C88: ='T2-B1M Screen 20 - Install'!I34 -> 20882.35 | D88: =IFERROR(C88/(1-F88),0) -> 24567.47 | E88: =IFERROR(D88-C88,0) -> 3685.12 | F88: 0.15
B89: Engineering & Permits | C89: ='T2-B1M Screen 20 - Install'!I52 -> 4705.88 | D89: =IFERROR(C89/(1-F89),0) -> 5536.33 | E89: =IFERROR(D89-C89,0) -> 830.45 | F89: 0.15
B90: SUBTOTAL | C90: =SUM(C84:C89) -> 87790.23 | D90: =SUM(D84:D89) -> 101747.09 | E90: =IFERROR(D90-C90,0) -> 13956.86 | F90: =IFERROR(1-C90/D90,0) -> 0.137172
B91: TAX | C91: 0 | D91: 0 | E91: 0 | G91: 0
B92: BOND | C92: 0 | D92: 0 | E92: 0 | G92: 0
B93: TARIFF | C93: 0 | D93: 0 | E93: 0 | G93: 0
B94: GRAND TOTAL | C94: =C90+C91+C92+C93 -> 87790.23 | D94: =D90+D91+D92+D93 -> 101747.09 | E94: =IFERROR(D94-C94,0) -> 13956.86 | F94: =IFERROR(1-C94/D94,0) -> 0.13717208
B96: T2-B1M Screen 21 — T2-B1M, WTC | D96: Selling Price
B97: LED Hardware | C97: ='LED Cost Sheet'!T11 -> 28714.71 | D97: ='LED Cost Sheet'!V11 -> 33782.01 | E97: =IFERROR(D97-C97,0) -> 5067.3 | F97: 0.15
B98: Structural Materials | C98: ='T2-B1M Screen 21 - Install'!I26 -> 1713.75 | D98: =IFERROR(C98/(1-F98),0) -> 2016.18 | E98: =IFERROR(D98-C98,0) -> 302.43 | F98: 0.15
B99: Structural Labor & LED Installation | C99: ='T2-B1M Screen 21 - Install'!I35-'T2-B1M Screen 21 - Install'!I34 -> 7140.63 | D99: =IFERROR(C99/(1-F99),0) -> 8400.74 | E99: =IFERROR(D99-C99,0) -> 1260.11 | F99: 0.15
B100: Electrical & Data | C100: ='T2-B1M Screen 21 - Install'!I44 -> 7140.63 | D100: =IFERROR(C100/(1-F100),0) -> 8400.74 | E100: =IFERROR(D100-C100,0) -> 1260.11 | F100: 0.15
B101: PM / General Conditions / Travel | C101: ='T2-B1M Screen 21 - Install'!I34 -> 20882.35 | D101: =IFERROR(C101/(1-F101),0) -> 24567.47 | E101: =IFERROR(D101-C101,0) -> 3685.12 | F101: 0.15
B102: Engineering & Permits | C102: ='T2-B1M Screen 21 - Install'!I52 -> 4705.88 | D102: =IFERROR(C102/(1-F102),0) -> 5536.33 | E102: =IFERROR(D102-C102,0) -> 830.45 | F102: 0.15
B103: SUBTOTAL | C103: =SUM(C97:C102) -> 70297.95 | D103: =SUM(D97:D102) -> 81602.53 | E103: =IFERROR(D103-C103,0) -> 11304.58 | F103: =IFERROR(1-C103/D103,0) -> 0.138532
B104: TAX | C104: 0 | D104: 0 | E104: 0 | G104: 0
B105: BOND | C105: 0 | D105: 0 | E105: 0 | G105: 0
B106: TARIFF | C106: 0 | D106: 0 | E106: 0 | G106: 0
B107: GRAND TOTAL | C107: =C103+C104+C105+C106 -> 70297.95 | D107: =D103+D104+D105+D106 -> 81602.53 | E107: =IFERROR(D107-C107,0) -> 11304.58 | F107: =IFERROR(1-C107/D107,0) -> 0.13853222
B109: T2-B1M Screen 22 — T2-B1M, WTC | D109: Selling Price
...

Sheet Budget Summary
A1: WTC Digital Signage Upgrade — Budget Summary
A2: Westfield | 2026-04-01 | By Category
B4: Category | C4: Cost | D4: Selling Price | E4: Margin $ | F4: Margin % | G4: Price / SqFt
B5: LED Hardware (all displays) | C5: =SUM('LED Cost Sheet'!Q4:Q14) -> 2071099.6 | D5: =SUM('LED Cost Sheet'!S4:S14) -> 2436587.7 | E5: =IFERROR(D5-C5,0) -> 365488.16 | F5: 0.15 | G5: =IFERROR(C5/6333.2,0) -> 327.02
B6: Structural Materials | C6: =SUM('Underpass 3 - Install'!I26:I26)+SUM('Underpass 4 - Install'!I26:I26)+SUM('Concourse - Install'!I26:I26)+SUM('T4-B1 (6-9) - Install'!I26:I26)+SUM('T4-B2 (10-18) - Install'!I26:I26)+SUM('T4 Lobby Elevator - Install'!I26:I26)+SUM('T2-B1M Screen 20 - Install'!I26:I26)+SUM('T2-B1M Screen 21 - Install'!I26:I26)+SUM('T2-B1M Screen 22 - Install'!I26:I26)+SUM('New Path Hall Option 1 - Instal'!I26:I26)+SUM('New Path Hall Option 2 - Instal'!I26:I26) -> 116055 | D6: =SUM('Underpass 3 - Install'!K26:K26)+SUM('Underpass 4 - Install'!K26:K26)+SUM('Concourse - Install'!K26:K26)+SUM('T4-B1 (6-9) - Install'!K26:K26)+SUM('T4-B2 (10-18) - Install'!K26:K26)+SUM('T4 Lobby Elevator - Install'!K26:K26)+SUM('T2-B1M Screen 20 - Install'!K26:K26)+SUM('T2-B1M Screen 21 - Install'!K26:K26)+SUM('T2-B1M Screen 22 - Install'!K26:K26)+SUM('New Path Hall Option 1 - Instal'!K26:K26)+SUM('New Path Hall Option 2 - Instal'!K26:K26) -> 136535.29 | E6: =IFERROR(D6-C6,0) -> 20480.29 | F6: 0.15 | G6: =IFERROR(C6/6333.2,0) -> 18.32
B7: Structural Labor & LED Installation | C7: =(SUM('Underpass 3 - Install'!I35:I35)-SUM('Underpass 3 - Install'!I34:I34))+(SUM('Underpass 4 - Install'!I35:I35)-SUM('Underpass 4 - Install'!I34:I34))+(SUM('Concourse - Install'!I35:I35)-SUM('Concourse - Install'!I34:I34))+(SUM('T4-B1 (6-9) - Install'!I35:I35)-SUM('T4-B1 (6-9) - Install'!I34:I34))+(SUM('T4-B2 (10-18) - Install'!I35:I35)-SUM('T4-B2 (10-18) - Install'!I34:I34))+(SUM('T4 Lobby Elevator - Install'!I35:I35)-SUM('T4 Lobby Elevator - Install'!I34:I34))+(SUM('T2-B1M Screen 20 - Install'!I35:I35)-SUM('T2-B1M Screen 20 - Install'!I34:I34))+(SUM('T2-B1M Screen 21 - Install'!I35:I35)-SUM('T2-B1M Screen 21 - Install'!I34:I34))+(SUM('T2-B1M Screen 22 - Install'!I35:I35)-SUM('T2-B1M Screen 22 - Install'!I34:I34))+(SUM('New Path Hall Option 1 - Instal'!I35:I35)-SUM('New Path Hall Option 1 - Instal'!I34:I34))+(SUM('New Path Hall Option 2 - Instal'!I35:I35)-SUM('New Path Hall Option 2 - Instal'!I34:I34)) -> 483562.52 | D7: =(SUM('Underpass 3 - Install'!K35:K35)-SUM('Underpass 3 - Install'!K34:K34))+(SUM('Underpass 4 - Install'!K35:K35)-SUM('Underpass 4 - Install'!K34:K34))+(SUM('Concourse - Install'!K35:K35)-SUM('Concourse - Install'!K34:K34))+(SUM('T4-B1 (6-9) - Install'!K35:K35)-SUM('T4-B1 (6-9) - Install'!K34:K34))+(SUM('T4-B2 (10-18) - Install'!K35:K35)-SUM('T4-B2 (10-18) - Install'!K34:K34))+(SUM('T4 Lobby Elevator - Install'!K35:K35)-SUM('T4 Lobby Elevator - Install'!K34:K34))+(SUM('T2-B1M Screen 20 - Install'!K35:K35)-SUM('T2-B1M Screen 20 - Install'!K34:K34))+(SUM('T2-B1M Screen 21 - Install'!K35:K35)-SUM('T2-B1M Screen 21 - Install'!K34:K34))+(SUM('T2-B1M Screen 22 - Install'!K35:K35)-SUM('T2-B1M Screen 22 - Install'!K34:K34))+(SUM('New Path Hall Option 1 - Instal'!K35:K35)-SUM('New Path Hall Option 1 - Instal'!K34:K34))+(SUM('New Path Hall Option 2 - Instal'!K35:K35)-SUM('New Path Hall Option 2 - Instal'!K34:K34)) -> 568897.08 | E7: =IFERROR(D7-C7,0) -> 85334.56 | F7: 0.15 | G7: =IFERROR(C7/6333.2,0) -> 76.35
B8: Electrical & Data | C8: =SUM('Underpass 3 - Install'!I44:I44)+SUM('Underpass 4 - Install'!I44:I44)+SUM('Concourse - Install'!I44:I44)+SUM('T4-B1 (6-9) - Install'!I44:I44)+SUM('T4-B2 (10-18) - Install'!I44:I44)+SUM('T4 Lobby Elevator - Install'!I44:I44)+SUM('T2-B1M Screen 20 - Install'!I44:I44)+SUM('T2-B1M Screen 21 - Install'!I44:I44)+SUM('T2-B1M Screen 22 - Install'!I44:I44)+SUM('New Path Hall Option 1 - Instal'!I44:I44)+SUM('New Path Hall Option 2 - Instal'!I44:I44) -> 483562.52 | D8: =SUM('Underpass 3 - Install'!K44:K44)+SUM('Underpass 4 - Install'!K44:K44)+SUM('Concourse - Install'!K44:K44)+SUM('T4-B1 (6-9) - Install'!K44:K44)+SUM('T4-B2 (10-18) - Install'!K44:K44)+SUM('T4 Lobby Elevator - Install'!K44:K44)+SUM('T2-B1M Screen 20 - Install'!K44:K44)+SUM('T2-B1M Screen 21 - Install'!K44:K44)+SUM('T2-B1M Screen 22 - Install'!K44:K44)+SUM('New Path Hall Option 1 - Instal'!K44:K44)+SUM('New Path Hall Option 2 - Instal'!K44:K44) -> 568897.08 | E8: =IFERROR(D8-C8,0) -> 85334.56 | F8: 0.15 | G8: =IFERROR(C8/6333.2,0) -> 76.35
B9: PM / General Conditions / Travel | C9: =SUM('Underpass 3 - Install'!I34:I34)+SUM('Underpass 4 - Install'!I34:I34)+SUM('Concourse - Install'!I34:I34)+SUM('T4-B1 (6-9) - Install'!I34:I34)+SUM('T4-B2 (10-18) - Install'!I34:I34)+SUM('T4 Lobby Elevator - Install'!I34:I34)+SUM('T2-B1M Screen 20 - Install'!I34:I34)+SUM('T2-B1M Screen 21 - Install'!I34:I34)+SUM('T2-B1M Screen 22 - Install'!I34:I34)+SUM('New Path Hall Option 1 - Instal'!I34:I34)+SUM('New Path Hall Option 2 - Instal'!I34:I34) -> 229705.85 | D9: =SUM('Underpass 3 - Install'!K34:K34)+SUM('Underpass 4 - Install'!K34:K34)+SUM('Concourse - Install'!K34:K34)+SUM('T4-B1 (6-9) - Install'!K34:K34)+SUM('T4-B2 (10-18) - Install'!K34:K34)+SUM('T4 Lobby Elevator - Install'!K34:K34)+SUM('T2-B1M Screen 20 - Install'!K34:K34)+SUM('T2-B1M Screen 21 - Install'!K34:K34)+SUM('T2-B1M Screen 22 - Install'!K34:K34)+SUM('New Path Hall Option 1 - Instal'!K34:K34)+SUM('New Path Hall Option 2 - Instal'!K34:K34) -> 270242.18 | E9: =IFERROR(D9-C9,0) -> 40536.33 | F9: 0.15
B10: Engineering & Permits | C10: =SUM('Underpass 3 - Install'!I52:I52)+SUM('Underpass 4 - Install'!I52:I52)+SUM('Concourse - Install'!I52:I52)+SUM('T4-B1 (6-9) - Install'!I52:I52)+SUM('T4-B2 (10-18) - Install'!I52:I52)+SUM('T4 Lobby Elevator - Install'!I52:I52)+SUM('T2-B1M Screen 20 - Install'!I52:I52)+SUM('T2-B1M Screen 21 - Install'!I52:I52)+SUM('T2-B1M Screen 22 - Install'!I52:I52)+SUM('New Path Hall Option 1 - Instal'!I52:I52)+SUM('New Path Hall Option 2 - Instal'!I52:I52) -> 51764.68 | D10: =SUM('Underpass 3 - Install'!K52:K52)+SUM('Underpass 4 - Install'!K52:K52)+SUM('Concourse - Install'!K52:K52)+SUM('T4-B1 (6-9) - Install'!K52:K52)+SUM('T4-B2 (10-18) - Install'!K52:K52)+SUM('T4 Lobby Elevator - Install'!K52:K52)+SUM('T2-B1M Screen 20 - Install'!K52:K52)+SUM('T2-B1M Screen 21 - Install'!K52:K52)+SUM('T2-B1M Screen 22 - Install'!K52:K52)+SUM('New Path Hall Option 1 - Instal'!K52:K52)+SUM('New Path Hall Option 2 - Instal'!K52:K52) -> 60899.62 | E10: =IFERROR(D10-C10,0) -> 9134.94 | F10: 0.15
B11: CMS (Content Management System) | C11: =SUM(CMS!F26:F26) -> 0 | D11: =SUM(CMS!H26:H26) -> 0 | E11: =IFERROR(D11-C11,0) -> 0 | F11: 0.15
B12: Scoring System | C12: =SUM(Scoring!F27:F27) -> 0 | D12: =SUM(Scoring!H27:H27) -> 0 | E12: =IFERROR(D12-C12,0) -> 0 | F12: 0.15
B13: Venue Services | C13: =SUM('Venue Services'!B17:B17) -> 0 | D13: =SUM('Venue Services'!C17:C17) -> 0 | E13: =IFERROR(D13-C13,0) -> 0 | F13: 0.15
B14: Game Clock | C14: =SUM('Additional Items'!F5:F5) -> 0 | D14: =SUM('Additional Items'!H5:H5) -> 0 | E14: =IFERROR(D14-C14,0) -> 0 | F14: 0.15
B15: Pitch Clocks | C15: =SUM('Additional Items'!F6:F6) -> 0 | D15: =SUM('Additional Items'!H6:H6) -> 0 | E15: =IFERROR(D15-C15,0) -> 0 | F15: 0.15
B16: OES / MIS / Timing | C16: =SUM('Additional Items'!F7:F7) -> 0 | D16: =SUM('Additional Items'!H7:H7) -> 0 | E16: =IFERROR(D16-C16,0) -> 0 | F16: 0.15
B17: DMX / Misc Equipment | C17: =SUM('Additional Items'!F8:F8) -> 0 | D17: =SUM('Additional Items'!H8:H8) -> 0 | E17: =IFERROR(D17-C17,0) -> 0 | F17: 0.15
B19: SUBTOTAL | C19: =SUM(C5:C17) -> 3435750.1 | D19: =SUM(D5:D17) -> 3967550.8 | E19: =IFERROR(D19-C19,0) -> 531800.62 | F19: =IFERROR(1-C19/D19,0) -> 0.13 | G19: =IFERROR(C19/6333.2,0) -> 542.5
B20: TAX | C20: 0 | D20: 0 | E20: 0 | F20: 0
B21: BOND | C21: 0 | D21: 0 | E21: 0 | F21: 0
B22: GRAND TOTAL | C22: =C19+C20+C21 -> 3435750.1 | D22: =D19+D20+D21 -> 3967550.8 | E22: =IFERROR(D22-C22,0) -> 531800.62 | F22: =IFERROR(1-C22/D22,0) -> 0.13 | G22: =IFERROR(C22/6333.2,0) -> 542.5

Sheet LED Cost Sheet
A1: WTC Digital Signage Upgrade — LED Cost Sheet
U2: LED Margin Override → | V2: 0.15
A3: Display | B3: RFP H (ft) | C3: RFP W (ft) | D3: RFP NITs | E3: Vendor | F3: Product | G3: Pitch | H3: H (ft) | I3: W (ft) | J3: H (px) | K3: W (px) | L3: Qty | M3: Total SqFt | N3: Product NITs | O3: Service | P3: $/SqFt | Q3: Display Cost | R3: Processor | S3: Shipping | T3: Total Cost | U3: Margin % | V3: Selling Price | W3: ANC Margin | X3: Weight (lbs) | Y3: Total Power (W) | Z3: BTU/hr
A4: Underpass 3 — Underpass 1-4, WTC | B4: 7.48 | C4: 29.92 | E4: =IFERROR(VLOOKUP(F4,'_Products'!$A$1:$G$23,2,FALSE),"") -> LG/Yaham | F4: C2.5-MIP 2.5mm Indoor (Alt) | G4: =IFERROR(VLOOKUP(F4,'_Products'!$A$1:$G$23,3,FALSE),0) -> 2.5 | H4: 7.48 | I4: 29.92 | J4: =IFERROR(ROUND(H4*304.8/G4,0),0) -> 912 | K4: =IFERROR(ROUND(I4*304.8/G4,0),0) -> 3648 | L4: 1 | M4: =H4*I4*L4 -> 223.8 | N4: =IFERROR(VLOOKUP(F4,'_Products'!$A$1:$G$23,5,FALSE),0) -> 2000 | O4: front | P4: =IFERROR(VLOOKUP(F4,'_Products'!$A$1:$G$23,4,FALSE),0) -> 291.44 | Q4: =P4*M4 -> 65223.83 | R4: =SUM('Bundle Equipment'!E10:E10) -> 584.28 | S4: =MAX(M4*10,500) -> 2238 | T4: =Q4+R4+S4 -> 68046.11 | U4: =V$2 -> 0.15 | V4: =IFERROR(T4/(1-U4),0) -> 80054.25 | W4: =V4-T4 -> 12008.14 | X4: =IFERROR(ROUND(M4*0.092903*VLOOKUP(F4,'_Products'!$A$1:$G$23,6,FALSE),0),0) -> 1094 | Y4: =IFERROR(ROUND(M4*0.092903*VLOOKUP(F4,'_Products'!$A$1:$G$23,7,FALSE),0),0) -> 8121 | Z4: =Y4*3.412 -> 27709
A5: Underpass 4 — Underpass 1-4, WTC | B5: 12.6 | C5: 29.92 | E5: =IFERROR(VLOOKUP(F5,'_Products'!$A$1:$G$23,2,FALSE),"") -> LG/Yaham | F5: C2.5-MIP 2.5mm Indoor (Alt) | G5: =IFERROR(VLOOKUP(F5,'_Products'!$A$1:$G$23,3,FALSE),0) -> 2.5 | H5: 12.6 | I5: 29.92 | J5: =IFERROR(ROUND(H5*304.8/G5,0),0) -> 1536 | K5: =IFERROR(ROUND(I5*304.8/G5,0),0) -> 3648 | L5: 1 | M5: =H5*I5*L5 -> 376.99 | N5: =IFERROR(VLOOKUP(F5,'_Products'!$A$1:$G$23,5,FALSE),0) -> 2000 | O5: front | P5: =IFERROR(VLOOKUP(F5,'_Products'!$A$1:$G$23,4,FALSE),0) -> 291.44 | Q5: =P5*M5 -> 109869.21 | R5: =SUM('Bundle Equipment'!E16:E16) -> 20626.19 | S5: =MAX(M5*10,500) -> 3769.9 | T5: =Q5+R5+S5 -> 134265.3 | U5: =V$2 -> 0.15 | V5: =IFERROR(T5/(1-U5),0) -> 157959.18 | W5: =V5-T5 -> 23693.88 | X5: =IFERROR(ROUND(M5*0.092903*VLOOKUP(F5,'_Products'!$A$1:$G$23,6,FALSE),0),0) -> 1842 | Y5: =IFERROR(ROUND(M5*0.092903*VLOOKUP(F5,'_Products'!$A$1:$G$23,7,FALSE),0),0) -> 13680 | Z5: =Y5*3.412 -> 46676
A6: Concourse — Concourse, WTC | B6: 9.45 | C6: 280.31 | E6: =IFERROR(VLOOKUP(F6,'_Products'!$A$1:$G$23,2,FALSE),"") -> LG/Yaham | F6: C2.5-MIP 2.5mm Indoor (Alt) | G6: =IFERROR(VLOOKUP(F6,'_Products'!$A$1:$G$23,3,FALSE),0) -> 2.5 | H6: 9.45 | I6: 280.31 | J6: =IFERROR(ROUND(H6*304.8/G6,0),0) -> 1152 | K6: =IFERROR(ROUND(I6*304.8/G6,0),0) -> 34175 | L6: 1 | M6: =H6*I6*L6 -> 2648.93 | N6: =IFERROR(VLOOKUP(F6,'_Products'!$A$1:$G$23,5,FALSE),0) -> 2000 | O6: front | P6: =IFERROR(VLOOKUP(F6,'_Products'!$A$1:$G$23,4,FALSE),0) -> 291.44 | Q6: =P6*M6 -> 771998.86 | R6: =SUM('Bundle Equipment'!E22:E22) -> 47189.36 | S6: =MAX(M6*10,500) -> 26489.3 | T6: =Q6+R6+S6 -> 845677.52 | U6: =V$2 -> 0.15 | V6: =IFERROR(T6/(1-U6),0) -> 994914.73 | W6: =V6-T6 -> 149237.21 | X6: =IFERROR(ROUND(M6*0.092903*VLOOKUP(F6,'_Products'!$A$1:$G$23,6,FALSE),0),0) -> 12945 | Y6: =IFERROR(ROUND(M6*0.092903*VLOOKUP(F6,'_Products'!$A$1:$G$23,7,FALSE),0),0) -> 96124 | Z6: =Y6*3.412 -> 327975
A7: T4-B1 (6-9) — T4-B1, WTC | B7: 7.87 | C7: 8.66 | E7: =IFERROR(VLOOKUP(F7,'_Products'!$A$1:$G$23,2,FALSE),"") -> LG/Yaham | F7: C2.5-MIP 2.5mm Indoor (Alt) | G7: =IFERROR(VLOOKUP(F7,'_Products'!$A$1:$G$23,3,FALSE),0) -> 2.5 | H7: 7.87 | I7: 8.66 | J7: =IFERROR(ROUND(H7*304.8/G7,0),0) -> 960 | K7: =IFERROR(ROUND(I7*304.8/G7,0),0) -> 1056 | L7: 4 | M7: =H7*I7*L7 -> 272.62 | N7: =IFERROR(VLOOKUP(F7,'_Products'!$A$1:$G$23,5,FALSE),0) -> 2000 | O7: front | P7: =IFERROR(VLOOKUP(F7,'_Products'!$A$1:$G$23,4,FALSE),0) -> 291.42 | Q7: =P7*M7 -> 79446 | R7: =SUM('Bundle Equipment'!E27:E27) -> 613.57 | S7: =MAX(M7*10,500) -> 2726.2 | T7: =Q7+R7+S7 -> 82785.77 | U7: =V$2 -> 0.15 | V7: =IFERROR(T7/(1-U7),0) -> 97395.02 | W7: =V7-T7 -> 14609.25 | X7: =IFERROR(ROUND(M7*0.092903*VLOOKUP(F7,'_Products'!$A$1:$G$23,6,FALSE),0),0) -> 1332 | Y7: =IFERROR(ROUND(M7*0.092903*VLOOKUP(F7,'_Products'!$A$1:$G$23,7,FALSE),0),0) -> 9893 | Z7: =Y7*3.412 -> 33755
A8: T4-B2 (10-18) — T4-B2, WTC | B8: 7.87 | C8: 8.66 | E8: =IFERROR(VLOOKUP(F8,'_Products'!$A$1:$G$23,2,FALSE),"") -> LG/Yaham | F8: C2.5-MIP 2.5mm Indoor (Alt) | G8: =IFERROR(VLOOKUP(F8,'_Products'!$A$1:$G$23,3,FALSE),0) -> 2.5 | H8: 7.87 | I8: 8.66 | J8: =IFERROR(ROUND(H8*304.8/G8,0),0) -> 960 | K8: =IFERROR(ROUND(I8*304.8/G8,0),0) -> 1056 | L8: 9 | M8: =H8*I8*L8 -> 613.39 | N8: =IFERROR(VLOOKUP(F8,'_Products'!$A$1:$G$23,5,FALSE),0) -> 2000 | O8: front | P8: =IFERROR(VLOOKUP(F8,'_Products'!$A$1:$G$23,4,FALSE),0) -> 291.42 | Q8: =P8*M8 -> 178753.5 | R8: =SUM('Bundle Equipment'!E33:E33) -> 20768.03 | S8: =MAX(M8*10,500) -> 6133.9 | T8: =Q8+R8+S8 -> 205655.43 | U8: =V$2 -> 0.15 | V8: =IFERROR(T8/(1-U8),0) -> 241947.56 | W8: =V8-T8 -> 36292.13 | X8: =IFERROR(ROUND(M8*0.092903*VLOOKUP(F8,'_Products'!$A$1:$G$23,6,FALSE),0),0) -> 2997 | Y8: =IFERROR(ROUND(M8*0.092903*VLOOKUP(F8,'_Products'!$A$1:$G$23,7,FALSE),0),0) -> 22259 | Z8: =Y8*3.412 -> 75948
A9: T4 Lobby Elevator — T4 Lobby Elevator, WTC | B9: 71.6 | C9: 5.5 | E9: =IFERROR(VLOOKUP(F9,'_Products'!$A$1:$G$23,2,FALSE),"") -> LG/Yaham | F9: C2.5-MIP 2.5mm Indoor (Alt) | G9: =IFERROR(VLOOKUP(F9,'_Products'!$A$1:$G$23,3,FALSE),0) -> 2.5 | H9: 71.6 | I9: 5.5 | J9: =IFERROR(ROUND(H9*304.8/G9,0),0) -> 8729 | K9: =IFERROR(ROUND(I9*304.8/G9,0),0) -> 671 | L9: 1 | M9: =H9*I9*L9 -> 393.8 | N9: =IFERROR(VLOOKUP(F9,'_Products'!$A$1:$G$23,5,FALSE),0) -> 2000 | O9: front | P9: =IFERROR(VLOOKUP(F9,'_Products'!$A$1:$G$23,4,FALSE),0) -> 291.44 | Q9: =P9*M9 -> 114768.29 | R9: =SUM('Bundle Equipment'!E39:E39) -> 20636.28 | S9: =MAX(M9*10,500) -> 3938 | T9: =Q9+R9+S9 -> 139342.57 | U9: =V$2 -> 0.15 | V9: =IFERROR(T9/(1-U9),0) -> 163932.44 | W9: =V9-T9 -> 24589.87 | X9: =IFERROR(ROUND(M9*0.092903*VLOOKUP(F9,'_Products'!$A$1:$G$23,6,FALSE),0),0) -> 1924 | Y9: =IFERROR(ROUND(M9*0.092903*VLOOKUP(F9,'_Products'!$A$1:$G$23,7,FALSE),0),0) -> 14290 | Z9: =Y9*3.412 -> 48757
A10: T2-B1M Screen 20 — T2-B1M, WTC | B10: 7.91 | C10: 16.5 | E10: =IFERROR(VLOOKUP(F10,'_Products'!$A$1:$G$23,2,FALSE),"") -> LG/Yaham | F10: C2.5-MIP 2.5mm Indoor (Alt) | G10: =IFERROR(VLOOKUP(F10,'_Products'!$A$1:$G$23,3,FALSE),0) -> 2.5 | H10: 7.91 | I10: 16.5 | J10: =IFERROR(ROUND(H10*304.8/G10,0),0) -> 964 | K10: =IFERROR(ROUND(I10*304.8/G10,0),0) -> 2012 | L10: 1 | M10: =H10*I10*L10 -> 130.52 | N10: =IFERROR(VLOOKUP(F10,'_Products'!$A$1:$G$23,5,FALSE),0) -> 2000 | O10: front | P10: =IFERROR(VLOOKUP(F10,'_Products'!$A$1:$G$23,4,FALSE),0) -> 291.44 | Q10: =P10*M10 -> 38038.49 | R10: =SUM('Bundle Equipment'!E44:E44) -> 528.31 | S10: =MAX(M10*10,500) -> 1305.2 | T10: =Q10+R10+S10 -> 39872 | U10: =V$2 -> 0.15 | V10: =IFERROR(T10/(1-U10),0) -> 46908.24 | W10: =V10-T10 -> 7036.24 | X10: =IFERROR(ROUND(M10*0.092903*VLOOKUP(F10,'_Products'!$A$1:$G$23,6,FALSE),0),0) -> 638 | Y10: =IFERROR(ROUND(M10*0.092903*VLOOKUP(F10,'_Products'!$A$1:$G$23,7,FALSE),0),0) -> 4736 | Z10: =Y10*3.412 -> 16159
A11: T2-B1M Screen 21 — T2-B1M, WTC | B11: 7.91 | C11: 11.83 | E11: =IFERROR(VLOOKUP(F11,'_Products'!$A$1:$G$23,2,FALSE),"") -> LG/Yaham | F11: C2.5-MIP 2.5mm Indoor (Alt) | G11: =IFERROR(VLOOKUP(F11,'_Products'!$A$1:$G$23,3,FALSE),0) -> 2.5 | H11: 7.91 | I11: 11.83 | J11: =IFERROR(ROUND(H11*304.8/G11,0),0) -> 964 | K11: =IFERROR(ROUND(I11*304.8/G11,0),0) -> 1442 | L11: 1 | M11: =H11*I11*L11 -> 93.58 | N11: =IFERROR(VLOOKUP(F11,'_Products'!$A$1:$G$23,5,FALSE),0) -> 2000 | O11: front | P11: =IFERROR(VLOOKUP(F11,'_Products'!$A$1:$G$23,4,FALSE),0) -> 291.44 | Q11: =P11*M11 -> 27272.76 | R11: =SUM('Bundle Equipment'!E49:E49) -> 506.15 | S11: =MAX(M11*10,500) -> 935.8 | T11: =Q11+R11+S11 -> 28714.71 | U11: =V$2 -> 0.15 | V11: =IFERROR(T11/(1-U11),0) -> 33782.01 | W11: =V11-T11 -> 5067.3 | X11: =IFERROR(ROUND(M11*0.092903*VLOOKUP(F11,'_Products'!$A$1:$G$23,6,FALSE),0),0) -> 457 | Y11: =IFERROR(ROUND(M11*0.092903*VLOOKUP(F11,'_Products'!$A$1:$G$23,7,FALSE),0),0) -> 3396 | Z11: =Y11*3.412 -> 11587
A12: T2-B1M Screen 22 — T2-B1M, WTC | B12: 7.91 | C12: 7.91 | E12: =IFERROR(VLOOKUP(F12,'_Products'!$A$1:$G$23,2,FALSE),"") -> LG/Yaham | F12: C2.5-MIP 2.5mm Indoor (Alt) | G12: =IFERROR(VLOOKUP(F12,'_Products'!$A$1:$G$23,3,FALSE),0) -> 2.5 | H12: 7.91 | I12: 7.91 | J12: =IFERROR(ROUND(H12*304.8/G12,0),0) -> 964 | K12: =IFERROR(ROUND(I12*304.8/G12,0),0) -> 964 | L12: 1 | M12: =H12*I12*L12 -> 62.57 | N12: =IFERROR(VLOOKUP(F12,'_Products'!$A$1:$G$23,5,FALSE),0) -> 2000 | O12: front | P12: =IFERROR(VLOOKUP(F12,'_Products'!$A$1:$G$23,4,FALSE),0) -> 291.44 | Q12: =P12*M12 -> 18235.28 | R12: =SUM('Bundle Equipment'!E54:E54) -> 487.54 | S12: =MAX(M12*10,500) -> 625.7 | T12: =Q12+R12+S12 -> 19348.52 | U12: =V$2 -> 0.15 | V12: =IFERROR(T12/(1-U12),0) -> 22762.96 | W12: =V12-T12 -> 3414.44 | X12: =IFERROR(ROUND(M12*0.092903*VLOOKUP(F12,'_Products'!$A$1:$G$23,6,FALSE),0),0) -> 306 | Y12: =IFERROR(ROUND(M12*0.092903*VLOOKUP(F12,'_Products'!$A$1:$G$23,7,FALSE),0),0) -> 2271 | Z12: =Y12*3.412 -> 7749
A13: New Path Hall Option 1 — New Path Hall, WTC | B13: 48 | C13: 14 | E13: =IFERROR(VLOOKUP(F13,'_Products'!$A$1:$G$23,2,FALSE),"") -> LG/Yaham | F13: C2.5-MIP 2.5mm Indoor (Alt) | G13: =IFERROR(VLOOKUP(F13,'_Products'!$A$1:$G$23,3,FALSE),0) -> 2.5 | H13: 48 | I13: 14 | J13: =IFERROR(ROUND(H13*304.8/G13,0),0) -> 5852 | K13: =IFERROR(ROUND(I13*304.8/G13,0),0) -> 1707 | L13: 1 | M13: =H13*I13*L13 -> 672 | N13: =IFERROR(VLOOKUP(F13,'_Products'!$A$1:$G$23,5,FALSE),0) -> 2000 | O13: front | P13: =IFERROR(VLOOKUP(F13,'_Products'!$A$1:$G$23,4,FALSE),0) -> 291.44 | Q13: =P13*M13 -> 195846.34 | R13: =SUM('Bundle Equipment'!E60:E60) -> 20803.2 | S13: =MAX(M13*10,500) -> 6720 | T13: =Q13+R13+S13 -> 223369.54 | U13: =V$2 -> 0.15 | V13: =IFERROR(T13/(1-U13),0) -> 262787.69 | W13: =V13-T13 -> 39418.15 | X13: =IFERROR(ROUND(M13*0.092903*VLOOKUP(F13,'_Products'!$A$1:$G$23,6,FALSE),0),0) -> 3284 | Y13: =IFERROR(ROUND(M13*0.092903*VLOOKUP(F13,'_Products'!$A$1:$G$23,7,FALSE),0),0) -> 24385 | Z13: =Y13*3.412 -> 83202
A14: New Path Hall Option 2 — New Path Hall, WTC | B14: 65 | C14: 13 | E14: =IFERROR(VLOOKUP(F14,'_Products'!$A$1:$G$23,2,FALSE),"") -> LG/Yaham | F14: C2.5-MIP 2.5mm Indoor (Alt) | G14: =IFERROR(VLOOKUP(F14,'_Products'!$A$1:$G$23,3,FALSE),0) -> 2.5 | H14: 65 | I14: 13 | J14: =IFERROR(ROUND(H14*304.8/G14,0),0) -> 7925 | K14: =IFERROR(ROUND(I14*304.8/G14,0),0) -> 1585 | L14: 1 | M14: =H14*I14*L14 -> 845 | N14: =IFERROR(VLOOKUP(F14,'_Products'!$A$1:$G$23,5,FALSE),0) -> 2000 | O14: front | P14: =IFERROR(VLOOKUP(F14,'_Products'!$A$1:$G$23,4,FALSE),0) -> 291.44 | Q14: =P14*M14 -> 246265.11 | R14: =SUM('Bundle Equipment'!E66:E66) -> 29307 | S14: =MAX(M14*10,500) -> 8450 | T14: =Q14+R14+S14 -> 284022.11 | U14: =V$2 -> 0.15 | V14: =IFERROR(T14/(1-U14),0) -> 334143.66 | W14: =V14-T14 -> 50121.55 | X14: =IFERROR(ROUND(M14*0.092903*VLOOKUP(F14,'_Products'!$A$1:$G$23,6,FALSE),0),0) -> 4129 | Y14: =IFERROR(ROUND(M14*0.092903*VLOOKUP(F14,'_Products'!$A$1:$G$23,7,FALSE),0),0) -> 30663 | Z14: =Y14*3.412 -> 104622
A16: TOTAL (11 displays) | M16: =SUM(M4:M14) -> 6333.2 | Q16: =SUM(Q4:Q14) -> 1845717.7 | R16: =SUM(R4:R14) -> 162049.91 | S16: =SUM(S4:S14) -> 63332 | T16: =SUM(T4:T14) -> 2071099.6 | U16: =IFERROR(1-T16/V16,0) -> 0.15 | V16: =SUM(V4:V14) -> 2436587.7 | W16: =SUM(W4:W14) -> 365488.16 | X16: =SUM(X4:X14) -> 86745 | Y16: =SUM(Y4:Y14) -> 786800 | Z16: =SUM(Z4:Z14) -> 2684562

Sheet Tech Specs (Installers)
A1: WTC Digital Signage Upgrade — LED Technical Specifications (No Pricing)
A2: Technical specifications only — no pricing data. Safe for installer/subcontractor distribution.
A4: Display Name | B4: Qty | C4: Pixel Pitch | D4: Height (ft) | E4: Width (ft) | F4: Pixels H | G4: Pixels W | H4: Sq Ft | I4: Brightness (nits) | J4: Service | K4: Environment | L4: Weight (lbs) | M4: Total Power (W) | N4: Fiber Strands | O4: BTU/hr
A5: ='LED Cost Sheet'!A4 -> Underpass 3 — Underpass 1-4, WTC | B5: ='LED Cost Sheet'!I4 -> 1 | C5: ='LED Cost Sheet'!D4 -> 2.5mm | D5: ='LED Cost Sheet'!E4 -> 7.48 | E5: ='LED Cost Sheet'!F4 -> 29.92 | F5: ='LED Cost Sheet'!G4 -> 912 | G5: ='LED Cost Sheet'!H4 -> 3648 | H5: =D5*E5*B5 -> 223.8 | I5: ='LED Cost Sheet'!K4 | J5: ='LED Cost Sheet'!L4 -> front | K5: indoor | L5: ='LED Cost Sheet'!U4 -> 1094 | M5: ='LED Cost Sheet'!V4 -> 8121 | N5: =IFERROR((F5*G5*B5)/400000,0) -> 8.32 | O5: ='LED Cost Sheet'!W4 -> 27709
A6: ='LED Cost Sheet'!A5 -> Underpass 4 — Underpass 1-4, WTC | B6: ='LED Cost Sheet'!I5 -> 1 | C6: ='LED Cost Sheet'!D5 -> 2.5mm | D6: ='LED Cost Sheet'!E5 -> 12.6 | E6: ='LED Cost Sheet'!F5 -> 29.92 | F6: ='LED Cost Sheet'!G5 -> 1536 | G6: ='LED Cost Sheet'!H5 -> 3648 | H6: =D6*E6*B6 -> 376.99 | I6: ='LED Cost Sheet'!K5 | J6: ='LED Cost Sheet'!L5 -> front | K6: indoor | L6: ='LED Cost Sheet'!U5 -> 1842 | M6: ='LED Cost Sheet'!V5 -> 13680 | N6: =IFERROR((F6*G6*B6)/400000,0) -> 14.01 | O6: ='LED Cost Sheet'!W5 -> 46676
A7: ='LED Cost Sheet'!A6 -> Concourse — Concourse, WTC | B7: ='LED Cost Sheet'!I6 -> 1 | C7: ='LED Cost Sheet'!D6 -> 2.5mm | D7: ='LED Cost Sheet'!E6 -> 9.45 | E7: ='LED Cost Sheet'!F6 -> 280.31 | F7: ='LED Cost Sheet'!G6 -> 1152 | G7: ='LED Cost Sheet'!H6 -> 34175 | H7: =D7*E7*B7 -> 2648.93 | I7: ='LED Cost Sheet'!K6 | J7: ='LED Cost Sheet'!L6 -> front | K7: indoor | L7: ='LED Cost Sheet'!U6 -> 12945 | M7: ='LED Cost Sheet'!V6 -> 96124 | N7: =IFERROR((F7*G7*B7)/400000,0) -> 98.42 | O7: ='LED Cost Sheet'!W6 -> 327975
A8: ='LED Cost Sheet'!A7 -> T4-B1 (6-9) — T4-B1, WTC | B8: ='LED Cost Sheet'!I7 -> 4 | C8: ='LED Cost Sheet'!D7 -> 2.5mm | D8: ='LED Cost Sheet'!E7 -> 7.87 | E8: ='LED Cost Sheet'!F7 -> 8.66 | F8: ='LED Cost Sheet'!G7 -> 960 | G8: ='LED Cost Sheet'!H7 -> 1056 | H8: =D8*E8*B8 -> 272.62 | I8: ='LED Cost Sheet'!K7 | J8: ='LED Cost Sheet'!L7 -> front | K8: indoor | L8: ='LED Cost Sheet'!U7 -> 1332 | M8: ='LED Cost Sheet'!V7 -> 9893 | N8: =IFERROR((F8*G8*B8)/400000,0) -> 10.14 | O8: ='LED Cost Sheet'!W7 -> 33755
A9: ='LED Cost Sheet'!A8 -> T4-B2 (10-18) — T4-B2, WTC | B9: ='LED Cost Sheet'!I8 -> 9 | C9: ='LED Cost Sheet'!D8 -> 2.5mm | D9: ='LED Cost Sheet'!E8 -> 7.87 | E9: ='LED Cost Sheet'!F8 -> 8.66 | F9: ='LED Cost Sheet'!G8 -> 960 | G9: ='LED Cost Sheet'!H8 -> 1056 | H9: =D9*E9*B9 -> 613.39 | I9: ='LED Cost Sheet'!K8 | J9: ='LED Cost Sheet'!L8 -> front | K9: indoor | L9: ='LED Cost Sheet'!U8 -> 2997 | M9: ='LED Cost Sheet'!V8 -> 22259 | N9: =IFERROR((F9*G9*B9)/400000,0) -> 22.81 | O9: ='LED Cost Sheet'!W8 -> 75948
A10: ='LED Cost Sheet'!A9 -> T4 Lobby Elevator — T4 Lobby Elevator, WTC | B10: ='LED Cost Sheet'!I9 -> 1 | C10: ='LED Cost Sheet'!D9 -> 2.5mm | D10: ='LED Cost Sheet'!E9 -> 71.6 | E10: ='LED Cost Sheet'!F9 -> 5.5 | F10: ='LED Cost Sheet'!G9 -> 8729 | G10: ='LED Cost Sheet'!H9 -> 671 | H10: =D10*E10*B10 -> 393.8 | I10: ='LED Cost Sheet'!K9 | J10: ='LED Cost Sheet'!L9 -> front | K10: indoor | L10: ='LED Cost Sheet'!U9 -> 1924 | M10: ='LED Cost Sheet'!V9 -> 14290 | N10: =IFERROR((F10*G10*B10)/400000,0) -> 14.64 | O10: ='LED Cost Sheet'!W9 -> 48757
A11: ='LED Cost Sheet'!A10 -> T2-B1M Screen 20 — T2-B1M, WTC | B11: ='LED Cost Sheet'!I10 -> 1 | C11: ='LED Cost Sheet'!D10 -> 2.5mm | D11: ='LED Cost Sheet'!E10 -> 7.91 | E11: ='LED Cost Sheet'!F10 -> 16.5 | F11: ='LED Cost Sheet'!G10 -> 964 | G11: ='LED Cost Sheet'!H10 -> 2012 | H11: =D11*E11*B11 -> 130.52 | I11: ='LED Cost Sheet'!K10 | J11: ='LED Cost Sheet'!L10 -> front | K11: indoor | L11: ='LED Cost Sheet'!U10 -> 638 | M11: ='LED Cost Sheet'!V10 -> 4736 | N11: =IFERROR((F11*G11*B11)/400000,0) -> 4.85 | O11: ='LED Cost Sheet'!W10 -> 16159
A12: ='LED Cost Sheet'!A11 -> T2-B1M Screen 21 — T2-B1M, WTC | B12: ='LED Cost Sheet'!I11 -> 1 | C12: ='LED Cost Sheet'!D11 -> 2.5mm | D12: ='LED Cost Sheet'!E11 -> 7.91 | E12: ='LED Cost Sheet'!F11 -> 11.83 | F12: ='LED Cost Sheet'!G11 -> 964 | G12: ='LED Cost Sheet'!H11 -> 1442 | H12: =D12*E12*B12 -> 93.58 | I12: ='LED Cost Sheet'!K11 | J12: ='LED Cost Sheet'!L11 -> front | K12: indoor | L12: ='LED Cost Sheet'!U11 -> 457 | M12: ='LED Cost Sheet'!V11 -> 3396 | N12: =IFERROR((F12*G12*B12)/400000,0) -> 3.48 | O12: ='LED Cost Sheet'!W11 -> 11587
A13: ='LED Cost Sheet'!A12 -> T2-B1M Screen 22 — T2-B1M, WTC | B13: ='LED Cost Sheet'!I12 -> 1 | C13: ='LED Cost Sheet'!D12 -> 2.5mm | D13: ='LED Cost Sheet'!E12 -> 7.91 | E13: ='LED Cost Sheet'!F12 -> 7.91 | F13: ='LED Cost Sheet'!G12 -> 964 | G13: ='LED Cost Sheet'!H12 -> 964 | H13: =D13*E13*B13 -> 62.57 | I13: ='LED Cost Sheet'!K12 | J13: ='LED Cost Sheet'!L12 -> front | K13: indoor | L13: ='LED Cost Sheet'!U12 -> 306 | M13: ='LED Cost Sheet'!V12 -> 2271 | N13: =IFERROR((F13*G13*B13)/400000,0) -> 2.32 | O13: ='LED Cost Sheet'!W12 -> 7749
A14: ='LED Cost Sheet'!A13 -> New Path Hall Option 1 — New Path Hall, WTC | B14: ='LED Cost Sheet'!I13 -> 1 | C14: ='LED Cost Sheet'!D13 -> 2.5mm | D14: ='LED Cost Sheet'!E13 -> 48 | E14: ='LED Cost Sheet'!F13 -> 14 | F14: ='LED Cost Sheet'!G13 -> 5852 | G14: ='LED Cost Sheet'!H13 -> 1707 | H14: =D14*E14*B14 -> 672 | I14: ='LED Cost Sheet'!K13 | J14: ='LED Cost Sheet'!L13 -> front | K14: indoor | L14: ='LED Cost Sheet'!U13 -> 3284 | M14: ='LED Cost Sheet'!V13 -> 24385 | N14: =IFERROR((F14*G14*B14)/400000,0) -> 24.97 | O14: ='LED Cost Sheet'!W13 -> 83202
A15: ='LED Cost Sheet'!A14 -> New Path Hall Option 2 — New Path Hall, WTC | B15: ='LED Cost Sheet'!I14 -> 1 | C15: ='LED Cost Sheet'!D14 -> 2.5mm | D15: ='LED Cost Sheet'!E14 -> 65 | E15: ='LED Cost Sheet'!F14 -> 13 | F15: ='LED Cost Sheet'!G14 -> 7925 | G15: ='LED Cost Sheet'!H14 -> 1585 | H15: =D15*E15*B15 -> 845 | I15: ='LED Cost Sheet'!K14 | J15: ='LED Cost Sheet'!L14 -> front | K15: indoor | L15: ='LED Cost Sheet'!U14 -> 4129 | M15: ='LED Cost Sheet'!V14 -> 30663 | N15: =IFERROR((F15*G15*B15)/400000,0) -> 31.4 | O15: ='LED Cost Sheet'!W14 -> 104622

Sheet Underpass 3 - Install
A3: Project Name: WTC Digital Signage Upgrade
A4: 2026-04-01
A5: Revised By: ANC Proposal Engine
C7: Linked Margin Assignment
C8: Install Margin | D8: 0.15
C9: Electrical Margin | D9: 0.15
C10: ANC Margin | D10: 0.15
C11: Engineering and Permits | D11: 0.15
B15: Underpass 3
B16: Height | C16: Width | D16: Total Sq. Ft | E16: QTY
B17: 7.48 | C17: 29.92 | D17: 223.8 | E17: 1
B19: Structural Materials: | C19: Subcontractor 1 | D19: Subcontractor 2 | E19: Subcontractor 3 | F19: Selected | G19: Additional Contingency | I19: Total Cost | J19: Install Margin | K19: Selling Price
B20: FABRICATE PRIMARY STEEL | C20: 0 | D20: 0 | E20: 0 | F20: 0 | G20: 0 | I20: =SUM(C20:G20) -> 0 | J20: =$D$8 -> 0.15 | K20: =I20/(1-J20) -> 0
B21: SUPPLY AND INSTALL PRIMARY PLYWOOD | C21: 0 | D21: 0 | E21: 0 | F21: 0 | G21: 0 | I21: =SUM(C21:G21) -> 0 | J21: =$D$8 -> 0.15 | K21: =I21/(1-J21) -> 0
B22: FABRICATE SECONDARY STEEL SUBSTRUCTURE | C22: 4102.5 | D22: 0 | E22: 0 | F22: 0 | G22: 0 | I22: =SUM(C22:G22) -> 4102.5 | J22: =$D$8 -> 0.15 | K22: =I22/(1-J22) -> 4826.47
B23: FABRICATE CLADDING AND TRIM | C23: 0 | D23: 0 | E23: 0 | F23: 0 | G23: 0 | I23: =SUM(C23:G23) -> 0 | J23: =$D$8 -> 0.15 | K23: =I23/(1-J23) -> 0
B24: OTHER SCOPE ITEM | C24: 0 | D24: 0 | E24: 0 | F24: 0 | G24: 0 | I24: =SUM(C24:G24) -> 0 | J24: =$D$8 -> 0.15 | K24: =I24/(1-J24) -> 0
B25: OTHER SCOPE ITEM | C25: 0 | D25: 0 | E25: 0 | F25: 0 | G25: 0 | I25: =SUM(C25:G25) -> 0 | J25: =$D$8 -> 0.15 | K25: =I25/(1-J25) -> 0
B26: SUBTOTAL | I26: =SUM(I20:I25) -> 4102.5 | K26: =SUM(K20:K25) -> 4826.47
B28: Structural Labor and LED Installation | C28: Subcontractor 1 | D28: Subcontractor 2 | E28: Subcontractor 3 | F28: Selected | G28: Additional Contingency | I28: Total Cost | J28: Install Margin | K28: Selling Price
B29: REMOVAL AND DISPOSAL | C29: 0 | D29: 0 | E29: 0 | F29: 0 | G29: 0 | I29: =SUM(C29:G29) -> 0 | J29: =$D$8 -> 0.15 | K29: =I29/(1-J29) -> 0
B30: INSTALL SECONDARY STEEL SUBSTRUCTURE | C30: 0 | D30: 0 | E30: 0 | F30: 0 | G30: 0 | I30: =SUM(C30:G30) -> 0 | J30: =$D$8 -> 0.15 | K30: =I30/(1-J30) -> 0
B31: INSTALL LED DISPLAYS | C31: 17093.75 | D31: 0 | E31: 0 | F31: 0 | G31: 0 | I31: =SUM(C31:G31) -> 17093.75 | J31: =$D$8 -> 0.15 | K31: =I31/(1-J31) -> 20110.29
B32: INSTALL CLADDING AND TRIM | C32: 0 | D32: 0 | E32: 0 | F32: 0 | G32: 0 | I32: =SUM(C32:G32) -> 0 | J32: =$D$8 -> 0.15 | K32: =I32/(1-J32) -> 0
B33: HEAVY EQUIPMENT | C33: 0 | D33: 0 | E33: 0 | F33: 0 | G33: 0 | I33: =SUM(C33:G33) -> 0 | J33: =$D$8 -> 0.15 | K33: =I33/(1-J33) -> 0
B34: PM/GENERAL CONDITIONS/TRAVEL | C34: 20882.35 | D34: 0 | E34: 0 | F34: 0 | G34: 0 | I34: =SUM(C34:G34) -> 20882.35 | J34: =$D$8 -> 0.15 | K34: =I34/(1-J34) -> 24567.47
B35: SUBTOTAL | I35: =SUM(I29:I34) -> 37976.1 | K35: =SUM(K29:K34) -> 44677.76
B37: Electrical and Data - Materials and Subcontracting | C37: Subcontractor 1 | D37: Subcontractor 2 | E37: Subcontractor 3 | F37: Selected | G37: Additional Contingency | I37: Total Cost | J37: Install Margin | K37: Selling Price
B38: ELECTRICAL MATERIALS | C38: 17093.75 | D38: 0 | E38: 0 | F38: 0 | G38: 0 | I38: =SUM(C38:G38) -> 17093.75 | J38: =$D$9 -> 0.15 | K38: =I38/(1-J38) -> 20110.29
B39: DATA MATERIALS | C39: 0 | D39: 0 | E39: 0 | F39: 0 | G39: 0 | I39: =SUM(C39:G39) -> 0 | J39: =$D$9 -> 0.15 | K39: =I39/(1-J39) -> 0
B40: ELECTRICAL LABOR | C40: 0 | D40: 0 | E40: 0 | F40: 0 | G40: 0 | I40: =SUM(C40:G40) -> 0 | J40: =$D$9 -> 0.15 | K40: =I40/(1-J40) -> 0
B41: DATA LABOR | C41: 0 | D41: 0 | E41: 0 | F41: 0 | G41: 0 | I41: =SUM(C41:G41) -> 0 | J41: =$D$9 -> 0.15 | K41: =I41/(1-J41) -> 0
B42: SUB PANEL | C42: 0 | D42: 0 | E42: 0 | F42: 0 | G42: 0 | I42: =SUM(C42:G42) -> 0 | J42: =$D$9 -> 0.15 | K42: =I42/(1-J42) -> 0
B43: MISC | C43: 0 | D43: 0 | E43: 0 | F43: 0 | G43: 0 | I43: =SUM(C43:G43) -> 0 | J43: =$D$9 -> 0.15 | K43: =I43/(1-J43) -> 0
B44: SUBTOTAL | I44: =SUM(I38:I43) -> 17093.75 | K44: =SUM(K38:K43) -> 20110.29
B46: Submittals, Engineering, and Permits | C46: Subcontractor 1 | D46: Subcontractor 2 | E46: Subcontractor 3 | F46: Selected | G46: Additional Contingency | I46: Total Cost | J46: Install Margin | K46: Selling Price
B47: STRUCTURAL ENGINEERING | C47: 4705.88 | D47: 0 | E47: 0 | F47: 0 | G47: 0 | I47: =SUM(C47:G47) -> 4705.88 | J47: =$D$11 -> 0.15 | K47: =I47/(1-J47) -> 5536.33
B48: STRUCTURAL CERTIFICATION | C48: 0 | D48: 0 | E48: 0 | F48: 0 | G48: 0 | I48: =SUM(C48:G48) -> 0 | J48: =$D$11 -> 0.15 | K48: =I48/(1-J48) -> 0
B49: ELECTRICAL ENGINEERING | C49: 0 | D49: 0 | E49: 0 | F49: 0 | G49: 0 | I49: =SUM(C49:G49) -> 0 | J49: =$D$11 -> 0.15 | K49: =I49/(1-J49) -> 0
B50: ELECTRICAL CERTIFICATION | C50: 0 | D50: 0 | E50: 0 | F50: 0 | G50: 0 | I50: =SUM(C50:G50) -> 0 | J50: =$D$11 -> 0.15 | K50: =I50/(1-J50) -> 0
B51: PERMITS | C51: 0 | D51: 0 | E51: 0 | F51: 0 | G51: 0 | I51: =SUM(C51:G51) -> 0 | J51: =$D$11 -> 0.15 | K51: =I51/(1-J51) -> 0
B52: SUBTOTAL | I52: =SUM(I47:I51) -> 4705.88 | K52: =SUM(K47:K51) -> 5536.33
B54: ZONE GRAND TOTAL | I54: =I26+I35+I44+I52 -> 131924.34 | K54: =K26+K35+K44+K52 -> 152572.17

Sheet Underpass 4 - Install
A3: Project Name: WTC Digital Signage Upgrade
A4: 2026-04-01
A5: Revised By: ANC Proposal Engine
C7: Linked Margin Assignment
C8: Install Margin | D8: 0.15
C9: Electrical Margin | D9: 0.15
C10: ANC Margin | D10: 0.15
C11: Engineering and Permits | D11: 0.15
B15: Underpass 4
B16: Height | C16: Width | D16: Total Sq. Ft | E16: QTY
B17: 12.6 | C17: 29.92 | D17: 376.99 | E17: 1
B19: Structural Materials: | C19: Subcontractor 1 | D19: Subcontractor 2 | E19: Subcontractor 3 | F19: Selected | G19: Additional Contingency | I19: Total Cost | J19: Install Margin | K19: Selling Price
B20: FABRICATE PRIMARY STEEL | C20: 0 | D20: 0 | E20: 0 | F20: 0 | G20: 0 | I20: =SUM(C20:G20) -> 0 | J20: =$D$8 -> 0.15 | K20: =I20/(1-J20) -> 0
B21: SUPPLY AND INSTALL PRIMARY PLYWOOD | C21: 0 | D21: 0 | E21: 0 | F21: 0 | G21: 0 | I21: =SUM(C21:G21) -> 0 | J21: =$D$8 -> 0.15 | K21: =I21/(1-J21) -> 0
B22: FABRICATE SECONDARY STEEL SUBSTRUCTURE | C22: 6907.5 | D22: 0 | E22: 0 | F22: 0 | G22: 0 | I22: =SUM(C22:G22) -> 6907.5 | J22: =$D$8 -> 0.15 | K22: =I22/(1-J22) -> 8126.47
B23: FABRICATE CLADDING AND TRIM | C23: 0 | D23: 0 | E23: 0 | F23: 0 | G23: 0 | I23: =SUM(C23:G23) -> 0 | J23: =$D$8 -> 0.15 | K23: =I23/(1-J23) -> 0
B24: OTHER SCOPE ITEM | C24: 0 | D24: 0 | E24: 0 | F24: 0 | G24: 0 | I24: =SUM(C24:G24) -> 0 | J24: =$D$8 -> 0.15 | K24: =I24/(1-J24) -> 0
B25: OTHER SCOPE ITEM | C25: 0 | D25: 0 | E25: 0 | F25: 0 | G25: 0 | I25: =SUM(C25:G25) -> 0 | J25: =$D$8 -> 0.15 | K25: =I25/(1-J25) -> 0
B26: SUBTOTAL | I26: =SUM(I20:I25) -> 6907.5 | K26: =SUM(K20:K25) -> 8126.47
B28: Structural Labor and LED Installation | C28: Subcontractor 1 | D28: Subcontractor 2 | E28: Subcontractor 3 | F28: Selected | G28: Additional Contingency | I28: Total Cost | J28: Install Margin | K28: Selling Price
B29: REMOVAL AND DISPOSAL | C29: 0 | D29: 0 | E29: 0 | F29: 0 | G29: 0 | I29: =SUM(C29:G29) -> 0 | J29: =$D$8 -> 0.15 | K29: =I29/(1-J29) -> 0
B30: INSTALL SECONDARY STEEL SUBSTRUCTURE | C30: 0 | D30: 0 | E30: 0 | F30: 0 | G30: 0 | I30: =SUM(C30:G30) -> 0 | J30: =$D$8 -> 0.15 | K30: =I30/(1-J30) -> 0
B31: INSTALL LED DISPLAYS | C31: 28781.25 | D31: 0 | E31: 0 | F31: 0 | G31: 0 | I31: =SUM(C31:G31) -> 28781.25 | J31: =$D$8 -> 0.15 | K31: =I31/(1-J31) -> 33860.29
B32: INSTALL CLADDING AND TRIM | C32: 0 | D32: 0 | E32: 0 | F32: 0 | G32: 0 | I32: =SUM(C32:G32) -> 0 | J32: =$D$8 -> 0.15 | K32: =I32/(1-J32) -> 0
B33: HEAVY EQUIPMENT | C33: 0 | D33: 0 | E33: 0 | F33: 0 | G33: 0 | I33: =SUM(C33:G33) -> 0 | J33: =$D$8 -> 0.15 | K33: =I33/(1-J33) -> 0
B34: PM/GENERAL CONDITIONS/TRAVEL | C34: 20882.35 | D34: 0 | E34: 0 | F34: 0 | G34: 0 | I34: =SUM(C34:G34) -> 20882.35 | J34: =$D$8 -> 0.15 | K34: =I34/(1-J34) -> 24567.47
B35: SUBTOTAL | I35: =SUM(I29:I34) -> 49663.6 | K35: =SUM(K29:K34) -> 58427.76
B37: Electrical and Data - Materials and Subcontracting | C37: Subcontractor 1 | D37: Subcontractor 2 | E37: Subcontractor 3 | F37: Selected | G37: Additional Contingency | I37: Total Cost | J37: Install Margin | K37: Selling Price
B38: ELECTRICAL MATERIALS | C38: 28781.25 | D38: 0 | E38: 0 | F38: 0 | G38: 0 | I38: =SUM(C38:G38) -> 28781.25 | J38: =$D$9 -> 0.15 | K38: =I38/(1-J38) -> 33860.29
B39: DATA MATERIALS | C39: 0 | D39: 0 | E39: 0 | F39: 0 | G39: 0 | I39: =SUM(C39:G39) -> 0 | J39: =$D$9 -> 0.15 | K39: =I39/(1-J39) -> 0
B40: ELECTRICAL LABOR | C40: 0 | D40: 0 | E40: 0 | F40: 0 | G40: 0 | I40: =SUM(C40:G40) -> 0 | J40: =$D$9 -> 0.15 | K40: =I40/(1-J40) -> 0
B41: DATA LABOR | C41: 0 | D41: 0 | E41: 0 | F41: 0 | G41: 0 | I41: =SUM(C41:G41) -> 0 | J41: =$D$9 -> 0.15 | K41: =I41/(1-J41) -> 0
B42: SUB PANEL | C42: 0 | D42: 0 | E42: 0 | F42: 0 | G42: 0 | I42: =SUM(C42:G42) -> 0 | J42: =$D$9 -> 0.15 | K42: =I42/(1-J42) -> 0
B43: MISC | C43: 0 | D43: 0 | E43: 0 | F43: 0 | G43: 0 | I43: =SUM(C43:G43) -> 0 | J43: =$D$9 -> 0.15 | K43: =I43/(1-J43) -> 0
B44: SUBTOTAL | I44: =SUM(I38:I43) -> 28781.25 | K44: =SUM(K38:K43) -> 33860.29
B46: Submittals, Engineering, and Permits | C46: Subcontractor 1 | D46: Subcontractor 2 | E46: Subcontractor 3 | F46: Selected | G46: Additional Contingency | I46: Total Cost | J46: Install Margin | K46: Selling Price
B47: STRUCTURAL ENGINEERING | C47: 4705.88 | D47: 0 | E47: 0 | F47: 0 | G47: 0 | I47: =SUM(C47:G47) -> 4705.88 | J47: =$D$11 -> 0.15 | K47: =I47/(1-J47) -> 5536.33
B48: STRUCTURAL CERTIFICATION | C48: 0 | D48: 0 | E48: 0 | F48: 0 | G48: 0 | I48: =SUM(C48:G48) -> 0 | J48: =$D$11 -> 0.15 | K48: =I48/(1-J48) -> 0
B49: ELECTRICAL ENGINEERING | C49: 0 | D49: 0 | E49: 0 | F49: 0 | G49: 0 | I49: =SUM(C49:G49) -> 0 | J49: =$D$11 -> 0.15 | K49: =I49/(1-J49) -> 0
B50: ELECTRICAL CERTIFICATION | C50: 0 | D50: 0 | E50: 0 | F50: 0 | G50: 0 | I50: =SUM(C50:G50) -> 0 | J50: =$D$11 -> 0.15 | K50: =I50/(1-J50) -> 0
B51: PERMITS | C51: 0 | D51: 0 | E51: 0 | F51: 0 | G51: 0 | I51: =SUM(C51:G51) -> 0 | J51: =$D$11 -> 0.15 | K51: =I51/(1-J51) -> 0
B52: SUBTOTAL | I52: =SUM(I47:I51) -> 4705.88 | K52: =SUM(K47:K51) -> 5536.33
B54: ZONE GRAND TOTAL | I54: =I26+I35+I44+I52 -> 224323.53 | K54: =K26+K35+K44+K52 -> 259474.86

Sheet Concourse - Install
A3: Project Name: WTC Digital Signage Upgrade
A4: 2026-04-01
A5: Revised By: ANC Proposal Engine
C7: Linked Margin Assignment
C8: Install Margin | D8: 0.15
C9: Electrical Margin | D9: 0.15
C10: ANC Margin | D10: 0.15
C11: Engineering and Permits | D11: 0.15
B15: Concourse
B16: Height | C16: Width | D16: Total Sq. Ft | E16: QTY
B17: 9.45 | C17: 280.31 | D17: 2648.93 | E17: 1
B19: Structural Materials: | C19: Subcontractor 1 | D19: Subcontractor 2 | E19: Subcontractor 3 | F19: Selected | G19: Additional Contingency | I19: Total Cost | J19: Install Margin | K19: Selling Price
B20: FABRICATE PRIMARY STEEL | C20: 0 | D20: 0 | E20: 0 | F20: 0 | G20: 0 | I20: =SUM(C20:G20) -> 0 | J20: =$D$8 -> 0.15 | K20: =I20/(1-J20) -> 0
B21: SUPPLY AND INSTALL PRIMARY PLYWOOD | C21: 0 | D21: 0 | E21: 0 | F21: 0 | G21: 0 | I21: =SUM(C21:G21) -> 0 | J21: =$D$8 -> 0.15 | K21: =I21/(1-J21) -> 0
B22: FABRICATE SECONDARY STEEL SUBSTRUCTURE | C22: 48536.25 | D22: 0 | E22: 0 | F22: 0 | G22: 0 | I22: =SUM(C22:G22) -> 48536.25 | J22: =$D$8 -> 0.15 | K22: =I22/(1-J22) -> 57101.47
B23: FABRICATE CLADDING AND TRIM | C23: 0 | D23: 0 | E23: 0 | F23: 0 | G23: 0 | I23: =SUM(C23:G23) -> 0 | J23: =$D$8 -> 0.15 | K23: =I23/(1-J23) -> 0
B24: OTHER SCOPE ITEM | C24: 0 | D24: 0 | E24: 0 | F24: 0 | G24: 0 | I24: =SUM(C24:G24) -> 0 | J24: =$D$8 -> 0.15 | K24: =I24/(1-J24) -> 0
B25: OTHER SCOPE ITEM | C25: 0 | D25: 0 | E25: 0 | F25: 0 | G25: 0 | I25: =SUM(C25:G25) -> 0 | J25: =$D$8 -> 0.15 | K25: =I25/(1-J25) -> 0
B26: SUBTOTAL | I26: =SUM(I20:I25) -> 48536.25 | K26: =SUM(K20:K25) -> 57101.47
B28: Structural Labor and LED Installation | C28: Subcontractor 1 | D28: Subcontractor 2 | E28: Subcontractor 3 | F28: Selected | G28: Additional Contingency | I28: Total Cost | J28: Install Margin | K28: Selling Price
B29: REMOVAL AND DISPOSAL | C29: 0 | D29: 0 | E29: 0 | F29: 0 | G29: 0 | I29: =SUM(C29:G29) -> 0 | J29: =$D$8 -> 0.15 | K29: =I29/(1-J29) -> 0
B30: INSTALL SECONDARY STEEL SUBSTRUCTURE | C30: 0 | D30: 0 | E30: 0 | F30: 0 | G30: 0 | I30: =SUM(C30:G30) -> 0 | J30: =$D$8 -> 0.15 | K30: =I30/(1-J30) -> 0
B31: INSTALL LED DISPLAYS | C31: 202234.38 | D31: 0 | E31: 0 | F31: 0 | G31: 0 | I31: =SUM(C31:G31) -> 202234.38 | J31: =$D$8 -> 0.15 | K31: =I31/(1-J31) -> 237922.8
B32: INSTALL CLADDING AND TRIM | C32: 0 | D32: 0 | E32: 0 | F32: 0 | G32: 0 | I32: =SUM(C32:G32) -> 0 | J32: =$D$8 -> 0.15 | K32: =I32/(1-J32) -> 0
B33: HEAVY EQUIPMENT | C33: 0 | D33: 0 | E33: 0 | F33: 0 | G33: 0 | I33: =SUM(C33:G33) -> 0 | J33: =$D$8 -> 0.15 | K33: =I33/(1-J33) -> 0
B34: PM/GENERAL CONDITIONS/TRAVEL | C34: 20882.35 | D34: 0 | E34: 0 | F34: 0 | G34: 0 | I34: =SUM(C34:G34) -> 20882.35 | J34: =$D$8 -> 0.15 | K34: =I34/(1-J34) -> 24567.47
B35: SUBTOTAL | I35: =SUM(I29:I34) -> 223116.73 | K35: =SUM(K29:K34) -> 262490.27
B37: Electrical and Data - Materials and Subcontracting | C37: Subcontractor 1 | D37: Subcontractor 2 | E37: Subcontractor 3 | F37: Selected | G37: Additional Contingency | I37: Total Cost | J37: Install Margin | K37: Selling Price
B38: ELECTRICAL MATERIALS | C38: 202234.38 | D38: 0 | E38: 0 | F38: 0 | G38: 0 | I38: =SUM(C38:G38) -> 202234.38 | J38: =$D$9 -> 0.15 | K38: =I38/(1-J38) -> 237922.8
B39: DATA MATERIALS | C39: 0 | D39: 0 | E39: 0 | F39: 0 | G39: 0 | I39: =SUM(C39:G39) -> 0 | J39: =$D$9 -> 0.15 | K39: =I39/(1-J39) -> 0
B40: ELECTRICAL LABOR | C40: 0 | D40: 0 | E40: 0 | F40: 0 | G40: 0 | I40: =SUM(C40:G40) -> 0 | J40: =$D$9 -> 0.15 | K40: =I40/(1-J40) -> 0
B41: DATA LABOR | C41: 0 | D41: 0 | E41: 0 | F41: 0 | G41: 0 | I41: =SUM(C41:G41) -> 0 | J41: =$D$9 -> 0.15 | K41: =I41/(1-J41) -> 0
B42: SUB PANEL | C42: 0 | D42: 0 | E42: 0 | F42: 0 | G42: 0 | I42: =SUM(C42:G42) -> 0 | J42: =$D$9 -> 0.15 | K42: =I42/(1-J42) -> 0
B43: MISC | C43: 0 | D43: 0 | E43: 0 | F43: 0 | G43: 0 | I43: =SUM(C43:G43) -> 0 | J43: =$D$9 -> 0.15 | K43: =I43/(1-J43) -> 0
B44: SUBTOTAL | I44: =SUM(I38:I43) -> 202234.38 | K44: =SUM(K38:K43) -> 237922.8
B46: Submittals, Engineering, and Permits | C46: Subcontractor 1 | D46: Subcontractor 2 | E46: Subcontractor 3 | F46: Selected | G46: Additional Contingency | I46: Total Cost | J46: Install Margin | K46: Selling Price
B47: STRUCTURAL ENGINEERING | C47: 4705.88 | D47: 0 | E47: 0 | F47: 0 | G47: 0 | I47: =SUM(C47:G47) -> 4705.88 | J47: =$D$11 -> 0.15 | K47: =I47/(1-J47) -> 5536.33
B48: STRUCTURAL CERTIFICATION | C48: 0 | D48: 0 | E48: 0 | F48: 0 | G48: 0 | I48: =SUM(C48:G48) -> 0 | J48: =$D$11 -> 0.15 | K48: =I48/(1-J48) -> 0
B49: ELECTRICAL ENGINEERING | C49: 0 | D49: 0 | E49: 0 | F49: 0 | G49: 0 | I49: =SUM(C49:G49) -> 0 | J49: =$D$11 -> 0.15 | K49: =I49/(1-J49) -> 0
B50: ELECTRICAL CERTIFICATION | C50: 0 | D50: 0 | E50: 0 | F50: 0 | G50: 0 | I50: =SUM(C50:G50) -> 0 | J50: =$D$11 -> 0.15 | K50: =I50/(1-J50) -> 0
B51: PERMITS | C51: 0 | D51: 0 | E51: 0 | F51: 0 | G51: 0 | I51: =SUM(C51:G51) -> 0 | J51: =$D$11 -> 0.15 | K51: =I51/(1-J51) -> 0
B52: SUBTOTAL | I52: =SUM(I47:I51) -> 4705.88 | K52: =SUM(K47:K51) -> 5536.33
B54: ZONE GRAND TOTAL | I54: =I26+I35+I44+I52 -> 1324270.8 | K54: =K26+K35+K44+K52 -> 1526801.7

Sheet T4-B1 (6-9) - Install
A3: Project Name: WTC Digital Signage Upgrade
A4: 2026-04-01
A5: Revised By: ANC Proposal Engine
C7: Linked Margin Assignment
C8: Install Margin | D8: 0.15
C9: Electrical Margin | D9: 0.15
C10: ANC Margin | D10: 0.15
C11: Engineering and Permits | D11: 0.15
B15: T4-B1 (6-9)
B16: Height | C16: Width | D16: Total Sq. Ft | E16: QTY
B17: 7.87 | C17: 8.66 | D17: 272.62 | E17: 4
B19: Structural Materials: | C19: Subcontractor 1 | D19: Subcontractor 2 | E19: Subcontractor 3 | F19: Selected | G19: Additional Contingency | I19: Total Cost | J19: Install Margin | K19: Selling Price
B20: FABRICATE PRIMARY STEEL | C20: 0 | D20: 0 | E20: 0 | F20: 0 | G20: 0 | I20: =SUM(C20:G20) -> 0 | J20: =$D$8 -> 0.15 | K20: =I20/(1-J20) -> 0
B21: SUPPLY AND INSTALL PRIMARY PLYWOOD | C21: 0 | D21: 0 | E21: 0 | F21: 0 | G21: 0 | I21: =SUM(C21:G21) -> 0 | J21: =$D$8 -> 0.15 | K21: =I21/(1-J21) -> 0
B22: FABRICATE SECONDARY STEEL SUBSTRUCTURE | C22: 4995 | D22: 0 | E22: 0 | F22: 0 | G22: 0 | I22: =SUM(C22:G22) -> 4995 | J22: =$D$8 -> 0.15 | K22: =I22/(1-J22) -> 5876.47
B23: FABRICATE CLADDING AND TRIM | C23: 0 | D23: 0 | E23: 0 | F23: 0 | G23: 0 | I23: =SUM(C23:G23) -> 0 | J23: =$D$8 -> 0.15 | K23: =I23/(1-J23) -> 0
B24: OTHER SCOPE ITEM | C24: 0 | D24: 0 | E24: 0 | F24: 0 | G24: 0 | I24: =SUM(C24:G24) -> 0 | J24: =$D$8 -> 0.15 | K24: =I24/(1-J24) -> 0
B25: OTHER SCOPE ITEM | C25: 0 | D25: 0 | E25: 0 | F25: 0 | G25: 0 | I25: =SUM(C25:G25) -> 0 | J25: =$D$8 -> 0.15 | K25: =I25/(1-J25) -> 0
B26: SUBTOTAL | I26: =SUM(I20:I25) -> 4995 | K26: =SUM(K20:K25) -> 5876.47
B28: Structural Labor and LED Installation | C28: Subcontractor 1 | D28: Subcontractor 2 | E28: Subcontractor 3 | F28: Selected | G28: Additional Contingency | I28: Total Cost | J28: Install Margin | K28: Selling Price
B29: REMOVAL AND DISPOSAL | C29: 0 | D29: 0 | E29: 0 | F29: 0 | G29: 0 | I29: =SUM(C29:G29) -> 0 | J29: =$D$8 -> 0.15 | K29: =I29/(1-J29) -> 0
B30: INSTALL SECONDARY STEEL SUBSTRUCTURE | C30: 0 | D30: 0 | E30: 0 | F30: 0 | G30: 0 | I30: =SUM(C30:G30) -> 0 | J30: =$D$8 -> 0.15 | K30: =I30/(1-J30) -> 0
B31: INSTALL LED DISPLAYS | C31: 20812.5 | D31: 0 | E31: 0 | F31: 0 | G31: 0 | I31: =SUM(C31:G31) -> 20812.5 | J31: =$D$8 -> 0.15 | K31: =I31/(1-J31) -> 24485.29
B32: INSTALL CLADDING AND TRIM | C32: 0 | D32: 0 | E32: 0 | F32: 0 | G32: 0 | I32: =SUM(C32:G32) -> 0 | J32: =$D$8 -> 0.15 | K32: =I32/(1-J32) -> 0
B33: HEAVY EQUIPMENT | C33: 0 | D33: 0 | E33: 0 | F33: 0 | G33: 0 | I33: =SUM(C33:G33) -> 0 | J33: =$D$8 -> 0.15 | K33: =I33/(1-J33) -> 0
B34: PM/GENERAL CONDITIONS/TRAVEL | C34: 20882.35 | D34: 0 | E34: 0 | F34: 0 | G34: 0 | I34: =SUM(C34:G34) -> 20882.35 | J34: =$D$8 -> 0.15 | K34: =I34/(1-J34) -> 24567.47
B35: SUBTOTAL | I35: =SUM(I29:I34) -> 41694.85 | K35: =SUM(K29:K34) -> 49052.76
B37: Electrical and Data - Materials and Subcontracting | C37: Subcontractor 1 | D37: Subcontractor 2 | E37: Subcontractor 3 | F37: Selected | G37: Additional Contingency | I37: Total Cost | J37: Install Margin | K37: Selling Price
B38: ELECTRICAL MATERIALS | C38: 20812.5 | D38: 0 | E38: 0 | F38: 0 | G38: 0 | I38: =SUM(C38:G38) -> 20812.5 | J38: =$D$9 -> 0.15 | K38: =I38/(1-J38) -> 24485.29
B39: DATA MATERIALS | C39: 0 | D39: 0 | E39: 0 | F39: 0 | G39: 0 | I39: =SUM(C39:G39) -> 0 | J39: =$D$9 -> 0.15 | K39: =I39/(1-J39) -> 0
B40: ELECTRICAL LABOR | C40: 0 | D40: 0 | E40: 0 | F40: 0 | G40: 0 | I40: =SUM(C40:G40) -> 0 | J40: =$D$9 -> 0.15 | K40: =I40/(1-J40) -> 0
B41: DATA LABOR | C41: 0 | D41: 0 | E41: 0 | F41: 0 | G41: 0 | I41: =SUM(C41:G41) -> 0 | J41: =$D$9 -> 0.15 | K41: =I41/(1-J41) -> 0
B42: SUB PANEL | C42: 0 | D42: 0 | E42: 0 | F42: 0 | G42: 0 | I42: =SUM(C42:G42) -> 0 | J42: =$D$9 -> 0.15 | K42: =I42/(1-J42) -> 0
B43: MISC | C43: 0 | D43: 0 | E43: 0 | F43: 0 | G43: 0 | I43: =SUM(C43:G43) -> 0 | J43: =$D$9 -> 0.15 | K43: =I43/(1-J43) -> 0
B44: SUBTOTAL | I44: =SUM(I38:I43) -> 20812.5 | K44: =SUM(K38:K43) -> 24485.29
B46: Submittals, Engineering, and Permits | C46: Subcontractor 1 | D46: Subcontractor 2 | E46: Subcontractor 3 | F46: Selected | G46: Additional Contingency | I46: Total Cost | J46: Install Margin | K46: Selling Price
B47: STRUCTURAL ENGINEERING | C47: 4705.88 | D47: 0 | E47: 0 | F47: 0 | G47: 0 | I47: =SUM(C47:G47) -> 4705.88 | J47: =$D$11 -> 0.15 | K47: =I47/(1-J47) -> 5536.33
B48: STRUCTURAL CERTIFICATION | C48: 0 | D48: 0 | E48: 0 | F48: 0 | G48: 0 | I48: =SUM(C48:G48) -> 0 | J48: =$D$11 -> 0.15 | K48: =I48/(1-J48) -> 0
B49: ELECTRICAL ENGINEERING | C49: 0 | D49: 0 | E49: 0 | F49: 0 | G49: 0 | I49: =SUM(C49:G49) -> 0 | J49: =$D$11 -> 0.15 | K49: =I49/(1-J49) -> 0
B50: ELECTRICAL CERTIFICATION | C50: 0 | D50: 0 | E50: 0 | F50: 0 | G50: 0 | I50: =SUM(C50:G50) -> 0 | J50: =$D$11 -> 0.15 | K50: =I50/(1-J50) -> 0
B51: PERMITS | C51: 0 | D51: 0 | E51: 0 | F51: 0 | G51: 0 | I51: =SUM(C51:G51) -> 0 | J51: =$D$11 -> 0.15 | K51: =I51/(1-J51) -> 0
B52: SUBTOTAL | I52: =SUM(I47:I51) -> 4705.88 | K52: =SUM(K47:K51) -> 5536.33
B54: ZONE GRAND TOTAL | I54: =I26+I35+I44+I52 -> 154994 | K54: =K26+K35+K44+K52 -> 179138.59

Sheet T4-B2 (10-18) - Install
A3: Project Name: WTC Digital Signage Upgrade
A4: 2026-04-01
A5: Revised By: ANC Proposal Engine
C7: Linked Margin Assignment
C8: Install Margin | D8: 0.15
C9: Electrical Margin | D9: 0.15
C10: ANC Margin | D10: 0.15
C11: Engineering and Permits | D11: 0.15
B15: T4-B2 (10-18)
B16: Height | C16: Width | D16: Total Sq. Ft | E16: QTY
B17: 7.87 | C17: 8.66 | D17: 613.39 | E17: 9
B19: Structural Materials: | C19: Subcontractor 1 | D19: Subcontractor 2 | E19: Subcontractor 3 | F19: Selected | G19: Additional Contingency | I19: Total Cost | J19: Install Margin | K19: Selling Price
B20: FABRICATE PRIMARY STEEL | C20: 0 | D20: 0 | E20: 0 | F20: 0 | G20: 0 | I20: =SUM(C20:G20) -> 0 | J20: =$D$8 -> 0.15 | K20: =I20/(1-J20) -> 0
B21: SUPPLY AND INSTALL PRIMARY PLYWOOD | C21: 0 | D21: 0 | E21: 0 | F21: 0 | G21: 0 | I21: =SUM(C21:G21) -> 0 | J21: =$D$8 -> 0.15 | K21: =I21/(1-J21) -> 0
B22: FABRICATE SECONDARY STEEL SUBSTRUCTURE | C22: 11238.75 | D22: 0 | E22: 0 | F22: 0 | G22: 0 | I22: =SUM(C22:G22) -> 11238.75 | J22: =$D$8 -> 0.15 | K22: =I22/(1-J22) -> 13222.06
B23: FABRICATE CLADDING AND TRIM | C23: 0 | D23: 0 | E23: 0 | F23: 0 | G23: 0 | I23: =SUM(C23:G23) -> 0 | J23: =$D$8 -> 0.15 | K23: =I23/(1-J23) -> 0
B24: OTHER SCOPE ITEM | C24: 0 | D24: 0 | E24: 0 | F24: 0 | G24: 0 | I24: =SUM(C24:G24) -> 0 | J24: =$D$8 -> 0.15 | K24: =I24/(1-J24) -> 0
B25: OTHER SCOPE ITEM | C25: 0 | D25: 0 | E25: 0 | F25: 0 | G25: 0 | I25: =SUM(C25:G25) -> 0 | J25: =$D$8 -> 0.15 | K25: =I25/(1-J25) -> 0
B26: SUBTOTAL | I26: =SUM(I20:I25) -> 11238.75 | K26: =SUM(K20:K25) -> 13222.06
B28: Structural Labor and LED Installation | C28: Subcontractor 1 | D28: Subcontractor 2 | E28: Subcontractor 3 | F28: Selected | G28: Additional Contingency | I28: Total Cost | J28: Install Margin | K28: Selling Price
B29: REMOVAL AND DISPOSAL | C29: 0 | D29: 0 | E29: 0 | F29: 0 | G29: 0 | I29: =SUM(C29:G29) -> 0 | J29: =$D$8 -> 0.15 | K29: =I29/(1-J29) -> 0
B30: INSTALL SECONDARY STEEL SUBSTRUCTURE | C30: 0 | D30: 0 | E30: 0 | F30: 0 | G30: 0 | I30: =SUM(C30:G30) -> 0 | J30: =$D$8 -> 0.15 | K30: =I30/(1-J30) -> 0
B31: INSTALL LED DISPLAYS | C31: 46828.13 | D31: 0 | E31: 0 | F31: 0 | G31: 0 | I31: =SUM(C31:G31) -> 46828.13 | J31: =$D$8 -> 0.15 | K31: =I31/(1-J31) -> 55091.92
B32: INSTALL CLADDING AND TRIM | C32: 0 | D32: 0 | E32: 0 | F32: 0 | G32: 0 | I32: =SUM(C32:G32) -> 0 | J32: =$D$8 -> 0.15 | K32: =I32/(1-J32) -> 0
B33: HEAVY EQUIPMENT | C33: 0 | D33: 0 | E33: 0 | F33: 0 | G33: 0 | I33: =SUM(C33:G33) -> 0 | J33: =$D$8 -> 0.15 | K33: =I33/(1-J33) -> 0
B34: PM/GENERAL CONDITIONS/TRAVEL | C34: 20882.35 | D34: 0 | E34: 0 | F34: 0 | G34: 0 | I34: =SUM(C34:G34) -> 20882.35 | J34: =$D$8 -> 0.15 | K34: =I34/(1-J34) -> 24567.47
B35: SUBTOTAL | I35: =SUM(I29:I34) -> 67710.48 | K35: =SUM(K29:K34) -> 79659.39
B37: Electrical and Data - Materials and Subcontracting | C37: Subcontractor 1 | D37: Subcontractor 2 | E37: Subcontractor 3 | F37: Selected | G37: Additional Contingency | I37: Total Cost | J37: Install Margin | K37: Selling Price
B38: ELECTRICAL MATERIALS | C38: 46828.13 | D38: 0 | E38: 0 | F38: 0 | G38: 0 | I38: =SUM(C38:G38) -> 46828.13 | J38: =$D$9 -> 0.15 | K38: =I38/(1-J38) -> 55091.92
B39: DATA MATERIALS | C39: 0 | D39: 0 | E39: 0 | F39: 0 | G39: 0 | I39: =SUM(C39:G39) -> 0 | J39: =$D$9 -> 0.15 | K39: =I39/(1-J39) -> 0
B40: ELECTRICAL LABOR | C40: 0 | D40: 0 | E40: 0 | F40: 0 | G40: 0 | I40: =SUM(C40:G40) -> 0 | J40: =$D$9 -> 0.15 | K40: =I40/(1-J40) -> 0
B41: DATA LABOR | C41: 0 | D41: 0 | E41: 0 | F41: 0 | G41: 0 | I41: =SUM(C41:G41) -> 0 | J41: =$D$9 -> 0.15 | K41: =I41/(1-J41) -> 0
B42: SUB PANEL | C42: 0 | D42: 0 | E42: 0 | F42: 0 | G42: 0 | I42: =SUM(C42:G42) -> 0 | J42: =$D$9 -> 0.15 | K42: =I42/(1-J42) -> 0
B43: MISC | C43: 0 | D43: 0 | E43: 0 | F43: 0 | G43: 0 | I43: =SUM(C43:G43) -> 0 | J43: =$D$9 -> 0.15 | K43: =I43/(1-J43) -> 0
B44: SUBTOTAL | I44: =SUM(I38:I43) -> 46828.13 | K44: =SUM(K38:K43) -> 55091.92
B46: Submittals, Engineering, and Permits | C46: Subcontractor 1 | D46: Subcontractor 2 | E46: Subcontractor 3 | F46: Selected | G46: Additional Contingency | I46: Total Cost | J46: Install Margin | K46: Selling Price
B47: STRUCTURAL ENGINEERING | C47: 4705.88 | D47: 0 | E47: 0 | F47: 0 | G47: 0 | I47: =SUM(C47:G47) -> 4705.88 | J47: =$D$11 -> 0.15 | K47: =I47/(1-J47) -> 5536.33
B48: STRUCTURAL CERTIFICATION | C48: 0 | D48: 0 | E48: 0 | F48: 0 | G48: 0 | I48: =SUM(C48:G48) -> 0 | J48: =$D$11 -> 0.15 | K48: =I48/(1-J48) -> 0
B49: ELECTRICAL ENGINEERING | C49: 0 | D49: 0 | E49: 0 | F49: 0 | G49: 0 | I49: =SUM(C49:G49) -> 0 | J49: =$D$11 -> 0.15 | K49: =I49/(1-J49) -> 0
B50: ELECTRICAL CERTIFICATION | C50: 0 | D50: 0 | E50: 0 | F50: 0 | G50: 0 | I50: =SUM(C50:G50) -> 0 | J50: =$D$11 -> 0.15 | K50: =I50/(1-J50) -> 0
B51: PERMITS | C51: 0 | D51: 0 | E51: 0 | F51: 0 | G51: 0 | I51: =SUM(C51:G51) -> 0 | J51: =$D$11 -> 0.15 | K51: =I51/(1-J51) -> 0
B52: SUBTOTAL | I52: =SUM(I47:I51) -> 4705.88 | K52: =SUM(K47:K51) -> 5536.33
B54: ZONE GRAND TOTAL | I54: =I26+I35+I44+I52 -> 336138.67 | K54: =K26+K35+K44+K52 -> 388240.91

Sheet T4 Lobby Elevator - Install
A3: Project Name: WTC Digital Signage Upgrade
A4: 2026-04-01
A5: Revised By: ANC Proposal Engine
C7: Linked Margin Assignment
C8: Install Margin | D8: 0.15
C9: Electrical Margin | D9: 0.15
C10: ANC Margin | D10: 0.15
C11: Engineering and Permits | D11: 0.15
B15: T4 Lobby Elevator
B16: Height | C16: Width | D16: Total Sq. Ft | E16: QTY
B17: 71.6 | C17: 5.5 | D17: 393.8 | E17: 1
B19: Structural Materials: | C19: Subcontractor 1 | D19: Subcontractor 2 | E19: Subcontractor 3 | F19: Selected | G19: Additional Contingency | I19: Total Cost | J19: Install Margin | K19: Selling Price
B20: FABRICATE PRIMARY STEEL | C20: 0 | D20: 0 | E20: 0 | F20: 0 | G20: 0 | I20: =SUM(C20:G20) -> 0 | J20: =$D$8 -> 0.15 | K20: =I20/(1-J20) -> 0
B21: SUPPLY AND INSTALL PRIMARY PLYWOOD | C21: 0 | D21: 0 | E21: 0 | F21: 0 | G21: 0 | I21: =SUM(C21:G21) -> 0 | J21: =$D$8 -> 0.15 | K21: =I21/(1-J21) -> 0
B22: FABRICATE SECONDARY STEEL SUBSTRUCTURE | C22: 7222.5 | D22: 0 | E22: 0 | F22: 0 | G22: 0 | I22: =SUM(C22:G22) -> 7222.5 | J22: =$D$8 -> 0.15 | K22: =I22/(1-J22) -> 8497.06
B23: FABRICATE CLADDING AND TRIM | C23: 0 | D23: 0 | E23: 0 | F23: 0 | G23: 0 | I23: =SUM(C23:G23) -> 0 | J23: =$D$8 -> 0.15 | K23: =I23/(1-J23) -> 0
B24: OTHER SCOPE ITEM | C24: 0 | D24: 0 | E24: 0 | F24: 0 | G24: 0 | I24: =SUM(C24:G24) -> 0 | J24: =$D$8 -> 0.15 | K24: =I24/(1-J24) -> 0
B25: OTHER SCOPE ITEM | C25: 0 | D25: 0 | E25: 0 | F25: 0 | G25: 0 | I25: =SUM(C25:G25) -> 0 | J25: =$D$8 -> 0.15 | K25: =I25/(1-J25) -> 0
B26: SUBTOTAL | I26: =SUM(I20:I25) -> 7222.5 | K26: =SUM(K20:K25) -> 8497.06
B28: Structural Labor and LED Installation | C28: Subcontractor 1 | D28: Subcontractor 2 | E28: Subcontractor 3 | F28: Selected | G28: Additional Contingency | I28: Total Cost | J28: Install Margin | K28: Selling Price
B29: REMOVAL AND DISPOSAL | C29: 0 | D29: 0 | E29: 0 | F29: 0 | G29: 0 | I29: =SUM(C29:G29) -> 0 | J29: =$D$8 -> 0.15 | K29: =I29/(1-J29) -> 0
B30: INSTALL SECONDARY STEEL SUBSTRUCTURE | C30: 0 | D30: 0 | E30: 0 | F30: 0 | G30: 0 | I30: =SUM(C30:G30) -> 0 | J30: =$D$8 -> 0.15 | K30: =I30/(1-J30) -> 0
B31: INSTALL LED DISPLAYS | C31: 30093.75 | D31: 0 | E31: 0 | F31: 0 | G31: 0 | I31: =SUM(C31:G31) -> 30093.75 | J31: =$D$8 -> 0.15 | K31: =I31/(1-J31) -> 35404.41
B32: INSTALL CLADDING AND TRIM | C32: 0 | D32: 0 | E32: 0 | F32: 0 | G32: 0 | I32: =SUM(C32:G32) -> 0 | J32: =$D$8 -> 0.15 | K32: =I32/(1-J32) -> 0
B33: HEAVY EQUIPMENT | C33: 0 | D33: 0 | E33: 0 | F33: 0 | G33: 0 | I33: =SUM(C33:G33) -> 0 | J33: =$D$8 -> 0.15 | K33: =I33/(1-J33) -> 0
B34: PM/GENERAL CONDITIONS/TRAVEL | C34: 20882.35 | D34: 0 | E34: 0 | F34: 0 | G34: 0 | I34: =SUM(C34:G34) -> 20882.35 | J34: =$D$8 -> 0.15 | K34: =I34/(1-J34) -> 24567.47
B35: SUBTOTAL | I35: =SUM(I29:I34) -> 50976.1 | K35: =SUM(K29:K34) -> 59971.88
B37: Electrical and Data - Materials and Subcontracting | C37: Subcontractor 1 | D37: Subcontractor 2 | E37: Subcontractor 3 | F37: Selected | G37: Additional Contingency | I37: Total Cost | J37: Install Margin | K37: Selling Price
B38: ELECTRICAL MATERIALS | C38: 30093.75 | D38: 0 | E38: 0 | F38: 0 | G38: 0 | I38: =SUM(C38:G38) -> 30093.75 | J38: =$D$9 -> 0.15 | K38: =I38/(1-J38) -> 35404.41
B39: DATA MATERIALS | C39: 0 | D39: 0 | E39: 0 | F39: 0 | G39: 0 | I39: =SUM(C39:G39) -> 0 | J39: =$D$9 -> 0.15 | K39: =I39/(1-J39) -> 0
B40: ELECTRICAL LABOR | C40: 0 | D40: 0 | E40: 0 | F40: 0 | G40: 0 | I40: =SUM(C40:G40) -> 0 | J40: =$D$9 -> 0.15 | K40: =I40/(1-J40) -> 0
B41: DATA LABOR | C41: 0 | D41: 0 | E41: 0 | F41: 0 | G41: 0 | I41: =SUM(C41:G41) -> 0 | J41: =$D$9 -> 0.15 | K41: =I41/(1-J41) -> 0
B42: SUB PANEL | C42: 0 | D42: 0 | E42: 0 | F42: 0 | G42: 0 | I42: =SUM(C42:G42) -> 0 | J42: =$D$9 -> 0.15 | K42: =I42/(1-J42) -> 0
B43: MISC | C43: 0 | D43: 0 | E43: 0 | F43: 0 | G43: 0 | I43: =SUM(C43:G43) -> 0 | J43: =$D$9 -> 0.15 | K43: =I43/(1-J43) -> 0
B44: SUBTOTAL | I44: =SUM(I38:I43) -> 30093.75 | K44: =SUM(K38:K43) -> 35404.41
B46: Submittals, Engineering, and Permits | C46: Subcontractor 1 | D46: Subcontractor 2 | E46: Subcontractor 3 | F46: Selected | G46: Additional Contingency | I46: Total Cost | J46: Install Margin | K46: Selling Price
B47: STRUCTURAL ENGINEERING | C47: 4705.88 | D47: 0 | E47: 0 | F47: 0 | G47: 0 | I47: =SUM(C47:G47) -> 4705.88 | J47: =$D$11 -> 0.15 | K47: =I47/(1-J47) -> 5536.33
B48: STRUCTURAL CERTIFICATION | C48: 0 | D48: 0 | E48: 0 | F48: 0 | G48: 0 | I48: =SUM(C48:G48) -> 0 | J48: =$D$11 -> 0.15 | K48: =I48/(1-J48) -> 0
B49: ELECTRICAL ENGINEERING | C49: 0 | D49: 0 | E49: 0 | F49: 0 | G49: 0 | I49: =SUM(C49:G49) -> 0 | J49: =$D$11 -> 0.15 | K49: =I49/(1-J49) -> 0
B50: ELECTRICAL CERTIFICATION | C50: 0 | D50: 0 | E50: 0 | F50: 0 | G50: 0 | I50: =SUM(C50:G50) -> 0 | J50: =$D$11 -> 0.15 | K50: =I50/(1-J50) -> 0
B51: PERMITS | C51: 0 | D51: 0 | E51: 0 | F51: 0 | G51: 0 | I51: =SUM(C51:G51) -> 0 | J51: =$D$11 -> 0.15 | K51: =I51/(1-J51) -> 0
B52: SUBTOTAL | I52: =SUM(I47:I51) -> 4705.88 | K52: =SUM(K47:K51) -> 5536.33
B54: ZONE GRAND TOTAL | I54: =I26+I35+I44+I52 -> 232340.8 | K54: =K26+K35+K44+K52 -> 268709.18

Sheet T2-B1M Screen 20 - Install
A3: Project Name: WTC Digital Signage Upgrade
A4: 2026-04-01
A5: Revised By: ANC Proposal Engine
C7: Linked Margin Assignment
C8: Install Margin | D8: 0.15
C9: Electrical Margin | D9: 0.15
C10: ANC Margin | D10: 0.15
C11: Engineering and Permits | D11: 0.15
B15: T2-B1M Screen 20
B16: Height | C16: Width | D16: Total Sq. Ft | E16: QTY
B17: 7.91 | C17: 16.5 | D17: 130.52 | E17: 1
B19: Structural Materials: | C19: Subcontractor 1 | D19: Subcontractor 2 | E19: Subcontractor 3 | F19: Selected | G19: Additional Contingency | I19: Total Cost | J19: Install Margin | K19: Selling Price
B20: FABRICATE PRIMARY STEEL | C20: 0 | D20: 0 | E20: 0 | F20: 0 | G20: 0 | I20: =SUM(C20:G20) -> 0 | J20: =$D$8 -> 0.15 | K20: =I20/(1-J20) -> 0
B21: SUPPLY AND INSTALL PRIMARY PLYWOOD | C21: 0 | D21: 0 | E21: 0 | F21: 0 | G21: 0 | I21: =SUM(C21:G21) -> 0 | J21: =$D$8 -> 0.15 | K21: =I21/(1-J21) -> 0
B22: FABRICATE SECONDARY STEEL SUBSTRUCTURE | C22: 2392.5 | D22: 0 | E22: 0 | F22: 0 | G22: 0 | I22: =SUM(C22:G22) -> 2392.5 | J22: =$D$8 -> 0.15 | K22: =I22/(1-J22) -> 2814.71
B23: FABRICATE CLADDING AND TRIM | C23: 0 | D23: 0 | E23: 0 | F23: 0 | G23: 0 | I23: =SUM(C23:G23) -> 0 | J23: =$D$8 -> 0.15 | K23: =I23/(1-J23) -> 0
B24: OTHER SCOPE ITEM | C24: 0 | D24: 0 | E24: 0 | F24: 0 | G24: 0 | I24: =SUM(C24:G24) -> 0 | J24: =$D$8 -> 0.15 | K24: =I24/(1-J24) -> 0
B25: OTHER SCOPE ITEM | C25: 0 | D25: 0 | E25: 0 | F25: 0 | G25: 0 | I25: =SUM(C25:G25) -> 0 | J25: =$D$8 -> 0.15 | K25: =I25/(1-J25) -> 0
B26: SUBTOTAL | I26: =SUM(I20:I25) -> 2392.5 | K26: =SUM(K20:K25) -> 2814.71
B28: Structural Labor and LED Installation | C28: Subcontractor 1 | D28: Subcontractor 2 | E28: Subcontractor 3 | F28: Selected | G28: Additional Contingency | I28: Total Cost | J28: Install Margin | K28: Selling Price
B29: REMOVAL AND DISPOSAL | C29: 0 | D29: 0 | E29: 0 | F29: 0 | G29: 0 | I29: =SUM(C29:G29) -> 0 | J29: =$D$8 -> 0.15 | K29: =I29/(1-J29) -> 0
B30: INSTALL SECONDARY STEEL SUBSTRUCTURE | C30: 0 | D30: 0 | E30: 0 | F30: 0 | G30: 0 | I30: =SUM(C30:G30) -> 0 | J30: =$D$8 -> 0.15 | K30: =I30/(1-J30) -> 0
B31: INSTALL LED DISPLAYS | C31: 9968.75 | D31: 0 | E31: 0 | F31: 0 | G31: 0 | I31: =SUM(C31:G31) -> 9968.75 | J31: =$D$8 -> 0.15 | K31: =I31/(1-J31) -> 11727.94
B32: INSTALL CLADDING AND TRIM | C32: 0 | D32: 0 | E32: 0 | F32: 0 | G32: 0 | I32: =SUM(C32:G32) -> 0 | J32: =$D$8 -> 0.15 | K32: =I32/(1-J32) -> 0
B33: HEAVY EQUIPMENT | C33: 0 | D33: 0 | E33: 0 | F33: 0 | G33: 0 | I33: =SUM(C33:G33) -> 0 | J33: =$D$8 -> 0.15 | K33: =I33/(1-J33) -> 0
B34: PM/GENERAL CONDITIONS/TRAVEL | C34: 20882.35 | D34: 0 | E34: 0 | F34: 0 | G34: 0 | I34: =SUM(C34:G34) -> 20882.35 | J34: =$D$8 -> 0.15 | K34: =I34/(1-J34) -> 24567.47
B35: SUBTOTAL | I35: =SUM(I29:I34) -> 30851.1 | K35: =SUM(K29:K34) -> 36295.41
B37: Electrical and Data - Materials and Subcontracting | C37: Subcontractor 1 | D37: Subcontractor 2 | E37: Subcontractor 3 | F37: Selected | G37: Additional Contingency | I37: Total Cost | J37: Install Margin | K37: Selling Price
B38: ELECTRICAL MATERIALS | C38: 9968.75 | D38: 0 | E38: 0 | F38: 0 | G38: 0 | I38: =SUM(C38:G38) -> 9968.75 | J38: =$D$9 -> 0.15 | K38: =I38/(1-J38) -> 11727.94
B39: DATA MATERIALS | C39: 0 | D39: 0 | E39: 0 | F39: 0 | G39: 0 | I39: =SUM(C39:G39) -> 0 | J39: =$D$9 -> 0.15 | K39: =I39/(1-J39) -> 0
B40: ELECTRICAL LABOR | C40: 0 | D40: 0 | E40: 0 | F40: 0 | G40: 0 | I40: =SUM(C40:G40) -> 0 | J40: =$D$9 -> 0.15 | K40: =I40/(1-J40) -> 0
B41: DATA LABOR | C41: 0 | D41: 0 | E41: 0 | F41: 0 | G41: 0 | I41: =SUM(C41:G41) -> 0 | J41: =$D$9 -> 0.15 | K41: =I41/(1-J41) -> 0
B42: SUB PANEL | C42: 0 | D42: 0 | E42: 0 | F42: 0 | G42: 0 | I42: =SUM(C42:G42) -> 0 | J42: =$D$9 -> 0.15 | K42: =I42/(1-J42) -> 0
B43: MISC | C43: 0 | D43: 0 | E43: 0 | F43: 0 | G43: 0 | I43: =SUM(C43:G43) -> 0 | J43: =$D$9 -> 0.15 | K43: =I43/(1-J43) -> 0
B44: SUBTOTAL | I44: =SUM(I38:I43) -> 9968.75 | K44: =SUM(K38:K43) -> 11727.94
B46: Submittals, Engineering, and Permits | C46: Subcontractor 1 | D46: Subcontractor 2 | E46: Subcontractor 3 | F46: Selected | G46: Additional Contingency | I46: Total Cost | J46: Install Margin | K46: Selling Price
B47: STRUCTURAL ENGINEERING | C47: 4705.88 | D47: 0 | E47: 0 | F47: 0 | G47: 0 | I47: =SUM(C47:G47) -> 4705.88 | J47: =$D$11 -> 0.15 | K47: =I47/(1-J47) -> 5536.33
B48: STRUCTURAL CERTIFICATION | C48: 0 | D48: 0 | E48: 0 | F48: 0 | G48: 0 | I48: =SUM(C48:G48) -> 0 | J48: =$D$11 -> 0.15 | K48: =I48/(1-J48) -> 0
B49: ELECTRICAL ENGINEERING | C49: 0 | D49: 0 | E49: 0 | F49: 0 | G49: 0 | I49: =SUM(C49:G49) -> 0 | J49: =$D$11 -> 0.15 | K49: =I49/(1-J49) -> 0
B50: ELECTRICAL CERTIFICATION | C50: 0 | D50: 0 | E50: 0 | F50: 0 | G50: 0 | I50: =SUM(C50:G50) -> 0 | J50: =$D$11 -> 0.15 | K50: =I50/(1-J50) -> 0
B51: PERMITS | C51: 0 | D51: 0 | E51: 0 | F51: 0 | G51: 0 | I51: =SUM(C51:G51) -> 0 | J51: =$D$11 -> 0.15 | K51: =I51/(1-J51) -> 0
B52: SUBTOTAL | I52: =SUM(I47:I51) -> 4705.88 | K52: =SUM(K47:K51) -> 5536.33
B54: ZONE GRAND TOTAL | I54: =I26+I35+I44+I52 -> 87790.23 | K54: =K26+K35+K44+K52 -> 101747.09

Sheet T2-B1M Screen 21 - Install
A3: Project Name: WTC Digital Signage Upgrade
A4: 2026-04-01
A5: Revised By: ANC Proposal Engine
C7: Linked Margin Assignment
C8: Install Margin | D8: 0.15
C9: Electrical Margin | D9: 0.15
C10: ANC Margin | D10: 0.15
C11: Engineering and Permits | D11: 0.15
B15: T2-B1M Screen 21
B16: Height | C16: Width | D16: Total Sq. Ft | E16: QTY
B17: 7.91 | C17: 11.83 | D17: 93.58 | E17: 1
B19: Structural Materials: | C19: Subcontractor 1 | D19: Subcontractor 2 | E19: Subcontractor 3 | F19: Selected | G19: Additional Contingency | I19: Total Cost | J19: Install Margin | K19: Selling Price
B20: FABRICATE PRIMARY STEEL | C20: 0 | D20: 0 | E20: 0 | F20: 0 | G20: 0 | I20: =SUM(C20:G20) -> 0 | J20: =$D$8 -> 0.15 | K20: =I20/(1-J20) -> 0
B21: SUPPLY AND INSTALL PRIMARY PLYWOOD | C21: 0 | D21: 0 | E21: 0 | F21: 0 | G21: 0 | I21: =SUM(C21:G21) -> 0 | J21: =$D$8 -> 0.15 | K21: =I21/(1-J21) -> 0
B22: FABRICATE SECONDARY STEEL SUBSTRUCTURE | C22: 1713.75 | D22: 0 | E22: 0 | F22: 0 | G22: 0 | I22: =SUM(C22:G22) -> 1713.75 | J22: =$D$8 -> 0.15 | K22: =I22/(1-J22) -> 2016.18
B23: FABRICATE CLADDING AND TRIM | C23: 0 | D23: 0 | E23: 0 | F23: 0 | G23: 0 | I23: =SUM(C23:G23) -> 0 | J23: =$D$8 -> 0.15 | K23: =I23/(1-J23) -> 0
B24: OTHER SCOPE ITEM | C24: 0 | D24: 0 | E24: 0 | F24: 0 | G24: 0 | I24: =SUM(C24:G24) -> 0 | J24: =$D$8 -> 0.15 | K24: =I24/(1-J24) -> 0
B25: OTHER SCOPE ITEM | C25: 0 | D25: 0 | E25: 0 | F25: 0 | G25: 0 | I25: =SUM(C25:G25) -> 0 | J25: =$D$8 -> 0.15 | K25: =I25/(1-J25) -> 0
B26: SUBTOTAL | I26: =SUM(I20:I25) -> 1713.75 | K26: =SUM(K20:K25) -> 2016.18
B28: Structural Labor and LED Installation | C28: Subcontractor 1 | D28: Subcontractor 2 | E28: Subcontractor 3 | F28: Selected | G28: Additional Contingency | I28: Total Cost | J28: Install Margin | K28: Selling Price
B29: REMOVAL AND DISPOSAL | C29: 0 | D29: 0 | E29: 0 | F29: 0 | G29: 0 | I29: =SUM(C29:G29) -> 0 | J29: =$D$8 -> 0.15 | K29: =I29/(1-J29) -> 0
B30: INSTALL SECONDARY STEEL SUBSTRUCTURE | C30: 0 | D30: 0 | E30: 0 | F30: 0 | G30: 0 | I30: =SUM(C30:G30) -> 0 | J30: =$D$8 -> 0.15 | K30: =I30/(1-J30) -> 0
B31: INSTALL LED DISPLAYS | C31: 7140.63 | D31: 0 | E31: 0 | F31: 0 | G31: 0 | I31: =SUM(C31:G31) -> 7140.63 | J31: =$D$8 -> 0.15 | K31: =I31/(1-J31) -> 8400.74
B32: INSTALL CLADDING AND TRIM | C32: 0 | D32: 0 | E32: 0 | F32: 0 | G32: 0 | I32: =SUM(C32:G32) -> 0 | J32: =$D$8 -> 0.15 | K32: =I32/(1-J32) -> 0
B33: HEAVY EQUIPMENT | C33: 0 | D33: 0 | E33: 0 | F33: 0 | G33: 0 | I33: =SUM(C33:G33) -> 0 | J33: =$D$8 -> 0.15 | K33: =I33/(1-J33) -> 0
B34: PM/GENERAL CONDITIONS/TRAVEL | C34: 20882.35 | D34: 0 | E34: 0 | F34: 0 | G34: 0 | I34: =SUM(C34:G34) -> 20882.35 | J34: =$D$8 -> 0.15 | K34: =I34/(1-J34) -> 24567.47
B35: SUBTOTAL | I35: =SUM(I29:I34) -> 28022.98 | K35: =SUM(K29:K34) -> 32968.21
B37: Electrical and Data - Materials and Subcontracting | C37: Subcontractor 1 | D37: Subcontractor 2 | E37: Subcontractor 3 | F37: Selected | G37: Additional Contingency | I37: Total Cost | J37: Install Margin | K37: Selling Price
B38: ELECTRICAL MATERIALS | C38: 7140.63 | D38: 0 | E38: 0 | F38: 0 | G38: 0 | I38: =SUM(C38:G38) -> 7140.63 | J38: =$D$9 -> 0.15 | K38: =I38/(1-J38) -> 8400.74
B39: DATA MATERIALS | C39: 0 | D39: 0 | E39: 0 | F39: 0 | G39: 0 | I39: =SUM(C39:G39) -> 0 | J39: =$D$9 -> 0.15 | K39: =I39/(1-J39) -> 0
B40: ELECTRICAL LABOR | C40: 0 | D40: 0 | E40: 0 | F40: 0 | G40: 0 | I40: =SUM(C40:G40) -> 0 | J40: =$D$9 -> 0.15 | K40: =I40/(1-J40) -> 0
B41: DATA LABOR | C41: 0 | D41: 0 | E41: 0 | F41: 0 | G41: 0 | I41: =SUM(C41:G41) -> 0 | J41: =$D$9 -> 0.15 | K41: =I41/(1-J41) -> 0
B42: SUB PANEL | C42: 0 | D42: 0 | E42: 0 | F42: 0 | G42: 0 | I42: =SUM(C42:G42) -> 0 | J42: =$D$9 -> 0.15 | K42: =I42/(1-J42) -> 0
B43: MISC | C43: 0 | D43: 0 | E43: 0 | F43: 0 | G43: 0 | I43: =SUM(C43:G43) -> 0 | J43: =$D$9 -> 0.15 | K43: =I43/(1-J43) -> 0
B44: SUBTOTAL | I44: =SUM(I38:I43) -> 7140.63 | K44: =SUM(K38:K43) -> 8400.74
B46: Submittals, Engineering, and Permits | C46: Subcontractor 1 | D46: Subcontractor 2 | E46: Subcontractor 3 | F46: Selected | G46: Additional Contingency | I46: Total Cost | J46: Install Margin | K46: Selling Price
B47: STRUCTURAL ENGINEERING | C47: 4705.88 | D47: 0 | E47: 0 | F47: 0 | G47: 0 | I47: =SUM(C47:G47) -> 4705.88 | J47: =$D$11 -> 0.15 | K47: =I47/(1-J47) -> 5536.33
B48: STRUCTURAL CERTIFICATION | C48: 0 | D48: 0 | E48: 0 | F48: 0 | G48: 0 | I48: =SUM(C48:G48) -> 0 | J48: =$D$11 -> 0.15 | K48: =I48/(1-J48) -> 0
B49: ELECTRICAL ENGINEERING | C49: 0 | D49: 0 | E49: 0 | F49: 0 | G49: 0 | I49: =SUM(C49:G49) -> 0 | J49: =$D$11 -> 0.15 | K49: =I49/(1-J49) -> 0
B50: ELECTRICAL CERTIFICATION | C50: 0 | D50: 0 | E50: 0 | F50: 0 | G50: 0 | I50: =SUM(C50:G50) -> 0 | J50: =$D$11 -> 0.15 | K50: =I50/(1-J50) -> 0
B51: PERMITS | C51: 0 | D51: 0 | E51: 0 | F51: 0 | G51: 0 | I51: =SUM(C51:G51) -> 0 | J51: =$D$11 -> 0.15 | K51: =I51/(1-J51) -> 0
B52: SUBTOTAL | I52: =SUM(I47:I51) -> 4705.88 | K52: =SUM(K47:K51) -> 5536.33
B54: ZONE GRAND TOTAL | I54: =I26+I35+I44+I52 -> 70297.95 | K54: =K26+K35+K44+K52 -> 81602.53

Sheet T2-B1M Screen 22 - Install
A3: Project Name: WTC Digital Signage Upgrade
A4: 2026-04-01
A5: Revised By: ANC Proposal Engine
C7: Linked Margin Assignment
C8: Install Margin | D8: 0.15
C9: Electrical Margin | D9: 0.15
C10: ANC Margin | D10: 0.15
C11: Engineering and Permits | D11: 0.15
B15: T2-B1M Screen 22
B16: Height | C16: Width | D16: Total Sq. Ft | E16: QTY
B17: 7.91 | C17: 7.91 | D17: 62.57 | E17: 1
B19: Structural Materials: | C19: Subcontractor 1 | D19: Subcontractor 2 | E19: Subcontractor 3 | F19: Selected | G19: Additional Contingency | I19: Total Cost | J19: Install Margin | K19: Selling Price
B20: FABRICATE PRIMARY STEEL | C20: 0 | D20: 0 | E20: 0 | F20: 0 | G20: 0 | I20: =SUM(C20:G20) -> 0 | J20: =$D$8 -> 0.15 | K20: =I20/(1-J20) -> 0
B21: SUPPLY AND INSTALL PRIMARY PLYWOOD | C21: 0 | D21: 0 | E21: 0 | F21: 0 | G21: 0 | I21: =SUM(C21:G21) -> 0 | J21: =$D$8 -> 0.15 | K21: =I21/(1-J21) -> 0
B22: FABRICATE SECONDARY STEEL SUBSTRUCTURE | C22: 1147.5 | D22: 0 | E22: 0 | F22: 0 | G22: 0 | I22: =SUM(C22:G22) -> 1147.5 | J22: =$D$8 -> 0.15 | K22: =I22/(1-J22) -> 1350
B23: FABRICATE CLADDING AND TRIM | C23: 0 | D23: 0 | E23: 0 | F23: 0 | G23: 0 | I23: =SUM(C23:G23) -> 0 | J23: =$D$8 -> 0.15 | K23: =I23/(1-J23) -> 0
B24: OTHER SCOPE ITEM | C24: 0 | D24: 0 | E24: 0 | F24: 0 | G24: 0 | I24: =SUM(C24:G24) -> 0 | J24: =$D$8 -> 0.15 | K24: =I24/(1-J24) -> 0
B25: OTHER SCOPE ITEM | C25: 0 | D25: 0 | E25: 0 | F25: 0 | G25: 0 | I25: =SUM(C25:G25) -> 0 | J25: =$D$8 -> 0.15 | K25: =I25/(1-J25) -> 0
B26: SUBTOTAL | I26: =SUM(I20:I25) -> 1147.5 | K26: =SUM(K20:K25) -> 1350
B28: Structural Labor and LED Installation | C28: Subcontractor 1 | D28: Subcontractor 2 | E28: Subcontractor 3 | F28: Selected | G28: Additional Contingency | I28: Total Cost | J28: Install Margin | K28: Selling Price
B29: REMOVAL AND DISPOSAL | C29: 0 | D29: 0 | E29: 0 | F29: 0 | G29: 0 | I29: =SUM(C29:G29) -> 0 | J29: =$D$8 -> 0.15 | K29: =I29/(1-J29) -> 0
B30: INSTALL SECONDARY STEEL SUBSTRUCTURE | C30: 0 | D30: 0 | E30: 0 | F30: 0 | G30: 0 | I30: =SUM(C30:G30) -> 0 | J30: =$D$8 -> 0.15 | K30: =I30/(1-J30) -> 0
B31: INSTALL LED DISPLAYS | C31: 4781.25 | D31: 0 | E31: 0 | F31: 0 | G31: 0 | I31: =SUM(C31:G31) -> 4781.25 | J31: =$D$8 -> 0.15 | K31: =I31/(1-J31) -> 5625
B32: INSTALL CLADDING AND TRIM | C32: 0 | D32: 0 | E32: 0 | F32: 0 | G32: 0 | I32: =SUM(C32:G32) -> 0 | J32: =$D$8 -> 0.15 | K32: =I32/(1-J32) -> 0
B33: HEAVY EQUIPMENT | C33: 0 | D33: 0 | E33: 0 | F33: 0 | G33: 0 | I33: =SUM(C33:G33) -> 0 | J33: =$D$8 -> 0.15 | K33: =I33/(1-J33) -> 0
B34: PM/GENERAL CONDITIONS/TRAVEL | C34: 20882.35 | D34: 0 | E34: 0 | F34: 0 | G34: 0 | I34: =SUM(C34:G34) -> 20882.35 | J34: =$D$8 -> 0.15 | K34: =I34/(1-J34) -> 24567.47
B35: SUBTOTAL | I35: =SUM(I29:I34) -> 25663.6 | K35: =SUM(K29:K34) -> 30192.47
B37: Electrical and Data - Materials and Subcontracting | C37: Subcontractor 1 | D37: Subcontractor 2 | E37: Subcontractor 3 | F37: Selected | G37: Additional Contingency | I37: Total Cost | J37: Install Margin | K37: Selling Price
B38: ELECTRICAL MATERIALS | C38: 4781.25 | D38: 0 | E38: 0 | F38: 0 | G38: 0 | I38: =SUM(C38:G38) -> 4781.25 | J38: =$D$9 -> 0.15 | K38: =I38/(1-J38) -> 5625
B39: DATA MATERIALS | C39: 0 | D39: 0 | E39: 0 | F39: 0 | G39: 0 | I39: =SUM(C39:G39) -> 0 | J39: =$D$9 -> 0.15 | K39: =I39/(1-J39) -> 0
B40: ELECTRICAL LABOR | C40: 0 | D40: 0 | E40: 0 | F40: 0 | G40: 0 | I40: =SUM(C40:G40) -> 0 | J40: =$D$9 -> 0.15 | K40: =I40/(1-J40) -> 0
B41: DATA LABOR | C41: 0 | D41: 0 | E41: 0 | F41: 0 | G41: 0 | I41: =SUM(C41:G41) -> 0 | J41: =$D$9 -> 0.15 | K41: =I41/(1-J41) -> 0
B42: SUB PANEL | C42: 0 | D42: 0 | E42: 0 | F42: 0 | G42: 0 | I42: =SUM(C42:G42) -> 0 | J42: =$D$9 -> 0.15 | K42: =I42/(1-J42) -> 0
B43: MISC | C43: 0 | D43: 0 | E43: 0 | F43: 0 | G43: 0 | I43: =SUM(C43:G43) -> 0 | J43: =$D$9 -> 0.15 | K43: =I43/(1-J43) -> 0
B44: SUBTOTAL | I44: =SUM(I38:I43) -> 4781.25 | K44: =SUM(K38:K43) -> 5625
B46: Submittals, Engineering, and Permits | C46: Subcontractor 1 | D46: Subcontractor 2 | E46: Subcontractor 3 | F46: Selected | G46: Additional Contingency | I46: Total Cost | J46: Install Margin | K46: Selling Price
B47: STRUCTURAL ENGINEERING | C47: 4705.88 | D47: 0 | E47: 0 | F47: 0 | G47: 0 | I47: =SUM(C47:G47) -> 4705.88 | J47: =$D$11 -> 0.15 | K47: =I47/(1-J47) -> 5536.33
B48: STRUCTURAL CERTIFICATION | C48: 0 | D48: 0 | E48: 0 | F48: 0 | G48: 0 | I48: =SUM(C48:G48) -> 0 | J48: =$D$11 -> 0.15 | K48: =I48/(1-J48) -> 0
B49: ELECTRICAL ENGINEERING | C49: 0 | D49: 0 | E49: 0 | F49: 0 | G49: 0 | I49: =SUM(C49:G49) -> 0 | J49: =$D$11 -> 0.15 | K49: =I49/(1-J49) -> 0
B50: ELECTRICAL CERTIFICATION | C50: 0 | D50: 0 | E50: 0 | F50: 0 | G50: 0 | I50: =SUM(C50:G50) -> 0 | J50: =$D$11 -> 0.15 | K50: =I50/(1-J50) -> 0
B51: PERMITS | C51: 0 | D51: 0 | E51: 0 | F51: 0 | G51: 0 | I51: =SUM(C51:G51) -> 0 | J51: =$D$11 -> 0.15 | K51: =I51/(1-J51) -> 0
B52: SUBTOTAL | I52: =SUM(I47:I51) -> 4705.88 | K52: =SUM(K47:K51) -> 5536.33
B54: ZONE GRAND TOTAL | I54: =I26+I35+I44+I52 -> 55646.75 | K54: =K26+K35+K44+K52 -> 64730.65

Sheet New Path Hall Option 1 - Instal
A3: Project Name: WTC Digital Signage Upgrade
A4: 2026-04-01
A5: Revised By: ANC Proposal Engine
C7: Linked Margin Assignment
C8: Install Margin | D8: 0.15
C9: Electrical Margin | D9: 0.15
C10: ANC Margin | D10: 0.15
C11: Engineering and Permits | D11: 0.15
B15: New Path Hall Option 1
B16: Height | C16: Width | D16: Total Sq. Ft | E16: QTY
B17: 48 | C17: 14 | D17: 672 | E17: 1
B19: Structural Materials: | C19: Subcontractor 1 | D19: Subcontractor 2 | E19: Subcontractor 3 | F19: Selected | G19: Additional Contingency | I19: Total Cost | J19: Install Margin | K19: Selling Price
B20: FABRICATE PRIMARY STEEL | C20: 0 | D20: 0 | E20: 0 | F20: 0 | G20: 0 | I20: =SUM(C20:G20) -> 0 | J20: =$D$8 -> 0.15 | K20: =I20/(1-J20) -> 0
B21: SUPPLY AND INSTALL PRIMARY PLYWOOD | C21: 0 | D21: 0 | E21: 0 | F21: 0 | G21: 0 | I21: =SUM(C21:G21) -> 0 | J21: =$D$8 -> 0.15 | K21: =I21/(1-J21) -> 0
B22: FABRICATE SECONDARY STEEL SUBSTRUCTURE | C22: 12315 | D22: 0 | E22: 0 | F22: 0 | G22: 0 | I22: =SUM(C22:G22) -> 12315 | J22: =$D$8 -> 0.15 | K22: =I22/(1-J22) -> 14488.24
B23: FABRICATE CLADDING AND TRIM | C23: 0 | D23: 0 | E23: 0 | F23: 0 | G23: 0 | I23: =SUM(C23:G23) -> 0 | J23: =$D$8 -> 0.15 | K23: =I23/(1-J23) -> 0
B24: OTHER SCOPE ITEM | C24: 0 | D24: 0 | E24: 0 | F24: 0 | G24: 0 | I24: =SUM(C24:G24) -> 0 | J24: =$D$8 -> 0.15 | K24: =I24/(1-J24) -> 0
B25: OTHER SCOPE ITEM | C25: 0 | D25: 0 | E25: 0 | F25: 0 | G25: 0 | I25: =SUM(C25:G25) -> 0 | J25: =$D$8 -> 0.15 | K25: =I25/(1-J25) -> 0
B26: SUBTOTAL | I26: =SUM(I20:I25) -> 12315 | K26: =SUM(K20:K25) -> 14488.24
B28: Structural Labor and LED Installation | C28: Subcontractor 1 | D28: Subcontractor 2 | E28: Subcontractor 3 | F28: Selected | G28: Additional Contingency | I28: Total Cost | J28: Install Margin | K28: Selling Price
B29: REMOVAL AND DISPOSAL | C29: 0 | D29: 0 | E29: 0 | F29: 0 | G29: 0 | I29: =SUM(C29:G29) -> 0 | J29: =$D$8 -> 0.15 | K29: =I29/(1-J29) -> 0
B30: INSTALL SECONDARY STEEL SUBSTRUCTURE | C30: 0 | D30: 0 | E30: 0 | F30: 0 | G30: 0 | I30: =SUM(C30:G30) -> 0 | J30: =$D$8 -> 0.15 | K30: =I30/(1-J30) -> 0
B31: INSTALL LED DISPLAYS | C31: 51312.5 | D31: 0 | E31: 0 | F31: 0 | G31: 0 | I31: =SUM(C31:G31) -> 51312.5 | J31: =$D$8 -> 0.15 | K31: =I31/(1-J31) -> 60367.65
B32: INSTALL CLADDING AND TRIM | C32: 0 | D32: 0 | E32: 0 | F32: 0 | G32: 0 | I32: =SUM(C32:G32) -> 0 | J32: =$D$8 -> 0.15 | K32: =I32/(1-J32) -> 0
B33: HEAVY EQUIPMENT | C33: 0 | D33: 0 | E33: 0 | F33: 0 | G33: 0 | I33: =SUM(C33:G33) -> 0 | J33: =$D$8 -> 0.15 | K33: =I33/(1-J33) -> 0
B34: PM/GENERAL CONDITIONS/TRAVEL | C34: 20882.35 | D34: 0 | E34: 0 | F34: 0 | G34: 0 | I34: =SUM(C34:G34) -> 20882.35 | J34: =$D$8 -> 0.15 | K34: =I34/(1-J34) -> 24567.47
B35: SUBTOTAL | I35: =SUM(I29:I34) -> 72194.85 | K35: =SUM(K29:K34) -> 84935.12
B37: Electrical and Data - Materials and Subcontracting | C37: Subcontractor 1 | D37: Subcontractor 2 | E37: Subcontractor 3 | F37: Selected | G37: Additional Contingency | I37: Total Cost | J37: Install Margin | K37: Selling Price
B38: ELECTRICAL MATERIALS | C38: 51312.5 | D38: 0 | E38: 0 | F38: 0 | G38: 0 | I38: =SUM(C38:G38) -> 51312.5 | J38: =$D$9 -> 0.15 | K38: =I38/(1-J38) -> 60367.65
B39: DATA MATERIALS | C39: 0 | D39: 0 | E39: 0 | F39: 0 | G39: 0 | I39: =SUM(C39:G39) -> 0 | J39: =$D$9 -> 0.15 | K39: =I39/(1-J39) -> 0
B40: ELECTRICAL LABOR | C40: 0 | D40: 0 | E40: 0 | F40: 0 | G40: 0 | I40: =SUM(C40:G40) -> 0 | J40: =$D$9 -> 0.15 | K40: =I40/(1-J40) -> 0
B41: DATA LABOR | C41: 0 | D41: 0 | E41: 0 | F41: 0 | G41: 0 | I41: =SUM(C41:G41) -> 0 | J41: =$D$9 -> 0.15 | K41: =I41/(1-J41) -> 0
B42: SUB PANEL | C42: 0 | D42: 0 | E42: 0 | F42: 0 | G42: 0 | I42: =SUM(C42:G42) -> 0 | J42: =$D$9 -> 0.15 | K42: =I42/(1-J42) -> 0
B43: MISC | C43: 0 | D43: 0 | E43: 0 | F43: 0 | G43: 0 | I43: =SUM(C43:G43) -> 0 | J43: =$D$9 -> 0.15 | K43: =I43/(1-J43) -> 0
B44: SUBTOTAL | I44: =SUM(I38:I43) -> 51312.5 | K44: =SUM(K38:K43) -> 60367.65
B46: Submittals, Engineering, and Permits | C46: Subcontractor 1 | D46: Subcontractor 2 | E46: Subcontractor 3 | F46: Selected | G46: Additional Contingency | I46: Total Cost | J46: Install Margin | K46: Selling Price
B47: STRUCTURAL ENGINEERING | C47: 4705.88 | D47: 0 | E47: 0 | F47: 0 | G47: 0 | I47: =SUM(C47:G47) -> 4705.88 | J47: =$D$11 -> 0.15 | K47: =I47/(1-J47) -> 5536.33
B48: STRUCTURAL CERTIFICATION | C48: 0 | D48: 0 | E48: 0 | F48: 0 | G48: 0 | I48: =SUM(C48:G48) -> 0 | J48: =$D$11 -> 0.15 | K48: =I48/(1-J48) -> 0
B49: ELECTRICAL ENGINEERING | C49: 0 | D49: 0 | E49: 0 | F49: 0 | G49: 0 | I49: =SUM(C49:G49) -> 0 | J49: =$D$11 -> 0.15 | K49: =I49/(1-J49) -> 0
B50: ELECTRICAL CERTIFICATION | C50: 0 | D50: 0 | E50: 0 | F50: 0 | G50: 0 | I50: =SUM(C50:G50) -> 0 | J50: =$D$11 -> 0.15 | K50: =I50/(1-J50) -> 0
B51: PERMITS | C51: 0 | D51: 0 | E51: 0 | F51: 0 | G51: 0 | I51: =SUM(C51:G51) -> 0 | J51: =$D$11 -> 0.15 | K51: =I51/(1-J51) -> 0
B52: SUBTOTAL | I52: =SUM(I47:I51) -> 4705.88 | K52: =SUM(K47:K51) -> 5536.33
B54: ZONE GRAND TOTAL | I54: =I26+I35+I44+I52 -> 363897.77 | K54: =K26+K35+K44+K52 -> 420209.14

Sheet New Path Hall Option 2 - Instal
A3: Project Name: WTC Digital Signage Upgrade
A4: 2026-04-01
A5: Revised By: ANC Proposal Engine
C7: Linked Margin Assignment
C8: Install Margin | D8: 0.15
C9: Electrical Margin | D9: 0.15
C10: ANC Margin | D10: 0.15
C11: Engineering and Permits | D11: 0.15
B15: New Path Hall Option 2
B16: Height | C16: Width | D16: Total Sq. Ft | E16: QTY
B17: 65 | C17: 13 | D17: 845 | E17: 1
B19: Structural Materials: | C19: Subcontractor 1 | D19: Subcontractor 2 | E19: Subcontractor 3 | F19: Selected | G19: Additional Contingency | I19: Total Cost | J19: Install Margin | K19: Selling Price
B20: FABRICATE PRIMARY STEEL | C20: 0 | D20: 0 | E20: 0 | F20: 0 | G20: 0 | I20: =SUM(C20:G20) -> 0 | J20: =$D$8 -> 0.15 | K20: =I20/(1-J20) -> 0
B21: SUPPLY AND INSTALL PRIMARY PLYWOOD | C21: 0 | D21: 0 | E21: 0 | F21: 0 | G21: 0 | I21: =SUM(C21:G21) -> 0 | J21: =$D$8 -> 0.15 | K21: =I21/(1-J21) -> 0
B22: FABRICATE SECONDARY STEEL SUBSTRUCTURE | C22: 15483.75 | D22: 0 | E22: 0 | F22: 0 | G22: 0 | I22: =SUM(C22:G22) -> 15483.75 | J22: =$D$8 -> 0.15 | K22: =I22/(1-J22) -> 18216.18
B23: FABRICATE CLADDING AND TRIM | C23: 0 | D23: 0 | E23: 0 | F23: 0 | G23: 0 | I23: =SUM(C23:G23) -> 0 | J23: =$D$8 -> 0.15 | K23: =I23/(1-J23) -> 0
B24: OTHER SCOPE ITEM | C24: 0 | D24: 0 | E24: 0 | F24: 0 | G24: 0 | I24: =SUM(C24:G24) -> 0 | J24: =$D$8 -> 0.15 | K24: =I24/(1-J24) -> 0
B25: OTHER SCOPE ITEM | C25: 0 | D25: 0 | E25: 0 | F25: 0 | G25: 0 | I25: =SUM(C25:G25) -> 0 | J25: =$D$8 -> 0.15 | K25: =I25/(1-J25) -> 0
B26: SUBTOTAL | I26: =SUM(I20:I25) -> 15483.75 | K26: =SUM(K20:K25) -> 18216.18
B28: Structural Labor and LED Installation | C28: Subcontractor 1 | D28: Subcontractor 2 | E28: Subcontractor 3 | F28: Selected | G28: Additional Contingency | I28: Total Cost | J28: Install Margin | K28: Selling Price
B29: REMOVAL AND DISPOSAL | C29: 0 | D29: 0 | E29: 0 | F29: 0 | G29: 0 | I29: =SUM(C29:G29) -> 0 | J29: =$D$8 -> 0.15 | K29: =I29/(1-J29) -> 0
B30: INSTALL SECONDARY STEEL SUBSTRUCTURE | C30: 0 | D30: 0 | E30: 0 | F30: 0 | G30: 0 | I30: =SUM(C30:G30) -> 0 | J30: =$D$8 -> 0.15 | K30: =I30/(1-J30) -> 0
B31: INSTALL LED DISPLAYS | C31: 64515.63 | D31: 0 | E31: 0 | F31: 0 | G31: 0 | I31: =SUM(C31:G31) -> 64515.63 | J31: =$D$8 -> 0.15 | K31: =I31/(1-J31) -> 75900.74
B32: INSTALL CLADDING AND TRIM | C32: 0 | D32: 0 | E32: 0 | F32: 0 | G32: 0 | I32: =SUM(C32:G32) -> 0 | J32: =$D$8 -> 0.15 | K32: =I32/(1-J32) -> 0
B33: HEAVY EQUIPMENT | C33: 0 | D33: 0 | E33: 0 | F33: 0 | G33: 0 | I33: =SUM(C33:G33) -> 0 | J33: =$D$8 -> 0.15 | K33: =I33/(1-J33) -> 0
B34: PM/GENERAL CONDITIONS/TRAVEL | C34: 20882.35 | D34: 0 | E34: 0 | F34: 0 | G34: 0 | I34: =SUM(C34:G34) -> 20882.35 | J34: =$D$8 -> 0.15 | K34: =I34/(1-J34) -> 24567.47
B35: SUBTOTAL | I35: =SUM(I29:I34) -> 85397.98 | K35: =SUM(K29:K34) -> 100468.21
B37: Electrical and Data - Materials and Subcontracting | C37: Subcontractor 1 | D37: Subcontractor 2 | E37: Subcontractor 3 | F37: Selected | G37: Additional Contingency | I37: Total Cost | J37: Install Margin | K37: Selling Price
B38: ELECTRICAL MATERIALS | C38: 64515.63 | D38: 0 | E38: 0 | F38: 0 | G38: 0 | I38: =SUM(C38:G38) -> 64515.63 | J38: =$D$9 -> 0.15 | K38: =I38/(1-J38) -> 75900.74
B39: DATA MATERIALS | C39: 0 | D39: 0 | E39: 0 | F39: 0 | G39: 0 | I39: =SUM(C39:G39) -> 0 | J39: =$D$9 -> 0.15 | K39: =I39/(1-J39) -> 0
B40: ELECTRICAL LABOR | C40: 0 | D40: 0 | E40: 0 | F40: 0 | G40: 0 | I40: =SUM(C40:G40) -> 0 | J40: =$D$9 -> 0.15 | K40: =I40/(1-J40) -> 0
B41: DATA LABOR | C41: 0 | D41: 0 | E41: 0 | F41: 0 | G41: 0 | I41: =SUM(C41:G41) -> 0 | J41: =$D$9 -> 0.15 | K41: =I41/(1-J41) -> 0
B42: SUB PANEL | C42: 0 | D42: 0 | E42: 0 | F42: 0 | G42: 0 | I42: =SUM(C42:G42) -> 0 | J42: =$D$9 -> 0.15 | K42: =I42/(1-J42) -> 0
B43: MISC | C43: 0 | D43: 0 | E43: 0 | F43: 0 | G43: 0 | I43: =SUM(C43:G43) -> 0 | J43: =$D$9 -> 0.15 | K43: =I43/(1-J43) -> 0
B44: SUBTOTAL | I44: =SUM(I38:I43) -> 64515.63 | K44: =SUM(K38:K43) -> 75900.74
B46: Submittals, Engineering, and Permits | C46: Subcontractor 1 | D46: Subcontractor 2 | E46: Subcontractor 3 | F46: Selected | G46: Additional Contingency | I46: Total Cost | J46: Install Margin | K46: Selling Price
B47: STRUCTURAL ENGINEERING | C47: 4705.88 | D47: 0 | E47: 0 | F47: 0 | G47: 0 | I47: =SUM(C47:G47) -> 4705.88 | J47: =$D$11 -> 0.15 | K47: =I47/(1-J47) -> 5536.33
B48: STRUCTURAL CERTIFICATION | C48: 0 | D48: 0 | E48: 0 | F48: 0 | G48: 0 | I48: =SUM(C48:G48) -> 0 | J48: =$D$11 -> 0.15 | K48: =I48/(1-J48) -> 0
B49: ELECTRICAL ENGINEERING | C49: 0 | D49: 0 | E49: 0 | F49: 0 | G49: 0 | I49: =SUM(C49:G49) -> 0 | J49: =$D$11 -> 0.15 | K49: =I49/(1-J49) -> 0
B50: ELECTRICAL CERTIFICATION | C50: 0 | D50: 0 | E50: 0 | F50: 0 | G50: 0 | I50: =SUM(C50:G50) -> 0 | J50: =$D$11 -> 0.15 | K50: =I50/(1-J50) -> 0
B51: PERMITS | C51: 0 | D51: 0 | E51: 0 | F51: 0 | G51: 0 | I51: =SUM(C51:G51) -> 0 | J51: =$D$11 -> 0.15 | K51: =I51/(1-J51) -> 0
B52: SUBTOTAL | I52: =SUM(I47:I51) -> 4705.88 | K52: =SUM(K47:K51) -> 5536.33
B54: ZONE GRAND TOTAL | I54: =I26+I35+I44+I52 -> 454125.35 | K54: =K26+K35+K44+K52 -> 524323.94

Sheet Processor Count
A1: WTC Digital Signage Upgrade — Processor Count
B4: Display | C4: Width (px) | D4: Height (px) | E4: Ports | F4: Ports (80%) | G4: 8-bit Video | H4: 8-bit (80%) | I4: 10/12/HDR bit
B5: 660 Pro | C5: 1920 | D5: 1080 | E5: 8 | G5: 650000 | H5: 455000 | I5: 320000
B6: MCTRL4K | C6: 3840 | D6: 2160 | E6: 16 | G6: 650000 | H6: 455000 | I6: 320000
B7: H9 Enhanced | C7: 7680 | D7: 4320 | E7: 20 | G7: 1200000 | H7: 960000 | I7: 650000
B10: DISPLAY PROCESSOR REQUIREMENTS
B11: Display | C11: Width (px) | D11: Height (px) | E11: Qty | F11: Total Pixels | G11: Ports Needed | H11: Processor Type | I11: Processors Needed
B12: ='LED Cost Sheet'!A4 -> Underpass 3 | C12: ='LED Cost Sheet'!K4 -> 0 | D12: ='LED Cost Sheet'!J4 -> 0 | E12: ='LED Cost Sheet'!L4 -> 1 | F12: =C12*D12*E12 -> 3326976 | G12: =IFERROR(CEILING(F12/650000,1),0) -> 6 | H12: =IF(G12>8,"MCTRL4K","660 Pro") -> 660 Pro | I12: =IFERROR(CEILING(G12/IF(G12>8,16,8),1),0) -> 1
B13: ='LED Cost Sheet'!A5 -> Underpass 4 | C13: ='LED Cost Sheet'!K5 -> 0 | D13: ='LED Cost Sheet'!J5 -> 0 | E13: ='LED Cost Sheet'!L5 -> 1 | F13: =C13*D13*E13 -> 5603328 | G13: =IFERROR(CEILING(F13/650000,1),0) -> 9 | H13: =IF(G13>8,"MCTRL4K","660 Pro") -> MCTRL4K | I13: =IFERROR(CEILING(G13/IF(G13>8,16,8),1),0) -> 1
B14: ='LED Cost Sheet'!A6 -> Concourse | C14: ='LED Cost Sheet'!K6 -> 0 | D14: ='LED Cost Sheet'!J6 -> 0 | E14: ='LED Cost Sheet'!L6 -> 1 | F14: =C14*D14*E14 -> 39369600 | G14: =IFERROR(CEILING(F14/650000,1),0) -> 61 | H14: =IF(G14>8,"MCTRL4K","660 Pro") -> MCTRL4K | I14: =IFERROR(CEILING(G14/IF(G14>8,16,8),1),0) -> 4
B15: ='LED Cost Sheet'!A7 -> T4-B1 (6-9) | C15: ='LED Cost Sheet'!K7 -> 0 | D15: ='LED Cost Sheet'!J7 -> 0 | E15: ='LED Cost Sheet'!L7 -> 4 | F15: =C15*D15*E15 -> 4055040 | G15: =IFERROR(CEILING(F15/650000,1),0) -> 7 | H15: =IF(G15>8,"MCTRL4K","660 Pro") -> 660 Pro | I15: =IFERROR(CEILING(G15/IF(G15>8,16,8),1),0) -> 1
B16: ='LED Cost Sheet'!A8 -> T4-B2 (10-18) | C16: ='LED Cost Sheet'!K8 -> 0 | D16: ='LED Cost Sheet'!J8 -> 0 | E16: ='LED Cost Sheet'!L8 -> 9 | F16: =C16*D16*E16 -> 9123840 | G16: =IFERROR(CEILING(F16/650000,1),0) -> 15 | H16: =IF(G16>8,"MCTRL4K","660 Pro") -> MCTRL4K | I16: =IFERROR(CEILING(G16/IF(G16>8,16,8),1),0) -> 1
B17: ='LED Cost Sheet'!A9 -> T4 Lobby Elevator | C17: ='LED Cost Sheet'!K9 -> 0 | D17: ='LED Cost Sheet'!J9 -> 0 | E17: ='LED Cost Sheet'!L9 -> 1 | F17: =C17*D17*E17 -> 5857159 | G17: =IFERROR(CEILING(F17/650000,1),0) -> 10 | H17: =IF(G17>8,"MCTRL4K","660 Pro") -> MCTRL4K | I17: =IFERROR(CEILING(G17/IF(G17>8,16,8),1),0) -> 1
B18: ='LED Cost Sheet'!A10 -> T2-B1M Screen 20 | C18: ='LED Cost Sheet'!K10 -> 0 | D18: ='LED Cost Sheet'!J10 -> 0 | E18: ='LED Cost Sheet'!L10 -> 1 | F18: =C18*D18*E18 -> 1939568 | G18: =IFERROR(CEILING(F18/650000,1),0) -> 3 | H18: =IF(G18>8,"MCTRL4K","660 Pro") -> 660 Pro | I18: =IFERROR(CEILING(G18/IF(G18>8,16,8),1),0) -> 1
B19: ='LED Cost Sheet'!A11 -> T2-B1M Screen 21 | C19: ='LED Cost Sheet'!K11 -> 0 | D19: ='LED Cost Sheet'!J11 -> 0 | E19: ='LED Cost Sheet'!L11 -> 1 | F19: =C19*D19*E19 -> 1390088 | G19: =IFERROR(CEILING(F19/650000,1),0) -> 3 | H19: =IF(G19>8,"MCTRL4K","660 Pro") -> 660 Pro | I19: =IFERROR(CEILING(G19/IF(G19>8,16,8),1),0) -> 1
B20: ='LED Cost Sheet'!A12 -> T2-B1M Screen 22 | C20: ='LED Cost Sheet'!K12 -> 0 | D20: ='LED Cost Sheet'!J12 -> 0 | E20: ='LED Cost Sheet'!L12 -> 1 | F20: =C20*D20*E20 -> 929296 | G20: =IFERROR(CEILING(F20/650000,1),0) -> 2 | H20: =IF(G20>8,"MCTRL4K","660 Pro") -> 660 Pro | I20: =IFERROR(CEILING(G20/IF(G20>8,16,8),1),0) -> 1
B21: ='LED Cost Sheet'!A13 -> New Path Hall Option 1 | C21: ='LED Cost Sheet'!K13 -> 0 | D21: ='LED Cost Sheet'!J13 -> 0 | E21: ='LED Cost Sheet'!L13 -> 1 | F21: =C21*D21*E21 -> 9989364 | G21: =IFERROR(CEILING(F21/650000,1),0) -> 16 | H21: =IF(G21>8,"MCTRL4K","660 Pro") -> MCTRL4K | I21: =IFERROR(CEILING(G21/IF(G21>8,16,8),1),0) -> 1
B22: ='LED Cost Sheet'!A14 -> New Path Hall Option 2 | C22: ='LED Cost Sheet'!K14 -> 0 | D22: ='LED Cost Sheet'!J14 -> 0 | E22: ='LED Cost Sheet'!L14 -> 1 | F22: =C22*D22*E22 -> 12561125 | G22: =IFERROR(CEILING(F22/650000,1),0) -> 20 | H22: =IF(G22>8,"MCTRL4K","660 Pro") -> MCTRL4K | I22: =IFERROR(CEILING(G22/IF(G22>8,16,8),1),0) -> 2
B23: TOTAL | F23: =SUM(F12:F22) -> 94145384 | G23: =SUM(G12:G22) -> 152 | I23: =SUM(I12:I22) -> 15

Sheet Bundle Equipment
A1: WTC Digital Signage Upgrade — Processor & Equipment Breakdown
A2: Editable — adjust component costs per display zone. Totals roll into Margin Analysis.
A6: Category | B6: Component | C6: Cost | D6: Qty | E6: Total Cost | F6: Margin | G6: Selling Price | H6: Margin $
A7: Underpass 3 — Underpass 1-4, WTC
A8: EQUIPMENT | B8: Sending Card | C8: 450 | D8: 1 | E8: =C8*D8 -> 450 | F8: 0.15 | G8: =IFERROR(E8/(1-F8),0) -> 529.41 | H8: =IFERROR(G8-E8,0) -> 79.41
A9: EQUIPMENT | B9: Signal Cable Kit | C9: 134.28 | D9: 1 | E9: =C9*D9 -> 134.28 | F9: 0.15 | G9: =IFERROR(E9/(1-F9),0) -> 157.98 | H9: =IFERROR(G9-E9,0) -> 23.7
B10: Zone Subtotal | E10: =SUM(E8:E9) -> 584.28 | G10: =SUM(G8:G9) -> 687.39 | H10: =IFERROR(G10-E10,0) -> 103.11
A12: Underpass 4 — Underpass 1-4, WTC
A13: EQUIPMENT | B13: Sending Card | C13: 8400 | D13: 1 | E13: =C13*D13 -> 8400 | F13: 0.15 | G13: =IFERROR(E13/(1-F13),0) -> 9882.35 | H13: =IFERROR(G13-E13,0) -> 1482.35
A14: EQUIPMENT | B14: Signal Cable Kit | C14: 226.19 | D14: 1 | E14: =C14*D14 -> 226.19 | F14: 0.15 | G14: =IFERROR(E14/(1-F14),0) -> 266.11 | H14: =IFERROR(G14-E14,0) -> 39.92
A15: EQUIPMENT | B15: Backup Video Processor | C15: 12000 | D15: 1 | E15: =C15*D15 -> 12000 | F15: 0.15 | G15: =IFERROR(E15/(1-F15),0) -> 14117.65 | H15: =IFERROR(G15-E15,0) -> 2117.65
B16: Zone Subtotal | E16: =SUM(E13:E15) -> 20626.19 | G16: =SUM(G13:G15) -> 24266.11 | H16: =IFERROR(G16-E16,0) -> 3639.92
A18: Concourse — Concourse, WTC
A19: EQUIPMENT | B19: Sending Card | C19: 33600 | D19: 1 | E19: =C19*D19 -> 33600 | F19: 0.15 | G19: =IFERROR(E19/(1-F19),0) -> 39529.41 | H19: =IFERROR(G19-E19,0) -> 5929.41
A20: EQUIPMENT | B20: Signal Cable Kit | C20: 1589.36 | D20: 1 | E20: =C20*D20 -> 1589.36 | F20: 0.15 | G20: =IFERROR(E20/(1-F20),0) -> 1869.84 | H20: =IFERROR(G20-E20,0) -> 280.48
A21: EQUIPMENT | B21: Backup Video Processor | C21: 12000 | D21: 1 | E21: =C21*D21 -> 12000 | F21: 0.15 | G21: =IFERROR(E21/(1-F21),0) -> 14117.65 | H21: =IFERROR(G21-E21,0) -> 2117.65
B22: Zone Subtotal | E22: =SUM(E19:E21) -> 47189.36 | G22: =SUM(G19:G21) -> 55516.9 | H22: =IFERROR(G22-E22,0) -> 8327.54
A24: T4-B1 (6-9) — T4-B1, WTC
A25: EQUIPMENT | B25: Sending Card | C25: 450 | D25: 1 | E25: =C25*D25 -> 450 | F25: 0.15 | G25: =IFERROR(E25/(1-F25),0) -> 529.41 | H25: =IFERROR(G25-E25,0) -> 79.41
A26: EQUIPMENT | B26: Signal Cable Kit | C26: 163.57 | D26: 1 | E26: =C26*D26 -> 163.57 | F26: 0.15 | G26: =IFERROR(E26/(1-F26),0) -> 192.44 | H26: =IFERROR(G26-E26,0) -> 28.87
B27: Zone Subtotal | E27: =SUM(E25:E26) -> 613.57 | G27: =SUM(G25:G26) -> 721.85 | H27: =IFERROR(G27-E27,0) -> 108.28
A29: T4-B2 (10-18) — T4-B2, WTC
A30: EQUIPMENT | B30: Sending Card | C30: 8400 | D30: 1 | E30: =C30*D30 -> 8400 | F30: 0.15 | G30: =IFERROR(E30/(1-F30),0) -> 9882.35 | H30: =IFERROR(G30-E30,0) -> 1482.35
A31: EQUIPMENT | B31: Signal Cable Kit | C31: 368.03 | D31: 1 | E31: =C31*D31 -> 368.03 | F31: 0.15 | G31: =IFERROR(E31/(1-F31),0) -> 432.98 | H31: =IFERROR(G31-E31,0) -> 64.95
A32: EQUIPMENT | B32: Backup Video Processor | C32: 12000 | D32: 1 | E32: =C32*D32 -> 12000 | F32: 0.15 | G32: =IFERROR(E32/(1-F32),0) -> 14117.65 | H32: =IFERROR(G32-E32,0) -> 2117.65
B33: Zone Subtotal | E33: =SUM(E30:E32) -> 20768.03 | G33: =SUM(G30:G32) -> 24432.98 | H33: =IFERROR(G33-E33,0) -> 3664.95
A35: T4 Lobby Elevator — T4 Lobby Elevator, WTC
A36: EQUIPMENT | B36: Sending Card | C36: 8400 | D36: 1 | E36: =C36*D36 -> 8400 | F36: 0.15 | G36: =IFERROR(E36/(1-F36),0) -> 9882.35 | H36: =IFERROR(G36-E36,0) -> 1482.35
A37: EQUIPMENT | B37: Signal Cable Kit | C37: 236.28 | D37: 1 | E37: =C37*D37 -> 236.28 | F37: 0.15 | G37: =IFERROR(E37/(1-F37),0) -> 277.98 | H37: =IFERROR(G37-E37,0) -> 41.7
A38: EQUIPMENT | B38: Backup Video Processor | C38: 12000 | D38: 1 | E38: =C38*D38 -> 12000 | F38: 0.15 | G38: =IFERROR(E38/(1-F38),0) -> 14117.65 | H38: =IFERROR(G38-E38,0) -> 2117.65
B39: Zone Subtotal | E39: =SUM(E36:E38) -> 20636.28 | G39: =SUM(G36:G38) -> 24277.98 | H39: =IFERROR(G39-E39,0) -> 3641.7
A41: T2-B1M Screen 20 — T2-B1M, WTC
A42: EQUIPMENT | B42: Sending Card | C42: 450 | D42: 1 | E42: =C42*D42 -> 450 | F42: 0.15 | G42: =IFERROR(E42/(1-F42),0) -> 529.41 | H42: =IFERROR(G42-E42,0) -> 79.41
A43: EQUIPMENT | B43: Signal Cable Kit | C43: 78.31 | D43: 1 | E43: =C43*D43 -> 78.31 | F43: 0.15 | G43: =IFERROR(E43/(1-F43),0) -> 92.13 | H43: =IFERROR(G43-E43,0) -> 13.82
B44: Zone Subtotal | E44: =SUM(E42:E43) -> 528.31 | G44: =SUM(G42:G43) -> 621.54 | H44: =IFERROR(G44-E44,0) -> 93.23
A46: T2-B1M Screen 21 — T2-B1M, WTC
A47: EQUIPMENT | B47: Sending Card | C47: 450 | D47: 1 | E47: =C47*D47 -> 450 | F47: 0.15 | G47: =IFERROR(E47/(1-F47),0) -> 529.41 | H47: =IFERROR(G47-E47,0) -> 79.41
A48: EQUIPMENT | B48: Signal Cable Kit | C48: 56.15 | D48: 1 | E48: =C48*D48 -> 56.15 | F48: 0.15 | G48: =IFERROR(E48/(1-F48),0) -> 66.06 | H48: =IFERROR(G48-E48,0) -> 9.91
B49: Zone Subtotal | E49: =SUM(E47:E48) -> 506.15 | G49: =SUM(G47:G48) -> 595.47 | H49: =IFERROR(G49-E49,0) -> 89.32
A51: T2-B1M Screen 22 — T2-B1M, WTC
A52: EQUIPMENT | B52: Sending Card | C52: 450 | D52: 1 | E52: =C52*D52 -> 450 | F52: 0.15 | G52: =IFERROR(E52/(1-F52),0) -> 529.41 | H52: =IFERROR(G52-E52,0) -> 79.41
A53: EQUIPMENT | B53: Signal Cable Kit | C53: 37.54 | D53: 1 | E53: =C53*D53 -> 37.54 | F53: 0.15 | G53: =IFERROR(E53/(1-F53),0) -> 44.16 | H53: =IFERROR(G53-E53,0) -> 6.62
B54: Zone Subtotal | E54: =SUM(E52:E53) -> 487.54 | G54: =SUM(G52:G53) -> 573.57 | H54: =IFERROR(G54-E54,0) -> 86.03
A56: New Path Hall Option 1 — New Path Hall, WTC
A57: EQUIPMENT | B57: Sending Card | C57: 8400 | D57: 1 | E57: =C57*D57 -> 8400 | F57: 0.15 | G57: =IFERROR(E57/(1-F57),0) -> 9882.35 | H57: =IFERROR(G57-E57,0) -> 1482.35
A58: EQUIPMENT | B58: Signal Cable Kit | C58: 403.2 | D58: 1 | E58: =C58*D58 -> 403.2 | F58: 0.15 | G58: =IFERROR(E58/(1-F58),0) -> 474.35 | H58: =IFERROR(G58-E58,0) -> 71.15
A59: EQUIPMENT | B59: Backup Video Processor | C59: 12000 | D59: 1 | E59: =C59*D59 -> 12000 | F59: 0.15 | G59: =IFERROR(E59/(1-F59),0) -> 14117.65 | H59: =IFERROR(G59-E59,0) -> 2117.65
B60: Zone Subtotal | E60: =SUM(E57:E59) -> 20803.2 | G60: =SUM(G57:G59) -> 24474.35 | H60: =IFERROR(G60-E60,0) -> 3671.15
A62: New Path Hall Option 2 — New Path Hall, WTC
A63: EQUIPMENT | B63: Sending Card | C63: 16800 | D63: 1 | E63: =C63*D63 -> 16800 | F63: 0.15 | G63: =IFERROR(E63/(1-F63),0) -> 19764.71 | H63: =IFERROR(G63-E63,0) -> 2964.71
A64: EQUIPMENT | B64: Signal Cable Kit | C64: 507 | D64: 1 | E64: =C64*D64 -> 507 | F64: 0.15 | G64: =IFERROR(E64/(1-F64),0) -> 596.47 | H64: =IFERROR(G64-E64,0) -> 89.47
A65: EQUIPMENT | B65: Backup Video Processor | C65: 12000 | D65: 1 | E65: =C65*D65 -> 12000 | F65: 0.15 | G65: =IFERROR(E65/(1-F65),0) -> 14117.65 | H65: =IFERROR(G65-E65,0) -> 2117.65
B66: Zone Subtotal | E66: =SUM(E63:E65) -> 29307 | G66: =SUM(G63:G65) -> 34478.83 | H66: =IFERROR(G66-E66,0) -> 5171.83
A68: EQUIPMENT GRAND TOTAL | E68: =E10+E16+E22+E27+E33+E39+E44+E49+E54+E60+E66 -> 162049.91 | G68: =G10+G16+G22+G27+G33+G39+G44+G49+G54+G60+G66 -> 190646.96 | H68: =IFERROR(G68-E68,0) -> 28597.05

Sheet ANC Travel
A1: WTC Digital Signage Upgrade — ANC Travel
B4: Travel - Installation | C4: Cost | D4: Quantity | E4: Total Cost
B5: Hotel | C5: 300 | D5: 0 | E5: 0
B6: Airfare | C6: 1000 | D6: 0 | E6: 0
B7: Car | C7: 125 | D7: 0 | E7: 0
B8: Per Diem | C8: 100 | D8: 0 | E8: 0
B9: Bundled | C9: 10000 | D9: 0 | E9: 0 | G9: Account for freelancer
B10: Total | E10: 0
B11: TOTAL | C11: USD: | E11: 0
B13: Travel - Commissioning | C13: Cost | D13: Quantity | E13: Total Cost
B14: Hotel | C14: 300 | D14: 0 | E14: 0
B15: Airfare | C15: 1000 | D15: 0 | E15: 0
B16: Car | C16: 125 | D16: 0 | E16: 0
B17: Per Diem | C17: 100 | D17: 0 | E17: 0
B18: Bundled | C18: 10000 | D18: 0 | E18: 0 | G18: Account for freelancer
B19: Total | E19: 0
B20: TOTAL | C20: USD: | E20: 0
B22: Game Support | C22: Cost | D22: Quantity | E22: Total Cost
B23: Hotel | C23: 300 | D23: 0 | E23: 0
B24: Airfare | C24: 1000 | D24: 0 | E24: 0
B25: Car | C25: 125 | D25: 0 | E25: 0
B26: Per Diem | C26: 100 | D26: 0 | E26: 0
B27: Bundled | C27: 10000 | D27: 0 | E27: 0 | G27: Account for freelancer
B28: Game Day Support | C28: 1500 | D28: 0 | E28: 0
B29: Total | E29: 0
B30: TOTAL | C30: USD: | E30: 0

Sheet CMS
A1: WTC Digital Signage Upgrade — Content Management System
B4: CMS Platform
B5: All costs require project-specific pricing — update items below based on RFP requirements
B6: Category | C6: Item | D6: Cost | E6: Quantity | F6: Total Cost | G6: Margin | H6: Selling Price | I6: Margin $
B7: PRIMARY | C7: DESIGN & CONTROL SOFTWARE | D7: 0 | E7: 0 | F7: =D7*E7 -> 0 | G7: 0.1 | H7: =IFERROR(F7/(1-G7),0) -> 0 | I7: =IFERROR(H7-F7,0) -> 0
B8: PRIMARY | C8: GRAPHICS PLAYBACK ENGINE | D8: 0 | E8: 0 | F8: =D8*E8 -> 0 | G8: 0.1 | H8: =IFERROR(F8/(1-G8),0) -> 0 | I8: =IFERROR(H8-F8,0) -> 0
B9: PRIMARY | C9: IMAGE PROCESSING | D9: 0 | E9: 0 | F9: =D9*E9 -> 0 | G9: 0.1 | H9: =IFERROR(F9/(1-G9),0) -> 0 | I9: =IFERROR(H9-F9,0) -> 0
B10: PRIMARY | C10: DEDICATED LED ROUTER / SWITCH | D10: 0 | E10: 0 | F10: =D10*E10 -> 0 | G10: 0.1 | H10: =IFERROR(F10/(1-G10),0) -> 0 | I10: =IFERROR(H10-F10,0) -> 0
B11: REDUNDANT | C11: DESIGN & CONTROL SOFTWARE | D11: 0 | E11: 0 | F11: =D11*E11 -> 0 | G11: 0.1 | H11: =IFERROR(F11/(1-G11),0) -> 0 | I11: =IFERROR(H11-F11,0) -> 0
B12: REDUNDANT | C12: GRAPHICS PLAYBACK ENGINE | D12: 0 | E12: 0 | F12: =D12*E12 -> 0 | G12: 0.1 | H12: =IFERROR(F12/(1-G12),0) -> 0 | I12: =IFERROR(H12-F12,0) -> 0
B13: REDUNDANT | C13: IMAGE PROCESSING | D13: 0 | E13: 0 | F13: =D13*E13 -> 0 | G13: 0.1 | H13: =IFERROR(F13/(1-G13),0) -> 0 | I13: =IFERROR(H13-F13,0) -> 0
B14: STANDARD SERVICES | C14: COMMISSIONING | D14: 0 | E14: 0 | F14: =D14*E14 -> 0 | G14: 0.1 | H14: =IFERROR(F14/(1-G14),0) -> 0 | I14: =IFERROR(H14-F14,0) -> 0
B15: STANDARD SERVICES | C15: EVENT SUPPORT | D15: 0 | E15: 0 | F15: =D15*E15 -> 0 | G15: 0.1 | H15: =IFERROR(F15/(1-G15),0) -> 0 | I15: =IFERROR(H15-F15,0) -> 0
B16: STANDARD SERVICES | C16: PROJECT MANAGEMENT | D16: 0 | E16: 0 | F16: =D16*E16 -> 0 | G16: 0.1 | H16: =IFERROR(F16/(1-G16),0) -> 0 | I16: =IFERROR(H16-F16,0) -> 0
C17: Integration Hardware | D17: 0 | E17: 0 | F17: =D17*E17 -> 0 | G17: 0.1 | H17: =IFERROR(F17/(1-G17),0) -> 0 | I17: =IFERROR(H17-F17,0) -> 0
C18: Integration Labor | D18: 0 | E18: 0 | F18: =D18*E18 -> 0 | G18: 0.1 | H18: =IFERROR(F18/(1-G18),0) -> 0 | I18: =IFERROR(H18-F18,0) -> 0
C19: Shipping | D19: 0 | E19: 0 | F19: =D19*E19 -> 0 | G19: 0.1 | H19: =IFERROR(F19/(1-G19),0) -> 0 | I19: =IFERROR(H19-F19,0) -> 0
C20: Travel | D20: 0 | E20: 0 | F20: =D20*E20 -> 0 | G20: 0.1 | H20: =IFERROR(F20/(1-G20),0) -> 0 | I20: =IFERROR(H20-F20,0) -> 0
C22: CMS TOTAL | F22: =SUM(F7:F20) -> 0 | H22: =SUM(H7:H20) -> 0 | I22: =IFERROR(H22-F22,0) -> 0
B24: TAX | F24: 0
B25: BOND | F25: 0
B26: SUB TOTAL | C26: USD: | F26: =F22+F24+F25 -> 0 | H26: =H22 -> 0 | I26: =IFERROR(H26-F26,0) -> 0

Sheet Scoring
A1: WTC Digital Signage Upgrade — Scoring System
B4: Scoring Platform
B5: All costs require project-specific pricing — update items below based on RFP requirements
B6: Category | C6: Item | D6: Cost | E6: Quantity | F6: Total Cost | G6: Margin | H6: Selling Price | I6: Margin $
B7: HARDWARE | C7: SCORING CONTROLLER / SERVER | D7: 0 | E7: 0 | F7: =D7*E7 -> 0 | G7: 0.1 | H7: =IFERROR(F7/(1-G7),0) -> 0 | I7: =IFERROR(H7-F7,0) -> 0
B8: HARDWARE | C8: OPERATOR WORKSTATION(S) | D8: 0 | E8: 0 | F8: =D8*E8 -> 0 | G8: 0.1 | H8: =IFERROR(F8/(1-G8),0) -> 0 | I8: =IFERROR(H8-F8,0) -> 0
B9: HARDWARE | C9: SCOREBOARD INPUT DEVICES | D9: 0 | E9: 0 | F9: =D9*E9 -> 0 | G9: 0.1 | H9: =IFERROR(F9/(1-G9),0) -> 0 | I9: =IFERROR(H9-F9,0) -> 0
B10: HARDWARE | C10: SHOT CLOCK / GAME CLOCK INTERFACE | D10: 0 | E10: 0 | F10: =D10*E10 -> 0 | G10: 0.1 | H10: =IFERROR(F10/(1-G10),0) -> 0 | I10: =IFERROR(H10-F10,0) -> 0
B11: HARDWARE | C11: STATISTICS INTERFACE | D11: 0 | E11: 0 | F11: =D11*E11 -> 0 | G11: 0.1 | H11: =IFERROR(F11/(1-G11),0) -> 0 | I11: =IFERROR(H11-F11,0) -> 0
B12: SOFTWARE | C12: SCORING SOFTWARE LICENSE | D12: 0 | E12: 0 | F12: =D12*E12 -> 0 | G12: 0.1 | H12: =IFERROR(F12/(1-G12),0) -> 0 | I12: =IFERROR(H12-F12,0) -> 0
B13: SOFTWARE | C13: GRAPHICS / ANIMATION PACKAGE | D13: 0 | E13: 0 | F13: =D13*E13 -> 0 | G13: 0.1 | H13: =IFERROR(F13/(1-G13),0) -> 0 | I13: =IFERROR(H13-F13,0) -> 0
B14: SOFTWARE | C14: STATISTICS INTEGRATION | D14: 0 | E14: 0 | F14: =D14*E14 -> 0 | G14: 0.1 | H14: =IFERROR(F14/(1-G14),0) -> 0 | I14: =IFERROR(H14-F14,0) -> 0
B15: SERVICES | C15: COMMISSIONING | D15: 0 | E15: 0 | F15: =D15*E15 -> 0 | G15: 0.1 | H15: =IFERROR(F15/(1-G15),0) -> 0 | I15: =IFERROR(H15-F15,0) -> 0
B16: SERVICES | C16: TRAINING | D16: 0 | E16: 0 | F16: =D16*E16 -> 0 | G16: 0.1 | H16: =IFERROR(F16/(1-G16),0) -> 0 | I16: =IFERROR(H16-F16,0) -> 0
B17: SERVICES | C17: PROJECT MANAGEMENT | D17: 0 | E17: 0 | F17: =D17*E17 -> 0 | G17: 0.1 | H17: =IFERROR(F17/(1-G17),0) -> 0 | I17: =IFERROR(H17-F17,0) -> 0
C18: Integration Hardware | D18: 0 | E18: 0 | F18: =D18*E18 -> 0 | G18: 0.1 | H18: =IFERROR(F18/(1-G18),0) -> 0 | I18: =IFERROR(H18-F18,0) -> 0
C19: Integration Labor | D19: 0 | E19: 0 | F19: =D19*E19 -> 0 | G19: 0.1 | H19: =IFERROR(F19/(1-G19),0) -> 0 | I19: =IFERROR(H19-F19,0) -> 0
C20: Shipping | D20: 0 | E20: 0 | F20: =D20*E20 -> 0 | G20: 0.1 | H20: =IFERROR(F20/(1-G20),0) -> 0 | I20: =IFERROR(H20-F20,0) -> 0
C21: Travel | D21: 0 | E21: 0 | F21: =D21*E21 -> 0 | G21: 0.1 | H21: =IFERROR(F21/(1-G21),0) -> 0 | I21: =IFERROR(H21-F21,0) -> 0
C23: SCORING TOTAL | F23: =SUM(F7:F21) -> 0 | H23: =SUM(H7:H21) -> 0 | I23: =IFERROR(H23-F23,0) -> 0
B25: TAX | F25: 0
B26: BOND | F26: 0
B27: SUB TOTAL | C27: USD: | F27: =F23+F25+F26 -> 0 | H27: =H23 -> 0 | I27: =IFERROR(H27-F27,0) -> 0

Sheet Venue Services
A1: WTC Digital Signage Upgrade — Venue Services
A2: Multi-year service contract calculator
A4: Contract Years | B4: 3 | C4: Editable service term
A5: Year 1 Cost | B5: 0 | C5: Base annual contract value
A6: Annual Escalation % | B6: 0.03 | C6: Applied to each renewal year
A7: Margin % | B7: 0.15 | C7: Target service-contract margin
A10: Year | B10: Cost | C10: Selling Price | D10: Margin $ | E10: Notes
A11: =IF($B$4>=1,"Year 1","") -> Year 1 | B11: =$B$5 -> 0 | C11: =IF(A11="",0,IFERROR(B11/(1-$B$7),0)) -> 0 | D11: =IF(A11="",0,IFERROR(C11-B11,0)) -> 0 | E11: Escalated annual term
A12: =IF($B$4>=2,"Year 2","") -> Year 2 | B12: =IF(A12="",0,B11*(1+$B$6)) -> 0 | C12: =IF(A12="",0,IFERROR(B12/(1-$B$7),0)) -> 0 | D12: =IF(A12="",0,IFERROR(C12-B12,0)) -> 0 | E12: Escalated annual term
A13: =IF($B$4>=3,"Year 3","") -> Year 3 | B13: =IF(A13="",0,B12*(1+$B$6)) -> 0 | C13: =IF(A13="",0,IFERROR(B13/(1-$B$7),0)) -> 0 | D13: =IF(A13="",0,IFERROR(C13-B13,0)) -> 0 | E13: Escalated annual term
A14: =IF($B$4>=4,"Year 4","") | B14: =IF(A14="",0,B13*(1+$B$6)) -> 0 | C14: =IF(A14="",0,IFERROR(B14/(1-$B$7),0)) -> 0 | D14: =IF(A14="",0,IFERROR(C14-B14,0)) -> 0
A15: =IF($B$4>=5,"Year 5","") | B15: =IF(A15="",0,B14*(1+$B$6)) -> 0 | C15: =IF(A15="",0,IFERROR(B15/(1-$B$7),0)) -> 0 | D15: =IF(A15="",0,IFERROR(C15-B15,0)) -> 0
A17: VENUE SERVICES TOTAL | B17: =SUM(B11:B15) -> 0 | C17: =SUM(C11:C15) -> 0 | D17: =IFERROR(C17-B17,0) -> 0

Sheet Additional Items
A1: WTC Digital Signage Upgrade — Additional Non-LED Items
B4: Category | C4: Item | D4: Cost | E4: Quantity | F4: Total Cost | G4: Margin | H4: Selling Price | I4: Margin $
B5: GAME CLOCK | C5: Six-Digit Game Clocks | D5: 0 | E5: 1 | F5: =D5*E5 -> 0 | G5: 0.15 | H5: =IFERROR(F5/(1-G5),0) -> 0 | I5: =IFERROR(H5-F5,0) -> 0
B6: PITCH CLOCK | C6: Pitch Clocks | D6: 0 | E6: 1 | F6: =D6*E6 -> 0 | G6: 0.15 | H6: =IFERROR(F6/(1-G6),0) -> 0 | I6: =IFERROR(H6-F6,0) -> 0
B7: OES / MIS | C7: OES / MIS / Timing | D7: 0 | E7: 1 | F7: =D7*E7 -> 0 | G7: 0.15 | H7: =IFERROR(F7/(1-G7),0) -> 0 | I7: =IFERROR(H7-F7,0) -> 0
B8: MISC | C8: DMX / Misc Equipment | D8: 0 | E8: 1 | F8: =D8*E8 -> 0 | G8: 0.15 | H8: =IFERROR(F8/(1-G8),0) -> 0 | I8: =IFERROR(H8-F8,0) -> 0
C10: ADDITIONAL ITEMS TOTAL | F10: =SUM(F5:F8) -> 0 | H10: =SUM(H5:H8) -> 0 | I10: =IFERROR(H10-F10,0) -> 0

Sheet Resp Matrix
B1: Project: WTC Digital Signage Upgrade
B2: Date: 4/1/2026
B4: Administrative | C4: ANC | D4: Purchaser
B5: Provide accurate architectural, structural engineering, and AV drawings. | D5: X
B6: Provide Payment and Performance Bond. | C6: NA
B7: All required zoning, building, street or sidewalk permits. | C7: NA
B8: Shipping of all equipment to site. | C8: X
B9: Receive, unload, and inspect all new equipment upon arrival. | C9: X
B10: Provide safe storage of video equipment and control room. | D10: X
B11: Unobstructed access to equipment and control room. | D11: X
B13: Engineering & Submittals | C13: ANC | D13: Purchaser
B14: Customer responsible to ensure existing structure supports new equipment. | D14: X
B15: Provide mechanical drawings, electrical drawings, and load calculations. | C15: X
B16: Engineering and certification for new equipment attachments. | C16: X
B17: Provide approval of all mechanical/electrical drawings. | D17: X
B18: Responsible to ensure structural integrity of existing conditions. | D18: X
B20: Physical Installation | C20: ANC | D20: Purchaser
B21: ANC assumes all base building structure is provided by others. | C21: Include Statement
B22: ANC has included removal and disposal of existing equipment. | D22: X
B23: ANC assumes reasonable access will be provided to the work area. | C23: Include Statement
B24: Fabricate, deliver, and install support structure. | C24: X
B25: Provide & Install LED components. | C25: X
B26: Provide all required Floor/Site Protection. | D26: X
B28: Electrical & Data Installation | C28: ANC | D28: Purchaser
B29: Submit electrical engineering drawings. | C29: X
B30: Provide primary power feed to each display location. | D30: X
B31: Provide secondary electrical panels and/or remote disconnects. | D31: X
B32: Furnish signal cables as specified by ANC. | C32: X
B33: Provide and install signal cable conduit. | D33: X
B34: Labor to pull signal cable. | C34: X
B35: Terminate signal cable at control system equipment. | C35: X
B36: Mount and install data patch panel. | C36: X
B37: Provide high speed internet connection to control room. | D37: X
B39: Control System | C39: ANC | D39: Purchaser
B40: ANC has provided display processors only. | C40: Include Statement
B41: Provide climate controlled control room. | D41: X
B42: Supply static IP address five (5) days prior to installation. | D42: X
B44: Training | C44: ANC | D44: Purchaser
B45: Provide appropriate on-site operation and maintenance training. | C45: X
B46: Provide sign off list for all training. | C46: X
B47: Perform one (1) day of maintenance training. | C47: X
B48: Perform final systems testing and commissioning. | C48: X
B50: General Conditions | C50: ANC | D50: Purchaser
B51: ANC has provided a parts only warranty, excluding labor. | C51: Include Statement
B52: ANC has included installation pricing with prevailing labor rates. | D52: X
B53: ANC has not included bonding of any kind. | C53: Include Statement
B54: ANC has not included any tax in the proposal. | C54: Include Statement
B55: Shipping included in quoted pricing. | C55: Include Statement

Sheet P&L
A1: WTC Digital Signage Upgrade — P&L
A3: Project #: | D3: 50/20/20/10
B5: PROJECTS BUDGET | I5: CONTRACT BUDGET
B6: Revenue | C6: Budgeted Cost | D6: Margin | I6: Revenue | J6: Budgeted Cost
A7: Base Contract | B7: 3967550.8 | C7: 3435750.1 | D7: 531800.62 | H7: TOTAL BASE CONTRACT | I7: 3967550.8 | J7: 3435750.1
A8: TOTAL BASE CONTRACT | B8: 3967550.8 | C8: 3435750.1 | D8: 531800.62
A10: Change Orders
A11: Total Change Order(s) Amount | B11: 0 | C11: 0 | D11: 0
A13: Grand Total | B13: 3967550.8 | C13: 3435750.1 | D13: 531800.62
A16: Cost Category | B16: Revenue | C16: Budget | D16: Committed POs | E16: Budget Remaining
A17: LED | B17: 0 | C17: 1757826.3 | D17: 0 | E17: 1757826.3
A18: Install | B18: 0 | C18: 599617.52 | D18: 0 | E18: 599617.52
A19: Electrical | B19: 0 | C19: 483562.52 | D19: 0 | E19: 483562.52
A20: ANC Travel | B20: 0 | C20: 165000 | D20: 0 | E20: 165000
A21: Structural Engineering | B21: 0 | C21: 51764.68 | D21: 0 | E21: 51764.68
A22: Electrical Engineering | B22: 0 | C22: 0 | D22: 0 | E22: 0
A23: CMS | B23: 0 | C23: 0 | D23: 0 | E23: 0
A24: Parts/Labor | B24: 0 | C24: 0 | D24: 0 | E24: 0
A25: Tax | B25: 0 | C25: 0 | D25: 0 | E25: 0
A26: Bond | B26: 0 | C26: 0 | D26: 0 | E26: 0
A27: BASE CONTRACT TOTAL | C27: 3435750.1 | D27: 0 | E27: 3435750.1

Sheet Cash Flow
A1: WTC Digital Signage Upgrade — Cash Flow
D3: Payment Terms: 50/20/20/10
D4: Payment Phases | E4: Contract Signed | F4: Product Shipping | G4: Substantial Completion | H4: Sign Off
D5: Percentages | E5: 0.5 | F5: 0.2 | G5: 0.2 | H5: 0.1
B6: Contract Award Date | C6: TBD
B7: Scheduled Completion | C7: TBD
B9: Revenue | C9: Expenses | D9: Gross Profit | E9: Gross Profit % | F9: Budget Tracking (+/-)
B10: 3967550.8 | C10: 3435750.1 | D10: 531800.62 | E10: 0.13403751 | F10: 0
A12: Month | E12: Month 1 | F12: Month 2 | G12: Month 3 | H12: Month 4 | I12: Month 5 | J12: Month 6 | K12: Month 7 | L12: Month 8 | M12: Month 9 | N12: Month 10
A13: Revenue | C13: Amount | D13: Date Submitted
A14: 1 | C14: 0 | E14: 0 | F14: 0 | G14: 0 | H14: 0 | I14: 0 | J14: 0 | K14: 0 | L14: 0 | M14: 0 | N14: 0
A15: 2 | C15: 0 | E15: 0 | F15: 0 | G15: 0 | H15: 0 | I15: 0 | J15: 0 | K15: 0 | L15: 0 | M15: 0 | N15: 0
A16: 3 | C16: 0 | E16: 0 | F16: 0 | G16: 0 | H16: 0 | I16: 0 | J16: 0 | K16: 0 | L16: 0 | M16: 0 | N16: 0
A17: 4 | C17: 0 | E17: 0 | F17: 0 | G17: 0 | H17: 0 | I17: 0 | J17: 0 | K17: 0 | L17: 0 | M17: 0 | N17: 0
A18: 5 | C18: 0 | E18: 0 | F18: 0 | G18: 0 | H18: 0 | I18: 0 | J18: 0 | K18: 0 | L18: 0 | M18: 0 | N18: 0
A19: 6 | C19: 0 | E19: 0 | F19: 0 | G19: 0 | H19: 0 | I19: 0 | J19: 0 | K19: 0 | L19: 0 | M19: 0 | N19: 0
A20: 7 | C20: 0 | E20: 0 | F20: 0 | G20: 0 | H20: 0 | I20: 0 | J20: 0 | K20: 0 | L20: 0 | M20: 0 | N20: 0
A21: 8 | C21: 0 | E21: 0 | F21: 0 | G21: 0 | H21: 0 | I21: 0 | J21: 0 | K21: 0 | L21: 0 | M21: 0 | N21: 0
A22: 9 | C22: 0 | E22: 0 | F22: 0 | G22: 0 | H22: 0 | I22: 0 | J22: 0 | K22: 0 | L22: 0 | M22: 0 | N22: 0
A23: 10 | C23: 0 | E23: 0 | F23: 0 | G23: 0 | H23: 0 | I23: 0 | J23: 0 | K23: 0 | L23: 0 | M23: 0 | N23: 0
A24: Total Revenue | C24: 0

Sheet PO's
A1: WTC Digital Signage Upgrade — Purchase Orders
A3: PO Number | B3: Vendor | C3: Title / Description | D3: Original Contract Amount | E3: Category
D4: 0
D5: 0
D6: 0
D7: 0
D8: 0
D9: 0
D10: 0
D11: 0
D12: 0
D13: 0
D14: 0
D15: 0
... D33: 0

Sheet _Products
A1: 10mm Mesh P10 (Nitxeon) | B1: Nitxeon | C1: 10 | D1: 260.13 | E1: 1500 | F1: 19.6 | G1: 298
A2: 2.5mm Indoor (Nationstar MIP) | B2: Nationstar | C2: 2.5 | D2: 501.68 | E2: 2000 | F2: 52.6 | G2: 390.6
A3: 4mm Indoor (Nitxeon) | B3: Nitxeon | C3: 4 | D3: 390.19 | E3: 2000 | F3: 45.4 | G3: 488.3
A4: C1.2-MIP 1.2mm Indoor (Alt) | B4: LG/Yaham | C4: 1.2 | D4: 430 | E4: 2000 | F4: 55 | G4: 590
A5: C1.8-MIP 1.8mm Indoor/VisiBowl (Alt) | B5: LG/Yaham | C5: 1.8 | D5: 0 | E5: 2000 | F5: 55 | G5: 540
A6: LG LSCA015 1.5mm Indoor Fine Pitch | B6: LG | C6: 1.5 | D6: 929.03 | E6: 1000 | F6: 55 | G6: 350
A7: LG LSCA039 3.91mm Indoor Ceiling | B7: LG | C7: 3.91 | D7: 113.34 | E7: 1000 | F7: 48 | G7: 400
A8: LG LSCB025 2.5mm Indoor Wall | B8: LG | C8: 2.5 | D8: 277.59 | E8: 1000 | F8: 50 | G8: 390
A9: LG LSGA039 3.9mm Indoor Wall | B9: LG | C9: 3.91 | D9: 111.67 | E9: 1000 | F9: 45 | G9: 400
A10: Mesh P10 FM1921 3.9mm Indoor | B10: LG/Yaham | C10: 3.9 | D10: 0 | E10: 6000 | F10: 33.07 | G10: 600
A11: Yaham Aura A10 Perimeter | B11: Yaham | C11: 10 | D11: 206.62 | E11: 7500 | F11: 84.2 | G11: 472.2
A12: Yaham Corona C10 Indoor | B12: Yaham | C12: 10 | D12: 112.23 | E12: 2000 | F12: 46.6 | G12: 401.5
... A23: Yaham Radiance R8 Outdoor | B23: Yaham | C23: 8.33 | D23: 194.07 | E23: 10000 | F23: 65 | G23: 650
